Workbook

Sheet 使用说明
B1: 进口到厂成本计算器 · Excel 版
B2: FOB / CFR / CIF 三口径 · 全公式 · 改参数自动重算
B4: 【30 秒上手】
B5: 只改黄色单元格：C6 单价、C7 数量、C10 市场汇率、C11 海关计征汇率、C14 海运费（仅 FOB）、C46~C51 境内费用。
B6: 看三个数：C61 最终经济成本 元/吨（★到厂成本）；C58 整票现金支出；C42 进口环节增值税现金。
B7: C64 状态若为「待补全」，说明有关键项没填——先补数据，不要用 C65 已知小计冒充完整到厂价。
B9: 【三口径怎么防重复计费】
B10: CFR 页：C29 海运费自动为 0（报价已含）；CIF 页：C29 与 C30 都为 0（海运+保险均已含）。
B11: 由此，CFR/CIF 报价里已经付过的运费/保费不会被再加一次。
B13: 【关税与增值税】
B14: 关税税率 C33 必须按税则查询后录入；可享优惠时先核验 4 道闸门：协定生效 / 降税清单 / 原产地规则 / 有效证书。
B15: 增值税分两栏：C42 现金支出 / C43 可抵扣进项；C60 = 现金支出 − 可抵扣。
... B26: 运费/保险/港杂/仓储为模拟情景；税率须按核验日期重新确认；最终金额以海关核定与实际单据为准。

Sheet FOB
B1: ① 商品与交易信息
B2: 产品 | C2: 工业级乙二醇 MEG | D2: 规格 | E2: ≥99.9% 工业级
B3: HS编码 | C3: 29053100 | D3: 原产国 | E3: SA 沙特阿拉伯
B4: 目的地 | C4: 宁波港 → 江苏苏州 | D4: 指定地点 | E4: 沙特朱拜勒 Al Jubail
B5: ② 报价与费用参数（黄色=可改，白色=公式；未填=待确认，绝不当作 0）
B6: 供应商单价（原币/计价单位） | C6: 640 | F6: 黄色单元格可修改
B7: 数量（吨） | C7: 62.5 | F7: 25×40' ISO 罐 × 25.0 吨
B8: 单价计价单位（MT / CONTAINER） | C8: MT | F8: MT=每吨价；CONTAINER=每柜价
B9: 包装是否已含于单价（TRUE/FALSE） | C9: TRUE | F9: 《关税法》第25条：包装费计入计税价格
B10: 市场参考汇率 USD/CNY | C10: 6.6807 | F10: ECB 2026-10-19；exchangerate-api 2026-10-20=6.69
B11: 海关计征汇率 USD/CNY（演示占位值，须替换） | C11: 6.72 | F11: 演示占位 6.7200（非2026-09-16官方值）；请替换为申报日对应上月第三个星期三亚行中间价；留空=待补全
B12: 出口侧费用 USD（EXW/FCA 填） | F12: 其余术语自动置 0
B13: 起运港费用 USD（EXW/FCA 填） | F13: FOB 及以上已含，自动置 0
B14: 海运费 USD/MT（报价未含时填） | C14: 45 | F14: 仅 FOB/EXW/FCA/FAS 需要
B15: 整票海运费 USD（可选） | F15: 货代按整票报价时填，优先于单价
B16: 保险费率 ‰ | C16: 0.55 | F16: 保费=(货值+运费)×费率×110%（模拟）
B17: 实际保险费 USD（可选） | F17: 有保单时填，优先于费率
B18: 保险是否已含于报价（TRUE/FALSE） | C18: FALSE | F18: CIF 默认 TRUE
B19: 包装费另计 USD | C19: 0 | F19: PI 另计包装时填；已含填 0
B20: 报价已含海运费（按术语判定） | C20: =OR("FOB"="CFR","FOB"="CIF","FOB"="CPT","FOB"="CIP","FOB"="DAP","FOB"="DPU","FOB"="DDP") | F20: Incoterms 2020
B21: 报价已含保险费（按术语判定） | C21: =OR("FOB"="CIF","FOB"="CIP","FOB"="DDP") | F21: Incoterms 2020
B22: 报价已含起运港费用（按术语判定） | C22: =NOT(OR("FOB"="EXW","FOB"="FCA")) | F22: EXW/FCA 不含装运港费用
B23: ③ 第一层：货值 → 到岸（C=原币；D=人民币，按市场参考汇率）
B24: 货值（单价×数量） | C24: =IF(AND(ISNUMBER(C6),ISNUMBER(C7)),C6*C7,"") | D24: =IF(ISNUMBER(C24),C24*$C$10,"") | E24: 人民币 | F24: 整票货值（原币）
B25: 单吨货值 | C25: =IF(AND(ISNUMBER(C24),C7>0),C24/C7,"") | D25: =IF(ISNUMBER(C25),C25*$C$10,"") | E25: 人民币 | F25: 原币/吨
B26: 包装费（另计） | C26: =IF(C9=TRUE,0,IF(ISNUMBER(C19),C19,"")) | D26: =IF(ISNUMBER(C26),C26*$C$10,"") | E26: 人民币 | F26: 单价已含包装 → 0
B27: 起运港费用 | C27: =IF(C22,0,IF(ISNUMBER(C13),C13,"")) | D27: =IF(ISNUMBER(C27),C27*$C$10,"") | E27: 人民币 | F27: 报价已含 → 0
B28: 出口侧费用 | C28: =IF(C22,0,IF(ISNUMBER(C12),C12,"")) | D28: =IF(ISNUMBER(C28),C28*$C$10,"") | E28: 人民币 | F28: 报价已含 → 0
B29: 海运费（整票） | C29: =IF(C20,0,IF(ISNUMBER(C15),C15,IF(AND(ISNUMBER(C14),ISNUMBER(C7)),C14*C7,""))) | D29: =IF(ISNUMBER(C29),C29*$C$10,"") | E29: 人民币 | F29: CFR/CIF 已含 → 0（不重复计费）
B30: 保险费（实际） | C30: =IF(C18,0,IF(ISNUMBER(C17),C17,IF(AND(ISNUMBER(C16),ISNUMBER(C24),ISNUMBER(C29)),(C24+C29)*C16/100*1.1,""))) | D30: =IF(ISNUMBER(C30),C30*$C$10,"") | E30: 人民币 | F30: CIF 已含 → 0；费率按 110% 投保额
B31: 到岸成本合计（CIF 等值） | C31: =IF(COUNT(C24,C26,C27,C28,C29,C30)=6,SUM(C24,C26,C27,C28,C29,C30),"") | D31: =IF(ISNUMBER(C31),C31*$C$10,"") | E31: 人民币 | F31: 货值+包装+起运港+出口侧+海运+保险（原币与人民币两列）
B32: ④ 第二层：进口税费（关税不可抵扣；增值税分现金/可抵扣两栏）
B33: 关税税率（实征，从税则查询录入） | C33: 0.055 | F33: 来源与核验日期见【数据来源】页
B34: 反倾销/反补贴税率 | C34: 0 | F34: 核验后填写；未查到填 0 并注明（≠不存在）
B35: 进口环节增值税率 | C35: 0.13 | F35: 一般货物 13%
B36: 增值税是否可抵扣（是/否） | C36: 是 | F36: 一般纳税人且用于应税项目=是
B37: 其中：计入计税价格的保险费 | C37: =IF(C18=TRUE,0,IF(ISNUMBER(C30),C30,IF(AND(ISNUMBER(C24),ISNUMBER(C29)),((C24)+IF(C9=TRUE,0,IF(ISNUMBER(C19),C19,0))+IF(C22,0,IF(ISNUMBER(C13),C13,0))+IF(C22,0,IF(ISNUMBER(C12),C12,0))+C29)*0.003/0.997,""))) | F37: 未投保时按（货价+运费）×0.3‰（第36条）
B38: 关税计税价格（人民币，完税价格） | C38: =IF(AND(ISNUMBER(C24),ISNUMBER(C11),ISNUMBER(C26),ISNUMBER(C28),ISNUMBER(C29),ISNUMBER(C30),ISNUMBER(C37)),(C24+C26+IF(ISNUMBER(C27),C27,0)+C28+C29+IF(C18,0,C37))*C11,"") | F38: ＝(货值+包装+起运港+出口侧+海运+实际保险+应计保险)×海关计征汇率
B39: 应纳关税 | C39: =IF(AND(ISNUMBER(C38),ISNUMBER(C33)),C38*C33,"") | F39: ＝计税价格×实征税率（不可抵扣，一定进成本）
B40: 反倾销/反补贴税 | C40: =IF(AND(ISNUMBER(C38),ISNUMBER(C34)),C38*C34,"") | F40: ＝计税价格×措施税率
B41: 组成计税价格（增值税基数） | C41: =IF(AND(ISNUMBER(C38),ISNUMBER(C39)),C38+C39+C40,"") | F41: ＝计税价格+关税+反倾销税（+消费税，本产品无）
B42: 进口环节增值税（现金支出） | C42: =IF(AND(ISNUMBER(C41),ISNUMBER(C35)),C41*C35,"") | F42: ＝组成计税价格×13%；现金支出，另行列可抵扣
B43: 其中：可抵扣进项税额 | C43: =IF(AND(ISNUMBER(C42),LEFT(C36,1)="是"),C42,0) | F43: 可抵扣部分不计入最终经济成本
B44: 其中：不可抵扣部分（进成本） | C44: =IF(ISNUMBER(C42),C42-C43,"") | F44: 不可抵扣时全额进入成本
B45: ⑤ 第三层：口岸与境内物流（人民币，整票；不进入计税价格）
B46: 港杂费 | C46: 600 | F46: THC/港建/换单/堆存等
B47: 报关代理费 | C47: 500 | F47: 宁波港公示 100–500 元/票
B48: 检验检测费 | C48: 0 | F48: 无检验填 0 并注明
B49: 仓储费 | C49: 3000 | F49: 无仓储填 0 并注明
B50: 国内运输费 | C50: 7812.5 | F50: 0.5 元/吨·km × 250km × 62.5t
B51: 资金/信用证成本 | C51: 0 | F51: 不计入计税价格
B52: 境内费用合计 | C52: =IF(COUNT(C46:C51)=6,SUM(C46:C51),"") | F52: 人民币，不受汇率影响
B53: ⑥ 汇总：现金支出 / 可抵扣税额 / 最终经济成本
B54: ① 到岸成本（不含进口税费） | C54: =IF(ISNUMBER(C31),D31,"") | F54: 货值+运费+保险（市场汇率）
B55: ② 关税 + 反倾销税 | C55: =IF(AND(ISNUMBER(C39),ISNUMBER(C40)),C39+C40,"") | F55: 不可抵扣
B56: ③ 进口环节增值税（现金全额） | C56: =IF(ISNUMBER(C42),C42,"") | F56: 现金支出
B57: ④ 境内费用 | C57: =IF(ISNUMBER(C52),C52,"")
B58: 整票现金支出 = ①+②+③+④ | C58: =IF(COUNT(C54:C57)=4,SUM(C54:C57),"") | F58: 所有实际付出去的钱
B59: 减：可抵扣进项税额 | C59: =IF(ISNUMBER(C43),-C43,"") | F59: 申报期抵扣、现金回流
B60: 最终经济成本（整票）= 现金支出 − 可抵扣 | C60: =IF(ISNUMBER(C58),C58+C59,"") | F60: 可抵扣时已剔除增值税
B61: ★ 最终经济成本 元/吨（参考到厂成本） | C61: =IF(AND(ISNUMBER(C60),C7>0),C60/C7,"")
B62: 现金支出 元/吨 | C62: =IF(AND(ISNUMBER(C58),C7>0),C58/C7,"")
B63: 到岸成本 元/吨 | C63: =IF(AND(ISNUMBER(C54),C7>0),C54/C7,"")
B64: 完整到厂成本状态 | C64: =IF(COUNT(C24,C26,C27,C28,C29,C30,C31,C38,C41,C42,C46,C47,C48,C49,C50,C51)=16,IF(COUNT(C11,C33,C35)=3,"完整","待补全（缺关税税率或海关计征汇率）"),"待补全（缺费用项）") | F64: 未填项不会被当作 0；待补全时完整到厂价不可对外使用
B65: 已知成本小计（下限参考，非完整到厂价） | C65: =IFERROR(SUM(C31,C39,C40,C42,C52),0) | F65: 待补全时只能引用此值

Sheet CFR
B1: ① 商品与交易信息
B2: 产品 | C2: 工业级乙二醇 MEG | D2: 规格 | E2: ≥99.9% 工业级
B3: HS编码 | C3: 29053100 | D3: 原产国 | E3: SA 沙特阿拉伯
B4: 目的地 | C4: 宁波港 → 江苏苏州 | D4: 指定地点 | E4: 中国宁波
B5: ② 报价与费用参数（黄色=可改，白色=公式；未填=待确认，绝不当作 0）
B6: 供应商单价（原币/计价单位） | C6: 685 | F6: 黄色单元格可修改
B7: 数量（吨） | C7: 62.5 | F7: 25×40' ISO 罐 × 25.0 吨
B8: 单价计价单位（MT / CONTAINER） | C8: MT | F8: MT=每吨价；CONTAINER=每柜价
B9: 包装是否已含于单价（TRUE/FALSE） | C9: TRUE | F9: 《关税法》第25条：包装费计入计税价格
B10: 市场参考汇率 USD/CNY | C10: 6.6807 | F10: ECB 2026-10-19；exchangerate-api 2026-10-20=6.69
B11: 海关计征汇率 USD/CNY（演示占位值，须替换） | C11: 6.72 | F11: 演示占位 6.7200（非2026-09-16官方值）；请替换为申报日对应上月第三个星期三亚行中间价；留空=待补全
B12: 出口侧费用 USD（EXW/FCA 填） | F12: 其余术语自动置 0
B13: 起运港费用 USD（EXW/FCA 填） | F13: FOB 及以上已含，自动置 0
B14: 海运费 USD/MT（报价未含时填） | F14: 仅 FOB/EXW/FCA/FAS 需要
B15: 整票海运费 USD（可选） | F15: 货代按整票报价时填，优先于单价
B16: 保险费率 ‰ | C16: 0.55 | F16: 保费=(货值+运费)×费率×110%（模拟）
B17: 实际保险费 USD（可选） | F17: 有保单时填，优先于费率
B18: 保险是否已含于报价（TRUE/FALSE） | C18: FALSE | F18: CIF 默认 TRUE
B19: 包装费另计 USD | C19: 0 | F19: PI 另计包装时填；已含填 0
B20: 报价已含海运费（按术语判定） | C20: =OR("CFR"="CFR","CFR"="CIF","CFR"="CPT","CFR"="CIP","CFR"="DAP","CFR"="DPU","CFR"="DDP") | F20: Incoterms 2020
B21: 报价已含保险费（按术语判定） | C21: =OR("CFR"="CIF","CFR"="CIP","CFR"="DDP") | F21: Incoterms 2020
B22: 报价已含起运港费用（按术语判定） | C22: =NOT(OR("CFR"="EXW","CFR"="FCA")) | F22: EXW/FCA 不含装运港费用
B23: ③ 第一层：货值 → 到岸（C=原币；D=人民币，按市场参考汇率）
B24: 货值（单价×数量） | C24: =IF(AND(ISNUMBER(C6),ISNUMBER(C7)),C6*C7,"") | D24: =IF(ISNUMBER(C24),C24*$C$10,"") | E24: 人民币 | F24: 整票货值（原币）
B25: 单吨货值 | C25: =IF(AND(ISNUMBER(C24),C7>0),C24/C7,"") | D25: =IF(ISNUMBER(C25),C25*$C$10,"") | E25: 人民币 | F25: 原币/吨
B26: 包装费（另计） | C26: =IF(C9=TRUE,0,IF(ISNUMBER(C19),C19,"")) | D26: =IF(ISNUMBER(C26),C26*$C$10,"") | E26: 人民币 | F26: 单价已含包装 → 0
B27: 起运港费用 | C27: =IF(C22,0,IF(ISNUMBER(C13),C13,"")) | D27: =IF(ISNUMBER(C27),C27*$C$10,"") | E27: 人民币 | F27: 报价已含 → 0
B28: 出口侧费用 | C28: =IF(C22,0,IF(ISNUMBER(C12),C12,"")) | D28: =IF(ISNUMBER(C28),C28*$C$10,"") | E28: 人民币 | F28: 报价已含 → 0
B29: 海运费（整票） | C29: =IF(C20,0,IF(ISNUMBER(C15),C15,IF(AND(ISNUMBER(C14),ISNUMBER(C7)),C14*C7,""))) | D29: =IF(ISNUMBER(C29),C29*$C$10,"") | E29: 人民币 | F29: CFR/CIF 已含 → 0（不重复计费）
B30: 保险费（实际） | C30: =IF(C18,0,IF(ISNUMBER(C17),C17,IF(AND(ISNUMBER(C16),ISNUMBER(C24),ISNUMBER(C29)),(C24+C29)*C16/100*1.1,""))) | D30: =IF(ISNUMBER(C30),C30*$C$10,"") | E30: 人民币 | F30: CIF 已含 → 0；费率按 110% 投保额
B31: 到岸成本合计（CIF 等值） | C31: =IF(COUNT(C24,C26,C27,C28,C29,C30)=6,SUM(C24,C26,C27,C28,C29,C30),"") | D31: =IF(ISNUMBER(C31),C31*$C$10,"") | E31: 人民币 | F31: 货值+包装+起运港+出口侧+海运+保险（原币与人民币两列）
B32: ④ 第二层：进口税费（关税不可抵扣；增值税分现金/可抵扣两栏）
B33: 关税税率（实征，从税则查询录入） | C33: 0.055 | F33: 来源与核验日期见【数据来源】页
B34: 反倾销/反补贴税率 | C34: 0 | F34: 核验后填写；未查到填 0 并注明（≠不存在）
B35: 进口环节增值税率 | C35: 0.13 | F35: 一般货物 13%
B36: 增值税是否可抵扣（是/否） | C36: 是 | F36: 一般纳税人且用于应税项目=是
B37: 其中：计入计税价格的保险费 | C37: =IF(C18=TRUE,0,IF(ISNUMBER(C30),C30,IF(AND(ISNUMBER(C24),ISNUMBER(C29)),((C24)+IF(C9=TRUE,0,IF(ISNUMBER(C19),C19,0))+IF(C22,0,IF(ISNUMBER(C13),C13,0))+IF(C22,0,IF(ISNUMBER(C12),C12,0))+C29)*0.003/0.997,""))) | F37: 未投保时按（货价+运费）×0.3‰（第36条）
B38: 关税计税价格（人民币，完税价格） | C38: =IF(AND(ISNUMBER(C24),ISNUMBER(C11),ISNUMBER(C26),ISNUMBER(C28),ISNUMBER(C29),ISNUMBER(C30),ISNUMBER(C37)),(C24+C26+IF(ISNUMBER(C27),C27,0)+C28+C29+IF(C18,0,C37))*C11,"") | F38: ＝(货值+包装+起运港+出口侧+海运+实际保险+应计保险)×海关计征汇率
B39: 应纳关税 | C39: =IF(AND(ISNUMBER(C38),ISNUMBER(C33)),C38*C33,"") | F39: ＝计税价格×实征税率（不可抵扣，一定进成本）
B40: 反倾销/反补贴税 | C40: =IF(AND(ISNUMBER(C38),ISNUMBER(C34)),C38*C34,"") | F40: ＝计税价格×措施税率
B41: 组成计税价格（增值税基数） | C41: =IF(AND(ISNUMBER(C38),ISNUMBER(C39)),C38+C39+C40,"") | F41: ＝计税价格+关税+反倾销税（+消费税，本产品无）
B42: 进口环节增值税（现金支出） | C42: =IF(AND(ISNUMBER(C41),ISNUMBER(C35)),C41*C35,"") | F42: ＝组成计税价格×13%；现金支出，另行列可抵扣
B43: 其中：可抵扣进项税额 | C43: =IF(AND(ISNUMBER(C42),LEFT(C36,1)="是"),C42,0) | F43: 可抵扣部分不计入最终经济成本
B44: 其中：不可抵扣部分（进成本） | C44: =IF(ISNUMBER(C42),C42-C43,"") | F44: 不可抵扣时全额进入成本
B45: ⑤ 第三层：口岸与境内物流（人民币，整票；不进入计税价格）
B46: 港杂费 | C46: 600 | F46: THC/港建/换单/堆存等
B47: 报关代理费 | C47: 500 | F47: 宁波港公示 100–500 元/票
B48: 检验检测费 | C48: 0 | F48: 无检验填 0 并注明
B49: 仓储费 | C49: 3000 | F49: 无仓储填 0 并注明
B50: 国内运输费 | C50: 7812.5 | F50: 0.5 元/吨·km × 250km × 62.5t
B51: 资金/信用证成本 | C51: 0 | F51: 不计入计税价格
B52: 境内费用合计 | C52: =IF(COUNT(C46:C51)=6,SUM(C46:C51),"") | F52: 人民币，不受汇率影响
B53: ⑥ 汇总：现金支出 / 可抵扣税额 / 最终经济成本
B54: ① 到岸成本（不含进口税费） | C54: =IF(ISNUMBER(C31),D31,"") | F54: 货值+运费+保险（市场汇率）
B55: ② 关税 + 反倾销税 | C55: =IF(AND(ISNUMBER(C39),ISNUMBER(C40)),C39+C40,"") | F55: 不可抵扣
B56: ③ 进口环节增值税（现金全额） | C56: =IF(ISNUMBER(C42),C42,"") | F56: 现金支出
B57: ④ 境内费用 | C57: =IF(ISNUMBER(C52),C52,"")
B58: 整票现金支出 = ①+②+③+④ | C58: =IF(COUNT(C54:C57)=4,SUM(C54:C57),"") | F58: 所有实际付出去的钱
B59: 减：可抵扣进项税额 | C59: =IF(ISNUMBER(C43),-C43,"") | F59: 申报期抵扣、现金回流
B60: 最终经济成本（整票）= 现金支出 − 可抵扣 | C60: =IF(ISNUMBER(C58),C58+C59,"") | F60: 可抵扣时已剔除增值税
B61: ★ 最终经济成本 元/吨（参考到厂成本） | C61: =IF(AND(ISNUMBER(C60),C7>0),C60/C7,"")
B62: 现金支出 元/吨 | C62: =IF(AND(ISNUMBER(C58),C7>0),C58/C7,"")
B63: 到岸成本 元/吨 | C63: =IF(AND(ISNUMBER(C54),C7>0),C54/C7,"")
B64: 完整到厂成本状态 | C64: =IF(COUNT(C24,C26,C27,C28,C29,C30,C31,C38,C41,C42,C46,C47,C48,C49,C50,C51)=16,IF(COUNT(C11,C33,C35)=3,"完整","待补全（缺关税税率或海关计征汇率）"),"待补全（缺费用项）") | F64: 未填项不会被当作 0；待补全时完整到厂价不可对外使用
B65: 已知成本小计（下限参考，非完整到厂价） | C65: =IFERROR(SUM(C31,C39,C40,C42,C52),0) | F65: 待补全时只能引用此值

Sheet CIF
B1: ① 商品与交易信息
B2: 产品 | C2: 工业级乙二醇 MEG | D2: 规格 | E2: ≥99.9% 工业级
B3: HS编码 | C3: 29053100 | D3: 原产国 | E3: SA 沙特阿拉伯
B4: 目的地 | C4: 宁波港 → 江苏苏州 | D4: 指定地点 | E4: 中国宁波
B5: ② 报价与费用参数（黄色=可改，白色=公式；未填=待确认，绝不当作 0）
B6: 供应商单价（原币/计价单位） | C6: 685.05 | F6: 黄色单元格可修改
B7: 数量（吨） | C7: 62.5 | F7: 25×40' ISO 罐 × 25.0 吨
B8: 单价计价单位（MT / CONTAINER） | C8: MT | F8: MT=每吨价；CONTAINER=每柜价
B9: 包装是否已含于单价（TRUE/FALSE） | C9: TRUE | F9: 《关税法》第25条：包装费计入计税价格
B10: 市场参考汇率 USD/CNY | C10: 6.6807 | F10: ECB 2026-10-19；exchangerate-api 2026-10-20=6.69
B11: 海关计征汇率 USD/CNY（演示占位值，须替换） | C11: 6.72 | F11: 演示占位 6.7200（非2026-09-16官方值）；请替换为申报日对应上月第三个星期三亚行中间价；留空=待补全
B12: 出口侧费用 USD（EXW/FCA 填） | F12: 其余术语自动置 0
B13: 起运港费用 USD（EXW/FCA 填） | F13: FOB 及以上已含，自动置 0
B14: 海运费 USD/MT（报价未含时填） | F14: 仅 FOB/EXW/FCA/FAS 需要
B15: 整票海运费 USD（可选） | F15: 货代按整票报价时填，优先于单价
B16: 保险费率 ‰ | C16: 0.55 | F16: 保费=(货值+运费)×费率×110%（模拟）
B17: 实际保险费 USD（可选） | F17: 有保单时填，优先于费率
B18: 保险是否已含于报价（TRUE/FALSE） | C18: TRUE | F18: CIF 默认 TRUE
B19: 包装费另计 USD | C19: 0 | F19: PI 另计包装时填；已含填 0
B20: 报价已含海运费（按术语判定） | C20: =OR("CIF"="CFR","CIF"="CIF","CIF"="CPT","CIF"="CIP","CIF"="DAP","CIF"="DPU","CIF"="DDP") | F20: Incoterms 2020
B21: 报价已含保险费（按术语判定） | C21: =OR("CIF"="CIF","CIF"="CIP","CIF"="DDP") | F21: Incoterms 2020
B22: 报价已含起运港费用（按术语判定） | C22: =NOT(OR("CIF"="EXW","CIF"="FCA")) | F22: EXW/FCA 不含装运港费用
B23: ③ 第一层：货值 → 到岸（C=原币；D=人民币，按市场参考汇率）
B24: 货值（单价×数量） | C24: =IF(AND(ISNUMBER(C6),ISNUMBER(C7)),C6*C7,"") | D24: =IF(ISNUMBER(C24),C24*$C$10,"") | E24: 人民币 | F24: 整票货值（原币）
B25: 单吨货值 | C25: =IF(AND(ISNUMBER(C24),C7>0),C24/C7,"") | D25: =IF(ISNUMBER(C25),C25*$C$10,"") | E25: 人民币 | F25: 原币/吨
B26: 包装费（另计） | C26: =IF(C9=TRUE,0,IF(ISNUMBER(C19),C19,"")) | D26: =IF(ISNUMBER(C26),C26*$C$10,"") | E26: 人民币 | F26: 单价已含包装 → 0
B27: 起运港费用 | C27: =IF(C22,0,IF(ISNUMBER(C13),C13,"")) | D27: =IF(ISNUMBER(C27),C27*$C$10,"") | E27: 人民币 | F27: 报价已含 → 0
B28: 出口侧费用 | C28: =IF(C22,0,IF(ISNUMBER(C12),C12,"")) | D28: =IF(ISNUMBER(C28),C28*$C$10,"") | E28: 人民币 | F28: 报价已含 → 0
B29: 海运费（整票） | C29: =IF(C20,0,IF(ISNUMBER(C15),C15,IF(AND(ISNUMBER(C14),ISNUMBER(C7)),C14*C7,""))) | D29: =IF(ISNUMBER(C29),C29*$C$10,"") | E29: 人民币 | F29: CFR/CIF 已含 → 0（不重复计费）
B30: 保险费（实际） | C30: =IF(C18,0,IF(ISNUMBER(C17),C17,IF(AND(ISNUMBER(C16),ISNUMBER(C24),ISNUMBER(C29)),(C24+C29)*C16/100*1.1,""))) | D30: =IF(ISNUMBER(C30),C30*$C$10,"") | E30: 人民币 | F30: CIF 已含 → 0；费率按 110% 投保额
B31: 到岸成本合计（CIF 等值） | C31: =IF(COUNT(C24,C26,C27,C28,C29,C30)=6,SUM(C24,C26,C27,C28,C29,C30),"") | D31: =IF(ISNUMBER(C31),C31*$C$10,"") | E31: 人民币 | F31: 货值+包装+起运港+出口侧+海运+保险（原币与人民币两列）
B32: ④ 第二层：进口税费（关税不可抵扣；增值税分现金/可抵扣两栏）
B33: 关税税率（实征，从税则查询录入） | C33: 0.055 | F33: 来源与核验日期见【数据来源】页
B34: 反倾销/反补贴税率 | C34: 0 | F34: 核验后填写；未查到填 0 并注明（≠不存在）
B35: 进口环节增值税率 | C35: 0.13 | F35: 一般货物 13%
B36: 增值税是否可抵扣（是/否） | C36: 是 | F36: 一般纳税人且用于应税项目=是
B37: 其中：计入计税价格的保险费 | C37: =IF(C18=TRUE,0,IF(ISNUMBER(C30),C30,IF(AND(ISNUMBER(C24),ISNUMBER(C29)),((C24)+IF(C9=TRUE,0,IF(ISNUMBER(C19),C19,0))+IF(C22,0,IF(ISNUMBER(C13),C13,0))+IF(C22,0,IF(ISNUMBER(C12),C12,0))+C29)*0.003/0.997,""))) | F37: 未投保时按（货价+运费）×0.3‰（第36条）
B38: 关税计税价格（人民币，完税价格） | C38: =IF(AND(ISNUMBER(C24),ISNUMBER(C11),ISNUMBER(C26),ISNUMBER(C28),ISNUMBER(C29),ISNUMBER(C30),ISNUMBER(C37)),(C24+C26+IF(ISNUMBER(C27),C27,0)+C28+C29+IF(C18,0,C37))*C11,"") | F38: ＝(货值+包装+起运港+出口侧+海运+实际保险+应计保险)×海关计征汇率
B39: 应纳关税 | C39: =IF(AND(ISNUMBER(C38),ISNUMBER(C33)),C38*C33,"") | F39: ＝计税价格×实征税率（不可抵扣，一定进成本）
B40: 反倾销/反补贴税 | C40: =IF(AND(ISNUMBER(C38),ISNUMBER(C34)),C38*C34,"") | F40: ＝计税价格×措施税率
B41: 组成计税价格（增值税基数） | C41: =IF(AND(ISNUMBER(C38),ISNUMBER(C39)),C38+C39+C40,"") | F41: ＝计税价格+关税+反倾销税（+消费税，本产品无）
B42: 进口环节增值税（现金支出） | C42: =IF(AND(ISNUMBER(C41),ISNUMBER(C35)),C41*C35,"") | F42: ＝组成计税价格×13%；现金支出，另行列可抵扣
B43: 其中：可抵扣进项税额 | C43: =IF(AND(ISNUMBER(C42),LEFT(C36,1)="是"),C42,0) | F43: 可抵扣部分不计入最终经济成本
B44: 其中：不可抵扣部分（进成本） | C44: =IF(ISNUMBER(C42),C42-C43,"") | F44: 不可抵扣时全额进入成本
B45: ⑤ 第三层：口岸与境内物流（人民币，整票；不进入计税价格）
B46: 港杂费 | C46: 600 | F46: THC/港建/换单/堆存等
B47: 报关代理费 | C47: 500 | F47: 宁波港公示 100–500 元/票
B48: 检验检测费 | C48: 0 | F48: 无检验填 0 并注明
B49: 仓储费 | C49: 3000 | F49: 无仓储填 0 并注明
B50: 国内运输费 | C50: 7812.5 | F50: 0.5 元/吨·km × 250km × 62.5t
B51: 资金/信用证成本 | C51: 0 | F51: 不计入计税价格
B52: 境内费用合计 | C52: =IF(COUNT(C46:C51)=6,SUM(C46:C51),"") | F52: 人民币，不受汇率影响
B53: ⑥ 汇总：现金支出 / 可抵扣税额 / 最终经济成本
B54: ① 到岸成本（不含进口税费） | C54: =IF(ISNUMBER(C31),D31,"") | F54: 货值+运费+保险（市场汇率）
B55: ② 关税 + 反倾销税 | C55: =IF(AND(ISNUMBER(C39),ISNUMBER(C40)),C39+C40,"") | F55: 不可抵扣
B56: ③ 进口环节增值税（现金全额） | C56: =IF(ISNUMBER(C42),C42,"") | F56: 现金支出
B57: ④ 境内费用 | C57: =IF(ISNUMBER(C52),C52,"")
B58: 整票现金支出 = ①+②+③+④ | C58: =IF(COUNT(C54:C57)=4,SUM(C54:C57),"") | F58: 所有实际付出去的钱
B59: 减：可抵扣进项税额 | C59: =IF(ISNUMBER(C43),-C43,"") | F59: 申报期抵扣、现金回流
B60: 最终经济成本（整票）= 现金支出 − 可抵扣 | C60: =IF(ISNUMBER(C58),C58+C59,"") | F60: 可抵扣时已剔除增值税
B61: ★ 最终经济成本 元/吨（参考到厂成本） | C61: =IF(AND(ISNUMBER(C60),C7>0),C60/C7,"")
B62: 现金支出 元/吨 | C62: =IF(AND(ISNUMBER(C58),C7>0),C58/C7,"")
B63: 到岸成本 元/吨 | C63: =IF(AND(ISNUMBER(C54),C7>0),C54/C7,"")
B64: 完整到厂成本状态 | C64: =IF(COUNT(C24,C26,C27,C28,C29,C30,C31,C38,C41,C42,C46,C47,C48,C49,C50,C51)=16,IF(COUNT(C11,C33,C35)=3,"完整","待补全（缺关税税率或海关计征汇率）"),"待补全（缺费用项）") | F64: 未填项不会被当作 0；待补全时完整到厂价不可对外使用
B65: 已知成本小计（下限参考，非完整到厂价） | C65: =IFERROR(SUM(C31,C39,C40,C42,C52),0) | F65: 待补全时只能引用此值

Sheet 口径对照
B1: FOB / CFR / CIF 三口径对照
B2: 经济实质相同时（FOB 640 + 运费 45 + 保费），三口径到厂成本应基本一致；差异只来自卖方对运费/保险的加价。
B4: 指标 | C4: FOB 朱拜勒 | D4: CFR 宁波 | E4: CIF 宁波 | F4: CFR−FOB | G4: CIF−FOB
B5: 报价（原币/吨） | C5: ='FOB'!C6 | D5: ='CFR'!C6 | E5: ='CIF'!C6 | F5: =IF(AND(ISNUMBER(C5),ISNUMBER(D5)),D5-C5,"") | G5: =IF(AND(ISNUMBER(C5),ISNUMBER(E5)),E5-C5,"")
B6: 到岸成本 元/吨 | C6: ='FOB'!C63 | D6: ='CFR'!C63 | E6: ='CIF'!C63 | F6: =IF(AND(ISNUMBER(C6),ISNUMBER(D6)),D6-C6,"") | G6: =IF(AND(ISNUMBER(C6),ISNUMBER(E6)),E6-C6,"")
B7: 关税计税价格（元） | C7: ='FOB'!C38 | D7: ='CFR'!C38 | E7: ='CIF'!C38 | F7: =IF(AND(ISNUMBER(C7),ISNUMBER(D7)),D7-C7,"") | G7: =IF(AND(ISNUMBER(C7),ISNUMBER(E7)),E7-C7,"")
B8: 应纳关税（元） | C8: ='FOB'!C39 | D8: ='CFR'!C39 | E8: ='CIF'!C39 | F8: =IF(AND(ISNUMBER(C8),ISNUMBER(D8)),D8-C8,"") | G8: =IF(AND(ISNUMBER(C8),ISNUMBER(E8)),E8-C8,"")
B9: 增值税（元，现金） | C9: ='FOB'!C42 | D9: ='CFR'!C42 | E9: ='CIF'!C42 | F9: =IF(AND(ISNUMBER(C9),ISNUMBER(D9)),D9-C9,"") | G9: =IF(AND(ISNUMBER(C9),ISNUMBER(E9)),E9-C9,"")
B10: 可抵扣进项（元） | C10: ='FOB'!C43 | D10: ='CFR'!C43 | E10: ='CIF'!C43 | F10: =IF(AND(ISNUMBER(C10),ISNUMBER(D10)),D10-C10,"") | G10: =IF(AND(ISNUMBER(C10),ISNUMBER(E10)),E10-C10,"")
B11: 整票现金支出（元） | C11: ='FOB'!C58 | D11: ='CFR'!C58 | E11: ='CIF'!C58 | F11: =IF(AND(ISNUMBER(C11),ISNUMBER(D11)),D11-C11,"") | G11: =IF(AND(ISNUMBER(C11),ISNUMBER(E11)),E11-C11,"")
B12: 最终经济成本（元） | C12: ='FOB'!C60 | D12: ='CFR'!C60 | E12: ='CIF'!C60 | F12: =IF(AND(ISNUMBER(C12),ISNUMBER(D12)),D12-C12,"") | G12: =IF(AND(ISNUMBER(C12),ISNUMBER(E12)),E12-C12,"")
B13: 最终经济成本 元/吨 | C13: ='FOB'!C61 | D13: ='CFR'!C61 | E13: ='CIF'!C61 | F13: =IF(AND(ISNUMBER(C13),ISNUMBER(D13)),D13-C13,"") | G13: =IF(AND(ISNUMBER(C13),ISNUMBER(E13)),E13-C13,"")
B14: 完整状态 | C14: ='FOB'!C64 | D14: ='CFR'!C64 | E14: ='CIF'!C64 | F14: =IF(AND(ISNUMBER(C14),ISNUMBER(D14)),D14-C14,"") | G14: =IF(AND(ISNUMBER(C14),ISNUMBER(E14)),E14-C14,"")
B16: 结论要点
B17: ① FOB 报价不含海运与保险，测算必须另加；CFR/CIF 已含海运费，绝不能再加一次。
B18: ② CIF 已含保险；买方另行加保的费用单列，不得与报价内保费重复。
B19: ③ 三口径到厂成本差异 = 卖方对运费/保险的加价 → 这是议价抓手。
B20: ④ 关税与增值税的计税价格都以 CIF 等值为基础：FOB 报价看着低，税费基数并不低。
B21: ⑤ 状态为「待补全」时，该口径的到厂价不可对外使用，只能用「已知成本小计」。

Sheet 敏感性分析
B1: 敏感性分析（基准 = FOB 页，全部由公式驱动）
B2: 每个情景独立复刻计算链：货值→CIF→关税计税价格→关税→增值税→现金支出→可抵扣→元/吨。未做线性近似。
B4: 基准（FOB 页） | C4: ='FOB'!C6 | D4: ='FOB'!C61 | E4: ='FOB'!C60 | G4: C=单价 / D=到厂 元吨 / E=整票
B6: ① 汇率 ±3%（市场汇率与海关计征汇率同向变动）
B7: 情景 | C7: 情景参数 | D7: 到厂成本 元/吨 | E7: Δ 元/吨 | F7: Δ % | G7: 说明
B9: 汇率 -3% | C9: -0.03 | D9: =IF(AND(ISNUMBER('FOB'!C6),ISNUMBER('FOB'!C7),ISNUMBER('FOB'!C10*(1+-0.03)),ISNUMBER(IF(ISNUMBER('FOB'!C11),'FOB'!C11*(1+-0.03),"")),ISNUMBER('FOB'!C33)),((IF(AND(ISNUMBER('FOB'!C6),ISNUMBER('FOB'!C7)),'FOB'!C6*'FOB'!C7,0)+IF('FOB'!C9=TRUE,0,IF(ISNUMBER('FOB'!C19),'FOB'!C19,0))+IF(ISNUMBER('FOB'!C13),IF('FOB'!C22,0,'FOB'!C13),0)+IF(ISNUMBER('FOB'!C12),IF('FOB'!C22,0,'FOB'!C12),0)+IF('FOB'!C20,0,IF(ISNUMBER('FOB'!C14),'FOB'!C14*'FOB'!C7,0))+IF('FOB'!C18,0,IF(ISNUMBER('FOB'!C17),'FOB'!C17,IF(ISNUMBER('FOB'!C16),(IF(AND(ISNUMBER('FOB'!C6),ISNUMBER('FOB'!C7)),'FOB'!C6*'FOB'!C7,0)+IF('FOB'!C20,0,IF(ISNUMBER('FOB'!C14),'FOB'!C14*'FOB'!C7,0)))*'FOB'!C16/100*1.1,(IF(AND(ISNUMBER('FOB'!C6),ISNUMBER('FOB'!C7)),'FOB'!C6*'FOB'!C7,0)+IF('FOB'!C9=TRUE,0,IF(ISNUMBER('FOB'!C19),'FOB'!C19,0))+IF(ISNUMBER('FOB'!C13),IF('FOB'!C22,0,'FOB'!C13),0)+IF(ISNUMBER('FOB'!C12),IF('FOB'!C22,0,'FOB'!C12),0)+IF('FOB'!C20,0,IF(ISNUMBER('FOB'!C14),'FOB'!C14*'FOB'!C7,0)))*0.003/0.997))))*IF(ISNUMBER('FOB'!C10*(1+-0.03)),'FOB'!C10*(1+-0.03),0)+IF(ISNUMBER(IF(ISNUMBER('FOB'!C11),'FOB'!C11*(1+-0.03),"")),(IF(AND(ISNUMBER('FOB'!C6),ISNUMBER('FOB'!C7)),'FOB'!C6*'FOB'!C7,0)+IF('FOB'!C9=TRUE,0,IF(ISNUMBER('FOB'!C19),'FOB'!C19,0))+IF(ISNUMBER('FOB'!C13),IF('FOB'!C22,0,'FOB'!C13),0)+IF(ISNUMBER('FOB'!C12),IF('FOB'!C22,0,'FOB'!C12),0)+IF('FOB'!C20,0,IF(ISNUMBER('FOB'!C14),'FOB'!C14*'FOB'!C7,0))+IF('FOB'!C18,0,IF(ISNUMBER('FOB'!C17),'FOB'!C17,IF(ISNUMBER('FOB'!C16),(IF(AND(ISNUMBER('FOB'!C6),ISNUMBER('FOB'!C7)),'FOB'!C6*'FOB'!C7,0)+IF('FOB'!C20,0,IF(ISNUMBER('FOB'!C14),'FOB'!C14*'FOB'!C7,0)))*'FOB'!C16/100*1.1,(IF(AND(ISNUMBER('FOB'!C6),ISNUMBER('FOB'!C7)),'FOB'!C6*'FOB'!C7,0)+IF('FOB'!C9=TRUE,0,IF(ISNUMBER('FOB'!C19),'FOB'!C19,0))+IF(ISNUMBER('FOB'!C13),IF('FOB'!C22,0,'FOB'!C13),0)+IF(ISNUMBER('FOB'!C12),IF('FOB'!C22,0,'FOB'!C12),0)+IF('FOB'!C20,0,IF(ISNUMBER('FOB'!C14),'FOB'!C14*'FOB'!C7,0)))*0.003/0.997))))*IF(ISNUMBER('FOB'!C11),'FOB'!C11*(1+-0.03),""),0)*IF(ISNUMBER('FOB'!C33),'FOB'!C33,0)*(1+IF(ISNUMBER('FOB'!C34),'FOB'!C34,0))+(IF(ISNUMBER(IF(ISNUMBER('FOB'!C11),'FOB'!C11*(1+-0.03),"")),(IF(AND(ISNUMBER('FOB'!C6),ISNUMBER('FOB'!C7)),'FOB'!C6*'FOB'!C7,0)+IF('FOB'!C9=TRUE,0,IF(ISNUMBER('FOB'!C19),'FOB'!C19,0))+IF(ISNUMBER('FOB'!C13),IF('FOB'!C22,0,'FOB'!C13),0)+IF(ISNUMBER('FOB'!C12),IF('FOB'!C22,0,'FOB'!C12),0)+IF('FOB'!C20,0,IF(ISNUMBER('FOB'!C14),'FOB'!C14*'FOB'!C7,0))+IF('FOB'!C18,0,IF(ISNUMBER('FOB'!C17),'FOB'!C17,IF(ISNUMBER('FOB'!C16),(IF(AND(ISNUMBER('FOB'!C6),ISNUMBER('FOB'!C7)),'FOB'!C6*'FOB'!C7,0)+IF('FOB'!C20,0,IF(ISNUMBER('FOB'!C14),'FOB'!C14*'FOB'!C7,0)))*'FOB'!C16/100*1.1,(IF(AND(ISNUMBER('FOB'!C6),ISNUMBER('FOB'!C7)),'FOB'!C6*'FOB'!C7,0)+IF('FOB'!C9=TRUE,0,IF(ISNUMBER('FOB'!C19),'FOB'!C19,0))+IF(ISNUMBER('FOB'!C13),IF('FOB'!C22,0,'FOB'!C13),0)+IF(ISNUMBER('FOB'!C12),IF('FOB'!C22,0,'FOB'!C12),0)+IF('FOB'!C20,0,IF(ISNUMBER('FOB'!C14),'FOB'!C14*'FOB'!C7,0)))*0.003/0.997))))*IF(ISNUMBER('FOB'!C11),'FOB'!C11*(1+-0.03),""),0)+IF(ISNUMBER(IF(ISNUMBER('FOB'!C11),'FOB'!C11*(1+-0.03),"")),(IF(AND(ISNUMBER('FOB'!C6),ISNUMBER('FOB'!C7)),'FOB'!C6*'FOB'!C7,0)+IF('FOB'!C9=TRUE,0,IF(ISNUMBER('FOB'!C19),'FOB'!C19,0))+IF(ISNUMBER('FOB'!C13),IF('FOB'!C22,0,'FOB'!C13),0)+IF(ISNUMBER('FOB'!C12),IF('FOB'!C22,0,'FOB'!C12),0)+IF('FOB'!C20,0,IF(ISNUMBER('FOB'!C14),'FOB'!C14*'FOB'!C7,0))+IF('FOB'!C18,0,IF(ISNUMBER('FOB'!C17),'FOB'!C17,IF(ISNUMBER('FOB'!C16),(IF(AND(ISNUMBER('FOB'!C6),ISNUMBER('FOB'!C7)),'FOB'!C6*'FOB'!C7,0)+IF('FOB'!C20,0,IF(ISNUMBER('FOB'!C14),'FOB'!C14*'FOB'!C7,0)))*'FOB'!C16/100*1.1,(IF(AND(ISNUMBER('FOB'!C6),ISNUMBER('FOB'!C7)),'FOB'!C6*'FOB'!C7,0)+IF('FOB'!C9=TRUE,0,IF(ISNUMBER('FOB'!C19),'FOB'!C19,0))+IF(ISNUMBER('FOB'!C13),IF('FOB'!C22,0,'FOB'!C13),0)+IF(ISNUMBER('FOB'!C12),IF('FOB'!C22,0,'FOB'!C12),0)+IF('FOB'!C20,0,IF(ISNUMBER('FOB'!C14),'FOB'!C14*'FOB'!C7,0)))*0.003/0.997))))*IF(ISNUMBER('FOB'!C11),'FOB'!C11*(1+-0.03),""),0)*IF(ISNUMBER('FOB'!C33),'FOB'!C33,0)*(1+IF(ISNUMBER('FOB'!C34),'FOB'!C34,0)))*IF(ISNUMBER('FOB'!C35),'FOB'!C35,0)+(IF(ISNUMBER('FOB'!C46),'FOB'!C46,0)+IF(ISNUMBER('FOB'!C47),'FOB'!C47,0)+IF(ISNUMBER('FOB'!C48),'FOB'!C48,0)+IF(ISNUMBER('FOB'!C49),'FOB'!C49,0)+IF(ISNUMBER('FOB'!C50),'FOB'!C50,0)+IF(ISNUMBER('FOB'!C51),'FOB'!C51,0))-IF(LEFT('FOB'!C36,1)="是",(IF(ISNUMBER(IF(ISNUMBER('FOB'!C11),'FOB'!C11*(1+-0.03),"")),(IF(AND(ISNUMBER('FOB'!C6),ISNUMBER('FOB'!C7)),'FOB'!C6*'FOB'!C7,0)+IF('FOB'!C9=TRUE,0,IF(ISNUMBER('FOB'!C19),'FOB'!C19,0))+IF(ISNUMBER('FOB'!C13),IF('FOB'!C22,0,'FOB'!C13),0)+IF(ISNUMBER('FOB'!C12),IF('FOB'!C22,0,'FOB'!C12),0)+IF('FOB'!C20,0,IF(ISNUMBER('FOB'!C14),'FOB'!C14*'FOB'!C7,0))+IF('FOB'!C18,0,IF(ISNUMBER('FOB'!C17),'FOB'!C17,IF(ISNUMBER('FOB'!C16),(IF(AND(ISNUMBER('FOB'!C6),ISNUMBER('FOB'!C7)),'FOB'!C6*'FOB'!C7,0)+IF('FOB'!C20,0,IF(ISNUMBER('FOB'!C14),'FOB'!C14*'FOB'!C7,0)))*'FOB'!C16/100*1.1,(IF(AND(ISNUMBER('FOB'!C6),ISNUMBER('FOB'!C7)),'FOB'!C6*'FOB'!C7,0)+IF('FOB'!C9=TRUE,0,IF(ISNUMBER('FOB'!C19),'FOB'!C19,0))+IF(ISNUMBER('FOB'!C13),IF('FOB'!C22,0,'FOB'!C13),0)+IF(ISNUMBER('FOB'!C12),IF('FOB'!C22,0,'FOB'!C12),0)+IF('FOB'!C20,0,IF(ISNUMBER('FOB'!C14),'FOB'!C14*'FOB'!C7,0)))*0.003/0.997))))*IF(ISNUMBER('FOB'!C11),'FOB'!C11*(1+-0.03),""),0)+IF(ISNUMBER(IF(ISNUMBER('FOB'!C11),'FOB'!C11*(1+-0.03),"")),(IF(AND(ISNUMBER('FOB'!C6),ISNUMBER('FOB'!C7)),'FOB'!C6*'FOB'!C7,0)+IF('FOB'!C9=TRUE,0,IF(ISNUMBER('FOB'!C19),'FOB'!C19,0))+IF(ISNUMBER('FOB'!C13),IF('FOB'!C22,0,'FOB'!C13),0)+IF(ISNUMBER('FOB'!C12),IF('FOB'!C22,0,'FOB'!C12),0)+IF('FOB'!C20,0,IF(ISNUMBER('FOB'!C14),'FOB'!C14*'FOB'!C7,0))+IF('FOB'!C18,0,IF(ISNUMBER('FOB'!C17),'FOB'!C17,IF(ISNUMBER('FOB'!C16),(IF(AND(ISNUMBER('FOB'!C6),ISNUMBER('FOB'!C7)),'FOB'!C6*'FOB'!C7,0)+IF('FOB'!C20,0,IF(ISNUMBER('FOB'!C14),'FOB'!C14*'FOB'!C7,0)))*'FOB'!C16/100*1.1,(IF(AND(ISNUMBER('FOB'!C6),ISNUMBER('FOB'!C7)),'FOB'!C6*'FOB'!C7,0)+IF('FOB'!C9=TRUE,0,IF(ISNUMBER('FOB'!C19),'FOB'!C19,0))+IF(ISNUMBER('FOB'!C13),IF('FOB'!C22,0,'FOB'!C13),0)+IF(ISNUMBER('FOB'!C12),IF('FOB'!C22,0,'FOB'!C12),0)+IF('FOB'!C20,0,IF(ISNUMBER('FOB'!C14),'FOB'!C14*'FOB'!C7,0)))*0.003/0.997))))*IF(ISNUMBER('FOB'!C11),'FOB'!C11*(1+-0.03),""),0)*IF(ISNUMBER('FOB'!C33),'FOB'!C33,0)*(1+IF(ISNUMBER('FOB'!C34),'FOB'!C34,0)))*IF(ISNUMBER('FOB'!C35),'FOB'!C35,0),0))/('FOB'!C7),"") | E9: =IF(AND(ISNUMBER(D9),ISNUMBER(D4)),D9-D4,"") | F9: =IF(AND(ISNUMBER(E9),ISNUMBER(D4)),E9/D4,"") | G9: 市场汇率影响现金，海关计征汇率影响税费基数
B10: 汇率 +0% | C10: 0 | D10: =IF(AND(ISNUMBER('FOB'!C6),ISNUMBER('FOB'!C7),ISNUMBER('FOB'!C10*(1+0.0)),ISNUMBER(IF(ISNUMBER('FOB'!C11),'FOB'!C11*(1+0.0),"")),ISNUMBER('FOB'!C33)),((IF(AND(ISNUMBER('FOB'!C6),ISNUMBER('FOB'!C7)),'FOB'!C6*'FOB'!C7,0)+IF('FOB'!C9=TRUE,0,IF(ISNUMBER('FOB'!C19),'FOB'!C19,0))+IF(ISNUMBER('FOB'!C13),IF('FOB'!C22,0,'FOB'!C13),0)+IF(ISNUMBER('FOB'!C12),IF('FOB'!C22,0,'FOB'!C12),0)+IF('FOB'!C20,0,IF(ISNUMBER('FOB'!C14),'FOB'!C14*'FOB'!C7,0))+IF('FOB'!C18,0,IF(ISNUMBER('FOB'!C17),'FOB'!C17,IF(ISNUMBER('FOB'!C16),(IF(AND(ISNUMBER('FOB'!C6),ISNUMBER('FOB'!C7)),'FOB'!C6*'FOB'!C7,0)+IF('FOB'!C20,0,IF(ISNUMBER('FOB'!C14),'FOB'!C14*'FOB'!C7,0)))*'FOB'!C16/100*1.1,(IF(AND(ISNUMBER('FOB'!C6),ISNUMBER('FOB'!C7)),'FOB'!C6*'FOB'!C7,0)+IF('FOB'!C9=TRUE,0,IF(ISNUMBER('FOB'!C19),'FOB'!C19,0))+IF(ISNUMBER('FOB'!C13),IF('FOB'!C22,0,'FOB'!C13),0)+IF(ISNUMBER('FOB'!C12),IF('FOB'!C22,0,'FOB'!C12),0)+IF('FOB'!C20,0,IF(ISNUMBER('FOB'!C14),'FOB'!C14*'FOB'!C7,0)))*0.003/0.997))))*IF(ISNUMBER('FOB'!C10*(1+0.0)),'FOB'!C10*(1+0.0),0)+IF(ISNUMBER(IF(ISNUMBER('FOB'!C11),'FOB'!C11*(1+0.0),"")),(IF(AND(ISNUMBER('FOB'!C6),ISNUMBER('FOB'!C7)),'FOB'!C6*'FOB'!C7,0)+IF('FOB'!C9=TRUE,0,IF(ISNUMBER('FOB'!C19),'FOB'!C19,0))+IF(ISNUMBER('FOB'!C13),IF('FOB'!C22,0,'FOB'!C13),0)+IF(ISNUMBER('FOB'!C12),IF('FOB'!C22,0,'FOB'!C12),0)+IF('FOB'!C20,0,IF(ISNUMBER('FOB'!C14),'FOB'!C14*'FOB'!C7,0))+IF('FOB'!C18,0,IF(ISNUMBER('FOB'!C17),'FOB'!C17,IF(ISNUMBER('FOB'!C16),(IF(AND(ISNUMBER('FOB'!C6),ISNUMBER('FOB'!C7)),'FOB'!C6*'FOB'!C7,0)+IF('FOB'!C20,0,IF(ISNUMBER('FOB'!C14),'FOB'!C14*'FOB'!C7,0)))*'FOB'!C16/100*1.1,(IF(AND(ISNUMBER('FOB'!C6),ISNUMBER('FOB'!C7)),'FOB'!C6*'FOB'!C7,0)+IF('FOB'!C9=TRUE,0,IF(ISNUMBER('FOB'!C19),'FOB'!C19,0))+IF(ISNUMBER('FOB'!C13),IF('FOB'!C22,0,'FOB'!C13),0)+IF(ISNUMBER('FOB'!C12),IF('FOB'!C22,0,'FOB'!C12),0)+IF('FOB'!C20,0,IF(ISNUMBER('FOB'!C14),'FOB'!C14*'FOB'!C7,0)))*0.003/0.997))))*IF(ISNUMBER('FOB'!C11),'FOB'!C11*(1+0.0),""),0)*IF(ISNUMBER('FOB'!C33),'FOB'!C33,0)*(1+IF(ISNUMBER('FOB'!C34),'FOB'!C34,0))+(IF(ISNUMBER(IF(ISNUMBER('FOB'!C11),'FOB'!C11*(1+0.0),"")),(IF(AND(ISNUMBER('FOB'!C6),ISNUMBER('FOB'!C7)),'FOB'!C6*'FOB'!C7,0)+IF('FOB'!C9=TRUE,0,IF(ISNUMBER('FOB'!C19),'FOB'!C19,0))+IF(ISNUMBER('FOB'!C13),IF('FOB'!C22,0,'FOB'!C13),0)+IF(ISNUMBER('FOB'!C12),IF('FOB'!C22,0,'FOB'!C12),0)+IF('FOB'!C20,0,IF(ISNUMBER('FOB'!C14),'FOB'!C14*'FOB'!C7,0))+IF('FOB'!C18,0,IF(ISNUMBER('FOB'!C17),'FOB'!C17,IF(ISNUMBER('FOB'!C16),(IF(AND(ISNUMBER('FOB'!C6),ISNUMBER('FOB'!C7)),'FOB'!C6*'FOB'!C7,0)+IF('FOB'!C20,0,IF(ISNUMBER('FOB'!C14),'FOB'!C14*'FOB'!C7,0)))*'FOB'!C16/100*1.1,(IF(AND(ISNUMBER('FOB'!C6),ISNUMBER('FOB'!C7)),'FOB'!C6*'FOB'!C7,0)+IF('FOB'!C9=TRUE,0,IF(ISNUMBER('FOB'!C19),'FOB'!C19,0))+IF(ISNUMBER('FOB'!C13),IF('FOB'!C22,0,'FOB'!C13),0)+IF(ISNUMBER('FOB'!C12),IF('FOB'!C22,0,'FOB'!C12),0)+IF('FOB'!C20,0,IF(ISNUMBER('FOB'!C14),'FOB'!C14*'FOB'!C7,0)))*0.003/0.997))))*IF(ISNUMBER('FOB'!C11),'FOB'!C11*(1+0.0),""),0)+IF(ISNUMBER(IF(ISNUMBER('FOB'!C11),'FOB'!C11*(1+0.0),"")),(IF(AND(ISNUMBER('FOB'!C6),ISNUMBER('FOB'!C7)),'FOB'!C6*'FOB'!C7,0)+IF('FOB'!C9=TRUE,0,IF(ISNUMBER('FOB'!C19),'FOB'!C19,0))+IF(ISNUMBER('FOB'!C13),IF('FOB'!C22,0,'FOB'!C13),0)+IF(ISNUMBER('FOB'!C12),IF('FOB'!C22,0,'FOB'!C12),0)+IF('FOB'!C20,0,IF(ISNUMBER('FOB'!C14),'FOB'!C14*'FOB'!C7,0))+IF('FOB'!C18,0,IF(ISNUMBER('FOB'!C17),'FOB'!C17,IF(ISNUMBER('FOB'!C16),(IF(AND(ISNUMBER('FOB'!C6),ISNUMBER('FOB'!C7)),'FOB'!C6*'FOB'!C7,0)+IF('FOB'!C20,0,IF(ISNUMBER('FOB'!C14),'FOB'!C14*'FOB'!C7,0)))*'FOB'!C16/100*1.1,(IF(AND(ISNUMBER('FOB'!C6),ISNUMBER('FOB'!C7)),'FOB'!C6*'FOB'!C7,0)+IF('FOB'!C9=TRUE,0,IF(ISNUMBER('FOB'!C19),'FOB'!C19,0))+IF(ISNUMBER('FOB'!C13),IF('FOB'!C22,0,'FOB'!C13),0)+IF(ISNUMBER('FOB'!C12),IF('FOB'!C22,0,'FOB'!C12),0)+IF('FOB'!C20,0,IF(ISNUMBER('FOB'!C14),'FOB'!C14*'FOB'!C7,0)))*0.003/0.997))))*IF(ISNUMBER('FOB'!C11),'FOB'!C11*(1+0.0),""),0)*IF(ISNUMBER('FOB'!C33),'FOB'!C33,0)*(1+IF(ISNUMBER('FOB'!C34),'FOB'!C34,0)))*IF(ISNUMBER('FOB'!C35),'FOB'!C35,0)+(IF(ISNUMBER('FOB'!C46),'FOB'!C46,0)+IF(ISNUMBER('FOB'!C47),'FOB'!C47,0)+IF(ISNUMBER('FOB'!C48),'FOB'!C48,0)+IF(ISNUMBER('FOB'!C49),'FOB'!C49,0)+IF(ISNUMBER('FOB'!C50),'FOB'!C50,0)+IF(ISNUMBER('FOB'!C51),'FOB'!C51,0))-IF(LEFT('FOB'!C36,1)="是",(IF(ISNUMBER(IF(ISNUMBER('FOB'!C11),'FOB'!C11*(1+0.0),"")),(IF(AND(ISNUMBER('FOB'!C6),ISNUMBER('FOB'!C7)),'FOB'!C6*'FOB'!C7,0)+IF('FOB'!C9=TRUE,0,IF(ISNUMBER('FOB'!C19),'FOB'!C19,0))+IF(ISNUMBER('FOB'!C13),IF('FOB'!C22,0,'FOB'!C13),0)+IF(ISNUMBER('FOB'!C12),IF('FOB'!C22,0,'FOB'!C12),0)+IF('FOB'!C20,0,IF(ISNUMBER('FOB'!C14),'FOB'!C14*'FOB'!C7,0))+IF('FOB'!C18,0,IF(ISNUMBER('FOB'!C17),'FOB'!C17,IF(ISNUMBER('FOB'!C16),(IF(AND(ISNUMBER('FOB'!C6),ISNUMBER('FOB'!C7)),'FOB'!C6*'FOB'!C7,0)+IF('FOB'!C20,0,IF(ISNUMBER('FOB'!C14),'FOB'!C14*'FOB'!C7,0)))*'FOB'!C16/100*1.1,(IF(AND(ISNUMBER('FOB'!C6),ISNUMBER('FOB'!C7)),'FOB'!C6*'FOB'!C7,0)+IF('FOB'!C9=TRUE,0,IF(ISNUMBER('FOB'!C19),'FOB'!C19,0))+IF(ISNUMBER('FOB'!C13),IF('FOB'!C22,0,'FOB'!C13),0)+IF(ISNUMBER('FOB'!C12),IF('FOB'!C22,0,'FOB'!C12),0)+IF('FOB'!C20,0,IF(ISNUMBER('FOB'!C14),'FOB'!C14*'FOB'!C7,0)))*0.003/0.997))))*IF(ISNUMBER('FOB'!C11),'FOB'!C11*(1+0.0),""),0)+IF(ISNUMBER(IF(ISNUMBER('FOB'!C11),'FOB'!C11*(1+0.0),"")),(IF(AND(ISNUMBER('FOB'!C6),ISNUMBER('FOB'!C7)),'FOB'!C6*'FOB'!C7,0)+IF('FOB'!C9=TRUE,0,IF(ISNUMBER('FOB'!C19),'FOB'!C19,0))+IF(ISNUMBER('FOB'!C13),IF('FOB'!C22,0,'FOB'!C13),0)+IF(ISNUMBER('FOB'!C12),IF('FOB'!C22,0,'FOB'!C12),0)+IF('FOB'!C20,0,IF(ISNUMBER('FOB'!C14),'FOB'!C14*'FOB'!C7,0))+IF('FOB'!C18,0,IF(ISNUMBER('FOB'!C17),'FOB'!C17,IF(ISNUMBER('FOB'!C16),(IF(AND(ISNUMBER('FOB'!C6),ISNUMBER('FOB'!C7)),'FOB'!C6*'FOB'!C7,0)+IF('FOB'!C20,0,IF(ISNUMBER('FOB'!C14),'FOB'!C14*'FOB'!C7,0)))*'FOB'!C16/100*1.1,(IF(AND(ISNUMBER('FOB'!C6),ISNUMBER('FOB'!C7)),'FOB'!C6*'FOB'!C7,0)+IF('FOB'!C9=TRUE,0,IF(ISNUMBER('FOB'!C19),'FOB'!C19,0))+IF(ISNUMBER('FOB'!C13),IF('FOB'!C22,0,'FOB'!C13),0)+IF(ISNUMBER('FOB'!C12),IF('FOB'!C22,0,'FOB'!C12),0)+IF('FOB'!C20,0,IF(ISNUMBER('FOB'!C14),'FOB'!C14*'FOB'!C7,0)))*0.003/0.997))))*IF(ISNUMBER('FOB'!C11),'FOB'!C11*(1+0.0),""),0)*IF(ISNUMBER('FOB'!C33),'FOB'!C33,0)*(1+IF(ISNUMBER('FOB'!C34),'FOB'!C34,0)))*IF(ISNUMBER('FOB'!C35),'FOB'!C35,0),0))/('FOB'!C7),"") | E10: =IF(AND(ISNUMBER(D10),ISNUMBER(D4)),D10-D4,"") | F10: =IF(AND(ISNUMBER(E10),ISNUMBER(D4)),E10/D4,"")
B11: 汇率 +3% | C11: 0.03 | D11: =IF(AND(ISNUMBER('FOB'!C6),ISNUMBER('FOB'!C7),ISNUMBER('FOB'!C10*(1+0.03)),ISNUMBER(IF(ISNUMBER('FOB'!C11),'FOB'!C11*(1+0.03),"")),ISNUMBER('FOB'!C33)),((IF(AND(ISNUMBER('FOB'!C6),ISNUMBER('FOB'!C7)),'FOB'!C6*'FOB'!C7,0)+IF('FOB'!C9=TRUE,0,IF(ISNUMBER('FOB'!C19),'FOB'!C19,0))+IF(ISNUMBER('FOB'!C13),IF('FOB'!C22,0,'FOB'!C13),0)+IF(ISNUMBER('FOB'!C12),IF('FOB'!C22,0,'FOB'!C12),0)+IF('FOB'!C20,0,IF(ISNUMBER('FOB'!C14),'FOB'!C14*'FOB'!C7,0))+IF('FOB'!C18,0,IF(ISNUMBER('FOB'!C17),'FOB'!C17,IF(ISNUMBER('FOB'!C16),(IF(AND(ISNUMBER('FOB'!C6),ISNUMBER('FOB'!C7)),'FOB'!C6*'FOB'!C7,0)+IF('FOB'!C20,0,IF(ISNUMBER('FOB'!C14),'FOB'!C14*'FOB'!C7,0)))*'FOB'!C16/100*1.1,(IF(AND(ISNUMBER('FOB'!C6),ISNUMBER('FOB'!C7)),'FOB'!C6*'FOB'!C7,0)+IF('FOB'!C9=TRUE,0,IF(ISNUMBER('FOB'!C19),'FOB'!C19,0))+IF(ISNUMBER('FOB'!C13),IF('FOB'!C22,0,'FOB'!C13),0)+IF(ISNUMBER('FOB'!C12),IF('FOB'!C22,0,'FOB'!C12),0)+IF('FOB'!C20,0,IF(ISNUMBER('FOB'!C14),'FOB'!C14*'FOB'!C7,0)))*0.003/0.997))))*IF(ISNUMBER('FOB'!C10*(1+0.03)),'FOB'!C10*(1+0.03),0)+IF(ISNUMBER(IF(ISNUMBER('FOB'!C11),'FOB'!C11*(1+0.03),"")),(IF(AND(ISNUMBER('FOB'!C6),ISNUMBER('FOB'!C7)),'FOB'!C6*'FOB'!C7,0)+IF('FOB'!C9=TRUE,0,IF(ISNUMBER('FOB'!C19),'FOB'!C19,0))+IF(ISNUMBER('FOB'!C13),IF('FOB'!C22,0,'FOB'!C13),0)+IF(ISNUMBER('FOB'!C12),IF('FOB'!C22,0,'FOB'!C12),0)+IF('FOB'!C20,0,IF(ISNUMBER('FOB'!C14),'FOB'!C14*'FOB'!C7,0))+IF('FOB'!C18,0,IF(ISNUMBER('FOB'!C17),'FOB'!C17,IF(ISNUMBER('FOB'!C16),(IF(AND(ISNUMBER('FOB'!C6),ISNUMBER('FOB'!C7)),'FOB'!C6*'FOB'!C7,0)+IF('FOB'!C20,0,IF(ISNUMBER('FOB'!C14),'FOB'!C14*'FOB'!C7,0)))*'FOB'!C16/100*1.1,(IF(AND(ISNUMBER('FOB'!C6),ISNUMBER('FOB'!C7)),'FOB'!C6*'FOB'!C7,0)+IF('FOB'!C9=TRUE,0,IF(ISNUMBER('FOB'!C19),'FOB'!C19,0))+IF(ISNUMBER('FOB'!C13),IF('FOB'!C22,0,'FOB'!C13),0)+IF(ISNUMBER('FOB'!C12),IF('FOB'!C22,0,'FOB'!C12),0)+IF('FOB'!C20,0,IF(ISNUMBER('FOB'!C14),'FOB'!C14*'FOB'!C7,0)))*0.003/0.997))))*IF(ISNUMBER('FOB'!C11),'FOB'!C11*(1+0.03),""),0)*IF(ISNUMBER('FOB'!C33),'FOB'!C33,0)*(1+IF(ISNUMBER('FOB'!C34),'FOB'!C34,0))+(IF(ISNUMBER(IF(ISNUMBER('FOB'!C11),'FOB'!C11*(1+0.03),"")),(IF(AND(ISNUMBER('FOB'!C6),ISNUMBER('FOB'!C7)),'FOB'!C6*'FOB'!C7,0)+IF('FOB'!C9=TRUE,0,IF(ISNUMBER('FOB'!C19),'FOB'!C19,0))+IF(ISNUMBER('FOB'!C13),IF('FOB'!C22,0,'FOB'!C13),0)+IF(ISNUMBER('FOB'!C12),IF('FOB'!C22,0,'FOB'!C12),0)+IF('FOB'!C20,0,IF(ISNUMBER('FOB'!C14),'FOB'!C14*'FOB'!C7,0))+IF('FOB'!C18,0,IF(ISNUMBER('FOB'!C17),'FOB'!C17,IF(ISNUMBER('FOB'!C16),(IF(AND(ISNUMBER('FOB'!C6),ISNUMBER('FOB'!C7)),'FOB'!C6*'FOB'!C7,0)+IF('FOB'!C20,0,IF(ISNUMBER('FOB'!C14),'FOB'!C14*'FOB'!C7,0)))*'FOB'!C16/100*1.1,(IF(AND(ISNUMBER('FOB'!C6),ISNUMBER('FOB'!C7)),'FOB'!C6*'FOB'!C7,0)+IF('FOB'!C9=TRUE,0,IF(ISNUMBER('FOB'!C19),'FOB'!C19,0))+IF(ISNUMBER('FOB'!C13),IF('FOB'!C22,0,'FOB'!C13),0)+IF(ISNUMBER('FOB'!C12),IF('FOB'!C22,0,'FOB'!C12),0)+IF('FOB'!C20,0,IF(ISNUMBER('FOB'!C14),'FOB'!C14*'FOB'!C7,0)))*0.003/0.997))))*IF(ISNUMBER('FOB'!C11),'FOB'!C11*(1+0.03),""),0)+IF(ISNUMBER(IF(ISNUMBER('FOB'!C11),'FOB'!C11*(1+0.03),"")),(IF(AND(ISNUMBER('FOB'!C6),ISNUMBER('FOB'!C7)),'FOB'!C6*'FOB'!C7,0)+IF('FOB'!C9=TRUE,0,IF(ISNUMBER('FOB'!C19),'FOB'!C19,0))+IF(ISNUMBER('FOB'!C13),IF('FOB'!C22,0,'FOB'!C13),0)+IF(ISNUMBER('FOB'!C12),IF('FOB'!C22,0,'FOB'!C12),0)+IF('FOB'!C20,0,IF(ISNUMBER('FOB'!C14),'FOB'!C14*'FOB'!C7,0))+IF('FOB'!C18,0,IF(ISNUMBER('FOB'!C17),'FOB'!C17,IF(ISNUMBER('FOB'!C16),(IF(AND(ISNUMBER('FOB'!C6),ISNUMBER('FOB'!C7)),'FOB'!C6*'FOB'!C7,0)+IF('FOB'!C20,0,IF(ISNUMBER('FOB'!C14),'FOB'!C14*'FOB'!C7,0)))*'FOB'!C16/100*1.1,(IF(AND(ISNUMBER('FOB'!C6),ISNUMBER('FOB'!C7)),'FOB'!C6*'FOB'!C7,0)+IF('FOB'!C9=TRUE,0,IF(ISNUMBER('FOB'!C19),'FOB'!C19,0))+IF(ISNUMBER('FOB'!C13),IF('FOB'!C22,0,'FOB'!C13),0)+IF(ISNUMBER('FOB'!C12),IF('FOB'!C22,0,'FOB'!C12),0)+IF('FOB'!C20,0,IF(ISNUMBER('FOB'!C14),'FOB'!C14*'FOB'!C7,0)))*0.003/0.997))))*IF(ISNUMBER('FOB'!C11),'FOB'!C11*(1+0.03),""),0)*IF(ISNUMBER('FOB'!C33),'FOB'!C33,0)*(1+IF(ISNUMBER('FOB'!C34),'FOB'!C34,0)))*IF(ISNUMBER('FOB'!C35),'FOB'!C35,0)+(IF(ISNUMBER('FOB'!C46),'FOB'!C46,0)+IF(ISNUMBER('FOB'!C47),'FOB'!C47,0)+IF(ISNUMBER('FOB'!C48),'FOB'!C48,0)+IF(ISNUMBER('FOB'!C49),'FOB'!C49,0)+IF(ISNUMBER('FOB'!C50),'FOB'!C50,0)+IF(ISNUMBER('FOB'!C51),'FOB'!C51,0))-IF(LEFT('FOB'!C36,1)="是",(IF(ISNUMBER(IF(ISNUMBER('FOB'!C11),'FOB'!C11*(1+0.03),"")),(IF(AND(ISNUMBER('FOB'!C6),ISNUMBER('FOB'!C7)),'FOB'!C6*'FOB'!C7,0)+IF('FOB'!C9=TRUE,0,IF(ISNUMBER('FOB'!C19),'FOB'!C19,0))+IF(ISNUMBER('FOB'!C13),IF('FOB'!C22,0,'FOB'!C13),0)+IF(ISNUMBER('FOB'!C12),IF('FOB'!C22,0,'FOB'!C12),0)+IF('FOB'!C20,0,IF(ISNUMBER('FOB'!C14),'FOB'!C14*'FOB'!C7,0))+IF('FOB'!C18,0,IF(ISNUMBER('FOB'!C17),'FOB'!C17,IF(ISNUMBER('FOB'!C16),(IF(AND(ISNUMBER('FOB'!C6),ISNUMBER('FOB'!C7)),'FOB'!C6*'FOB'!C7,0)+IF('FOB'!C20,0,IF(ISNUMBER('FOB'!C14),'FOB'!C14*'FOB'!C7,0)))*'FOB'!C16/100*1.1,(IF(AND(ISNUMBER('FOB'!C6),ISNUMBER('FOB'!C7)),'FOB'!C6*'FOB'!C7,0)+IF('FOB'!C9=TRUE,0,IF(ISNUMBER('FOB'!C19),'FOB'!C19,0))+IF(ISNUMBER('FOB'!C13),IF('FOB'!C22,0,'FOB'!C13),0)+IF(ISNUMBER('FOB'!C12),IF('FOB'!C22,0,'FOB'!C12),0)+IF('FOB'!C20,0,IF(ISNUMBER('FOB'!C14),'FOB'!C14*'FOB'!C7,0)))*0.003/0.997))))*IF(ISNUMBER('FOB'!C11),'FOB'!C11*(1+0.03),""),0)+IF(ISNUMBER(IF(ISNUMBER('FOB'!C11),'FOB'!C11*(1+0.03),"")),(IF(AND(ISNUMBER('FOB'!C6),ISNUMBER('FOB'!C7)),'FOB'!C6*'FOB'!C7,0)+IF('FOB'!C9=TRUE,0,IF(ISNUMBER('FOB'!C19),'FOB'!C19,0))+IF(ISNUMBER('FOB'!C13),IF('FOB'!C22,0,'FOB'!C13),0)+IF(ISNUMBER('FOB'!C12),IF('FOB'!C22,0,'FOB'!C12),0)+IF('FOB'!C20,0,IF(ISNUMBER('FOB'!C14),'FOB'!C14*'FOB'!C7,0))+IF('FOB'!C18,0,IF(ISNUMBER('FOB'!C17),'FOB'!C17,IF(ISNUMBER('FOB'!C16),(IF(AND(ISNUMBER('FOB'!C6),ISNUMBER('FOB'!C7)),'FOB'!C6*'FOB'!C7,0)+IF('FOB'!C20,0,IF(ISNUMBER('FOB'!C14),'FOB'!C14*'FOB'!C7,0)))*'FOB'!C16/100*1.1,(IF(AND(ISNUMBER('FOB'!C6),ISNUMBER('FOB'!C7)),'FOB'!C6*'FOB'!C7,0)+IF('FOB'!C9=TRUE,0,IF(ISNUMBER('FOB'!C19),'FOB'!C19,0))+IF(ISNUMBER('FOB'!C13),IF('FOB'!C22,0,'FOB'!C13),0)+IF(ISNUMBER('FOB'!C12),IF('FOB'!C22,0,'FOB'!C12),0)+IF('FOB'!C20,0,IF(ISNUMBER('FOB'!C14),'FOB'!C14*'FOB'!C7,0)))*0.003/0.997))))*IF(ISNUMBER('FOB'!C11),'FOB'!C11*(1+0.03),""),0)*IF(ISNUMBER('FOB'!C33),'FOB'!C33,0)*(1+IF(ISNUMBER('FOB'!C34),'FOB'!C34,0)))*IF(ISNUMBER('FOB'!C35),'FOB'!C35,0),0))/('FOB'!C7),"") | E11: =IF(AND(ISNUMBER(D11),ISNUMBER(D4)),D11-D4,"") | F11: =IF(AND(ISNUMBER(E11),ISNUMBER(D4)),E11/D4,"")
B12: ② 海运费变化（运费会被关税放大）
B13: 情景 | C13: 情景参数 | D13: 到厂成本 元/吨 | E13: Δ 元/吨 | F13: Δ % | G13: 说明
B15: 海运费 -20% | C15: 'FOB'!C14*(1+-0.2) | D15: =IF(AND(ISNUMBER('FOB'!C6),ISNUMBER('FOB'!C7),ISNUMBER('FOB'!C10),ISNUMBER('FOB'!C11),ISNUMBER('FOB'!C33)),((IF(AND(ISNUMBER('FOB'!C6),ISNUMBER('FOB'!C7)),'FOB'!C6*'FOB'!C7,0)+IF('FOB'!C9=TRUE,0,IF(ISNUMBER('FOB'!C19),'FOB'!C19,0))+IF(ISNUMBER('FOB'!C13),IF('FOB'!C22,0,'FOB'!C13),0)+IF(ISNUMBER('FOB'!C12),IF('FOB'!C22,0,'FOB'!C12),0)+IF('FOB'!C20,0,IF(ISNUMBER('FOB'!C14*(1+-0.2)),'FOB'!C14*(1+-0.2)*'FOB'!C7,0))+IF('FOB'!C18,0,IF(ISNUMBER('FOB'!C17),'FOB'!C17,IF(ISNUMBER('FOB'!C16),(IF(AND(ISNUMBER('FOB'!C6),ISNUMBER('FOB'!C7)),'FOB'!C6*'FOB'!C7,0)+IF('FOB'!C20,0,IF(ISNUMBER('FOB'!C14*(1+-0.2)),'FOB'!C14*(1+-0.2)*'FOB'!C7,0)))*'FOB'!C16/100*1.1,(IF(AND(ISNUMBER('FOB'!C6),ISNUMBER('FOB'!C7)),'FOB'!C6*'FOB'!C7,0)+IF('FOB'!C9=TRUE,0,IF(ISNUMBER('FOB'!C19),'FOB'!C19,0))+IF(ISNUMBER('FOB'!C13),IF('FOB'!C22,0,'FOB'!C13),0)+IF(ISNUMBER('FOB'!C12),IF('FOB'!C22,0,'FOB'!C12),0)+IF('FOB'!C20,0,IF(ISNUMBER('FOB'!C14*(1+-0.2)),'FOB'!C14*(1+-0.2)*'FOB'!C7,0)))*0.003/0.997))))*IF(ISNUMBER('FOB'!C10),'FOB'!C10,0)+IF(ISNUMBER('FOB'!C11),(IF(AND(ISNUMBER('FOB'!C6),ISNUMBER('FOB'!C7)),'FOB'!C6*'FOB'!C7,0)+IF('FOB'!C9=TRUE,0,IF(ISNUMBER('FOB'!C19),'FOB'!C19,0))+IF(ISNUMBER('FOB'!C13),IF('FOB'!C22,0,'FOB'!C13),0)+IF(ISNUMBER('FOB'!C12),IF('FOB'!C22,0,'FOB'!C12),0)+IF('FOB'!C20,0,IF(ISNUMBER('FOB'!C14*(1+-0.2)),'FOB'!C14*(1+-0.2)*'FOB'!C7,0))+IF('FOB'!C18,0,IF(ISNUMBER('FOB'!C17),'FOB'!C17,IF(ISNUMBER('FOB'!C16),(IF(AND(ISNUMBER('FOB'!C6),ISNUMBER('FOB'!C7)),'FOB'!C6*'FOB'!C7,0)+IF('FOB'!C20,0,IF(ISNUMBER('FOB'!C14*(1+-0.2)),'FOB'!C14*(1+-0.2)*'FOB'!C7,0)))*'FOB'!C16/100*1.1,(IF(AND(ISNUMBER('FOB'!C6),ISNUMBER('FOB'!C7)),'FOB'!C6*'FOB'!C7,0)+IF('FOB'!C9=TRUE,0,IF(ISNUMBER('FOB'!C19),'FOB'!C19,0))+IF(ISNUMBER('FOB'!C13),IF('FOB'!C22,0,'FOB'!C13),0)+IF(ISNUMBER('FOB'!C12),IF('FOB'!C22,0,'FOB'!C12),0)+IF('FOB'!C20,0,IF(ISNUMBER('FOB'!C14*(1+-0.2)),'FOB'!C14*(1+-0.2)*'FOB'!C7,0)))*0.003/0.997))))*'FOB'!C11,0)*IF(ISNUMBER('FOB'!C33),'FOB'!C33,0)*(1+IF(ISNUMBER('FOB'!C34),'FOB'!C34,0))+(IF(ISNUMBER('FOB'!C11),(IF(AND(ISNUMBER('FOB'!C6),ISNUMBER('FOB'!C7)),'FOB'!C6*'FOB'!C7,0)+IF('FOB'!C9=TRUE,0,IF(ISNUMBER('FOB'!C19),'FOB'!C19,0))+IF(ISNUMBER('FOB'!C13),IF('FOB'!C22,0,'FOB'!C13),0)+IF(ISNUMBER('FOB'!C12),IF('FOB'!C22,0,'FOB'!C12),0)+IF('FOB'!C20,0,IF(ISNUMBER('FOB'!C14*(1+-0.2)),'FOB'!C14*(1+-0.2)*'FOB'!C7,0))+IF('FOB'!C18,0,IF(ISNUMBER('FOB'!C17),'FOB'!C17,IF(ISNUMBER('FOB'!C16),(IF(AND(ISNUMBER('FOB'!C6),ISNUMBER('FOB'!C7)),'FOB'!C6*'FOB'!C7,0)+IF('FOB'!C20,0,IF(ISNUMBER('FOB'!C14*(1+-0.2)),'FOB'!C14*(1+-0.2)*'FOB'!C7,0)))*'FOB'!C16/100*1.1,(IF(AND(ISNUMBER('FOB'!C6),ISNUMBER('FOB'!C7)),'FOB'!C6*'FOB'!C7,0)+IF('FOB'!C9=TRUE,0,IF(ISNUMBER('FOB'!C19),'FOB'!C19,0))+IF(ISNUMBER('FOB'!C13),IF('FOB'!C22,0,'FOB'!C13),0)+IF(ISNUMBER('FOB'!C12),IF('FOB'!C22,0,'FOB'!C12),0)+IF('FOB'!C20,0,IF(ISNUMBER('FOB'!C14*(1+-0.2)),'FOB'!C14*(1+-0.2)*'FOB'!C7,0)))*0.003/0.997))))*'FOB'!C11,0)+IF(ISNUMBER('FOB'!C11),(IF(AND(ISNUMBER('FOB'!C6),ISNUMBER('FOB'!C7)),'FOB'!C6*'FOB'!C7,0)+IF('FOB'!C9=TRUE,0,IF(ISNUMBER('FOB'!C19),'FOB'!C19,0))+IF(ISNUMBER('FOB'!C13),IF('FOB'!C22,0,'FOB'!C13),0)+IF(ISNUMBER('FOB'!C12),IF('FOB'!C22,0,'FOB'!C12),0)+IF('FOB'!C20,0,IF(ISNUMBER('FOB'!C14*(1+-0.2)),'FOB'!C14*(1+-0.2)*'FOB'!C7,0))+IF('FOB'!C18,0,IF(ISNUMBER('FOB'!C17),'FOB'!C17,IF(ISNUMBER('FOB'!C16),(IF(AND(ISNUMBER('FOB'!C6),ISNUMBER('FOB'!C7)),'FOB'!C6*'FOB'!C7,0)+IF('FOB'!C20,0,IF(ISNUMBER('FOB'!C14*(1+-0.2)),'FOB'!C14*(1+-0.2)*'FOB'!C7,0)))*'FOB'!C16/100*1.1,(IF(AND(ISNUMBER('FOB'!C6),ISNUMBER('FOB'!C7)),'FOB'!C6*'FOB'!C7,0)+IF('FOB'!C9=TRUE,0,IF(ISNUMBER('FOB'!C19),'FOB'!C19,0))+IF(ISNUMBER('FOB'!C13),IF('FOB'!C22,0,'FOB'!C13),0)+IF(ISNUMBER('FOB'!C12),IF('FOB'!C22,0,'FOB'!C12),0)+IF('FOB'!C20,0,IF(ISNUMBER('FOB'!C14*(1+-0.2)),'FOB'!C14*(1+-0.2)*'FOB'!C7,0)))*0.003/0.997))))*'FOB'!C11,0)*IF(ISNUMBER('FOB'!C33),'FOB'!C33,0)*(1+IF(ISNUMBER('FOB'!C34),'FOB'!C34,0)))*IF(ISNUMBER('FOB'!C35),'FOB'!C35,0)+(IF(ISNUMBER('FOB'!C46),'FOB'!C46,0)+IF(ISNUMBER('FOB'!C47),'FOB'!C47,0)+IF(ISNUMBER('FOB'!C48),'FOB'!C48,0)+IF(ISNUMBER('FOB'!C49),'FOB'!C49,0)+IF(ISNUMBER('FOB'!C50),'FOB'!C50,0)+IF(ISNUMBER('FOB'!C51),'FOB'!C51,0))-IF(LEFT('FOB'!C36,1)="是",(IF(ISNUMBER('FOB'!C11),(IF(AND(ISNUMBER('FOB'!C6),ISNUMBER('FOB'!C7)),'FOB'!C6*'FOB'!C7,0)+IF('FOB'!C9=TRUE,0,IF(ISNUMBER('FOB'!C19),'FOB'!C19,0))+IF(ISNUMBER('FOB'!C13),IF('FOB'!C22,0,'FOB'!C13),0)+IF(ISNUMBER('FOB'!C12),IF('FOB'!C22,0,'FOB'!C12),0)+IF('FOB'!C20,0,IF(ISNUMBER('FOB'!C14*(1+-0.2)),'FOB'!C14*(1+-0.2)*'FOB'!C7,0))+IF('FOB'!C18,0,IF(ISNUMBER('FOB'!C17),'FOB'!C17,IF(ISNUMBER('FOB'!C16),(IF(AND(ISNUMBER('FOB'!C6),ISNUMBER('FOB'!C7)),'FOB'!C6*'FOB'!C7,0)+IF('FOB'!C20,0,IF(ISNUMBER('FOB'!C14*(1+-0.2)),'FOB'!C14*(1+-0.2)*'FOB'!C7,0)))*'FOB'!C16/100*1.1,(IF(AND(ISNUMBER('FOB'!C6),ISNUMBER('FOB'!C7)),'FOB'!C6*'FOB'!C7,0)+IF('FOB'!C9=TRUE,0,IF(ISNUMBER('FOB'!C19),'FOB'!C19,0))+IF(ISNUMBER('FOB'!C13),IF('FOB'!C22,0,'FOB'!C13),0)+IF(ISNUMBER('FOB'!C12),IF('FOB'!C22,0,'FOB'!C12),0)+IF('FOB'!C20,0,IF(ISNUMBER('FOB'!C14*(1+-0.2)),'FOB'!C14*(1+-0.2)*'FOB'!C7,0)))*0.003/0.997))))*'FOB'!C11,0)+IF(ISNUMBER('FOB'!C11),(IF(AND(ISNUMBER('FOB'!C6),ISNUMBER('FOB'!C7)),'FOB'!C6*'FOB'!C7,0)+IF('FOB'!C9=TRUE,0,IF(ISNUMBER('FOB'!C19),'FOB'!C19,0))+IF(ISNUMBER('FOB'!C13),IF('FOB'!C22,0,'FOB'!C13),0)+IF(ISNUMBER('FOB'!C12),IF('FOB'!C22,0,'FOB'!C12),0)+IF('FOB'!C20,0,IF(ISNUMBER('FOB'!C14*(1+-0.2)),'FOB'!C14*(1+-0.2)*'FOB'!C7,0))+IF('FOB'!C18,0,IF(ISNUMBER('FOB'!C17),'FOB'!C17,IF(ISNUMBER('FOB'!C16),(IF(AND(ISNUMBER('FOB'!C6),ISNUMBER('FOB'!C7)),'FOB'!C6*'FOB'!C7,0)+IF('FOB'!C20,0,IF(ISNUMBER('FOB'!C14*(1+-0.2)),'FOB'!C14*(1+-0.2)*'FOB'!C7,0)))*'FOB'!C16/100*1.1,(IF(AND(ISNUMBER('FOB'!C6),ISNUMBER('FOB'!C7)),'FOB'!C6*'FOB'!C7,0)+IF('FOB'!C9=TRUE,0,IF(ISNUMBER('FOB'!C19),'FOB'!C19,0))+IF(ISNUMBER('FOB'!C13),IF('FOB'!C22,0,'FOB'!C13),0)+IF(ISNUMBER('FOB'!C12),IF('FOB'!C22,0,'FOB'!C12),0)+IF('FOB'!C20,0,IF(ISNUMBER('FOB'!C14*(1+-0.2)),'FOB'!C14*(1+-0.2)*'FOB'!C7,0)))*0.003/0.997))))*'FOB'!C11,0)*IF(ISNUMBER('FOB'!C33),'FOB'!C33,0)*(1+IF(ISNUMBER('FOB'!C34),'FOB'!C34,0)))*IF(ISNUMBER('FOB'!C35),'FOB'!C35,0),0))/('FOB'!C7),"") | E15: =IF(AND(ISNUMBER(D15),ISNUMBER(D4)),D15-D4,"") | F15: =IF(AND(ISNUMBER(E15),ISNUMBER(D4)),E15/D4,"") | G15: 运费 +1 USD/MT ≈ +(1+关税率)×汇率 元/吨
B16: 海运费 -10% | C16: 'FOB'!C14*(1+-0.1) | D16: =IF(AND(ISNUMBER('FOB'!C6),ISNUMBER('FOB'!C7),ISNUMBER('FOB'!C10),ISNUMBER('FOB'!C11),ISNUMBER('FOB'!C33)),((IF(AND(ISNUMBER('FOB'!C6),ISNUMBER('FOB'!C7)),'FOB'!C6*'FOB'!C7,0)+IF('FOB'!C9=TRUE,0,IF(ISNUMBER('FOB'!C19),'FOB'!C19,0))+IF(ISNUMBER('FOB'!C13),IF('FOB'!C22,0,'FOB'!C13),0)+IF(ISNUMBER('FOB'!C12),IF('FOB'!C22,0,'FOB'!C12),0)+IF('FOB'!C20,0,IF(ISNUMBER('FOB'!C14*(1+-0.1)),'FOB'!C14*(1+-0.1)*'FOB'!C7,0))+IF('FOB'!C18,0,IF(ISNUMBER('FOB'!C17),'FOB'!C17,IF(ISNUMBER('FOB'!C16),(IF(AND(ISNUMBER('FOB'!C6),ISNUMBER('FOB'!C7)),'FOB'!C6*'FOB'!C7,0)+IF('FOB'!C20,0,IF(ISNUMBER('FOB'!C14*(1+-0.1)),'FOB'!C14*(1+-0.1)*'FOB'!C7,0)))*'FOB'!C16/100*1.1,(IF(AND(ISNUMBER('FOB'!C6),ISNUMBER('FOB'!C7)),'FOB'!C6*'FOB'!C7,0)+IF('FOB'!C9=TRUE,0,IF(ISNUMBER('FOB'!C19),'FOB'!C19,0))+IF(ISNUMBER('FOB'!C13),IF('FOB'!C22,0,'FOB'!C13),0)+IF(ISNUMBER('FOB'!C12),IF('FOB'!C22,0,'FOB'!C12),0)+IF('FOB'!C20,0,IF(ISNUMBER('FOB'!C14*(1+-0.1)),'FOB'!C14*(1+-0.1)*'FOB'!C7,0)))*0.003/0.997))))*IF(ISNUMBER('FOB'!C10),'FOB'!C10,0)+IF(ISNUMBER('FOB'!C11),(IF(AND(ISNUMBER('FOB'!C6),ISNUMBER('FOB'!C7)),'FOB'!C6*'FOB'!C7,0)+IF('FOB'!C9=TRUE,0,IF(ISNUMBER('FOB'!C19),'FOB'!C19,0))+IF(ISNUMBER('FOB'!C13),IF('FOB'!C22,0,'FOB'!C13),0)+IF(ISNUMBER('FOB'!C12),IF('FOB'!C22,0,'FOB'!C12),0)+IF('FOB'!C20,0,IF(ISNUMBER('FOB'!C14*(1+-0.1)),'FOB'!C14*(1+-0.1)*'FOB'!C7,0))+IF('FOB'!C18,0,IF(ISNUMBER('FOB'!C17),'FOB'!C17,IF(ISNUMBER('FOB'!C16),(IF(AND(ISNUMBER('FOB'!C6),ISNUMBER('FOB'!C7)),'FOB'!C6*'FOB'!C7,0)+IF('FOB'!C20,0,IF(ISNUMBER('FOB'!C14*(1+-0.1)),'FOB'!C14*(1+-0.1)*'FOB'!C7,0)))*'FOB'!C16/100*1.1,(IF(AND(ISNUMBER('FOB'!C6),ISNUMBER('FOB'!C7)),'FOB'!C6*'FOB'!C7,0)+IF('FOB'!C9=TRUE,0,IF(ISNUMBER('FOB'!C19),'FOB'!C19,0))+IF(ISNUMBER('FOB'!C13),IF('FOB'!C22,0,'FOB'!C13),0)+IF(ISNUMBER('FOB'!C12),IF('FOB'!C22,0,'FOB'!C12),0)+IF('FOB'!C20,0,IF(ISNUMBER('FOB'!C14*(1+-0.1)),'FOB'!C14*(1+-0.1)*'FOB'!C7,0)))*0.003/0.997))))*'FOB'!C11,0)*IF(ISNUMBER('FOB'!C33),'FOB'!C33,0)*(1+IF(ISNUMBER('FOB'!C34),'FOB'!C34,0))+(IF(ISNUMBER('FOB'!C11),(IF(AND(ISNUMBER('FOB'!C6),ISNUMBER('FOB'!C7)),'FOB'!C6*'FOB'!C7,0)+IF('FOB'!C9=TRUE,0,IF(ISNUMBER('FOB'!C19),'FOB'!C19,0))+IF(ISNUMBER('FOB'!C13),IF('FOB'!C22,0,'FOB'!C13),0)+IF(ISNUMBER('FOB'!C12),IF('FOB'!C22,0,'FOB'!C12),0)+IF('FOB'!C20,0,IF(ISNUMBER('FOB'!C14*(1+-0.1)),'FOB'!C14*(1+-0.1)*'FOB'!C7,0))+IF('FOB'!C18,0,IF(ISNUMBER('FOB'!C17),'FOB'!C17,IF(ISNUMBER('FOB'!C16),(IF(AND(ISNUMBER('FOB'!C6),ISNUMBER('FOB'!C7)),'FOB'!C6*'FOB'!C7,0)+IF('FOB'!C20,0,IF(ISNUMBER('FOB'!C14*(1+-0.1)),'FOB'!C14*(1+-0.1)*'FOB'!C7,0)))*'FOB'!C16/100*1.1,(IF(AND(ISNUMBER('FOB'!C6),ISNUMBER('FOB'!C7)),'FOB'!C6*'FOB'!C7,0)+IF('FOB'!C9=TRUE,0,IF(ISNUMBER('FOB'!C19),'FOB'!C19,0))+IF(ISNUMBER('FOB'!C13),IF('FOB'!C22,0,'FOB'!C13),0)+IF(ISNUMBER('FOB'!C12),IF('FOB'!C22,0,'FOB'!C12),0)+IF('FOB'!C20,0,IF(ISNUMBER('FOB'!C14*(1+-0.1)),'FOB'!C14*(1+-0.1)*'FOB'!C7,0)))*0.003/0.997))))*'FOB'!C11,0)+IF(ISNUMBER('FOB'!C11),(IF(AND(ISNUMBER('FOB'!C6),ISNUMBER('FOB'!C7)),'FOB'!C6*'FOB'!C7,0)+IF('FOB'!C9=TRUE,0,IF(ISNUMBER('FOB'!C19),'FOB'!C19,0))+IF(ISNUMBER('FOB'!C13),IF('FOB'!C22,0,'FOB'!C13),0)+IF(ISNUMBER('FOB'!C12),IF('FOB'!C22,0,'FOB'!C12),0)+IF('FOB'!C20,0,IF(ISNUMBER('FOB'!C14*(1+-0.1)),'FOB'!C14*(1+-0.1)*'FOB'!C7,0))+IF('FOB'!C18,0,IF(ISNUMBER('FOB'!C17),'FOB'!C17,IF(ISNUMBER('FOB'!C16),(IF(AND(ISNUMBER('FOB'!C6),ISNUMBER('FOB'!C7)),'FOB'!C6*'FOB'!C7,0)+IF('FOB'!C20,0,IF(ISNUMBER('FOB'!C14*(1+-0.1)),'FOB'!C14*(1+-0.1)*'FOB'!C7,0)))*'FOB'!C16/100*1.1,(IF(AND(ISNUMBER('FOB'!C6),ISNUMBER('FOB'!C7)),'FOB'!C6*'FOB'!C7,0)+IF('FOB'!C9=TRUE,0,IF(ISNUMBER('FOB'!C19),'FOB'!C19,0))+IF(ISNUMBER('FOB'!C13),IF('FOB'!C22,0,'FOB'!C13),0)+IF(ISNUMBER('FOB'!C12),IF('FOB'!C22,0,'FOB'!C12),0)+IF('FOB'!C20,0,IF(ISNUMBER('FOB'!C14*(1+-0.1)),'FOB'!C14*(1+-0.1)*'FOB'!C7,0)))*0.003/0.997))))*'FOB'!C11,0)*IF(ISNUMBER('FOB'!C33),'FOB'!C33,0)*(1+IF(ISNUMBER('FOB'!C34),'FOB'!C34,0)))*IF(ISNUMBER('FOB'!C35),'FOB'!C35,0)+(IF(ISNUMBER('FOB'!C46),'FOB'!C46,0)+IF(ISNUMBER('FOB'!C47),'FOB'!C47,0)+IF(ISNUMBER('FOB'!C48),'FOB'!C48,0)+IF(ISNUMBER('FOB'!C49),'FOB'!C49,0)+IF(ISNUMBER('FOB'!C50),'FOB'!C50,0)+IF(ISNUMBER('FOB'!C51),'FOB'!C51,0))-IF(LEFT('FOB'!C36,1)="是",(IF(ISNUMBER('FOB'!C11),(IF(AND(ISNUMBER('FOB'!C6),ISNUMBER('FOB'!C7)),'FOB'!C6*'FOB'!C7,0)+IF('FOB'!C9=TRUE,0,IF(ISNUMBER('FOB'!C19),'FOB'!C19,0))+IF(ISNUMBER('FOB'!C13),IF('FOB'!C22,0,'FOB'!C13),0)+IF(ISNUMBER('FOB'!C12),IF('FOB'!C22,0,'FOB'!C12),0)+IF('FOB'!C20,0,IF(ISNUMBER('FOB'!C14*(1+-0.1)),'FOB'!C14*(1+-0.1)*'FOB'!C7,0))+IF('FOB'!C18,0,IF(ISNUMBER('FOB'!C17),'FOB'!C17,IF(ISNUMBER('FOB'!C16),(IF(AND(ISNUMBER('FOB'!C6),ISNUMBER('FOB'!C7)),'FOB'!C6*'FOB'!C7,0)+IF('FOB'!C20,0,IF(ISNUMBER('FOB'!C14*(1+-0.1)),'FOB'!C14*(1+-0.1)*'FOB'!C7,0)))*'FOB'!C16/100*1.1,(IF(AND(ISNUMBER('FOB'!C6),ISNUMBER('FOB'!C7)),'FOB'!C6*'FOB'!C7,0)+IF('FOB'!C9=TRUE,0,IF(ISNUMBER('FOB'!C19),'FOB'!C19,0))+IF(ISNUMBER('FOB'!C13),IF('FOB'!C22,0,'FOB'!C13),0)+IF(ISNUMBER('FOB'!C12),IF('FOB'!C22,0,'FOB'!C12),0)+IF('FOB'!C20,0,IF(ISNUMBER('FOB'!C14*(1+-0.1)),'FOB'!C14*(1+-0.1)*'FOB'!C7,0)))*0.003/0.997))))*'FOB'!C11,0)+IF(ISNUMBER('FOB'!C11),(IF(AND(ISNUMBER('FOB'!C6),ISNUMBER('FOB'!C7)),'FOB'!C6*'FOB'!C7,0)+IF('FOB'!C9=TRUE,0,IF(ISNUMBER('FOB'!C19),'FOB'!C19,0))+IF(ISNUMBER('FOB'!C13),IF('FOB'!C22,0,'FOB'!C13),0)+IF(ISNUMBER('FOB'!C12),IF('FOB'!C22,0,'FOB'!C12),0)+IF('FOB'!C20,0,IF(ISNUMBER('FOB'!C14*(1+-0.1)),'FOB'!C14*(1+-0.1)*'FOB'!C7,0))+IF('FOB'!C18,0,IF(ISNUMBER('FOB'!C17),'FOB'!C17,IF(ISNUMBER('FOB'!C16),(IF(AND(ISNUMBER('FOB'!C6),ISNUMBER('FOB'!C7)),'FOB'!C6*'FOB'!C7,0)+IF('FOB'!C20,0,IF(ISNUMBER('FOB'!C14*(1+-0.1)),'FOB'!C14*(1+-0.1)*'FOB'!C7,0)))*'FOB'!C16/100*1.1,(IF(AND(ISNUMBER('FOB'!C6),ISNUMBER('FOB'!C7)),'FOB'!C6*'FOB'!C7,0)+IF('FOB'!C9=TRUE,0,IF(ISNUMBER('FOB'!C19),'FOB'!C19,0))+IF(ISNUMBER('FOB'!C13),IF('FOB'!C22,0,'FOB'!C13),0)+IF(ISNUMBER('FOB'!C12),IF('FOB'!C22,0,'FOB'!C12),0)+IF('FOB'!C20,0,IF(ISNUMBER('FOB'!C14*(1+-0.1)),'FOB'!C14*(1+-0.1)*'FOB'!C7,0)))*0.003/0.997))))*'FOB'!C11,0)*IF(ISNUMBER('FOB'!C33),'FOB'!C33,0)*(1+IF(ISNUMBER('FOB'!C34),'FOB'!C34,0)))*IF(ISNUMBER('FOB'!C35),'FOB'!C35,0),0))/('FOB'!C7),"") | E16: =IF(AND(ISNUMBER(D16),ISNUMBER(D4)),D16-D4,"") | F16: =IF(AND(ISNUMBER(E16),ISNUMBER(D4)),E16/D4,"")
B17: 海运费 +0% | C17: 'FOB'!C14*(1+0.0) | D17: =IF(AND(ISNUMBER('FOB'!C6),ISNUMBER('FOB'!C7),ISNUMBER('FOB'!C10),ISNUMBER('FOB'!C11),ISNUMBER('FOB'!C33)),((IF(AND(ISNUMBER('FOB'!C6),ISNUMBER('FOB'!C7)),'FOB'!C6*'FOB'!C7,0)+IF('FOB'!C9=TRUE,0,IF(ISNUMBER('FOB'!C19),'FOB'!C19,0))+IF(ISNUMBER('FOB'!C13),IF('FOB'!C22,0,'FOB'!C13),0)+IF(ISNUMBER('FOB'!C12),IF('FOB'!C22,0,'FOB'!C12),0)+IF('FOB'!C20,0,IF(ISNUMBER('FOB'!C14*(1+0.0)),'FOB'!C14*(1+0.0)*'FOB'!C7,0))+IF('FOB'!C18,0,IF(ISNUMBER('FOB'!C17),'FOB'!C17,IF(ISNUMBER('FOB'!C16),(IF(AND(ISNUMBER('FOB'!C6),ISNUMBER('FOB'!C7)),'FOB'!C6*'FOB'!C7,0)+IF('FOB'!C20,0,IF(ISNUMBER('FOB'!C14*(1+0.0)),'FOB'!C14*(1+0.0)*'FOB'!C7,0)))*'FOB'!C16/100*1.1,(IF(AND(ISNUMBER('FOB'!C6),ISNUMBER('FOB'!C7)),'FOB'!C6*'FOB'!C7,0)+IF('FOB'!C9=TRUE,0,IF(ISNUMBER('FOB'!C19),'FOB'!C19,0))+IF(ISNUMBER('FOB'!C13),IF('FOB'!C22,0,'FOB'!C13),0)+IF(ISNUMBER('FOB'!C12),IF('FOB'!C22,0,'FOB'!C12),0)+IF('FOB'!C20,0,IF(ISNUMBER('FOB'!C14*(1+0.0)),'FOB'!C14*(1+0.0)*'FOB'!C7,0)))*0.003/0.997))))*IF(ISNUMBER('FOB'!C10),'FOB'!C10,0)+IF(ISNUMBER('FOB'!C11),(IF(AND(ISNUMBER('FOB'!C6),ISNUMBER('FOB'!C7)),'FOB'!C6*'FOB'!C7,0)+IF('FOB'!C9=TRUE,0,IF(ISNUMBER('FOB'!C19),'FOB'!C19,0))+IF(ISNUMBER('FOB'!C13),IF('FOB'!C22,0,'FOB'!C13),0)+IF(ISNUMBER('FOB'!C12),IF('FOB'!C22,0,'FOB'!C12),0)+IF('FOB'!C20,0,IF(ISNUMBER('FOB'!C14*(1+0.0)),'FOB'!C14*(1+0.0)*'FOB'!C7,0))+IF('FOB'!C18,0,IF(ISNUMBER('FOB'!C17),'FOB'!C17,IF(ISNUMBER('FOB'!C16),(IF(AND(ISNUMBER('FOB'!C6),ISNUMBER('FOB'!C7)),'FOB'!C6*'FOB'!C7,0)+IF('FOB'!C20,0,IF(ISNUMBER('FOB'!C14*(1+0.0)),'FOB'!C14*(1+0.0)*'FOB'!C7,0)))*'FOB'!C16/100*1.1,(IF(AND(ISNUMBER('FOB'!C6),ISNUMBER('FOB'!C7)),'FOB'!C6*'FOB'!C7,0)+IF('FOB'!C9=TRUE,0,IF(ISNUMBER('FOB'!C19),'FOB'!C19,0))+IF(ISNUMBER('FOB'!C13),IF('FOB'!C22,0,'FOB'!C13),0)+IF(ISNUMBER('FOB'!C12),IF('FOB'!C22,0,'FOB'!C12),0)+IF('FOB'!C20,0,IF(ISNUMBER('FOB'!C14*(1+0.0)),'FOB'!C14*(1+0.0)*'FOB'!C7,0)))*0.003/0.997))))*'FOB'!C11,0)*IF(ISNUMBER('FOB'!C33),'FOB'!C33,0)*(1+IF(ISNUMBER('FOB'!C34),'FOB'!C34,0))+(IF(ISNUMBER('FOB'!C11),(IF(AND(ISNUMBER('FOB'!C6),ISNUMBER('FOB'!C7)),'FOB'!C6*'FOB'!C7,0)+IF('FOB'!C9=TRUE,0,IF(ISNUMBER('FOB'!C19),'FOB'!C19,0))+IF(ISNUMBER('FOB'!C13),IF('FOB'!C22,0,'FOB'!C13),0)+IF(ISNUMBER('FOB'!C12),IF('FOB'!C22,0,'FOB'!C12),0)+IF('FOB'!C20,0,IF(ISNUMBER('FOB'!C14*(1+0.0)),'FOB'!C14*(1+0.0)*'FOB'!C7,0))+IF('FOB'!C18,0,IF(ISNUMBER('FOB'!C17),'FOB'!C17,IF(ISNUMBER('FOB'!C16),(IF(AND(ISNUMBER('FOB'!C6),ISNUMBER('FOB'!C7)),'FOB'!C6*'FOB'!C7,0)+IF('FOB'!C20,0,IF(ISNUMBER('FOB'!C14*(1+0.0)),'FOB'!C14*(1+0.0)*'FOB'!C7,0)))*'FOB'!C16/100*1.1,(IF(AND(ISNUMBER('FOB'!C6),ISNUMBER('FOB'!C7)),'FOB'!C6*'FOB'!C7,0)+IF('FOB'!C9=TRUE,0,IF(ISNUMBER('FOB'!C19),'FOB'!C19,0))+IF(ISNUMBER('FOB'!C13),IF('FOB'!C22,0,'FOB'!C13),0)+IF(ISNUMBER('FOB'!C12),IF('FOB'!C22,0,'FOB'!C12),0)+IF('FOB'!C20,0,IF(ISNUMBER('FOB'!C14*(1+0.0)),'FOB'!C14*(1+0.0)*'FOB'!C7,0)))*0.003/0.997))))*'FOB'!C11,0)+IF(ISNUMBER('FOB'!C11),(IF(AND(ISNUMBER('FOB'!C6),ISNUMBER('FOB'!C7)),'FOB'!C6*'FOB'!C7,0)+IF('FOB'!C9=TRUE,0,IF(ISNUMBER('FOB'!C19),'FOB'!C19,0))+IF(ISNUMBER('FOB'!C13),IF('FOB'!C22,0,'FOB'!C13),0)+IF(ISNUMBER('FOB'!C12),IF('FOB'!C22,0,'FOB'!C12),0)+IF('FOB'!C20,0,IF(ISNUMBER('FOB'!C14*(1+0.0)),'FOB'!C14*(1+0.0)*'FOB'!C7,0))+IF('FOB'!C18,0,IF(ISNUMBER('FOB'!C17),'FOB'!C17,IF(ISNUMBER('FOB'!C16),(IF(AND(ISNUMBER('FOB'!C6),ISNUMBER('FOB'!C7)),'FOB'!C6*'FOB'!C7,0)+IF('FOB'!C20,0,IF(ISNUMBER('FOB'!C14*(1+0.0)),'FOB'!C14*(1+0.0)*'FOB'!C7,0)))*'FOB'!C16/100*1.1,(IF(AND(ISNUMBER('FOB'!C6),ISNUMBER('FOB'!C7)),'FOB'!C6*'FOB'!C7,0)+IF('FOB'!C9=TRUE,0,IF(ISNUMBER('FOB'!C19),'FOB'!C19,0))+IF(ISNUMBER('FOB'!C13),IF('FOB'!C22,0,'FOB'!C13),0)+IF(ISNUMBER('FOB'!C12),IF('FOB'!C22,0,'FOB'!C12),0)+IF('FOB'!C20,0,IF(ISNUMBER('FOB'!C14*(1+0.0)),'FOB'!C14*(1+0.0)*'FOB'!C7,0)))*0.003/0.997))))*'FOB'!C11,0)*IF(ISNUMBER('FOB'!C33),'FOB'!C33,0)*(1+IF(ISNUMBER('FOB'!C34),'FOB'!C34,0)))*IF(ISNUMBER('FOB'!C35),'FOB'!C35,0)+(IF(ISNUMBER('FOB'!C46),'FOB'!C46,0)+IF(ISNUMBER('FOB'!C47),'FOB'!C47,0)+IF(ISNUMBER('FOB'!C48),'FOB'!C48,0)+IF(ISNUMBER('FOB'!C49),'FOB'!C49,0)+IF(ISNUMBER('FOB'!C50),'FOB'!C50,0)+IF(ISNUMBER('FOB'!C51),'FOB'!C51,0))-IF(LEFT('FOB'!C36,1)="是",(IF(ISNUMBER('FOB'!C11),(IF(AND(ISNUMBER('FOB'!C6),ISNUMBER('FOB'!C7)),'FOB'!C6*'FOB'!C7,0)+IF('FOB'!C9=TRUE,0,IF(ISNUMBER('FOB'!C19),'FOB'!C19,0))+IF(ISNUMBER('FOB'!C13),IF('FOB'!C22,0,'FOB'!C13),0)+IF(ISNUMBER('FOB'!C12),IF('FOB'!C22,0,'FOB'!C12),0)+IF('FOB'!C20,0,IF(ISNUMBER('FOB'!C14*(1+0.0)),'FOB'!C14*(1+0.0)*'FOB'!C7,0))+IF('FOB'!C18,0,IF(ISNUMBER('FOB'!C17),'FOB'!C17,IF(ISNUMBER('FOB'!C16),(IF(AND(ISNUMBER('FOB'!C6),ISNUMBER('FOB'!C7)),'FOB'!C6*'FOB'!C7,0)+IF('FOB'!C20,0,IF(ISNUMBER('FOB'!C14*(1+0.0)),'FOB'!C14*(1+0.0)*'FOB'!C7,0)))*'FOB'!C16/100*1.1,(IF(AND(ISNUMBER('FOB'!C6),ISNUMBER('FOB'!C7)),'FOB'!C6*'FOB'!C7,0)+IF('FOB'!C9=TRUE,0,IF(ISNUMBER('FOB'!C19),'FOB'!C19,0))+IF(ISNUMBER('FOB'!C13),IF('FOB'!C22,0,'FOB'!C13),0)+IF(ISNUMBER('FOB'!C12),IF('FOB'!C22,0,'FOB'!C12),0)+IF('FOB'!C20,0,IF(ISNUMBER('FOB'!C14*(1+0.0)),'FOB'!C14*(1+0.0)*'FOB'!C7,0)))*0.003/0.997))))*'FOB'!C11,0)+IF(ISNUMBER('FOB'!C11),(IF(AND(ISNUMBER('FOB'!C6),ISNUMBER('FOB'!C7)),'FOB'!C6*'FOB'!C7,0)+IF('FOB'!C9=TRUE,0,IF(ISNUMBER('FOB'!C19),'FOB'!C19,0))+IF(ISNUMBER('FOB'!C13),IF('FOB'!C22,0,'FOB'!C13),0)+IF(ISNUMBER('FOB'!C12),IF('FOB'!C22,0,'FOB'!C12),0)+IF('FOB'!C20,0,IF(ISNUMBER('FOB'!C14*(1+0.0)),'FOB'!C14*(1+0.0)*'FOB'!C7,0))+IF('FOB'!C18,0,IF(ISNUMBER('FOB'!C17),'FOB'!C17,IF(ISNUMBER('FOB'!C16),(IF(AND(ISNUMBER('FOB'!C6),ISNUMBER('FOB'!C7)),'FOB'!C6*'FOB'!C7,0)+IF('FOB'!C20,0,IF(ISNUMBER('FOB'!C14*(1+0.0)),'FOB'!C14*(1+0.0)*'FOB'!C7,0)))*'FOB'!C16/100*1.1,(IF(AND(ISNUMBER('FOB'!C6),ISNUMBER('FOB'!C7)),'FOB'!C6*'FOB'!C7,0)+IF('FOB'!C9=TRUE,0,IF(ISNUMBER('FOB'!C19),'FOB'!C19,0))+IF(ISNUMBER('FOB'!C13),IF('FOB'!C22,0,'FOB'!C13),0)+IF(ISNUMBER('FOB'!C12),IF('FOB'!C22,0,'FOB'!C12),0)+IF('FOB'!C20,0,IF(ISNUMBER('FOB'!C14*(1+0.0)),'FOB'!C14*(1+0.0)*'FOB'!C7,0)))*0.003/0.997))))*'FOB'!C11,0)*IF(ISNUMBER('FOB'!C33),'FOB'!C33,0)*(1+IF(ISNUMBER('FOB'!C34),'FOB'!C34,0)))*IF(ISNUMBER('FOB'!C35),'FOB'!C35,0),0))/('FOB'!C7),"") | E17: =IF(AND(ISNUMBER(D17),ISNUMBER(D4)),D17-D4,"") | F17: =IF(AND(ISNUMBER(E17),ISNUMBER(D4)),E17/D4,"")
B18: 海运费 +10% | C18: 'FOB'!C14*(1+0.1) | D18: =IF(AND(ISNUMBER('FOB'!C6),ISNUMBER('FOB'!C7),ISNUMBER('FOB'!C10),ISNUMBER('FOB'!C11),ISNUMBER('FOB'!C33)),((IF(AND(ISNUMBER('FOB'!C6),ISNUMBER('FOB'!C7)),'FOB'!C6*'FOB'!C7,0)+IF('FOB'!C9=TRUE,0,IF(ISNUMBER('FOB'!C19),'FOB'!C19,0))+IF(ISNUMBER('FOB'!C13),IF('FOB'!C22,0,'FOB'!C13),0)+IF(ISNUMBER('FOB'!C12),IF('FOB'!C22,0,'FOB'!C12),0)+IF('FOB'!C20,0,IF(ISNUMBER('FOB'!C14*(1+0.1)),'FOB'!C14*(1+0.1)*'FOB'!C7,0))+IF('FOB'!C18,0,IF(ISNUMBER('FOB'!C17),'FOB'!C17,IF(ISNUMBER('FOB'!C16),(IF(AND(ISNUMBER('FOB'!C6),ISNUMBER('FOB'!C7)),'FOB'!C6*'FOB'!C7,0)+IF('FOB'!C20,0,IF(ISNUMBER('FOB'!C14*(1+0.1)),'FOB'!C14*(1+0.1)*'FOB'!C7,0)))*'FOB'!C16/100*1.1,(IF(AND(ISNUMBER('FOB'!C6),ISNUMBER('FOB'!C7)),'FOB'!C6*'FOB'!C7,0)+IF('FOB'!C9=TRUE,0,IF(ISNUMBER('FOB'!C19),'FOB'!C19,0))+IF(ISNUMBER('FOB'!C13),IF('FOB'!C22,0,'FOB'!C13),0)+IF(ISNUMBER('FOB'!C12),IF('FOB'!C22,0,'FOB'!C12),0)+IF('FOB'!C20,0,IF(ISNUMBER('FOB'!C14*(1+0.1)),'FOB'!C14*(1+0.1)*'FOB'!C7,0)))*0.003/0.997))))*IF(ISNUMBER('FOB'!C10),'FOB'!C10,0)+IF(ISNUMBER('FOB'!C11),(IF(AND(ISNUMBER('FOB'!C6),ISNUMBER('FOB'!C7)),'FOB'!C6*'FOB'!C7,0)+IF('FOB'!C9=TRUE,0,IF(ISNUMBER('FOB'!C19),'FOB'!C19,0))+IF(ISNUMBER('FOB'!C13),IF('FOB'!C22,0,'FOB'!C13),0)+IF(ISNUMBER('FOB'!C12),IF('FOB'!C22,0,'FOB'!C12),0)+IF('FOB'!C20,0,IF(ISNUMBER('FOB'!C14*(1+0.1)),'FOB'!C14*(1+0.1)*'FOB'!C7,0))+IF('FOB'!C18,0,IF(ISNUMBER('FOB'!C17),'FOB'!C17,IF(ISNUMBER('FOB'!C16),(IF(AND(ISNUMBER('FOB'!C6),ISNUMBER('FOB'!C7)),'FOB'!C6*'FOB'!C7,0)+IF('FOB'!C20,0,IF(ISNUMBER('FOB'!C14*(1+0.1)),'FOB'!C14*(1+0.1)*'FOB'!C7,0)))*'FOB'!C16/100*1.1,(IF(AND(ISNUMBER('FOB'!C6),ISNUMBER('FOB'!C7)),'FOB'!C6*'FOB'!C7,0)+IF('FOB'!C9=TRUE,0,IF(ISNUMBER('FOB'!C19),'FOB'!C19,0))+IF(ISNUMBER('FOB'!C13),IF('FOB'!C22,0,'FOB'!C13),0)+IF(ISNUMBER('FOB'!C12),IF('FOB'!C22,0,'FOB'!C12),0)+IF('FOB'!C20,0,IF(ISNUMBER('FOB'!C14*(1+0.1)),'FOB'!C14*(1+0.1)*'FOB'!C7,0)))*0.003/0.997))))*'FOB'!C11,0)*IF(ISNUMBER('FOB'!C33),'FOB'!C33,0)*(1+IF(ISNUMBER('FOB'!C34),'FOB'!C34,0))+(IF(ISNUMBER('FOB'!C11),(IF(AND(ISNUMBER('FOB'!C6),ISNUMBER('FOB'!C7)),'FOB'!C6*'FOB'!C7,0)+IF('FOB'!C9=TRUE,0,IF(ISNUMBER('FOB'!C19),'FOB'!C19,0))+IF(ISNUMBER('FOB'!C13),IF('FOB'!C22,0,'FOB'!C13),0)+IF(ISNUMBER('FOB'!C12),IF('FOB'!C22,0,'FOB'!C12),0)+IF('FOB'!C20,0,IF(ISNUMBER('FOB'!C14*(1+0.1)),'FOB'!C14*(1+0.1)*'FOB'!C7,0))+IF('FOB'!C18,0,IF(ISNUMBER('FOB'!C17),'FOB'!C17,IF(ISNUMBER('FOB'!C16),(IF(AND(ISNUMBER('FOB'!C6),ISNUMBER('FOB'!C7)),'FOB'!C6*'FOB'!C7,0)+IF('FOB'!C20,0,IF(ISNUMBER('FOB'!C14*(1+0.1)),'FOB'!C14*(1+0.1)*'FOB'!C7,0)))*'FOB'!C16/100*1.1,(IF(AND(ISNUMBER('FOB'!C6),ISNUMBER('FOB'!C7)),'FOB'!C6*'FOB'!C7,0)+IF('FOB'!C9=TRUE,0,IF(ISNUMBER('FOB'!C19),'FOB'!C19,0))+IF(ISNUMBER('FOB'!C13),IF('FOB'!C22,0,'FOB'!C13),0)+IF(ISNUMBER('FOB'!C12),IF('FOB'!C22,0,'FOB'!C12),0)+IF('FOB'!C20,0,IF(ISNUMBER('FOB'!C14*(1+0.1)),'FOB'!C14*(1+0.1)*'FOB'!C7,0)))*0.003/0.997))))*'FOB'!C11,0)+IF(ISNUMBER('FOB'!C11),(IF(AND(ISNUMBER('FOB'!C6),ISNUMBER('FOB'!C7)),'FOB'!C6*'FOB'!C7,0)+IF('FOB'!C9=TRUE,0,IF(ISNUMBER('FOB'!C19),'FOB'!C19,0))+IF(ISNUMBER('FOB'!C13),IF('FOB'!C22,0,'FOB'!C13),0)+IF(ISNUMBER('FOB'!C12),IF('FOB'!C22,0,'FOB'!C12),0)+IF('FOB'!C20,0,IF(ISNUMBER('FOB'!C14*(1+0.1)),'FOB'!C14*(1+0.1)*'FOB'!C7,0))+IF('FOB'!C18,0,IF(ISNUMBER('FOB'!C17),'FOB'!C17,IF(ISNUMBER('FOB'!C16),(IF(AND(ISNUMBER('FOB'!C6),ISNUMBER('FOB'!C7)),'FOB'!C6*'FOB'!C7,0)+IF('FOB'!C20,0,IF(ISNUMBER('FOB'!C14*(1+0.1)),'FOB'!C14*(1+0.1)*'FOB'!C7,0)))*'FOB'!C16/100*1.1,(IF(AND(ISNUMBER('FOB'!C6),ISNUMBER('FOB'!C7)),'FOB'!C6*'FOB'!C7,0)+IF('FOB'!C9=TRUE,0,IF(ISNUMBER('FOB'!C19),'FOB'!C19,0))+IF(ISNUMBER('FOB'!C13),IF('FOB'!C22,0,'FOB'!C13),0)+IF(ISNUMBER('FOB'!C12),IF('FOB'!C22,0,'FOB'!C12),0)+IF('FOB'!C20,0,IF(ISNUMBER('FOB'!C14*(1+0.1)),'FOB'!C14*(1+0.1)*'FOB'!C7,0)))*0.003/0.997))))*'FOB'!C11,0)*IF(ISNUMBER('FOB'!C33),'FOB'!C33,0)*(1+IF(ISNUMBER('FOB'!C34),'FOB'!C34,0)))*IF(ISNUMBER('FOB'!C35),'FOB'!C35,0)+(IF(ISNUMBER('FOB'!C46),'FOB'!C46,0)+IF(ISNUMBER('FOB'!C47),'FOB'!C47,0)+IF(ISNUMBER('FOB'!C48),'FOB'!C48,0)+IF(ISNUMBER('FOB'!C49),'FOB'!C49,0)+IF(ISNUMBER('FOB'!C50),'FOB'!C50,0)+IF(ISNUMBER('FOB'!C51),'FOB'!C51,0))-IF(LEFT('FOB'!C36,1)="是",(IF(ISNUMBER('FOB'!C11),(IF(AND(ISNUMBER('FOB'!C6),ISNUMBER('FOB'!C7)),'FOB'!C6*'FOB'!C7,0)+IF('FOB'!C9=TRUE,0,IF(ISNUMBER('FOB'!C19),'FOB'!C19,0))+IF(ISNUMBER('FOB'!C13),IF('FOB'!C22,0,'FOB'!C13),0)+IF(ISNUMBER('FOB'!C12),IF('FOB'!C22,0,'FOB'!C12),0)+IF('FOB'!C20,0,IF(ISNUMBER('FOB'!C14*(1+0.1)),'FOB'!C14*(1+0.1)*'FOB'!C7,0))+IF('FOB'!C18,0,IF(ISNUMBER('FOB'!C17),'FOB'!C17,IF(ISNUMBER('FOB'!C16),(IF(AND(ISNUMBER('FOB'!C6),ISNUMBER('FOB'!C7)),'FOB'!C6*'FOB'!C7,0)+IF('FOB'!C20,0,IF(ISNUMBER('FOB'!C14*(1+0.1)),'FOB'!C14*(1+0.1)*'FOB'!C7,0)))*'FOB'!C16/100*1.1,(IF(AND(ISNUMBER('FOB'!C6),ISNUMBER('FOB'!C7)),'FOB'!C6*'FOB'!C7,0)+IF('FOB'!C9=TRUE,0,IF(ISNUMBER('FOB'!C19),'FOB'!C19,0))+IF(ISNUMBER('FOB'!C13),IF('FOB'!C22,0,'FOB'!C13),0)+IF(ISNUMBER('FOB'!C12),IF('FOB'!C22,0,'FOB'!C12),0)+IF('FOB'!C20,0,IF(ISNUMBER('FOB'!C14*(1+0.1)),'FOB'!C14*(1+0.1)*'FOB'!C7,0)))*0.003/0.997))))*'FOB'!C11,0)+IF(ISNUMBER('FOB'!C11),(IF(AND(ISNUMBER('FOB'!C6),ISNUMBER('FOB'!C7)),'FOB'!C6*'FOB'!C7,0)+IF('FOB'!C9=TRUE,0,IF(ISNUMBER('FOB'!C19),'FOB'!C19,0))+IF(ISNUMBER('FOB'!C13),IF('FOB'!C22,0,'FOB'!C13),0)+IF(ISNUMBER('FOB'!C12),IF('FOB'!C22,0,'FOB'!C12),0)+IF('FOB'!C20,0,IF(ISNUMBER('FOB'!C14*(1+0.1)),'FOB'!C14*(1+0.1)*'FOB'!C7,0))+IF('FOB'!C18,0,IF(ISNUMBER('FOB'!C17),'FOB'!C17,IF(ISNUMBER('FOB'!C16),(IF(AND(ISNUMBER('FOB'!C6),ISNUMBER('FOB'!C7)),'FOB'!C6*'FOB'!C7,0)+IF('FOB'!C20,0,IF(ISNUMBER('FOB'!C14*(1+0.1)),'FOB'!C14*(1+0.1)*'FOB'!C7,0)))*'FOB'!C16/100*1.1,(IF(AND(ISNUMBER('FOB'!C6),ISNUMBER('FOB'!C7)),'FOB'!C6*'FOB'!C7,0)+IF('FOB'!C9=TRUE,0,IF(ISNUMBER('FOB'!C19),'FOB'!C19,0))+IF(ISNUMBER('FOB'!C13),IF('FOB'!C22,0,'FOB'!C13),0)+IF(ISNUMBER('FOB'!C12),IF('FOB'!C22,0,'FOB'!C12),0)+IF('FOB'!C20,0,IF(ISNUMBER('FOB'!C14*(1+0.1)),'FOB'!C14*(1+0.1)*'FOB'!C7,0)))*0.003/0.997))))*'FOB'!C11,0)*IF(ISNUMBER('FOB'!C33),'FOB'!C33,0)*(1+IF(ISNUMBER('FOB'!C34),'FOB'!C34,0)))*IF(ISNUMBER('FOB'!C35),'FOB'!C35,0),0))/('FOB'!C7),"") | E18: =IF(AND(ISNUMBER(D18),ISNUMBER(D4)),D18-D4,"") | F18: =IF(AND(ISNUMBER(E18),ISNUMBER(D4)),E18/D4,"")
B19: 海运费 +20% | C19: 'FOB'!C14*(1+0.2) | D19: =IF(AND(ISNUMBER('FOB'!C6),ISNUMBER('FOB'!C7),ISNUMBER('FOB'!C10),ISNUMBER('FOB'!C11),ISNUMBER('FOB'!C33)),((IF(AND(ISNUMBER('FOB'!C6),ISNUMBER('FOB'!C7)),'FOB'!C6*'FOB'!C7,0)+IF('FOB'!C9=TRUE,0,IF(ISNUMBER('FOB'!C19),'FOB'!C19,0))+IF(ISNUMBER('FOB'!C13),IF('FOB'!C22,0,'FOB'!C13),0)+IF(ISNUMBER('FOB'!C12),IF('FOB'!C22,0,'FOB'!C12),0)+IF('FOB'!C20,0,IF(ISNUMBER('FOB'!C14*(1+0.2)),'FOB'!C14*(1+0.2)*'FOB'!C7,0))+IF('FOB'!C18,0,IF(ISNUMBER('FOB'!C17),'FOB'!C17,IF(ISNUMBER('FOB'!C16),(IF(AND(ISNUMBER('FOB'!C6),ISNUMBER('FOB'!C7)),'FOB'!C6*'FOB'!C7,0)+IF('FOB'!C20,0,IF(ISNUMBER('FOB'!C14*(1+0.2)),'FOB'!C14*(1+0.2)*'FOB'!C7,0)))*'FOB'!C16/100*1.1,(IF(AND(ISNUMBER('FOB'!C6),ISNUMBER('FOB'!C7)),'FOB'!C6*'FOB'!C7,0)+IF('FOB'!C9=TRUE,0,IF(ISNUMBER('FOB'!C19),'FOB'!C19,0))+IF(ISNUMBER('FOB'!C13),IF('FOB'!C22,0,'FOB'!C13),0)+IF(ISNUMBER('FOB'!C12),IF('FOB'!C22,0,'FOB'!C12),0)+IF('FOB'!C20,0,IF(ISNUMBER('FOB'!C14*(1+0.2)),'FOB'!C14*(1+0.2)*'FOB'!C7,0)))*0.003/0.997))))*IF(ISNUMBER('FOB'!C10),'FOB'!C10,0)+IF(ISNUMBER('FOB'!C11),(IF(AND(ISNUMBER('FOB'!C6),ISNUMBER('FOB'!C7)),'FOB'!C6*'FOB'!C7,0)+IF('FOB'!C9=TRUE,0,IF(ISNUMBER('FOB'!C19),'FOB'!C19,0))+IF(ISNUMBER('FOB'!C13),IF('FOB'!C22,0,'FOB'!C13),0)+IF(ISNUMBER('FOB'!C12),IF('FOB'!C22,0,'FOB'!C12),0)+IF('FOB'!C20,0,IF(ISNUMBER('FOB'!C14*(1+0.2)),'FOB'!C14*(1+0.2)*'FOB'!C7,0))+IF('FOB'!C18,0,IF(ISNUMBER('FOB'!C17),'FOB'!C17,IF(ISNUMBER('FOB'!C16),(IF(AND(ISNUMBER('FOB'!C6),ISNUMBER('FOB'!C7)),'FOB'!C6*'FOB'!C7,0)+IF('FOB'!C20,0,IF(ISNUMBER('FOB'!C14*(1+0.2)),'FOB'!C14*(1+0.2)*'FOB'!C7,0)))*'FOB'!C16/100*1.1,(IF(AND(ISNUMBER('FOB'!C6),ISNUMBER('FOB'!C7)),'FOB'!C6*'FOB'!C7,0)+IF('FOB'!C9=TRUE,0,IF(ISNUMBER('FOB'!C19),'FOB'!C19,0))+IF(ISNUMBER('FOB'!C13),IF('FOB'!C22,0,'FOB'!C13),0)+IF(ISNUMBER('FOB'!C12),IF('FOB'!C22,0,'FOB'!C12),0)+IF('FOB'!C20,0,IF(ISNUMBER('FOB'!C14*(1+0.2)),'FOB'!C14*(1+0.2)*'FOB'!C7,0)))*0.003/0.997))))*'FOB'!C11,0)*IF(ISNUMBER('FOB'!C33),'FOB'!C33,0)*(1+IF(ISNUMBER('FOB'!C34),'FOB'!C34,0))+(IF(ISNUMBER('FOB'!C11),(IF(AND(ISNUMBER('FOB'!C6),ISNUMBER('FOB'!C7)),'FOB'!C6*'FOB'!C7,0)+IF('FOB'!C9=TRUE,0,IF(ISNUMBER('FOB'!C19),'FOB'!C19,0))+IF(ISNUMBER('FOB'!C13),IF('FOB'!C22,0,'FOB'!C13),0)+IF(ISNUMBER('FOB'!C12),IF('FOB'!C22,0,'FOB'!C12),0)+IF('FOB'!C20,0,IF(ISNUMBER('FOB'!C14*(1+0.2)),'FOB'!C14*(1+0.2)*'FOB'!C7,0))+IF('FOB'!C18,0,IF(ISNUMBER('FOB'!C17),'FOB'!C17,IF(ISNUMBER('FOB'!C16),(IF(AND(ISNUMBER('FOB'!C6),ISNUMBER('FOB'!C7)),'FOB'!C6*'FOB'!C7,0)+IF('FOB'!C20,0,IF(ISNUMBER('FOB'!C14*(1+0.2)),'FOB'!C14*(1+0.2)*'FOB'!C7,0)))*'FOB'!C16/100*1.1,(IF(AND(ISNUMBER('FOB'!C6),ISNUMBER('FOB'!C7)),'FOB'!C6*'FOB'!C7,0)+IF('FOB'!C9=TRUE,0,IF(ISNUMBER('FOB'!C19),'FOB'!C19,0))+IF(ISNUMBER('FOB'!C13),IF('FOB'!C22,0,'FOB'!C13),0)+IF(ISNUMBER('FOB'!C12),IF('FOB'!C22,0,'FOB'!C12),0)+IF('FOB'!C20,0,IF(ISNUMBER('FOB'!C14*(1+0.2)),'FOB'!C14*(1+0.2)*'FOB'!C7,0)))*0.003/0.997))))*'FOB'!C11,0)+IF(ISNUMBER('FOB'!C11),(IF(AND(ISNUMBER('FOB'!C6),ISNUMBER('FOB'!C7)),'FOB'!C6*'FOB'!C7,0)+IF('FOB'!C9=TRUE,0,IF(ISNUMBER('FOB'!C19),'FOB'!C19,0))+IF(ISNUMBER('FOB'!C13),IF('FOB'!C22,0,'FOB'!C13),0)+IF(ISNUMBER('FOB'!C12),IF('FOB'!C22,0,'FOB'!C12),0)+IF('FOB'!C20,0,IF(ISNUMBER('FOB'!C14*(1+0.2)),'FOB'!C14*(1+0.2)*'FOB'!C7,0))+IF('FOB'!C18,0,IF(ISNUMBER('FOB'!C17),'FOB'!C17,IF(ISNUMBER('FOB'!C16),(IF(AND(ISNUMBER('FOB'!C6),ISNUMBER('FOB'!C7)),'FOB'!C6*'FOB'!C7,0)+IF('FOB'!C20,0,IF(ISNUMBER('FOB'!C14*(1+0.2)),'FOB'!C14*(1+0.2)*'FOB'!C7,0)))*'FOB'!C16/100*1.1,(IF(AND(ISNUMBER('FOB'!C6),ISNUMBER('FOB'!C7)),'FOB'!C6*'FOB'!C7,0)+IF('FOB'!C9=TRUE,0,IF(ISNUMBER('FOB'!C19),'FOB'!C19,0))+IF(ISNUMBER('FOB'!C13),IF('FOB'!C22,0,'FOB'!C13),0)+IF(ISNUMBER('FOB'!C12),IF('FOB'!C22,0,'FOB'!C12),0)+IF('FOB'!C20,0,IF(ISNUMBER('FOB'!C14*(1+0.2)),'FOB'!C14*(1+0.2)*'FOB'!C7,0)))*0.003/0.997))))*'FOB'!C11,0)*IF(ISNUMBER('FOB'!C33),'FOB'!C33,0)*(1+IF(ISNUMBER('FOB'!C34),'FOB'!C34,0)))*IF(ISNUMBER('FOB'!C35),'FOB'!C35,0)+(IF(ISNUMBER('FOB'!C46),'FOB'!C46,0)+IF(ISNUMBER('FOB'!C47),'FOB'!C47,0)+IF(ISNUMBER('FOB'!C48),'FOB'!C48,0)+IF(ISNUMBER('FOB'!C49),'FOB'!C49,0)+IF(ISNUMBER('FOB'!C50),'FOB'!C50,0)+IF(ISNUMBER('FOB'!C51),'FOB'!C51,0))-IF(LEFT('FOB'!C36,1)="是",(IF(ISNUMBER('FOB'!C11),(IF(AND(ISNUMBER('FOB'!C6),ISNUMBER('FOB'!C7)),'FOB'!C6*'FOB'!C7,0)+IF('FOB'!C9=TRUE,0,IF(ISNUMBER('FOB'!C19),'FOB'!C19,0))+IF(ISNUMBER('FOB'!C13),IF('FOB'!C22,0,'FOB'!C13),0)+IF(ISNUMBER('FOB'!C12),IF('FOB'!C22,0,'FOB'!C12),0)+IF('FOB'!C20,0,IF(ISNUMBER('FOB'!C14*(1+0.2)),'FOB'!C14*(1+0.2)*'FOB'!C7,0))+IF('FOB'!C18,0,IF(ISNUMBER('FOB'!C17),'FOB'!C17,IF(ISNUMBER('FOB'!C16),(IF(AND(ISNUMBER('FOB'!C6),ISNUMBER('FOB'!C7)),'FOB'!C6*'FOB'!C7,0)+IF('FOB'!C20,0,IF(ISNUMBER('FOB'!C14*(1+0.2)),'FOB'!C14*(1+0.2)*'FOB'!C7,0)))*'FOB'!C16/100*1.1,(IF(AND(ISNUMBER('FOB'!C6),ISNUMBER('FOB'!C7)),'FOB'!C6*'FOB'!C7,0)+IF('FOB'!C9=TRUE,0,IF(ISNUMBER('FOB'!C19),'FOB'!C19,0))+IF(ISNUMBER('FOB'!C13),IF('FOB'!C22,0,'FOB'!C13),0)+IF(ISNUMBER('FOB'!C12),IF('FOB'!C22,0,'FOB'!C12),0)+IF('FOB'!C20,0,IF(ISNUMBER('FOB'!C14*(1+0.2)),'FOB'!C14*(1+0.2)*'FOB'!C7,0)))*0.003/0.997))))*'FOB'!C11,0)+IF(ISNUMBER('FOB'!C11),(IF(AND(ISNUMBER('FOB'!C6),ISNUMBER('FOB'!C7)),'FOB'!C6*'FOB'!C7,0)+IF('FOB'!C9=TRUE,0,IF(ISNUMBER('FOB'!C19),'FOB'!C19,0))+IF(ISNUMBER('FOB'!C13),IF('FOB'!C22,0,'FOB'!C13),0)+IF(ISNUMBER('FOB'!C12),IF('FOB'!C22,0,'FOB'!C12),0)+IF('FOB'!C20,0,IF(ISNUMBER('FOB'!C14*(1+0.2)),'FOB'!C14*(1+0.2)*'FOB'!C7,0))+IF('FOB'!C18,0,IF(ISNUMBER('FOB'!C17),'FOB'!C17,IF(ISNUMBER('FOB'!C16),(IF(AND(ISNUMBER('FOB'!C6),ISNUMBER('FOB'!C7)),'FOB'!C6*'FOB'!C7,0)+IF('FOB'!C20,0,IF(ISNUMBER('FOB'!C14*(1+0.2)),'FOB'!C14*(1+0.2)*'FOB'!C7,0)))*'FOB'!C16/100*1.1,(IF(AND(ISNUMBER('FOB'!C6),ISNUMBER('FOB'!C7)),'FOB'!C6*'FOB'!C7,0)+IF('FOB'!C9=TRUE,0,IF(ISNUMBER('FOB'!C19),'FOB'!C19,0))+IF(ISNUMBER('FOB'!C13),IF('FOB'!C22,0,'FOB'!C13),0)+IF(ISNUMBER('FOB'!C12),IF('FOB'!C22,0,'FOB'!C12),0)+IF('FOB'!C20,0,IF(ISNUMBER('FOB'!C14*(1+0.2)),'FOB'!C14*(1+0.2)*'FOB'!C7,0)))*0.003/0.997))))*'FOB'!C11,0)*IF(ISNUMBER('FOB'!C33),'FOB'!C33,0)*(1+IF(ISNUMBER('FOB'!C34),'FOB'!C34,0)))*IF(ISNUMBER('FOB'!C35),'FOB'!C35,0),0))/('FOB'!C7),"") | E19: =IF(AND(ISNUMBER(D19),ISNUMBER(D4)),D19-D4,"") | F19: =IF(AND(ISNUMBER(E19),ISNUMBER(D4)),E19/D4,"")
B20: ③ 采购数量变化（按票固定费用摊薄）
B21: 情景 | C21: 情景参数 | D21: 到厂成本 元/吨 | E21: Δ 元/吨 | F21: Δ % | G21: 说明
B23: 数量 ×0.5 | C23: ='FOB'!C7*0.5 | D23: =IF(AND(ISNUMBER('FOB'!C6),ISNUMBER('FOB'!C7*0.5),ISNUMBER('FOB'!C10),ISNUMBER('FOB'!C11),ISNUMBER('FOB'!C33)),((IF(AND(ISNUMBER('FOB'!C6),ISNUMBER('FOB'!C7*0.5)),'FOB'!C6*'FOB'!C7*0.5,0)+IF('FOB'!C9=TRUE,0,IF(ISNUMBER('FOB'!C19),'FOB'!C19,0))+IF(ISNUMBER('FOB'!C13),IF('FOB'!C22,0,'FOB'!C13),0)+IF(ISNUMBER('FOB'!C12),IF('FOB'!C22,0,'FOB'!C12),0)+IF('FOB'!C20,0,IF(ISNUMBER('FOB'!C14),'FOB'!C14*'FOB'!C7*0.5,0))+IF('FOB'!C18,0,IF(ISNUMBER('FOB'!C17),'FOB'!C17,IF(ISNUMBER('FOB'!C16),(IF(AND(ISNUMBER('FOB'!C6),ISNUMBER('FOB'!C7*0.5)),'FOB'!C6*'FOB'!C7*0.5,0)+IF('FOB'!C20,0,IF(ISNUMBER('FOB'!C14),'FOB'!C14*'FOB'!C7*0.5,0)))*'FOB'!C16/100*1.1,(IF(AND(ISNUMBER('FOB'!C6),ISNUMBER('FOB'!C7*0.5)),'FOB'!C6*'FOB'!C7*0.5,0)+IF('FOB'!C9=TRUE,0,IF(ISNUMBER('FOB'!C19),'FOB'!C19,0))+IF(ISNUMBER('FOB'!C13),IF('FOB'!C22,0,'FOB'!C13),0)+IF(ISNUMBER('FOB'!C12),IF('FOB'!C22,0,'FOB'!C12),0)+IF('FOB'!C20,0,IF(ISNUMBER('FOB'!C14),'FOB'!C14*'FOB'!C7*0.5,0)))*0.003/0.997))))*IF(ISNUMBER('FOB'!C10),'FOB'!C10,0)+IF(ISNUMBER('FOB'!C11),(IF(AND(ISNUMBER('FOB'!C6),ISNUMBER('FOB'!C7*0.5)),'FOB'!C6*'FOB'!C7*0.5,0)+IF('FOB'!C9=TRUE,0,IF(ISNUMBER('FOB'!C19),'FOB'!C19,0))+IF(ISNUMBER('FOB'!C13),IF('FOB'!C22,0,'FOB'!C13),0)+IF(ISNUMBER('FOB'!C12),IF('FOB'!C22,0,'FOB'!C12),0)+IF('FOB'!C20,0,IF(ISNUMBER('FOB'!C14),'FOB'!C14*'FOB'!C7*0.5,0))+IF('FOB'!C18,0,IF(ISNUMBER('FOB'!C17),'FOB'!C17,IF(ISNUMBER('FOB'!C16),(IF(AND(ISNUMBER('FOB'!C6),ISNUMBER('FOB'!C7*0.5)),'FOB'!C6*'FOB'!C7*0.5,0)+IF('FOB'!C20,0,IF(ISNUMBER('FOB'!C14),'FOB'!C14*'FOB'!C7*0.5,0)))*'FOB'!C16/100*1.1,(IF(AND(ISNUMBER('FOB'!C6),ISNUMBER('FOB'!C7*0.5)),'FOB'!C6*'FOB'!C7*0.5,0)+IF('FOB'!C9=TRUE,0,IF(ISNUMBER('FOB'!C19),'FOB'!C19,0))+IF(ISNUMBER('FOB'!C13),IF('FOB'!C22,0,'FOB'!C13),0)+IF(ISNUMBER('FOB'!C12),IF('FOB'!C22,0,'FOB'!C12),0)+IF('FOB'!C20,0,IF(ISNUMBER('FOB'!C14),'FOB'!C14*'FOB'!C7*0.5,0)))*0.003/0.997))))*'FOB'!C11,0)*IF(ISNUMBER('FOB'!C33),'FOB'!C33,0)*(1+IF(ISNUMBER('FOB'!C34),'FOB'!C34,0))+(IF(ISNUMBER('FOB'!C11),(IF(AND(ISNUMBER('FOB'!C6),ISNUMBER('FOB'!C7*0.5)),'FOB'!C6*'FOB'!C7*0.5,0)+IF('FOB'!C9=TRUE,0,IF(ISNUMBER('FOB'!C19),'FOB'!C19,0))+IF(ISNUMBER('FOB'!C13),IF('FOB'!C22,0,'FOB'!C13),0)+IF(ISNUMBER('FOB'!C12),IF('FOB'!C22,0,'FOB'!C12),0)+IF('FOB'!C20,0,IF(ISNUMBER('FOB'!C14),'FOB'!C14*'FOB'!C7*0.5,0))+IF('FOB'!C18,0,IF(ISNUMBER('FOB'!C17),'FOB'!C17,IF(ISNUMBER('FOB'!C16),(IF(AND(ISNUMBER('FOB'!C6),ISNUMBER('FOB'!C7*0.5)),'FOB'!C6*'FOB'!C7*0.5,0)+IF('FOB'!C20,0,IF(ISNUMBER('FOB'!C14),'FOB'!C14*'FOB'!C7*0.5,0)))*'FOB'!C16/100*1.1,(IF(AND(ISNUMBER('FOB'!C6),ISNUMBER('FOB'!C7*0.5)),'FOB'!C6*'FOB'!C7*0.5,0)+IF('FOB'!C9=TRUE,0,IF(ISNUMBER('FOB'!C19),'FOB'!C19,0))+IF(ISNUMBER('FOB'!C13),IF('FOB'!C22,0,'FOB'!C13),0)+IF(ISNUMBER('FOB'!C12),IF('FOB'!C22,0,'FOB'!C12),0)+IF('FOB'!C20,0,IF(ISNUMBER('FOB'!C14),'FOB'!C14*'FOB'!C7*0.5,0)))*0.003/0.997))))*'FOB'!C11,0)+IF(ISNUMBER('FOB'!C11),(IF(AND(ISNUMBER('FOB'!C6),ISNUMBER('FOB'!C7*0.5)),'FOB'!C6*'FOB'!C7*0.5,0)+IF('FOB'!C9=TRUE,0,IF(ISNUMBER('FOB'!C19),'FOB'!C19,0))+IF(ISNUMBER('FOB'!C13),IF('FOB'!C22,0,'FOB'!C13),0)+IF(ISNUMBER('FOB'!C12),IF('FOB'!C22,0,'FOB'!C12),0)+IF('FOB'!C20,0,IF(ISNUMBER('FOB'!C14),'FOB'!C14*'FOB'!C7*0.5,0))+IF('FOB'!C18,0,IF(ISNUMBER('FOB'!C17),'FOB'!C17,IF(ISNUMBER('FOB'!C16),(IF(AND(ISNUMBER('FOB'!C6),ISNUMBER('FOB'!C7*0.5)),'FOB'!C6*'FOB'!C7*0.5,0)+IF('FOB'!C20,0,IF(ISNUMBER('FOB'!C14),'FOB'!C14*'FOB'!C7*0.5,0)))*'FOB'!C16/100*1.1,(IF(AND(ISNUMBER('FOB'!C6),ISNUMBER('FOB'!C7*0.5)),'FOB'!C6*'FOB'!C7*0.5,0)+IF('FOB'!C9=TRUE,0,IF(ISNUMBER('FOB'!C19),'FOB'!C19,0))+IF(ISNUMBER('FOB'!C13),IF('FOB'!C22,0,'FOB'!C13),0)+IF(ISNUMBER('FOB'!C12),IF('FOB'!C22,0,'FOB'!C12),0)+IF('FOB'!C20,0,IF(ISNUMBER('FOB'!C14),'FOB'!C14*'FOB'!C7*0.5,0)))*0.003/0.997))))*'FOB'!C11,0)*IF(ISNUMBER('FOB'!C33),'FOB'!C33,0)*(1+IF(ISNUMBER('FOB'!C34),'FOB'!C34,0)))*IF(ISNUMBER('FOB'!C35),'FOB'!C35,0)+(IF(ISNUMBER('FOB'!C46),'FOB'!C46,0)+IF(ISNUMBER('FOB'!C47),'FOB'!C47,0)+IF(ISNUMBER('FOB'!C48),'FOB'!C48,0)+IF(ISNUMBER('FOB'!C49),'FOB'!C49,0)+IF(ISNUMBER('FOB'!C50),'FOB'!C50,0)+IF(ISNUMBER('FOB'!C51),'FOB'!C51,0))-IF(LEFT('FOB'!C36,1)="是",(IF(ISNUMBER('FOB'!C11),(IF(AND(ISNUMBER('FOB'!C6),ISNUMBER('FOB'!C7*0.5)),'FOB'!C6*'FOB'!C7*0.5,0)+IF('FOB'!C9=TRUE,0,IF(ISNUMBER('FOB'!C19),'FOB'!C19,0))+IF(ISNUMBER('FOB'!C13),IF('FOB'!C22,0,'FOB'!C13),0)+IF(ISNUMBER('FOB'!C12),IF('FOB'!C22,0,'FOB'!C12),0)+IF('FOB'!C20,0,IF(ISNUMBER('FOB'!C14),'FOB'!C14*'FOB'!C7*0.5,0))+IF('FOB'!C18,0,IF(ISNUMBER('FOB'!C17),'FOB'!C17,IF(ISNUMBER('FOB'!C16),(IF(AND(ISNUMBER('FOB'!C6),ISNUMBER('FOB'!C7*0.5)),'FOB'!C6*'FOB'!C7*0.5,0)+IF('FOB'!C20,0,IF(ISNUMBER('FOB'!C14),'FOB'!C14*'FOB'!C7*0.5,0)))*'FOB'!C16/100*1.1,(IF(AND(ISNUMBER('FOB'!C6),ISNUMBER('FOB'!C7*0.5)),'FOB'!C6*'FOB'!C7*0.5,0)+IF('FOB'!C9=TRUE,0,IF(ISNUMBER('FOB'!C19),'FOB'!C19,0))+IF(ISNUMBER('FOB'!C13),IF('FOB'!C22,0,'FOB'!C13),0)+IF(ISNUMBER('FOB'!C12),IF('FOB'!C22,0,'FOB'!C12),0)+IF('FOB'!C20,0,IF(ISNUMBER('FOB'!C14),'FOB'!C14*'FOB'!C7*0.5,0)))*0.003/0.997))))*'FOB'!C11,0)+IF(ISNUMBER('FOB'!C11),(IF(AND(ISNUMBER('FOB'!C6),ISNUMBER('FOB'!C7*0.5)),'FOB'!C6*'FOB'!C7*0.5,0)+IF('FOB'!C9=TRUE,0,IF(ISNUMBER('FOB'!C19),'FOB'!C19,0))+IF(ISNUMBER('FOB'!C13),IF('FOB'!C22,0,'FOB'!C13),0)+IF(ISNUMBER('FOB'!C12),IF('FOB'!C22,0,'FOB'!C12),0)+IF('FOB'!C20,0,IF(ISNUMBER('FOB'!C14),'FOB'!C14*'FOB'!C7*0.5,0))+IF('FOB'!C18,0,IF(ISNUMBER('FOB'!C17),'FOB'!C17,IF(ISNUMBER('FOB'!C16),(IF(AND(ISNUMBER('FOB'!C6),ISNUMBER('FOB'!C7*0.5)),'FOB'!C6*'FOB'!C7*0.5,0)+IF('FOB'!C20,0,IF(ISNUMBER('FOB'!C14),'FOB'!C14*'FOB'!C7*0.5,0)))*'FOB'!C16/100*1.1,(IF(AND(ISNUMBER('FOB'!C6),ISNUMBER('FOB'!C7*0.5)),'FOB'!C6*'FOB'!C7*0.5,0)+IF('FOB'!C9=TRUE,0,IF(ISNUMBER('FOB'!C19),'FOB'!C19,0))+IF(ISNUMBER('FOB'!C13),IF('FOB'!C22,0,'FOB'!C13),0)+IF(ISNUMBER('FOB'!C12),IF('FOB'!C22,0,'FOB'!C12),0)+IF('FOB'!C20,0,IF(ISNUMBER('FOB'!C14),'FOB'!C14*'FOB'!C7*0.5,0)))*0.003/0.997))))*'FOB'!C11,0)*IF(ISNUMBER('FOB'!C33),'FOB'!C33,0)*(1+IF(ISNUMBER('FOB'!C34),'FOB'!C34,0)))*IF(ISNUMBER('FOB'!C35),'FOB'!C35,0),0))/('FOB'!C7*0.5),"") | E23: =IF(AND(ISNUMBER(D23),ISNUMBER(D4)),D23-D4,"") | F23: =IF(AND(ISNUMBER(E23),ISNUMBER(D4)),E23/D4,"") | G23: 海运费按 USD/MT 随量；港杂/报关/仓储/国内运输按票不随量
B24: 数量 ×0.75 | C24: ='FOB'!C7*0.75 | D24: =IF(AND(ISNUMBER('FOB'!C6),ISNUMBER('FOB'!C7*0.75),ISNUMBER('FOB'!C10),ISNUMBER('FOB'!C11),ISNUMBER('FOB'!C33)),((IF(AND(ISNUMBER('FOB'!C6),ISNUMBER('FOB'!C7*0.75)),'FOB'!C6*'FOB'!C7*0.75,0)+IF('FOB'!C9=TRUE,0,IF(ISNUMBER('FOB'!C19),'FOB'!C19,0))+IF(ISNUMBER('FOB'!C13),IF('FOB'!C22,0,'FOB'!C13),0)+IF(ISNUMBER('FOB'!C12),IF('FOB'!C22,0,'FOB'!C12),0)+IF('FOB'!C20,0,IF(ISNUMBER('FOB'!C14),'FOB'!C14*'FOB'!C7*0.75,0))+IF('FOB'!C18,0,IF(ISNUMBER('FOB'!C17),'FOB'!C17,IF(ISNUMBER('FOB'!C16),(IF(AND(ISNUMBER('FOB'!C6),ISNUMBER('FOB'!C7*0.75)),'FOB'!C6*'FOB'!C7*0.75,0)+IF('FOB'!C20,0,IF(ISNUMBER('FOB'!C14),'FOB'!C14*'FOB'!C7*0.75,0)))*'FOB'!C16/100*1.1,(IF(AND(ISNUMBER('FOB'!C6),ISNUMBER('FOB'!C7*0.75)),'FOB'!C6*'FOB'!C7*0.75,0)+IF('FOB'!C9=TRUE,0,IF(ISNUMBER('FOB'!C19),'FOB'!C19,0))+IF(ISNUMBER('FOB'!C13),IF('FOB'!C22,0,'FOB'!C13),0)+IF(ISNUMBER('FOB'!C12),IF('FOB'!C22,0,'FOB'!C12),0)+IF('FOB'!C20,0,IF(ISNUMBER('FOB'!C14),'FOB'!C14*'FOB'!C7*0.75,0)))*0.003/0.997))))*IF(ISNUMBER('FOB'!C10),'FOB'!C10,0)+IF(ISNUMBER('FOB'!C11),(IF(AND(ISNUMBER('FOB'!C6),ISNUMBER('FOB'!C7*0.75)),'FOB'!C6*'FOB'!C7*0.75,0)+IF('FOB'!C9=TRUE,0,IF(ISNUMBER('FOB'!C19),'FOB'!C19,0))+IF(ISNUMBER('FOB'!C13),IF('FOB'!C22,0,'FOB'!C13),0)+IF(ISNUMBER('FOB'!C12),IF('FOB'!C22,0,'FOB'!C12),0)+IF('FOB'!C20,0,IF(ISNUMBER('FOB'!C14),'FOB'!C14*'FOB'!C7*0.75,0))+IF('FOB'!C18,0,IF(ISNUMBER('FOB'!C17),'FOB'!C17,IF(ISNUMBER('FOB'!C16),(IF(AND(ISNUMBER('FOB'!C6),ISNUMBER('FOB'!C7*0.75)),'FOB'!C6*'FOB'!C7*0.75,0)+IF('FOB'!C20,0,IF(ISNUMBER('FOB'!C14),'FOB'!C14*'FOB'!C7*0.75,0)))*'FOB'!C16/100*1.1,(IF(AND(ISNUMBER('FOB'!C6),ISNUMBER('FOB'!C7*0.75)),'FOB'!C6*'FOB'!C7*0.75,0)+IF('FOB'!C9=TRUE,0,IF(ISNUMBER('FOB'!C19),'FOB'!C19,0))+IF(ISNUMBER('FOB'!C13),IF('FOB'!C22,0,'FOB'!C13),0)+IF(ISNUMBER('FOB'!C12),IF('FOB'!C22,0,'FOB'!C12),0)+IF('FOB'!C20,0,IF(ISNUMBER('FOB'!C14),'FOB'!C14*'FOB'!C7*0.75,0)))*0.003/0.997))))*'FOB'!C11,0)*IF(ISNUMBER('FOB'!C33),'FOB'!C33,0)*(1+IF(ISNUMBER('FOB'!C34),'FOB'!C34,0))+(IF(ISNUMBER('FOB'!C11),(IF(AND(ISNUMBER('FOB'!C6),ISNUMBER('FOB'!C7*0.75)),'FOB'!C6*'FOB'!C7*0.75,0)+IF('FOB'!C9=TRUE,0,IF(ISNUMBER('FOB'!C19),'FOB'!C19,0))+IF(ISNUMBER('FOB'!C13),IF('FOB'!C22,0,'FOB'!C13),0)+IF(ISNUMBER('FOB'!C12),IF('FOB'!C22,0,'FOB'!C12),0)+IF('FOB'!C20,0,IF(ISNUMBER('FOB'!C14),'FOB'!C14*'FOB'!C7*0.75,0))+IF('FOB'!C18,0,IF(ISNUMBER('FOB'!C17),'FOB'!C17,IF(ISNUMBER('FOB'!C16),(IF(AND(ISNUMBER('FOB'!C6),ISNUMBER('FOB'!C7*0.75)),'FOB'!C6*'FOB'!C7*0.75,0)+IF('FOB'!C20,0,IF(ISNUMBER('FOB'!C14),'FOB'!C14*'FOB'!C7*0.75,0)))*'FOB'!C16/100*1.1,(IF(AND(ISNUMBER('FOB'!C6),ISNUMBER('FOB'!C7*0.75)),'FOB'!C6*'FOB'!C7*0.75,0)+IF('FOB'!C9=TRUE,0,IF(ISNUMBER('FOB'!C19),'FOB'!C19,0))+IF(ISNUMBER('FOB'!C13),IF('FOB'!C22,0,'FOB'!C13),0)+IF(ISNUMBER('FOB'!C12),IF('FOB'!C22,0,'FOB'!C12),0)+IF('FOB'!C20,0,IF(ISNUMBER('FOB'!C14),'FOB'!C14*'FOB'!C7*0.75,0)))*0.003/0.997))))*'FOB'!C11,0)+IF(ISNUMBER('FOB'!C11),(IF(AND(ISNUMBER('FOB'!C6),ISNUMBER('FOB'!C7*0.75)),'FOB'!C6*'FOB'!C7*0.75,0)+IF('FOB'!C9=TRUE,0,IF(ISNUMBER('FOB'!C19),'FOB'!C19,0))+IF(ISNUMBER('FOB'!C13),IF('FOB'!C22,0,'FOB'!C13),0)+IF(ISNUMBER('FOB'!C12),IF('FOB'!C22,0,'FOB'!C12),0)+IF('FOB'!C20,0,IF(ISNUMBER('FOB'!C14),'FOB'!C14*'FOB'!C7*0.75,0))+IF('FOB'!C18,0,IF(ISNUMBER('FOB'!C17),'FOB'!C17,IF(ISNUMBER('FOB'!C16),(IF(AND(ISNUMBER('FOB'!C6),ISNUMBER('FOB'!C7*0.75)),'FOB'!C6*'FOB'!C7*0.75,0)+IF('FOB'!C20,0,IF(ISNUMBER('FOB'!C14),'FOB'!C14*'FOB'!C7*0.75,0)))*'FOB'!C16/100*1.1,(IF(AND(ISNUMBER('FOB'!C6),ISNUMBER('FOB'!C7*0.75)),'FOB'!C6*'FOB'!C7*0.75,0)+IF('FOB'!C9=TRUE,0,IF(ISNUMBER('FOB'!C19),'FOB'!C19,0))+IF(ISNUMBER('FOB'!C13),IF('FOB'!C22,0,'FOB'!C13),0)+IF(ISNUMBER('FOB'!C12),IF('FOB'!C22,0,'FOB'!C12),0)+IF('FOB'!C20,0,IF(ISNUMBER('FOB'!C14),'FOB'!C14*'FOB'!C7*0.75,0)))*0.003/0.997))))*'FOB'!C11,0)*IF(ISNUMBER('FOB'!C33),'FOB'!C33,0)*(1+IF(ISNUMBER('FOB'!C34),'FOB'!C34,0)))*IF(ISNUMBER('FOB'!C35),'FOB'!C35,0)+(IF(ISNUMBER('FOB'!C46),'FOB'!C46,0)+IF(ISNUMBER('FOB'!C47),'FOB'!C47,0)+IF(ISNUMBER('FOB'!C48),'FOB'!C48,0)+IF(ISNUMBER('FOB'!C49),'FOB'!C49,0)+IF(ISNUMBER('FOB'!C50),'FOB'!C50,0)+IF(ISNUMBER('FOB'!C51),'FOB'!C51,0))-IF(LEFT('FOB'!C36,1)="是",(IF(ISNUMBER('FOB'!C11),(IF(AND(ISNUMBER('FOB'!C6),ISNUMBER('FOB'!C7*0.75)),'FOB'!C6*'FOB'!C7*0.75,0)+IF('FOB'!C9=TRUE,0,IF(ISNUMBER('FOB'!C19),'FOB'!C19,0))+IF(ISNUMBER('FOB'!C13),IF('FOB'!C22,0,'FOB'!C13),0)+IF(ISNUMBER('FOB'!C12),IF('FOB'!C22,0,'FOB'!C12),0)+IF('FOB'!C20,0,IF(ISNUMBER('FOB'!C14),'FOB'!C14*'FOB'!C7*0.75,0))+IF('FOB'!C18,0,IF(ISNUMBER('FOB'!C17),'FOB'!C17,IF(ISNUMBER('FOB'!C16),(IF(AND(ISNUMBER('FOB'!C6),ISNUMBER('FOB'!C7*0.75)),'FOB'!C6*'FOB'!C7*0.75,0)+IF('FOB'!C20,0,IF(ISNUMBER('FOB'!C14),'FOB'!C14*'FOB'!C7*0.75,0)))*'FOB'!C16/100*1.1,(IF(AND(ISNUMBER('FOB'!C6),ISNUMBER('FOB'!C7*0.75)),'FOB'!C6*'FOB'!C7*0.75,0)+IF('FOB'!C9=TRUE,0,IF(ISNUMBER('FOB'!C19),'FOB'!C19,0))+IF(ISNUMBER('FOB'!C13),IF('FOB'!C22,0,'FOB'!C13),0)+IF(ISNUMBER('FOB'!C12),IF('FOB'!C22,0,'FOB'!C12),0)+IF('FOB'!C20,0,IF(ISNUMBER('FOB'!C14),'FOB'!C14*'FOB'!C7*0.75,0)))*0.003/0.997))))*'FOB'!C11,0)+IF(ISNUMBER('FOB'!C11),(IF(AND(ISNUMBER('FOB'!C6),ISNUMBER('FOB'!C7*0.75)),'FOB'!C6*'FOB'!C7*0.75,0)+IF('FOB'!C9=TRUE,0,IF(ISNUMBER('FOB'!C19),'FOB'!C19,0))+IF(ISNUMBER('FOB'!C13),IF('FOB'!C22,0,'FOB'!C13),0)+IF(ISNUMBER('FOB'!C12),IF('FOB'!C22,0,'FOB'!C12),0)+IF('FOB'!C20,0,IF(ISNUMBER('FOB'!C14),'FOB'!C14*'FOB'!C7*0.75,0))+IF('FOB'!C18,0,IF(ISNUMBER('FOB'!C17),'FOB'!C17,IF(ISNUMBER('FOB'!C16),(IF(AND(ISNUMBER('FOB'!C6),ISNUMBER('FOB'!C7*0.75)),'FOB'!C6*'FOB'!C7*0.75,0)+IF('FOB'!C20,0,IF(ISNUMBER('FOB'!C14),'FOB'!C14*'FOB'!C7*0.75,0)))*'FOB'!C16/100*1.1,(IF(AND(ISNUMBER('FOB'!C6),ISNUMBER('FOB'!C7*0.75)),'FOB'!C6*'FOB'!C7*0.75,0)+IF('FOB'!C9=TRUE,0,IF(ISNUMBER('FOB'!C19),'FOB'!C19,0))+IF(ISNUMBER('FOB'!C13),IF('FOB'!C22,0,'FOB'!C13),0)+IF(ISNUMBER('FOB'!C12),IF('FOB'!C22,0,'FOB'!C12),0)+IF('FOB'!C20,0,IF(ISNUMBER('FOB'!C14),'FOB'!C14*'FOB'!C7*0.75,0)))*0.003/0.997))))*'FOB'!C11,0)*IF(ISNUMBER('FOB'!C33),'FOB'!C33,0)*(1+IF(ISNUMBER('FOB'!C34),'FOB'!C34,0)))*IF(ISNUMBER('FOB'!C35),'FOB'!C35,0),0))/('FOB'!C7*0.75),"") | E24: =IF(AND(ISNUMBER(D24),ISNUMBER(D4)),D24-D4,"") | F24: =IF(AND(ISNUMBER(E24),ISNUMBER(D4)),E24/D4,"")
B25: 数量 ×1 | C25: ='FOB'!C7*1.0 | D25: =IF(AND(ISNUMBER('FOB'!C6),ISNUMBER('FOB'!C7*1.0),ISNUMBER('FOB'!C10),ISNUMBER('FOB'!C11),ISNUMBER('FOB'!C33)),((IF(AND(ISNUMBER('FOB'!C6),ISNUMBER('FOB'!C7*1.0)),'FOB'!C6*'FOB'!C7*1.0,0)+IF('FOB'!C9=TRUE,0,IF(ISNUMBER('FOB'!C19),'FOB'!C19,0))+IF(ISNUMBER('FOB'!C13),IF('FOB'!C22,0,'FOB'!C13),0)+IF(ISNUMBER('FOB'!C12),IF('FOB'!C22,0,'FOB'!C12),0)+IF('FOB'!C20,0,IF(ISNUMBER('FOB'!C14),'FOB'!C14*'FOB'!C7*1.0,0))+IF('FOB'!C18,0,IF(ISNUMBER('FOB'!C17),'FOB'!C17,IF(ISNUMBER('FOB'!C16),(IF(AND(ISNUMBER('FOB'!C6),ISNUMBER('FOB'!C7*1.0)),'FOB'!C6*'FOB'!C7*1.0,0)+IF('FOB'!C20,0,IF(ISNUMBER('FOB'!C14),'FOB'!C14*'FOB'!C7*1.0,0)))*'FOB'!C16/100*1.1,(IF(AND(ISNUMBER('FOB'!C6),ISNUMBER('FOB'!C7*1.0)),'FOB'!C6*'FOB'!C7*1.0,0)+IF('FOB'!C9=TRUE,0,IF(ISNUMBER('FOB'!C19),'FOB'!C19,0))+IF(ISNUMBER('FOB'!C13),IF('FOB'!C22,0,'FOB'!C13),0)+IF(ISNUMBER('FOB'!C12),IF('FOB'!C22,0,'FOB'!C12),0)+IF('FOB'!C20,0,IF(ISNUMBER('FOB'!C14),'FOB'!C14*'FOB'!C7*1.0,0)))*0.003/0.997))))*IF(ISNUMBER('FOB'!C10),'FOB'!C10,0)+IF(ISNUMBER('FOB'!C11),(IF(AND(ISNUMBER('FOB'!C6),ISNUMBER('FOB'!C7*1.0)),'FOB'!C6*'FOB'!C7*1.0,0)+IF('FOB'!C9=TRUE,0,IF(ISNUMBER('FOB'!C19),'FOB'!C19,0))+IF(ISNUMBER('FOB'!C13),IF('FOB'!C22,0,'FOB'!C13),0)+IF(ISNUMBER('FOB'!C12),IF('FOB'!C22,0,'FOB'!C12),0)+IF('FOB'!C20,0,IF(ISNUMBER('FOB'!C14),'FOB'!C14*'FOB'!C7*1.0,0))+IF('FOB'!C18,0,IF(ISNUMBER('FOB'!C17),'FOB'!C17,IF(ISNUMBER('FOB'!C16),(IF(AND(ISNUMBER('FOB'!C6),ISNUMBER('FOB'!C7*1.0)),'FOB'!C6*'FOB'!C7*1.0,0)+IF('FOB'!C20,0,IF(ISNUMBER('FOB'!C14),'FOB'!C14*'FOB'!C7*1.0,0)))*'FOB'!C16/100*1.1,(IF(AND(ISNUMBER('FOB'!C6),ISNUMBER('FOB'!C7*1.0)),'FOB'!C6*'FOB'!C7*1.0,0)+IF('FOB'!C9=TRUE,0,IF(ISNUMBER('FOB'!C19),'FOB'!C19,0))+IF(ISNUMBER('FOB'!C13),IF('FOB'!C22,0,'FOB'!C13),0)+IF(ISNUMBER('FOB'!C12),IF('FOB'!C22,0,'FOB'!C12),0)+IF('FOB'!C20,0,IF(ISNUMBER('FOB'!C14),'FOB'!C14*'FOB'!C7*1.0,0)))*0.003/0.997))))*'FOB'!C11,0)*IF(ISNUMBER('FOB'!C33),'FOB'!C33,0)*(1+IF(ISNUMBER('FOB'!C34),'FOB'!C34,0))+(IF(ISNUMBER('FOB'!C11),(IF(AND(ISNUMBER('FOB'!C6),ISNUMBER('FOB'!C7*1.0)),'FOB'!C6*'FOB'!C7*1.0,0)+IF('FOB'!C9=TRUE,0,IF(ISNUMBER('FOB'!C19),'FOB'!C19,0))+IF(ISNUMBER('FOB'!C13),IF('FOB'!C22,0,'FOB'!C13),0)+IF(ISNUMBER('FOB'!C12),IF('FOB'!C22,0,'FOB'!C12),0)+IF('FOB'!C20,0,IF(ISNUMBER('FOB'!C14),'FOB'!C14*'FOB'!C7*1.0,0))+IF('FOB'!C18,0,IF(ISNUMBER('FOB'!C17),'FOB'!C17,IF(ISNUMBER('FOB'!C16),(IF(AND(ISNUMBER('FOB'!C6),ISNUMBER('FOB'!C7*1.0)),'FOB'!C6*'FOB'!C7*1.0,0)+IF('FOB'!C20,0,IF(ISNUMBER('FOB'!C14),'FOB'!C14*'FOB'!C7*1.0,0)))*'FOB'!C16/100*1.1,(IF(AND(ISNUMBER('FOB'!C6),ISNUMBER('FOB'!C7*1.0)),'FOB'!C6*'FOB'!C7*1.0,0)+IF('FOB'!C9=TRUE,0,IF(ISNUMBER('FOB'!C19),'FOB'!C19,0))+IF(ISNUMBER('FOB'!C13),IF('FOB'!C22,0,'FOB'!C13),0)+IF(ISNUMBER('FOB'!C12),IF('FOB'!C22,0,'FOB'!C12),0)+IF('FOB'!C20,0,IF(ISNUMBER('FOB'!C14),'FOB'!C14*'FOB'!C7*1.0,0)))*0.003/0.997))))*'FOB'!C11,0)+IF(ISNUMBER('FOB'!C11),(IF(AND(ISNUMBER('FOB'!C6),ISNUMBER('FOB'!C7*1.0)),'FOB'!C6*'FOB'!C7*1.0,0)+IF('FOB'!C9=TRUE,0,IF(ISNUMBER('FOB'!C19),'FOB'!C19,0))+IF(ISNUMBER('FOB'!C13),IF('FOB'!C22,0,'FOB'!C13),0)+IF(ISNUMBER('FOB'!C12),IF('FOB'!C22,0,'FOB'!C12),0)+IF('FOB'!C20,0,IF(ISNUMBER('FOB'!C14),'FOB'!C14*'FOB'!C7*1.0,0))+IF('FOB'!C18,0,IF(ISNUMBER('FOB'!C17),'FOB'!C17,IF(ISNUMBER('FOB'!C16),(IF(AND(ISNUMBER('FOB'!C6),ISNUMBER('FOB'!C7*1.0)),'FOB'!C6*'FOB'!C7*1.0,0)+IF('FOB'!C20,0,IF(ISNUMBER('FOB'!C14),'FOB'!C14*'FOB'!C7*1.0,0)))*'FOB'!C16/100*1.1,(IF(AND(ISNUMBER('FOB'!C6),ISNUMBER('FOB'!C7*1.0)),'FOB'!C6*'FOB'!C7*1.0,0)+IF('FOB'!C9=TRUE,0,IF(ISNUMBER('FOB'!C19),'FOB'!C19,0))+IF(ISNUMBER('FOB'!C13),IF('FOB'!C22,0,'FOB'!C13),0)+IF(ISNUMBER('FOB'!C12),IF('FOB'!C22,0,'FOB'!C12),0)+IF('FOB'!C20,0,IF(ISNUMBER('FOB'!C14),'FOB'!C14*'FOB'!C7*1.0,0)))*0.003/0.997))))*'FOB'!C11,0)*IF(ISNUMBER('FOB'!C33),'FOB'!C33,0)*(1+IF(ISNUMBER('FOB'!C34),'FOB'!C34,0)))*IF(ISNUMBER('FOB'!C35),'FOB'!C35,0)+(IF(ISNUMBER('FOB'!C46),'FOB'!C46,0)+IF(ISNUMBER('FOB'!C47),'FOB'!C47,0)+IF(ISNUMBER('FOB'!C48),'FOB'!C48,0)+IF(ISNUMBER('FOB'!C49),'FOB'!C49,0)+IF(ISNUMBER('FOB'!C50),'FOB'!C50,0)+IF(ISNUMBER('FOB'!C51),'FOB'!C51,0))-IF(LEFT('FOB'!C36,1)="是",(IF(ISNUMBER('FOB'!C11),(IF(AND(ISNUMBER('FOB'!C6),ISNUMBER('FOB'!C7*1.0)),'FOB'!C6*'FOB'!C7*1.0,0)+IF('FOB'!C9=TRUE,0,IF(ISNUMBER('FOB'!C19),'FOB'!C19,0))+IF(ISNUMBER('FOB'!C13),IF('FOB'!C22,0,'FOB'!C13),0)+IF(ISNUMBER('FOB'!C12),IF('FOB'!C22,0,'FOB'!C12),0)+IF('FOB'!C20,0,IF(ISNUMBER('FOB'!C14),'FOB'!C14*'FOB'!C7*1.0,0))+IF('FOB'!C18,0,IF(ISNUMBER('FOB'!C17),'FOB'!C17,IF(ISNUMBER('FOB'!C16),(IF(AND(ISNUMBER('FOB'!C6),ISNUMBER('FOB'!C7*1.0)),'FOB'!C6*'FOB'!C7*1.0,0)+IF('FOB'!C20,0,IF(ISNUMBER('FOB'!C14),'FOB'!C14*'FOB'!C7*1.0,0)))*'FOB'!C16/100*1.1,(IF(AND(ISNUMBER('FOB'!C6),ISNUMBER('FOB'!C7*1.0)),'FOB'!C6*'FOB'!C7*1.0,0)+IF('FOB'!C9=TRUE,0,IF(ISNUMBER('FOB'!C19),'FOB'!C19,0))+IF(ISNUMBER('FOB'!C13),IF('FOB'!C22,0,'FOB'!C13),0)+IF(ISNUMBER('FOB'!C12),IF('FOB'!C22,0,'FOB'!C12),0)+IF('FOB'!C20,0,IF(ISNUMBER('FOB'!C14),'FOB'!C14*'FOB'!C7*1.0,0)))*0.003/0.997))))*'FOB'!C11,0)+IF(ISNUMBER('FOB'!C11),(IF(AND(ISNUMBER('FOB'!C6),ISNUMBER('FOB'!C7*1.0)),'FOB'!C6*'FOB'!C7*1.0,0)+IF('FOB'!C9=TRUE,0,IF(ISNUMBER('FOB'!C19),'FOB'!C19,0))+IF(ISNUMBER('FOB'!C13),IF('FOB'!C22,0,'FOB'!C13),0)+IF(ISNUMBER('FOB'!C12),IF('FOB'!C22,0,'FOB'!C12),0)+IF('FOB'!C20,0,IF(ISNUMBER('FOB'!C14),'FOB'!C14*'FOB'!C7*1.0,0))+IF('FOB'!C18,0,IF(ISNUMBER('FOB'!C17),'FOB'!C17,IF(ISNUMBER('FOB'!C16),(IF(AND(ISNUMBER('FOB'!C6),ISNUMBER('FOB'!C7*1.0)),'FOB'!C6*'FOB'!C7*1.0,0)+IF('FOB'!C20,0,IF(ISNUMBER('FOB'!C14),'FOB'!C14*'FOB'!C7*1.0,0)))*'FOB'!C16/100*1.1,(IF(AND(ISNUMBER('FOB'!C6),ISNUMBER('FOB'!C7*1.0)),'FOB'!C6*'FOB'!C7*1.0,0)+IF('FOB'!C9=TRUE,0,IF(ISNUMBER('FOB'!C19),'FOB'!C19,0))+IF(ISNUMBER('FOB'!C13),IF('FOB'!C22,0,'FOB'!C13),0)+IF(ISNUMBER('FOB'!C12),IF('FOB'!C22,0,'FOB'!C12),0)+IF('FOB'!C20,0,IF(ISNUMBER('FOB'!C14),'FOB'!C14*'FOB'!C7*1.0,0)))*0.003/0.997))))*'FOB'!C11,0)*IF(ISNUMBER('FOB'!C33),'FOB'!C33,0)*(1+IF(ISNUMBER('FOB'!C34),'FOB'!C34,0)))*IF(ISNUMBER('FOB'!C35),'FOB'!C35,0),0))/('FOB'!C7*1.0),"") | E25: =IF(AND(ISNUMBER(D25),ISNUMBER(D4)),D25-D4,"") | F25: =IF(AND(ISNUMBER(E25),ISNUMBER(D4)),E25/D4,"")
B26: 数量 ×1.5 | C26: ='FOB'!C7*1.5 | D26: =IF(AND(ISNUMBER('FOB'!C6),ISNUMBER('FOB'!C7*1.5),ISNUMBER('FOB'!C10),ISNUMBER('FOB'!C11),ISNUMBER('FOB'!C33)),((IF(AND(ISNUMBER('FOB'!C6),ISNUMBER('FOB'!C7*1.5)),'FOB'!C6*'FOB'!C7*1.5,0)+IF('FOB'!C9=TRUE,0,IF(ISNUMBER('FOB'!C19),'FOB'!C19,0))+IF(ISNUMBER('FOB'!C13),IF('FOB'!C22,0,'FOB'!C13),0)+IF(ISNUMBER('FOB'!C12),IF('FOB'!C22,0,'FOB'!C12),0)+IF('FOB'!C20,0,IF(ISNUMBER('FOB'!C14),'FOB'!C14*'FOB'!C7*1.5,0))+IF('FOB'!C18,0,IF(ISNUMBER('FOB'!C17),'FOB'!C17,IF(ISNUMBER('FOB'!C16),(IF(AND(ISNUMBER('FOB'!C6),ISNUMBER('FOB'!C7*1.5)),'FOB'!C6*'FOB'!C7*1.5,0)+IF('FOB'!C20,0,IF(ISNUMBER('FOB'!C14),'FOB'!C14*'FOB'!C7*1.5,0)))*'FOB'!C16/100*1.1,(IF(AND(ISNUMBER('FOB'!C6),ISNUMBER('FOB'!C7*1.5)),'FOB'!C6*'FOB'!C7*1.5,0)+IF('FOB'!C9=TRUE,0,IF(ISNUMBER('FOB'!C19),'FOB'!C19,0))+IF(ISNUMBER('FOB'!C13),IF('FOB'!C22,0,'FOB'!C13),0)+IF(ISNUMBER('FOB'!C12),IF('FOB'!C22,0,'FOB'!C12),0)+IF('FOB'!C20,0,IF(ISNUMBER('FOB'!C14),'FOB'!C14*'FOB'!C7*1.5,0)))*0.003/0.997))))*IF(ISNUMBER('FOB'!C10),'FOB'!C10,0)+IF(ISNUMBER('FOB'!C11),(IF(AND(ISNUMBER('FOB'!C6),ISNUMBER('FOB'!C7*1.5)),'FOB'!C6*'FOB'!C7*1.5,0)+IF('FOB'!C9=TRUE,0,IF(ISNUMBER('FOB'!C19),'FOB'!C19,0))+IF(ISNUMBER('FOB'!C13),IF('FOB'!C22,0,'FOB'!C13),0)+IF(ISNUMBER('FOB'!C12),IF('FOB'!C22,0,'FOB'!C12),0)+IF('FOB'!C20,0,IF(ISNUMBER('FOB'!C14),'FOB'!C14*'FOB'!C7*1.5,0))+IF('FOB'!C18,0,IF(ISNUMBER('FOB'!C17),'FOB'!C17,IF(ISNUMBER('FOB'!C16),(IF(AND(ISNUMBER('FOB'!C6),ISNUMBER('FOB'!C7*1.5)),'FOB'!C6*'FOB'!C7*1.5,0)+IF('FOB'!C20,0,IF(ISNUMBER('FOB'!C14),'FOB'!C14*'FOB'!C7*1.5,0)))*'FOB'!C16/100*1.1,(IF(AND(ISNUMBER('FOB'!C6),ISNUMBER('FOB'!C7*1.5)),'FOB'!C6*'FOB'!C7*1.5,0)+IF('FOB'!C9=TRUE,0,IF(ISNUMBER('FOB'!C19),'FOB'!C19,0))+IF(ISNUMBER('FOB'!C13),IF('FOB'!C22,0,'FOB'!C13),0)+IF(ISNUMBER('FOB'!C12),IF('FOB'!C22,0,'FOB'!C12),0)+IF('FOB'!C20,0,IF(ISNUMBER('FOB'!C14),'FOB'!C14*'FOB'!C7*1.5,0)))*0.003/0.997))))*'FOB'!C11,0)*IF(ISNUMBER('FOB'!C33),'FOB'!C33,0)*(1+IF(ISNUMBER('FOB'!C34),'FOB'!C34,0))+(IF(ISNUMBER('FOB'!C11),(IF(AND(ISNUMBER('FOB'!C6),ISNUMBER('FOB'!C7*1.5)),'FOB'!C6*'FOB'!C7*1.5,0)+IF('FOB'!C9=TRUE,0,IF(ISNUMBER('FOB'!C19),'FOB'!C19,0))+IF(ISNUMBER('FOB'!C13),IF('FOB'!C22,0,'FOB'!C13),0)+IF(ISNUMBER('FOB'!C12),IF('FOB'!C22,0,'FOB'!C12),0)+IF('FOB'!C20,0,IF(ISNUMBER('FOB'!C14),'FOB'!C14*'FOB'!C7*1.5,0))+IF('FOB'!C18,0,IF(ISNUMBER('FOB'!C17),'FOB'!C17,IF(ISNUMBER('FOB'!C16),(IF(AND(ISNUMBER('FOB'!C6),ISNUMBER('FOB'!C7*1.5)),'FOB'!C6*'FOB'!C7*1.5,0)+IF('FOB'!C20,0,IF(ISNUMBER('FOB'!C14),'FOB'!C14*'FOB'!C7*1.5,0)))*'FOB'!C16/100*1.1,(IF(AND(ISNUMBER('FOB'!C6),ISNUMBER('FOB'!C7*1.5)),'FOB'!C6*'FOB'!C7*1.5,0)+IF('FOB'!C9=TRUE,0,IF(ISNUMBER('FOB'!C19),'FOB'!C19,0))+IF(ISNUMBER('FOB'!C13),IF('FOB'!C22,0,'FOB'!C13),0)+IF(ISNUMBER('FOB'!C12),IF('FOB'!C22,0,'FOB'!C12),0)+IF('FOB'!C20,0,IF(ISNUMBER('FOB'!C14),'FOB'!C14*'FOB'!C7*1.5,0)))*0.003/0.997))))*'FOB'!C11,0)+IF(ISNUMBER('FOB'!C11),(IF(AND(ISNUMBER('FOB'!C6),ISNUMBER('FOB'!C7*1.5)),'FOB'!C6*'FOB'!C7*1.5,0)+IF('FOB'!C9=TRUE,0,IF(ISNUMBER('FOB'!C19),'FOB'!C19,0))+IF(ISNUMBER('FOB'!C13),IF('FOB'!C22,0,'FOB'!C13),0)+IF(ISNUMBER('FOB'!C12),IF('FOB'!C22,0,'FOB'!C12),0)+IF('FOB'!C20,0,IF(ISNUMBER('FOB'!C14),'FOB'!C14*'FOB'!C7*1.5,0))+IF('FOB'!C18,0,IF(ISNUMBER('FOB'!C17),'FOB'!C17,IF(ISNUMBER('FOB'!C16),(IF(AND(ISNUMBER('FOB'!C6),ISNUMBER('FOB'!C7*1.5)),'FOB'!C6*'FOB'!C7*1.5,0)+IF('FOB'!C20,0,IF(ISNUMBER('FOB'!C14),'FOB'!C14*'FOB'!C7*1.5,0)))*'FOB'!C16/100*1.1,(IF(AND(ISNUMBER('FOB'!C6),ISNUMBER('FOB'!C7*1.5)),'FOB'!C6*'FOB'!C7*1.5,0)+IF('FOB'!C9=TRUE,0,IF(ISNUMBER('FOB'!C19),'FOB'!C19,0))+IF(ISNUMBER('FOB'!C13),IF('FOB'!C22,0,'FOB'!C13),0)+IF(ISNUMBER('FOB'!C12),IF('FOB'!C22,0,'FOB'!C12),0)+IF('FOB'!C20,0,IF(ISNUMBER('FOB'!C14),'FOB'!C14*'FOB'!C7*1.5,0)))*0.003/0.997))))*'FOB'!C11,0)*IF(ISNUMBER('FOB'!C33),'FOB'!C33,0)*(1+IF(ISNUMBER('FOB'!C34),'FOB'!C34,0)))*IF(ISNUMBER('FOB'!C35),'FOB'!C35,0)+(IF(ISNUMBER('FOB'!C46),'FOB'!C46,0)+IF(ISNUMBER('FOB'!C47),'FOB'!C47,0)+IF(ISNUMBER('FOB'!C48),'FOB'!C48,0)+IF(ISNUMBER('FOB'!C49),'FOB'!C49,0)+IF(ISNUMBER('FOB'!C50),'FOB'!C50,0)+IF(ISNUMBER('FOB'!C51),'FOB'!C51,0))-IF(LEFT('FOB'!C36,1)="是",(IF(ISNUMBER('FOB'!C11),(IF(AND(ISNUMBER('FOB'!C6),ISNUMBER('FOB'!C7*1.5)),'FOB'!C6*'FOB'!C7*1.5,0)+IF('FOB'!C9=TRUE,0,IF(ISNUMBER('FOB'!C19),'FOB'!C19,0))+IF(ISNUMBER('FOB'!C13),IF('FOB'!C22,0,'FOB'!C13),0)+IF(ISNUMBER('FOB'!C12),IF('FOB'!C22,0,'FOB'!C12),0)+IF('FOB'!C20,0,IF(ISNUMBER('FOB'!C14),'FOB'!C14*'FOB'!C7*1.5,0))+IF('FOB'!C18,0,IF(ISNUMBER('FOB'!C17),'FOB'!C17,IF(ISNUMBER('FOB'!C16),(IF(AND(ISNUMBER('FOB'!C6),ISNUMBER('FOB'!C7*1.5)),'FOB'!C6*'FOB'!C7*1.5,0)+IF('FOB'!C20,0,IF(ISNUMBER('FOB'!C14),'FOB'!C14*'FOB'!C7*1.5,0)))*'FOB'!C16/100*1.1,(IF(AND(ISNUMBER('FOB'!C6),ISNUMBER('FOB'!C7*1.5)),'FOB'!C6*'FOB'!C7*1.5,0)+IF('FOB'!C9=TRUE,0,IF(ISNUMBER('FOB'!C19),'FOB'!C19,0))+IF(ISNUMBER('FOB'!C13),IF('FOB'!C22,0,'FOB'!C13),0)+IF(ISNUMBER('FOB'!C12),IF('FOB'!C22,0,'FOB'!C12),0)+IF('FOB'!C20,0,IF(ISNUMBER('FOB'!C14),'FOB'!C14*'FOB'!C7*1.5,0)))*0.003/0.997))))*'FOB'!C11,0)+IF(ISNUMBER('FOB'!C11),(IF(AND(ISNUMBER('FOB'!C6),ISNUMBER('FOB'!C7*1.5)),'FOB'!C6*'FOB'!C7*1.5,0)+IF('FOB'!C9=TRUE,0,IF(ISNUMBER('FOB'!C19),'FOB'!C19,0))+IF(ISNUMBER('FOB'!C13),IF('FOB'!C22,0,'FOB'!C13),0)+IF(ISNUMBER('FOB'!C12),IF('FOB'!C22,0,'FOB'!C12),0)+IF('FOB'!C20,0,IF(ISNUMBER('FOB'!C14),'FOB'!C14*'FOB'!C7*1.5,0))+IF('FOB'!C18,0,IF(ISNUMBER('FOB'!C17),'FOB'!C17,IF(ISNUMBER('FOB'!C16),(IF(AND(ISNUMBER('FOB'!C6),ISNUMBER('FOB'!C7*1.5)),'FOB'!C6*'FOB'!C7*1.5,0)+IF('FOB'!C20,0,IF(ISNUMBER('FOB'!C14),'FOB'!C14*'FOB'!C7*1.5,0)))*'FOB'!C16/100*1.1,(IF(AND(ISNUMBER('FOB'!C6),ISNUMBER('FOB'!C7*1.5)),'FOB'!C6*'FOB'!C7*1.5,0)+IF('FOB'!C9=TRUE,0,IF(ISNUMBER('FOB'!C19),'FOB'!C19,0))+IF(ISNUMBER('FOB'!C13),IF('FOB'!C22,0,'FOB'!C13),0)+IF(ISNUMBER('FOB'!C12),IF('FOB'!C22,0,'FOB'!C12),0)+IF('FOB'!C20,0,IF(ISNUMBER('FOB'!C14),'FOB'!C14*'FOB'!C7*1.5,0)))*0.003/0.997))))*'FOB'!C11,0)*IF(ISNUMBER('FOB'!C33),'FOB'!C33,0)*(1+IF(ISNUMBER('FOB'!C34),'FOB'!C34,0)))*IF(ISNUMBER('FOB'!C35),'FOB'!C35,0),0))/('FOB'!C7*1.5),"") | E26: =IF(AND(ISNUMBER(D26),ISNUMBER(D4)),D26-D4,"") | F26: =IF(AND(ISNUMBER(E26),ISNUMBER(D4)),E26/D4,"")
B27: 数量 ×2 | C27: ='FOB'!C7*2.0 | D27: =IF(AND(ISNUMBER('FOB'!C6),ISNUMBER('FOB'!C7*2.0),ISNUMBER('FOB'!C10),ISNUMBER('FOB'!C11),ISNUMBER('FOB'!C33)),((IF(AND(ISNUMBER('FOB'!C6),ISNUMBER('FOB'!C7*2.0)),'FOB'!C6*'FOB'!C7*2.0,0)+IF('FOB'!C9=TRUE,0,IF(ISNUMBER('FOB'!C19),'FOB'!C19,0))+IF(ISNUMBER('FOB'!C13),IF('FOB'!C22,0,'FOB'!C13),0)+IF(ISNUMBER('FOB'!C12),IF('FOB'!C22,0,'FOB'!C12),0)+IF('FOB'!C20,0,IF(ISNUMBER('FOB'!C14),'FOB'!C14*'FOB'!C7*2.0,0))+IF('FOB'!C18,0,IF(ISNUMBER('FOB'!C17),'FOB'!C17,IF(ISNUMBER('FOB'!C16),(IF(AND(ISNUMBER('FOB'!C6),ISNUMBER('FOB'!C7*2.0)),'FOB'!C6*'FOB'!C7*2.0,0)+IF('FOB'!C20,0,IF(ISNUMBER('FOB'!C14),'FOB'!C14*'FOB'!C7*2.0,0)))*'FOB'!C16/100*1.1,(IF(AND(ISNUMBER('FOB'!C6),ISNUMBER('FOB'!C7*2.0)),'FOB'!C6*'FOB'!C7*2.0,0)+IF('FOB'!C9=TRUE,0,IF(ISNUMBER('FOB'!C19),'FOB'!C19,0))+IF(ISNUMBER('FOB'!C13),IF('FOB'!C22,0,'FOB'!C13),0)+IF(ISNUMBER('FOB'!C12),IF('FOB'!C22,0,'FOB'!C12),0)+IF('FOB'!C20,0,IF(ISNUMBER('FOB'!C14),'FOB'!C14*'FOB'!C7*2.0,0)))*0.003/0.997))))*IF(ISNUMBER('FOB'!C10),'FOB'!C10,0)+IF(ISNUMBER('FOB'!C11),(IF(AND(ISNUMBER('FOB'!C6),ISNUMBER('FOB'!C7*2.0)),'FOB'!C6*'FOB'!C7*2.0,0)+IF('FOB'!C9=TRUE,0,IF(ISNUMBER('FOB'!C19),'FOB'!C19,0))+IF(ISNUMBER('FOB'!C13),IF('FOB'!C22,0,'FOB'!C13),0)+IF(ISNUMBER('FOB'!C12),IF('FOB'!C22,0,'FOB'!C12),0)+IF('FOB'!C20,0,IF(ISNUMBER('FOB'!C14),'FOB'!C14*'FOB'!C7*2.0,0))+IF('FOB'!C18,0,IF(ISNUMBER('FOB'!C17),'FOB'!C17,IF(ISNUMBER('FOB'!C16),(IF(AND(ISNUMBER('FOB'!C6),ISNUMBER('FOB'!C7*2.0)),'FOB'!C6*'FOB'!C7*2.0,0)+IF('FOB'!C20,0,IF(ISNUMBER('FOB'!C14),'FOB'!C14*'FOB'!C7*2.0,0)))*'FOB'!C16/100*1.1,(IF(AND(ISNUMBER('FOB'!C6),ISNUMBER('FOB'!C7*2.0)),'FOB'!C6*'FOB'!C7*2.0,0)+IF('FOB'!C9=TRUE,0,IF(ISNUMBER('FOB'!C19),'FOB'!C19,0))+IF(ISNUMBER('FOB'!C13),IF('FOB'!C22,0,'FOB'!C13),0)+IF(ISNUMBER('FOB'!C12),IF('FOB'!C22,0,'FOB'!C12),0)+IF('FOB'!C20,0,IF(ISNUMBER('FOB'!C14),'FOB'!C14*'FOB'!C7*2.0,0)))*0.003/0.997))))*'FOB'!C11,0)*IF(ISNUMBER('FOB'!C33),'FOB'!C33,0)*(1+IF(ISNUMBER('FOB'!C34),'FOB'!C34,0))+(IF(ISNUMBER('FOB'!C11),(IF(AND(ISNUMBER('FOB'!C6),ISNUMBER('FOB'!C7*2.0)),'FOB'!C6*'FOB'!C7*2.0,0)+IF('FOB'!C9=TRUE,0,IF(ISNUMBER('FOB'!C19),'FOB'!C19,0))+IF(ISNUMBER('FOB'!C13),IF('FOB'!C22,0,'FOB'!C13),0)+IF(ISNUMBER('FOB'!C12),IF('FOB'!C22,0,'FOB'!C12),0)+IF('FOB'!C20,0,IF(ISNUMBER('FOB'!C14),'FOB'!C14*'FOB'!C7*2.0,0))+IF('FOB'!C18,0,IF(ISNUMBER('FOB'!C17),'FOB'!C17,IF(ISNUMBER('FOB'!C16),(IF(AND(ISNUMBER('FOB'!C6),ISNUMBER('FOB'!C7*2.0)),'FOB'!C6*'FOB'!C7*2.0,0)+IF('FOB'!C20,0,IF(ISNUMBER('FOB'!C14),'FOB'!C14*'FOB'!C7*2.0,0)))*'FOB'!C16/100*1.1,(IF(AND(ISNUMBER('FOB'!C6),ISNUMBER('FOB'!C7*2.0)),'FOB'!C6*'FOB'!C7*2.0,0)+IF('FOB'!C9=TRUE,0,IF(ISNUMBER('FOB'!C19),'FOB'!C19,0))+IF(ISNUMBER('FOB'!C13),IF('FOB'!C22,0,'FOB'!C13),0)+IF(ISNUMBER('FOB'!C12),IF('FOB'!C22,0,'FOB'!C12),0)+IF('FOB'!C20,0,IF(ISNUMBER('FOB'!C14),'FOB'!C14*'FOB'!C7*2.0,0)))*0.003/0.997))))*'FOB'!C11,0)+IF(ISNUMBER('FOB'!C11),(IF(AND(ISNUMBER('FOB'!C6),ISNUMBER('FOB'!C7*2.0)),'FOB'!C6*'FOB'!C7*2.0,0)+IF('FOB'!C9=TRUE,0,IF(ISNUMBER('FOB'!C19),'FOB'!C19,0))+IF(ISNUMBER('FOB'!C13),IF('FOB'!C22,0,'FOB'!C13),0)+IF(ISNUMBER('FOB'!C12),IF('FOB'!C22,0,'FOB'!C12),0)+IF('FOB'!C20,0,IF(ISNUMBER('FOB'!C14),'FOB'!C14*'FOB'!C7*2.0,0))+IF('FOB'!C18,0,IF(ISNUMBER('FOB'!C17),'FOB'!C17,IF(ISNUMBER('FOB'!C16),(IF(AND(ISNUMBER('FOB'!C6),ISNUMBER('FOB'!C7*2.0)),'FOB'!C6*'FOB'!C7*2.0,0)+IF('FOB'!C20,0,IF(ISNUMBER('FOB'!C14),'FOB'!C14*'FOB'!C7*2.0,0)))*'FOB'!C16/100*1.1,(IF(AND(ISNUMBER('FOB'!C6),ISNUMBER('FOB'!C7*2.0)),'FOB'!C6*'FOB'!C7*2.0,0)+IF('FOB'!C9=TRUE,0,IF(ISNUMBER('FOB'!C19),'FOB'!C19,0))+IF(ISNUMBER('FOB'!C13),IF('FOB'!C22,0,'FOB'!C13),0)+IF(ISNUMBER('FOB'!C12),IF('FOB'!C22,0,'FOB'!C12),0)+IF('FOB'!C20,0,IF(ISNUMBER('FOB'!C14),'FOB'!C14*'FOB'!C7*2.0,0)))*0.003/0.997))))*'FOB'!C11,0)*IF(ISNUMBER('FOB'!C33),'FOB'!C33,0)*(1+IF(ISNUMBER('FOB'!C34),'FOB'!C34,0)))*IF(ISNUMBER('FOB'!C35),'FOB'!C35,0)+(IF(ISNUMBER('FOB'!C46),'FOB'!C46,0)+IF(ISNUMBER('FOB'!C47),'FOB'!C47,0)+IF(ISNUMBER('FOB'!C48),'FOB'!C48,0)+IF(ISNUMBER('FOB'!C49),'FOB'!C49,0)+IF(ISNUMBER('FOB'!C50),'FOB'!C50,0)+IF(ISNUMBER('FOB'!C51),'FOB'!C51,0))-IF(LEFT('FOB'!C36,1)="是",(IF(ISNUMBER('FOB'!C11),(IF(AND(ISNUMBER('FOB'!C6),ISNUMBER('FOB'!C7*2.0)),'FOB'!C6*'FOB'!C7*2.0,0)+IF('FOB'!C9=TRUE,0,IF(ISNUMBER('FOB'!C19),'FOB'!C19,0))+IF(ISNUMBER('FOB'!C13),IF('FOB'!C22,0,'FOB'!C13),0)+IF(ISNUMBER('FOB'!C12),IF('FOB'!C22,0,'FOB'!C12),0)+IF('FOB'!C20,0,IF(ISNUMBER('FOB'!C14),'FOB'!C14*'FOB'!C7*2.0,0))+IF('FOB'!C18,0,IF(ISNUMBER('FOB'!C17),'FOB'!C17,IF(ISNUMBER('FOB'!C16),(IF(AND(ISNUMBER('FOB'!C6),ISNUMBER('FOB'!C7*2.0)),'FOB'!C6*'FOB'!C7*2.0,0)+IF('FOB'!C20,0,IF(ISNUMBER('FOB'!C14),'FOB'!C14*'FOB'!C7*2.0,0)))*'FOB'!C16/100*1.1,(IF(AND(ISNUMBER('FOB'!C6),ISNUMBER('FOB'!C7*2.0)),'FOB'!C6*'FOB'!C7*2.0,0)+IF('FOB'!C9=TRUE,0,IF(ISNUMBER('FOB'!C19),'FOB'!C19,0))+IF(ISNUMBER('FOB'!C13),IF('FOB'!C22,0,'FOB'!C13),0)+IF(ISNUMBER('FOB'!C12),IF('FOB'!C22,0,'FOB'!C12),0)+IF('FOB'!C20,0,IF(ISNUMBER('FOB'!C14),'FOB'!C14*'FOB'!C7*2.0,0)))*0.003/0.997))))*'FOB'!C11,0)+IF(ISNUMBER('FOB'!C11),(IF(AND(ISNUMBER('FOB'!C6),ISNUMBER('FOB'!C7*2.0)),'FOB'!C6*'FOB'!C7*2.0,0)+IF('FOB'!C9=TRUE,0,IF(ISNUMBER('FOB'!C19),'FOB'!C19,0))+IF(ISNUMBER('FOB'!C13),IF('FOB'!C22,0,'FOB'!C13),0)+IF(ISNUMBER('FOB'!C12),IF('FOB'!C22,0,'FOB'!C12),0)+IF('FOB'!C20,0,IF(ISNUMBER('FOB'!C14),'FOB'!C14*'FOB'!C7*2.0,0))+IF('FOB'!C18,0,IF(ISNUMBER('FOB'!C17),'FOB'!C17,IF(ISNUMBER('FOB'!C16),(IF(AND(ISNUMBER('FOB'!C6),ISNUMBER('FOB'!C7*2.0)),'FOB'!C6*'FOB'!C7*2.0,0)+IF('FOB'!C20,0,IF(ISNUMBER('FOB'!C14),'FOB'!C14*'FOB'!C7*2.0,0)))*'FOB'!C16/100*1.1,(IF(AND(ISNUMBER('FOB'!C6),ISNUMBER('FOB'!C7*2.0)),'FOB'!C6*'FOB'!C7*2.0,0)+IF('FOB'!C9=TRUE,0,IF(ISNUMBER('FOB'!C19),'FOB'!C19,0))+IF(ISNUMBER('FOB'!C13),IF('FOB'!C22,0,'FOB'!C13),0)+IF(ISNUMBER('FOB'!C12),IF('FOB'!C22,0,'FOB'!C12),0)+IF('FOB'!C20,0,IF(ISNUMBER('FOB'!C14),'FOB'!C14*'FOB'!C7*2.0,0)))*0.003/0.997))))*'FOB'!C11,0)*IF(ISNUMBER('FOB'!C33),'FOB'!C33,0)*(1+IF(ISNUMBER('FOB'!C34),'FOB'!C34,0)))*IF(ISNUMBER('FOB'!C35),'FOB'!C35,0),0))/('FOB'!C7*2.0),"") | E27: =IF(AND(ISNUMBER(D27),ISNUMBER(D4)),D27-D4,"") | F27: =IF(AND(ISNUMBER(E27),ISNUMBER(D4)),E27/D4,"")
B28: 口径说明：情景逐项复刻计算链，未做线性近似。数值已与 Python 引擎对账（scripts/verify_workbook.py 输出 build/workbook_reconciliation.json）。

Sheet 数据来源
B1: 数据来源与核验记录
B2: 每个数字必须能回答：谁给的、什么时候核验的、失效条件是什么。
A4: # | B4: 项目 | C4: 取值 | D4: 类型 | E4: 来源 / 依据 | F4: 核验日
A5: 1 | B5: HS 编码 | C5: 29053100 | D5: 公开查询 | E5: 2026年进出口税则（zhengdao.ai/tariff/2026/29053100） | F5: 2026-10-20
A6: 2 | B6: 最惠国关税税率 | C6: 5.5% | D6: 公开查询 | E6: 2026年进出口税则 29053100（税委会公告2025年第12号） | F6: 2026-07-15
A7: 3 | B7: 普通税率 | C7: 30% | D7: 公开查询 | E7: 同上；原产地不明时适用，不适用暂定税率 | F7: 2026-07-15
A8: 4 | B8: 协定税率（沙特） | C8: 不适用 | D8: 公开查询 | E8: 中国—海合会自贸协定未生效（商务部自贸区服务网） | F8: 2026-10-20
A9: 5 | B9: 进口环节增值税率 | C9: 13% | D9: 公开查询 | E9: 一般货物；计税公式见《关税法》第70条 | F9: 2026-10-20
A10: 6 | B10: 市场参考汇率 | C10: 6.6807 | D10: 公开查询 | E10: ECB 参考汇率交叉（frankfurter.app，2026-10-19） | F10: 2026-10-20
A11: 7 | B11: 海关计征汇率 | C11: 待确认 | D11: 待确认 | E11: 申报日对应上月第三个星期三（2026-09-16）PBOC 中间价 | F11: 2026-10-20
A12: 8 | B12: 保险费 0.3‰ 口径 | C12: （货价+运费）×0.3‰ | D12: 公开查询 | E12: 《确定进出口货物计税价格办法》第36条 | F12: 2026-10-20
A13: 9 | B13: 计税价格构成 | C13: 成交价格+运保费 | D13: 公开查询 | E13: 《关税法》第24、25、26条 | F13: 2024-12-01
A14: 10 | B14: 关税计算 | C14: 计税价格×税率 | D14: 公开查询 | E14: 《关税法》第23条 | F14: 2024-12-01
A15: 11 | B15: FOB 报价 | C15: 640.00 USD/MT | D15: 模拟情景 | E15: 演示建模假设，非实时市场报价 | F15: —
A16: 12 | B16: 海运费 | C16: 45.00 USD/MT | D16: 模拟情景 | E16: 朱拜勒→宁波；非货代实盘报价 | F16: —
... A21: 17 | B21: 国内运输 | C21: 7812.5 元/票 | D21: 公开费率×假设 | E21: 0.5 元/吨·km×250km×62.5t | F21: 2026-10-20

Sheet 术语规则
B1: Incoterms 2020 成本归属矩阵
B3: 术语 | C3: 中文 | D3: 出口报关 | E3: 主运费 | F3: 保险 | G3: 进口关税/清关
B4: EXW | C4: 工厂交货 | D4: 买方 | E4: 买方 | F4: 买方 | G4: 买方
B5: FCA | C5: 货交承运人 | D5: 卖方 | E5: 买方 | F5: 买方 | G5: 买方
B6: FAS | C6: 船边交货 | D6: 卖方 | E6: 买方 | F6: 买方 | G6: 买方
B7: FOB | C7: 船上交货 | D7: 卖方 | E7: 买方 | F7: 买方 | G7: 买方
B8: CFR | C8: 成本加运费 | D8: 卖方 | E8: 卖方 | F8: 买方 | G8: 买方
B9: CIF | C9: 成本保险费加运费 | D9: 卖方 | E9: 卖方 | F9: 卖方 | G9: 买方
B10: CPT | C10: 运费付至 | D10: 卖方 | E10: 卖方 | F10: 买方 | G10: 买方
B11: CIP | C11: 运费保险费付至 | D11: 卖方 | E11: 卖方 | F11: 卖方 | G11: 买方
B12: DAP | C12: 目的地交货 | D12: 卖方 | E12: 卖方 | F12: 买方 | G12: 买方
B13: DPU | C13: 卸货地交货 | D13: 卖方 | E13: 卖方 | F13: 买方 | G13: 买方
B14: DDP | C14: 完税后交货 | D14: 卖方 | E14: 卖方 | F14: 卖方 | G14: 卖方
B16: 要点
B17: "卖方承担" = 已含在报价中，测算时不能再加一次。
B18: FOB→加海运+保险；CFR→只加保险；CIF→都不加。
B19: CIF/CIP 保险最低保障 110% 合同价（2020 版 CIP 为 A 条款）。
B20: DDP 卖方付进口关税与清关，但进口环节增值税通常仍由境内进口方承担。
B21: 术语必须注明指定地点与版本，例：CIF 宁波 Incoterms 2020。
