Workbook

Sheet 00_封面与结论
A1: 重质纯碱 · 华东地区 客户市场价核验
A2: 规格：重质纯碱（重碱），工业级 Na₂CO₃ ≥99.2%（未逐批核验粒度与铁含量） | 地区口径：隆众资讯『华东地区』市场口径（含江苏、浙江、上海、安徽、山东等华东产销区），非单一城市或单一工厂 | 基准日：2026-10-20 | 案例：SODA-EAST-2026-10-20
A4: ⚠ 本条客户消息为 Skill 验收用模拟输入，其中 1400 元/吨 仅为测试数字，不代表任何真实客户的真实报价或真实市场水平。
A6: 一、客户所述价格（原文与已识别信息）
A7: 客户原话 | B7: 【模拟】现在华东重质纯碱市场才1400元/吨，你们报价是不是太高了？ | C7: 识别渠道 | D7: 微信
A8: 客户所述价格 | B8: 1400 | C8: 税费口径 | D8: 未注明
A9: 客户所述规格 | B9: 重质纯碱 | C9: 交付口径 | D9: 未注明
A10: 客户所述地区 | B10: 华东地区 | C10: 付款方式 | D10: 未注明
A11: 采购数量 | B11: 未说明 | C11: 价格取得日期 | D11: 未说明
A13: 二、市场参考价格（同规格·同地区·同税费·同交付）
A14: 市场参考区间 | B14: =TEXT('01_客户报价输入'!B22,"#,##0")&" – "&TEXT('01_客户报价输入'!B23,"#,##0")&" 元/吨" | C14: 报价日期 | D14: 2026-10-20
A15: 数据来源 | B15: 隆众资讯（经我的钢铁网 mysteel.com 转载） | C15: 口径 | D15: 现金含税 · 送到
A16: 原始链接 | B16: https://www.mysteel.com/oilchem/a/26102015/0877CD14C3251184.html
A17: 市场报价类型 | B17: 市场报价区间（置信度 高） | C17: 近3月价格带 | D17: 1,125 – 1,200 元/吨（n=12）
A19: 三、核验结论
A20: ='04_偏离计算'!B35
A21: 客户价高于区间上沿 200 元/吨（区间半宽 75 元/吨，区间宽 150）。；且客户价高于近 3 个月同口径价格带上沿 1200 元/吨。（口径提示：客户未说明含税/不含税；客户未说明出厂/送到；客户未说明付款方式/账期，需客户确认后复核）
A23: 四、使用说明
A24: 1. 先在「01_客户报价输入」里填客户价格、税费/交付口径、我方报价（与报价文件一致）；其它表会自动重算。
A25: 2. 「03_市场报价与历史」是可替换的数据区：换品种/换地区时，按表头六项口径逐行替换即可，不要改「04_偏离计算」里的公式。
A26: 3. 「04_偏离计算」所有偏离金额与比例都是公式，可鼠标点到单元格查看引用关系。
A27: 4. 「08_数据缺口」列出拿不到的数据；在补上之前，不要给出比表内区间更细的结论。
A28: 5. 本簿不提供报价建议、不提供让价幅度；沟通话术在「10_沟通事实要点」中仅是客观事实，需人工审核后使用。

Sheet 01_客户报价输入
A1: 客户报价输入（黄色单元格为可修改项）
A2: 口径不一致或缺失时，请在「推断口径」一栏说明来源；不要凭猜填写。
A4: 字段 | B4: 值 | C4: 备注 / 口径 | D4: 说明
A5: 客户所述价格 | B5: 1400 | C5: 必填。客户口头或微信里给出的数字，不要自行折算。
A6: 单位 | B6: 元/吨 | C6: 若不是元/吨，请在上方注明换算关系，不要直接相乘。
A7: 价差基准价（市场参考） | B7: =B25 | C7: 公式引用 B25（市场区间中值）
A8: 客户所述税费口径 | B8: 未注明 | C8: 含税 / 不含税 / 未注明。必须与市场口径一致才能直接比。
A9: 客户所述交付口径 | B9: 未注明 | C9: 出厂 / 送到 / 库提。送到与出厂差运费。
A10: 客户所述付款方式 | B10: 未注明 | C10: 现金 / 承兑。承兑需贴现，不可默认等同现金。
A11: 客户所述采购数量 | B11: 未说明 | C11: 吨/月或单笔吨位，影响成交区间位置。
A12: 客户所述取得日期 | B12: 未说明 | C12: 客户说『现在才…』时，请他给出具体日期与来源。
A13: 我方历史报价 | C13: 选填。用于算『我方报价 vs 客户价』，不是建议价。
A14: 我方报价税费口径 | B14: 未注明 | C14: 选填。
A15: 已知运费（元/吨） | C15: 仅在客户为出厂、市场为送到时使用；没有就留空 → 显示无法直接折算。
A16: 已知税率（增值税） | B16: 0.13 | C16: 纯碱适用 13%；其它品种请按实际税率填写。换算系数自动算出。
A17: 税费换算系数 | B17: =1+B16 | C17: 含税 = 不含税 × (1+税率)；由公式得出，不要手改。
A19: 市场参考口径（来自 03 表，或手工指定）
A20: 项目 | B20: 值 | C20: 口径 | D20: 说明
A21: 市场税费口径 | B21: 含税 | C21: 参照行 | D21: 必须与客户口径可比；不可比时在 04 表会显示口径提示
A22: 市场交付口径 | B22: 送到 | C22: 参照行 | D22: 送到价含运费；出厂价不含运费
A23: 市场区间下沿 | B23: 1050 | C23: 元/吨 | D23: 来自「03_市场报价与历史」所选行
A24: 市场区间上沿 | B24: 1200 | C24: 元/吨
A25: 市场区间中值（公式） | B25: =AVERAGE(B23:B24) | C25: 元/吨 | D25: =(下沿+上沿)/2，仅取同一来源的区间
A26: 报价日期 | B26: 2026-10-20 | C26: 日期 | D26: 客户价比对必须看日期

Sheet 02_口径对照
A1: 规格与交易口径对照（同口径优先）
A2: 每一维度都问一句：客户说的和市场上报的，是不是同一个东西。
A4: 维度 | B4: 客户所述 | C4: 市场口径 | D4: 是否一致 | E4: 对价格的影响 | F4: 需确认 / 动作
A5: 规格 | B5: 重质纯碱（未细分粒度/铁含量) | C5: 重质纯碱（市场口径未细分粒度） | D5: 一致 | E5: 若为玻璃用重碱，一般与市场口径一致；若要求特定粒度或低铁，实际可匹配报价更窄 | F5: 确认粒度（30/40/50 目等）与 Fe₂O₃、不溶物指标
A6: 地区 | B6: 华东 | C6: 华东地区（隆众口径） | D6: 一致 | E6: 若客户位于苏北、山东沿海等非华东主干道，运距会改变送到成本 | F6: 确认具体收货地（城市/厂区）
A7: 税费 | B7: 未说明 | C7: 含税（现金含税，增值税率 13%） | D7: 信息缺失 | E7: 若客户价为不含税，含税等值 = 客户价×1.13，差异可能近 12% | F7: 确认客户所述价格含税与否、是否只能开专票
A8: 交付条件 | B8: 未说明 | C8: 送到（到厂） | D8: 信息缺失 | E8: 若客户价为出厂，需加运费才能与市场送到价比较；本案例未获运费数据 → 无法直接折算 | F8: 确认是出厂自提还是送到到厂
A9: 付款方式 | B9: 未说明 | C9: 现金（现汇） | D9: 信息缺失 | E9: 若为承兑，通常需按贴现利率折让；本案例无贴现率数据 → 不自行折算 | F9: 确认现金/承兑，承兑期限
A10: 采购数量 | B10: 未说明 | C10: 市场区间，不区分单笔吨位 | D10: 信息缺失 | E10: 整车/包销与大单通常对应区间下沿；需求方无法量化 | F10: 确认月用量、单笔订车吨位
A11: 包装 | B11: 未说明 | C11: 市场报价未区分袋装/散装/吨袋 | D11: 信息缺失 | E11: 吨袋与散装通常存在包装差价，市场区间未拆分 | F11: 确认吨袋/40kg 袋/散装罐车
A12: 数据日期 | B12: "现在"（未说明具体日期） | C12: 2026-10-20（交易日日更报价） | D12: 信息缺失 | E12: 若客户引用的是数周前或数年前的价格，需按历史序列对位查证 | F12: 请客户说明价格取得时间与来源
A14: 可能导致价格差异的因素（客观解释，不是话术）
A15: 因素 | B15: 说明 | D15: 对价格的影响
A16: 规格与纯度 | B16: 重质纯碱的粒度（目数）、铁含量、水不溶物、堆积密度差异会影响可用于玻璃/光伏/冶金等不同下游的单吨价值；市场『重质纯碱』大类报价未细分这些指标。 | D16: 同为大类『重质纯碱』时价差有限；若客户需求为特殊规格，需另找匹配报价
A17: 地区与运距 | B17: 华东 1050-1200、华中 1050-1150、华北 1150、华南 1200-1300、东北 1200-1350（均含税送到，2026-10-10/12/20 报价）。 | D17: 运距直接进入价差；华南与东北价格高于华东约 75-150 元/吨
A18: 税费口径 | B18: 市场报价为现金含税；若客户引述不含税价，含税等值需 ×1.13。 | D18: 最容易造成数百元/吨的『看起来的巨差』
A19: 出厂 vs 到厂 | B19: 华东重质市场报价为送到价；厂家出厂报价（如江苏井神重质出厂 1100-1150）不含运费。 | D19: 出厂价与送到价之间必须补运费，本案例无运费数据，故不交叉折算
A20: 采购数量与订车 | B20: 厂家多『一单一议、实单成交灵活』（隆众表注），整车大单与零星单价格不同。 | D20: 区间下沿通常对应更大量与更优账期，具体幅度无公开数据
A21: 包装形式 | B21: 散装罐车/吨袋/小包装的包装与装卸成本不同，市场价格未拆分。 | D21: 吨袋与散装存在差价，幅度需按具体报价确认
A22: 账期与付款 | B22: 现金与承兑、账期长短影响卖方资金占用。 | D22: 无贴现率数据时不自行折算；需客户说明账期
A23: 物流费用 | B23: 跨区调货的汽运/船运成本随运距、油价、回程车源波动。 | D23: 这是『出厂价更低』与『到厂价更高』之间的主要解释
A24: 个别低价成交 | B24: 清库、检修前抛货、出口转内销、单笔买断等特殊情况可能短时出现低于市场区间的成交，但不可作为普遍市场价。 | D24: 若客户称有更低成交，应要求提供成交时间、规格、数量、付款与交付方式，再判断是否可比

Sheet 03_市场报价与历史
A1: 市场报价与历史序列（可替换的数据区）
A2: 每条报价必须六项齐全：数值·规格·地区·税费·交付·日期·来源。缺一项只能放「08_数据缺口」。
A4: 日期 | B4: 规格 | C4: 地区 | D4: 税费 | E4: 交付 | F4: 付款 | G4: 下沿 | H4: 上沿 | I4: 中值/主流价 | J4: 单位 | K4: 来源 / 类型 | L4: 原始链接（可点）
A5: 2026-10-20 | B5: 重质纯碱（未细分粒度） | C5: 华东地区 | D5: 现金含税 | E5: 送到 | F5: 现金 | G5: 1050 | H5: 1200 | I5: 1100 | J5: 元/吨 | K5: 隆众资讯（经我的钢铁网 mysteel.com 转载）（市场报价区间，置信高） | L5: https://www.mysteel.com/oilchem/a/26102015/0877CD14C3251184.html
A6: 2026-10-20 | B6: 重质纯碱（华中） | C6: 华中地区 | D6: 现金含税 | E6: 送到 | F6: 现金 | G6: 1050 | H6: 1150 | I6: 1100 | J6: 元/吨 | K6: 隆众资讯（经我的钢铁网转载）（市场报价区间，置信高） | L6: https://www.mysteel.com/oilchem/a/26102015/EA2C185BD7E6C29E.html
A7: 2026-10-16 | B7: 重质纯碱（日照、连云港） | C7: 华东-山东/苏北出口集散地 | D7: 未注明 | E7: 集港价 | F7: 未注明 | G7: 1350 | H7: 1450 | I7: 1400 | J7: 元/吨 | K7: 生意社（chemall 中国石油和化工网转载）（个别成交参考，置信低） ｜不可直接比较：集港出口价，含港杂与内陆集港成本、面向出口订单，与内贸现货『华东出厂/送到』不是同一口径，不可与中国内贸价格直接比较；且原文为搜索摘要，未见完整原表 | L7: https://www.chemall.com.cn/news/show-264502.html
A8: 2026-10-12 | B8: 重质纯碱（华北） | C8: 华北地区 | D8: 现金含税 | E8: 送到 | F8: 现金 | I8: 1150 | J8: 元/吨 | K8: 隆众资讯（经我的钢铁网转载）（市场报价，置信高） | L8: https://www.mysteel.com/oilchem/a/26101214/7B985DEE621CAC82.html
A9: 2026-10-12 | B9: 重质纯碱（广东） | C9: 华南地区 | D9: 现汇含税 | E9: 送到 | F9: 现汇 | G9: 1200 | H9: 1300 | I9: 1250 | J9: 元/吨 | K9: 隆众资讯（经我的钢铁网转载）（市场报价区间，置信高） | L9: https://www.mysteel.com/oilchem/a/26101214/7FA69DFCD8D8BADE.html
A10: 2026-10-10 | B10: 重质纯碱 | C10: 华东地区 | D10: 未注明（同花顺原文未标注含税与否） | E10: 未注明 | F10: 未注明 | I10: 1150 | J10: 元/吨 | K10: 同花顺 iFinD（iNews 现货汇总）（主流参考价（单点），置信中） | L10: https://news.10jqka.com.cn/20261010/c680552148.shtml
A11: 2026-10-10 | B11: 重质纯碱（东北） | C11: 东北地区 | D11: 含税 | E11: 送到 | F11: 未注明 | G11: 1200 | H11: 1350 | I11: 1275 | J11: 元/吨 | K11: 隆众资讯（经我的钢铁网转载）（市场报价区间，置信高） | L11: https://www.mysteel.com/oilchem/a/26101014/FF1A43B14CB11155.html
A13: 历史序列（同规格·同地区·同口径，按日期排序；走势与价格带以此为底）
A14: 日期 | B14: 规格 | C14: 地区 | D14: 税费 | E14: 交付 | F14: 类型 | G14: 下沿 | H14: 上沿 | I14: 中值 | J14: 单位 | K14: 来源 | L14: 原始链接（可点）
A15: 2026-04-27 | B15: 重质纯碱 | C15: 华东地区 | D15: 含税 | E15: 送到 | F15: 日更区间 | G15: 1230 | H15: 1250 | I15: 1250 | J15: 元/吨 | K15: 隆众资讯 | L15: https://www.mysteel.com/oilchem/a/26042715/5E8BB24F8B18A1AC.html
A16: 2026-05-19 | B16: 重质纯碱 | C16: 华东地区 | D16: 含税 | E16: 送到 | F16: 日更区间 | G16: 1230 | H16: 1250 | I16: 1250 | J16: 元/吨 | K16: 隆众资讯 | L16: https://www.mysteel.com/oilchem/a/26051916/CE4605A2620E90F7.html
A17: 2026-06-17 | B17: 重质纯碱 | C17: 华东地区 | D17: 含税 | E17: 送到 | F17: 主流价单点 | G17: 1250 | H17: 1250 | I17: 1250 | J17: 元/吨 | K17: 同花顺 iFinD（主流价） | L17: https://news.10jqka.com.cn/20260617/c677534618.shtml
A18: 2026-07-27 | B18: 重质纯碱 | C18: 华东地区 | D18: 含税 | E18: 送到 | F18: 日更区间 | G18: 1150 | H18: 1250 | I18: 1200 | J18: 元/吨 | K18: 隆众资讯 | L18: https://www.mysteel.com/oilchem/a/26072716/13649DB9A94FCAFB.html
A19: 2026-07-28 | B19: 重质纯碱 | C19: 华东地区 | D19: 未注明 | E19: 未注明 | F19: 主流价单点 | G19: 1215 | H19: 1215 | I19: 1215 | J19: 元/吨 | K19: 同花顺 iFinD（主流价） | L19: https://stock.10jqka.com.cn/20260728/c678488931.shtml
A20: 2026-08-05 | B20: 重质纯碱 | C20: 华东地区 | D20: 含税 | E20: 送到 | F20: 日更区间 | G20: 1050 | H20: 1200 | I20: 1125 | J20: 元/吨 | K20: 隆众资讯 | L20: https://www.mysteel.com/oilchem/a/26080516/799ED20A6BBB9B16.html
A21: 2026-08-06 | B21: 重质纯碱 | C21: 华东地区 | D21: 未注明 | E21: 未注明 | F21: 主流价单点 | G21: 1150 | H21: 1150 | I21: 1150 | J21: 元/吨 | K21: 同花顺 iFinD（主流价） | L21: https://news.10jqka.com.cn/20260806/c678727075.shtml
A22: 2026-08-12 | B22: 重质纯碱 | C22: 华东地区 | D22: 含税 | E22: 送到 | F22: 日更区间 | G22: 1050 | H22: 1200 | I22: 1125 | J22: 元/吨 | K22: 隆众资讯 | L22: https://www.mysteel.com/oilchem/a/26081215/3C2125C354434659.html
A23: 2026-08-18 | B23: 重质纯碱 | C23: 华东地区 | D23: 含税 | E23: 送到 | F23: 日更区间 | G23: 1050 | H23: 1200 | I23: 1125 | J23: 元/吨 | K23: 隆众资讯 | L23: https://www.mysteel.com/oilchem/a/26081815/DFBD0BCD84683417.html
A24: 2026-09-10 | B24: 重质纯碱 | C24: 华东地区 | D24: 含税 | E24: 送到 | F24: 日更区间 | G24: 1050 | H24: 1200 | I24: 1125 | J24: 元/吨 | K24: 隆众资讯 | L24: https://www.mysteel.com/oilchem/a/26091015/A0D182907C402BE9.html
A25: 2026-09-14 | B25: 重质纯碱 | C25: 华东地区 | D25: 含税 | E25: 送到 | F25: 日更区间 | G25: 1050 | H25: 1200 | I25: 1125 | J25: 元/吨 | K25: 隆众资讯 | L25: https://www.mysteel.com/oilchem/a/26091415/CE109E81A14E10E9.html
A26: 2026-09-20 | B26: 重质纯碱 | C26: 华东地区 | D26: 含税 | E26: 送到 | F26: 日更区间 | G26: 1050 | H26: 1200 | I26: 1125 | J26: 元/吨 | K26: 隆众资讯 | L26: https://www.mysteel.com/oilchem/a/26092014/FCF532383597976E.html
... A31: 2026-10-20 | B31: 重质纯碱 | C31: 华东地区 | D31: 含税 | E31: 送到 | F31: 日更区间 | G31: 1050 | H31: 1200 | I31: 1125 | J31: 元/吨 | K31: 隆众资讯 | L31: https://www.mysteel.com/oilchem/a/26102015/0877CD14C3251184.html
A33: 序列统计（全部为公式，替换数据后自动更新）
A34: 样本数 | B34: =COUNT(I15:I31)
A35: 近3月最高 | B35: =MAX(I15:I31)
A36: 近3月最低 | B36: =MIN(I15:I31)
A37: 近3月中值 | B37: =MEDIAN(I15:I31)
A38: 近3月均值 | B38: =AVERAGE(I15:I31)
A39: 最大波动幅度 | B39: =MAX(I15:I31)-MIN(I15:I31)

Sheet 04_偏离计算
A1: 价格偏离计算（全部为公式；改 01 表客户价即自动重算）
A2: 公式口径：偏离金额 = 客户价 − 市场参考值；偏离比例 = 偏离金额 ÷ 市场参考值。
A4: 一、输入（引用 01 表）
A5: 项目 | B5: 数值 | C5: 单位 | F5: 公式 / 说明
A6: 客户所述价格 | B6: ='01_客户报价输入'!B5 | C6: 元/吨 | F6: 直接引用 01!B5
A7: 客户税费口径 | B7: ='01_客户报价输入'!B8 | F7: 含税/不含税/未注明
A8: 客户交付口径 | B8: ='01_客户报价输入'!B9 | F8: 出厂/送到/库提
A9: 市场税费口径 | B9: ='01_客户报价输入'!B21 | F9: 参照 03 表
A10: 市场交付口径 | B10: ='01_客户报价输入'!B22 | F10: 参照 03 表
A11: 市场区间下沿 | B11: ='01_客户报价输入'!B23 | C11: 元/吨 | F11: 同日同口径
A12: 市场区间上沿 | B12: ='01_客户报价输入'!B24 | C12: 元/吨 | F12: 同日同口径
A13: 市场参考值（中值） | B13: ='01_客户报价输入'!B25 | C13: 元/吨 | F13: =(下沿+上沿)/2
A14: 税率 | B14: ='01_客户报价输入'!B16 | F14: 增值税
A15: 已知运费 | B15: ='01_客户报价输入'!B15 | C15: 元/吨 | F15: 出厂→送到时使用；空则无法折算
A17: 二、口径标准化（确定性换算，非推测）
A18: 步骤 | B18: 数值 | C18: 说明 | F18: 公式
A19: 客户价（换算到市场税基） | B19: =IF(AND(B7="不含税",B9="含税"),B6*(1+B14),IF(AND(B7="含税",B9="不含税"),B6/(1+B14),B6)) | C19: 仅当两侧税基明确且不同才换算 | F19: 客户「未注明」时不加税、不减税，直接按市场税基比较，并在结论里标注口径风险
A20: 客户价（换算到市场交付口径） | B20: =IF(AND(B10="送到",B8="出厂"),IFERROR(B19+B15,B19),IF(AND(B10="出厂",B8="送到"),IFERROR(B19-B15,B19),B19)) | C20: 出厂+运费→送到；送到−运费→出厂；无运费则保持原值并提示 | F20: 运费为空时不做任何假设，04 结论区会显示「无法直接折算」
A21: 口径是否可直接比较 | B21: =IF(AND(B10="送到",B8="出厂",B15=""),"无法直接折算（缺运费）","可比较（已按口径换算）") | C21: 条件 | F21: 只比较同税基、同交付口径的价格
A23: 三、偏离金额与比例
A24: 指标 | B24: 数值（元/吨 或 %） | C24: 计算方法 | F24: Excel 公式
A25: ① 偏离金额（相对中值） | B25: =B20-B13 | C25: 客户价 − 市场参考值（正=客户更高） | F25: =B20-B13
A26: ② 偏离比例（相对中值） | B26: =IFERROR(B25/B13,"") | C26: 偏离金额 ÷ 市场参考值 | F26: =IFERROR(B25/B13,"")
A27: ③ 相对区间上沿的金额 | B27: =B20-B12 | C27: 客户价 − 上沿（>0 表示高于市场最高报价） | F27: =B20-B12
A28: ④ 相对上沿的比例 | B28: =IFERROR(B27/B12,"") | C28: 相对上沿金额 ÷ 上沿 | F28: =IFERROR(B27/B12,"")
A29: ⑤ 相对区间下沿的金额 | B29: =B20-B11 | C29: 客户价 − 下沿（<0 表示低于市场最低报价） | F29: =B20-B11
A30: ⑥ 相对下沿的比例 | B30: =IFERROR(B29/B11,"") | C30: 相对下沿金额 ÷ 下沿 | F30: =IFERROR(B29/B11,"")
A31: ⑦ 是否落在市场区间内 | B31: =IF(B20=B13,"待输入客户价",IF(AND(B20>=B11,B20<=B12),"是","否")) | C31: 下沿 ≤ 客户价 ≤ 上沿 → 是
A32: ⑧ 区间半宽（判定尺度） | B32: =(B12-B11)/2 | C32: 半宽 = (上沿−下沿)/2，用作『明显』判定的自然尺度 | F32: =(B12-B11)/2
A34: 四、判定（依据区间位置 + 近3月价格带，不用固定百分比阈值）
A35: 核验结论 | B35: =IF(OR(B11="",B12="",NOT(ISNUMBER(B11)),NOT(ISNUMBER(B12))),"无可靠市场数据，无法验证",IF(B21<>"可比较（已按口径换算）","口径不一致，暂时无法直接比较",IF(AND(B20>=B11-0.01,B20<=B12+0.01),"接近市场参考区间",IF(ABS(B20-IF(B20>B12,B12,B11))<=B32+0.01,IF(B20>B12,"略高于市场参考区间","略低于市场参考区间"),IF(B20>B12,"明显偏高","明显偏低")))))
A36: 判定规则 | B36: ①客户价在[下沿,上沿]内→接近市场；②区间外但距最近端点 ≤ 半宽 → 略高/略低；③距最近端点 > 半宽 → 明显偏高/明显偏低；④口径不可比 → 无法直接比较。「明显」的尺度取自该市场报价自身的宽度，而不是人为设定的百分比。
A37: 口径提示 | B37: 客户未说明含税/不含税；客户未说明出厂/送到；客户未说明付款方式/账期
A38: 我方报价 vs 客户价 | B38: =IF('01_客户报价输入'!B13="","未填写我方报价","我方报价 "&TEXT('01_客户报价输入'!B13,"#,##0")&" 元/吨，较客户价 "&TEXT('01_客户报价输入'!B13-B6,"+#,##0;-#,##0;0")&" 元/吨（"&TEXT(IFERROR(('01_客户报价输入'!B13-B6)/B6,0),"+0.0%;-0.0%")&"）")
A40: 五、历史窗口对比（7天 / 30天 / 3个月）
A41: 窗口 | B41: 起点日期 | C41: 起点价格 | D41: 最新价格 | E41: 变化 | F41: 变化比例
A42: 近7天 | B42: 2026-10-10 | C42: 1125 | D42: 1125 | E42: =D42-C42 | F42: =IFERROR(E42/C42,"")
A43: 近30天 | B43: 2026-09-20 | C43: 1125 | D43: 1125 | E43: =D43-C43 | F43: =IFERROR(E43/C43,"")
A44: 近3个月 | B44: 2026-06-17 | C44: 1250 | D44: 1125 | E44: =D44-C44 | F44: =IFERROR(E44/C44,"")
A46: 客户价在历史中的位置 | B46: 历史序列区间 1,125–1,250 元/吨；客户价高于序列最高点 150 元/吨（12.0%）

Sheet 05_历史走势数据
A1: 历史价格序列（供 Excel 折线图 / 复核任意一天）
A2: 同一来源、同一口径的连续点；不同来源标注了口径差异，不做平均合并。
A4: 日期 | B4: 规格 | C4: 地区 | D4: 口径 | E4: 区间下沿 | F4: 区间上沿 | G4: 中值/主流价 | H4: 来源
A5: 2026-04-27 | B5: 重质纯碱 | C5: 华东地区 | D5: 含税·送到 | E5: 1230 | F5: 1250 | G5: 1250 | H5: 隆众资讯
A6: 2026-05-19 | B6: 重质纯碱 | C6: 华东地区 | D6: 含税·送到 | E6: 1230 | F6: 1250 | G6: 1250 | H6: 隆众资讯
A7: 2026-06-17 | B7: 重质纯碱 | C7: 华东地区 | D7: 含税·送到 | E7: 1250 | F7: 1250 | G7: 1250 | H7: 同花顺 iFinD（主流价）
A8: 2026-07-27 | B8: 重质纯碱 | C8: 华东地区 | D8: 含税·送到 | E8: 1150 | F8: 1250 | G8: 1200 | H8: 隆众资讯
A9: 2026-07-28 | B9: 重质纯碱 | C9: 华东地区 | D9: 未注明·未注明 | E9: 1215 | F9: 1215 | G9: 1215 | H9: 同花顺 iFinD（主流价）
A10: 2026-08-05 | B10: 重质纯碱 | C10: 华东地区 | D10: 含税·送到 | E10: 1050 | F10: 1200 | G10: 1125 | H10: 隆众资讯
A11: 2026-08-06 | B11: 重质纯碱 | C11: 华东地区 | D11: 未注明·未注明 | E11: 1150 | F11: 1150 | G11: 1150 | H11: 同花顺 iFinD（主流价）
A12: 2026-08-12 | B12: 重质纯碱 | C12: 华东地区 | D12: 含税·送到 | E12: 1050 | F12: 1200 | G12: 1125 | H12: 隆众资讯
A13: 2026-08-18 | B13: 重质纯碱 | C13: 华东地区 | D13: 含税·送到 | E13: 1050 | F13: 1200 | G13: 1125 | H13: 隆众资讯
A14: 2026-09-10 | B14: 重质纯碱 | C14: 华东地区 | D14: 含税·送到 | E14: 1050 | F14: 1200 | G14: 1125 | H14: 隆众资讯
A15: 2026-09-14 | B15: 重质纯碱 | C15: 华东地区 | D15: 含税·送到 | E15: 1050 | F15: 1200 | G15: 1125 | H15: 隆众资讯
A16: 2026-09-20 | B16: 重质纯碱 | C16: 华东地区 | D16: 含税·送到 | E16: 1050 | F16: 1200 | G16: 1125 | H16: 隆众资讯
... A21: 2026-10-20 | B21: 重质纯碱 | C21: 华东地区 | D21: 含税·送到 | E21: 1050 | F21: 1200 | G21: 1125 | H21: 隆众资讯
A23: 辅助列：客户价在历史的什么位置
A24: 客户价（引用01） | B24: ='01_客户报价输入'!B5
A25: 高于序列最高点？ | B25: =IF(B24>MAX(G5:G21),"高于最高点 "&TEXT(B24-MAX(G5:G21),"#,##0")&" 元/吨","在序列范围内")

Sheet 06_区域对比
A1: 相邻地区价格对比（同为含税·送到口径）
A2: 区域价差主要来自运距与供需结构；不能据此判断『某地市场更高/更低』。
A4: 地区 | B4: 下沿 | C4: 上沿 | D4: 中值 | E4: 税费 | F4: 交付 | G4: 日期 | H4: 较基准价差 | I4: 较基准比例
A5: 华东地区（基准） | B5: ='01_客户报价输入'!B24 | C5: ='01_客户报价输入'!B24 | D5: =AVERAGE(B5:C5) | E5: ='01_客户报价输入'!B22 | F5: ='01_客户报价输入'!B22 | G5: 2026-10-20 | H5: 0 | I5: 0
A6: 华中地区 | B6: 1050 | C6: 1150 | D6: =AVERAGE(B6:C6) | E6: 含税 | F6: 送到 | G6: 2026-10-20 | H6: =D6-D$5 | I6: =IFERROR(H6/D$5,"") | J6: 同规格、同税基、同为送到口径；距离华东最近的区域参考
A7: 华北地区 | B7: 1150 | C7: 1150 | D7: =AVERAGE(B7:C7) | E7: 含税 | F7: 送到 | G7: 2026-10-12 | H7: =D7-D$5 | I7: =IFERROR(H7/D$5,"") | J7: 同规格、同税基、送到口径；日期早 8 天
A8: 华南地区 | B8: 1200 | C8: 1300 | D8: =AVERAGE(B8:C8) | E8: 含税 | F8: 送到 | G8: 2026-10-12 | H8: =D8-D$5 | I8: =IFERROR(H8/D$5,"") | J8: 同规格、同税基、送到口径；运距远，价差含运价
A9: 东北地区 | B9: 1200 | C9: 1350 | D9: =AVERAGE(B9:C9) | E9: 含税 | F9: 送到 | G9: 2026-10-10 | H9: =D9-D$5 | I9: =IFERROR(H9/D$5,"") | J9: 同规格、同税基、送到口径；运距最远，价格最高
A11: 可比性说明 | B11: 各区域均为同规格、同税基、送到口径；日期相差 1-10 天的已在「日期」列标出。跨区比价的前提是『同一客户、同一交付地』；运距不同时，价差不能直接当作报价依据。

Sheet 07_待确认问题
A1: 需要向客户确认的问题清单
A2: 按优先级排序；每条对应一个口径缺口。得到答复后回填到「客户答复」，再复核结论。
A4: # | B4: 优先级 | C4: 问题 | D4: 为什么要问 | E4: 客户答复（回填）
A5: 1 | B5: 高 | C5: 您说的 1400 元/吨，是含税还是不含税？能不能开 13% 增值税专用发票？ | D5: 含税/不含税差 13%，是数百元/吨差异的第一来源
A6: 2 | B6: 高 | C6: 这个价格是出厂价（您自提）还是送到价（到您厂）？送到哪里？ | D6: 出厂与送到之间差运费，决定能否直接对比
A7: 3 | B7: 高 | C7: 价格是哪天、从哪里看到的（哪家供应商/哪个平台/群里报价）？ | D7: 用于判断是否为最新价、是否为个别成交
A8: 4 | B8: 高 | C8: 具体是重质还是轻质？粒度要求是多少（如 30/40 目）、对铁含量或不溶物有无上限？ | D8: 华轻重碱当前价差很小，但规格不同仍可能不具可比性
A9: 5 | B9: 中 | C9: 月用量和单笔订货量是多少？是散装罐车、吨袋还是 40kg 小包装？ | D9: 量与包装会显著影响成交价
A10: 6 | B10: 中 | C10: 付款是现汇还是承兑？账期多久？ | D10: 账期与承兑需按贴现成本折算，不可默认相同
A11: 7 | B11: 中 | C11: 您说的低价是否有明确的成交凭证（合同/订单/送货单），是哪家、什么时候？ | D11: 区分市场报价、个别成交与传闻
A12: 8 | B12: 中 | C12: 收货具体地点在华东哪个城市？有没有指定卸货条件（如现场可容罐车/叉车卸货）？ | D12: 运距与卸货条件影响送到成本
A13: 9 | B13: 低 | C13: 您比较时是否把运费、税费、账期都算进去了？ | D13: 帮助客户自行核对口径，减少无效争议

Sheet 08_数据缺口
A1: 数据缺口与研究边界
A2: 缺口不是缺陷列表，而是『这份报告能走多远』的刻度。补上一条，结论才能细一分。
A4: 缺口项 | B4: 影响 | C4: 补法 | D4: 状态
A5: 华东重质『含税出厂』同日公开报价 | B5: 无法把厂家出厂价直接与客户价对比 | C5: 向客户确认口径，或获取江苏/山东厂家针对该客户的正式报价 | D5: 待补
A6: 华东→客户具体工厂的运费/运距数据 | B6: 出厂价与送到价之间无法折算 | C6: 按实际收货地询价（含税运价单）后再折算 | D6: 待补
A7: 承兑贴现率 | B7: 账期与承兑口径无法折算 | C7: 按公司财务给定的贴现率折算，不自行假设 | D7: 待补
A8: 粒度/铁含量等细分规格报价 | B8: 若客户需求为特殊规格，市场大类报价不适用 | C8: 向厂家询特定规格报价 | D8: 待补
A9: 客户所述 1400 元/吨 的来源与日期 | B9: 无法判断是否为个别成交或历史价格 | C9: 按 Q3/Q7 向客户确认 | D9: 待补
A10: 我方历史报价 | B10: 无法计算我方报价与客户价的偏离 | C10: 销售在 Excel『01_客户报价输入』填入后自动重算 | D10: 待补
A11: 2026 年 1-3 月华东重质连续日线 | B11: 『近一年位置』结论受限 | C11: 后续补充 1-3 月日更页面 | D11: 待补
A13: 研究方法说明
A14: • 基准比较采用①同一时段（2026-10-20）②同一规格（重质纯碱）③同一区域（华东）④同一税费（含税）⑤同一交付（送到）的隆众数据。
A15: • 客户价 1400 元/吨 高于同日市场区间上沿 1200 元/吨 达 200 元/吨，超过区间半宽（75 元/吨），且高于近半年华东序列的最高点 1250 元/吨，按本 Skill 的判断规则属『明显偏高』，且该价在近半年任何时点都不存在于华东重质现货口径。
A16: • 客户未说明含税/含税交付条件，故本结论附条件：若客户实际为『不含税出厂』，则其口径与市场不同，需另行折算——但即使按不含税 1400（含税等值 1582）也远高于市场，折算不会改变方向性结论。
A17: • 本报告不使用『压价/虚报』等定性，仅陈述可核实的价格事实与口径差异。
A19: 期货参考（仅说明税基差异，不作为现货参考价）
A20: 说明 | B20: 期货为不含税、含交割成本的标准化合约价，不可直接与现货含税送到价相减。本 Skill 不使用期货价格作为市场参考价，仅在沟通中用于说明『盘面与现货的差异不在同一税基』。
A21: 日期 | B21: 收盘（元/吨） | C21: 合约 | D21: 来源
A22: 2026-09-30 | B22: 985 | C22: SA2701（郑商所纯碱主力合约） | D22: 郑商所日行情（经隆众『纯碱期货……』简报转述）
A23: 2026-10-09 | B23: 948 | C23: SA2701（郑商所纯碱主力合约） | D23: 郑商所日行情（经隆众『纯碱期货……』简报转述）
A24: 2026-10-12 | B24: 941 | C24: SA2701（郑商所纯碱主力合约） | D24: 郑商所日行情（经隆众『纯碱期货……』简报转述）
A25: 2026-10-13 | B25: 950 | C25: SA2701（郑商所纯碱主力合约） | D25: 郑商所日行情（经隆众『纯碱期货……』简报转述）
A26: 2026-10-14 | B26: 946 | C26: SA2701（郑商所纯碱主力合约） | D26: 郑商所日行情（经隆众『纯碱期货……』简报转述）
A27: 2026-10-15 | B27: 935 | C27: SA2701（郑商所纯碱主力合约） | D27: 郑商所日行情（经隆众『纯碱期货……』简报转述）
A28: 2026-10-16 | B28: 933 | C28: SA2701（郑商所纯碱主力合约） | D28: 郑商所日行情（经隆众『纯碱期货……』简报转述）
A29: 2026-10-19 | B29: 930 | C29: SA2701（郑商所纯碱主力合约） | D29: 郑商所日行情（经隆众『纯碱期货……』简报转述）

Sheet 09_计算过程
A1: 计算过程（可复核）
A2: 每个派生数字的公式、输入与结果；任何人可用同一来源复现。
A4: # | B4: 步骤 | C4: 公式 | D4: 输入 | E4: 结果
A5: S1 | B5: 确定市场参考区间 | C5: 取同日同规格同地区含税送到的最新区间报价 | D5: 来源：隆众资讯（经我的钢铁网 mysteel.com 转载）；日期：2026-10-20；口径：现金含税·送到 | E5: low：1050；high：1200
A6: S2 | B6: 客户价相对市场区间的偏离 | C6: 偏离金额 = 客户价 − 区间中值；偏离比例 = 偏离金额 ÷ 区间中值；另算相对上下沿的金额与比例 | D6: 客户价：1400；区间：[1050, 1200]；区间中值：1125.0 | E6: delta_to_dot：275.0；pct_to_dot：0.24444444444444444；delta_to_low：350；pct_to_low：0.3333333333333333；delta_to_high：200；pct_to_high：0.16666666666666666；pos：above
A7: S3 | B7: 近3个月同口径价格带 | C7: 近 92 天同地区同规格同口径历史点的 min / max / median / mean（不使用不同来源混算） | D7: 样本数：12 | E7: min：1125.0；max：1200.0；median：1125.0；mean：1131.25
A8: S4 | B8: 结论判定 | C8: 区间内=接近市场；区间外但距离≤区间半宽=略高/略低；距离>区间半宽 且 超出近3月价格带=明显偏高/偏低 | D8: 客户价：1400；区间半宽：75.0；近3月最高：1200.0；近3月最低：1125.0 | E8: verdict：high；label：明显偏高
A9: S5 | B9: 7/30/90 天价格变化 | C9: 变化 = 最新价 − 取最新日向前推 N 天最近的同口径点；比例 = 变化 ÷ 起点价 | D9: 基准日：2026-10-20 | E9: 7d：0.0；30d：0.0；90d：-0.1
A10: S6 | B10: 客户价在历史序列中的位置 | C10: 判断客户价是否落近 3 月同口径序列 [min, max]；并找序列中与客户价最接近的点 | D10: 客户价：1400；序列最低：1125.0；序列最高：1250.0 | E10: 在序列内：False；高于序列最高：150.0；最近点：{'gap': 150.0, 'date': '2026-04-27', 'point': 1250.0, 'source': '隆众资讯', 'url': 'https://www.mysteel.com/oilchem/a/26042715/5E8BB24F8B18A1AC.html'}

Sheet 10_沟通事实要点
A1: 与客户沟通可引用的客观事实
A2: 每条都有来源、日期、口径。引用时建议同时说明『这是市场报价区间，实际成交一单一议』。
A4: # | B4: 事实要点 | C4: 来源 | D4: 日期 | E4: 置信度 | F4: 备注
A5: 1 | B5: 2026-10-20 隆众资讯华东市场重质纯碱报价 1050-1200 元/吨（现金含税、送到），该口径已连续。 | C5: 隆众资讯（经我的钢铁网转载） | D5: 2026-10-20 | E5: 高 | F5: 范围对应华东市场整体，非单一厂家
A6: 2 | B6: 同口径自 2026-08-05 至 10-20 基本维持 1050-1200 元/吨，说明近三个月市场中枢稳定。 | C6: 隆众资讯历史日更（多日） | D6: 2026-08-05~10-20 | E6: 高 | F6: 同一来源、同一口径连续序列
A7: 3 | B7: 华东重质 2026 年 4-5 月在 1230-1250 元/吨，6 月一度回到 1250 元/吨，均未达到 1400 元/吨。 | C7: 隆众资讯 / 同花顺 iFinD | D7: 2026-04-27~06-17 | E7: 高 | F7: 已查最近半年华东序列，无 1400 元/吨时点
A8: 4 | B8: 厂家侧交叉验证：江苏井神化工重质报价出厂 1100-1150 元/吨（1016），台玻实联化工重碱送到 1080-1150 元/吨（1016）。 | C8: 隆众资讯企业价格快讯 | D8: 2026-10-16 | E8: 高 | F8: 个别厂家出厂/送到价，不能代表全区市场
A9: 5 | B9: 区域参考（同为含税送到）：华中 1050-1150（1020）、华北 1150（1012）、华南 1200-1300（1012）、东北 1200-1350（1010）。 | C9: 隆众资讯各区域日更 | D9: 2026-10-10~10-20 | E9: 高 | F9: 区域差含运价，应作为『运距解释』而非『市场更贵』
A10: 6 | B10: 期货主力 SA2701 10-19 收盘约 930 元/吨，属不含税盘面价，与含税送到现货不是同一税基。 | C10: 郑商所日行情（隆众简报转述） | D10: 2026-10-19 | E10: 中 | F10: 仅用于说明税基差异，不作为现货参考价
A13: 沟通稿草稿（销售可直接改；内容只含已核实事实，不含价格承诺）
A14: 您好，关于重质纯碱的价格，我把公开市场行情同步给您，方便我们对齐口径： 1）2026-10-20 华东地区市场重质纯碱报价为 1,050–1,200 元/吨（含税、送到），来源：隆众资讯（经我的钢铁网 mysteel.com 转载）。 2）您提到的价格与这个口径相比，差 +275 元/吨（约 24.4%，以区间中值 1,125 元/吨计）。 3）2026-10-20 隆众资讯华东市场重质纯碱报价 1050-1200 元/吨（现金含税、送到），该口径已连续。 4）同口径自 2026-08-05 至 10-20 基本维持 1050-1200 元/吨，说明近三个月市场中枢稳定。 5）华东重质 2026 年 4-5 月在 1230-1250 元/吨，6 月一度回到 1250 元/吨，均未达到 1400 元/吨。 想请您确认：价格含税与否、是出厂还是送到、取得日期与来源、月用量与包装、付款账期。有了这些我按您的实际口径重新对一遍。

Sheet 11_数据来源清单
A1: 数据来源清单（逐条可追溯）
A2: 点链接即可复核原始口径；二手引用已标注「未见表」。
A4: # | B4: 来源 | C4: 类型 | D4: 日期 | E4: 取用内容 | F4: 置信度 | G4: 链接
A5: 1 | B5: 隆众资讯（经我的钢铁网 mysteel.com 转载） | C5: 产业资讯日更报价 | D5: 2026-10-20 | E5: 华东地区 重质纯碱（未细分粒度） 1050-1200（现金含税·送到） | F5: 高 | G5: https://www.mysteel.com/oilchem/a/26102015/0877CD14C3251184.html
A6: 2 | B6: 同花顺 iFinD（iNews 现货汇总） | C6: 行情终端汇总 | D6: 2026-10-10 | E6: 华东地区 重质纯碱 None-None（未注明（同花顺原文未标注含税与否）·未注明） | F6: 中 | G6: https://news.10jqka.com.cn/20261010/c680552148.shtml
A7: 3 | B7: 隆众资讯（经我的钢铁网转载） | C7: 产业资讯日更报价 | D7: 2026-10-12 | E7: 华北地区 重质纯碱（华北） None-None（现金含税·送到） | F7: 高 | G7: https://www.mysteel.com/oilchem/a/26101214/7B985DEE621CAC82.html
A8: 4 | B8: 隆众资讯（经我的钢铁网转载） | C8: 产业资讯日更报价 | D8: 2026-10-12 | E8: 华南地区 重质纯碱（广东） 1200-1300（现汇含税·送到） | F8: 高 | G8: https://www.mysteel.com/oilchem/a/26101214/7FA69DFCD8D8BADE.html
A9: 5 | B9: 隆众资讯（经我的钢铁网转载） | C9: 产业资讯日更报价 | D9: 2026-10-20 | E9: 华中地区 重质纯碱（华中） 1050-1150（现金含税·送到） | F9: 高 | G9: https://www.mysteel.com/oilchem/a/26102015/EA2C185BD7E6C29E.html
A10: 6 | B10: 隆众资讯（经我的钢铁网转载） | C10: 产业资讯日更报价 | D10: 2026-10-10 | E10: 东北地区 重质纯碱（东北） 1200-1350（含税·送到） | F10: 高 | G10: https://www.mysteel.com/oilchem/a/26101014/FF1A43B14CB11155.html
A11: 7 | B11: 生意社（chemall 中国石油和化工网转载） | C11: 第三方资讯 | D11: 2026-10-16 | E11: 华东-山东/苏北出口集散地 重质纯碱（日照、连云港） 1350-1450（未注明·集港价） | F11: 低 | G11: https://www.chemall.com.cn/news/show-264502.html
A12: 8 | B12: 隆众资讯 | C12: 日更区间 | D12: 2026-04-27 | E12: 华东地区 重质纯碱 1230-1250（含税·送到） | F12: 高 | G12: https://www.mysteel.com/oilchem/a/26042715/5E8BB24F8B18A1AC.html
A13: 9 | B13: 隆众资讯 | C13: 日更区间 | D13: 2026-05-19 | E13: 华东地区 重质纯碱 1230-1250（含税·送到） | F13: 高 | G13: https://www.mysteel.com/oilchem/a/26051916/CE4605A2620E90F7.html
A14: 10 | B14: 同花顺 iFinD（主流价） | C14: 主流价单点 | D14: 2026-06-17 | E14: 华东地区 重质纯碱 1250-1250（含税·送到） | F14: 高 | G14: https://news.10jqka.com.cn/20260617/c677534618.shtml
A15: 11 | B15: 隆众资讯 | C15: 日更区间 | D15: 2026-07-27 | E15: 华东地区 重质纯碱 1150-1250（含税·送到） | F15: 高 | G15: https://www.mysteel.com/oilchem/a/26072716/13649DB9A94FCAFB.html
A16: 12 | B16: 同花顺 iFinD（主流价） | C16: 主流价单点 | D16: 2026-07-28 | E16: 华东地区 重质纯碱 1215-1215（未注明·未注明） | F16: 高 | G16: https://stock.10jqka.com.cn/20260728/c678488931.shtml
... A28: 24 | B28: 隆众资讯 | C28: 日更区间 | D28: 2026-10-20 | E28: 华东地区 重质纯碱 1050-1200（含税·送到） | F28: 高 | G28: https://www.mysteel.com/oilchem/a/26102015/0877CD14C3251184.html
