Workbook

Sheet 00_说明
A1: 供应商真伪核验工作簿 · 纯碱（碳酸钠 Na₂CO₃）
A2: 查供应商是不是真厂家：直接生产证据 / 间接业务证据 / 不构成证据 三分法 + 四类结论 + 12 项索取清单
A3: 报告编号 SV-2026-CN-NA2CO3-001 产品 纯碱（碳酸钠 Na₂CO₃） 规格 轻质 / 重质；GB/T 210 Ⅱ类优等品；重碱执行郑商所纯碱期货交割标准 数据截止 2026-10-19 版本 v1.0
A6: 一、这份表解决什么问题
B7: 内贸采购最怕把贸易商当厂家：报价、账期都谈成了，最后发现对方只是调货，质量、交期、发票主体全都对不上。本工作簿不靠“经营范围”和“厂家直销”下结论，而是把材料分成三组：能直接指向装置的硬证据、只能说明在做生意的旁证、以及最容易被误采信的材料。
B8: 5 个案例演示同一套方法的不同落点：山东海化（生产厂家）、博源银根（生产厂家）、杭实善成（贸易经销）、分装样例（分装或复配）、证据不足样例（证据不足暂无法确认）。
A10: 二、五步使用法
A11: STEP 1 | B11: 录入企业与产品：企业全名、统一社会信用代码、目标产品与规格（轻质 / 重质；GB/T 210 Ⅱ类优等品；重碱执行郑商所纯碱期货交割标准）。
A12: STEP 2 | B12: 跑直接证据：排污许可证（行业类别：无机碱制造 C2612）；项目环评批复 + 竣工环保验收（载明纯碱产品与产能）；产能置换公示 / 技改项目备案（联碱、氨碱、天然碱）；上市公司产量、非计划停产公告。
A13: STEP 3 | B13: 补间接证据：官网产品页、自营商城、交易所交割厂库、协会名录、原料采购、生产岗位招聘、专利、行业报道。
A14: STEP 4 | B14: 剔除伪证据：把营业执照经营范围、“厂家直销”、注册资本、可大量供货、单张照片单独归入“不构成证据”，不计分。
A15: STEP 5 | B15: 按 Q1→Q4 判定，输出四类结论之一；证据不足就写“暂无法确认”，并按 06 表发索取清单。
A17: 三、证据三分法
B18: A 直接生产证据 | C18: 能独立指向“装置存在且在运行” | E18: 排污许可证（行业类别：无机碱制造 C2612）；环评批复与验收、项目备案/产能置换、上市公司产量、非计划停产公告
B19: B 间接业务证据 | C19: 说明在做这门生意，不能单独证明自产 | E19: 官网产品页、自营商城、交易所交割厂库、协会名录、原料采购、生产岗位招聘、专利、行业报道
B20: C 不构成证据 | C20: 容易被误采信，采信会出错 | E20: 营业执照经营范围、“厂家直销”、注册资本、可大量供货、单张无定位照片、口头承诺
A22: 四、判定顺序（不能跳步）
B23: 步骤 | C23: 问题 | D23: 判定依据（命中任一即可） | G23: 是 → | H23: 否 →
B24: Q1 | C24: 是否存在以该企业为主体的目标产品生产硬证据？ | D24: 排污许可证（对应行业类别）；或环评批复/验收载明该产品与产能；或项目备案/产能置换公示载明该企业为主体；危化品/食品/农药等另有法定许可 | G24: 进入 Q2 | H24: 进入 Q3
B25: Q2 | C25: 公开产能、产量、厂址与许可是否自洽？ | D25: 产能与产量量级匹配、厂址与许可地址一致、工艺路线能解释原料与副产品、产品规格对得上 | G25: 判定：生产厂家 | H25: 判定：生产厂家（待现场核验）
B26: Q3 | C26: 是否存在分装/复配特征？ | D26: 仅持有分装类许可；无合成/反应/精馏/结晶主装置；设备为粉碎、筛分、混合、稀释、包装；外购成品或半成品 | G26: 判定：分装或复配 | H26: 进入 Q4
B27: Q4 | C27: 是否存在贸易经销特征？ | D27: 交易所贸易商厂库、生产厂代理授权、无生产装置与排污许可、注册地为写字楼、以调货为主 | G27: 判定：贸易经销 | H27: 判定：证据不足，暂无法确认
A29: 五、四类结论与含义
B30: 结论 | C30: 含义 | F30: 典型证据
B31: 生产厂家 | C31: 以自有装置完成目标化学品的合成/提纯，可开出厂价、可验厂 | F31: 排污许可证（行业类别：无机碱制造 C2612）；项目环评批复 + 竣工环保验收（载明纯碱产品与产能）
B32: 分装或复配 | C32: 不合成目标产品，仅做破碎、筛分、混合、稀释、小包装或复配 | F32: 分装类许可/备案 + 后处理设备清单 + 外购成品发票
B33: 贸易经销 | C33: 以调货、代理、仓储交割为主，无自有生产装置 | F33: 贸易商厂库/代理授权 + 无排污许可 + 背靠背发票
B34: 证据不足暂无法确认 | C34: 公开可核证据不足以支撑任何一类判断，需补材料或现场核验 | F34: 仅有执照、报价单、无定位照片；既无硬证据也无贸易侧证
A36: 免责：本工作簿为采购尽调辅助工具，不构成法律意见；“证据充分度”衡量证据链完整度，不代表企业信用或产品质量。脱敏样例不对应任何真实企业。数据截止 2026-10-19，正式签约前应重新核验许可与名单。

Sheet 01_核验总表
A1: 01 · 核验总表
A2: 5 家供应商的核验结论与证据计数（纯碱（碳酸钠 Na₂CO₃））；计数列由 02/03/04 三张明细表自动汇总。
A3: 报告编号 SV-2026-CN-NA2CO3-001 数据截止 2026-10-19 ★ 可直接在空白行套用：填企业名 → 明细表打标签 → 计数与分数自动更新
A4: 序号 | B4: 企业名称 | C4: 产品 / 规格 | D4: 核验结论 | E4: 证据充分度 | F4: 置信度 | G4: 生产地址（公开） | H4: 公开产能 | I4: 工艺路线 | J4: 直接证据 | K4: 间接证据 | L4: 排除项 | M4: 关键缺口 / 风险 | N4: 建议动作 | O4: 报告日期
A5: 1 | B5: 山东海化股份有限公司 | C5: 纯碱（碳酸钠）· 轻质 / 重质 · 工业级 | D5: 生产厂家 | E5: ='05_评分模型'!C10 | F5: 高 | G5: 山东省潍坊市滨海经济技术开发区沂河大街14201号 | H5: 280 万吨/年（老线 120 + 新线 160） | I5: 氨碱法（索尔维法） | J5: =COUNTIFS('02_直接生产证据'!$B$4:$B$200,$B5) | K5: =COUNTIFS('03_间接业务证据'!$B$4:$B$200,$B5) | L5: =COUNTIFS('04_不构成证据'!$B$4:$B$200,$B5) | M5: 排污许可证副本中“主要生产设施”与“排放口”页（确认碳化塔、煅烧炉、蒸氨塔在证） | N5: 先做视频验厂（碳化塔—煅烧—包装线—地磅），再签“生产商=发票销售方=发货地”三合一条款；技改期约定供应保障。 | O5: 2026-10-19
A6: 2 | B6: 内蒙古博源银根化工有限公司 | C6: 纯碱（碳酸钠）· 重质为主 · 天然碱法 | D6: 生产厂家 | E6: ='05_评分模型'!D10 | F6: 高 | G6: 内蒙古自治区阿拉善盟阿拉善右旗塔木素苏木恩格日乌苏嘎查 | H6: 一期 500 万吨/年（规划总产能 780 万吨/年） | I6: 天然碱法（一水碱/倍半碱加工） | J6: =COUNTIFS('02_直接生产证据'!$B$4:$B$200,$B6) | K6: =COUNTIFS('03_间接业务证据'!$B$4:$B$200,$B6) | L6: =COUNTIFS('04_不构成证据'!$B$4:$B$200,$B6) | M6: 排污许可证（行业类别、主要生产设施、排放口） | N6: 天然碱法重碱粒度与堆积密度需与玻璃窑炉匹配，先索取样检测；确认二期投产节奏对 2027 年供应量的影响。 | O6: 2026-10-19
A7: 3 | B7: 浙江杭实善成实业有限公司 | C7: 纯碱（碳酸钠）· 贸易分销 | D7: 贸易经销 | E7: ='05_评分模型'!E10 | F7: 高 | G7: 浙江省杭州市（杭实集团体系） | H7: 无自有纯碱合成装置 | I7: —（不涉及合成） | J7: =COUNTIFS('02_直接生产证据'!$B$4:$B$200,$B7) | K7: =COUNTIFS('03_间接业务证据'!$B$4:$B$200,$B7) | L7: =COUNTIFS('04_不构成证据'!$B$4:$B$200,$B7) | M7: 生产厂（山东海化/三友/金山等）出具的经销授权书 | N7: 可与其做分销/代采，但合同须写明“实际生产商”并附授权链；要求发票由碱厂直开或提供完整背靠背链条。 | O7: 2026-10-19
A8: 4 | B8: 某食品配料有限公司（脱敏样例） | C8: 食品添加剂碳酸钠（食用纯碱）· 小包装分装 | D8: 分装或复配 | E8: ='05_评分模型'!F10 | F8: 中高 | G8: 华东某食品产业园（脱敏） | H8: 分装/复配产能，无合成产能 | I8: 物理后处理（无碳化、无蒸氨、无煅烧） | J8: =COUNTIFS('02_直接生产证据'!$B$4:$B$200,$B8) | K8: =COUNTIFS('03_间接业务证据'!$B$4:$B$200,$B8) | L8: =COUNTIFS('04_不构成证据'!$B$4:$B$200,$B8) | M8: SC 证明细页（确认“分装”单元与品种） | N8: 按“分装商”而非“厂家”议价；要求其标注实际生产厂与批号，食品级需提供 GB 1886.1 全项检测。 | O8: 2026-10-19
A9: 5 | B9: 某询价供应商（脱敏样例） | C9: 纯碱（碳酸钠）· 重质 | D9: 证据不足暂无法确认 | E9: ='05_评分模型'!G10 | F9: 低 | G9: 未披露（执照地址为某写字楼） | H9: 未披露 | I9: 未披露 | J9: =COUNTIFS('02_直接生产证据'!$B$4:$B$200,$B9) | K9: =COUNTIFS('03_间接业务证据'!$B$4:$B$200,$B9) | L9: =COUNTIFS('04_不构成证据'!$B$4:$B$200,$B9) | M9: 排污许可证或环评批复（任一即可打破僵局） | N9: 先按“未认证供应商”处理：不预付、不做长协；补齐 P0 材料后再复核，或直接转向已核验的碱厂/授权经销商。 | O9: 2026-10-19

Sheet 02_直接生产证据
A1: 02 · 直接生产证据
A2: 只有这一组能独立支撑“装置存在且在运行”。判定时只看 A 组；B 组用于交叉，C 组不计分。
A3: 报告编号 SV-2026-CN-NA2CO3-001 数据截止 2026-10-19 证据强度：●●● 强 / ●●○ 中 / ●○○ 弱
A4: 证据编号 | B4: 企业名称 | C4: 证据类别 | D4: 证据名称 | E4: 证据内容 / 原文摘录 | F4: 来源机构 | G4: 来源链接 | H4: 发布 / 有效期 | I4: 证据强度 | J4: 采信理由（为什么算 / 为什么不算） | K4: 对应结论
A5: D1 | B5: 山东海化股份有限公司 | C5: 许可与环保 | D5: 排污许可证：行业类别“无机碱制造” | E5: 山东海化股份有限公司纯碱厂 生产经营场所地址：山东省潍坊市滨海经济技术开发区沂河大街014201号 行业类别：无机碱制造 所在地区：山东省-潍坊市-滨海区 发证机关：潍坊市生态环境局 | F5: 全国排污许可证管理信息平台 | G5: https://permit.mee.gov.cn/perxxgkinfo/xkgkAction!xkgk.action?xkgk=getxxgkContent&dataid=0dc1d33753c74827836b97bf901ac9d8 | H5: 2026-08 复核（有效期内） | I5: ●●● 强 | J5: 排污许可按“行业类别 + 主要生产设施 + 排放口”核发，无机碱制造类别对应纯碱/烧碱生产装置；证载厂址与官网门牌一致，可排除“注册在 A 地、生产挂靠 B 厂”的常见套牌。这是本案例最硬的一条证据。 | K5: 生产厂家
A6: D2 | B6: 山东海化股份有限公司 | C6: 产能与装置 | D6: 官网工厂页：两条线、280 万吨、15 个车间 | E6: 建成新、老两条生产线，其中老线120万吨，新线160万吨，年生产能力达280万吨，占全国总产能的十分之一……设有1个生产运行中心、7个部室、15个车间。在岗员工1886人……主导产品为纯碱（Na2CO3），分为轻质纯碱、重质纯碱，生产工艺为氨碱法。 | F6: 山东海化集团官网 · 成员企业 | G6: https://www.haihua.com.cn/About_11/1664471386467147776.html | H6: 2026-10 访问 | I6: ●●○ 中 | J6: 官网属于企业自述，单独看只能算“弱证据”；但该页同时给出装置条线、车间编制、在岗人数、工艺路线与门牌地址，可与 D1 的许可地址、D3 的年报产量三角互证，因此升级采信为直接证据的辅证。 | K6: 生产厂家
A7: D3 | B7: 山东海化股份有限公司 | C7: 产能与装置 | D7: 上市公司年报：2023 年实际生产 319.31 万吨 | E7: 全年生产纯碱319.31万吨、烧碱（折百）27.70万吨。公司采用的氨碱法纯碱生产工艺虽在生产成本方面承压较大，但在产品品质…… | F7: 山东海化 2023 年年度报告（PDF） | G7: https://stockn.xueqiu.com/SZ000822/20240321181962.pdf | H7: 2024-03 披露 | I7: ●●● 强 | J7: 上市公司年报披露的“生产量”口径为自产而非采购转售；319 万吨高于 280 万吨设计产能，符合氨碱装置长周期满负荷、技改挖潜的运行特征，数量级上无法由贸易量伪造。 | K7: 生产厂家
A8: D4 | B8: 山东海化股份有限公司 | C8: 产能与装置 | D8: 产能置换技改：120 万吨氨碱改 100 万吨联碱 | E8: 以100万吨/年联碱法纯碱装置产能，置换替代公司已运行超过30年的120万吨/年氨碱法纯碱老生产线……产能置换比例为1.2:1，属于减量置换。项目总投资为48.37亿元。 | F8: 公司公告 / 新浪财经 / 齐鲁网 | G8: https://finance.sina.com.cn/wm/2026-03-02/doc-inhpqvan8207030.shtml | H8: 2026-03 至 2026-10 | I8: ●●● 强 | J8: 纯碱技改须履行产能置换程序：经省级主管部门公示、重新环评并变更排污许可。一份“减量置换”公告等于官方间接确认：该企业名下确有 120 万吨在产氨碱装置。同时提示 2026—2028 年老线停产改造，供货稳定性要写进合同。 | K8: 生产厂家
A9: D5 | B9: 山东海化股份有限公司 | C9: 许可与环保 | D9: 同址小苏打装置单独持证（证书编号可核） | E9: 排污许可证 证书编号：91370700MA3WQ80C30002V 单位名称：山东海化股份有限公司小苏打厂-小苏打二车间 生产经营场所地址：山东省潍坊市滨海经济开发区沂河大街014201号山东海化股份有限公司纯碱厂内 行业类别：无机碱制造 | F9: 全国排污许可证管理信息平台 | G9: https://permit.mee.gov.cn/perxxgkinfo/syssb/xkgg/xkgg!downloadFile.action?method=download&fileType=fbfile&datafileid=83c3cc72f1254301a1a704d07865d270&dataid=3b5cdc9a379841209f6d3c32e4038047 | H9: 2026-08 复核 | I9: ●●○ 中 | J9: 小苏打（碳酸氢钠）装置建在纯碱厂内并单独持证，说明这里是“装置群”而非单一包装车间；纯碱—小苏打联产正是氨碱/联碱企业的典型厂区结构，贸易商不可能具备。 | K9: 生产厂家
A10: D6 | B10: 山东海化股份有限公司 | C10: 产能与装置 | D10: 自有原盐基地：羊口盐场为股份公司成员企业 | E10: 山东海化股份有限公司 → 山东海化股份有限公司纯碱厂 / 山东海化股份公司羊口盐场 / 山东海化股份有限公司小苏打厂 / 山东海化股份有限公司氯化钙厂 | F10: 山东海化集团官网 · 成员企业导航 | G10: https://www.haihua.com.cn/About_11/1664470890664321024.html | H10: 2026-10 访问 | I10: ●●○ 中 | J10: 氨碱法每吨纯碱约耗原盐 1.5 吨，原盐成本占比高。自有盐场 + 纯碱厂 + 氯化钙厂（消化废液）构成典型氨碱一体化布局，是“真工厂”的结构性特征；纯贸易商没有这种资产组合。 | K10: 生产厂家
A11: D1 | B11: 内蒙古博源银根化工有限公司 | C11: 产能与装置 | D11: 上市公司公告：一期 500 万吨纯碱达产 | E11: 银根矿业阿拉善塔木素天然碱开发利用项目规划总产能为纯碱780万吨/年、小苏打80万吨/年……目前一期已达产，已形成年产500万吨纯碱和40万吨小苏打的生产能力。 | F11: 博源化工（000683）公告 · 巨潮资讯 / 新浪财经 | G11: https://static.cninfo.com.cn/finalpage/2026-05-20/1225316281.PDF | H11: 2026-05-20 | I11: ●●● 强 | J11: 上市公司公告对“达产”表述承担披露责任，且产能数字与项目备案、后续碳回收项目规模互相印证，属于强证据。 | K11: 生产厂家
A12: D2 | B12: 内蒙古博源银根化工有限公司 | C12: 产能与装置 | D12: 二期启动公告：分期建设、总投资与进度 | E12: 项目总体规划纯碱780万吨/年、小苏打80万吨/年，分两期建设，其中一期规划建设纯碱500万吨/年……本次启动阿拉善塔木素天然碱开发利用项目二期。 | F12: 远兴能源公告（PDF） | G12: https://pdf.dfcfw.com/pdf/H2_AN202312281615153969_1.pdf | H12: 2023-12-28 | I12: ●●● 强 | J12: 分期建设的产能规划与 D1 的“一期达产”形成时间序列，说明不是一次性宣传口径，而是持续投入的实体项目。 | K12: 生产厂家
A13: D3 | B13: 内蒙古博源银根化工有限公司 | C13: 产能与装置 | D13: 资源底座：塔木素天然碱矿 10.78 亿吨 | E13: 公司位于内蒙古阿拉善盟阿拉善右旗塔木素苏木恩格日乌苏嘎查境内……所持有并开采的塔木素天然碱矿资源储量丰富，已探明天然碱矿石量10.78亿吨。 | F13: 内蒙古博源银根矿业官网 | G13: https://boyuanyingen.com/ | H13: 2026-10 访问 | I13: ●●○ 中 | J13: 天然碱法企业必须绑定矿山资源与采矿权。有矿权、有选矿与加工装置，才可能稳定产出重碱；纯贸易商无法复制这一结构。 | K13: 生产厂家
A14: D4 | B14: 内蒙古博源银根化工有限公司 | C14: 产能与装置 | D14: 非计划停产公告：降负荷 3,000 吨/天 | E14: 远兴能源：控股子公司阿拉善塔木素天然碱开发利用项目生产线因设备故障降负荷运行，预计影响纯碱产量约3,000吨/天。 | F14: 财联社 | G14: https://www.cls.cn/detail/1790345 | H14: 2025-04 | I14: ●●● 强 | J14: “停产/降负荷”公告是判断真实在产的最好侧证：只有拥有运行装置的企业，才需要向市场披露产量损失。造假者通常只宣传产能，不会公告故障。 | K14: 生产厂家
A15: D5 | B15: 内蒙古博源银根化工有限公司 | C15: 产能与装置 | D15: 项目列入自治区与盟级重点项目 | E15: 银根矿业阿拉善塔木素天然碱项目已被列为阿拉善盟和内蒙古自治区重点项目。 | F15: 券商研报 / 证券时报 | G15: https://www.stcn.com/article/detail/1077670.html | H15: 2023-12 | I15: ●●○ 中 | J15: 重点项目身份意味着备案、用地、环评、能耗指标均已落地；属间接证据，需与 D1/D2 联读。 | K15: 生产厂家

Sheet 03_间接业务证据
A1: 03 · 间接业务证据
A2: 能证明“确实在做纯碱（碳酸钠 Na₂CO₃）这门生意”，但不能单独证明自产，必须与 A 组联读。
A3: 报告编号 SV-2026-CN-NA2CO3-001 数据截止 2026-10-19 证据强度：●●● 强 / ●●○ 中 / ●○○ 弱
A4: 证据编号 | B4: 企业名称 | C4: 证据类别 | D4: 证据名称 | E4: 证据内容 / 原文摘录 | F4: 来源机构 | G4: 来源链接 | H4: 发布 / 有效期 | I4: 证据强度 | J4: 采信理由（为什么算 / 为什么不算） | K4: 对应结论
A5: I1 | B5: 山东海化股份有限公司 | C5: 产品与市场 | D5: 海化商城：自建 B2B 在售纯碱 | E5: 海化商城为山东海化自营电子交易平台，挂牌销售纯碱、小苏打、氯化钙、溴素等自产品。 | F5: 海化商城（e-sale.haihua.com.cn） | G5: https://e-sale.haihua.com.cn | H5: 2026-10 访问 | I5: ●●○ 中 | J5: 自营平台说明“销售主体 = 生产主体”，可作为交付与结算路径的佐证；但平台本身不证明产能，需与 D1/D3 联合使用。 | K5: 生产厂家
A6: I2 | B6: 山东海化股份有限公司 | C6: 产品与市场 | D6: 官网产品名录：轻质/重质纯碱规格齐全 | E6: 产品名录按纯碱（轻质、重质）、小苏打、氯化钙、溴素等分类，标注牌号“鸢都”及应用领域。 | F6: 山东海化集团官网 · 产品营销 | G6: https://www.haihua.com.cn/About_6/990945257334263808.html | H6: 2026-10 访问 | I6: ●●○ 中 | J6: 产品页能证明“公开资料中存在目标产品”，是判断供应商是否经营该品类的必要但不充分条件；需注意贸易商官网同样可以挂产品页。 | K6: 生产厂家
A7: I3 | B7: 山东海化股份有限公司 | C7: 运营痕迹 | D7: 物流配置：铁运分公司 + 汽运公司 + 供应链公司 | E7: 成员企业含：山东海化能源有限公司铁运分公司、山东海化集团潍坊永安汽车运输有限公司、潍坊长运供应链管理有限公司。 | F7: 山东海化集团官网 · 成员企业 | G7: https://www.haihua.com.cn/About_11/1664470890664321024.html | H7: 2026-10 访问 | I7: ●●○ 中 | J7: 大宗纯碱依赖铁路专用线与汽运车队。自有铁运/汽运主体说明其具备整列发运与出厂交付能力，与“厂门口提货”的贸易商模式不同。 | K7: 生产厂家
A8: I4 | B8: 山东海化股份有限公司 | C8: 运营痕迹 | D8: 人才招聘入口：长期招录化工操作与设备岗位 | E8: 官网设“社会招聘 / 校园招聘”栏目，岗位以化工操作、设备维护、分析化验为主。 | F8: 山东海化集团官网 · 人才招聘 | G8: https://www.haihua.com.cn/About_14.html | H8: 2026-10 访问 | I8: ●○○ 弱 | J8: 连续招聘一线操作岗是“装置在运行”的软信号；但需抓到具体岗位 JD（含工作地点、班制、装置名称）才能升级为中等强度证据。 | K8: 生产厂家
A9: I5 | B9: 山东海化股份有限公司 | C9: 产品与市场 | D9: 行业媒体：48 亿元绿色技改的持续报道 | E9: 4.83亿元政策性借款落地，将用于山东海化纯碱改造项目；项目以100万吨/年联碱法装置置换原有120万吨/年氨碱法装置。 | F9: 新浪财经 / 齐鲁网 / 中证网 | G9: https://news.iqilu.com/shandong/shandonggedi/20261013/5951923.shtml | H9: 2026-03 至 2026-10 | I9: ●○○ 弱 | J9: 多家媒体与政策性银行同时披露同一项目，说明项目已进入资金落地阶段；媒体本身是二手信息，只作旁证，不替代 D4 的公告原文。 | K9: 生产厂家
A10: I1 | B10: 内蒙古博源银根化工有限公司 | C10: 运营痕迹 | D10: 碳回收综合利用项目：装置群在扩张 | E10: 利用天然碱开发利用项目生产过程中产生的二氧化碳气体及含碱母液，结合风电、光伏发电……投资建设碳回收综合利用项目。 | F10: 公司公告（PDF） | G10: https://file.finance.qq.com/finance/hs/pdf/2025/04/25/1223283096.PDF | H10: 2025-04-25 | I10: ●●○ 中 | J10: 碳回收项目依附于纯碱装置的二氧化碳与含碱母液，说明主装置已稳定运行并产生可计量的尾气/母液。 | K10: 生产厂家
A11: I2 | B11: 内蒙古博源银根化工有限公司 | C11: 产品与市场 | D11: 纯碱期货交割品牌与厂库体系 | E11: 生产企业符合纯碱期货交割标准的重碱年产量30万吨以上；贸易企业符合纯碱期货交割标准的重碱年贸易量15万吨以上。 | F11: 郑州商品交易所 | G11: https://finance.sina.com.cn/wm/2026-07-06/doc-inifwmvv1799146.shtml | H11: 2026-07 公告 | I11: ●●○ 中 | J11: 郑商所对生产型厂库设有 30 万吨/年重碱产量门槛并需现场考察，进入交割体系可作为产能与品质的第三方背书；具体名单应以郑商所最新公告为准。 | K11: 生产厂家
A12: I3 | B12: 内蒙古博源银根化工有限公司 | C12: 产品与市场 | D12: 行业报道：天然碱法成本优势 | E12: 天然碱法单吨成本显著低于氨碱法，项目投产后改变国内纯碱供给格局。 | F12: 证券时报 / 券商研报 | G12: https://www.stcn.com/article/detail/1077670.html | H12: 2024—2025 | I12: ●○○ 弱 | J12: 媒体分析属二手信息，仅用于理解其成本位置与扩产动机，不单独作为产能证据。 | K12: 生产厂家
A13: I1 | B13: 浙江杭实善成实业有限公司 | C13: 产品与市场 | D13: 郑商所公告：增设为纯碱指定交割厂库 | E13: 郑商所8月25日——关于增设指定纯碱交割厂库的公告：增设……浙江杭实善成实业有限公司、河北正大玻璃有限公司为指定纯碱交割厂库。 | F13: 郑州商品交易所公告（2020-08-25） | G13: https://www.xinhu.cn/article/zhengshangsuo8yue25ri-guanyuzengshezhidingchunjianjiaogechangkudegonggao-91311-1.html | H13: 2020-08-26 | I13: ●●● 强 | J13: 这是“正向的贸易证据”：能成为交割厂库说明其具备仓储、质检、资金与交割能力，但郑商所规则同时允许生产企业和贸易企业申请，因此该资格不能推出“自产”。 | K13: 贸易经销
A14: I2 | B14: 浙江杭实善成实业有限公司 | C14: 产品与市场 | D14: 行业媒体明确称其为“纯碱贸易商厂库” | E14: 浙江杭实善成实业有限公司、浙江景诚实业有限公司、杭州冀正贸易有限公司等多家纯碱贸易商厂库也都落地于此，为当地纯碱市场营造了较好的期现氛围。 | F14: 期货日报（走访沙河） | G14: https://edu.dzqh.com.cn:33443/14393.html | H14: 2024—2025 | I14: ●●● 强 | J14: 媒体将其与另两家贸易企业并列称为“贸易商厂库”，性质表述明确；这比“没有找到生产证据”更强，属于对“贸易经销”的正向认定。 | K14: 贸易经销
A15: I3 | B15: 浙江杭实善成实业有限公司 | C15: 运营痕迹 | D15: 公司化工事业部负责人谈纯碱期现与贸易 | E15: 浙江杭实善成实业有限公司玻璃纯碱负责人刘哲表示，2024年上半年，重碱需求端光伏玻璃及浮法玻璃产量增加对纯碱现货价格有一定支撑…… | F15: 证券时报 / 上海证券报 | G15: https://stcn.com/article/detail/1510460.html | H15: 2019-12 至 2025-01 | I15: ●●○ 中 | J15: 以“玻璃纯碱负责人”身份对现货价格与需求发表判断，符合贸易商/期现商的业务角色；生产企业通常由销售或生产负责人出面谈产能与成本。 | K15: 贸易经销
A16: I4 | B16: 浙江杭实善成实业有限公司 | C16: 产品与市场 | D16: 沙河布局：贴近玻璃集群的贸易商厂库 | E16: 沙河是纯碱和玻璃产品的集散地……多家纯碱贸易商厂库落地于此。 | F16: 期货日报 | G16: https://edu.dzqh.com.cn:33443/14393.html | H16: 2024—2025 | I16: ●●○ 中 | J16: 在消费地设厂库、做期现套利，是贸易商的典型动作；生产企业会在资源地建装置，不会只在集散地建库。 | K16: 贸易经销
A17: I1 | B17: 某食品配料有限公司（脱敏样例） | C17: 许可与环保 | D17: 食品生产许可证：许可明细为“分装” | E17: 许可类别：食品添加剂；品种明细：碳酸钠（分装）；生产地址：XX 食品产业园 3 号厂房。 | F17: 国家企业信用信息公示系统 / 对方提供 | H17: 2026-09 | I17: ●●○ 中 | J17: SC 证能证明“有食品级生产/分装资质”，但“分装”二字同时说明其不合成纯碱。这是典型的“真证、非厂家”。 | K17: 分装或复配
A18: I2 | B18: 某食品配料有限公司（脱敏样例） | C18: 产能与装置 | D18: 车间设备清单：只有后处理设备 | E18: 主要设备：气流粉碎机、旋振筛、V 型混合机、螺杆计量包装机、喷码机。 | F18: 对方提供的设备清单与车间照片 | H18: 2026-09 | I18: ●●○ 中 | J18: 纯碱合成需要碳化塔、蒸氨塔、煅烧炉、凉碱炉等大型装置。仅有粉碎—筛分—混合—包装，属于物理后处理，不具备合成能力。 | K18: 分装或复配
A19: I3 | B19: 某食品配料有限公司（脱敏样例） | C19: 运营痕迹 | D19: 原料采购发票：向碱厂购买重碱 | E19: 购买方：某食品配料有限公司；销售方：XX 碱业有限公司；品名：重质纯碱；数量：300 吨。 | F19: 对方提供的采购发票（脱敏） | H19: 2026-08 | I19: ●●○ 中 | J19: 原料端外购是分装/复配的定性证据。结合 I2 的设备清单，可确认其业务是“买碱—加工—卖小包装”。 | K19: 分装或复配
A20: I4 | B20: 某食品配料有限公司（脱敏样例） | C20: 产品与市场 | D20: 客户结构：食品与日化小包装定制 | E20: 为食品厂、日化企业提供 1kg/25kg 定制小包装与复配助剂。 | F20: 官网/客户案例 | H20: 2026-09 | I20: ●○○ 弱 | J20: 小批量、多规格、定制包装是分装商的典型客户结构，与碱厂“整车、散装、长协”的销售模式明显不同。 | K20: 分装或复配
A21: I1 | B21: 某询价供应商（脱敏样例） | C21: 产品与市场 | D21: 报价单：品名与价格，但缺少生产厂 | E21: 纯碱 99.2% 重质，出厂价 XXXX 元/吨，交货地：待定，生产厂：未注明。 | F21: 对方提供（脱敏） | H21: 2026-10 | I21: ●○○ 弱 | J21: 报价单只能证明“愿意卖”，不能证明“谁来生产”。缺少生产厂、执行标准、交货地与结算方式，无法与任何装置对应。 | K21: 证据不足暂无法确认

Sheet 04_不构成证据
A1: 04 · 不构成证据（排除项）
A2: 这些材料不是“没用”，而是“不能用来证明自产”。把它们单独归档，可以避免把贸易商误判成厂家。
A3: 报告编号 SV-2026-CN-NA2CO3-001 数据截止 2026-10-19 本表不计入证据充分度
A4: 编号 | B4: 企业名称 | C4: 材料 / 常见话术 | D4: 对方常见表述 | E4: 为什么不算证据 | F4: 正确用法 / 应换取的替代证据
A5: X1 | B5: 山东海化股份有限公司 | C5: 营业执照经营范围含“纯碱生产、销售” | D5: 经营范围：纯碱、小苏打、氯化钙、溴素的生产与销售…… | E5: 经营范围是登记承诺，不是产能许可。大量贸易商、代理商同样登记“生产”字样；市场监管部门不核验是否真有装置。只能证明“允许做”，不能证明“在做”。 | F5: 见 06 表对应材料：排污许可 / 环评 / 磅单 / 发票 / 视频验厂
A6: X2 | B6: 山东海化股份有限公司 | C6: 官网/销售话术“厂家直销、源头工厂” | D6: 厂家直销，一手货源，支持验厂。 | E6: 属于企业自述营销语，无第三方可核对象。真正可核的是“哪套装置、哪个地址、哪张排污证”，而不是“厂家”两个字。 | F6: 见 06 表对应材料：排污许可 / 环评 / 磅单 / 发票 / 视频验厂
A7: X3 | B7: 山东海化股份有限公司 | C7: 注册资本、成立年限、集团排名 | D7: 注册资本 12 亿元，成立于 1998 年，中国化工 500 强。 | E7: 资金实力与是否自产无因果关系。贸易商同样可以注册资本过亿；老企业也可能早已停产、只留贸易主体。 | F7: 见 06 表对应材料：排污许可 / 环评 / 磅单 / 发票 / 视频验厂
A8: X4 | B8: 山东海化股份有限公司 | C8: “月供万吨、价格低于市场 50 元/吨” | D8: 每月可稳定供应 1 万吨，价格比出厂价低 50 元。 | E8: 供货能力与价格优势只能说明资金和渠道，反而更像是贸易商在调货。低于出厂价长期供货，需警惕品牌串货或转手货源。 | F8: 见 06 表对应材料：排污许可 / 环评 / 磅单 / 发票 / 视频验厂
A9: X5 | B9: 山东海化股份有限公司 | C9: 一张工厂照片 / 一段车间视频 | D9: （对方微信发送的厂区照片，无水印、无定位、无门牌） | E9: 照片可盗用、可购买、可在他人厂区拍摄。必须与排污证地址、卫星图、装置特征（碳化塔高度、煅烧炉、凉碱炉、包装线）比对后才可采信。 | F9: 见 06 表对应材料：排污许可 / 环评 / 磅单 / 发票 / 视频验厂
A10: X1 | B10: 内蒙古博源银根化工有限公司 | C10: 工商经营范围含“纯碱生产” | D10: 经营范围：纯碱、小苏打的生产与销售。 | E10: 同前：登记承诺不等于装置存在，尤其对项目公司而言，经营范围往往在项目立项时即写入。 | F10: 见 06 表对应材料：排污许可 / 环评 / 磅单 / 发票 / 视频验厂
A11: X2 | B11: 内蒙古博源银根化工有限公司 | C11: “国内最大天然碱基地”宣传语 | D11: 打造国内最大天然碱生产基地。 | E11: 宣传语无法核验，需落到具体公告的产能数字与达产时间。 | F11: 见 06 表对应材料：排污许可 / 环评 / 磅单 / 发票 / 视频验厂
A12: X3 | B12: 内蒙古博源银根化工有限公司 | C12: 一期达产的新闻通稿（转载） | D12: 多家媒体转载“一期达产”消息。 | E12: 转载不等于独立信源，且通稿常由企业提供。以 D1 的公告原文为准，通稿只作传播痕迹。 | F12: 见 06 表对应材料：排污许可 / 环评 / 磅单 / 发票 / 视频验厂
A13: X1 | B13: 浙江杭实善成实业有限公司 | C13: 公司名称含“实业”二字 | D13: 浙江杭实善成实业有限公司 | E13: “实业”只是字号用词，工商登记不核验是否有工厂。大量贸易、供应链、投资公司都以“实业”命名。 | F13: 见 06 表对应材料：排污许可 / 环评 / 磅单 / 发票 / 视频验厂
A14: X2 | B14: 浙江杭实善成实业有限公司 | C14: 纯碱指定交割厂库资格 | D14: 我们是郑商所纯碱交割厂库。 | E14: 最容易误读的一条。郑商所规则允许生产企业和贸易企业申请厂库，贸易企业只需重碱年贸易量 15 万吨以上（生产企业为产量 30 万吨以上）。厂库资格证明“能交割”，不证明“能生产”。 | F14: 见 06 表对应材料：排污许可 / 环评 / 磅单 / 发票 / 视频验厂
A15: X3 | B15: 浙江杭实善成实业有限公司 | C15: 注册资本、集团背景、仓储面积 | D15: 注册资本 1 亿元，背靠杭实集团，自有仓库 2 万平米。 | E15: 资金与仓储是贸易能力，不是生产能力。仓库可以存放别家生产的纯碱。 | F15: 见 06 表对应材料：排污许可 / 环评 / 磅单 / 发票 / 视频验厂
... A22: X3 | B22: 某询价供应商（脱敏样例） | C22: “我们有自己的厂，欢迎来看” | D22: 厂在XX，随时可以来看。 | E22: 口头邀约不是证据；在未提供地址、许可与装置信息前，不改变“证据不足”的结论。 | F22: 见 06 表对应材料：排污许可 / 环评 / 磅单 / 发票 / 视频验厂

Sheet 05_评分模型
A1: 05 · 证据充分度模型（100 分制）
A2: 分数衡量“证据链完整度”，不是真假概率。同一套权重，5 个案例横向可比；现场核验未完成时，该维度记 0 分。
A3: 报告编号 SV-2026-CN-NA2CO3-001 ★ 修改 02/03 明细后，本表与总表分数需重新计算（Excel 会自动重算）
A4: 评分维度 | B4: 权重 | C4: 山东海化 | D4: 博源银根 | E4: 杭实善成 | F4: 分装样例 | G4: 证据不足样例 | H4: 评分要点
A5: 生产许可与环保手续 | B5: 30 | C5: 28 | D5: 24 | E5: 0 | F5: 8 | G5: 0 | H5: 排污许可（无机碱制造）、环评批复/验收中的产品与产能、项目备案/节能审查、产能置换公示
A6: 产能与装置实据 | B6: 30 | C6: 30 | D6: 28 | E6: 0 | F6: 8 | G6: 2 | H6: 公开产能与产量、装置条线与车间编制、厂址与门牌、原料一体化配置、同址关联装置
A7: 产品与市场证据 | B7: 20 | C7: 18 | D7: 16 | E7: 12 | F7: 12 | G7: 4 | H7: 官网产品页与牌号规格、自营销售渠道、交易所交割厂库/协会名录、客户与中标记录、品牌
A8: 运营侧痕迹 | B8: 10 | C8: 8 | D8: 8 | E8: 6 | F8: 5 | G8: 2 | H8: 原盐/石灰石/煤采购、生产岗位招聘、专利与技术论文、物流与铁路专用线
A9: 现场与第三方核验 | B9: 10 | C9: 0 | D9: 0 | E9: 0 | F9: 0 | G9: 0 | H9: 视频验厂、磅单、批次质检、第三方验厂报告、发票与发货地一致性
A10: 证据充分度合计 | B10: =SUM(B5:B9) | C10: =SUM(C5:C9) | D10: =SUM(D5:D9) | E10: =SUM(E5:E9) | F10: =SUM(F5:F9) | G10: =SUM(G5:G9) | H10: ≥70：可判生产厂家；40—69：需补证；<40：多为贸易/分装，或证据不足
A11: 判定结论 | B11: — | C11: 生产厂家 | D11: 生产厂家 | E11: 贸易经销 | F11: 分装或复配 | G11: 证据不足暂无法确认 | H11: 结论由 Q1→Q4 规则决定，分数只作辅助与横向比较
A13: 评分口径 | C13: 强证据（●●●）指政府许可/备案、交易所或协会名录、上市公司审计披露、可复现第三方记录；中证据（●●○）指可与第三方互证的企业官网信息、行业媒体、招聘/招标；弱证据（●○○）指自述宣传、单张照片、口头承诺。
A14: 一票否决 | C14: 排污许可行业类别与目标产品不符、且无对应环评/备案 → 不可能是该产品生产厂，直接进入 Q3/Q4；反之，只要有任一硬证据，也不能仅凭“没找到官网”否定其生产。
A15: 现场权重 | C15: 现场与第三方核验占 10 分，未做就是 0 分。这不是扣分，而是提醒：线上证据再全，也不能替代一次不预约的视频验厂。

Sheet 06_待索取材料
A1: 06 · 待索取材料清单（12 项）
A2: P0 拿不到，不进入打款与长协；话术可直接复制给业务员。勾选“状态”即为已获取。
A3: 报告编号 SV-2026-CN-NA2CO3-001 数据截止 2026-10-19 优先级：P0 必取 / P1 视场景 / P2 合规参考
A4: 编号 | B4: 材料 | C4: 优先级 | D4: 核验目的 | E4: 关键看点 | F4: 索取话术 | G4: 适用场景 | H4: 状态
A5: M1 | B5: 排污许可证正本 + 副本（含主要生产设施页） | C5: P0 | D5: 确认“行业类别=无机碱制造”及装置在证 | E5: 行业类别、主要生产设施、排放口、有效期、厂址 | F5: 麻烦提供贵司纯碱装置的排污许可证正副本扫描件，重点要有“主要生产设施”和“排放口”那几页，我们核对行业类别和证载厂址。 | G5: 所有供应商 | H5: 未获取
A6: M2 | B6: 纯碱项目环评批复 + 竣工验收报告 | C6: P0 | D6: 确认产品方案、产能与工艺路线 | E6: 产品为碳酸钠、产能万吨/年、工艺（氨碱/联碱/天然碱） | F6: 请提供纯碱项目的环评批复和竣工环保验收报告，产品方案和产能那两页即可。 | G6: 声称自产的供应商 | H6: 未获取
A7: M3 | B7: 项目备案 / 产能置换公示 / 节能审查 | C7: P1 | D7: 确认项目主体与合规产能 | E7: 备案主体是否为目标企业、产能数字、置换比例 | F7: 技改或在建项目，请提供备案证或省级产能置换公示链接。 | G7: 有技改/在建项目的企业 | H7: 未获取
A8: M4 | B8: 近 3 个月出厂磅单 3—5 车 | C8: P0 | D8: 验证真实发货与发货地 | E8: 车牌、日期、品名、净重、发货单位与地址 | F8: 随机给 3 车最近发货的磅单，能看清车牌、日期、净重和发货地就行。 | G8: 所有供应商 | H8: 未获取
A9: M5 | B9: 批次质检报告（COA） | C9: P0 | D9: 确认产品规格与批次可追溯 | E9: 执行标准 GB/T 210、批次号、Na₂CO₃ 含量、氯化物、粒度 | F9: 请提供拟供货批次的 COA，注明执行标准与批号，我们做第三方复检。 | G9: 所有供应商 | H9: 未获取
A10: M6 | B10: 包装袋 / 合格证 / 喷码照片 | C10: P0 | D10: 核对生产商名称与地址 | E10: 包装上“生产商”是否为目标企业、地址是否与许可一致 | F10: 拍一张完整包装袋正面和喷码位置，要能看清生产商名称、地址、执行标准和批号。 | G10: 所有供应商 | H10: 未获取
A11: M7 | B11: 增值税发票样本 | C11: P0 | D11: 确认销售主体=生产主体 | E11: 销售方名称、纳税人识别号、品名“纯碱”、税率 | F11: 提供一张近期纯碱发票的票样（可遮挡金额），我们核对销售方与生产商是否一致。 | G11: 所有供应商 | H11: 未获取
A12: M8 | B12: 食品生产许可证（SC）及明细 | C12: P1 | D12: 食品级碳酸钠的资质与工艺单元 | E12: 品种明细是否含“分装”、生产地址、有效期 | F12: 食品级的话，请提供 SC 证及品种明细页，注意看是不是“分装”。 | G12: 食品级采购 | H12: 未获取
A13: M9 | B13: 危化品相关许可（液氨/氨水） | C13: P2 | D13: 安全合规核查（非纯碱生产证据） | E13: 许可范围是液氨而非纯碱；储存与运输资质 | F13: 氨碱法涉及液氨，请提供液氨相关的安全许可与储运资质。 | G13: 氨碱法企业 | H13: 未获取
A14: M10 | B14: 视频验厂或第三方验厂报告 | C14: P0 | D14: 确认装置真实运行 | E14: 碳化塔、煅烧炉、凉碱炉、包装线、地磅、成品库 | F14: 安排一次 20 分钟视频验厂，按碳化—煅烧—包装—地磅顺序走，不要剪辑。 | G14: 所有声称自产的企业 | H14: 未获取
A15: M11 | B15: 生产厂授权书 / 经销协议 | C15: P0 | D15: 贸易商场景下追溯生产厂 | E15: 授权主体、授权品类、授权区域、有效期 | F15: 如果是代理，请提供碱厂盖章的授权书，以及你们从碱厂采购的发票。 | G15: 贸易商/经销商 | H15: 未获取
A16: M12 | B16: 运输合同与承运人信息 | C16: P1 | D16: 验证发货地与厂址一致 | E16: 起运地、承运人、运单号与磅单匹配 | F16: 提供本次发货的运输合同或运单，起运地要与排污证地址一致。 | G16: 所有供应商 | H16: 未获取

Sheet 07_现场验厂
A1: 07 · 现场 / 视频验厂脚本
A2: 不预约、不剪辑、按顺序走：门牌 → 装置 → 原料 → 包装 → 地磅 → 中控 → 三废。
A3: 报告编号 SV-2026-CN-NA2CO3-001 数据截止 2026-10-19 建议全程录屏并保留时间戳
A4: 序号 | B4: 检查项 | C4: 核验方法 | D4: 合格标准 | E4: 常见造假信号 | F4: 权重
A5: 1 | B5: 厂区门牌与地址 | C5: 视频从大门门牌开始，连续走到装置区 | D5: 门牌与排污证地址一致，园区有化工定位 | E5: 只拍车间内部、拒绝拍门牌、地址含糊 | F5: 10
A6: 2 | B6: 碳化塔 / 蒸氨塔 | C6: 要求拍设备铭牌与塔体全貌 | D6: 塔体高耸、有管线与操作平台，铭牌厂家/年份可读 | E6: 只有储罐与包装机，无塔器 | F6: 10
A7: 3 | B7: 煅烧炉 / 凉碱炉 | C7: 拍运行中的炉体、传动与温度表 | D7: 设备运行、有蒸汽/燃气管道、DCS 有对应画面 | E7: 设备停用积灰、无管线连接 | F7: 10
A8: 4 | B8: 原料堆场 | C8: 原盐/石灰石堆场与输送皮带 | D8: 大宗原料库存与上料系统 | E8: 只有成品垛，无原料 | F8: 10
A9: 5 | B9: 包装线与喷码 | C9: 现场打印一张合格证并拍喷码 | D9: 喷码含生产商、批号、日期，与 COA 对应 | E9: 预先印好的包装袋、无喷码机 | F9: 10
A10: 6 | B10: 成品库与地磅 | C10: 随机抽一垛货，核对磅单与库位 | D10: 库存与发货记录可对应，地磅有近期记录 | E10: 仓库是第三方仓储，货权不清 | F10: 10
A11: 7 | B11: 中控室 DCS | C11: 要求看纯碱工段画面与趋势曲线 | D11: 有碳化、蒸氨、煅烧工段实时数据 | E11: 只有视频监控，无工艺画面 | F11: 10
A12: 8 | B12: 三废与排污口 | C12: 废液/碱渣处理与在线监测 | D12: 与排污许可证载明的排放口一致 | E12: 无处理设施、排放口与证不符 | F12: 10

Sheet 08_案例对照
A1: 08 · 5 个案例横向对照
A2: 同一套方法，不同的证据结构，落点自然不同：有的能定“厂家”，有的只能定“贸易”，有的必须留白。
A3: 报告编号 SV-2026-CN-NA2CO3-001 数据截止 2026-10-19
A4: 企业 | B4: 结论 | C4: 充分度 | D4: 直接 | E4: 间接 | F4: 排除 | G4: 关键硬证据 | H4: 关键缺口 / 下一步 | I4: 置信度
A5: 山东海化股份有限公司 | B5: 生产厂家 | C5: 84 | D5: 6 | E5: 5 | F5: 5 | G5: 排污许可证：行业类别“无机碱制造”；官网工厂页：两条线、280 万吨、15 个车间；上市公司年报：2023 年实际生产 319.31 万吨 | H5: 先做视频验厂（碳化塔—煅烧—包装线—地磅），再签“生产商=发票销售方=发货地”三合一条款；技改期约定供应保障。 | I5: 高
A6: 内蒙古博源银根化工有限公司 | B6: 生产厂家 | C6: 76 | D6: 5 | E6: 3 | F6: 3 | G6: 上市公司公告：一期 500 万吨纯碱达产；二期启动公告：分期建设、总投资与进度；资源底座：塔木素天然碱矿 10.78 亿吨 | H6: 天然碱法重碱粒度与堆积密度需与玻璃窑炉匹配，先索取样检测；确认二期投产节奏对 2027 年供应量的影响。 | I6: 高
A7: 浙江杭实善成实业有限公司 | B7: 贸易经销 | C7: 18 | D7: 0 | E7: 4 | F7: 4 | G7: 无（0 条直接生产证据） | H7: 可与其做分销/代采，但合同须写明“实际生产商”并附授权链；要求发票由碱厂直开或提供完整背靠背链条。 | I7: 高
A8: 某食品配料有限公司（脱敏样例） | B8: 分装或复配 | C8: 33 | D8: 0 | E8: 4 | F8: 3 | G8: 无（0 条直接生产证据） | H8: 按“分装商”而非“厂家”议价；要求其标注实际生产厂与批号，食品级需提供 GB 1886.1 全项检测。 | I8: 中高
A9: 某询价供应商（脱敏样例） | B9: 证据不足暂无法确认 | C9: 8 | D9: 0 | E9: 1 | F9: 3 | G9: 无（0 条直接生产证据） | H9: 先按“未认证供应商”处理：不预付、不做长协；补齐 P0 材料后再复核，或直接转向已核验的碱厂/授权经销商。 | I9: 低

Sheet 09_数据来源
A1: 09 · 数据来源与可复核性
A2: 只采信可公开复核的来源；企业官网信息标注为“自述”，须与许可/公告/交易所文件交叉。
A3: 报告编号 SV-2026-CN-NA2CO3-001 数据截止 2026-10-19 链接失效时，可按“机构 + 标题 + 日期”二次检索
A4: 编号 | B4: 来源 | C4: 类型 | D4: 链接 | E4: 引用内容 | F4: 访问日期
A5: id | B5: source | C5: type | D5: url | E5: quote | F5: 2026-10-19
A6: id | B6: source | C6: type | D6: url | E6: quote | F6: 2026-10-19
A7: id | B7: source | C7: type | D7: url | E7: quote | F7: 2026-10-19
A8: id | B8: source | C8: type | D8: url | E8: quote | F8: 2026-10-19
A9: id | B9: source | C9: type | D9: url | E9: quote | F9: 2026-10-19
A10: id | B10: source | C10: type | D10: url | E10: quote | F10: 2026-10-19
A11: id | B11: source | C11: type | D11: url | E11: quote | F11: 2026-10-19
A12: id | B12: source | C12: type | D12: url | E12: quote | F12: 2026-10-19
A13: id | B13: source | C13: type | D13: url | E13: quote | F13: 2026-10-19
A14: id | B14: source | C14: type | D14: url | E14: quote | F14: 2026-10-19
A15: id | B15: source | C15: type | D15: url | E15: quote | F15: 2026-10-19
... A18: id | B18: source | C18: type | D18: url | E18: quote | F18: 2026-10-19
