Workbook

Sheet 00_封面说明
B2: 汇率波动对报价的影响 · 测算工作簿
B4: 案例 | C4: 中国出口重质纯碱 10 万美元订单，预计 90 天后收汇
B5: 产品 / 规格 | C5: 重质纯碱 重质纯碱（Dense Soda Ash, Na₂CO₃ ≥ 99.2%，GB/T 210-2022 II 类）
B6: 交易方向 | C6: 出口收汇
B7: 金额 / 币种 | C7: 100,000.00 USD（USD/CNY）
B8: 结算日 / 期限 | C8: 2027-01-17（90 个自然日）
B9: 汇率数据截至 | C9: 2026-10-19
B10: 历史序列 | C10: 2023-10-09 ~ 2026-10-19，735 个交易日，来源：国家外汇管理局人民币汇率中间价
B11: 生成时间 | C11: 2026-10-19 19:38:11
A13: 一、怎么用（改黄底，全簿自动重算）
B14: ① 改参数 | C14: 在「01_输入参数」只改黄底单元格：金额、币种、方向、汇率、成本、目标毛利、分批比例。其余全是公式。
B15: ② 看结果 | C15: 「02_汇率敏感性」「03_毛利测算」「05_分批结算」会自动重算；切方向后毛利率、平衡汇率同步切换口径。
B16: ③ 查历史 | C16: 「06_历史汇率序列」是官方中间价的日频原始数据（静态值）；「07_历史分位」用公式实时计算分位与区间。
B17: ④ 对公式 | C17: 「04_计算公式」「10_口径与免责」写明每一步的公式；scripts/verify.py 会用 Python 重算并与 Excel 交叉核对。
B18: ⑤ 带报价 | C18: 「09_报价带入」给出目标毛利下的最低外币金额，可直接粘到报价单或形式发票环节。
A20: 二、数据标签（必读）
B21: 真实 | C21: 官方中间价历史序列、当日中间价、银行牌价，均有可回溯来源与日期。
B22: 模拟 | C22: 人民币成本、结算期限、分批比例等示例参数，仅为演示计算流程，不是该订单真实数据。已模拟字段：cny_cost、settle_date、batches_alt。
B23: 估算 | C23: 银行点差带（示例值）、结汇手续费率（默认 0）——不是任何一家银行的真实报价。
A25: 三、合规边界
B26: 本工作簿只做汇率情景测算：所有「若汇率为 R」的假设都是压力测试，不代表对未来汇率的任何判断，也未预测走势。 本工作簿不推荐、不比较任何具体外汇避险产品（远期、期权、掉期、结构性产品）或操作；是否锁汇、如何锁汇由企业与银行独立决定。 毛利与毛利率只反映汇率与成本假设下的静态关系；退税率、运费、合同条款、多币种交叉盘等未计入，见「10_口径与免责」。 对外使用前请把模拟参数替换为真实数据，并核对银行实际结汇/购汇价。

Sheet 01_输入参数
A1: 01 · 输入参数与汇率口径
A2: 只改黄底单元格；白底为公式派生。出口收汇与进口付汇的计算方向由「交易方向」自动切换。
A4: A. 业务输入
B5: 交易方向 | C5: 出口收汇 | D5: 输入 | E5: 出口收汇 / 进口付汇（下拉选择）
B6: 结算币种代码 | C6: USD | D6: 输入 | E6: 如 USD / EUR / 100JPY
B7: 汇率对 | C7: USD/CNY | D7: 输入 | E7: 直接标价：1 单位外币 = X 人民币
B8: 业务外币金额 | C8: 100000 | D8: 输入 | E8: 本笔业务的外币计价款（可含分批合计）
B9: 当日中间价 | C9: 6.7208 | D9: 输入 | E9: 来源：国家外汇管理局 / 中国外汇交易中心；可直接覆盖
B10: 中间价日期 | C10: 46314 | D10: 输入
B11: 银行点差带（单侧 %） | C11: 0.0025 | D11: 输入 | E11: 示例值；真实点差以银行报价为准
B12: 银行实际结汇/购汇价 | D12: 输入 | E12: 有就填（最真实），口径选「实际成交价」
B13: 基准汇率口径 | C13: 中间价+点差带 | D13: 输入 | E13: 下拉：官方中间价 / 中间价+点差带 / 实际成交价
B14: 人民币成本 | C14: 600000 | D14: 输入 | E14: 出口：人民币成本；进口：货款外的人民币成本
B15: 进口后人民币销售收入 | D15: 输入 | E15: 仅进口付汇需要（毛利率分母）
B16: 目标毛利率 | C16: 0.1 | D16: 输入 | E16: 填小数（0.10 = 10%），单元格显示为百分比；留空不算目标平衡汇率
B17: 目标毛利额（元） | D17: 输入 | E17: 可选；与毛利率可同时存在
B18: 银行费用率 toll | C18: 0 | D18: 输入 | E18: 填小数；出口：从收入扣减；进口：加到成本
B19: 交易日 | C19: 46314 | D19: 输入
B20: 预计结算日 | C20: 46404 | D20: 输入
B21: 合同约定汇率 | D21: 输入 | E21: 可选；用于量化与市场汇率的差额
B22: 敏感性档位（%） | C22: -5,-3,-2,-1,0,1,2,3,5 | D22: 输入 | E22: 逗号分隔，可任意增删
A24: B. 派生口径（公式，勿手改）
B25: 结汇价（银行现汇买入）= 中间价 ×(1−点差) | C25: =IF($C$13="实际成交价",IF(ISNUMBER($C$12),$C$12,$C$9*(1-$C$11)),$C$9*(1-$C$11)) | D25: 公式
B26: 购汇价（银行现汇卖出）= 中间价 ×(1+点差) | C26: =IF($C$13="实际成交价",IF(ISNUMBER($C$12),$C$12,$C$9*(1+$C$11)),$C$9*(1+$C$11)) | D26: 公式
B27: 方向符号（出口 −1 / 进口 +1） | C27: =IF($C$5="出口收汇",-1,1) | D27: 公式
B28: 基准汇率（用于测算） | C28: =IF($C$13="官方中间价",$C$9,IF($C$13="实际成交价",IF(ISNUMBER($C$12),$C$12,$C$9),IF($C$5="出口收汇",$C$25,$C$26))) | D28: 公式
B29: 口径说明（自动） | C29: =IF($C$13="官方中间价","官方中间价：只适合分位对照",IF($C$13="实际成交价","银行实际成交价：最真实的口径","中间价×点差带：示例估算，非银行真实报价")) | D29: 公式
B30: 结算期限（自然日） | C30: =$C$20-$C$19 | D30: 公式
B31: 结算期限（交易日估算） | C31: =ROUND($C$30*5/7,0) | D31: 公式
B32: 汇率每变动 1% 的敞口（元） | C32: =ABS($C$8*$C$28*(1-$C$18))*0.01 | D32: 公式
A34: C. 口径提示
B35: • 出口收汇：人民币收入 = 外币金额 × 结汇价 × (1 − 费用率)；结汇价用银行「现汇买入价」。
B36: • 进口付汇：人民币支出 = 外币金额 × 购汇价 × (1 + 费用率)；购汇价用银行「现汇卖出价」。
B37: • 中间价 ≠ 成交价：本例 2026-10-19 中国银行美元现汇买入价 6.6701，较当日中间价 6.7208 低约 0.75%。
B38: • 银行费用率默认 0（未计入手续费与电讯费），结汇/购汇手续费、远期锁汇点价、点差均需另行确认。
B39: • 本工作簿不预测汇率，不推荐避险产品。

Sheet 02_汇率敏感性
A1: 02 · 汇率敏感性矩阵（汇率变动 ±1% / ±3% / ±5% …）
A2: 档位可改；RATE 为情景汇率。出口看人民币收入，进口看人民币支出。汇率变动只用于测算，不代表预测。
B4: 汇率变动 | C4: 情景汇率 | D4: 外币金额 | E4: 人民币毛额 | F4: 银行费用 | G4: 人民币净额 | H4: 较基准变化 | I4: 变化率 | J4: 毛利额 | K4: 毛利率
B5: -0.05 | C5: =ROUND('01_输入参数'!$C$28*(1+B5),6) | D5: ='01_输入参数'!$C$8 | E5: =D5*C5 | F5: =ABS(E5-D5*C5*(1+'01_输入参数'!$C$27*'01_输入参数'!$C$18)) | G5: =E5*(1+'01_输入参数'!$C$27*'01_输入参数'!$C$18) | H5: =G5-G$14 | I5: =IF(G$14=0,0,H5/G$14) | J5: =IF(('01_输入参数'!$C$5="出口收汇"),IF(N('01_输入参数'!$C$14)=0,G5-'01_输入参数'!$C$14,G5-'01_输入参数'!$C$14),IF(AND(N('01_输入参数'!$C$15)>0,N('01_输入参数'!$C$14)>=0),'01_输入参数'!$C$15-(G5+'01_输入参数'!$C$14),"")) | K5: =IF(J5="","",IF(('01_输入参数'!$C$5="出口收汇"),IF(G5=0,"",J5/G5),IF('01_输入参数'!$C$15=0,"",J5/'01_输入参数'!$C$15)))
B6: -0.03 | C6: =ROUND('01_输入参数'!$C$28*(1+B6),6) | D6: ='01_输入参数'!$C$8 | E6: =D6*C6 | F6: =ABS(E6-D6*C6*(1+'01_输入参数'!$C$27*'01_输入参数'!$C$18)) | G6: =E6*(1+'01_输入参数'!$C$27*'01_输入参数'!$C$18) | H6: =G6-G$14 | I6: =IF(G$14=0,0,H6/G$14) | J6: =IF(('01_输入参数'!$C$5="出口收汇"),IF(N('01_输入参数'!$C$14)=0,G6-'01_输入参数'!$C$14,G6-'01_输入参数'!$C$14),IF(AND(N('01_输入参数'!$C$15)>0,N('01_输入参数'!$C$14)>=0),'01_输入参数'!$C$15-(G6+'01_输入参数'!$C$14),"")) | K6: =IF(J6="","",IF(('01_输入参数'!$C$5="出口收汇"),IF(G6=0,"",J6/G6),IF('01_输入参数'!$C$15=0,"",J6/'01_输入参数'!$C$15)))
B7: -0.02 | C7: =ROUND('01_输入参数'!$C$28*(1+B7),6) | D7: ='01_输入参数'!$C$8 | E7: =D7*C7 | F7: =ABS(E7-D7*C7*(1+'01_输入参数'!$C$27*'01_输入参数'!$C$18)) | G7: =E7*(1+'01_输入参数'!$C$27*'01_输入参数'!$C$18) | H7: =G7-G$14 | I7: =IF(G$14=0,0,H7/G$14) | J7: =IF(('01_输入参数'!$C$5="出口收汇"),IF(N('01_输入参数'!$C$14)=0,G7-'01_输入参数'!$C$14,G7-'01_输入参数'!$C$14),IF(AND(N('01_输入参数'!$C$15)>0,N('01_输入参数'!$C$14)>=0),'01_输入参数'!$C$15-(G7+'01_输入参数'!$C$14),"")) | K7: =IF(J7="","",IF(('01_输入参数'!$C$5="出口收汇"),IF(G7=0,"",J7/G7),IF('01_输入参数'!$C$15=0,"",J7/'01_输入参数'!$C$15)))
B8: -0.01 | C8: =ROUND('01_输入参数'!$C$28*(1+B8),6) | D8: ='01_输入参数'!$C$8 | E8: =D8*C8 | F8: =ABS(E8-D8*C8*(1+'01_输入参数'!$C$27*'01_输入参数'!$C$18)) | G8: =E8*(1+'01_输入参数'!$C$27*'01_输入参数'!$C$18) | H8: =G8-G$14 | I8: =IF(G$14=0,0,H8/G$14) | J8: =IF(('01_输入参数'!$C$5="出口收汇"),IF(N('01_输入参数'!$C$14)=0,G8-'01_输入参数'!$C$14,G8-'01_输入参数'!$C$14),IF(AND(N('01_输入参数'!$C$15)>0,N('01_输入参数'!$C$14)>=0),'01_输入参数'!$C$15-(G8+'01_输入参数'!$C$14),"")) | K8: =IF(J8="","",IF(('01_输入参数'!$C$5="出口收汇"),IF(G8=0,"",J8/G8),IF('01_输入参数'!$C$15=0,"",J8/'01_输入参数'!$C$15)))
B9: 0 | C9: =ROUND('01_输入参数'!$C$28*(1+B9),6) | D9: ='01_输入参数'!$C$8 | E9: =D9*C9 | F9: =ABS(E9-D9*C9*(1+'01_输入参数'!$C$27*'01_输入参数'!$C$18)) | G9: =E9*(1+'01_输入参数'!$C$27*'01_输入参数'!$C$18) | H9: =G9-G$14 | I9: =IF(G$14=0,0,H9/G$14) | J9: =IF(('01_输入参数'!$C$5="出口收汇"),IF(N('01_输入参数'!$C$14)=0,G9-'01_输入参数'!$C$14,G9-'01_输入参数'!$C$14),IF(AND(N('01_输入参数'!$C$15)>0,N('01_输入参数'!$C$14)>=0),'01_输入参数'!$C$15-(G9+'01_输入参数'!$C$14),"")) | K9: =IF(J9="","",IF(('01_输入参数'!$C$5="出口收汇"),IF(G9=0,"",J9/G9),IF('01_输入参数'!$C$15=0,"",J9/'01_输入参数'!$C$15)))
B10: 0.01 | C10: =ROUND('01_输入参数'!$C$28*(1+B10),6) | D10: ='01_输入参数'!$C$8 | E10: =D10*C10 | F10: =ABS(E10-D10*C10*(1+'01_输入参数'!$C$27*'01_输入参数'!$C$18)) | G10: =E10*(1+'01_输入参数'!$C$27*'01_输入参数'!$C$18) | H10: =G10-G$14 | I10: =IF(G$14=0,0,H10/G$14) | J10: =IF(('01_输入参数'!$C$5="出口收汇"),IF(N('01_输入参数'!$C$14)=0,G10-'01_输入参数'!$C$14,G10-'01_输入参数'!$C$14),IF(AND(N('01_输入参数'!$C$15)>0,N('01_输入参数'!$C$14)>=0),'01_输入参数'!$C$15-(G10+'01_输入参数'!$C$14),"")) | K10: =IF(J10="","",IF(('01_输入参数'!$C$5="出口收汇"),IF(G10=0,"",J10/G10),IF('01_输入参数'!$C$15=0,"",J10/'01_输入参数'!$C$15)))
B11: 0.02 | C11: =ROUND('01_输入参数'!$C$28*(1+B11),6) | D11: ='01_输入参数'!$C$8 | E11: =D11*C11 | F11: =ABS(E11-D11*C11*(1+'01_输入参数'!$C$27*'01_输入参数'!$C$18)) | G11: =E11*(1+'01_输入参数'!$C$27*'01_输入参数'!$C$18) | H11: =G11-G$14 | I11: =IF(G$14=0,0,H11/G$14) | J11: =IF(('01_输入参数'!$C$5="出口收汇"),IF(N('01_输入参数'!$C$14)=0,G11-'01_输入参数'!$C$14,G11-'01_输入参数'!$C$14),IF(AND(N('01_输入参数'!$C$15)>0,N('01_输入参数'!$C$14)>=0),'01_输入参数'!$C$15-(G11+'01_输入参数'!$C$14),"")) | K11: =IF(J11="","",IF(('01_输入参数'!$C$5="出口收汇"),IF(G11=0,"",J11/G11),IF('01_输入参数'!$C$15=0,"",J11/'01_输入参数'!$C$15)))
B12: 0.03 | C12: =ROUND('01_输入参数'!$C$28*(1+B12),6) | D12: ='01_输入参数'!$C$8 | E12: =D12*C12 | F12: =ABS(E12-D12*C12*(1+'01_输入参数'!$C$27*'01_输入参数'!$C$18)) | G12: =E12*(1+'01_输入参数'!$C$27*'01_输入参数'!$C$18) | H12: =G12-G$14 | I12: =IF(G$14=0,0,H12/G$14) | J12: =IF(('01_输入参数'!$C$5="出口收汇"),IF(N('01_输入参数'!$C$14)=0,G12-'01_输入参数'!$C$14,G12-'01_输入参数'!$C$14),IF(AND(N('01_输入参数'!$C$15)>0,N('01_输入参数'!$C$14)>=0),'01_输入参数'!$C$15-(G12+'01_输入参数'!$C$14),"")) | K12: =IF(J12="","",IF(('01_输入参数'!$C$5="出口收汇"),IF(G12=0,"",J12/G12),IF('01_输入参数'!$C$15=0,"",J12/'01_输入参数'!$C$15)))
B13: 0.05 | C13: =ROUND('01_输入参数'!$C$28*(1+B13),6) | D13: ='01_输入参数'!$C$8 | E13: =D13*C13 | F13: =ABS(E13-D13*C13*(1+'01_输入参数'!$C$27*'01_输入参数'!$C$18)) | G13: =E13*(1+'01_输入参数'!$C$27*'01_输入参数'!$C$18) | H13: =G13-G$14 | I13: =IF(G$14=0,0,H13/G$14) | J13: =IF(('01_输入参数'!$C$5="出口收汇"),IF(N('01_输入参数'!$C$14)=0,G13-'01_输入参数'!$C$14,G13-'01_输入参数'!$C$14),IF(AND(N('01_输入参数'!$C$15)>0,N('01_输入参数'!$C$14)>=0),'01_输入参数'!$C$15-(G13+'01_输入参数'!$C$14),"")) | K13: =IF(J13="","",IF(('01_输入参数'!$C$5="出口收汇"),IF(G13=0,"",J13/G13),IF('01_输入参数'!$C$15=0,"",J13/'01_输入参数'!$C$15)))
B14: 0 | C14: ='01_输入参数'!$C$28 | D14: ='01_输入参数'!$C$8 | E14: =D14*C14 | F14: =ABS(E14-D14*C14*(1+'01_输入参数'!$C$27*'01_输入参数'!$C$18)) | G14: =E14*(1+'01_输入参数'!$C$27*'01_输入参数'!$C$18) | H14: 0 | I14: 0 | J14: =IF(('01_输入参数'!$C$5="出口收汇"),IF(N('01_输入参数'!$C$14)=0,G14-'01_输入参数'!$C$14,G14-'01_输入参数'!$C$14),IF(AND(N('01_输入参数'!$C$15)>0,N('01_输入参数'!$C$14)>=0),'01_输入参数'!$C$15-(G14+'01_输入参数'!$C$14),"")) | K14: =IF(J14="","",IF(('01_输入参数'!$C$5="出口收汇"),IF(G14=0,"",J14/G14),IF('01_输入参数'!$C$15=0,"",J14/'01_输入参数'!$C$15)))
A16: 说明
B17: • 情景汇率 = 基准汇率 ×(1 + 汇率变动)；基准汇率来自「01_输入参数」C28，随口径切换自动变化。
B18: • 人民币净额 = 外币金额 × 情景汇率 ×(1 + 方向符号 × 费用率)；出口方向符号 −1（扣除），进口 +1（加上）。
B19: • 变化率以人民币净额计；由于费用率按比例计提，变化率与汇率变动幅度一致（费用率为 0 时完全相同）。
B20: • 毛利额：出口 = 人民币净额 − 人民币成本；进口 = 进口后人民币销售收入 −（人民币净额 + 其他人民币成本）。
B21: • 本表为固定 9 档。若需其它档位，直接修改 B 列百分比即可（或在 HTML 版里任意增删档位）。

Sheet 03_毛利测算
A1: 03 · 毛利测算与盈亏平衡汇率
A2: 平衡汇率随输入成本与目标毛利自动重算；出口与进口的公式方向不同，方向切换后自动套用。
A4: A. 当前基准下的毛利
B5: 项目 | C5: 数值 | D5: 公式 / 说明
B6: 基准汇率 | C6: ='01_输入参数'!$C$28 | D6: 来自「01_输入参数」C28
B7: 外币金额 | C7: ='01_输入参数'!$C$8
B8: 人民币毛额 | C8: =C7*C6 | D8: 外币金额 × 汇率
B9: 银行费用/点差（按比例） | C9: =ABS(C8-C10) | D9: 金额 × 汇率 × 费用率
B10: 人民币净额 | C10: =C8*(1+'01_输入参数'!$C$27*'01_输入参数'!$C$18) | D10: 毛额 −/+ 费用（出口扣减、进口增加）
B11: 人民币成本（出口）/ 其他成本（进口） | C11: =N('01_输入参数'!$C$14) | D11: 来自输入
B12: 进口后人民币销售收入 | C12: =IF(N('01_输入参数'!$C$15)=0,"",'01_输入参数'!$C$15) | D12: 仅进口用
B13: 毛利额 | C13: =IF(('01_输入参数'!$C$5="出口收汇"),C10-C11,IF(N(C12)=0,"",C12-(C10+C11))) | D13: 出口：净额 − 成本；进口：销售收入 − (净额 + 其他成本)
B14: 毛利率 | C14: =IF(N(C13)=0,"",IF(('01_输入参数'!$C$5="出口收汇"),IF(C10=0,"",C13/C10),IF(N(C12)=0,"",C13/C12))) | D14: 出口：毛利 ÷ 净额；进口：毛利 ÷ 销售收入
A16: B. 盈亏平衡汇率（成本与其他条件不变）
B17: 平衡点 | C17: 汇率 | D17: 较基准 | E17: 公式
B18: 毛利额 = 0 | C18: =IF(('01_输入参数'!$C$5="出口收汇"),IF(C7*(1-'01_输入参数'!$C$18)=0,"",C11/(C7*(1-'01_输入参数'!$C$18))),IF(N(C12)=0,"",(C12-C11)/(C7*(1+'01_输入参数'!$C$18)))) | D18: =IF(ISNUMBER(C18),C18/$C$6-1,"") | E18: 出口：R* = 成本 ÷ [金额 ×(1−费用率)]；进口：R* = (销售收入 − 其他成本) ÷ [金额 ×(1+费用率)]
B19: 达到目标毛利率 | C19: =IF(AND(('01_输入参数'!$C$5="出口收汇"),N('01_输入参数'!$C$16)>0),C11/(C7*(1-'01_输入参数'!$C$18)*(1-'01_输入参数'!$C$16)),"仅出口且填目标毛利率时计算") | D19: =IF(ISNUMBER(C19),C19/$C$6-1,"") | E19: R* = 成本 ÷ [金额 ×(1−费用率)×(1−目标毛利率)]
B20: 达到目标毛利额 | C20: =IF(AND(('01_输入参数'!$C$5="出口收汇"),N('01_输入参数'!$C$17)>0),(C11+'01_输入参数'!$C$17)/(C7*(1-'01_输入参数'!$C$18)),"仅出口且填目标毛利额时计算") | D20: =IF(ISNUMBER(C20),C20/$C$6-1,"") | E20: R* = (成本 + 目标毛利额) ÷ [金额 ×(1−费用率)]
B21: 汇率缓冲（毛利=0 平衡点相对基准） | C21: =IF(ISNUMBER(C18),C18/C6-1,"") | E21: 负值 = 汇率还要再跌这么多才亏（出口）；正值 = 还要涨这么多才亏（进口）
A23: C. 毛利对汇率的一阶敏感
B24: 汇率每变动 1% 的毛利变化（元） | C24: ='01_输入参数'!$C$32 | E24: =|金额 × 汇率 ×(1−费用率)| × 1%；汇率下降 1% 则毛利减少同额（出口）
B25: 毛利=0 时汇率可跌/涨幅度（相对基准） | C25: =IF(ISNUMBER(C18),ABS(C18/C6-1),"") | E25: =|平衡汇率 ÷ 基准 − 1|
B26: 毛利被汇率吃光所需的变动幅度 | C26: =IF('01_输入参数'!$C$32=0,"",C13/'01_输入参数'!$C$32) | E26: 当前毛利额 ÷ 每 1% 敞口，即毛利被汇率吃光的百分比（仅出口有意义）

Sheet 04_计算公式
A1: 04 · 计算公式（与本簿各表、Python 验证脚本同源）
A2: 符号：A=外币金额；R=汇率；t=银行费用率；C=人民币成本；S=进口后销售收入；M=毛利额；m=毛利率。
B4: 项目 | C4: 计算逻辑 | D4: 公式
B5: 汇率口径 | C5: 直接标价：1 单位外币 = X 人民币。出口结汇看现汇买入价，进口购汇看现汇卖出价。 | D5: 结汇价 R_s = R_mid×(1−band)；购汇价 R_b = R_mid×(1+band)
B6: 出口收汇 | C6: 收到外币 → 结汇成人民币 | D6: 收入 Rev = A × R_s × (1 − t)
B7: 进口付汇 | C7: 付出人民币 → 购汇付外币 | D7: 支出 Pay = A × R_b × (1 + t)
B8: 出口毛利 | C8: 收入减人民币成本 | D8: M = Rev − C；m = M ÷ Rev
B9: 进口毛利 | C9: 人民币销售收入减（外币折算支付 + 其他成本） | D9: M = S − (Pay + C_oth)；m = M ÷ S
B10: 汇率变动 ±n% | C10: 情景汇率与人民币金额变化 | D10: R′ = R×(1±n)；ΔRev = A × R × n × (1 − t)
B11: 每 1% 敞口 | C11: 汇率相对变动 1% 对应的人民币金额 | D11: Exp = |A × R × (1 − t)| × 1%
B12: 盈亏平衡（出口） | C12: 毛利=0 | D12: R* = C ÷ [A × (1 − t)]
B13: 盈亏平衡（进口） | C13: 毛利=0 | D13: R* = (S − C_oth) ÷ [A × (1 + t)]
B14: 目标毛利率汇率 | C14: 保目标毛利率所需最低汇率（出口） | D14: R* = C ÷ [A × (1 − t) × (1 − m)]
B15: 目标毛利额汇率 | C15: 保目标毛利额所需最低汇率（出口） | D15: R* = (C + M) ÷ [A × (1 − t)]
... B20: 分批 vs 一次性 | C20: 分批结构效应（基准汇率差异） | D20: Δ = Σ(A_i×R_i) − ΣA_i × R_首日

Sheet 05_分批结算
A1: 05 · 分批结算情景（按各批次金额与结算时间）
A2: 各批次金额与假设汇率可改；合计校验自动提示。分批真正改变的是暴露时点分散，不降低期望损失。
B4: 批次 | C4: 外币金额 | D4: 距结算天数 | E4: 假设汇率 | F4: 占比 | G4: 折算人民币（净） | H4: 占合计 | I4: (示例) 该批序号
B5: T/T 30% 定金（签约即付） | C5: 30000 | D5: 0 | E5: 6.703998 | F5: =IF($C$8=0,"",C5/$C$8) | G5: =C5*E5*(1+'01_输入参数'!$C$27*'01_输入参数'!$C$18) | H5: =IF($G$8=0,"",G5/$G$8)
B6: 装运后 60 天 40% | C6: 40000 | D6: 60 | E6: 6.703998 | F6: =IF($C$8=0,"",C6/$C$8) | G6: =C6*E6*(1+'01_输入参数'!$C$27*'01_输入参数'!$C$18) | H6: =IF($G$8=0,"",G6/$G$8)
B7: 提单日 90 天 30% | C7: 30000 | D7: 90 | E7: 6.703998 | F7: =IF($C$8=0,"",C7/$C$8) | G7: =C7*E7*(1+'01_输入参数'!$C$27*'01_输入参数'!$C$18) | H7: =IF($G$8=0,"",G7/$G$8)
B8: 合计 | C8: =SUM(C5:C7) | D8: =IF(C8=0,0,SUMPRODUCT(C5:C7,D5:D7)/C8) | E8: =IF(C8=0,0,SUMPRODUCT(C5:C7,E5:E7)/C8) | F8: 1 | G8: =SUM(G5:G7) | H8: 1
B10: 与订单金额校验 | C10: =IF(ABS(C8-'01_输入参数'!$C$8)<0.01,"一致","不一致：差 "&TEXT(C8-'01_输入参数'!$C$8,"#,##0.00"))
A12: 分批 × 汇率变动敏感性（各批次同向等比例平移）
B13: 汇率变动 | C13: 分批合计（净） | D13: 一次性全额（净） | E13: 分批−一次性 | F13: 较分批基准
B14: -0.05 | C14: =SUMPRODUCT($C$5:$C$7,$E$5:$E$7)*(1+B14)*(1+'01_输入参数'!$C$27*'01_输入参数'!$C$18) | D14: ='01_输入参数'!$C$8*$E$8*(1+B14)*(1+'01_输入参数'!$C$27*'01_输入参数'!$C$18) | E14: =C14-D14 | F14: =C14-$G$8
B15: -0.03 | C15: =SUMPRODUCT($C$5:$C$7,$E$5:$E$7)*(1+B15)*(1+'01_输入参数'!$C$27*'01_输入参数'!$C$18) | D15: ='01_输入参数'!$C$8*$E$8*(1+B15)*(1+'01_输入参数'!$C$27*'01_输入参数'!$C$18) | E15: =C15-D15 | F15: =C15-$G$8
B16: -0.01 | C16: =SUMPRODUCT($C$5:$C$7,$E$5:$E$7)*(1+B16)*(1+'01_输入参数'!$C$27*'01_输入参数'!$C$18) | D16: ='01_输入参数'!$C$8*$E$8*(1+B16)*(1+'01_输入参数'!$C$27*'01_输入参数'!$C$18) | E16: =C16-D16 | F16: =C16-$G$8
B17: 0 | C17: =SUMPRODUCT($C$5:$C$7,$E$5:$E$7)*(1+B17)*(1+'01_输入参数'!$C$27*'01_输入参数'!$C$18) | D17: ='01_输入参数'!$C$8*$E$8*(1+B17)*(1+'01_输入参数'!$C$27*'01_输入参数'!$C$18) | E17: =C17-D17 | F17: =C17-$G$8
B18: 0.01 | C18: =SUMPRODUCT($C$5:$C$7,$E$5:$E$7)*(1+B18)*(1+'01_输入参数'!$C$27*'01_输入参数'!$C$18) | D18: ='01_输入参数'!$C$8*$E$8*(1+B18)*(1+'01_输入参数'!$C$27*'01_输入参数'!$C$18) | E18: =C18-D18 | F18: =C18-$G$8
B19: 0.03 | C19: =SUMPRODUCT($C$5:$C$7,$E$5:$E$7)*(1+B19)*(1+'01_输入参数'!$C$27*'01_输入参数'!$C$18) | D19: ='01_输入参数'!$C$8*$E$8*(1+B19)*(1+'01_输入参数'!$C$27*'01_输入参数'!$C$18) | E19: =C19-D19 | F19: =C19-$G$8
B20: 0.05 | C20: =SUMPRODUCT($C$5:$C$7,$E$5:$E$7)*(1+B20)*(1+'01_输入参数'!$C$27*'01_输入参数'!$C$18) | D20: ='01_输入参数'!$C$8*$E$8*(1+B20)*(1+'01_输入参数'!$C$27*'01_输入参数'!$C$18) | E20: =C20-D20 | F20: =C20-$G$8
B22: • 折算人民币（净）= 批次金额 × 假设汇率 ×(1 + 方向符号 × 费用率)。
B23: • 一次性全额按第一批次（最早）的假设汇率折算，因此「分批−一次性」只反映各批基准汇率差异（结构效应）。
B24: • 敏感性档位对全部批次同向等比例平移；若想模拟「不同批次落在不同汇率」，直接改 E 列各批次汇率。
B25: • 分批并不降低期望损失：当方向未知时，它降低的是单点集中度。这里不做任何汇率预测。

Sheet 06_历史汇率序列
A1: 06 · 历史汇率原始序列（官方中间价，日频）
A2: 来源：国家外汇管理局人民币汇率中间价；2023-10-09 ~ 2026-10-19，共 735 个交易日。缺失工作日均为法定节假日，未插值。单位：1 单位外币 = X 人民币（JPY 为 100 JPY）。
A4: 日期 | B4: USD（美元） | C4: EUR（欧元） | D4: JPY（日元） | E4: HKD（港元） | F4: GBP（英镑） | G4: AUD（澳大利亚元） | H4: NZD（新西兰元） | I4: SGD（新加坡元） | J4: CHF（瑞士法郎） | K4: CAD（加拿大元） | L4: MOP（澳门元） | M4: MYR（林吉特） | N4: RUB（卢布） | O4: ZAR（南非兰特） | Q4: 其余币种（同一天） | R4: KRW（韩元） | S4: AED（阿联酋迪拉姆） | T4: SAR（沙特里亚尔） | U4: HUF（匈牙利福林） | V4: PLN（波兰兹罗提） | W4: DKK（丹麦克朗） | X4: SEK（瑞典克朗） | Y4: NOK（挪威克朗） | Z4: TRY（土耳其里拉） | AA4: MXN（墨西哥比索） | AB4: THB（泰国铢）
A5: 45208 | B5: 7.1789 | C5: 7.6229 | D5: 0.048515 | E5: 0.91654 | F5: 8.8159 | G5: 4.601 | H5: 4.3255 | I5: 5.2765 | J5: 7.9382 | K5: 5.2857 | M5: 0.65667 | N5: 13.9007 | O5: 2.6935 | R5: 185.74 | S5: 0.50996 | T5: 0.5208 | U5: 50.9763 | V5: 0.60351 | W5: 0.9809 | X5: 1.5221 | Y5: 1.5098 | Z5: 3.83724 | AA5: 2.5406 | AB5: 5.1033
A6: 45209 | B6: 7.1781 | C6: 7.6171 | D6: 0.048673 | E6: 0.91679 | F6: 8.8208 | G6: 4.6284 | H6: 4.3567 | I6: 5.2764 | J6: 7.9483 | K6: 5.3077 | M6: 0.65835 | N6: 13.6774 | O6: 2.69 | R6: 186.39 | S6: 0.51083 | T6: 0.52168 | U6: 51.2246 | V6: 0.60171 | W6: 0.981 | X6: 1.5204 | Y6: 1.496 | Z6: 3.85418 | AA6: 2.5397 | AB6: 5.1135
A7: 45210 | B7: 7.1779 | C7: 7.6443 | D7: 0.048583 | E7: 0.91798 | F7: 8.8582 | G7: 4.6437 | H7: 4.3719 | I7: 5.2847 | J7: 7.9679 | K7: 5.311 | M7: 0.65892 | N7: 13.7879 | O7: 2.6419 | R7: 185.71 | S7: 0.51084 | T7: 0.52168 | U7: 50.9471 | V7: 0.59666 | W7: 0.9781 | X7: 1.5082 | Y7: 1.4994 | Z7: 3.85546 | AA7: 2.5023 | AB7: 5.0632
A8: 45211 | B8: 7.1776 | C8: 7.6561 | D8: 0.048449 | E8: 0.91758 | F8: 8.8701 | G8: 4.6327 | H8: 4.3541 | I8: 5.2842 | J8: 7.9973 | K8: 5.3075 | M8: 0.65759 | N8: 13.7606 | O8: 2.6164 | R8: 185.05 | S8: 0.51069 | T8: 0.52156 | U8: 50.7116 | V8: 0.59381 | W8: 0.9771 | X8: 1.5128 | Y8: 1.5058 | Z8: 3.85035 | AA8: 2.488 | AB8: 5.0341
A9: 45212 | B9: 7.1775 | C9: 7.6045 | D9: 0.048258 | E9: 0.91747 | F9: 8.799 | G9: 4.5694 | H9: 4.2941 | I9: 5.2682 | J9: 7.9575 | K9: 5.2809 | M9: 0.65798 | N9: 13.4998 | O9: 2.6409 | R9: 185.52 | S9: 0.50969 | T9: 0.52042 | U9: 51.1667 | V9: 0.59978 | W9: 0.9841 | X9: 1.5216 | Y9: 1.5204 | Z9: 3.85538 | AA9: 2.5031 | AB9: 5.013
A10: 45215 | B10: 7.1798 | C10: 7.592 | D10: 0.04832 | E10: 0.9177 | F10: 8.772 | G10: 4.56 | H10: 4.2753 | I10: 5.265 | J10: 7.9927 | K10: 5.2917 | M10: 0.65906 | N10: 13.4832 | O10: 2.6354 | R10: 186.45 | S10: 0.50993 | T10: 0.52073 | U10: 51.3833 | V10: 0.59095 | W10: 0.9859 | X10: 1.526 | Y10: 1.5155 | Z10: 3.84276 | AA10: 2.5133 | AB10: 4.9982
A11: 45216 | B11: 7.1796 | C11: 7.5944 | D11: 0.048314 | E11: 0.91851 | F11: 8.8046 | G11: 4.5687 | H11: 4.2585 | I11: 5.2652 | J11: 8.0088 | K11: 5.3016 | M11: 0.65852 | N11: 13.4497 | O11: 2.609 | R11: 186.24 | S11: 0.51036 | T11: 0.52122 | U11: 51.0065 | V11: 0.58763 | W11: 0.9844 | X11: 1.5175 | Y11: 1.5207 | Z11: 3.87008 | AA11: 2.4973 | AB11: 5.0128
A12: 45217 | B12: 7.1795 | C12: 7.6259 | D12: 0.048287 | E12: 0.91764 | F12: 8.7863 | G12: 4.5983 | H12: 4.269 | I12: 5.2667 | J12: 8.0153 | K12: 5.2909 | M12: 0.65961 | N12: 13.4871 | O12: 2.6124 | R12: 186.44 | S12: 0.51002 | T12: 0.52087 | U12: 50.6576 | V12: 0.58261 | W12: 0.9815 | X12: 1.5129 | Y12: 1.5195 | Z12: 3.88142 | AA12: 2.5111 | AB12: 5.0206
A13: 45218 | B13: 7.1795 | C13: 7.6082 | D13: 0.048278 | E13: 0.91721 | F13: 8.7713 | G13: 4.577 | H13: 4.2413 | I13: 5.2546 | J13: 8.0327 | K13: 5.2732 | M13: 0.66088 | N13: 13.4935 | O13: 2.6352 | R13: 186.51 | S13: 0.50966 | T13: 0.52051 | U13: 50.7627 | V13: 0.58863 | W13: 0.9844 | X13: 1.5265 | Y13: 1.5331 | Z13: 3.88821 | AA13: 2.5431 | AB13: 5.0182
A14: 45219 | B14: 7.1793 | C14: 7.6275 | D14: 0.048232 | E14: 0.91786 | F14: 8.751 | G14: 4.5634 | H14: 4.2246 | I14: 5.2462 | J14: 8.0835 | K14: 5.2615 | M14: 0.66503 | N14: 13.3228 | O14: 2.6429 | R14: 187.05 | S14: 0.51033 | T14: 0.52116 | U14: 50.425 | V14: 0.58622 | W14: 0.9818 | X14: 1.52 | Y14: 1.5273 | Z14: 3.89317 | AA14: 2.5552 | AB14: 5.0332
A15: 45222 | B15: 7.1792 | C15: 7.6378 | D15: 0.048234 | E15: 0.91739 | F15: 8.7696 | G15: 4.5647 | H15: 4.2208 | I15: 5.2649 | J15: 8.0798 | K15: 5.2696 | M15: 0.66105 | N15: 13.226 | O15: 2.6386 | R15: 186.44 | S15: 0.51024 | T15: 0.52102 | U15: 50.2829 | V15: 0.58625 | W15: 0.9804 | X15: 1.5221 | Y15: 1.5345 | Z15: 3.89133 | AA15: 2.5396 | AB15: 5.0421
A16: 45223 | B16: 7.1786 | C16: 7.6899 | D16: 0.048265 | E16: 0.91739 | F16: 8.8271 | G16: 4.5734 | H16: 4.2326 | I16: 5.269 | J16: 8.0775 | K16: 5.2709 | M16: 0.66736 | N16: 13.0848 | O16: 2.6358 | R16: 185.98 | S16: 0.51063 | T16: 0.52155 | U16: 49.879 | V16: 0.58298 | W16: 0.9739 | X16: 1.522 | Y16: 1.5377 | Z16: 3.90243 | AA16: 2.5303 | AB16: 5.0217
... A64: 45289 | B64: 7.0827 | C64: 7.8592 | D64: 0.050213 | E64: 0.90622 | F64: 9.0411 | G64: 4.8484 | H64: 4.4991 | I64: 5.3772 | J64: 8.4184 | K64: 5.3673 | M64: 0.6487 | N64: 12.4582 | O64: 2.6183 | R64: 181.36 | S64: 0.51745 | T64: 0.52836 | U64: 48.7105 | V64: 0.55227 | W64: 0.9491 | X64: 1.4065 | Y64: 1.4362 | Z64: 4.15785 | AA64: 2.3915 | AB64: 4.8225
A65: 45293 | B65: 7.077 | C65: 7.8218 | D65: 0.050274 | E65: 0.90564 | F65: 9.0226 | G65: 4.8277 | H65: 4.4784 | I65: 5.37 | J65: 8.4194 | K65: 5.352 | L65: 1.1374 | M65: 0.64812 | N65: 12.606 | O65: 2.5832 | R65: 182.07 | S65: 0.51827 | T65: 0.52923 | U65: 48.9692 | V65: 0.5557 | W65: 0.9533 | X65: 1.421 | Y65: 1.4353 | Z65: 4.16662 | AA65: 2.394 | AB65: 4.8368
A66: 45294 | B66: 7.1002 | C66: 7.7802 | D66: 0.05008 | E66: 0.90864 | F66: 8.9794 | G66: 4.8174 | H66: 4.4561 | I66: 5.3621 | J66: 8.3712 | K66: 5.3427 | L66: 1.1335 | M66: 0.64941 | N66: 12.7368 | O66: 2.6109 | R66: 183.34 | S66: 0.51665 | T66: 0.52755 | U66: 49.1431 | V66: 0.56247 | W66: 0.959 | X66: 1.4345 | Y66: 1.4547 | Z66: 4.18546 | AA66: 2.4007 | AB66: 4.8036
A67: 45295 | B67: 7.0997 | C67: 7.7762 | D67: 0.049788 | E67: 0.90946 | F67: 9.0216 | G67: 4.7959 | H67: 4.4536 | I67: 5.3569 | J67: 8.3855 | K67: 5.3357 | L67: 1.1334 | M67: 0.65197 | N67: 12.8737 | O67: 2.6286 | R67: 183.28 | S67: 0.51605 | T67: 0.52698 | U67: 48.9566 | V67: 0.5604 | W67: 0.96 | X67: 1.4444 | Y67: 1.4533 | Z67: 4.18481 | AA67: 2.3942 | AB67: 4.8273
A68: 45296 | B68: 7.1029 | C68: 7.7907 | D68: 0.04923 | E68: 0.90939 | F68: 9.0283 | G68: 4.7756 | H68: 4.4412 | I68: 5.3514 | J68: 8.3731 | K68: 5.3322 | L68: 1.1317 | M68: 0.65356 | N68: 12.8043 | O68: 2.6298 | R68: 183.83 | S68: 0.51628 | T68: 0.52717 | U68: 48.7059 | V68: 0.55897 | W68: 0.9587 | X68: 1.4351 | Y68: 1.4466 | Z68: 4.19445 | AA68: 2.3967 | AB68: 4.844
A69: 45299 | B69: 7.1006 | C69: 7.7828 | D69: 0.049148 | E69: 0.90914 | F69: 9.045 | G69: 4.78 | H69: 4.4495 | I69: 5.3489 | J69: 8.3601 | K69: 5.3265 | L69: 1.1337 | M69: 0.65468 | N69: 12.7655 | O69: 2.6265 | R69: 184.4 | S69: 0.5164 | T69: 0.52734 | U69: 48.6312 | V69: 0.55919 | W69: 0.9596 | X69: 1.4429 | Y69: 1.4507 | Z69: 4.19363 | AA69: 2.3775 | AB69: 4.8657
A70: 45300 | B70: 7.101 | C70: 7.7876 | D70: 0.049376 | E70: 0.90934 | F70: 9.0643 | G70: 4.7811 | H70: 4.4506 | I70: 5.353 | J70: 8.387 | K70: 5.3278 | L70: 1.1327 | M70: 0.65539 | N70: 12.7636 | O70: 2.6165 | R70: 184.21 | S70: 0.51682 | T70: 0.52773 | U70: 48.5774 | V70: 0.5576 | W70: 0.9592 | X70: 1.4377 | Y70: 1.4577 | Z70: 4.20933 | AA70: 2.3722 | AB70: 4.9054
A71: 45301 | B71: 7.1055 | C71: 7.7809 | D71: 0.049334 | E71: 0.90897 | F71: 9.0488 | G71: 4.7618 | H71: 4.4471 | I71: 5.3467 | J71: 8.3538 | K71: 5.3184 | L71: 1.134 | M71: 0.65399 | N71: 12.5684 | O71: 2.6232 | R71: 184.76 | S71: 0.51616 | T71: 0.52706 | U71: 48.7993 | V71: 0.55973 | W71: 0.9598 | X71: 1.4399 | Y71: 1.4563 | Z71: 4.21085 | AA71: 2.3893 | AB71: 4.9001
A72: 45302 | B72: 7.1087 | C72: 7.8139 | D72: 0.04893 | E72: 0.90937 | F72: 9.0757 | G72: 4.777 | H72: 4.4439 | I72: 5.3473 | J72: 8.3737 | K72: 5.3252 | L72: 1.1327 | M72: 0.65303 | N72: 12.5383 | O72: 2.6224 | R72: 184.69 | S72: 0.51594 | T72: 0.52686 | U72: 48.4692 | V72: 0.55581 | W72: 0.9561 | X72: 1.4347 | Y72: 1.4534 | Z72: 4.19393 | AA72: 2.3898 | AB72: 4.9096
A73: 45303 | B73: 7.105 | C73: 7.8142 | D73: 0.049109 | E73: 0.90894 | F73: 9.0917 | G73: 4.7685 | H73: 4.446 | I73: 5.3506 | J73: 8.3602 | K73: 5.3192 | L73: 1.1332 | M73: 0.6532 | N73: 12.4434 | O73: 2.622 | R73: 184.2 | S73: 0.51619 | T73: 0.52708 | U73: 48.5834 | V73: 0.55789 | W73: 0.9559 | X73: 1.4406 | Y73: 1.4474 | Z73: 4.22332 | AA73: 2.3788 | AB73: 4.9108
A74: 45306 | B74: 7.1084 | C74: 7.7975 | D74: 0.049138 | E74: 0.909 | F74: 9.0747 | G74: 4.7677 | H74: 4.4459 | I74: 5.3455 | J74: 8.351 | K74: 5.3145 | L74: 1.1331 | M74: 0.65392 | N74: 12.3575 | O74: 2.6238 | R74: 184.12 | S74: 0.51595 | T74: 0.52685 | U74: 48.7385 | V74: 0.55992 | W74: 0.9582 | X74: 1.4441 | Y74: 1.4453 | Z74: 4.22562 | AA74: 2.3738 | AB74: 4.9003
A75: 45307 | B75: 7.1134 | C75: 7.803 | D75: 0.048934 | E75: 0.90934 | F75: 9.0693 | G75: 4.7453 | H75: 4.4189 | I75: 5.3442 | J75: 8.3318 | K75: 5.3113 | L75: 1.1332 | M75: 0.65682 | N75: 12.2948 | O75: 2.6226 | R75: 185.13 | S75: 0.51542 | T75: 0.52628 | U75: 48.6592 | V75: 0.56135 | W75: 0.9576 | X75: 1.4489 | Y75: 1.4532 | Z75: 4.22228 | AA75: 2.3764 | AB75: 4.8985
A76: 45308 | B76: 7.1168 | C76: 7.7729 | D76: 0.048635 | E76: 0.90954 | F76: 9.0363 | G76: 4.7146 | H76: 4.3978 | I76: 5.322 | J76: 8.3012 | K76: 5.3023 | L76: 1.133 | M76: 0.65928 | N76: 12.3326 | O76: 2.6562 | R76: 186.3 | S76: 0.51413 | T76: 0.52501 | U76: 48.9332 | V76: 0.56633 | W76: 0.9607 | X76: 1.4597 | Y76: 1.4642 | Z76: 4.21712 | AA76: 2.4163 | AB76: 4.9443
... A739: 46314 | B739: 6.7208 | C739: 7.5237 | D739: 0.04248 | E739: 0.85642 | F739: 8.9362 | G739: 4.67 | H739: 3.7901 | I739: 5.241 | J739: 8.1377 | K739: 4.7452 | L739: 1.2031 | M739: 0.60803 | N739: 12.4537 | O739: 2.4555 | R739: 199.47 | S739: 0.54792 | T739: 0.55982 | U739: 48.226 | V739: 0.58039 | W739: 0.9937 | X739: 1.4797 | Y739: 1.4076 | Z739: 7.38509 | AA739: 2.749 | AB739: 4.9925

Sheet 07_历史分位
A1: 07 · 历史区间与分位（全部由公式实时计算）
A2: 直接引用「06_历史汇率序列」的原始列计算：换币种 = 改 C5 的列字母；窗口 = 末日往前 365 / 1095 天，左开右闭。
A4: A. 计算设定
B5: 数据末日 | C5: =MAX('06_历史汇率序列'!$A$5:$A$739) | D5: 自动取 06 表最新日期
B6: 币种列（06 表中的列字母） | C6: B | D6: B=USD C=EUR D=JPY E=HKD F=GBP G=AUD H=NZD I=SGD J=CHF K=CAD L=MOP M=MYR N=RUB
B7: 当前中间价（分位基准） | C7: ='01_输入参数'!$C$9 | D7: 来自「01_输入参数」C9；可覆盖为其他口径值
A9: B. 分位与区间
B10: 指标 | C10: 近 1 年 | D10: 近 3 年 | E10: 公式说明
B11: 窗口起点 | C11: =$C$5-365 | D11: =$C$5-1095 | E11: 末日 − 365 / − 1095 天
B12: 样本交易日数 | C12: =SUMPRODUCT(--(('06_历史汇率序列'!$A$5:$A$739>=$C$11)*(INDIRECT("'06_历史汇率序列'!$"&$C$6&"$5:$"&$C$6&"$739")>0))) | D12: =SUMPRODUCT(--(('06_历史汇率序列'!$A$5:$A$739>=$D$11)*(INDIRECT("'06_历史汇率序列'!$"&$C$6&"$5:$"&$C$6&"$739")>0))) | E12: SUMPRODUCT(--窗口掩码)
B13: 窗口最高 | C13: =IFERROR(AGGREGATE(14,6,INDIRECT("'06_历史汇率序列'!$"&$C$6&"$5:$"&$C$6&"$739")/(('06_历史汇率序列'!$A$5:$A$739>=$C$11)*(INDIRECT("'06_历史汇率序列'!$"&$C$6&"$5:$"&$C$6&"$739")>0)),1),"") | D13: =IFERROR(AGGREGATE(14,6,INDIRECT("'06_历史汇率序列'!$"&$C$6&"$5:$"&$C$6&"$739")/(('06_历史汇率序列'!$A$5:$A$739>=$D$11)*(INDIRECT("'06_历史汇率序列'!$"&$C$6&"$5:$"&$C$6&"$739")>0)),1),"") | E13: AGGREGATE(14,6,列/掩码,1)
B14: 最高出现日 | C14: =IFERROR(INDEX('06_历史汇率序列'!$A$5:$A$739,MATCH(C13,INDIRECT("'06_历史汇率序列'!$"&$C$6&"$5:$"&$C$6&"$739"),0)),"") | D14: =IFERROR(INDEX('06_历史汇率序列'!$A$5:$A$739,MATCH(D13,INDIRECT("'06_历史汇率序列'!$"&$C$6&"$5:$"&$C$6&"$739"),0)),"") | E14: INDEX/MATCH 取该值对应日期
B15: 窗口最低 | C15: =IFERROR(AGGREGATE(15,6,INDIRECT("'06_历史汇率序列'!$"&$C$6&"$5:$"&$C$6&"$739")/(('06_历史汇率序列'!$A$5:$A$739>=$C$11)*(INDIRECT("'06_历史汇率序列'!$"&$C$6&"$5:$"&$C$6&"$739")>0)),1),"") | D15: =IFERROR(AGGREGATE(15,6,INDIRECT("'06_历史汇率序列'!$"&$C$6&"$5:$"&$C$6&"$739")/(('06_历史汇率序列'!$A$5:$A$739>=$D$11)*(INDIRECT("'06_历史汇率序列'!$"&$C$6&"$5:$"&$C$6&"$739")>0)),1),"") | E15: AGGREGATE(15,6,列/掩码,1)
B16: 最低出现日 | C16: =IFERROR(INDEX('06_历史汇率序列'!$A$5:$A$739,MATCH(C15,INDIRECT("'06_历史汇率序列'!$"&$C$6&"$5:$"&$C$6&"$739"),0)),"") | D16: =IFERROR(INDEX('06_历史汇率序列'!$A$5:$A$739,MATCH(D15,INDIRECT("'06_历史汇率序列'!$"&$C$6&"$5:$"&$C$6&"$739"),0)),"") | E16: INDEX/MATCH 取该值对应日期
B17: 窗口均值 | C17: =IFERROR(SUMPRODUCT((('06_历史汇率序列'!$A$5:$A$739>=$C$11)*(INDIRECT("'06_历史汇率序列'!$"&$C$6&"$5:$"&$C$6&"$739")>0))*INDIRECT("'06_历史汇率序列'!$"&$C$6&"$5:$"&$C$6&"$739"))/C12,"") | D17: =IFERROR(SUMPRODUCT((('06_历史汇率序列'!$A$5:$A$739>=$D$11)*(INDIRECT("'06_历史汇率序列'!$"&$C$6&"$5:$"&$C$6&"$739")>0))*INDIRECT("'06_历史汇率序列'!$"&$C$6&"$5:$"&$C$6&"$739"))/D12,"") | E17: SUMPRODUCT(掩码×列) ÷ 样本数
B18: 窗口中位数 | C18: =IFERROR(MEDIAN(IF((('06_历史汇率序列'!$A$5:$A$739>=$C$11)*(INDIRECT("'06_历史汇率序列'!$"&$C$6&"$5:$"&$C$6&"$739")>0)),INDIRECT("'06_历史汇率序列'!$"&$C$6&"$5:$"&$C$6&"$739"))),"") | D18: =IFERROR(MEDIAN(IF((('06_历史汇率序列'!$A$5:$A$739>=$D$11)*(INDIRECT("'06_历史汇率序列'!$"&$C$6&"$5:$"&$C$6&"$739")>0)),INDIRECT("'06_历史汇率序列'!$"&$C$6&"$5:$"&$C$6&"$739"))),"") | E18: MEDIAN(IF(掩码,列))
B19: 当前值分位 | C19: =IF(C12=0,"",(COUNTIFS('06_历史汇率序列'!$A$5:$A$739,">="&$C$11,INDIRECT("'06_历史汇率序列'!$"&$C$6&"$5:$"&$C$6&"$739"),"<"&$C$7)+0.5*COUNTIFS('06_历史汇率序列'!$A$5:$A$739,">="&$C$11,INDIRECT("'06_历史汇率序列'!$"&$C$6&"$5:$"&$C$6&"$739"),$C$7))/C12) | D19: =IF(D12=0,"",(COUNTIFS('06_历史汇率序列'!$A$5:$A$739,">="&$D$11,INDIRECT("'06_历史汇率序列'!$"&$C$6&"$5:$"&$C$6&"$739"),"<"&$C$7)+0.5*COUNTIFS('06_历史汇率序列'!$A$5:$A$739,">="&$D$11,INDIRECT("'06_历史汇率序列'!$"&$C$6&"$5:$"&$C$6&"$739"),$C$7))/D12) | E19: (低于当前 + 0.5×等于当前) ÷ 样本数
B20: 当前距最高 | C20: =IFERROR($C$7/C13-1,"") | D20: =IFERROR($C$7/D13-1,"") | E20: 当前值 ÷ 最高 − 1
B21: 当前距最低 | C21: =IFERROR($C$7/C15-1,"") | D21: =IFERROR($C$7/D15-1,"") | E21: 当前值 ÷ 最低 − 1
B22: 区间最高/最低 | C22: =IFERROR(C13/C15-1,"") | D22: =IFERROR(D13/D15-1,"") | E22: 最高 ÷ 最低 − 1
B24: • 分位口径与 HTML、Python 完全一致：(低于当前值样本数 + 0.5 × 等于当前值样本数) ÷ 窗口样本数。
B25: • 窗口按自然日回看 365 / 1095 天，左开右闭（起点之后、含末日）；缺失的工作日均为法定节假日，未做插值。
B26: • 为兼容各类 Office 版本，本表刻意不使用 MAXIFS / MINIFS（部分版本会返回 #NAME?），改用 AGGREGATE + SUMPRODUCT。
B27: • 「窗口中位数」是数组公式：在 Excel 里选中该格后按 Ctrl+Shift+Enter 确认一次即可。
B28: • 本表只描述过去到过哪里：分位低不等于会涨，分位高不等于会跌。

Sheet 08_实时汇率记录
A1: 08 · 实时汇率取数记录（可追溯）
A2: 每次取数追加一行：谁取的、何时、从哪个页面、什么口径、数值。报价留痕就靠这张表。
A4: 取数时间 | B4: 来源 | C4: 页面/接口 | D4: 币种对 | E4: 口径 | F4: 数值 | G4: 备注
A5: 2026-10-19 19:38 | B5: 国家外汇管理局 | C5: https://www.safe.gov.cn/AppStructured/hlw/RMBQuery.do | D5: USD/CNY | E5: 中间价 | F5: 6.7208 | G5: 当日 09:15 公布；历史序列同源（07 表）
A6: 2026-10-19 16:27:56 | B6: 中国银行外汇牌价 | C6: https://www.boc.cn/sourcedb/whpj/ | D6: USD/CNY | E6: 现汇买入价 | F6: 6.6701 | G6: 出口结汇到手价参考；单位 100 外币
A7: 2026-10-19 16:27:56 | B7: 中国银行外汇牌价 | C7: https://www.boc.cn/sourcedb/whpj/ | D7: USD/CNY | E7: 现汇卖出价 | F7: 6.6982 | G7: 进口购汇付出价参考
A8: 2026-10-19 16:27:56 | B8: 中国银行外汇牌价 | C8: https://www.boc.cn/sourcedb/whpj/ | D8: USD/CNY | E8: 中行折算价 | F8: 6.7208 | G8: 银行内部折算口径，非成交价
A9: 2026-10-16 | B9: 欧洲央行参考汇率（经 Frankfurter API） | C9: https://api.frankfurter.app/latest?from=USD&to=CNY | D9: USD/CNY | E9: 交叉核对 | F9: 6.6862 | G9: 此处的 USD/CNY 由 ECB 以 EUR 为桥的参考汇率推导（非 ECB 直接报价），仅作数量级交叉核对。
A10: 2026-10-19 00:02 UTC | B10: open.er-api.com 聚合汇率 | C10: https://open.er-api.com/v6/latest/USD | D10: USD/CNY | E10: 交叉核对 | F10: 6.69274 | G10: 第三方聚合器，非官方，仅作数量级交叉核对。
A12: • 口径不可混用：中间价不能当作结汇价；现汇买入价 ≠ 现汇卖出价。
A13: • 取数要连带记时间：盘中汇率随时变动，报价单上写「某日某时」比写「今日汇率」可追溯。
A14: • 第三方聚合器（ECB 经桥接换算、er-api 等）只做数量级核对，不作报价依据。

Sheet 09_报价带入
A1: 09 · 把汇率参数带入出口报价
A2: 输入目标毛利率与人民币成本，得到「汇率不变时必须达到的最低外币金额」；这是报价底线，不是市场价预测。
A4: 报价底线计算
B5: 项目 | C5: 数值 | D5: 单位 | E5: 公式 / 说明
B6: 人民币成本 | C6: ='01_输入参数'!$C$14 | D6: 元 | E6: 来自输入
B7: 目标毛利率 | C7: ='01_输入参数'!$C$16 | D7: % | E7: 来自输入（示例 10%）
B8: 银行费用率 | C8: ='01_输入参数'!$C$18 | D8: % | E8: 来自输入
B9: 所需人民币收入（下限，含费用） | C9: =IFERROR(C6/((1-C7)*(1-C8)),"") | D9: 元 | E9: =成本 ÷ [(1−目标毛利率)×(1−费用率)]
B10: 对应外币金额（下限） | C10: =IFERROR(C9/'01_输入参数'!$C$28,"") | D10: 外币 | E10: =所需收入 ÷ 基准汇率（汇率不变假设）
B11: 数量（可选） | C11: 377 | D11: 吨 | E11: 填写实际数量，自动折算单价
B12: 折算单价（下限） | C12: =IFERROR(C10/C11,"") | D12: 外币/吨 | E12: =外币金额下限 ÷ 数量
A14: 报价确定性检查（汇率变动多少会把底线打穿）
B15: • 底线外币金额是按「汇率不变」算出来的；汇率一旦下行，同样的外币收入折算成人民币就会变少。
B16: • 把上面的金额与「03_毛利测算」的平衡汇率一起看：平衡汇率就是底线被打穿的位置。
B17: • 报价单上建议注明：所用汇率与取数时间、口径（中间价/银行成交价）、以及汇率大幅变动时的重新议价条件（是否写入由业务与法务决定）。
B18: • 本表不预测汇率，不推荐避险产品。

Sheet 10_口径与免责
A1: 10 · 口径、数据缺口与免责
A2: 缺口比结论更重要：每一项未计入因素都可能改变最后那个数字。
B4: 项目 | C4: 说明 | D4: 处理方式
B5: 结汇/购汇手续费 | C5: 银行电讯费、手续费、单证费等，按笔收取，部分银行对大额另议。 | D5: 费用率默认 0；拿到实际费率后填入「01_输入参数」C18
B6: 银行点差 | C6: 买价与卖价之差，随币种、金额、时段、客户等级浮动，且盘中变化。 | D6: 点差带为示例 ±0.25%；建议改用银行实际成交价（口径选「实际成交价」）
B7: 远期锁汇点价 | C7: 远期汇率 = 即期 + 掉期点，取决于两币利差与期限；本簿未取任何远期报价。 | D7: 未计入；如需测算锁汇成本，属独立任务
B8: 交易日与节假日 | C8: 长假导致实际可结汇日顺延，影响占用天数。 | D8: 按自然日计算，交易日按 ×5/7 估算
B9: 多币种交叉盘 | C9: 以第三币种计价/结算时的交叉汇率。 | D9: 未处理；需另取两组中间价合成
B10: 合同条款 | C10: 付款条件、汇率调整条款、迟延利息等改变实际暴露。 | D10: 按线性模型计算，未建模条款
B11: 成本端汇率联动 | C11: 若原料或运费以外币计价，人民币成本本身随汇率变动。 | D11: 成本视为常数
B12: 税务与退税 | C12: 出口退税率、免抵退对成本折算的影响。 | D12: 未纳入；属报价与税务环节
B13: 样本口径差异 | C13: 历史序列为官方中间价；银行牌价与之常年存在差异。 | D13: 跨口径比较会失真，已分别标注
A15: 数据来源
B16: 来源 | C16: 地址 / 口径 | D16: 时间
B17: 国家外汇管理局 · 人民币汇率中间价 | C17: https://www.safe.gov.cn/AppStructured/hlw/RMBQuery.do 该口径为中国外汇交易中心公布的中间价，非银行挂牌买卖价；中间价不含银行点差与结售汇手续费。 | D17: 2023-10-09 ~ 2026-10-19，共 735 个交易日
B18: 中国人民银行授权中国外汇交易中心 · 当日中间价（实时页） | C18: https://www.chinamoney.com.cn/r/cms/www/chinamoney/data/fx/ccpr.json 当日 09:15 公布的官方中间价，与历史序列同一来源口径。 | D18: 2026-10-19 09:15
B19: 中国银行外汇牌价（现汇买入价/现汇卖出价） | C19: https://www.boc.cn/sourcedb/whpj/ 银行现汇买入价 = 客户把外币结汇成人民币的到手价（出口收汇用）；现汇卖出价 = 客户用人民币购汇的付出价（进口付汇用）。牌价表单位为 100 外币兑人民币。 | D19: 2026-10-19 16:27:56
B20: 欧洲央行参考汇率（经 Frankfurter API） | C20: https://api.frankfurter.app/latest?from=USD&to=CNY 此处的 USD/CNY 由 ECB 以 EUR 为桥的参考汇率推导（非 ECB 直接报价），仅作数量级交叉核对。 | D20: 2026-10-16
B21: open.er-api.com 聚合汇率 | C21: https://open.er-api.com/v6/latest/USD 第三方聚合器，非官方，仅作数量级交叉核对。 | D21: 2026-10-19 00:02 UTC
B23: 免责：本工作簿只做汇率情景测算，不预测汇率走势，不构成任何外汇避险产品或交易操作的推荐。 「若汇率为 R」的全部内容均为压力测试假设，不代表对未来汇率的判断。 模拟参数（已标注）仅用于演示计算流程；对外使用前请替换为真实数据并核对银行实际成交价。
