Workbook

Sheet 0_封面说明
A1: 轻质纯碱（碳酸钠，Na₂CO₃，CAS 497-19-8） · 理论原料成本分析工作簿
A2: 数据截止 2026-10-20 ｜ 价格口径：含税 ｜ 币种 CNY ｜ 单位：元/吨产品 ｜ 由 chem-cost-model skill 生成
A4: 产品 | B4: 轻质纯碱（碳酸钠，Na₂CO₃，CAS 497-19-8）
A5: 产品 CAS | B5: 497-19-8
A6: 工艺口径 | B6: 氨碱法（索尔维法）
A7: 工艺说明 | B7: 化盐→盐水精制→吸氨→碳化→过滤→煅烧→蒸氨再生；副产氯化钙废液
A8: 反应式 | B8: NaCl + NH3 + CO2 + H2O -> NaHCO3 + NH4Cl; 2 NaHCO3 -> Na2CO3 + CO2 + H2O
A9: 数据截止日 | B9: 2026-10-20
A10: 采购方 / 视角 | B10: 氨碱法纯碱厂 · 采购部
A11: 区域口径 | B11: 华东（原盐/石灰石按厂区就近采购，价格列为缺口）
A12: 单耗口径 | B12: 净单耗（已扣回收、含转化/收率/副反应损失）
A14: 本工作簿怎么用
A15: ① 只改「1_原料参数」的黄色单元格（单耗、价格、规格/地区/来源）与「3_敏感性矩阵」第 5 行的涨跌幅；
A16: ② 「2_成本构成」「3_敏感性矩阵」「4_组合情景明细」「5_历史理论成本」「6_贡献分解」全部是公式，改数即联动；
A17: ③ 「5_历史理论成本」的价格列是真实序列，可替换为你自己的采购成交价（保持日期列）；
A18: ④ 无可靠价格的原料，价格留空 —— 成本显示为空、占比受 IF 保护，这是"缺口"，不要填 0。
A20: 未纳入的成本项（理论原料成本 ≠ 完整生产成本 ≠ 利润）
A21: 未纳入项 | B21: 原因 / 影响
A22: 原盐 | B22: 缺可核验日度价格，按缺口列示（未按 0 计入）——本示例的核心缺口
A23: 石灰石 | B23: 矿山直供价随运距变化，缺可核验价格，按缺口列示
A24: 烟煤（煅烧用） | B24: 行业拆解常单列烟煤 0.1 t/t，本次未采集到可核验价格
A25: 能源（电、蒸汽） | B25: 占氨碱法成本显著比例，需企业能耗台账
A26: 人工与制造费用 | B26: 不属"原料"
A27: 折旧、维护、环保（废液处理） | B27: 资本性与环保支出，氨碱法废液处理成本高
A28: 运输、包装、仓储、资金占用 | B28: 与提货方式、账期相关
A29: 税费（增值税以外的附加、环保税、碳排放成本） | B29: 不进入原料成本
A31: 文献中存在但无法量化的项
A32: 氯化铵联产（联碱法才有） | B32: 原因：本示例为氨碱法，不产氯化铵 ｜ 影响：不影响本模型
A33: 碳排放成本 | B33: 原因：吨碱碳排放核算口径与配额价格未定 ｜ 影响：可能显著推高完全成本，但不属原料成本
A35: 使用限制
A36: · 本表是"理论原料成本"模型：只含"有价格的原料单耗 × 价格"，不含能源、人工、折旧、维护、运输、包装与期间费用。
A37: · 不得把本表结果当作完整生产成本、销售成本或利润，也不得据此对外报价。
A38: · 本表不预测原料未来价格；敏感性矩阵只是"若涨/跌 X% 则成本变化"的机械演算。
A39: · 单耗为行业典型值时，已在「1_原料参数」列明来源与适用工艺；替换为企业实测值后结论可能显著改变。
A40: · 历史价格缺口未插值，一律留空；数据来源见「7_数据来源」与「9_缺口与待补」。

Sheet 1_原料参数
A1: ① 原料参数（黄色 = 可修改的原始输入；灰色 = 公式）
A2: 改这里，其余工作表自动重算。单耗统一换算为 t/t 产品；价格统一换算为 含税 元/吨。
A3: 原料ID | B3: 原料名称 | C3: CAS | D3: 主/辅 | E3: 单耗(原值) | F3: 单耗单位 | G3: 单耗(t/t) | H3: 价格(原值) | I3: 计价单位 | J3: 原口径 | K3: 价格(元/t目标口径) | L3: 单项成本(元/t) | M3: 成本占比 | N3: 规格 | O3: 地区 | P3: 交货方式 | Q3: 价格日期 | R3: 单耗来源 | S3: 价格来源
A4: salt | B4: 原盐（工业盐，NaCl） | C4: 7647-14-5 | D4: 主料 | E4: 1.5 | F4: t/t | G4: =IF(E4="","",E4*1.0) | I4: CNY/t | J4: 含税 | K4: =IF(H4="","",H4*1.0*1.0) | L4: =IF(OR($G4="",$K4=""),"",$G4*$K4) | M4: =IF($L4="","",IF(SUM($L$4:$L$7)=0,"",$L4/SUM($L$4:$L$7))) | N4: 工业盐 ≥96% | O4: 华东 | P4: 送到 | Q4: — | R4: 行业协会/机构 | S4: （无价格：缺口）
A5: lime | B5: 石灰石（CaCO₃） | C5: 471-34-1 | D5: 主料 | E5: 1.3 | F5: t/t | G5: =IF(E5="","",E5*1.0) | I5: CNY/t | J5: 含税 | K5: =IF(H5="","",H5*1.0*1.0) | L5: =IF(OR($G5="",$K5=""),"",$G5*$K5) | M5: =IF($L5="","",IF(SUM($L$4:$L$7)=0,"",$L5/SUM($L$4:$L$7))) | N5: CaCO₃ ≥95%，30-60mm | O5: 华东 | P5: 矿山直送 | Q5: — | R5: 行业协会/机构 | S5: （无价格：缺口）
A6: coal | B6: 动力煤（燃料） | C6: — | D6: 辅料 | E6: 0.58 | F6: t/t | G6: =IF(E6="","",E6*1.0) | H6: 1041 | I6: CNY/t | J6: 含税 | K6: =IF(H6="","",H6*1.0*1.0) | L6: =IF(OR($G6="",$K6=""),"",$G6*$K6) | M6: =IF($L6="","",IF(SUM($L$4:$L$7)=0,"",$L6/SUM($L$4:$L$7))) | N6: Q5500 | O6: 全国综合 | P6: 市场价 | Q6: 2026-10-20 | R6: 券商/研究机构 | S6: 生意社（100ppi.com）动力煤基准价
A7: amm | B7: 液氨（补充氨耗） | C7: 7664-41-7 | D7: 辅料 | E7: 0.004 | F7: t/t | G7: =IF(E7="","",E7*1.0) | H7: 2686.67 | I7: CNY/t | J7: 含税 | K7: =IF(H7="","",H7*1.0*1.0) | L7: =IF(OR($G7="",$K7=""),"",$G7*$K7) | M7: =IF($L7="","",IF(SUM($L$4:$L$7)=0,"",$L7/SUM($L$4:$L$7))) | N7: ≥99.6% | O7: 全国综合 | P7: 市场价 | Q7: 2026-10-21 | R7: 券商/研究机构 | S7: 生意社（100ppi.com）液氨基准价
B8: 合计（仅计有价格的原料） | G8: =SUM(G4:G7) | L8: =SUM(L4:L7) | M8: =IF(L8=0,"",SUM(M4:M7))
A10: 单位与税口径换算：单耗(t/t) = 原值 × 系数（kg/t→0.001，g/t→0.000001）；价格(元/t) = 原值 × 计价换算（元/kg→1000）× 税口径系数（含税→不含税 ÷1.13，反之 ×1.13）。公式写在单元格里，可直接点开查看。
A11: 税率 13% 为增值税一般税率默认值，须由企业按自身纳税身份核定；若为小规模纳税人或享受优惠，请把本表 X 列（见「8_公式与口径」）改成本企业实际值。

Sheet 2_成本构成
A1: ② 单位产品理论原料成本与构成
A2: 公式：C = Σ(q_i × p_i)；占比 = c_i / C。全部引用「1_原料参数」。
A3: 原料 | B3: 单耗(t/t) | C3: 价格(元/t) | D3: 单项成本(元/t) | E3: 成本占比 | F3: 累计占比 | G3: 排名
A4: ='1_原料参数'!B6 | B4: ='1_原料参数'!G6 | C4: ='1_原料参数'!K6 | D4: ='1_原料参数'!L6 | E4: =IF($D$6=0,"",D4/$D$6) | F4: =E4 | G4: 1
A5: ='1_原料参数'!B7 | B5: ='1_原料参数'!G7 | C5: ='1_原料参数'!K7 | D5: ='1_原料参数'!L7 | E5: =IF($D$6=0,"",D5/$D$6) | F5: =F4+E5 | G5: 2
A6: 理论原料成本合计 | B6: =SUM(B4:B5) | D6: =SUM(D4:D5) | E6: =SUM(E4:E5)
A8: 主料合计 | D8: =SUMIF('1_原料参数'!$D$4:$D$7,"主料",'1_原料参数'!$L$4:$L$7)
A9: 辅料合计 | D9: =SUMIF('1_原料参数'!$D$4:$D$7,"辅料",'1_原料参数'!$L$4:$L$7)
A10: 已计价原料条数 | D10: =COUNT('1_原料参数'!$L$4:$L$7)&" / 4 条"
A11: 未计价（缺口）原料 | D11: 原盐（工业盐，NaCl）、石灰石（CaCO₃）

Sheet 3_敏感性矩阵
A1: ③ 价格敏感性矩阵与组合情景
A2: Δc_i = q_i × p_i × r_i；组合 ΔC = ΣΔc_i。第 5 行涨跌幅（%）为输入，其余为公式。
A4: 涨跌幅档位（与热力图 D 列起一一对齐） | D4: -10% | E4: -5% | F4: 0% | G4: +5% | H4: +10% | I4: 单耗+1% 影响(元/吨)
D5: -0.1 | E5: -0.05 | F5: 0 | G5: 0.05 | H5: 0.1
A6: 第 5 行可改（例如改成 3、7、15），下方热力图与合计自动跟随。
A7: A. 敏感性热力图：单位成本变化（元/吨产品）
A8: 原料 | B8: 单耗(t/t) | C8: 价格(元/t) | D8: -10% | E8: -5% | F8: 0% | G8: +5% | H8: +10%
A9: ='1_原料参数'!B6 | B9: ='1_原料参数'!G6 | C9: ='1_原料参数'!K6 | D9: =$B9*$C9*D$5 | E9: =$B9*$C9*E$5 | F9: =$B9*$C9*F$5 | G9: =$B9*$C9*G$5 | H9: =$B9*$C9*H$5
A10: ='1_原料参数'!B7 | B10: ='1_原料参数'!G7 | C10: ='1_原料参数'!K7 | D10: =$B10*$C10*D$5 | E10: =$B10*$C10*E$5 | F10: =$B10*$C10*F$5 | G10: =$B10*$C10*G$5 | H10: =$B10*$C10*H$5
A11: 合计/全部原料同步 | B11: =SUM(B9:B10) | D11: =SUM(D9:D10) | E11: =SUM(E9:E10) | F11: =SUM(F9:F10) | G11: =SUM(G9:G10) | H11: =SUM(H9:H10)
A13: B. 单原料逐档明细（基于「2_成本构成」合计 D6）
A14: 原料 | B14: -10% 后成本 | C14: -5% 后成本 | D14: 0% 后成本 | E14: +5% 后成本 | F14: +10% 后成本 | G14: -10% Δ% | H14: -5% Δ% | I14: 0% Δ% | J14: +5% Δ% | K14: +10% Δ%
A15: ='1_原料参数'!B6 | B15: =$D$6*$C$9+D9 | C15: =$D$6*$C$9+E9 | D15: =$D$6*$C$9+F9 | E15: =$D$6*$C$9+G9 | F15: =$D$6*$C$9+H9 | G15: =IF($D$6=0,"",D9/$D$6) | H15: =IF($D$6=0,"",E9/$D$6) | I15: =IF($D$6=0,"",F9/$D$6) | J15: =IF($D$6=0,"",G9/$D$6) | K15: =IF($D$6=0,"",H9/$D$6)
A16: ='1_原料参数'!B7 | B16: =$D$6*$C$10+D10 | C16: =$D$6*$C$10+E10 | D16: =$D$6*$C$10+F10 | E16: =$D$6*$C$10+G10 | F16: =$D$6*$C$10+H10 | G16: =IF($D$6=0,"",D10/$D$6) | H16: =IF($D$6=0,"",E10/$D$6) | I16: =IF($D$6=0,"",F10/$D$6) | J16: =IF($D$6=0,"",G10/$D$6) | K16: =IF($D$6=0,"",H10/$D$6)
A18: C. 组合情景：多原料同时变动后每吨理论原料成本
A19: 情景 | B19: 动力煤（燃料） % | C19: 液氨（补充氨耗） % | D19: 基准成本 | E19: 情景成本 | F19: Δ成本 | G19: Δ%
A20: 燃料煤 +10% | B20: 10 | C20: 0 | D20: ='2_成本构成'!$D$6 | E20: ='1_原料参数'!$G$6*'1_原料参数'!$K$6*(1+B20/100)+'1_原料参数'!$G$7*'1_原料参数'!$K$7*(1+C20/100) | F20: =E20-D20 | G20: =IF(D20=0,"",F20/D20)
A21: 煤 +10% / 液氨 +10% | B21: 10 | C21: 10 | D21: ='2_成本构成'!$D$6 | E21: ='1_原料参数'!$G$6*'1_原料参数'!$K$6*(1+B21/100)+'1_原料参数'!$G$7*'1_原料参数'!$K$7*(1+C21/100) | F21: =E21-D21 | G21: =IF(D21=0,"",F21/D21)
A22: 煤 +20% | B22: 20 | C22: 0 | D22: ='2_成本构成'!$D$6 | E22: ='1_原料参数'!$G$6*'1_原料参数'!$K$6*(1+B22/100)+'1_原料参数'!$G$7*'1_原料参数'!$K$7*(1+C22/100) | F22: =E22-D22 | G22: =IF(D22=0,"",F22/D22)
A24: 情景成本 = Σ 单耗_i × 价格_i × (1 + 涨跌幅_i/100)。缺价原料不进入求和——若某原料缺价，情景结果与该缺口同口径（页面已在"缺口"清单中标注）。

Sheet 4_组合情景明细
A1: ④ 组合情景逐原料贡献
A2: 每情景下各原料成本变化与对总成本的贡献。
A3: 燃料煤 +10%
A4: 原料 | B4: 变动幅度 | C4: 原成本 | D4: 新成本 | E4: Δ成本 | F4: Δ占总成本
A5: ='1_原料参数'!B6 | B5: 10 | C5: ='1_原料参数'!L6 | D5: =IF(C5="","",C5*(1+B5/100)) | E5: =IF(D5="","",D5-C5) | F5: =IF('2_成本构成'!$D$6=0,"",E5/'2_成本构成'!$D$6)
A6: ='1_原料参数'!B7 | B6: 0 | C6: ='1_原料参数'!L7 | D6: =IF(C6="","",C6*(1+B6/100)) | E6: =IF(D6="","",D6-C6) | F6: =IF('2_成本构成'!$D$6=0,"",E6/'2_成本构成'!$D$6)
A7: 合计 | C7: =SUM(C5:C6) | D7: =SUM(D5:D6) | E7: =SUM(E5:E6) | F7: =IF('2_成本构成'!$D$6=0,"",E7/'2_成本构成'!$D$6)
A9: 煤 +10% / 液氨 +10%
A10: 原料 | B10: 变动幅度 | C10: 原成本 | D10: 新成本 | E10: Δ成本 | F10: Δ占总成本
A11: ='1_原料参数'!B6 | B11: 10 | C11: ='1_原料参数'!L6 | D11: =IF(C11="","",C11*(1+B11/100)) | E11: =IF(D11="","",D11-C11) | F11: =IF('2_成本构成'!$D$6=0,"",E11/'2_成本构成'!$D$6)
A12: ='1_原料参数'!B7 | B12: 10 | C12: ='1_原料参数'!L7 | D12: =IF(C12="","",C12*(1+B12/100)) | E12: =IF(D12="","",D12-C12) | F12: =IF('2_成本构成'!$D$6=0,"",E12/'2_成本构成'!$D$6)
A13: 合计 | C13: =SUM(C11:C12) | D13: =SUM(D11:D12) | E13: =SUM(E11:E12) | F13: =IF('2_成本构成'!$D$6=0,"",E13/'2_成本构成'!$D$6)
A15: 煤 +20%
A16: 原料 | B16: 变动幅度 | C16: 原成本 | D16: 新成本 | E16: Δ成本 | F16: Δ占总成本
A17: ='1_原料参数'!B6 | B17: 20 | C17: ='1_原料参数'!L6 | D17: =IF(C17="","",C17*(1+B17/100)) | E17: =IF(D17="","",D17-C17) | F17: =IF('2_成本构成'!$D$6=0,"",E17/'2_成本构成'!$D$6)
A18: ='1_原料参数'!B7 | B18: 0 | C18: ='1_原料参数'!L7 | D18: =IF(C18="","",C18*(1+B18/100)) | E18: =IF(D18="","",D18-C18) | F18: =IF('2_成本构成'!$D$6=0,"",E18/'2_成本构成'!$D$6)
A19: 合计 | C19: =SUM(C17:C18) | D19: =SUM(D17:D18) | E19: =SUM(E17:E18) | F19: =IF('2_成本构成'!$D$6=0,"",E19/'2_成本构成'!$D$6)

Sheet 5_历史理论成本
A1: ⑤ 历史价格原始数据与历史理论原料成本
A2: 价格列 = 真实序列；成本列 = 公式（固定单耗 × 当日价格）。价格留空 → 成本留空（缺口，不插值）。
A3: 日期 | B3: 动力煤 价格(元/t) | C3: 液氨 价格(元/t) | D3: 动力煤（燃料） 成本 | E3: 液氨（补充氨耗） 成本 | F3: 历史理论原料成本(元/t)
A4: 2026-07-21 | B4: 840.5 | C4: 2176.67 | D4: =IF(B4="","",'1_原料参数'!$G$6*B4) | E4: =IF(C4="","",'1_原料参数'!$G$7*C4) | F4: =IF(OR(D4="",E4=""),"",SUM(D4:E4))
A5: 2026-07-22 | B5: 840.5 | C5: 2176.67 | D5: =IF(B5="","",'1_原料参数'!$G$6*B5) | E5: =IF(C5="","",'1_原料参数'!$G$7*C5) | F5: =IF(OR(D5="",E5=""),"",SUM(D5:E5))
A6: 2026-07-23 | B6: 841.5 | C6: 2166.67 | D6: =IF(B6="","",'1_原料参数'!$G$6*B6) | E6: =IF(C6="","",'1_原料参数'!$G$7*C6) | F6: =IF(OR(D6="",E6=""),"",SUM(D6:E6))
A7: 2026-07-24 | B7: 841.5 | C7: 2150 | D7: =IF(B7="","",'1_原料参数'!$G$6*B7) | E7: =IF(C7="","",'1_原料参数'!$G$7*C7) | F7: =IF(OR(D7="",E7=""),"",SUM(D7:E7))
A8: 2026-07-25 | B8: 841.5 | C8: 2150 | D8: =IF(B8="","",'1_原料参数'!$G$6*B8) | E8: =IF(C8="","",'1_原料参数'!$G$7*C8) | F8: =IF(OR(D8="",E8=""),"",SUM(D8:E8))
A9: 2026-07-26 | B9: 841.5 | C9: 2150 | D9: =IF(B9="","",'1_原料参数'!$G$6*B9) | E9: =IF(C9="","",'1_原料参数'!$G$7*C9) | F9: =IF(OR(D9="",E9=""),"",SUM(D9:E9))
A10: 2026-07-27 | B10: 841.5 | C10: 2243.33 | D10: =IF(B10="","",'1_原料参数'!$G$6*B10) | E10: =IF(C10="","",'1_原料参数'!$G$7*C10) | F10: =IF(OR(D10="",E10=""),"",SUM(D10:E10))
A11: 2026-07-28 | B11: 841.5 | C11: 2250 | D11: =IF(B11="","",'1_原料参数'!$G$6*B11) | E11: =IF(C11="","",'1_原料参数'!$G$7*C11) | F11: =IF(OR(D11="",E11=""),"",SUM(D11:E11))
A12: 2026-07-29 | B12: 841.5 | C12: 2250 | D12: =IF(B12="","",'1_原料参数'!$G$6*B12) | E12: =IF(C12="","",'1_原料参数'!$G$7*C12) | F12: =IF(OR(D12="",E12=""),"",SUM(D12:E12))
A13: 2026-07-30 | B13: 841.5 | C13: 2250 | D13: =IF(B13="","",'1_原料参数'!$G$6*B13) | E13: =IF(C13="","",'1_原料参数'!$G$7*C13) | F13: =IF(OR(D13="",E13=""),"",SUM(D13:E13))
A14: 2026-07-31 | B14: 844 | C14: 2240 | D14: =IF(B14="","",'1_原料参数'!$G$6*B14) | E14: =IF(C14="","",'1_原料参数'!$G$7*C14) | F14: =IF(OR(D14="",E14=""),"",SUM(D14:E14))
A15: 2026-08-01 | B15: 844 | C15: 2240 | D15: =IF(B15="","",'1_原料参数'!$G$6*B15) | E15: =IF(C15="","",'1_原料参数'!$G$7*C15) | F15: =IF(OR(D15="",E15=""),"",SUM(D15:E15))
... A95: 2026-10-20 | B95: 1041 | C95: 2686.67 | D95: =IF(B95="","",'1_原料参数'!$G$6*B95) | E95: =IF(C95="","",'1_原料参数'!$G$7*C95) | F95: =IF(OR(D95="",E95=""),"",SUM(D95:E95))
A97: 历史变化统计（按日历回溯；起点早于数据起点 → 缺口，不插值）
A98: 窗口 | B98: 起点日 | C98: 起点成本 | D98: 终点日 | E98: 终点成本 | F98: Δ成本 | G98: Δ%
A99: 30天 | B99: 2026-09-20 | C99: 582.81332 | D99: 2026-10-20 | E99: =F95 | F99: =E99-C99 | G99: =IF(C99=0,"",F99/C99)
A100: 3个月 | B100: 2026-07-21 | C100: 496.19668 | D100: 2026-10-20 | E100: =F95 | F100: =E100-C100 | G100: =IF(C100=0,"",F100/C100)
A101: 1年 | B101: — | D101: 2026-10-20 | E101: =F95 | F101: 缺口，未插值 | G101: —
A102: 3年 | B102: — | D102: 2026-10-20 | E102: =F95 | F102: 缺口，未插值 | G102: —

Sheet 6_贡献分解
A1: ⑥ 各原料对历史成本变化的贡献
A2: Δc_i = q_i×(p_i,T − p_i,0)；贡献比 = Δc_i / ΔC_T（ΔC_T≈0 时留空）。
A3: 窗口 30天：2026-09-20 → 2026-10-20
A4: 原料 | B4: 起点成本 | C4: 终点成本 | D4: Δ成本 | E4: 占总变化比
A5: 动力煤（燃料） | B5: 570.72 | C5: 603.78 | D5: =C5-B5 | E5: =IF(ABS($D$7)<0.000001,"",D5/$D$7)
A6: 液氨（补充氨耗） | B6: 12.09332 | C6: 10.74668 | D6: =C6-B6 | E6: =IF(ABS($D$7)<0.000001,"",D6/$D$7)
A7: 合计 | B7: =SUM(B5:B6) | C7: =SUM(C5:C6) | D7: =SUM(D5:D6) | E7: =IF(ABS(D7)<0.000001,"",SUM(E5:E6))
A9: 窗口 3个月：2026-07-21 → 2026-10-20
A10: 原料 | B10: 起点成本 | C10: 终点成本 | D10: Δ成本 | E10: 占总变化比
A11: 动力煤（燃料） | B11: 487.49 | C11: 603.78 | D11: =C11-B11 | E11: =IF(ABS($D$13)<0.000001,"",D11/$D$13)
A12: 液氨（补充氨耗） | B12: 8.70668 | C12: 10.74668 | D12: =C12-B12 | E12: =IF(ABS($D$13)<0.000001,"",D12/$D$13)
A13: 合计 | B13: =SUM(B11:B12) | C13: =SUM(C11:C12) | D13: =SUM(D11:D12) | E13: =IF(ABS(D13)<0.000001,"",SUM(E11:E12))
A15: 窗口 1年：— → —
A16: 缺口：该窗口起点早于可得数据（2026-07-21 起），无法计算，未做插值/补数
A18: 窗口 3年：— → —
A19: 缺口：该窗口起点早于可得数据（2026-07-21 起），无法计算，未做插值/补数

Sheet 7_数据来源
A1: ⑦ 数据来源清单（单耗 / 价格 / 标准）
A3: 来源ID | B3: 类型 | C3: 标题 | D3: URL | E3: 用于哪些参数
A4: S1 | B4: B/资讯商 | C4: 生意社（100ppi.com）动力煤基准价（Q5500） | D4: https://www.100ppi.com/graph/cindex.php?f=graph_ppid_ave&ppid=369 | E4: 燃料煤价格与93天历史
A5: S2 | B5: B/资讯商 | C5: 生意社（100ppi.com）液氨基准价 | D5: https://www.100ppi.com/graph/cindex.php?f=graph_ppid_ave&ppid=965 | E5: 液氨价格与历史
A6: S3 | B6: B/资讯商 | C6: 生意社（100ppi.com）重质纯碱基准价 | D6: https://www.100ppi.com/graph/cindex.php?f=graph_ppid_ave&ppid=737 | E6: 产品价参照与加工价差
A7: S4 | B7: C/行业媒体 | C7: 山东化工网《氨碱法纯碱：在变局中探寻可持续发展之路》(2025-02-27) | D7: http://www.sdchem.com.cn/html/wuji/gnxw/2025/0227/38746.html | E7: 原盐 1.5 t/t、石灰石 1.3 t/t 的行业口径
A8: S5 | B8: C/研究 | C8: 七禾网《纯碱生产成本核算》(2025-04-24) | D8: https://www.7hcn.com/article/469438-1.html | E8: 氨碱法成本公式：原盐*1.6 + 动力煤*0.58 + 烟煤*0.1 + 550
A9: S6 | B9: C/研究 | C9: 光期研究《走进纯碱原料——原盐》 | D9: http://www.cfachina.org/servicesupport/analygarden/nyhgl/cj_5769/202306/P020230630561088700775.pdf | E9: 氨碱法原盐吨耗 1.6 t/t 交叉验证

Sheet 8_公式与口径
A1: ⑧ 计算公式、单位换算与口径约定
A3: 项目 | B3: 公式 / 规则 | C3: 说明 / 本例取值
A4: 单项成本 | B4: c_i = q_i × p_i | C4: 单耗(t/t) × 价格(元/t) = 元/吨产品
A5: 理论原料成本 | B5: C = Σ c_i | C5: 只含已计价原料，缺价原料不按 0 计
A6: 成本占比 | B6: w_i = c_i / C | C6: 缺价原料存在时为"占已计价部分"口径
A7: 涨价影响 | B7: Δc_i = q_i × p_i × r | C7: r 为涨跌幅，+10% 即 0.10
A9: 单位换算 | B9: 1 t = 1000 kg；1 kg/t 产品 = 0.001 t/t 产品；涨跌幅列按"%"填写，公式内部 ÷100
A10: 税口径 | B10: 含税→不含税 ÷(1+税率)；不含税→含税 ×(1+税率)。税率由「1_原料参数」X 列语义约定，默认 13%，须企业核定
A11: 单耗口径 | B11: 净单耗（已扣回收、含转化/收率/副反应损失）。单耗取公开行业口径（多源交叉）：原盐 1.5-1.6 t/t、石灰石 1.3 t/t、动力煤 0.58 t/t、液氨 ~4 kg/t。本示例取保守值：原盐 1.5、石灰石 1.3、动力煤 0.58、液氨 0.004。收率定义未取得，未参与计算。
A12: 成品收率 | B12: 收率 — / 转化率 — / 过量醇回收率 —

Sheet 9_缺口与待补
A1: ⑨ 缺口、未量化项与待补数据
A2: 缺什么、影响什么、怎么补。没有可靠数据的一律留空，不估算、不插值。
A3: 类型 | B3: 项目 | C3: 说明 | D3: 影响 | E3: 补齐路径
A4: 价格缺口 | B4: 原盐（工业盐，NaCl） | C4: 价格缺失：该原料成本无法计入（不按 0 处理，单列为缺口） | D4: 该原料未计入理论原料成本；总成本仅覆盖已计价原料，口径为"部分覆盖" | E4: 补充同规格/同区域/同税口径的现货价（含数据日期与来源）
A5: 价格缺口 | B5: 石灰石（CaCO₃） | C5: 价格缺失：该原料成本无法计入（不按 0 处理，单列为缺口） | D5: 该原料未计入理论原料成本；总成本仅覆盖已计价原料，口径为"部分覆盖" | E5: 补充同规格/同区域/同税口径的现货价（含数据日期与来源）
A6: 历史序列 | B6: 原盐价格 | C6: 生意社未收录可公开核验的原盐日度基准价序列 | D6: 原盐占氨碱法原料成本的大头（1.5 t/t），缺价会使合计严重低估 | E6: 用本厂采购合同价或当地盐业公司挂牌价，按六项口径填入 materials[salt].price
A7: 历史序列 | B7: 石灰石价格 | C7: 矿山直供价，随运距剧烈变化，无公开日序列 | D7: 石灰石 1.3 t/t 未计入 | E7: 用本厂到厂价（含运费）填入 materials[lime].price
A8: 历史序列 | B8: 历史长度 | C8: 100ppi 端点只返回 93 天 | D8: 1年/3年窗口无法计算 | E8: 卓创/隆众付费终端或自建日采集
A9: 历史窗口 | B9: 1年 | C9: 该窗口起点早于可得数据（2026-07-21 起），无法计算，未做插值/补数 | D9: 该时间窗的理论成本变化不展示为数字 | E9: 接入更长历史价格源（付费终端/自采积累）
A10: 历史窗口 | B10: 3年 | C10: 该窗口起点早于可得数据（2026-07-21 起），无法计算，未做插值/补数 | D10: 该时间窗的理论成本变化不展示为数字 | E10: 接入更长历史价格源（付费终端/自采积累）

Sheet 10_与产品价并列
A1: ⑩ 理论原料成本 vs 产品现货价（加工价差 ≠ 利润）
A2: 价差 = 产品价 − 理论原料成本，仅表示"原料之外还剩多少空间"，未扣能源/人工/折旧/运费，不是利润。
A3: 日期 | B3: 产品价(元/t) | C3: 理论原料成本(元/t) | D3: 价差(元/t) | E3: 价差率
A4: 2026-07-21 | B4: 1152.86 | C4: ='5_历史理论成本'!F4 | D4: =IF(OR(B4="",C4=""),"",B4-C4) | E4: =IF(OR(B4="",C4="",B4=0),"",D4/B4)
A5: 2026-07-22 | B5: 1152.86 | C5: ='5_历史理论成本'!F5 | D5: =IF(OR(B5="",C5=""),"",B5-C5) | E5: =IF(OR(B5="",C5="",B5=0),"",D5/B5)
A6: 2026-07-23 | B6: 1152.86 | C6: ='5_历史理论成本'!F6 | D6: =IF(OR(B6="",C6=""),"",B6-C6) | E6: =IF(OR(B6="",C6="",B6=0),"",D6/B6)
A7: 2026-07-24 | B7: 1152.86 | C7: ='5_历史理论成本'!F7 | D7: =IF(OR(B7="",C7=""),"",B7-C7) | E7: =IF(OR(B7="",C7="",B7=0),"",D7/B7)
A8: 2026-07-25 | B8: 1152.86 | C8: ='5_历史理论成本'!F8 | D8: =IF(OR(B8="",C8=""),"",B8-C8) | E8: =IF(OR(B8="",C8="",B8=0),"",D8/B8)
A9: 2026-07-26 | B9: 1152.86 | C9: ='5_历史理论成本'!F9 | D9: =IF(OR(B9="",C9=""),"",B9-C9) | E9: =IF(OR(B9="",C9="",B9=0),"",D9/B9)
A10: 2026-07-27 | B10: 1144.29 | C10: ='5_历史理论成本'!F10 | D10: =IF(OR(B10="",C10=""),"",B10-C10) | E10: =IF(OR(B10="",C10="",B10=0),"",D10/B10)
A11: 2026-07-28 | B11: 1144.29 | C11: ='5_历史理论成本'!F11 | D11: =IF(OR(B11="",C11=""),"",B11-C11) | E11: =IF(OR(B11="",C11="",B11=0),"",D11/B11)
A12: 2026-07-29 | B12: 1144.29 | C12: ='5_历史理论成本'!F12 | D12: =IF(OR(B12="",C12=""),"",B12-C12) | E12: =IF(OR(B12="",C12="",B12=0),"",D12/B12)
A13: 2026-07-30 | B13: 1140 | C13: ='5_历史理论成本'!F13 | D13: =IF(OR(B13="",C13=""),"",B13-C13) | E13: =IF(OR(B13="",C13="",B13=0),"",D13/B13)
A14: 2026-07-31 | B14: 1104.29 | C14: ='5_历史理论成本'!F14 | D14: =IF(OR(B14="",C14=""),"",B14-C14) | E14: =IF(OR(B14="",C14="",B14=0),"",D14/B14)
A15: 2026-08-01 | B15: 1104.29 | C15: ='5_历史理论成本'!F15 | D15: =IF(OR(B15="",C15=""),"",B15-C15) | E15: =IF(OR(B15="",C15="",B15=0),"",D15/B15)
... A95: 2026-10-20 | B95: 1062.86 | C95: ='5_历史理论成本'!F95 | D95: =IF(OR(B95="",C95=""),"",B95-C95) | E95: =IF(OR(B95="",C95="",B95=0),"",D95/B95)
A97: 产品价来源：生意社（100ppi.com）基准价 · 重质纯碱（重质纯碱，全国综合）
A98: 仅用于与理论原料成本并列展示加工价差，不是成本的一部分
