Workbook

Sheet 0-说明
A1: 进口窗口判断 · 进口乙二醇（MEG）· 海外报价 vs 华东现货
A2: 中国华东地区自海外市场进口聚酯级乙二醇，与华东（张家港）罐区现货价比较
A4: 基准日 | B4: 2026-10-16
A5: 商品 / 规格 | B5: 乙二醇（聚酯级（Polyester grade，含量 ≥99.9%，散水/散装））· HS 29053100 · CAS 107-21-1
A6: 海外市场 → 国内区域 | B6: 海外市场（中东 / 东北亚，按 CFR 中国口径） → 中国华东 · 江苏张家港（长江口罐区）
A7: 币种 / 单位 | B7: 海外 USD/吨；国内 CNY/吨
A8: 生成时间 | B8: 2026-10-20
A10: 【本表怎么用】
A11: 1. 黄色单元格 = 可修改的输入（报价、汇率、运费、税率、费用等）；改完 Excel 自动重算全表。
A12: 2. 蓝灰色单元格 = 公式，请勿手改。
A13: 3. 任何"待补"都表示该项数据缺失，不得当成 0 使用；在「8-缺口登记」补齐来源后再算。
A14: 4. 「9-引擎校验」为独立计算引擎的对照结果，用于确认真实计算与页面一致。
A16: 【口径声明】
A17: · 比较对象：国内含税现货价（增值税可抵扣） ↔ 进口"含税净成本"（剔除可抵扣进口增值税）。
A18: · 两端都只算到"口岸/罐区"，不含内陆配送；如国内是有送货价，必须扣回。
A19: · 理论价差 ≠ 可执行贸易利润：运费、资金、罐容、损耗、对手方风险均未包含。
A20: · 本表不做价格预测，也不给出交易指令。
A22: 本页只做同一口径下的折算与比较，不构成进口交易指令，不预测价格走势。理论价差不等于可执行贸易利润。

Sheet 1-参数
A1: ① 参数区（黄底=可编辑，改完自动重算全表）
A3: 参数 | B3: 值 | C3: 单位 | D3: 来源 / 依据 | E3: 备注
A5: — 商品与批次 —
A6: 商品 | B6: 乙二醇 | D6: 本案例
A7: 规格 | B7: 聚酯级（Polyester grade，含量 ≥99.9%，散水/散装） | D7: 本案例 | E7: 规格不同不可比
A8: HS 税号 | B8: 29053100 | D8: 财政部 2026 暂定税率表 | E8: 以实际报关税号为准
A9: 单批数量 | B9: 5000 | C9: 吨 | D9: 本案例 | E9: 影响运费与议价
A10: 预计航程 | B10: 12 | C10: 天 | D10: 常规航程 | E10: 用于资金占用测算
A12: — 海外报价 —
A13: 报价日期 | B13: 2026-10-16 | D13: S-CPH-1015
A14: 海外报价 | B14: 685 | C14: USD/吨 | D14: S-CPH-1015 | E14: 指数/到岸评估价（不是某一供应商对某一票货的报盘）
A15: 贸易术语 | B15: CFR | D15: 报价单 | E15: FOB / CFR / CIF
A16: 升贴水 | B16: 0 | C16: USD/吨 | D16: 议价结果
A17: 交货口岸 | B17: CFR China Main Port（华东主港）
A19: — 国际运费与保险 —
A20: 国际运费 | C20: USD/吨 | D20: 未取得 | E20: 缺口时务必留空，不要填 0
A21: 保险费率 | C21: %（占 CIF×110%） | D21: 缺口 G7 | E21: CFR 口径需另加保险
A23: — 汇率 —
A24: 汇率日期 | B24: 2026-10-16 | D24: S-ECB-REF / S-CFETS | E24: 必须与价格同日
A25: USD/CNY | B25: 6.6862 | C25: CNY/USD | D25: S-ECB-REF | E25: 海关适用汇率可能略低
A27: — 关税与增值税 —
A28: 关税税率 | B28: 5.5 | C28: % | D28: S-MOF-TARIFF2026 | E28: 以报关日税则为准
A29: 进口增值税率 | B29: 13 | C29: % | D29: 增值税暂行条例 | E29: 13% 标准税率
A30: 增值税可抵扣 | B30: 是 | E30: 一般纳税人为"是"
A32: — 境内费用 —
A33: 境内费用合计 | C33: 元/吨 | D33: 港杂/报关/仓储/短驳实票 | E33: 缺口 G6
A34: 其他费用 | B34: 0 | C34: 元/吨
A36: — 国内现货 —
A37: 国内现货价（含税） | B37: 5865.33 | C37: 元/吨 | D37: S-OILCHEM-SERIES | E37: 隆众 MEG 全国主流市场均价（10-16）
A38: 交货方式 | B38: 罐区自提（ex-tank） | E38: 自提价不可与送到价直接比
A39: 是否含税 | B39: 是

Sheet 2-进口成本折算
A1: ② 折算过程（全部为公式，随「1-参数」实时重算）
A3: 步骤 | B3: 项目 | C3: 公式（中文口径） | D3: 金额 | E3: 单位 | F3: 取值说明
A4: 1 | B4: 海外报价（净价） | C4: 报价 − 升贴水补充 | D4: =IF('1-参数'!B14="","待补",'1-参数'!B14+IF('1-参数'!B16="",0,'1-参数'!B16)) | E4: USD/吨 | F4: 报价加升贴水
A5: 2 | B5: CFR 价格 | C5: FOB 加运费；CFR/CIF 直接取 | D5: =IF('1-参数'!B15="FOB",IF(OR('1-参数'!B20="",'1-参数'!B20=0),"待补",D4+'1-参数'!B20),D4) | E5: USD/吨 | F5: 缺运费则 FOB 不可折算
A6: 3 | B6: 保险费 | C6: CFR × 费率 × 110% ÷ (1 − 费率×1.1) | D6: =IF('1-参数'!B15="CIF",0,IF('1-参数'!B21="",0,D5*'1-参数'!B21/100*1.1/(1-'1-参数'!B21/100*1.1))) | E6: USD/吨 | F6: CIF 已含保险
A7: 4 | B7: CIF 价格 | C7: CFR + 保险费 | D7: =IF(NOT(ISNUMBER(D5)),"待补",IF('1-参数'!B15="CIF",D5,D5+IF(ISNUMBER(D6),D6,0))) | E7: USD/吨 | F7: 到岸价
A8: 5 | B8: 汇率 | C8: USD/CNY | D8: =IF('1-参数'!B25="","待补",'1-参数'!B25) | E8: CNY/USD | F8: 当期汇率
A9: 6 | B9: 关税完税价格 | C9: CIF × 汇率 | D9: =IF(AND(ISNUMBER(D7),ISNUMBER(D8)),D7*D8,"待补") | E9: 元/吨 | F9: 海关计征基数
A10: 7 | B10: 关税 | C10: 完税价格 × 关税税率 | D10: =IF(AND(ISNUMBER(D9),ISNUMBER('1-参数'!B28)),D9*'1-参数'!B28/100,"待补") | E10: 元/吨
A11: 8 | B11: 进口环节增值税 | C11: （完税价格 + 关税）× 增值税率 | D11: =IF(AND(ISNUMBER(D9),ISNUMBER(D10),ISNUMBER('1-参数'!B29)),(D9+D10)*'1-参数'!B29/100,"待补") | E11: 元/吨 | F11: 可抵扣则为进项
A12: 9 | B12: 境内费用 | C12: 港杂/报关/仓储/短驳 | D12: =IF(OR('1-参数'!B33="",'1-参数'!B33="待补"),0,'1-参数'!B33)+IF('1-参数'!B34="",0,'1-参数'!B34) | E12: 元/吨 | F12: 缺则为 0 并登记缺口
A13: 10 | B13: 进口含税净成本 | C13: 完税价 + 关税 + 境内费用（+不可抵扣增值税） | D13: =IF(NOT(ISNUMBER(D11)),"待补",IF(NOT(ISNUMBER(D9)),"待补",D9+D10+D12+IF('1-参数'!B30="否",D11,0))) | E13: 元/吨 | F13: 与国内含税价相减
A14: 11 | B14: 进口全口径付现 | C14: 含可抵扣增值税的全部付款 | D14: =IF(NOT(ISNUMBER(D11)),"待补",D9+D10+D11+D12) | E14: 元/吨 | F14: 资金占用参考
A15: 12 | B15: 国内现货（含税） | C15: 同规格、同交货地 | D15: =IF('1-参数'!B37="","待补",'1-参数'!B37) | E15: 元/吨
A16: 13 | B16: 理论进口价差 | C16: 国内含税价 − 进口含税净成本 | D16: =IF(AND(ISNUMBER(D13),ISNUMBER(D15)),D15-D13,"待补") | E16: 元/吨 | F16: >0 国内更贵
A17: 14 | B17: 价差占国内价 | C17: 价差 ÷ 国内价 | D17: =IF(AND(ISNUMBER(D16),ISNUMBER(D15),D15>0),D16/D15,"待补") | E17: %
B19: 关键结论
B20: 理论进口价差（元/吨） | C20: =D16
B21: 口径状态 | C21: =IF(NOT(ISNUMBER(D16)),"不可计算：关键数据缺失",IF(D16>0,"理论上有进口空间（国内更贵）","理论上无进口空间（国内更便宜）"))
B22: 一句话提醒 | C22: 本数只是"到岸 vs 罐区自提"的价差，未含资金、罐容、损耗与对手方风险，不等于可执行贸易利润。

Sheet 3-可比性核对
A1: ③ 可比性核对：海外价与国内价是否真能相减
A3: # | B3: 检查项 | C3: 海外/进口口径 | D3: 国内口径 | E3: 是否可比 | F3: 处理方式
A4: 1 | B4: 规格牌号 | C4: 聚酯级（Polyester grade，含量 ≥99.9%，散水/散装） | D4: 聚酯级（Polyester grade，≥99.9%） | E4: 可比 | F4: 同规格
A5: 2 | B5: 价格日期 | C5: 2026-10-16 | D5: 2026-10-16 | E5: 可比 | F5: 必须同日或注明错配影响
A6: 3 | B6: 贸易术语 | C6: CFR 中国主港 | D6: 罐区自提（ex-tank） | E6: 需折算 | F6: CFR→含税净成本后再比
A7: 4 | B7: 计价币种 | C7: USD/吨 × 汇率 | D7: CNY/吨 | E7: 可比 | F7: 按当日汇率折算
A8: 5 | B8: 含税口径 | C8: 完税价+关税，VAT可抵扣 | D8: 含 13% 增值税 | E8: 可比 | F8: 两端均为"可抵扣VAT之外"口径
A9: 6 | B9: 数量/包装 | C9: 5,000 t/船批 | D9: 罐内零单/整车提货 | E9: 需注意 | F9: 散装船批 vs 罐区零单
A10: 7 | B10: 交货地点 | C10: CFR China Main Port（华东主港） | D10: 华东（江苏张家港/太仓罐区） | E10: 需注意 | F10: 口岸 vs 罐区，均不含内陆
A11: 8 | B11: 货物状态 | C11: 船货/远月船期 | D11: 罐内现货 | E11: 需注意 | F11: 时间价值不同
A12: 9 | B12: 报价性质 | C12: 指数评估价 | D12: 市场成交价 | E12: 需注意 | F12: 指数±5–15 USD 议价空间
B14: 结论 | C14: 存在"需折算/需注意"项 → 价差可算，但须标注为"带有保留项的口径"，不能与可执行利润混为一谈。

Sheet 4-历史价差
A1: ④ 历史进口价差（逐日取当期报价/汇率/国内价；缺任一项则留空，不插值）
A3: 日期 | B3: 海外报价 USD/吨 | C3: 贸易术语 | D3: 汇率 | E3: 国内含税价 | F3: CIF USD/吨 | G3: 完税价 | H3: 关税 | I3: 进口含税净成本 | J3: 理论价差 | K3: 价差% | L3: 状态 | M3: 说明
A4: 2026-10-09 | B4: 705 | C4: CFR | D4: 6.6921 | F4: =IF(OR(C4="CFR",C4="CIF"),B4,"待补") | G4: =IF(ISNUMBER(F4),F4*D4,"待补") | H4: =IF(ISNUMBER(G4),G4*IFERROR('1-参数'!B28/100,0),"待补") | I4: =IF(AND(ISNUMBER(G4),ISNUMBER(H4)),G4+H4,"待补") | J4: =IF(AND(ISNUMBER(I4),ISNUMBER(E4)),E4-I4,"待补") | K4: =IF(AND(ISNUMBER(J4),ISNUMBER(E4),E4>0),J4/E4,"待补") | L4: =IF(ISNUMBER(J4),"可配对","缺口")
A5: 2026-10-13 | B5: 670 | C5: CFR | D5: 6.6938 | E5: 5870.83 | F5: =IF(OR(C5="CFR",C5="CIF"),B5,"待补") | G5: =IF(ISNUMBER(F5),F5*D5,"待补") | H5: =IF(ISNUMBER(G5),G5*IFERROR('1-参数'!B28/100,0),"待补") | I5: =IF(AND(ISNUMBER(G5),ISNUMBER(H5)),G5+H5,"待补") | J5: =IF(AND(ISNUMBER(I5),ISNUMBER(E5)),E5-I5,"待补") | K5: =IF(AND(ISNUMBER(J5),ISNUMBER(E5),E5>0),J5/E5,"待补") | L5: =IF(ISNUMBER(J5),"可配对","缺口")
A6: 2026-10-14 | B6: 700 | C6: CFR | D6: 6.6927 | E6: 5942.83 | F6: =IF(OR(C6="CFR",C6="CIF"),B6,"待补") | G6: =IF(ISNUMBER(F6),F6*D6,"待补") | H6: =IF(ISNUMBER(G6),G6*IFERROR('1-参数'!B28/100,0),"待补") | I6: =IF(AND(ISNUMBER(G6),ISNUMBER(H6)),G6+H6,"待补") | J6: =IF(AND(ISNUMBER(I6),ISNUMBER(E6)),E6-I6,"待补") | K6: =IF(AND(ISNUMBER(J6),ISNUMBER(E6),E6>0),J6/E6,"待补") | L6: =IF(ISNUMBER(J6),"可配对","缺口")
A7: 2026-10-15 | B7: 685 | C7: CFR | D7: 6.691 | E7: 5898.33 | F7: =IF(OR(C7="CFR",C7="CIF"),B7,"待补") | G7: =IF(ISNUMBER(F7),F7*D7,"待补") | H7: =IF(ISNUMBER(G7),G7*IFERROR('1-参数'!B28/100,0),"待补") | I7: =IF(AND(ISNUMBER(G7),ISNUMBER(H7)),G7+H7,"待补") | J7: =IF(AND(ISNUMBER(I7),ISNUMBER(E7)),E7-I7,"待补") | K7: =IF(AND(ISNUMBER(J7),ISNUMBER(E7),E7>0),J7/E7,"待补") | L7: =IF(ISNUMBER(J7),"可配对","缺口")
A8: 2026-10-16 | B8: 685 | C8: CFR | D8: 6.6862 | E8: 5865.33 | F8: =IF(OR(C8="CFR",C8="CIF"),B8,"待补") | G8: =IF(ISNUMBER(F8),F8*D8,"待补") | H8: =IF(ISNUMBER(G8),G8*IFERROR('1-参数'!B28/100,0),"待补") | I8: =IF(AND(ISNUMBER(G8),ISNUMBER(H8)),G8+H8,"待补") | J8: =IF(AND(ISNUMBER(I8),ISNUMBER(E8)),E8-I8,"待补") | K8: =IF(AND(ISNUMBER(J8),ISNUMBER(E8),E8>0),J8/E8,"待补") | L8: =IF(ISNUMBER(J8),"可配对","缺口")
A9: 2026-10-08 | L9: 不生成 | M9: 海外价：10-08 有中国到岸价文章但本次未取得正文数值 → 该日不生成价差点。
A10: 2026-10-10 / 10-12 | L10: 不生成 | M10: 海外价：10-10 为国庆后周末、10-12 为周一，无 CFR 中国收盘披露（亚洲市场按工作日评估）→ 不生成价差点。
A11: 2026-10-13 / 10-14 | L11: 不生成 | M11: 国内价：10-13、10-14 国内价可得（5,870.83 / 5,942.83），但这两个交易日的价差档已计入；10-14 海外 700 与国内同日 5,942.83 已配对。
A12: 2026-10-17 / 10-18 | L12: 不生成 | M12: 双方：周末无报价 → 不生成价差点，也不做线性补点。
A13: 2026-10-19 / 10-20 | L13: 不生成 | M13: 海外价：10-19 国内价 5,735 可得，但当日 CFR 中国美元价未取得 → 不生成价差点（不能用 10-15 的 685 顶替 10-19）。
A14: 近 1 年 | L14: 不生成 | M14: 双方：1 年窗口内双方**可配对的连续历史序列**（同口径海外 CFR、同口径国内现货、同日汇率、当期税率、当期运费）本次均未取得 → 1 年曲线留空，原始数据接入后可直接回填，无需改结构。

Sheet 5-敏感性
A1: ⑤ 敏感性分析（公式驱动：改 B 列参数即重算三张表）
A3: 基准进口含税净成本 | C3: =IFERROR('2-进口成本折算'!D13,0)
A4: 基准理论价差 | C4: =IFERROR('2-进口成本折算'!D16,0)
A5: 基准汇率 | C5: =IFERROR('1-参数'!B25,"待补")
A6: 基准海外报价 | C6: =IFERROR('1-参数'!B14,"待补")
A7: 汇率每 +1 对成本的影响（≈ 完税价/汇率） | C7: =IFERROR(IF(AND(ISNUMBER(C3),ISNUMBER(C5)),('2-进口成本折算'!D9)/C5,"待补"),"待补")
A8: 报价每 +1 USD 对成本的影响（汇率×(1+关税)） | C8: =IFERROR(IF(AND(ISNUMBER(C5),ISNUMBER('1-参数'!B25)),C5*(1+'1-参数'!B28/100),"待补"),"待补")
A9: 注：C3/C4 若显示"计算未完成"，表示缺关键参数，此时敏感性表一律显示"待补"，不按 0 计算。
A10: A. 汇率变动对价差的影响
A11: 汇率变动 | B11: 情景汇率 | C11: 情景价差 | D11: 相对基准
A12: -0.03 | B12: =IFERROR($C$5*(1+-0.03),"待补") | C12: =IF(AND(ISNUMBER($C$3),ISNUMBER($C$4),ISNUMBER($C$5),ISNUMBER($C$7)),$C$4-(($C$3+($C$5*(1+(-0.03))-$C$5)*$C$7)-$C$3),"待补") | D12: =IF(ISNUMBER(C12),C12-$C$4,"待补")
A13: -0.015 | B13: =IFERROR($C$5*(1+-0.015),"待补") | C13: =IF(AND(ISNUMBER($C$3),ISNUMBER($C$4),ISNUMBER($C$5),ISNUMBER($C$7)),$C$4-(($C$3+($C$5*(1+(-0.015))-$C$5)*$C$7)-$C$3),"待补") | D13: =IF(ISNUMBER(C13),C13-$C$4,"待补")
A14: 0 | B14: =IFERROR($C$5*(1+0),"待补") | C14: =IF(AND(ISNUMBER($C$3),ISNUMBER($C$4),ISNUMBER($C$5),ISNUMBER($C$7)),$C$4-(($C$3+($C$5*(1+(0))-$C$5)*$C$7)-$C$3),"待补") | D14: =IF(ISNUMBER(C14),C14-$C$4,"待补")
A15: 0.015 | B15: =IFERROR($C$5*(1+0.015),"待补") | C15: =IF(AND(ISNUMBER($C$3),ISNUMBER($C$4),ISNUMBER($C$5),ISNUMBER($C$7)),$C$4-(($C$3+($C$5*(1+(0.015))-$C$5)*$C$7)-$C$3),"待补") | D15: =IF(ISNUMBER(C15),C15-$C$4,"待补")
A16: 0.03 | B16: =IFERROR($C$5*(1+0.03),"待补") | C16: =IF(AND(ISNUMBER($C$3),ISNUMBER($C$4),ISNUMBER($C$5),ISNUMBER($C$7)),$C$4-(($C$3+($C$5*(1+(0.03))-$C$5)*$C$7)-$C$3),"待补") | D16: =IF(ISNUMBER(C16),C16-$C$4,"待补")
A18: B. 海外报价变动对价差的影响
A19: 报价变动 | B19: 情景报价 | C19: 情景价差 | D19: 相对基准
A20: -0.03 | B20: =IFERROR($C$6*(1+-0.03),"待补") | C20: =IF(OR(NOT(ISNUMBER($C$3)),NOT(ISNUMBER($C$4)),NOT(ISNUMBER($C$6)),NOT(ISNUMBER($C$8))),"待补",$C$4-(($C$3+($C$6*(1+-0.03)-$C$6)*$C$8)-$C$3)) | D20: =IF(ISNUMBER(C20),C20-$C$4,"待补")
A21: -0.015 | B21: =IFERROR($C$6*(1+-0.015),"待补") | C21: =IF(OR(NOT(ISNUMBER($C$3)),NOT(ISNUMBER($C$4)),NOT(ISNUMBER($C$6)),NOT(ISNUMBER($C$8))),"待补",$C$4-(($C$3+($C$6*(1+-0.015)-$C$6)*$C$8)-$C$3)) | D21: =IF(ISNUMBER(C21),C21-$C$4,"待补")
A22: 0 | B22: =IFERROR($C$6*(1+0),"待补") | C22: =IF(OR(NOT(ISNUMBER($C$3)),NOT(ISNUMBER($C$4)),NOT(ISNUMBER($C$6)),NOT(ISNUMBER($C$8))),"待补",$C$4-(($C$3+($C$6*(1+0)-$C$6)*$C$8)-$C$3)) | D22: =IF(ISNUMBER(C22),C22-$C$4,"待补")
A23: 0.015 | B23: =IFERROR($C$6*(1+0.015),"待补") | C23: =IF(OR(NOT(ISNUMBER($C$3)),NOT(ISNUMBER($C$4)),NOT(ISNUMBER($C$6)),NOT(ISNUMBER($C$8))),"待补",$C$4-(($C$3+($C$6*(1+0.015)-$C$6)*$C$8)-$C$3)) | D23: =IF(ISNUMBER(C23),C23-$C$4,"待补")
A24: 0.03 | B24: =IFERROR($C$6*(1+0.03),"待补") | C24: =IF(OR(NOT(ISNUMBER($C$3)),NOT(ISNUMBER($C$4)),NOT(ISNUMBER($C$6)),NOT(ISNUMBER($C$8))),"待补",$C$4-(($C$3+($C$6*(1+0.03)-$C$6)*$C$8)-$C$3)) | D24: =IF(ISNUMBER(C24),C24-$C$4,"待补")
A26: C. 国际运费变动
A27: 说明 | B27: 运费每变动 1 USD/吨，进口含税净成本变动 = 汇率 ×(1+关税) ≈ （见「1-参数」汇率×(1+关税))，即用 2-进口成本折算 的公式逐点重算。当前运费缺失时本项无法计算，请先在「1-参数」补入运费。

Sheet 6-理论vs真实
A1: ⑥ 理论价差 ≠ 可执行利润：差距在哪里
A3: 项目 | B3: 金额(元/吨) | C3: 是否已计入 | D3: 性质与备注
A4: 理论进口价差 | B4: ='2-进口成本折算'!D16 | C4: 是 | D4: 国内含税现货 − 进口含税净成本
A5: 国际运费（FOB 时） | B5: =IF('1-参数'!B20="","待补",-'1-参数'!B20*'1-参数'!B25) | C5: 见口径 | D5: CFR 已含则不计
A6: 境内费用 | B6: ='2-进口成本折算'!D12 | C6: 是 | D6: 港杂/报关/仓储/短驳
A7: 可抵扣进口增值税 | B7: ='2-进口成本折算'!D11 | C7: 否 | D7: 现金流占用，非成本
A8: 资金成本（90天） | B8: 待补 | C8: 否 | D8: 授信/信用证/锁汇成本
A9: 计量与质量损耗 | B9: 待补 | C9: 否 | D9: 卸货损耗、纯度偏差索赔
A10: 罐容与滞期 | B10: 待补 | C10: 否 | D10: 到港集中时的接卸约束
A11: 对手方与结算风险 | B11: 待补 | C11: 否 | D11: 预付比例、单据、合规审查
A13: 提醒 | B13: 理论价差只回答"同一时点、同一口径下便宜/贵多少"；能不能做还取决于上表待补项。本表不提供交易建议，也不预测价格。

Sheet 7-来源清单
A1: ⑦ 来源清单（A=官方；B=专业资讯/研报；C=转述/参照）
A3: 等级 | B3: 编号 | C3: 发布方 | D3: 标题 | E3: 日期 | F3: URL | G3: 原文摘录
A4: A | B4: S-CFETS | C4: 中国外汇交易中心 CFETS | D4: 人民币汇率中间价（USD/CNY） | E4: 2026-10-20 | F4: https://www.chinamoney.com.cn/chinese/bkccpr/ | G4: 2026-10-20 USD/CNY 中间价 6.72000，每交易日 9:15 公布
A5: A | B5: S-MEGLOBAL-ACP | C5: MEGlobal（EQUATE 集团） | D5: MEGlobal announces ACP for November 2026 | E5: 2026-10-15 | F5: https://www.meglobal.biz/news-and-media/ | G5: ACP for MEG will be US$880/MT CFR Asian main ports for arrival November 2026（10 月 ACP 同为 880，9 月 780，8 月 770）
A6: A | B6: S-MOF-TARIFF2026 | C6: 国务院关税税则委员会（财政部） | D6: 2026 年关税调整方案 · 附件1 进口商品暂定税率表 | E6: 2025-12-26 | F6: https://gss.mof.gov.cn/gzdt/zhengcefabu/202512/P020251229510521217364.pdf | G6: 第 233–240 行：29011010 乙烷 2/1、29031500 1,2-二氯乙烷 5.5/1、29053990 1,3-丙二醇 5.5/3、29054500 丙三醇 8/3……29053100 未列入暂定税率表
A7: A | B7: S-SSE-SCFI | C7: 上海航运交易所 | D7: 上海出口集装箱运价指数（SCFI） | E7: 2026-10-16 | F7: https://www.sse.net.cn/index/singleIndex?indexType=scfi | G7: 综合指数 上期(10-09) 3664.11 → 本期(10-16) 3679.58（+15.47）；波斯湾 20ft（迪拜）权重 5.0%
A8: B | B8: S-CPH-1015 | C8: ChemPriceHub | D8: Lack of bullish confidence leads to a sluggish market rebound | E8: 2026-10-15 | F8: https://www.chempricehub.com/news/detail-lack-of-bullish-confidence-leads-to-a-sluggish-market-rebound-aiu8ty1q.html | G8: Table 1: Asia / CFR China / Oct 14 = 700 / Oct 15 = 685 (−15, −2.1%)；East China Ex-works 5685；Zhangjiagang closing 5,685 CNY/ton；Jiangsu basis Nov+482；华东主港库存 11.5 万吨
A9: B | B9: S-CPH-EGFIX | C9: ChemPriceHub | D9: Morning Market Update: Monoethylene Glycol (MEG) | E9: 2026-10-16 | F9: https://www.chempricehub.com/news/detail-morning-market-update-monoethylene-glycol-meg-8rp9uqzx.html | G9: Price table: MEG USD 700→685 (USD/ton)；MEG RMB 5722→5685 (CNY/ton)；capacity util 63.50%
A10: B | B10: S-ECB-REF | C10: Frankfurter API（基于 ECB） | D10: USD/CNY reference rates（European Central Bank reference rates） | E10: 2026-10-19 | F10: https://api.frankfurter.dev/v1/2026-10-01..2026-10-20?base=USD&symbols=CNY | G10: 2026-10-01 6.7045；10-08 6.7023；10-09 6.6921；10-12 6.6928；10-13 6.6938；10-14 6.6927；10-15 6.6910；10-16 6.6862；10-19 6.6807
A11: B | B11: S-GJ-1017 | C11: 国金证券 | D11: 石油化工行业周报（20261017） | E11: 2026-10-17 | F11: https://pdf.dfcfw.com/pdf/H3_AP202610181830661080_1.pdf | G11: 乙二醇市场价格跌后回弹；行业开工率约 63.16%、乙烯制 62.64%；天津渤化 30 万吨、联泓格润 17 万吨 10-10 停车；美金市场船货资源有限、价格坚挺
A12: B | B12: S-HTFC-JUL | C12: 华泰期货研究院 | D12: 乙二醇低库存下还要去库多久（聚酯产业链专题） | E12: 2026-07-30 | F12: https://htfc.com/wz_upload/png_upload/20260803/17857445397862ad7b7.pdf | G12: 2025 年自沙特、科威特、阿曼、伊朗、阿联酋进口占比 66.3%（约 512 万吨），沙特占 55%；霍尔木兹周边 EG 产能占海外 27%；中东负荷降至 20% 以下；延布、拉比格装置在运行
A13: B | B13: S-MY-1009 | C13: 隆众资讯（我的钢铁网转载） | D13: [乙二醇]：亚洲乙二醇市场周度综述（20261005-1009） | E13: 2026-10-12 | F13: https://nenghua.m.mysteel.com/a/26101214/5569B90ECA7A6D66_abc.html | G13: 10月9日中国到岸价MEG为705美元/吨，较10月5日下跌45美元/吨，较10月8日下跌70美元/吨。中国国内评估价环比下跌590元/吨，至5,680元/吨（出厂价）。
A14: B | B14: S-MY-ZJG-1019 | C14: 隆众资讯（我的钢铁网转载） | D14: [乙二醇]：10月19日（14:00）张家港市场乙二醇价格行情 | E14: 2026-10-19 | F14: https://nenghua.mysteel.com/a/26101913/162A9873F33DEBAA.html | G14: 午后张家港乙二醇现货下跌，买盘 5394，卖盘 5404，现货基差 11+360 至 11+370；下周买盘 5344、卖盘 5364（元/吨）
... A20: C | B20: S-MARITIMENEWS-VLCC | C20: Maritime News（引 Baltic Exchange） | D20: Tanker Rates Ease After Record Highs | E20: 2026-10-18 | F20: https://maritimenews.com/tanker/tanker-rates-ease-middle-east-disruptions | G20: Gulf of Oman to China VLCC rates fell to about Worldscale 776 from 841 the previous week

Sheet 8-缺口登记
A1: ⑧ 数据缺口登记（缺什么 / 影响什么 / 怎么补）
A3: 优先级 | B3: 缺口项 | C3: 对结论的影响 | D3: 补数方法 | E3: 影响模块 | F3: 状态
A4: 高 | B4: 中东→华东化学品船 / 散装液货船实盘运费（美元/吨） | C4: CFR 与 CIF 口径的进口成本中，运费是最大的单一费用项（典型 40–90 美元/吨，约合 270–600 元/吨）。缺它，任何「FOB 报价「都无法折算到岸。 | D4: 向 2–3 家货代/船东询同航线 5,000–10,000 吨批次的实盘报价，记录询价日、航线、船型、批量和附加费。 | E4: 完全折算、FOB 报价 | F4: 待补
A5: 高 | B5: 乙二醇（29053100）2026 年最惠国关税税率权威原值与适用税号 | C5: 关税在 5.0% 与 5.5% 两种口径下，1,000 元量级的价差会移动约 30–40 元/吨；若可享协定税率，影响更大。 | D5: 以报关行/海关税则查询平台按「报关日税则、实际税号、原产地「确认；如可享中国—沙特等协定税率，补充原产地证书要求。 | E5: 关税、含税净成本 | F5: 待补
A6: 高 | B6: 国内现货「张家港罐区自提「的当期日价格序列（非全国均价） | C6: 现用隆众「全国主流市场均价「作比较基准，与华东张家港实际成交存在 100–200 元/吨的口径差。 | D6: 接入隆众/卓创「华东张家港「单点价格序列，或直接取企业实际采购成交价（含票、含税）。 | E6: 国内现价、价差 | F6: 待补
A7: 中 | B7: 2026-10-17 以来（含 10-20 当日）的 CFR 中国美元价与张家港成交价 | C7: 基准日只能退到 10-16；若近期价格快速变化，当前窗口判断可能偏离。 | D7: 使用资讯平台会员账号获取日更正文，或将本报告基准日滚动手工更新。 | E7: 当前窗口 | F7: 待补
A8: 中 | B8: 1 年窗口的同口径连续历史序列（海外 CFR 日/周、国内华东现货日、当日汇率、当期关税与运价） | C8: 当前只有 5 个海外价锚点、7 个国内价锚点，能配对的仅 4 个交易日；无法画出 30 天以上、更无法画 1 年价差曲线。 | D8: 导出资讯商历史数据（隆众/CCF/ICIS 或 iFinD 终端）+ CFETS 历史中间价 + 税率版本表；按 schema 的 fx / quotes_hist / domestic_hist 三条序列灌入即可自动出曲线。 | E8: 历史价差、趋势分析 | F8: 待补
A9: 中 | B9: 港杂费、报关代理、仓储、短驳等境内费用实票 | C9: 境内费用通常 50–120 元/吨，直接等额削减理论价差。 | D9: 取上一票进口的港杂/报关/仓储实付凭证，按吨折。 | E9: 境内费用、价差 | F9: 待补
A10: 中 | B10: 保险费率与投保方式 | C10: CIF×110% 投保、费率 0.1%–0.3%，折合 5–15 元/吨。 | D10: 取现有保单费率；若走供应商 CIF 免自投，则无需此项。 | E10: 到岸价 | F10: 待补
A11: 低 | B11: 开证保证金、授信占用、外汇锁汇成本 | C11: 6,000 元/吨货值、90 天账期的资金成本约 30–60 元/吨，属「理论价差「与「真实利润「之间的主要差距之一。 | D11: 取财务授信成本率与付款条件（T/T 预付比例、L/C 期限）。 | E11: 真实利润 | F11: 待补
A12: 低 | B12: 中国—沙特等自贸协定项下乙二醇的协定税率适用性 | C12: 如可享零/低关税，进口成本整体下移 5% 完税价。 | D12: 查询自贸协定税率表 + 向供应商确认能否出具原产地证书。 | E12: 关税 | F12: 待补

Sheet 9-引擎校验
A1: ⑨ 独立引擎校验：Excel 公式 vs 计算引擎（两者不一致即为计算错误）
A3: 项目 | B3: Excel 公式值 | C3: 引擎计算值 | D3: 差值 | E3: 判定
A4: 关税完税价格 | B4: ='2-进口成本折算'!D9 | C4: 4580.047 | D4: =IF(AND(ISNUMBER(B4),ISNUMBER(C4)),B4-C4,"缺") | E4: =IF(NOT(AND(ISNUMBER(B4),ISNUMBER(C4))),IF(AND(ISERR(B4),C4=""),"无须计算",IF(AND(NOT(ISNUMBER(B4)),NOT(ISNUMBER(C4))),"两侧均无值","待核对")),IF(ABS(D4)<0.02,"一致","复核"))
A5: 关税 | B5: ='2-进口成本折算'!D10 | C5: 251.9026 | D5: =IF(AND(ISNUMBER(B5),ISNUMBER(C5)),B5-C5,"缺") | E5: =IF(NOT(AND(ISNUMBER(B5),ISNUMBER(C5))),IF(AND(ISERR(B5),C5=""),"无须计算",IF(AND(NOT(ISNUMBER(B5)),NOT(ISNUMBER(C5))),"两侧均无值","待核对")),IF(ABS(D5)<0.02,"一致","复核"))
A6: 进口增值税 | B6: ='2-进口成本折算'!D11 | C6: 628.1534 | D6: =IF(AND(ISNUMBER(B6),ISNUMBER(C6)),B6-C6,"缺") | E6: =IF(NOT(AND(ISNUMBER(B6),ISNUMBER(C6))),IF(AND(ISERR(B6),C6=""),"无须计算",IF(AND(NOT(ISNUMBER(B6)),NOT(ISNUMBER(C6))),"两侧均无值","待核对")),IF(ABS(D6)<0.02,"一致","复核"))
A7: 进口含税净成本 | B7: ='2-进口成本折算'!D13 | C7: 4831.9496 | D7: =IF(AND(ISNUMBER(B7),ISNUMBER(C7)),B7-C7,"缺") | E7: =IF(NOT(AND(ISNUMBER(B7),ISNUMBER(C7))),IF(AND(ISERR(B7),C7=""),"无须计算",IF(AND(NOT(ISNUMBER(B7)),NOT(ISNUMBER(C7))),"两侧均无值","待核对")),IF(ABS(D7)<0.02,"一致","复核"))
A8: 理论价差 | B8: ='2-进口成本折算'!D16 | C8: 1033.3804 | D8: =IF(AND(ISNUMBER(B8),ISNUMBER(C8)),B8-C8,"缺") | E8: =IF(NOT(AND(ISNUMBER(B8),ISNUMBER(C8))),IF(AND(ISERR(B8),C8=""),"无须计算",IF(AND(NOT(ISNUMBER(B8)),NOT(ISNUMBER(C8))),"两侧均无值","待核对")),IF(ABS(D8)<0.02,"一致","复核"))
A10: 说明 | B10: 引擎值为外部程序（Node/Python 同一算法）独立算得的结果。若"判定"出现"复核"，说明 Excel 公式口径与引擎不一致，请检查 2-进口成本折算 的公式引用。
