Workbook

Sheet 0-说明
A1: 重质纯碱（Na₂CO₃，工业级） · 区域采购成本模型
A2: 口径：含税人民币元/吨｜浅黄底=需你填写，灰蓝底=公式自动算｜留空一律表示「未知」，不是 0
B4: 产品 / 规格 | C4: 重质纯碱（Na₂CO₃，工业级）｜
B5: 收货地 | C5: 江苏省苏州市（收货地按苏州市区处理；若为下辖县级市如张家港/昆山/太仓，里程需相应增加）
B6: 采购数量（吨） | C6: 100
B7: 价格口径 | C7: 含 13% 增值税，元/吨（净重）
B8: 基准区域 | C8: 山东
B9: 生成时间 | C9: 2026-10-19
B11: 工作表导航
B12: 1-参数 | C12: 采购数量、税率、装卸费单价。改这里，全表联动。
B13: 2-价格口径 | C13: 各区域现货价、区间、交货方式、数据日、来源；含税与不含税并列。
B14: 3-到厂成本 | C14: 逐区域填运费，自动算到厂单价与整单总额；运费留空显示「待补」。
B15: 4-因素分解 | C15: 相对基准区域，把到厂差拆成 裸价差+运输差+装卸差，并校验是否闭合。
B16: 5-线路与距离 | C16: 每条线路的起点/终点/可核验里程/高速方案/替代运输方式。
B17: 6-历史价差 | C17: 同日同规格的分区价差序列与极差。
B18: 7-缺口与假设 | C18: 缺哪些参数、为什么缺、补上会怎样。
B19: 8-来源 | C19: 每个价格对应的原始出处与采集日。
B21: 三条硬规矩
C22: · 同一区域若只有单一来源且未注明交货口径，不得进入基准列表
C23: · 价格日期与基准日不一致且无中间价格说明，不得做价差
C24: · 运费、装卸费、检测费缺失时，到厂成本不得给出具体数字或排序
C25: · 不得使用行业均值、经验值填补运价

Sheet 1-参数
A1: 采购参数（改这里，全表联动）
A2: 浅黄底为输入项。装卸费留空 = 未知，下游显示「待补」而不是 0。
A4: 参数 | B4: 取值 | C4: 单位 | D4: 说明
A5: 采购数量 | B5: 100 | C5: 吨 | D5: 100 吨约 3.2 车（13m 半挂按 31 吨/车）
A6: 运费税率 | B6: 9 | C6: % | D6: 公路运输增值税 9%，一般纳税人可抵扣
A7: 装车费 | C7: 元/吨 | D7: 留空=未知；填 0 表示「已包含在车板价内」
A8: 卸车费 | C8: 元/吨 | D8: 留空=未知
A9: 检测/取样费 | C9: 元/吨 | D9: 留空=未知
A10: 货物增值税率 | B10: 13 | C10: % | D10: 纯碱适用 13%
A13: 提示 | B13: 这里的装卸费是全线路统一值。若某条线路的装卸口径不同（例如自提货由卖方装车、送到货由买方卸车），请在「3-到厂成本」对应行的「装车元/吨、卸车元/吨」列单独填写覆盖。

Sheet 2-价格口径
A1: 各地区现货价格（统一口径后）
A2: 同规格、同单位、同税费口径、同数据日。交货方式（送到/自提/出厂）不同，是不能直接比大小的关键原因。
A4: 区域 | B4: 市场归属 | C4: 规格 | D4: 交货方式 | E4: 价格下限 | F4: 价格上限 | G4: 取用值(含税) | H4: 不含税(元/吨) | I4: 数据日 | J4: 来源 | K4: 备注
A5: 山东 | B5: 华北 | C5: 工业级 Na₂CO₃ ≥98% | D5: 送到 | E5: 1100 | F5: 1200 | G5: =ROUND(AVERAGE(E5:F5),0) | H5: =IF(G5="","",ROUND(G5/(1+'1-参数'!$B$10/100),2)) | I5: 2026-10-16 | J5: 化盟网《纯碱日评》分区价格表（2026-10-16） | K5: 区间宽，建议上下限各算一遍
A6: 河北 | B6: 华北（沙河） | C6: 工业级 Na₂CO₃ ≥98% | D6: 自提 | E6: 940 | F6: 950 | G6: =ROUND(AVERAGE(E6:F6),0) | H6: =IF(G6="","",ROUND(G6/(1+'1-参数'!$B$10/100),2)) | I6: 2026-10-16 | J6: 化盟网《纯碱日评》分区价格表（2026-10-16） | K6: ⚠ 自提价：买方自担提货运输
A7: 河南 | B7: 华中 | C7: 工业级 Na₂CO₃ ≥98% | D7: 送到 | E7: 1050 | F7: 1150 | G7: =ROUND(AVERAGE(E7:F7),0) | H7: =IF(G7="","",ROUND(G7/(1+'1-参数'!$B$10/100),2)) | I7: 2026-10-16 | J7: 化盟网《纯碱日评》分区价格表（2026-10-16） | K7: 区间宽，建议上下限各算一遍
A8: 江苏本地 | B8: 华东 | C8: 工业级 Na₂CO₃ ≥98% | D8: 送到 | E8: 1100 | F8: 1200 | G8: =ROUND(AVERAGE(E8:F8),0) | H8: =IF(G8="","",ROUND(G8/(1+'1-参数'!$B$10/100),2)) | I8: 2026-10-16 | J8: 化盟网《纯碱日评》分区价格表（2026-10-16） | K8: 区间宽，建议上下限各算一遍

Sheet 3-到厂成本
A1: 到厂成本计算（填运费 → 自动出到厂价）
A2: 运费三种填法按优先级：总运费 > 包干运价(元/吨)。都空则该行「待补」，不参与排名。
A4: 区域 | B4: 裸价 (元/吨) | C4: 里程 (km) | D4: 包干运价 (元/吨) | E4: 总运费 (元) | F4: 运费 (元/吨) | G4: 装车 (元/吨) | H4: 卸车 (元/吨) | I4: 到厂单价 (元/吨) | J4: 整单总额 (元) | K4: 状态
A5: 山东 | B5: ='2-价格口径'!G5 | C5: 760 | F5: =IF(E5<>"",ROUND(E5/'1-参数'!$B$5,2),IF(D5<>"",D5,"")) | I5: =IF(OR(B5="",F5=""),"",ROUND(B5+F5+IF(G5<>"",G5,'1-参数'!$B$7)+IF(H5<>"",H5,'1-参数'!$B$8),2)) | J5: =IF(I5="","",ROUND(I5*'1-参数'!$B$5,0)) | K5: =IF(I5="","待补：缺运费","可算")
A6: 河北 | B6: ='2-价格口径'!G6 | C6: 999 | F6: =IF(E6<>"",ROUND(E6/'1-参数'!$B$5,2),IF(D6<>"",D6,"")) | I6: =IF(OR(B6="",F6=""),"",ROUND(B6+F6+IF(G6<>"",G6,'1-参数'!$B$7)+IF(H6<>"",H6,'1-参数'!$B$8),2)) | J6: =IF(I6="","",ROUND(I6*'1-参数'!$B$5,0)) | K6: =IF(I6="","待补：缺运费","可算")
A7: 河南 | B7: ='2-价格口径'!G7 | C7: 665 | F7: =IF(E7<>"",ROUND(E7/'1-参数'!$B$5,2),IF(D7<>"",D7,"")) | I7: =IF(OR(B7="",F7=""),"",ROUND(B7+F7+IF(G7<>"",G7,'1-参数'!$B$7)+IF(H7<>"",H7,'1-参数'!$B$8),2)) | J7: =IF(I7="","",ROUND(I7*'1-参数'!$B$5,0)) | K7: =IF(I7="","待补：缺运费","可算")
A8: 江苏本地 | B8: ='2-价格口径'!G8 | C8: 336 | F8: =IF(E8<>"",ROUND(E8/'1-参数'!$B$5,2),IF(D8<>"",D8,"")) | I8: =IF(OR(B8="",F8=""),"",ROUND(B8+F8+IF(G8<>"",G8,'1-参数'!$B$7)+IF(H8<>"",H8,'1-参数'!$B$8),2)) | J8: =IF(I8="","",ROUND(I8*'1-参数'!$B$5,0)) | K8: =IF(I8="","待补：缺运费","可算")
A9: 汇总 | B9: 裸价最低： | C9: =IF(COUNT(B5:B8)=0,"—",INDEX(A5:A8,MATCH(MIN(B5:B8),B5:B8,0))) | E9: 到厂最低： | F9: =IF(COUNT(I5:I8)<4,"不排名（有缺项）",INDEX(A5:A8,MATCH(MIN(I5:I8),I5:I8,0))) | I9: =IF(COUNT(I5:I8)<4,"待补",ROUND(MIN(I5:I8),0)) | J9: =IF(COUNT(J5:J8)<4,"待补",ROUND(SUM(J5:J8),0)) | K9: =IF(COUNT(I5:I8)<4,"✗ 不完整","✓ 齐全")
A11: 填法说明： 1) 只填「包干运价(元/吨)」→ 运费/吨 = 该价；整单总额 = (裸价+运费+装卸) × 数量； 2) 只填「总运费(元)」→ 运费/吨 = 总运费 ÷ 数量（整单议价时用这个）； 3) 两者都填 → 以总运费为准（整单结算更接近实际）； 4) 全空 → 该行到厂单价为空，汇总显示「不排名」。 5) 「装车/卸车」本行为空时，自动取「1-参数」中的统一值；本行填了就用本行的。

Sheet 4-因素分解
A1: 到厂成本差异的因素分解
A2: 以基准区域为 0，把到厂差拆成「市场裸价差 + 运输费用差 + 装卸差」。三项合计必须等于 Δ到厂。
A4: 区域 | B4: 裸价 (元/吨) | C4: 运费/吨 | D4: 装卸/吨 | E4: 到厂单价 | F4: Δ裸价 | G4: Δ运费 | H4: Δ装卸 | I4: 三项合计 | J4: Δ到厂 | K4: 校验
A5: 山东（基准） | B5: ='3-到厂成本'!B5 | C5: =IF('3-到厂成本'!F5="","",'3-到厂成本'!F5) | D5: =ROUND(N('3-到厂成本'!G5)+N('3-到厂成本'!H5),2) | E5: =IF('3-到厂成本'!I5="","",'3-到厂成本'!I5) | F5: =IF(OR(B5="",B5=""),"",B5-B5) | G5: =IF(OR(C5="",C5=""),"",C5-C5) | H5: =D5-D5 | I5: =IF(OR(F5="",G5=""),"待补",ROUND(F5+G5+H5,2)) | J5: =IF(OR(E5="",E5=""),"待补",ROUND(E5-E5,2)) | K5: =IF(OR(I5="待补",J5="待补"),"缺运费",IF(ABS(I5-J5)<0.01,"✓ 闭合","✗ 差 "&TEXT(I5-J5,"0.00")))
A6: 河北 | B6: ='3-到厂成本'!B6 | C6: =IF('3-到厂成本'!F6="","",'3-到厂成本'!F6) | D6: =ROUND(N('3-到厂成本'!G6)+N('3-到厂成本'!H6),2) | E6: =IF('3-到厂成本'!I6="","",'3-到厂成本'!I6) | F6: =IF(OR(B6="",B5=""),"",B6-B5) | G6: =IF(OR(C6="",C5=""),"",C6-C5) | H6: =D6-D5 | I6: =IF(OR(F6="",G6=""),"待补",ROUND(F6+G6+H6,2)) | J6: =IF(OR(E6="",E5=""),"待补",ROUND(E6-E5,2)) | K6: =IF(OR(I6="待补",J6="待补"),"缺运费",IF(ABS(I6-J6)<0.01,"✓ 闭合","✗ 差 "&TEXT(I6-J6,"0.00")))
A7: 河南 | B7: ='3-到厂成本'!B7 | C7: =IF('3-到厂成本'!F7="","",'3-到厂成本'!F7) | D7: =ROUND(N('3-到厂成本'!G7)+N('3-到厂成本'!H7),2) | E7: =IF('3-到厂成本'!I7="","",'3-到厂成本'!I7) | F7: =IF(OR(B7="",B5=""),"",B7-B5) | G7: =IF(OR(C7="",C5=""),"",C7-C5) | H7: =D7-D5 | I7: =IF(OR(F7="",G7=""),"待补",ROUND(F7+G7+H7,2)) | J7: =IF(OR(E7="",E5=""),"待补",ROUND(E7-E5,2)) | K7: =IF(OR(I7="待补",J7="待补"),"缺运费",IF(ABS(I7-J7)<0.01,"✓ 闭合","✗ 差 "&TEXT(I7-J7,"0.00")))
A8: 江苏本地 | B8: ='3-到厂成本'!B8 | C8: =IF('3-到厂成本'!F8="","",'3-到厂成本'!F8) | D8: =ROUND(N('3-到厂成本'!G8)+N('3-到厂成本'!H8),2) | E8: =IF('3-到厂成本'!I8="","",'3-到厂成本'!I8) | F8: =IF(OR(B8="",B5=""),"",B8-B5) | G8: =IF(OR(C8="",C5=""),"",C8-C5) | H8: =D8-D5 | I8: =IF(OR(F8="",G8=""),"待补",ROUND(F8+G8+H8,2)) | J8: =IF(OR(E8="",E5=""),"待补",ROUND(E8-E5,2)) | K8: =IF(OR(I8="待补",J8="待补"),"缺运费",IF(ABS(I8-J8)<0.01,"✓ 闭合","✗ 差 "&TEXT(I8-J8,"0.00")))
A10: 读法： · Δ裸价 < 0 表示该区域裸价更便宜；Δ运费 > 0 表示到该区域的运费更贵； · 「三项合计」= 「Δ到厂」 说明差异被三项解释完（校验列显示「✓ 闭合」）； · 显示「缺运费」= 该区域还没填运价，此时只能比裸价差，不能得出到厂结论； · 不要用「里程 × 某个拍脑袋的吨公里价」来填空——那不是承运方报价。

Sheet 5-线路与距离
A1: 运输线路与可核验里程
A2: 里程来自可在线复核的公路路线（高速主推方案）。拿到承运方 GPS 实跑里程后，直接改「里程(km)」。
A4: 区域 | B4: 起点（低端/高端） | C4: 终点 | D4: 里程(km) | E4: 里程依据 | F4: 高速方案 | G4: 可替代运输方式 | H4: 时效(h)
A5: 山东 | B5: 潍坊（760 km） 济宁（707 km） | C5: 苏州 | D5: 760 | E5: 待核验 | F5: G20 青银→G15 沈海→G25 长深→G2 京沪→沪陕 | G5: 内河/海运联运：潍坊港/莱州港装船 → 长江口/苏州港，适合 1000 吨以上；需另询船代运价 铁路：潍坊/淄博 → 苏州西，30 车起（约 1800 吨），需另询国铁 95306 运价 | H5: 8.1
A6: 河北 | B6: 邢台（999 km） 唐山（1126 km） | C6: 苏州 | D6: 999 | E6: 待核验 | F6: G4 京港澳→G22→G3→G2 | G6: 海铁联运：京唐港/天津港 → 连云港/太仓港，再短驳；适合 1000 吨以上 | H6: 10.7
A7: 河南 | B7: 商丘（665 km） 南阳（881 km） | C7: 苏州 | D7: 665 | E7: 待核验 | F7: G30 连霍→G3 京台→G2 | G7: 铁路：平顶山东/桐柏 → 苏州西，需批量与配车日 | H7: 7.1
A8: 江苏本地 | B8: 淮安（336 km） 连云港（436 km） | C8: 苏州 | D8: 336 | E8: 待核验 | F8: G2 京沪 | G8: 内河驳船：连云港 → 灌河/盐河 → 京杭运河 → 苏州 | H8: 3.8
A10: 为什么一个省要用两个起点：单个城市代表不了一个省。山东东端（潍坊）到苏州 760 km，西端（济宁）707 km；河北真正的省内产能集中在唐山（1126 km），比沙河市场所在地多 127 km。所以到厂成本应给「低端—高端」区间，而不是一个点。

Sheet 6-历史价差
A1: 历史区域价差
A2: 只统计「同一天、同规格、同交货口径」都有报价的日期；缺的那天不插值、不拼凑。
A4: 日期 | B4: 山东 (元/吨) | C4: 河北 (元/吨) | D4: 河南 (元/吨) | E4: 江苏本地 (元/吨) | F4: 区域极差
A5: 2026-10-16 | B5: 1100–1200 | C5: 940–950 | D5: 1050–1150 | E5: 1100–1200 | F5: =IFERROR(MAX(B5:E5)-MIN(B5:E5),"")
A6: 2026-10-14 | B6: 1100–1200 | C6: 940–950 | D6: 1050–1150 | E6: 1100–1200 | F6: =IFERROR(MAX(B6:E6)-MIN(B6:E6),"")
A7: 2026-09-29 | B7: 1100–1200 | C7: — | D7: 1050–1150 | E7: 1100–1200 | F7: =IFERROR(MAX(B7:E7)-MIN(B7:E7),"")
A8: 2026-09-24 | B8: 1100–1200 | C8: 970–980 | D8: 1050–1150 | E8: 1100–1200 | F8: =IFERROR(MAX(B8:E8)-MIN(B8:E8),"")
A9: 2026-09-18 | B9: 1120–1220 | C9: — | D9: 1090–1180 | E9: 1130–1230 | F9: =IFERROR(MAX(B9:E9)-MIN(B9:E9),"")
A10: 2026-09-11 | B10: 1120–1220 | C10: — | D10: 1090–1180 | E10: 1130–1230 | F10: =IFERROR(MAX(B10:E10)-MIN(B10:E10),"")
A11: 2026-07-29 | B11: 1250–1320 | C11: — | D11: — | E11: 1210–1280 | F11: =IFERROR(MAX(B11:E11)-MIN(B11:E11),"")
A13: 说明：「区域极差」是对该日各区报价中值两两比较的最大差，反映当日区域分化程度。这些日期不是每个区域都有同日报价，缺的日期不插值，因此统计只覆盖可比日。

Sheet 7-缺口与假设
A1: 数据缺口与关键假设
A2: 缺失项不会被估算填充，只会被标出来。补齐之后才能做排名。
A4: 级别 | B4: 缺口 | C4: 缺什么 | D4: 为什么缺 | E4: 怎么补 | F4: 影响
A5: 阻断 | B5: 全部线路运费（元/吨） | C5: 山东/河北/河南/江苏→苏州 的公路整车运价 | D5: 没有任何 30 吨左右袋装普货的公路运价可以直接引用：运价随油价、回程车、淡旺季波动，且属于承运方报价，不公开。 | E5: 向 2 家以上承运方询价（注明车型、起终点、是否回程、装货等待、税费），把每吨运价填进表格即可解锁到厂成本。 | F5: 到厂成本与排名无法计算，但价格差、距离与因素方向可以给出
A6: 阻断 | B6: 装车费、卸车费 | C6: 袋装纯碱的装车、卸车（含卸货到指定库位）单价 | D6: 通常由发货厂/收货方/承运方分别承担，不同厂家差异大，且多数厂家含在车板价里。 | E6: 确认‘是否含装卸’：含则填 0 并注明，不含则按实际报价填入。 | F6: 影响约 5~30 元/吨量级，对接近的排名可能造成翻转
A7: 提示 | B7: 袋装/散装与堆密度细分规格 | C7: 25kg 袋与吨包的价差、袋装与散装价差 | D7: 分区报价表未按包装细分，袋装通常较散装溢价。 | E7: 询价时注明包装并取得同规格报价 | F7: 约 10~40 元/吨
A8: 提示 | B8: 山东/河南‘送到’的具体送达范围 | C8: 分区表标注‘送到’但未定义送到半径，实际可能是本省/本大区内送到，而非送到苏州 | D8: 若‘送到’仅覆盖区域内，则到苏州仍需追加运费 | E8: 向供应商确认‘出厂价’与‘送到苏州价’分别报价 | F8: 可能高估分区价的含运程度（对山东/河南更不利）
A10: 关键假设
A11: A1 | B11: 价格口径：全部为含 13% 增值税的人民币价格，计价单位元/吨（净重）。
A12: A2 | B12: 交货口径：沙河列为自提；华北/华中/华东列为送到或出厂（未细分）。三大来源地若为出厂价，则到厂还需加全程运费；若为送到本区域，则到苏州仍需追加长途运费。两种情况下方向一致：非江苏来源都要另付长途运费。
A13: A3 | B13: 取区间中值作为点估计，并在报告中同时给出区间上下限（敏感性）。
A14: A4 | B14: 运距采用可核验的高德/车主手册类公路路线里程（高速主推方案），不含厂区到高速口的短驳，实际±5%。
A15: A5 | B15: 装卸、检测等费用无法核实，一律留空；用户填 0 表示“确认含在车板价内”。
A16: A6 | B16: 100 吨约需 3.2 车（13m 半挂按 31 吨/车），整车包干运价通常以单程车为单位议价。
A17: A7 | B17: 不预测未来价格。报告中所有关于涨跌的描述均为已发生事实。

Sheet 8-来源
A1: 数据来源
A2: 每个价格都能点回原文。
A4: 编号 | B4: 来源 | C4: 类型 | D4: 口径等级 | E4: 采集时间 | F4: 链接 | G4: 备注
A5: S1 | B5: 化盟网《纯碱日评》分区价格表（2026-10-16） | C5: 市场资讯 | D5: 送到/自提 | E5: 2026-10-19 | F5: https://zx.hm-w.com/viewpoint/detail/17862 | G5: 该表按‘沙河/华北/华东/华中/华南’分区列重碱与轻碱区间价，日频更新，并给出与上一交易日的涨跌。
A6: S2 | B6: 隆众资讯《纯碱日评》分区价格表（2026-10-14） | C6: 市场资讯 | D6: 送到/自提 | E6: 2026-10-19 | F6: https://zx.hm-w.com/viewpoint/detail/17828 | G6: 作为 S1 的回测对照：各分区重碱价格与 10-16 一致，说明近三个交易日现货平稳。
A7: S3 | B7: 海证期货·隆众口径分区重碱价（2026-09-18） | C7: 期货公司日报（引隆众） | D7: 送到 | E7: 2026-10-19 | F7: https://www.sohu.com/a/1077654435_122014422 | G7: 华北 1120-1220、华东 1130-1230、华中 1090-1180。
A8: S4 | B8: 海证期货·隆众口径分区重碱价（2026-09-11） | C8: 期货公司日报（引隆众） | D8: 送到 | E8: 2026-10-19 | F8: https://www.sohu.com/a/1074629703_122014422 | G8: 华北 1120-1220、华东 1130-1230、华中 1090-1180（与 S3 一致）。
A9: S5 | B9: 化盟网《纯碱日评》（2026-09-24 / 2026-09-29） | C9: 市场资讯 | D9: 送到/自提 | E9: 2026-10-19 | F9: https://zx.hm-w.com/viewpoint/detail/17688 | G9: 沙河重碱 09-24 为 970-980（前一日 975-985）；09-29 表中华北/华东重碱 1100-1200、华中 1050-1150。
A10: S6 | B10: 新华财经·玻多多华北/华东重碱价（2026-07-29） | C10: 新闻通讯社 | D10: 主流报价（含税，口径同城） | E10: 2026-10-19 | F10: https://finance.eastmoney.com/a/202607303826720998.html | G10: 华北重碱 1250-1320、华东重碱 1210-1280；华北轻碱 1150-1210、华东轻碱 1010-1570。
A11: S7 | B11: 生意社·重质纯碱基准价与现期图（2026-07-21 ~ 2026-10-19） | C11: 价格指数（全国） | D11: 全国加权参考价 | E11: 2026-10-19 | F11: https://www.100ppi.com/sf/737.html | G11: 10-19 重碱基准价 1062.86 元/吨；同页给出主力合约与基差，可复核全国价格中枢走向。
A12: S8 | B12: 隆众资讯：纯碱期货合约标准化说明（转引郑商所） | C12: 交易所规则 | D12: 规则 | E12: 2026-10-19 | F12: https://www.czce.com.cn/cn/rootfiles/2021/09/03/1605597062097884-1605597062128743.pdf | G12: “轻碱统一采用出厂价；重碱除西北以外的地区采用送到价，西北地区采用出厂价”——这是本报告区分‘出厂/送到’依据。
