Workbook
Name Lambda: '01_参数'!$C$5
Name OtherCost: '01_参数'!$C$6
Name WinB: '01_参数'!$C$7
Name WinC: '01_参数'!$C$8
Name Alpha: '01_参数'!$C$9

Sheet 00_使用说明
A1: 上下游价格联动分析模板
A2: 换品种时：改「01_参数」→ 粘贴价格到「02_原始数据」→ 下拉公式 → 看「04_价差」与「06_相关性」
B4: 1. 核实产业关系 | C4: 先在 references/02-工艺与单耗台账.md 里找到上游是不是下游唯一主要原料；不是唯一，就不要用本模板算价差。
B5: 2. 填参数 | C5: 「01_参数」填单耗 λ、其他成本；λ 必须有出处。
B6: 3. 粘数据 | C6: 「02_原始数据」A5 起粘贴 日期/上游价/下游价；行数变化后把公式列下拉到新行数。
B7: 4. 看结果 | C7: 「04_价差」看分位与滚动均值；「06_相关性」看水平 vs 收益率；「08_阶段」改起止日期即自动重算。
B8: 5. 写报告 | C8: 按 references/07-报告模板.md 的九节结构写；每个数字都要能回到本工作簿。
B10: 注意：本模板中的数字来自示例数据，不是真实行情。

Sheet 01_参数
A1: 参数（改这里，全表重算）
A2: 黄色单元格是参数，已被命名为 Lambda / OtherCost 等，公式直接引用。
A4: 参数 | B4: 名称 | C4: 取值 | D4: 单位 | E4: 来源/说明
A5: 单耗系数 λ | B5: Lambda | C5: 0.655 | D5: t/t | E5: 必须来自单耗台账（示例：PX→PTA 0.655）
A6: 其他成本 | B6: OtherCost | C6: 0 | D6: 元/吨 | E6: 醋酸+动力+折旧简化项；0 = 收入型加工费
A7: 滚动窗口 | B7: WinB | C7: 20 | D7: 观测 | E7: 滚动均值/标准差窗口
A8: 滚动窗口2 | B8: WinC | C8: 60 | D8: 观测 | E8: 第二档窗口
A9: 显著水平 | B9: Alpha | C9: 0.05 | D9: — | E9: 双尾

Sheet 02_原始数据
A1: 原始价格数据（示例行，请替换）
A2: E~H 列为公式；替换 A~C 后把 E~H 下拉到底。
A4: 日期 | B4: 上游价格 | C4: 下游价格 | D4: 摘要 | E4: 价差 | F4: 价比 | G4: 上游收益率 | H4: 下游收益率
A5: 2025-01-02 | B5: 7000 | C5: 5000 | D5: 示例数据 | E5: =C5-Lambda*B5-OtherCost | F5: =C5/B5
A6: 2025-01-03 | B6: 7020 | C6: 5010 | D6: 示例数据 | E6: =C6-Lambda*B6-OtherCost | F6: =C6/B6 | G6: =B6/B5-1 | H6: =C6/C5-1
A7: 2025-01-06 | B7: 6990 | C7: 4990 | D7: 示例数据 | E7: =C7-Lambda*B7-OtherCost | F7: =C7/B7 | G7: =B7/B6-1 | H7: =C7/C6-1
A8: 2025-01-07 | B8: 7050 | C8: 5030 | D8: 示例数据 | E8: =C8-Lambda*B8-OtherCost | F8: =C8/B8 | G8: =B8/B7-1 | H8: =C8/C7-1
A9: 2025-01-08 | B9: 7100 | C9: 5050 | D9: 示例数据 | E9: =C9-Lambda*B9-OtherCost | F9: =C9/B9 | G9: =B9/B8-1 | H9: =C9/C8-1
A10: 2025-01-09 | B10: 7080 | C10: 5060 | D10: 示例数据 | E10: =C10-Lambda*B10-OtherCost | F10: =C10/B10 | G10: =B10/B9-1 | H10: =C10/C9-1

Sheet 03_单耗台账
A1: 单耗台账（必须逐条有出处）
A2: 无出处的行请删除；不要保留估算值。
A4: 来源/装置 | B4: 主料单耗 t/t | C4: 辅料单耗 t/t | D4: 出处 | E4: 备注
A5: 行业通用值 | B5: 0.655 | C5: 0.032 | D5: （填写你的文献来源） | E5: 示例
A6: 装置 A | B6: 0.657 | C6: 0.036 | D6: （填写）
A7: 装置 B | B7: 0.649 | C7: 0.029 | D7: （填写）
A9: 均值 | B9: =AVERAGE(B5:B7)
A10: 极差 | B10: =MAX(B5:B7)-MIN(B5:B7)

Sheet 04_价差
A1: 加工价差与分位
A2: 公式引用 02_原始数据；替换数据后下拉。
A4: 日期 | B4: 上游 | C4: 下游 | D4: 价差 | E4: 历史分位 | F4: 滚动均值
A5: ='02_原始数据'!A5 | B5: ='02_原始数据'!B5 | C5: ='02_原始数据'!C5 | D5: ='02_原始数据'!E5 | E5: =_xlfn.PERCENTRANK.INC('02_原始数据'!$E$5:$E$10,'02_原始数据'!E5) | F5: =IF(COUNT('02_原始数据'!$E$5:$E5)>=2,AVERAGE('02_原始数据'!$E$5:$E5),"")
A6: ='02_原始数据'!A6 | B6: ='02_原始数据'!B6 | C6: ='02_原始数据'!C6 | D6: ='02_原始数据'!E6 | E6: =_xlfn.PERCENTRANK.INC('02_原始数据'!$E$5:$E$10,'02_原始数据'!E6) | F6: =IF(COUNT('02_原始数据'!$E$5:$E6)>=2,AVERAGE('02_原始数据'!$E$5:$E6),"")
A7: ='02_原始数据'!A7 | B7: ='02_原始数据'!B7 | C7: ='02_原始数据'!C7 | D7: ='02_原始数据'!E7 | E7: =_xlfn.PERCENTRANK.INC('02_原始数据'!$E$5:$E$10,'02_原始数据'!E7) | F7: =IF(COUNT('02_原始数据'!$E$5:$E7)>=2,AVERAGE('02_原始数据'!$E$5:$E7),"")
A8: ='02_原始数据'!A8 | B8: ='02_原始数据'!B8 | C8: ='02_原始数据'!C8 | D8: ='02_原始数据'!E8 | E8: =_xlfn.PERCENTRANK.INC('02_原始数据'!$E$5:$E$10,'02_原始数据'!E8) | F8: =IF(COUNT('02_原始数据'!$E$5:$E8)>=2,AVERAGE('02_原始数据'!$E$5:$E8),"")
A9: ='02_原始数据'!A9 | B9: ='02_原始数据'!B9 | C9: ='02_原始数据'!C9 | D9: ='02_原始数据'!E9 | E9: =_xlfn.PERCENTRANK.INC('02_原始数据'!$E$5:$E$10,'02_原始数据'!E9) | F9: =IF(COUNT('02_原始数据'!$E$5:$E9)>=2,AVERAGE('02_原始数据'!$E$5:$E9),"")
A10: ='02_原始数据'!A10 | B10: ='02_原始数据'!B10 | C10: ='02_原始数据'!C10 | D10: ='02_原始数据'!E10 | E10: =_xlfn.PERCENTRANK.INC('02_原始数据'!$E$5:$E$10,'02_原始数据'!E10) | F10: =IF(COUNT('02_原始数据'!$E$5:$E10)>=2,AVERAGE('02_原始数据'!$E$5:$E10),"")
A13: 统计量 | B13: 数值 | C13: 说明
A14: P10 | B14: =_xlfn.PERCENTILE.INC('02_原始数据'!$E$5:$E$10,0.1) | C14: 历史 10% 分位
A15: P50 | B15: =_xlfn.PERCENTILE.INC('02_原始数据'!$E$5:$E$10,0.5) | C15: 中位（抗极端值）
A16: P90 | B16: =_xlfn.PERCENTILE.INC('02_原始数据'!$E$5:$E$10,0.9) | C16: 历史 90% 分位
A17: 均值 | B17: =AVERAGE('02_原始数据'!$E$5:$E$10) | C17: 算术均值
A18: 标准差 | B18: =STDEV('02_原始数据'!$E$5:$E$10) | C18: 样本标准差
A19: 当前值 | B19: ='02_原始数据'!E10 | C19: 最后一个观测

Sheet 05_单耗敏感性
A1: 单耗敏感性（λ 不确定时价差怎么变）
A2: 价差 = 下游 − λ×上游 − 其他成本；每行一个 λ。
F3: 辅助：各 λ 下的价差序列
A4: λ | B4: 价差均值 | C4: 价差中位 | D4: 标准差
A5: 0.6 | B5: =AVERAGE($F$5:$F$10) | C5: =MEDIAN($F$5:$F$10) | D5: =STDEV($F$5:$F$10) | F5: ='02_原始数据'!C5-0.6*'02_原始数据'!B5-OtherCost | G5: ='02_原始数据'!C5-0.605*'02_原始数据'!B5-OtherCost | H5: ='02_原始数据'!C5-0.61*'02_原始数据'!B5-OtherCost | I5: ='02_原始数据'!C5-0.615*'02_原始数据'!B5-OtherCost | J5: ='02_原始数据'!C5-0.62*'02_原始数据'!B5-OtherCost | K5: ='02_原始数据'!C5-0.625*'02_原始数据'!B5-OtherCost | L5: ='02_原始数据'!C5-0.63*'02_原始数据'!B5-OtherCost | M5: ='02_原始数据'!C5-0.635*'02_原始数据'!B5-OtherCost | N5: ='02_原始数据'!C5-0.64*'02_原始数据'!B5-OtherCost
A6: 0.605 | B6: =AVERAGE($G$5:$G$10) | C6: =MEDIAN($G$5:$G$10) | D6: =STDEV($G$5:$G$10) | F6: ='02_原始数据'!C6-0.6*'02_原始数据'!B6-OtherCost | G6: ='02_原始数据'!C6-0.605*'02_原始数据'!B6-OtherCost | H6: ='02_原始数据'!C6-0.61*'02_原始数据'!B6-OtherCost | I6: ='02_原始数据'!C6-0.615*'02_原始数据'!B6-OtherCost | J6: ='02_原始数据'!C6-0.62*'02_原始数据'!B6-OtherCost | K6: ='02_原始数据'!C6-0.625*'02_原始数据'!B6-OtherCost | L6: ='02_原始数据'!C6-0.63*'02_原始数据'!B6-OtherCost | M6: ='02_原始数据'!C6-0.635*'02_原始数据'!B6-OtherCost | N6: ='02_原始数据'!C6-0.64*'02_原始数据'!B6-OtherCost
A7: 0.61 | B7: =AVERAGE($H$5:$H$10) | C7: =MEDIAN($H$5:$H$10) | D7: =STDEV($H$5:$H$10) | F7: ='02_原始数据'!C7-0.6*'02_原始数据'!B7-OtherCost | G7: ='02_原始数据'!C7-0.605*'02_原始数据'!B7-OtherCost | H7: ='02_原始数据'!C7-0.61*'02_原始数据'!B7-OtherCost | I7: ='02_原始数据'!C7-0.615*'02_原始数据'!B7-OtherCost | J7: ='02_原始数据'!C7-0.62*'02_原始数据'!B7-OtherCost | K7: ='02_原始数据'!C7-0.625*'02_原始数据'!B7-OtherCost | L7: ='02_原始数据'!C7-0.63*'02_原始数据'!B7-OtherCost | M7: ='02_原始数据'!C7-0.635*'02_原始数据'!B7-OtherCost | N7: ='02_原始数据'!C7-0.64*'02_原始数据'!B7-OtherCost
A8: 0.615 | B8: =AVERAGE($I$5:$I$10) | C8: =MEDIAN($I$5:$I$10) | D8: =STDEV($I$5:$I$10) | F8: ='02_原始数据'!C8-0.6*'02_原始数据'!B8-OtherCost | G8: ='02_原始数据'!C8-0.605*'02_原始数据'!B8-OtherCost | H8: ='02_原始数据'!C8-0.61*'02_原始数据'!B8-OtherCost | I8: ='02_原始数据'!C8-0.615*'02_原始数据'!B8-OtherCost | J8: ='02_原始数据'!C8-0.62*'02_原始数据'!B8-OtherCost | K8: ='02_原始数据'!C8-0.625*'02_原始数据'!B8-OtherCost | L8: ='02_原始数据'!C8-0.63*'02_原始数据'!B8-OtherCost | M8: ='02_原始数据'!C8-0.635*'02_原始数据'!B8-OtherCost | N8: ='02_原始数据'!C8-0.64*'02_原始数据'!B8-OtherCost
A9: 0.62 | B9: =AVERAGE($J$5:$J$10) | C9: =MEDIAN($J$5:$J$10) | D9: =STDEV($J$5:$J$10) | F9: ='02_原始数据'!C9-0.6*'02_原始数据'!B9-OtherCost | G9: ='02_原始数据'!C9-0.605*'02_原始数据'!B9-OtherCost | H9: ='02_原始数据'!C9-0.61*'02_原始数据'!B9-OtherCost | I9: ='02_原始数据'!C9-0.615*'02_原始数据'!B9-OtherCost | J9: ='02_原始数据'!C9-0.62*'02_原始数据'!B9-OtherCost | K9: ='02_原始数据'!C9-0.625*'02_原始数据'!B9-OtherCost | L9: ='02_原始数据'!C9-0.63*'02_原始数据'!B9-OtherCost | M9: ='02_原始数据'!C9-0.635*'02_原始数据'!B9-OtherCost | N9: ='02_原始数据'!C9-0.64*'02_原始数据'!B9-OtherCost
A10: 0.625 | B10: =AVERAGE($K$5:$K$10) | C10: =MEDIAN($K$5:$K$10) | D10: =STDEV($K$5:$K$10) | F10: ='02_原始数据'!C10-0.6*'02_原始数据'!B10-OtherCost | G10: ='02_原始数据'!C10-0.605*'02_原始数据'!B10-OtherCost | H10: ='02_原始数据'!C10-0.61*'02_原始数据'!B10-OtherCost | I10: ='02_原始数据'!C10-0.615*'02_原始数据'!B10-OtherCost | J10: ='02_原始数据'!C10-0.62*'02_原始数据'!B10-OtherCost | K10: ='02_原始数据'!C10-0.625*'02_原始数据'!B10-OtherCost | L10: ='02_原始数据'!C10-0.63*'02_原始数据'!B10-OtherCost | M10: ='02_原始数据'!C10-0.635*'02_原始数据'!B10-OtherCost | N10: ='02_原始数据'!C10-0.64*'02_原始数据'!B10-OtherCost
A11: 0.63 | B11: =AVERAGE($L$5:$L$10) | C11: =MEDIAN($L$5:$L$10) | D11: =STDEV($L$5:$L$10)
A12: 0.635 | B12: =AVERAGE($M$5:$M$10) | C12: =MEDIAN($M$5:$M$10) | D12: =STDEV($M$5:$M$10)
A13: 0.64 | B13: =AVERAGE($N$5:$N$10) | C13: =MEDIAN($N$5:$N$10) | D13: =STDEV($N$5:$N$10)

Sheet 06_相关性
A1: 水平相关 vs 收益率相关
A2: 两个数不能互相替代：水平含共同趋势，收益率才反映逐期传导。
A4: 口径 | B4: Pearson r | C4: R² | D4: N | E4: t | F4: p（双尾） | G4: 95%CI
A5: 价格水平 | B5: =CORREL('02_原始数据'!$B$5:$B$10,'02_原始数据'!$C$5:$C$10) | C5: =RSQ('02_原始数据'!$C$5:$C$10,'02_原始数据'!$B$5:$B$10) | D5: =COUNT('02_原始数据'!$B$5:$B$10) | E5: =B5*SQRT((D5-2)/(1-B5^2)) | F5: =IF(D5>2,_xlfn.T.DIST.2T(ABS(E5),D5-2),"NA") | G5: =TEXT(TANH(ATANH(B5)-_xlfn.NORM.S.INV(1-Alpha/2)/SQRT(D5-3)),"0.000")&" ~ "&TEXT(TANH(ATANH(B5)+_xlfn.NORM.S.INV(1-Alpha/2)/SQRT(D5-3)),"0.000")
A6: 日收益率 | B6: =CORREL('02_原始数据'!$G$6:$G$10,'02_原始数据'!$H$6:$H$10) | C6: =RSQ('02_原始数据'!$H$6:$H$10,'02_原始数据'!$G$6:$G$10) | D6: =COUNT('02_原始数据'!$G$6:$G$10) | E6: =B6*SQRT((D6-2)/(1-B6^2)) | F6: =IF(D6>2,_xlfn.T.DIST.2T(ABS(E6),D6-2),"NA") | G6: =TEXT(TANH(ATANH(B6)-_xlfn.NORM.S.INV(1-Alpha/2)/SQRT(D6-3)),"0.000")&" ~ "&TEXT(TANH(ATANH(B6)+_xlfn.NORM.S.INV(1-Alpha/2)/SQRT(D6-3)),"0.000")

Sheet 07_滚动相关
A1: 滚动相关（窗口内样本不足 80% 留空）
A2: 窗口由「01_参数」的 WinB 控制。
A4: 日期 | B4: 滚动 r（水平） | C4: 有效样本
A5: ='02_原始数据'!A5 | B5: =IF(COUNT('02_原始数据'!B5:B5)>=2,IFERROR(CORREL('02_原始数据'!B5:B5,'02_原始数据'!C5:C5),""),"") | C5: =COUNT('02_原始数据'!B5:B5)
A6: ='02_原始数据'!A6 | B6: =IF(COUNT('02_原始数据'!B5:B6)>=2,IFERROR(CORREL('02_原始数据'!B5:B6,'02_原始数据'!C5:C6),""),"") | C6: =COUNT('02_原始数据'!B5:B6)
A7: ='02_原始数据'!A7 | B7: =IF(COUNT('02_原始数据'!B5:B7)>=2,IFERROR(CORREL('02_原始数据'!B5:B7,'02_原始数据'!C5:C7),""),"") | C7: =COUNT('02_原始数据'!B5:B7)
A8: ='02_原始数据'!A8 | B8: =IF(COUNT('02_原始数据'!B5:B8)>=2,IFERROR(CORREL('02_原始数据'!B5:B8,'02_原始数据'!C5:C8),""),"") | C8: =COUNT('02_原始数据'!B5:B8)
A9: ='02_原始数据'!A9 | B9: =IF(COUNT('02_原始数据'!B5:B9)>=2,IFERROR(CORREL('02_原始数据'!B5:B9,'02_原始数据'!C5:C9),""),"") | C9: =COUNT('02_原始数据'!B5:B9)
A10: ='02_原始数据'!A10 | B10: =IF(COUNT('02_原始数据'!B6:B10)>=2,IFERROR(CORREL('02_原始数据'!B6:B10,'02_原始数据'!C6:C10),""),"") | C10: =COUNT('02_原始数据'!B6:B10)

Sheet 08_阶段
A1: 阶段统计（改起止日期自动重算）
A2: 阶段必须按产业事件预先定义，不要按结果反复切。
A4: 阶段 | B4: 起 | C4: 止 | D4: N | E4: 上游涨跌 | F4: 下游涨跌
A5: S1 | B5: 2025-01-01 | C5: 2025-03-31 | D5: =COUNTIFS('02_原始数据'!$A$5:$A$10,">="&B5,'02_原始数据'!$A$5:$A$10,"<="&C5) | E5: =IFERROR(AVERAGEIFS('02_原始数据'!$G$6:$G$10,'02_原始数据'!$A$6:$A$10,">="&B5,'02_原始数据'!$A$6:$A$10,"<="&C5),"") | F5: =IFERROR(AVERAGEIFS('02_原始数据'!$H$6:$H$10,'02_原始数据'!$A$6:$A$10,">="&B5,'02_原始数据'!$A$6:$A$10,"<="&C5),"")
A6: S2 | B6: 2025-04-01 | C6: 2025-06-30 | D6: =COUNTIFS('02_原始数据'!$A$5:$A$10,">="&B6,'02_原始数据'!$A$5:$A$10,"<="&C6) | E6: =IFERROR(AVERAGEIFS('02_原始数据'!$G$6:$G$10,'02_原始数据'!$A$6:$A$10,">="&B6,'02_原始数据'!$A$6:$A$10,"<="&C6),"") | F6: =IFERROR(AVERAGEIFS('02_原始数据'!$H$6:$H$10,'02_原始数据'!$A$6:$A$10,">="&B6,'02_原始数据'!$A$6:$A$10,"<="&C6),"")
