Workbook

Sheet 00 说明与使用指南
A1: 两指标相关性研究工作簿｜甲醇港口库存 × 太仓现货价
A2: 示例数据为按真实行业口径拟真的 DEMO 数据（见“01 口径与来源”）。把真实历史数据贴进“02 原始数据”，本工作簿所有公式自动重算。
B4: 这份工作簿解决什么 | C4: 回答“两个指标到底相不相关、在什么条件下相关、这个相关是否可信”。不回答“买还是卖”，也不给因果结论。
B5: 第 1 步 输入数据 | C5: 在“02 原始数据”替换 B/C/D/G 列（观测日、价格锚日、库存、价格）。缺失就留空或用 =NA()，绝不插值补数。
B6: 第 2 步 核对口径 | C6: “01 口径与来源”逐项填全：单位、频率、区域、样本口径、发布时点、来源。任一项缺失，结论不可对外引用。
B7: 第 3 步 频率对齐 | C7: “03 频率对齐”标出每期配对状态（成功/缺失-剔除），并给出有效配对 N 与缺失期数。
B8: 第 4 步 变换 | C8: “04 变换后数据”把库存/价格分别做成 水平、差分、环比%。库存常看变化，价格常看变化率。
B9: 第 5 步 读结果 | C9: “05 总体相关”给 5 种形态组合的 r/N/R²/t/p/判定；“06 滚动相关”看强度随时间变化；“07 分阶段”按业务阶段重算。
B10: 第 6 步 查伪相关 | C10: “09 稳健性与伪相关诊断”+“09b 辅助计算(残差)”：去趋势、差分、剔极值、分段、偏相关；自相关强时用有效样本量修正。
B11: 第 7 步 写结论 | C11: 结论必须带口径、形态、时间段、N、显著性、稳健性；禁止把相关性写成因果，禁止输出交易建议。
B12: 公式透明 | C12: “12 公式说明”逐条给出公式定义与 Excel 写法，全部可在表内复核（无宏、无加载项）。
B14: ⚠ 重要声明 | C14: 相关性不等于因果关系；滚动相关只描述历史窗口内的共变强度，不外推未来；本工作簿不提供任何交易建议或价格预测。

Sheet 01 口径与来源
A1: 口径与来源（数据可否引用的前提）
A2: 每列都要有值。任一项写“待确认”，对应结论只能当探索性提示。
B4: 指标 | C4: 指标全称 | D4: 单位 | E4: 频率 | F4: 统计区域/样本 | G4: 发布时点（口径） | H4: 来源与链接 | I4: 备注（口径风险）
B5: 指标 X（库存） | C5: 中国甲醇样本港口库存（总） | D5: 万吨 | E5: 周度 | F5: 华东（江苏/浙江各港口）+ 华南 | G5: 调查日=每周三，机构当日或次日发布 | H5: DEMO：按隆众资讯周度口径拟真，非真实市场数据 | I5: 示例为拟真数据；真实使用请替换为可获得的历史序列
B6: 指标 Y（价格） | C6: 江苏太仓甲醇出罐现货价（现汇） | D6: 元/吨 | E6: 周度（由日报汇总） | F6: 江苏太仓 | G6: 日报午评口径（如 12:00），取当周锚日 | H6: DEMO：按隆众/我的钢铁日报口径拟真，非真实市场数据 | I6: 现货报价的税基/现汇/库提口径需与成交口径核对
B7: 控制变量（可选） | C7: 动力煤 5500 现货价 | D7: 元/吨 | E7: 周度 | F7: 环渤海/秦皇岛 | G7: 周度发布 | H7: DEMO：成本参照 | I7: 仅用于偏相关诊断“共同外部因素”
B8: 分析频率 | C8: 周度（周三对齐） | D8: — | E8: 周度 | F8: — | G8: — | H8: 对齐规则见“03 频率对齐” | I8: 若原始为日度，须按同一时点汇总，禁止使用未来信息
B10: 数据状态 | C10: 本文件所有数值为教学/演示用拟真数据（机制见 scripts/make_data.py），不得作为真实行情或研究结论引用。

Sheet 02 原始数据
A1: 原始数据（唯一数据入口，其余表全部由本表驱动）
A2: 橙底两列为需替换的核心输入列（库存、价格）。留空=缺失，全表按缺失处理，不插补。
A4: 序号 | B4: 观测日(库存调查日) | C4: 价格锚日 | D4: 港口库存-总计 | E4: 港口库存-华东 | F4: 港口库存-华南 | G4: 太仓现货价 | H4: 动力煤5500 | I4: 下游开工率% | J4: 周度到港 | K4: 周度提货
A5: 1 | B5: 2023-10-11 | C5: 2023-10-11 | D5: 57.54 | E5: 38.52 | F5: 19.02 | G5: 2640 | H5: 799 | I5: 70 | J5: 7.03 | K5: 13.19
A6: 2 | B6: 2023-10-18 | C6: 2023-10-18 | D6: 60.29 | E6: 37.3 | F6: 22.99 | G6: 2444 | H6: 815 | I6: 70.3 | J6: 10.42 | K6: 11.88
A7: 3 | B7: 2023-10-25 | C7: 2023-10-25 | D7: 55.24 | E7: 37.12 | F7: 18.12 | G7: 2938 | H7: 811 | I7: 68.7 | J7: 8.14 | K7: 11.28
A8: 4 | B8: 2023-11-01 | C8: 2023-11-01 | D8: 57.64 | E8: 38.53 | F8: 19.11 | G8: 2726 | H8: 808 | I8: 71.4 | J8: 13.42 | K8: 11.99
A9: 5 | B9: 2023-11-08 | C9: 2023-11-08 | D9: 67.02 | E9: 43.43 | F9: 23.59 | G9: 2069 | H9: 808 | I9: 71.4 | J9: 16.04 | K9: 11.28
A10: 6 | B10: 2023-11-15 | C10: 2023-11-15 | D10: 67.23 | E10: 45.81 | F10: 21.42 | G10: 2050 | H10: 818 | I10: 72.8 | J10: 12.18 | K10: 12.52
A11: 7 | B11: 2023-11-22 | C11: 2023-11-22 | D11: 64.21 | E11: 42.73 | F11: 21.48 | G11: 2155 | H11: 821 | I11: 70.8 | J11: 9.36 | K11: 13.79
A12: 8 | B12: 2023-11-29 | C12: 2023-11-29 | D12: 67.39 | E12: 43.85 | F12: 23.54 | G12: 2087 | H12: 812 | I12: 71.7 | J12: 15.03 | K12: 11.68
A13: 9 | B13: 2023-12-06 | C13: 2023-12-06 | D13: 65.95 | E13: 43.43 | F13: 22.52 | G13: 2181 | H13: 814 | I13: 72.4 | J13: 11.34 | K13: 12.44
A14: 10 | B14: 2023-12-13 | C14: 2023-12-13 | D14: 58.84 | E14: 38.1 | F14: 20.74 | G14: 2675 | H14: 822 | I14: 72.7 | J14: 8.49 | K14: 12.2
A15: 11 | B15: 2023-12-20 | C15: 2023-12-20 | D15: 54.79 | E15: 35.39 | F15: 19.4 | G15: 2940 | H15: 818 | I15: 73.6 | J15: 9.22 | K15: 13.38
A16: 12 | B16: 2023-12-27 | C16: 2023-12-27 | D16: 52.11 | E16: 33.63 | F16: 18.48 | G16: 3228 | H16: 810 | I16: 74.9 | J16: 9.71 | K16: 11.82
... A160: 156 | B160: 2026-09-30 | C160: 2026-09-30 | D160: 78.39 | E160: 49.73 | F160: 28.66 | G160: 1668 | H160: 777 | I160: 74.9 | J160: 22.5 | K160: 11.52

Sheet 03 频率对齐
A1: 频率对齐与配对规则
A2: 库存为周三调查值，价格为同一交易日午评报价；两序列均按周度处理，直接按观测日一一配对。任一期缺失则不参与配对，也不补数。
A4: 序号 | B4: 观测日 | C4: 价格锚日 | D4: 配对状态 | E4: 库存 | F4: 价格 | G4: 库存形态 | H4: 价格形态 | I4: 时点一致性
A5: 1 | B5: ='02 原始数据'!B5 | C5: ='02 原始数据'!C5 | D5: =IF(OR(E5="",F5=""),"缺失-剔除","配对成功") | E5: ='02 原始数据'!D5 | F5: ='02 原始数据'!G5 | G5: =IF(D5="配对成功","水平可用","") | H5: ="" | I5: =IF(B5=C5,"同日","不同日，需注明时点差")
A6: 2 | B6: ='02 原始数据'!B6 | C6: ='02 原始数据'!C6 | D6: =IF(OR(E6="",F6=""),"缺失-剔除","配对成功") | E6: ='02 原始数据'!D6 | F6: ='02 原始数据'!G6 | G6: =IF(D6="配对成功","水平可用","") | H6: =IF(AND(D6="配对成功",A6>1,E5<>""),"变化可用","") | I6: =IF(B6=C6,"同日","不同日，需注明时点差")
A7: 3 | B7: ='02 原始数据'!B7 | C7: ='02 原始数据'!C7 | D7: =IF(OR(E7="",F7=""),"缺失-剔除","配对成功") | E7: ='02 原始数据'!D7 | F7: ='02 原始数据'!G7 | G7: =IF(D7="配对成功","水平可用","") | H7: =IF(AND(D7="配对成功",A7>1,E6<>""),"变化可用","") | I7: =IF(B7=C7,"同日","不同日，需注明时点差")
A8: 4 | B8: ='02 原始数据'!B8 | C8: ='02 原始数据'!C8 | D8: =IF(OR(E8="",F8=""),"缺失-剔除","配对成功") | E8: ='02 原始数据'!D8 | F8: ='02 原始数据'!G8 | G8: =IF(D8="配对成功","水平可用","") | H8: =IF(AND(D8="配对成功",A8>1,E7<>""),"变化可用","") | I8: =IF(B8=C8,"同日","不同日，需注明时点差")
A9: 5 | B9: ='02 原始数据'!B9 | C9: ='02 原始数据'!C9 | D9: =IF(OR(E9="",F9=""),"缺失-剔除","配对成功") | E9: ='02 原始数据'!D9 | F9: ='02 原始数据'!G9 | G9: =IF(D9="配对成功","水平可用","") | H9: =IF(AND(D9="配对成功",A9>1,E8<>""),"变化可用","") | I9: =IF(B9=C9,"同日","不同日，需注明时点差")
A10: 6 | B10: ='02 原始数据'!B10 | C10: ='02 原始数据'!C10 | D10: =IF(OR(E10="",F10=""),"缺失-剔除","配对成功") | E10: ='02 原始数据'!D10 | F10: ='02 原始数据'!G10 | G10: =IF(D10="配对成功","水平可用","") | H10: =IF(AND(D10="配对成功",A10>1,E9<>""),"变化可用","") | I10: =IF(B10=C10,"同日","不同日，需注明时点差")
A11: 7 | B11: ='02 原始数据'!B11 | C11: ='02 原始数据'!C11 | D11: =IF(OR(E11="",F11=""),"缺失-剔除","配对成功") | E11: ='02 原始数据'!D11 | F11: ='02 原始数据'!G11 | G11: =IF(D11="配对成功","水平可用","") | H11: =IF(AND(D11="配对成功",A11>1,E10<>""),"变化可用","") | I11: =IF(B11=C11,"同日","不同日，需注明时点差")
A12: 8 | B12: ='02 原始数据'!B12 | C12: ='02 原始数据'!C12 | D12: =IF(OR(E12="",F12=""),"缺失-剔除","配对成功") | E12: ='02 原始数据'!D12 | F12: ='02 原始数据'!G12 | G12: =IF(D12="配对成功","水平可用","") | H12: =IF(AND(D12="配对成功",A12>1,E11<>""),"变化可用","") | I12: =IF(B12=C12,"同日","不同日，需注明时点差")
A13: 9 | B13: ='02 原始数据'!B13 | C13: ='02 原始数据'!C13 | D13: =IF(OR(E13="",F13=""),"缺失-剔除","配对成功") | E13: ='02 原始数据'!D13 | F13: ='02 原始数据'!G13 | G13: =IF(D13="配对成功","水平可用","") | H13: =IF(AND(D13="配对成功",A13>1,E12<>""),"变化可用","") | I13: =IF(B13=C13,"同日","不同日，需注明时点差")
A14: 10 | B14: ='02 原始数据'!B14 | C14: ='02 原始数据'!C14 | D14: =IF(OR(E14="",F14=""),"缺失-剔除","配对成功") | E14: ='02 原始数据'!D14 | F14: ='02 原始数据'!G14 | G14: =IF(D14="配对成功","水平可用","") | H14: =IF(AND(D14="配对成功",A14>1,E13<>""),"变化可用","") | I14: =IF(B14=C14,"同日","不同日，需注明时点差")
A15: 11 | B15: ='02 原始数据'!B15 | C15: ='02 原始数据'!C15 | D15: =IF(OR(E15="",F15=""),"缺失-剔除","配对成功") | E15: ='02 原始数据'!D15 | F15: ='02 原始数据'!G15 | G15: =IF(D15="配对成功","水平可用","") | H15: =IF(AND(D15="配对成功",A15>1,E14<>""),"变化可用","") | I15: =IF(B15=C15,"同日","不同日，需注明时点差")
A16: 12 | B16: ='02 原始数据'!B16 | C16: ='02 原始数据'!C16 | D16: =IF(OR(E16="",F16=""),"缺失-剔除","配对成功") | E16: ='02 原始数据'!D16 | F16: ='02 原始数据'!G16 | G16: =IF(D16="配对成功","水平可用","") | H16: =IF(AND(D16="配对成功",A16>1,E15<>""),"变化可用","") | I16: =IF(B16=C16,"同日","不同日，需注明时点差")
A17: 13 | B17: ='02 原始数据'!B17 | C17: ='02 原始数据'!C17 | D17: =IF(OR(E17="",F17=""),"缺失-剔除","配对成功") | E17: ='02 原始数据'!D17 | F17: ='02 原始数据'!G17 | G17: =IF(D17="配对成功","水平可用","") | H17: =IF(AND(D17="配对成功",A17>1,E16<>""),"变化可用","") | I17: =IF(B17=C17,"同日","不同日，需注明时点差")
... A160: 156 | B160: ='02 原始数据'!B160 | C160: ='02 原始数据'!C160 | D160: =IF(OR(E160="",F160=""),"缺失-剔除","配对成功") | E160: ='02 原始数据'!D160 | F160: ='02 原始数据'!G160 | G160: =IF(D160="配对成功","水平可用","") | H160: =IF(AND(D160="配对成功",A160>1,E159<>""),"变化可用","") | I160: =IF(B160=C160,"同日","不同日，需注明时点差")
B162: 有效配对数 N = | E162: =COUNTIF(D5:D160,"配对成功")
B163: 缺失期数 = | E163: =COUNTIF(D5:D160,"缺失-剔除")

Sheet 04 变换后数据
A1: 变换：水平 / 一阶差分 / 环比%
A2: 差分与环比的首期必为空（没有上一期），这是设计而非缺数。库存变化单位是万吨，价格变化单位是%，相关系数本身与单位无关，但经济含义不同。
A4: 序号 | B4: 观测日 | C4: 库存-水平 | D4: 库存-差分 | E4: 库存-环比% | F4: 价格-水平 | G4: 价格-差分 | H4: 价格-环比% | I4: 煤价-水平 | J4: 开工率-水平 | K4: 库存/提货比
A5: 1 | B5: ='02 原始数据'!B5 | C5: ='02 原始数据'!D5 | D5: ="" | E5: ="" | F5: ='02 原始数据'!G5 | G5: ="" | H5: ="" | I5: ='02 原始数据'!H5 | J5: ='02 原始数据'!I5 | K5: =IFERROR(IF(C5="","",C5/'02 原始数据'!K5),"")
A6: 2 | B6: ='02 原始数据'!B6 | C6: ='02 原始数据'!D6 | D6: =IF(OR(C6="",C5=""),"",C6-C5) | E6: =IF(OR(C6="",C5=""),"",(C6-C5)/ABS(C5)) | F6: ='02 原始数据'!G6 | G6: =IF(OR(F6="",F5=""),"",F6-F5) | H6: =IF(OR(F6="",F5=""),"",(F6-F5)/ABS(F5)) | I6: ='02 原始数据'!H6 | J6: ='02 原始数据'!I6 | K6: =IFERROR(IF(C6="","",C6/'02 原始数据'!K6),"")
A7: 3 | B7: ='02 原始数据'!B7 | C7: ='02 原始数据'!D7 | D7: =IF(OR(C7="",C6=""),"",C7-C6) | E7: =IF(OR(C7="",C6=""),"",(C7-C6)/ABS(C6)) | F7: ='02 原始数据'!G7 | G7: =IF(OR(F7="",F6=""),"",F7-F6) | H7: =IF(OR(F7="",F6=""),"",(F7-F6)/ABS(F6)) | I7: ='02 原始数据'!H7 | J7: ='02 原始数据'!I7 | K7: =IFERROR(IF(C7="","",C7/'02 原始数据'!K7),"")
A8: 4 | B8: ='02 原始数据'!B8 | C8: ='02 原始数据'!D8 | D8: =IF(OR(C8="",C7=""),"",C8-C7) | E8: =IF(OR(C8="",C7=""),"",(C8-C7)/ABS(C7)) | F8: ='02 原始数据'!G8 | G8: =IF(OR(F8="",F7=""),"",F8-F7) | H8: =IF(OR(F8="",F7=""),"",(F8-F7)/ABS(F7)) | I8: ='02 原始数据'!H8 | J8: ='02 原始数据'!I8 | K8: =IFERROR(IF(C8="","",C8/'02 原始数据'!K8),"")
A9: 5 | B9: ='02 原始数据'!B9 | C9: ='02 原始数据'!D9 | D9: =IF(OR(C9="",C8=""),"",C9-C8) | E9: =IF(OR(C9="",C8=""),"",(C9-C8)/ABS(C8)) | F9: ='02 原始数据'!G9 | G9: =IF(OR(F9="",F8=""),"",F9-F8) | H9: =IF(OR(F9="",F8=""),"",(F9-F8)/ABS(F8)) | I9: ='02 原始数据'!H9 | J9: ='02 原始数据'!I9 | K9: =IFERROR(IF(C9="","",C9/'02 原始数据'!K9),"")
A10: 6 | B10: ='02 原始数据'!B10 | C10: ='02 原始数据'!D10 | D10: =IF(OR(C10="",C9=""),"",C10-C9) | E10: =IF(OR(C10="",C9=""),"",(C10-C9)/ABS(C9)) | F10: ='02 原始数据'!G10 | G10: =IF(OR(F10="",F9=""),"",F10-F9) | H10: =IF(OR(F10="",F9=""),"",(F10-F9)/ABS(F9)) | I10: ='02 原始数据'!H10 | J10: ='02 原始数据'!I10 | K10: =IFERROR(IF(C10="","",C10/'02 原始数据'!K10),"")
A11: 7 | B11: ='02 原始数据'!B11 | C11: ='02 原始数据'!D11 | D11: =IF(OR(C11="",C10=""),"",C11-C10) | E11: =IF(OR(C11="",C10=""),"",(C11-C10)/ABS(C10)) | F11: ='02 原始数据'!G11 | G11: =IF(OR(F11="",F10=""),"",F11-F10) | H11: =IF(OR(F11="",F10=""),"",(F11-F10)/ABS(F10)) | I11: ='02 原始数据'!H11 | J11: ='02 原始数据'!I11 | K11: =IFERROR(IF(C11="","",C11/'02 原始数据'!K11),"")
A12: 8 | B12: ='02 原始数据'!B12 | C12: ='02 原始数据'!D12 | D12: =IF(OR(C12="",C11=""),"",C12-C11) | E12: =IF(OR(C12="",C11=""),"",(C12-C11)/ABS(C11)) | F12: ='02 原始数据'!G12 | G12: =IF(OR(F12="",F11=""),"",F12-F11) | H12: =IF(OR(F12="",F11=""),"",(F12-F11)/ABS(F11)) | I12: ='02 原始数据'!H12 | J12: ='02 原始数据'!I12 | K12: =IFERROR(IF(C12="","",C12/'02 原始数据'!K12),"")
A13: 9 | B13: ='02 原始数据'!B13 | C13: ='02 原始数据'!D13 | D13: =IF(OR(C13="",C12=""),"",C13-C12) | E13: =IF(OR(C13="",C12=""),"",(C13-C12)/ABS(C12)) | F13: ='02 原始数据'!G13 | G13: =IF(OR(F13="",F12=""),"",F13-F12) | H13: =IF(OR(F13="",F12=""),"",(F13-F12)/ABS(F12)) | I13: ='02 原始数据'!H13 | J13: ='02 原始数据'!I13 | K13: =IFERROR(IF(C13="","",C13/'02 原始数据'!K13),"")
A14: 10 | B14: ='02 原始数据'!B14 | C14: ='02 原始数据'!D14 | D14: =IF(OR(C14="",C13=""),"",C14-C13) | E14: =IF(OR(C14="",C13=""),"",(C14-C13)/ABS(C13)) | F14: ='02 原始数据'!G14 | G14: =IF(OR(F14="",F13=""),"",F14-F13) | H14: =IF(OR(F14="",F13=""),"",(F14-F13)/ABS(F13)) | I14: ='02 原始数据'!H14 | J14: ='02 原始数据'!I14 | K14: =IFERROR(IF(C14="","",C14/'02 原始数据'!K14),"")
A15: 11 | B15: ='02 原始数据'!B15 | C15: ='02 原始数据'!D15 | D15: =IF(OR(C15="",C14=""),"",C15-C14) | E15: =IF(OR(C15="",C14=""),"",(C15-C14)/ABS(C14)) | F15: ='02 原始数据'!G15 | G15: =IF(OR(F15="",F14=""),"",F15-F14) | H15: =IF(OR(F15="",F14=""),"",(F15-F14)/ABS(F14)) | I15: ='02 原始数据'!H15 | J15: ='02 原始数据'!I15 | K15: =IFERROR(IF(C15="","",C15/'02 原始数据'!K15),"")
A16: 12 | B16: ='02 原始数据'!B16 | C16: ='02 原始数据'!D16 | D16: =IF(OR(C16="",C15=""),"",C16-C15) | E16: =IF(OR(C16="",C15=""),"",(C16-C15)/ABS(C15)) | F16: ='02 原始数据'!G16 | G16: =IF(OR(F16="",F15=""),"",F16-F15) | H16: =IF(OR(F16="",F15=""),"",(F16-F15)/ABS(F15)) | I16: ='02 原始数据'!H16 | J16: ='02 原始数据'!I16 | K16: =IFERROR(IF(C16="","",C16/'02 原始数据'!K16),"")
A17: 13 | B17: ='02 原始数据'!B17 | C17: ='02 原始数据'!D17 | D17: =IF(OR(C17="",C16=""),"",C17-C16) | E17: =IF(OR(C17="",C16=""),"",(C17-C16)/ABS(C16)) | F17: ='02 原始数据'!G17 | G17: =IF(OR(F17="",F16=""),"",F17-F16) | H17: =IF(OR(F17="",F16=""),"",(F17-F16)/ABS(F16)) | I17: ='02 原始数据'!H17 | J17: ='02 原始数据'!I17 | K17: =IFERROR(IF(C17="","",C17/'02 原始数据'!K17),"")
... A160: 156 | B160: ='02 原始数据'!B160 | C160: ='02 原始数据'!D160 | D160: =IF(OR(C160="",C159=""),"",C160-C159) | E160: =IF(OR(C160="",C159=""),"",(C160-C159)/ABS(C159)) | F160: ='02 原始数据'!G160 | G160: =IF(OR(F160="",F159=""),"",F160-F159) | H160: =IF(OR(F160="",F159=""),"",(F160-F159)/ABS(F159)) | I160: ='02 原始数据'!H160 | J160: ='02 原始数据'!I160 | K160: =IFERROR(IF(C160="","",C160/'02 原始数据'!K160),"")

Sheet 05 总体相关
A1: 总体相关系数（Excel 原生公式，可在表内直接重算）
A2: 五种形态组合齐列，避免“只用一种口径下结论”。p 用 T.DIST.2T，R² 用 RSQ，N 用 COUNT 系列函数统计有效数。
B4: 组合 | C4: Pearson r | D4: N | E4: R² | F4: t 统计量 | G4: p 值（双侧） | H4: 判定
B5: ① 库存水平 × 价格水平 | C5: =IFERROR(CORREL('04 变换后数据'!$C$5:$C$160,'04 变换后数据'!$F$5:$F$160),"样本不足") | D5: =SUMPRODUCT(--ISNUMBER('04 变换后数据'!$C$5:$C$160),--ISNUMBER('04 变换后数据'!$F$5:$F$160)) | E5: =IFERROR(C5^2,"") | F5: =IFERROR(C5*SQRT((D5-2)/(1-C5^2)),"") | G5: =IFERROR(_XLFN.T.DIST.2T(ABS(F5),D5-2),"") | H5: =IF(G5="","",IF(G5<0.01,"显著(1%)",IF(G5<0.05,"显著(5%)",IF(G5<0.1,"边际(10%)","不显著"))))
B6: ② 库存水平 × 价格环比% | C6: =IFERROR(CORREL('04 变换后数据'!$C$5:$C$160,'04 变换后数据'!$H$5:$H$160),"样本不足") | D6: =SUMPRODUCT(--ISNUMBER('04 变换后数据'!$C$5:$C$160),--ISNUMBER('04 变换后数据'!$H$5:$H$160)) | E6: =IFERROR(C6^2,"") | F6: =IFERROR(C6*SQRT((D6-2)/(1-C6^2)),"") | G6: =IFERROR(_XLFN.T.DIST.2T(ABS(F6),D6-2),"") | H6: =IF(G6="","",IF(G6<0.01,"显著(1%)",IF(G6<0.05,"显著(5%)",IF(G6<0.1,"边际(10%)","不显著"))))
B7: ③ 库存差分 × 价格环比% | C7: =IFERROR(CORREL('04 变换后数据'!$D$5:$D$160,'04 变换后数据'!$H$5:$H$160),"样本不足") | D7: =SUMPRODUCT(--ISNUMBER('04 变换后数据'!$D$5:$D$160),--ISNUMBER('04 变换后数据'!$H$5:$H$160)) | E7: =IFERROR(C7^2,"") | F7: =IFERROR(C7*SQRT((D7-2)/(1-C7^2)),"") | G7: =IFERROR(_XLFN.T.DIST.2T(ABS(F7),D7-2),"") | H7: =IF(G7="","",IF(G7<0.01,"显著(1%)",IF(G7<0.05,"显著(5%)",IF(G7<0.1,"边际(10%)","不显著"))))
B8: ④ 库存差分 × 价格差分 | C8: =IFERROR(CORREL('04 变换后数据'!$D$5:$D$160,'04 变换后数据'!$G$5:$G$160),"样本不足") | D8: =SUMPRODUCT(--ISNUMBER('04 变换后数据'!$D$5:$D$160),--ISNUMBER('04 变换后数据'!$G$5:$G$160)) | E8: =IFERROR(C8^2,"") | F8: =IFERROR(C8*SQRT((D8-2)/(1-C8^2)),"") | G8: =IFERROR(_XLFN.T.DIST.2T(ABS(F8),D8-2),"") | H8: =IF(G8="","",IF(G8<0.01,"显著(1%)",IF(G8<0.05,"显著(5%)",IF(G8<0.1,"边际(10%)","不显著"))))
B9: ⑤ 库存环比% × 价格环比% | C9: =IFERROR(CORREL('04 变换后数据'!$E$5:$E$160,'04 变换后数据'!$H$5:$H$160),"样本不足") | D9: =SUMPRODUCT(--ISNUMBER('04 变换后数据'!$E$5:$E$160),--ISNUMBER('04 变换后数据'!$H$5:$H$160)) | E9: =IFERROR(C9^2,"") | F9: =IFERROR(C9*SQRT((D9-2)/(1-C9^2)),"") | G9: =IFERROR(_XLFN.T.DIST.2T(ABS(F9),D9-2),"") | H9: =IF(G9="","",IF(G9<0.01,"显著(1%)",IF(G9<0.05,"显著(5%)",IF(G9<0.1,"边际(10%)","不显著"))))
B11: N 的算法 | C11: SUMPRODUCT(--ISNUMBER(x),--ISNUMBER(y)) 统计“两列同时有数”的期数；缺失用 NA() 表示，CORREL 会自动跳过缺配对，不会把缺失当 0。
B12: p 值的含义 | C12: “若总体真实相关为 0，出现这么极端样本的概率”。p 小只说明不像偶然；相关强不强看 |r|，是不是因果与 p 无关。
B13: 为什么列五种组合 | C13: 同一对指标换个形态，r 可能完全不同。只报一种口径的相关系数，无法被复核。

Sheet 06 滚动相关
A1: 滚动相关系数（12 / 26 / 52 周；主口径：库存差分 × 价格环比%）
A2: 每行对应窗口末端日期。窗口内有效配对数低于“最小样本数”时输出空白，不外推、不插值。改第 3 行窗口参数后整表自动重算。
B3: 12周窗口 | C3: 12 | D3: 26周窗口 | E3: 26 | F3: 52周窗口 | G3: 52
A4: 序号 | B4: 窗口末端日期 | C4: 12周 r | D4: 12周 N | E4: 26周 r | F4: 26周 N | G4: 52周 r | H4: 52周 N | I4: 主口径强度
A5: 1 | B5: ='04 变换后数据'!B5 | C5: =IF(1<$C$3,"",IF(45=0,"",IF(45<MAX(5,ROUND($C$3*0.8,0)),"样本不足",CORREL(OFFSET('04 变换后数据'!$D$5:$D$160,ROW()-5-$C$3+1,0,$C$3,1),OFFSET('04 变换后数据'!$H$5:$H$160,ROW()-5-$C$3+1,0,$C$3,1)))) | D5: =IF(1<$C$3,0,SUMPRODUCT(--(ROW('04 变换后数据'!$D$5:$D$160)<=ROW()),--ISNUMBER(OFFSET('04 变换后数据'!$D$5:$D$160,ROW()-5-$C$3+1,0,MIN($C$3,ROW()-4),1)),--ISNUMBER(OFFSET('04 变换后数据'!$H$5:$H$160,ROW()-5-$C$3+1,0,MIN($C$3,ROW()-4),1)))) | E5: =IF(1<$E$3,"",IF(65=0,"",IF(65<MAX(5,ROUND($E$3*0.8,0)),"样本不足",CORREL(OFFSET('04 变换后数据'!$D$5:$D$160,ROW()-5-$E$3+1,0,$E$3,1),OFFSET('04 变换后数据'!$H$5:$H$160,ROW()-5-$E$3+1,0,$E$3,1)))) | F5: =IF(1<$E$3,0,SUMPRODUCT(--(ROW('04 变换后数据'!$D$5:$D$160)<=ROW()),--ISNUMBER(OFFSET('04 变换后数据'!$D$5:$D$160,ROW()-5-$E$3+1,0,MIN($E$3,ROW()-4),1)),--ISNUMBER(OFFSET('04 变换后数据'!$H$5:$H$160,ROW()-5-$E$3+1,0,MIN($E$3,ROW()-4),1)))) | G5: =IF(1<$G$3,"",IF(85=0,"",IF(85<MAX(5,ROUND($G$3*0.8,0)),"样本不足",CORREL(OFFSET('04 变换后数据'!$D$5:$D$160,ROW()-5-$G$3+1,0,$G$3,1),OFFSET('04 变换后数据'!$H$5:$H$160,ROW()-5-$G$3+1,0,$G$3,1)))) | H5: =IF(1<$G$3,0,SUMPRODUCT(--(ROW('04 变换后数据'!$D$5:$D$160)<=ROW()),--ISNUMBER(OFFSET('04 变换后数据'!$D$5:$D$160,ROW()-5-$G$3+1,0,MIN($G$3,ROW()-4),1)),--ISNUMBER(OFFSET('04 变换后数据'!$H$5:$H$160,ROW()-5-$G$3+1,0,MIN($G$3,ROW()-4),1)))) | I5: =IF(ISNUMBER(E5),IF(ABS(E5)>=0.7,"强",IF(ABS(E5)>=0.4,"中","弱")),"-")
A6: 2 | B6: ='04 变换后数据'!B6 | C6: =IF(2<$C$3,"",IF(46=0,"",IF(46<MAX(5,ROUND($C$3*0.8,0)),"样本不足",CORREL(OFFSET('04 变换后数据'!$D$5:$D$160,ROW()-5-$C$3+1,0,$C$3,1),OFFSET('04 变换后数据'!$H$5:$H$160,ROW()-5-$C$3+1,0,$C$3,1)))) | D6: =IF(2<$C$3,0,SUMPRODUCT(--(ROW('04 变换后数据'!$D$5:$D$160)<=ROW()),--ISNUMBER(OFFSET('04 变换后数据'!$D$5:$D$160,ROW()-5-$C$3+1,0,MIN($C$3,ROW()-4),1)),--ISNUMBER(OFFSET('04 变换后数据'!$H$5:$H$160,ROW()-5-$C$3+1,0,MIN($C$3,ROW()-4),1)))) | E6: =IF(2<$E$3,"",IF(66=0,"",IF(66<MAX(5,ROUND($E$3*0.8,0)),"样本不足",CORREL(OFFSET('04 变换后数据'!$D$5:$D$160,ROW()-5-$E$3+1,0,$E$3,1),OFFSET('04 变换后数据'!$H$5:$H$160,ROW()-5-$E$3+1,0,$E$3,1)))) | F6: =IF(2<$E$3,0,SUMPRODUCT(--(ROW('04 变换后数据'!$D$5:$D$160)<=ROW()),--ISNUMBER(OFFSET('04 变换后数据'!$D$5:$D$160,ROW()-5-$E$3+1,0,MIN($E$3,ROW()-4),1)),--ISNUMBER(OFFSET('04 变换后数据'!$H$5:$H$160,ROW()-5-$E$3+1,0,MIN($E$3,ROW()-4),1)))) | G6: =IF(2<$G$3,"",IF(86=0,"",IF(86<MAX(5,ROUND($G$3*0.8,0)),"样本不足",CORREL(OFFSET('04 变换后数据'!$D$5:$D$160,ROW()-5-$G$3+1,0,$G$3,1),OFFSET('04 变换后数据'!$H$5:$H$160,ROW()-5-$G$3+1,0,$G$3,1)))) | H6: =IF(2<$G$3,0,SUMPRODUCT(--(ROW('04 变换后数据'!$D$5:$D$160)<=ROW()),--ISNUMBER(OFFSET('04 变换后数据'!$D$5:$D$160,ROW()-5-$G$3+1,0,MIN($G$3,ROW()-4),1)),--ISNUMBER(OFFSET('04 变换后数据'!$H$5:$H$160,ROW()-5-$G$3+1,0,MIN($G$3,ROW()-4),1)))) | I6: =IF(ISNUMBER(E6),IF(ABS(E6)>=0.7,"强",IF(ABS(E6)>=0.4,"中","弱")),"-")
A7: 3 | B7: ='04 变换后数据'!B7 | C7: =IF(3<$C$3,"",IF(47=0,"",IF(47<MAX(5,ROUND($C$3*0.8,0)),"样本不足",CORREL(OFFSET('04 变换后数据'!$D$5:$D$160,ROW()-5-$C$3+1,0,$C$3,1),OFFSET('04 变换后数据'!$H$5:$H$160,ROW()-5-$C$3+1,0,$C$3,1)))) | D7: =IF(3<$C$3,0,SUMPRODUCT(--(ROW('04 变换后数据'!$D$5:$D$160)<=ROW()),--ISNUMBER(OFFSET('04 变换后数据'!$D$5:$D$160,ROW()-5-$C$3+1,0,MIN($C$3,ROW()-4),1)),--ISNUMBER(OFFSET('04 变换后数据'!$H$5:$H$160,ROW()-5-$C$3+1,0,MIN($C$3,ROW()-4),1)))) | E7: =IF(3<$E$3,"",IF(67=0,"",IF(67<MAX(5,ROUND($E$3*0.8,0)),"样本不足",CORREL(OFFSET('04 变换后数据'!$D$5:$D$160,ROW()-5-$E$3+1,0,$E$3,1),OFFSET('04 变换后数据'!$H$5:$H$160,ROW()-5-$E$3+1,0,$E$3,1)))) | F7: =IF(3<$E$3,0,SUMPRODUCT(--(ROW('04 变换后数据'!$D$5:$D$160)<=ROW()),--ISNUMBER(OFFSET('04 变换后数据'!$D$5:$D$160,ROW()-5-$E$3+1,0,MIN($E$3,ROW()-4),1)),--ISNUMBER(OFFSET('04 变换后数据'!$H$5:$H$160,ROW()-5-$E$3+1,0,MIN($E$3,ROW()-4),1)))) | G7: =IF(3<$G$3,"",IF(87=0,"",IF(87<MAX(5,ROUND($G$3*0.8,0)),"样本不足",CORREL(OFFSET('04 变换后数据'!$D$5:$D$160,ROW()-5-$G$3+1,0,$G$3,1),OFFSET('04 变换后数据'!$H$5:$H$160,ROW()-5-$G$3+1,0,$G$3,1)))) | H7: =IF(3<$G$3,0,SUMPRODUCT(--(ROW('04 变换后数据'!$D$5:$D$160)<=ROW()),--ISNUMBER(OFFSET('04 变换后数据'!$D$5:$D$160,ROW()-5-$G$3+1,0,MIN($G$3,ROW()-4),1)),--ISNUMBER(OFFSET('04 变换后数据'!$H$5:$H$160,ROW()-5-$G$3+1,0,MIN($G$3,ROW()-4),1)))) | I7: =IF(ISNUMBER(E7),IF(ABS(E7)>=0.7,"强",IF(ABS(E7)>=0.4,"中","弱")),"-")
A8: 4 | B8: ='04 变换后数据'!B8 | C8: =IF(4<$C$3,"",IF(48=0,"",IF(48<MAX(5,ROUND($C$3*0.8,0)),"样本不足",CORREL(OFFSET('04 变换后数据'!$D$5:$D$160,ROW()-5-$C$3+1,0,$C$3,1),OFFSET('04 变换后数据'!$H$5:$H$160,ROW()-5-$C$3+1,0,$C$3,1)))) | D8: =IF(4<$C$3,0,SUMPRODUCT(--(ROW('04 变换后数据'!$D$5:$D$160)<=ROW()),--ISNUMBER(OFFSET('04 变换后数据'!$D$5:$D$160,ROW()-5-$C$3+1,0,MIN($C$3,ROW()-4),1)),--ISNUMBER(OFFSET('04 变换后数据'!$H$5:$H$160,ROW()-5-$C$3+1,0,MIN($C$3,ROW()-4),1)))) | E8: =IF(4<$E$3,"",IF(68=0,"",IF(68<MAX(5,ROUND($E$3*0.8,0)),"样本不足",CORREL(OFFSET('04 变换后数据'!$D$5:$D$160,ROW()-5-$E$3+1,0,$E$3,1),OFFSET('04 变换后数据'!$H$5:$H$160,ROW()-5-$E$3+1,0,$E$3,1)))) | F8: =IF(4<$E$3,0,SUMPRODUCT(--(ROW('04 变换后数据'!$D$5:$D$160)<=ROW()),--ISNUMBER(OFFSET('04 变换后数据'!$D$5:$D$160,ROW()-5-$E$3+1,0,MIN($E$3,ROW()-4),1)),--ISNUMBER(OFFSET('04 变换后数据'!$H$5:$H$160,ROW()-5-$E$3+1,0,MIN($E$3,ROW()-4),1)))) | G8: =IF(4<$G$3,"",IF(88=0,"",IF(88<MAX(5,ROUND($G$3*0.8,0)),"样本不足",CORREL(OFFSET('04 变换后数据'!$D$5:$D$160,ROW()-5-$G$3+1,0,$G$3,1),OFFSET('04 变换后数据'!$H$5:$H$160,ROW()-5-$G$3+1,0,$G$3,1)))) | H8: =IF(4<$G$3,0,SUMPRODUCT(--(ROW('04 变换后数据'!$D$5:$D$160)<=ROW()),--ISNUMBER(OFFSET('04 变换后数据'!$D$5:$D$160,ROW()-5-$G$3+1,0,MIN($G$3,ROW()-4),1)),--ISNUMBER(OFFSET('04 变换后数据'!$H$5:$H$160,ROW()-5-$G$3+1,0,MIN($G$3,ROW()-4),1)))) | I8: =IF(ISNUMBER(E8),IF(ABS(E8)>=0.7,"强",IF(ABS(E8)>=0.4,"中","弱")),"-")
A9: 5 | B9: ='04 变换后数据'!B9 | C9: =IF(5<$C$3,"",IF(49=0,"",IF(49<MAX(5,ROUND($C$3*0.8,0)),"样本不足",CORREL(OFFSET('04 变换后数据'!$D$5:$D$160,ROW()-5-$C$3+1,0,$C$3,1),OFFSET('04 变换后数据'!$H$5:$H$160,ROW()-5-$C$3+1,0,$C$3,1)))) | D9: =IF(5<$C$3,0,SUMPRODUCT(--(ROW('04 变换后数据'!$D$5:$D$160)<=ROW()),--ISNUMBER(OFFSET('04 变换后数据'!$D$5:$D$160,ROW()-5-$C$3+1,0,MIN($C$3,ROW()-4),1)),--ISNUMBER(OFFSET('04 变换后数据'!$H$5:$H$160,ROW()-5-$C$3+1,0,MIN($C$3,ROW()-4),1)))) | E9: =IF(5<$E$3,"",IF(69=0,"",IF(69<MAX(5,ROUND($E$3*0.8,0)),"样本不足",CORREL(OFFSET('04 变换后数据'!$D$5:$D$160,ROW()-5-$E$3+1,0,$E$3,1),OFFSET('04 变换后数据'!$H$5:$H$160,ROW()-5-$E$3+1,0,$E$3,1)))) | F9: =IF(5<$E$3,0,SUMPRODUCT(--(ROW('04 变换后数据'!$D$5:$D$160)<=ROW()),--ISNUMBER(OFFSET('04 变换后数据'!$D$5:$D$160,ROW()-5-$E$3+1,0,MIN($E$3,ROW()-4),1)),--ISNUMBER(OFFSET('04 变换后数据'!$H$5:$H$160,ROW()-5-$E$3+1,0,MIN($E$3,ROW()-4),1)))) | G9: =IF(5<$G$3,"",IF(89=0,"",IF(89<MAX(5,ROUND($G$3*0.8,0)),"样本不足",CORREL(OFFSET('04 变换后数据'!$D$5:$D$160,ROW()-5-$G$3+1,0,$G$3,1),OFFSET('04 变换后数据'!$H$5:$H$160,ROW()-5-$G$3+1,0,$G$3,1)))) | H9: =IF(5<$G$3,0,SUMPRODUCT(--(ROW('04 变换后数据'!$D$5:$D$160)<=ROW()),--ISNUMBER(OFFSET('04 变换后数据'!$D$5:$D$160,ROW()-5-$G$3+1,0,MIN($G$3,ROW()-4),1)),--ISNUMBER(OFFSET('04 变换后数据'!$H$5:$H$160,ROW()-5-$G$3+1,0,MIN($G$3,ROW()-4),1)))) | I9: =IF(ISNUMBER(E9),IF(ABS(E9)>=0.7,"强",IF(ABS(E9)>=0.4,"中","弱")),"-")
A10: 6 | B10: ='04 变换后数据'!B10 | C10: =IF(6<$C$3,"",IF(410=0,"",IF(410<MAX(5,ROUND($C$3*0.8,0)),"样本不足",CORREL(OFFSET('04 变换后数据'!$D$5:$D$160,ROW()-5-$C$3+1,0,$C$3,1),OFFSET('04 变换后数据'!$H$5:$H$160,ROW()-5-$C$3+1,0,$C$3,1)))) | D10: =IF(6<$C$3,0,SUMPRODUCT(--(ROW('04 变换后数据'!$D$5:$D$160)<=ROW()),--ISNUMBER(OFFSET('04 变换后数据'!$D$5:$D$160,ROW()-5-$C$3+1,0,MIN($C$3,ROW()-4),1)),--ISNUMBER(OFFSET('04 变换后数据'!$H$5:$H$160,ROW()-5-$C$3+1,0,MIN($C$3,ROW()-4),1)))) | E10: =IF(6<$E$3,"",IF(610=0,"",IF(610<MAX(5,ROUND($E$3*0.8,0)),"样本不足",CORREL(OFFSET('04 变换后数据'!$D$5:$D$160,ROW()-5-$E$3+1,0,$E$3,1),OFFSET('04 变换后数据'!$H$5:$H$160,ROW()-5-$E$3+1,0,$E$3,1)))) | F10: =IF(6<$E$3,0,SUMPRODUCT(--(ROW('04 变换后数据'!$D$5:$D$160)<=ROW()),--ISNUMBER(OFFSET('04 变换后数据'!$D$5:$D$160,ROW()-5-$E$3+1,0,MIN($E$3,ROW()-4),1)),--ISNUMBER(OFFSET('04 变换后数据'!$H$5:$H$160,ROW()-5-$E$3+1,0,MIN($E$3,ROW()-4),1)))) | G10: =IF(6<$G$3,"",IF(810=0,"",IF(810<MAX(5,ROUND($G$3*0.8,0)),"样本不足",CORREL(OFFSET('04 变换后数据'!$D$5:$D$160,ROW()-5-$G$3+1,0,$G$3,1),OFFSET('04 变换后数据'!$H$5:$H$160,ROW()-5-$G$3+1,0,$G$3,1)))) | H10: =IF(6<$G$3,0,SUMPRODUCT(--(ROW('04 变换后数据'!$D$5:$D$160)<=ROW()),--ISNUMBER(OFFSET('04 变换后数据'!$D$5:$D$160,ROW()-5-$G$3+1,0,MIN($G$3,ROW()-4),1)),--ISNUMBER(OFFSET('04 变换后数据'!$H$5:$H$160,ROW()-5-$G$3+1,0,MIN($G$3,ROW()-4),1)))) | I10: =IF(ISNUMBER(E10),IF(ABS(E10)>=0.7,"强",IF(ABS(E10)>=0.4,"中","弱")),"-")
A11: 7 | B11: ='04 变换后数据'!B11 | C11: =IF(7<$C$3,"",IF(411=0,"",IF(411<MAX(5,ROUND($C$3*0.8,0)),"样本不足",CORREL(OFFSET('04 变换后数据'!$D$5:$D$160,ROW()-5-$C$3+1,0,$C$3,1),OFFSET('04 变换后数据'!$H$5:$H$160,ROW()-5-$C$3+1,0,$C$3,1)))) | D11: =IF(7<$C$3,0,SUMPRODUCT(--(ROW('04 变换后数据'!$D$5:$D$160)<=ROW()),--ISNUMBER(OFFSET('04 变换后数据'!$D$5:$D$160,ROW()-5-$C$3+1,0,MIN($C$3,ROW()-4),1)),--ISNUMBER(OFFSET('04 变换后数据'!$H$5:$H$160,ROW()-5-$C$3+1,0,MIN($C$3,ROW()-4),1)))) | E11: =IF(7<$E$3,"",IF(611=0,"",IF(611<MAX(5,ROUND($E$3*0.8,0)),"样本不足",CORREL(OFFSET('04 变换后数据'!$D$5:$D$160,ROW()-5-$E$3+1,0,$E$3,1),OFFSET('04 变换后数据'!$H$5:$H$160,ROW()-5-$E$3+1,0,$E$3,1)))) | F11: =IF(7<$E$3,0,SUMPRODUCT(--(ROW('04 变换后数据'!$D$5:$D$160)<=ROW()),--ISNUMBER(OFFSET('04 变换后数据'!$D$5:$D$160,ROW()-5-$E$3+1,0,MIN($E$3,ROW()-4),1)),--ISNUMBER(OFFSET('04 变换后数据'!$H$5:$H$160,ROW()-5-$E$3+1,0,MIN($E$3,ROW()-4),1)))) | G11: =IF(7<$G$3,"",IF(811=0,"",IF(811<MAX(5,ROUND($G$3*0.8,0)),"样本不足",CORREL(OFFSET('04 变换后数据'!$D$5:$D$160,ROW()-5-$G$3+1,0,$G$3,1),OFFSET('04 变换后数据'!$H$5:$H$160,ROW()-5-$G$3+1,0,$G$3,1)))) | H11: =IF(7<$G$3,0,SUMPRODUCT(--(ROW('04 变换后数据'!$D$5:$D$160)<=ROW()),--ISNUMBER(OFFSET('04 变换后数据'!$D$5:$D$160,ROW()-5-$G$3+1,0,MIN($G$3,ROW()-4),1)),--ISNUMBER(OFFSET('04 变换后数据'!$H$5:$H$160,ROW()-5-$G$3+1,0,MIN($G$3,ROW()-4),1)))) | I11: =IF(ISNUMBER(E11),IF(ABS(E11)>=0.7,"强",IF(ABS(E11)>=0.4,"中","弱")),"-")
A12: 8 | B12: ='04 变换后数据'!B12 | C12: =IF(8<$C$3,"",IF(412=0,"",IF(412<MAX(5,ROUND($C$3*0.8,0)),"样本不足",CORREL(OFFSET('04 变换后数据'!$D$5:$D$160,ROW()-5-$C$3+1,0,$C$3,1),OFFSET('04 变换后数据'!$H$5:$H$160,ROW()-5-$C$3+1,0,$C$3,1)))) | D12: =IF(8<$C$3,0,SUMPRODUCT(--(ROW('04 变换后数据'!$D$5:$D$160)<=ROW()),--ISNUMBER(OFFSET('04 变换后数据'!$D$5:$D$160,ROW()-5-$C$3+1,0,MIN($C$3,ROW()-4),1)),--ISNUMBER(OFFSET('04 变换后数据'!$H$5:$H$160,ROW()-5-$C$3+1,0,MIN($C$3,ROW()-4),1)))) | E12: =IF(8<$E$3,"",IF(612=0,"",IF(612<MAX(5,ROUND($E$3*0.8,0)),"样本不足",CORREL(OFFSET('04 变换后数据'!$D$5:$D$160,ROW()-5-$E$3+1,0,$E$3,1),OFFSET('04 变换后数据'!$H$5:$H$160,ROW()-5-$E$3+1,0,$E$3,1)))) | F12: =IF(8<$E$3,0,SUMPRODUCT(--(ROW('04 变换后数据'!$D$5:$D$160)<=ROW()),--ISNUMBER(OFFSET('04 变换后数据'!$D$5:$D$160,ROW()-5-$E$3+1,0,MIN($E$3,ROW()-4),1)),--ISNUMBER(OFFSET('04 变换后数据'!$H$5:$H$160,ROW()-5-$E$3+1,0,MIN($E$3,ROW()-4),1)))) | G12: =IF(8<$G$3,"",IF(812=0,"",IF(812<MAX(5,ROUND($G$3*0.8,0)),"样本不足",CORREL(OFFSET('04 变换后数据'!$D$5:$D$160,ROW()-5-$G$3+1,0,$G$3,1),OFFSET('04 变换后数据'!$H$5:$H$160,ROW()-5-$G$3+1,0,$G$3,1)))) | H12: =IF(8<$G$3,0,SUMPRODUCT(--(ROW('04 变换后数据'!$D$5:$D$160)<=ROW()),--ISNUMBER(OFFSET('04 变换后数据'!$D$5:$D$160,ROW()-5-$G$3+1,0,MIN($G$3,ROW()-4),1)),--ISNUMBER(OFFSET('04 变换后数据'!$H$5:$H$160,ROW()-5-$G$3+1,0,MIN($G$3,ROW()-4),1)))) | I12: =IF(ISNUMBER(E12),IF(ABS(E12)>=0.7,"强",IF(ABS(E12)>=0.4,"中","弱")),"-")
A13: 9 | B13: ='04 变换后数据'!B13 | C13: =IF(9<$C$3,"",IF(413=0,"",IF(413<MAX(5,ROUND($C$3*0.8,0)),"样本不足",CORREL(OFFSET('04 变换后数据'!$D$5:$D$160,ROW()-5-$C$3+1,0,$C$3,1),OFFSET('04 变换后数据'!$H$5:$H$160,ROW()-5-$C$3+1,0,$C$3,1)))) | D13: =IF(9<$C$3,0,SUMPRODUCT(--(ROW('04 变换后数据'!$D$5:$D$160)<=ROW()),--ISNUMBER(OFFSET('04 变换后数据'!$D$5:$D$160,ROW()-5-$C$3+1,0,MIN($C$3,ROW()-4),1)),--ISNUMBER(OFFSET('04 变换后数据'!$H$5:$H$160,ROW()-5-$C$3+1,0,MIN($C$3,ROW()-4),1)))) | E13: =IF(9<$E$3,"",IF(613=0,"",IF(613<MAX(5,ROUND($E$3*0.8,0)),"样本不足",CORREL(OFFSET('04 变换后数据'!$D$5:$D$160,ROW()-5-$E$3+1,0,$E$3,1),OFFSET('04 变换后数据'!$H$5:$H$160,ROW()-5-$E$3+1,0,$E$3,1)))) | F13: =IF(9<$E$3,0,SUMPRODUCT(--(ROW('04 变换后数据'!$D$5:$D$160)<=ROW()),--ISNUMBER(OFFSET('04 变换后数据'!$D$5:$D$160,ROW()-5-$E$3+1,0,MIN($E$3,ROW()-4),1)),--ISNUMBER(OFFSET('04 变换后数据'!$H$5:$H$160,ROW()-5-$E$3+1,0,MIN($E$3,ROW()-4),1)))) | G13: =IF(9<$G$3,"",IF(813=0,"",IF(813<MAX(5,ROUND($G$3*0.8,0)),"样本不足",CORREL(OFFSET('04 变换后数据'!$D$5:$D$160,ROW()-5-$G$3+1,0,$G$3,1),OFFSET('04 变换后数据'!$H$5:$H$160,ROW()-5-$G$3+1,0,$G$3,1)))) | H13: =IF(9<$G$3,0,SUMPRODUCT(--(ROW('04 变换后数据'!$D$5:$D$160)<=ROW()),--ISNUMBER(OFFSET('04 变换后数据'!$D$5:$D$160,ROW()-5-$G$3+1,0,MIN($G$3,ROW()-4),1)),--ISNUMBER(OFFSET('04 变换后数据'!$H$5:$H$160,ROW()-5-$G$3+1,0,MIN($G$3,ROW()-4),1)))) | I13: =IF(ISNUMBER(E13),IF(ABS(E13)>=0.7,"强",IF(ABS(E13)>=0.4,"中","弱")),"-")
A14: 10 | B14: ='04 变换后数据'!B14 | C14: =IF(10<$C$3,"",IF(414=0,"",IF(414<MAX(5,ROUND($C$3*0.8,0)),"样本不足",CORREL(OFFSET('04 变换后数据'!$D$5:$D$160,ROW()-5-$C$3+1,0,$C$3,1),OFFSET('04 变换后数据'!$H$5:$H$160,ROW()-5-$C$3+1,0,$C$3,1)))) | D14: =IF(10<$C$3,0,SUMPRODUCT(--(ROW('04 变换后数据'!$D$5:$D$160)<=ROW()),--ISNUMBER(OFFSET('04 变换后数据'!$D$5:$D$160,ROW()-5-$C$3+1,0,MIN($C$3,ROW()-4),1)),--ISNUMBER(OFFSET('04 变换后数据'!$H$5:$H$160,ROW()-5-$C$3+1,0,MIN($C$3,ROW()-4),1)))) | E14: =IF(10<$E$3,"",IF(614=0,"",IF(614<MAX(5,ROUND($E$3*0.8,0)),"样本不足",CORREL(OFFSET('04 变换后数据'!$D$5:$D$160,ROW()-5-$E$3+1,0,$E$3,1),OFFSET('04 变换后数据'!$H$5:$H$160,ROW()-5-$E$3+1,0,$E$3,1)))) | F14: =IF(10<$E$3,0,SUMPRODUCT(--(ROW('04 变换后数据'!$D$5:$D$160)<=ROW()),--ISNUMBER(OFFSET('04 变换后数据'!$D$5:$D$160,ROW()-5-$E$3+1,0,MIN($E$3,ROW()-4),1)),--ISNUMBER(OFFSET('04 变换后数据'!$H$5:$H$160,ROW()-5-$E$3+1,0,MIN($E$3,ROW()-4),1)))) | G14: =IF(10<$G$3,"",IF(814=0,"",IF(814<MAX(5,ROUND($G$3*0.8,0)),"样本不足",CORREL(OFFSET('04 变换后数据'!$D$5:$D$160,ROW()-5-$G$3+1,0,$G$3,1),OFFSET('04 变换后数据'!$H$5:$H$160,ROW()-5-$G$3+1,0,$G$3,1)))) | H14: =IF(10<$G$3,0,SUMPRODUCT(--(ROW('04 变换后数据'!$D$5:$D$160)<=ROW()),--ISNUMBER(OFFSET('04 变换后数据'!$D$5:$D$160,ROW()-5-$G$3+1,0,MIN($G$3,ROW()-4),1)),--ISNUMBER(OFFSET('04 变换后数据'!$H$5:$H$160,ROW()-5-$G$3+1,0,MIN($G$3,ROW()-4),1)))) | I14: =IF(ISNUMBER(E14),IF(ABS(E14)>=0.7,"强",IF(ABS(E14)>=0.4,"中","弱")),"-")
A15: 11 | B15: ='04 变换后数据'!B15 | C15: =IF(11<$C$3,"",IF(415=0,"",IF(415<MAX(5,ROUND($C$3*0.8,0)),"样本不足",CORREL(OFFSET('04 变换后数据'!$D$5:$D$160,ROW()-5-$C$3+1,0,$C$3,1),OFFSET('04 变换后数据'!$H$5:$H$160,ROW()-5-$C$3+1,0,$C$3,1)))) | D15: =IF(11<$C$3,0,SUMPRODUCT(--(ROW('04 变换后数据'!$D$5:$D$160)<=ROW()),--ISNUMBER(OFFSET('04 变换后数据'!$D$5:$D$160,ROW()-5-$C$3+1,0,MIN($C$3,ROW()-4),1)),--ISNUMBER(OFFSET('04 变换后数据'!$H$5:$H$160,ROW()-5-$C$3+1,0,MIN($C$3,ROW()-4),1)))) | E15: =IF(11<$E$3,"",IF(615=0,"",IF(615<MAX(5,ROUND($E$3*0.8,0)),"样本不足",CORREL(OFFSET('04 变换后数据'!$D$5:$D$160,ROW()-5-$E$3+1,0,$E$3,1),OFFSET('04 变换后数据'!$H$5:$H$160,ROW()-5-$E$3+1,0,$E$3,1)))) | F15: =IF(11<$E$3,0,SUMPRODUCT(--(ROW('04 变换后数据'!$D$5:$D$160)<=ROW()),--ISNUMBER(OFFSET('04 变换后数据'!$D$5:$D$160,ROW()-5-$E$3+1,0,MIN($E$3,ROW()-4),1)),--ISNUMBER(OFFSET('04 变换后数据'!$H$5:$H$160,ROW()-5-$E$3+1,0,MIN($E$3,ROW()-4),1)))) | G15: =IF(11<$G$3,"",IF(815=0,"",IF(815<MAX(5,ROUND($G$3*0.8,0)),"样本不足",CORREL(OFFSET('04 变换后数据'!$D$5:$D$160,ROW()-5-$G$3+1,0,$G$3,1),OFFSET('04 变换后数据'!$H$5:$H$160,ROW()-5-$G$3+1,0,$G$3,1)))) | H15: =IF(11<$G$3,0,SUMPRODUCT(--(ROW('04 变换后数据'!$D$5:$D$160)<=ROW()),--ISNUMBER(OFFSET('04 变换后数据'!$D$5:$D$160,ROW()-5-$G$3+1,0,MIN($G$3,ROW()-4),1)),--ISNUMBER(OFFSET('04 变换后数据'!$H$5:$H$160,ROW()-5-$G$3+1,0,MIN($G$3,ROW()-4),1)))) | I15: =IF(ISNUMBER(E15),IF(ABS(E15)>=0.7,"强",IF(ABS(E15)>=0.4,"中","弱")),"-")
A16: 12 | B16: ='04 变换后数据'!B16 | C16: =IF(12<$C$3,"",IF(416=0,"",IF(416<MAX(5,ROUND($C$3*0.8,0)),"样本不足",CORREL(OFFSET('04 变换后数据'!$D$5:$D$160,ROW()-5-$C$3+1,0,$C$3,1),OFFSET('04 变换后数据'!$H$5:$H$160,ROW()-5-$C$3+1,0,$C$3,1)))) | D16: =IF(12<$C$3,0,SUMPRODUCT(--(ROW('04 变换后数据'!$D$5:$D$160)<=ROW()),--ISNUMBER(OFFSET('04 变换后数据'!$D$5:$D$160,ROW()-5-$C$3+1,0,MIN($C$3,ROW()-4),1)),--ISNUMBER(OFFSET('04 变换后数据'!$H$5:$H$160,ROW()-5-$C$3+1,0,MIN($C$3,ROW()-4),1)))) | E16: =IF(12<$E$3,"",IF(616=0,"",IF(616<MAX(5,ROUND($E$3*0.8,0)),"样本不足",CORREL(OFFSET('04 变换后数据'!$D$5:$D$160,ROW()-5-$E$3+1,0,$E$3,1),OFFSET('04 变换后数据'!$H$5:$H$160,ROW()-5-$E$3+1,0,$E$3,1)))) | F16: =IF(12<$E$3,0,SUMPRODUCT(--(ROW('04 变换后数据'!$D$5:$D$160)<=ROW()),--ISNUMBER(OFFSET('04 变换后数据'!$D$5:$D$160,ROW()-5-$E$3+1,0,MIN($E$3,ROW()-4),1)),--ISNUMBER(OFFSET('04 变换后数据'!$H$5:$H$160,ROW()-5-$E$3+1,0,MIN($E$3,ROW()-4),1)))) | G16: =IF(12<$G$3,"",IF(816=0,"",IF(816<MAX(5,ROUND($G$3*0.8,0)),"样本不足",CORREL(OFFSET('04 变换后数据'!$D$5:$D$160,ROW()-5-$G$3+1,0,$G$3,1),OFFSET('04 变换后数据'!$H$5:$H$160,ROW()-5-$G$3+1,0,$G$3,1)))) | H16: =IF(12<$G$3,0,SUMPRODUCT(--(ROW('04 变换后数据'!$D$5:$D$160)<=ROW()),--ISNUMBER(OFFSET('04 变换后数据'!$D$5:$D$160,ROW()-5-$G$3+1,0,MIN($G$3,ROW()-4),1)),--ISNUMBER(OFFSET('04 变换后数据'!$H$5:$H$160,ROW()-5-$G$3+1,0,MIN($G$3,ROW()-4),1)))) | I16: =IF(ISNUMBER(E16),IF(ABS(E16)>=0.7,"强",IF(ABS(E16)>=0.4,"中","弱")),"-")
A17: 13 | B17: ='04 变换后数据'!B17 | C17: =IF(13<$C$3,"",IF(417=0,"",IF(417<MAX(5,ROUND($C$3*0.8,0)),"样本不足",CORREL(OFFSET('04 变换后数据'!$D$5:$D$160,ROW()-5-$C$3+1,0,$C$3,1),OFFSET('04 变换后数据'!$H$5:$H$160,ROW()-5-$C$3+1,0,$C$3,1)))) | D17: =IF(13<$C$3,0,SUMPRODUCT(--(ROW('04 变换后数据'!$D$5:$D$160)<=ROW()),--ISNUMBER(OFFSET('04 变换后数据'!$D$5:$D$160,ROW()-5-$C$3+1,0,MIN($C$3,ROW()-4),1)),--ISNUMBER(OFFSET('04 变换后数据'!$H$5:$H$160,ROW()-5-$C$3+1,0,MIN($C$3,ROW()-4),1)))) | E17: =IF(13<$E$3,"",IF(617=0,"",IF(617<MAX(5,ROUND($E$3*0.8,0)),"样本不足",CORREL(OFFSET('04 变换后数据'!$D$5:$D$160,ROW()-5-$E$3+1,0,$E$3,1),OFFSET('04 变换后数据'!$H$5:$H$160,ROW()-5-$E$3+1,0,$E$3,1)))) | F17: =IF(13<$E$3,0,SUMPRODUCT(--(ROW('04 变换后数据'!$D$5:$D$160)<=ROW()),--ISNUMBER(OFFSET('04 变换后数据'!$D$5:$D$160,ROW()-5-$E$3+1,0,MIN($E$3,ROW()-4),1)),--ISNUMBER(OFFSET('04 变换后数据'!$H$5:$H$160,ROW()-5-$E$3+1,0,MIN($E$3,ROW()-4),1)))) | G17: =IF(13<$G$3,"",IF(817=0,"",IF(817<MAX(5,ROUND($G$3*0.8,0)),"样本不足",CORREL(OFFSET('04 变换后数据'!$D$5:$D$160,ROW()-5-$G$3+1,0,$G$3,1),OFFSET('04 变换后数据'!$H$5:$H$160,ROW()-5-$G$3+1,0,$G$3,1)))) | H17: =IF(13<$G$3,0,SUMPRODUCT(--(ROW('04 变换后数据'!$D$5:$D$160)<=ROW()),--ISNUMBER(OFFSET('04 变换后数据'!$D$5:$D$160,ROW()-5-$G$3+1,0,MIN($G$3,ROW()-4),1)),--ISNUMBER(OFFSET('04 变换后数据'!$H$5:$H$160,ROW()-5-$G$3+1,0,MIN($G$3,ROW()-4),1)))) | I17: =IF(ISNUMBER(E17),IF(ABS(E17)>=0.7,"强",IF(ABS(E17)>=0.4,"中","弱")),"-")
A18: 14 | B18: ='04 变换后数据'!B18 | C18: =IF(14<$C$3,"",IF(418=0,"",IF(418<MAX(5,ROUND($C$3*0.8,0)),"样本不足",CORREL(OFFSET('04 变换后数据'!$D$5:$D$160,ROW()-5-$C$3+1,0,$C$3,1),OFFSET('04 变换后数据'!$H$5:$H$160,ROW()-5-$C$3+1,0,$C$3,1)))) | D18: =IF(14<$C$3,0,SUMPRODUCT(--(ROW('04 变换后数据'!$D$5:$D$160)<=ROW()),--ISNUMBER(OFFSET('04 变换后数据'!$D$5:$D$160,ROW()-5-$C$3+1,0,MIN($C$3,ROW()-4),1)),--ISNUMBER(OFFSET('04 变换后数据'!$H$5:$H$160,ROW()-5-$C$3+1,0,MIN($C$3,ROW()-4),1)))) | E18: =IF(14<$E$3,"",IF(618=0,"",IF(618<MAX(5,ROUND($E$3*0.8,0)),"样本不足",CORREL(OFFSET('04 变换后数据'!$D$5:$D$160,ROW()-5-$E$3+1,0,$E$3,1),OFFSET('04 变换后数据'!$H$5:$H$160,ROW()-5-$E$3+1,0,$E$3,1)))) | F18: =IF(14<$E$3,0,SUMPRODUCT(--(ROW('04 变换后数据'!$D$5:$D$160)<=ROW()),--ISNUMBER(OFFSET('04 变换后数据'!$D$5:$D$160,ROW()-5-$E$3+1,0,MIN($E$3,ROW()-4),1)),--ISNUMBER(OFFSET('04 变换后数据'!$H$5:$H$160,ROW()-5-$E$3+1,0,MIN($E$3,ROW()-4),1)))) | G18: =IF(14<$G$3,"",IF(818=0,"",IF(818<MAX(5,ROUND($G$3*0.8,0)),"样本不足",CORREL(OFFSET('04 变换后数据'!$D$5:$D$160,ROW()-5-$G$3+1,0,$G$3,1),OFFSET('04 变换后数据'!$H$5:$H$160,ROW()-5-$G$3+1,0,$G$3,1)))) | H18: =IF(14<$G$3,0,SUMPRODUCT(--(ROW('04 变换后数据'!$D$5:$D$160)<=ROW()),--ISNUMBER(OFFSET('04 变换后数据'!$D$5:$D$160,ROW()-5-$G$3+1,0,MIN($G$3,ROW()-4),1)),--ISNUMBER(OFFSET('04 变换后数据'!$H$5:$H$160,ROW()-5-$G$3+1,0,MIN($G$3,ROW()-4),1)))) | I18: =IF(ISNUMBER(E18),IF(ABS(E18)>=0.7,"强",IF(ABS(E18)>=0.4,"中","弱")),"-")
A19: 15 | B19: ='04 变换后数据'!B19 | C19: =IF(15<$C$3,"",IF(419=0,"",IF(419<MAX(5,ROUND($C$3*0.8,0)),"样本不足",CORREL(OFFSET('04 变换后数据'!$D$5:$D$160,ROW()-5-$C$3+1,0,$C$3,1),OFFSET('04 变换后数据'!$H$5:$H$160,ROW()-5-$C$3+1,0,$C$3,1)))) | D19: =IF(15<$C$3,0,SUMPRODUCT(--(ROW('04 变换后数据'!$D$5:$D$160)<=ROW()),--ISNUMBER(OFFSET('04 变换后数据'!$D$5:$D$160,ROW()-5-$C$3+1,0,MIN($C$3,ROW()-4),1)),--ISNUMBER(OFFSET('04 变换后数据'!$H$5:$H$160,ROW()-5-$C$3+1,0,MIN($C$3,ROW()-4),1)))) | E19: =IF(15<$E$3,"",IF(619=0,"",IF(619<MAX(5,ROUND($E$3*0.8,0)),"样本不足",CORREL(OFFSET('04 变换后数据'!$D$5:$D$160,ROW()-5-$E$3+1,0,$E$3,1),OFFSET('04 变换后数据'!$H$5:$H$160,ROW()-5-$E$3+1,0,$E$3,1)))) | F19: =IF(15<$E$3,0,SUMPRODUCT(--(ROW('04 变换后数据'!$D$5:$D$160)<=ROW()),--ISNUMBER(OFFSET('04 变换后数据'!$D$5:$D$160,ROW()-5-$E$3+1,0,MIN($E$3,ROW()-4),1)),--ISNUMBER(OFFSET('04 变换后数据'!$H$5:$H$160,ROW()-5-$E$3+1,0,MIN($E$3,ROW()-4),1)))) | G19: =IF(15<$G$3,"",IF(819=0,"",IF(819<MAX(5,ROUND($G$3*0.8,0)),"样本不足",CORREL(OFFSET('04 变换后数据'!$D$5:$D$160,ROW()-5-$G$3+1,0,$G$3,1),OFFSET('04 变换后数据'!$H$5:$H$160,ROW()-5-$G$3+1,0,$G$3,1)))) | H19: =IF(15<$G$3,0,SUMPRODUCT(--(ROW('04 变换后数据'!$D$5:$D$160)<=ROW()),--ISNUMBER(OFFSET('04 变换后数据'!$D$5:$D$160,ROW()-5-$G$3+1,0,MIN($G$3,ROW()-4),1)),--ISNUMBER(OFFSET('04 变换后数据'!$H$5:$H$160,ROW()-5-$G$3+1,0,MIN($G$3,ROW()-4),1)))) | I19: =IF(ISNUMBER(E19),IF(ABS(E19)>=0.7,"强",IF(ABS(E19)>=0.4,"中","弱")),"-")
A20: 16 | B20: ='04 变换后数据'!B20 | C20: =IF(16<$C$3,"",IF(420=0,"",IF(420<MAX(5,ROUND($C$3*0.8,0)),"样本不足",CORREL(OFFSET('04 变换后数据'!$D$5:$D$160,ROW()-5-$C$3+1,0,$C$3,1),OFFSET('04 变换后数据'!$H$5:$H$160,ROW()-5-$C$3+1,0,$C$3,1)))) | D20: =IF(16<$C$3,0,SUMPRODUCT(--(ROW('04 变换后数据'!$D$5:$D$160)<=ROW()),--ISNUMBER(OFFSET('04 变换后数据'!$D$5:$D$160,ROW()-5-$C$3+1,0,MIN($C$3,ROW()-4),1)),--ISNUMBER(OFFSET('04 变换后数据'!$H$5:$H$160,ROW()-5-$C$3+1,0,MIN($C$3,ROW()-4),1)))) | E20: =IF(16<$E$3,"",IF(620=0,"",IF(620<MAX(5,ROUND($E$3*0.8,0)),"样本不足",CORREL(OFFSET('04 变换后数据'!$D$5:$D$160,ROW()-5-$E$3+1,0,$E$3,1),OFFSET('04 变换后数据'!$H$5:$H$160,ROW()-5-$E$3+1,0,$E$3,1)))) | F20: =IF(16<$E$3,0,SUMPRODUCT(--(ROW('04 变换后数据'!$D$5:$D$160)<=ROW()),--ISNUMBER(OFFSET('04 变换后数据'!$D$5:$D$160,ROW()-5-$E$3+1,0,MIN($E$3,ROW()-4),1)),--ISNUMBER(OFFSET('04 变换后数据'!$H$5:$H$160,ROW()-5-$E$3+1,0,MIN($E$3,ROW()-4),1)))) | G20: =IF(16<$G$3,"",IF(820=0,"",IF(820<MAX(5,ROUND($G$3*0.8,0)),"样本不足",CORREL(OFFSET('04 变换后数据'!$D$5:$D$160,ROW()-5-$G$3+1,0,$G$3,1),OFFSET('04 变换后数据'!$H$5:$H$160,ROW()-5-$G$3+1,0,$G$3,1)))) | H20: =IF(16<$G$3,0,SUMPRODUCT(--(ROW('04 变换后数据'!$D$5:$D$160)<=ROW()),--ISNUMBER(OFFSET('04 变换后数据'!$D$5:$D$160,ROW()-5-$G$3+1,0,MIN($G$3,ROW()-4),1)),--ISNUMBER(OFFSET('04 变换后数据'!$H$5:$H$160,ROW()-5-$G$3+1,0,MIN($G$3,ROW()-4),1)))) | I20: =IF(ISNUMBER(E20),IF(ABS(E20)>=0.7,"强",IF(ABS(E20)>=0.4,"中","弱")),"-")
A21: 17 | B21: ='04 变换后数据'!B21 | C21: =IF(17<$C$3,"",IF(421=0,"",IF(421<MAX(5,ROUND($C$3*0.8,0)),"样本不足",CORREL(OFFSET('04 变换后数据'!$D$5:$D$160,ROW()-5-$C$3+1,0,$C$3,1),OFFSET('04 变换后数据'!$H$5:$H$160,ROW()-5-$C$3+1,0,$C$3,1)))) | D21: =IF(17<$C$3,0,SUMPRODUCT(--(ROW('04 变换后数据'!$D$5:$D$160)<=ROW()),--ISNUMBER(OFFSET('04 变换后数据'!$D$5:$D$160,ROW()-5-$C$3+1,0,MIN($C$3,ROW()-4),1)),--ISNUMBER(OFFSET('04 变换后数据'!$H$5:$H$160,ROW()-5-$C$3+1,0,MIN($C$3,ROW()-4),1)))) | E21: =IF(17<$E$3,"",IF(621=0,"",IF(621<MAX(5,ROUND($E$3*0.8,0)),"样本不足",CORREL(OFFSET('04 变换后数据'!$D$5:$D$160,ROW()-5-$E$3+1,0,$E$3,1),OFFSET('04 变换后数据'!$H$5:$H$160,ROW()-5-$E$3+1,0,$E$3,1)))) | F21: =IF(17<$E$3,0,SUMPRODUCT(--(ROW('04 变换后数据'!$D$5:$D$160)<=ROW()),--ISNUMBER(OFFSET('04 变换后数据'!$D$5:$D$160,ROW()-5-$E$3+1,0,MIN($E$3,ROW()-4),1)),--ISNUMBER(OFFSET('04 变换后数据'!$H$5:$H$160,ROW()-5-$E$3+1,0,MIN($E$3,ROW()-4),1)))) | G21: =IF(17<$G$3,"",IF(821=0,"",IF(821<MAX(5,ROUND($G$3*0.8,0)),"样本不足",CORREL(OFFSET('04 变换后数据'!$D$5:$D$160,ROW()-5-$G$3+1,0,$G$3,1),OFFSET('04 变换后数据'!$H$5:$H$160,ROW()-5-$G$3+1,0,$G$3,1)))) | H21: =IF(17<$G$3,0,SUMPRODUCT(--(ROW('04 变换后数据'!$D$5:$D$160)<=ROW()),--ISNUMBER(OFFSET('04 变换后数据'!$D$5:$D$160,ROW()-5-$G$3+1,0,MIN($G$3,ROW()-4),1)),--ISNUMBER(OFFSET('04 变换后数据'!$H$5:$H$160,ROW()-5-$G$3+1,0,MIN($G$3,ROW()-4),1)))) | I21: =IF(ISNUMBER(E21),IF(ABS(E21)>=0.7,"强",IF(ABS(E21)>=0.4,"中","弱")),"-")
A22: 18 | B22: ='04 变换后数据'!B22 | C22: =IF(18<$C$3,"",IF(422=0,"",IF(422<MAX(5,ROUND($C$3*0.8,0)),"样本不足",CORREL(OFFSET('04 变换后数据'!$D$5:$D$160,ROW()-5-$C$3+1,0,$C$3,1),OFFSET('04 变换后数据'!$H$5:$H$160,ROW()-5-$C$3+1,0,$C$3,1)))) | D22: =IF(18<$C$3,0,SUMPRODUCT(--(ROW('04 变换后数据'!$D$5:$D$160)<=ROW()),--ISNUMBER(OFFSET('04 变换后数据'!$D$5:$D$160,ROW()-5-$C$3+1,0,MIN($C$3,ROW()-4),1)),--ISNUMBER(OFFSET('04 变换后数据'!$H$5:$H$160,ROW()-5-$C$3+1,0,MIN($C$3,ROW()-4),1)))) | E22: =IF(18<$E$3,"",IF(622=0,"",IF(622<MAX(5,ROUND($E$3*0.8,0)),"样本不足",CORREL(OFFSET('04 变换后数据'!$D$5:$D$160,ROW()-5-$E$3+1,0,$E$3,1),OFFSET('04 变换后数据'!$H$5:$H$160,ROW()-5-$E$3+1,0,$E$3,1)))) | F22: =IF(18<$E$3,0,SUMPRODUCT(--(ROW('04 变换后数据'!$D$5:$D$160)<=ROW()),--ISNUMBER(OFFSET('04 变换后数据'!$D$5:$D$160,ROW()-5-$E$3+1,0,MIN($E$3,ROW()-4),1)),--ISNUMBER(OFFSET('04 变换后数据'!$H$5:$H$160,ROW()-5-$E$3+1,0,MIN($E$3,ROW()-4),1)))) | G22: =IF(18<$G$3,"",IF(822=0,"",IF(822<MAX(5,ROUND($G$3*0.8,0)),"样本不足",CORREL(OFFSET('04 变换后数据'!$D$5:$D$160,ROW()-5-$G$3+1,0,$G$3,1),OFFSET('04 变换后数据'!$H$5:$H$160,ROW()-5-$G$3+1,0,$G$3,1)))) | H22: =IF(18<$G$3,0,SUMPRODUCT(--(ROW('04 变换后数据'!$D$5:$D$160)<=ROW()),--ISNUMBER(OFFSET('04 变换后数据'!$D$5:$D$160,ROW()-5-$G$3+1,0,MIN($G$3,ROW()-4),1)),--ISNUMBER(OFFSET('04 变换后数据'!$H$5:$H$160,ROW()-5-$G$3+1,0,MIN($G$3,ROW()-4),1)))) | I22: =IF(ISNUMBER(E22),IF(ABS(E22)>=0.7,"强",IF(ABS(E22)>=0.4,"中","弱")),"-")
A23: 19 | B23: ='04 变换后数据'!B23 | C23: =IF(19<$C$3,"",IF(423=0,"",IF(423<MAX(5,ROUND($C$3*0.8,0)),"样本不足",CORREL(OFFSET('04 变换后数据'!$D$5:$D$160,ROW()-5-$C$3+1,0,$C$3,1),OFFSET('04 变换后数据'!$H$5:$H$160,ROW()-5-$C$3+1,0,$C$3,1)))) | D23: =IF(19<$C$3,0,SUMPRODUCT(--(ROW('04 变换后数据'!$D$5:$D$160)<=ROW()),--ISNUMBER(OFFSET('04 变换后数据'!$D$5:$D$160,ROW()-5-$C$3+1,0,MIN($C$3,ROW()-4),1)),--ISNUMBER(OFFSET('04 变换后数据'!$H$5:$H$160,ROW()-5-$C$3+1,0,MIN($C$3,ROW()-4),1)))) | E23: =IF(19<$E$3,"",IF(623=0,"",IF(623<MAX(5,ROUND($E$3*0.8,0)),"样本不足",CORREL(OFFSET('04 变换后数据'!$D$5:$D$160,ROW()-5-$E$3+1,0,$E$3,1),OFFSET('04 变换后数据'!$H$5:$H$160,ROW()-5-$E$3+1,0,$E$3,1)))) | F23: =IF(19<$E$3,0,SUMPRODUCT(--(ROW('04 变换后数据'!$D$5:$D$160)<=ROW()),--ISNUMBER(OFFSET('04 变换后数据'!$D$5:$D$160,ROW()-5-$E$3+1,0,MIN($E$3,ROW()-4),1)),--ISNUMBER(OFFSET('04 变换后数据'!$H$5:$H$160,ROW()-5-$E$3+1,0,MIN($E$3,ROW()-4),1)))) | G23: =IF(19<$G$3,"",IF(823=0,"",IF(823<MAX(5,ROUND($G$3*0.8,0)),"样本不足",CORREL(OFFSET('04 变换后数据'!$D$5:$D$160,ROW()-5-$G$3+1,0,$G$3,1),OFFSET('04 变换后数据'!$H$5:$H$160,ROW()-5-$G$3+1,0,$G$3,1)))) | H23: =IF(19<$G$3,0,SUMPRODUCT(--(ROW('04 变换后数据'!$D$5:$D$160)<=ROW()),--ISNUMBER(OFFSET('04 变换后数据'!$D$5:$D$160,ROW()-5-$G$3+1,0,MIN($G$3,ROW()-4),1)),--ISNUMBER(OFFSET('04 变换后数据'!$H$5:$H$160,ROW()-5-$G$3+1,0,MIN($G$3,ROW()-4),1)))) | I23: =IF(ISNUMBER(E23),IF(ABS(E23)>=0.7,"强",IF(ABS(E23)>=0.4,"中","弱")),"-")
A24: 20 | B24: ='04 变换后数据'!B24 | C24: =IF(20<$C$3,"",IF(424=0,"",IF(424<MAX(5,ROUND($C$3*0.8,0)),"样本不足",CORREL(OFFSET('04 变换后数据'!$D$5:$D$160,ROW()-5-$C$3+1,0,$C$3,1),OFFSET('04 变换后数据'!$H$5:$H$160,ROW()-5-$C$3+1,0,$C$3,1)))) | D24: =IF(20<$C$3,0,SUMPRODUCT(--(ROW('04 变换后数据'!$D$5:$D$160)<=ROW()),--ISNUMBER(OFFSET('04 变换后数据'!$D$5:$D$160,ROW()-5-$C$3+1,0,MIN($C$3,ROW()-4),1)),--ISNUMBER(OFFSET('04 变换后数据'!$H$5:$H$160,ROW()-5-$C$3+1,0,MIN($C$3,ROW()-4),1)))) | E24: =IF(20<$E$3,"",IF(624=0,"",IF(624<MAX(5,ROUND($E$3*0.8,0)),"样本不足",CORREL(OFFSET('04 变换后数据'!$D$5:$D$160,ROW()-5-$E$3+1,0,$E$3,1),OFFSET('04 变换后数据'!$H$5:$H$160,ROW()-5-$E$3+1,0,$E$3,1)))) | F24: =IF(20<$E$3,0,SUMPRODUCT(--(ROW('04 变换后数据'!$D$5:$D$160)<=ROW()),--ISNUMBER(OFFSET('04 变换后数据'!$D$5:$D$160,ROW()-5-$E$3+1,0,MIN($E$3,ROW()-4),1)),--ISNUMBER(OFFSET('04 变换后数据'!$H$5:$H$160,ROW()-5-$E$3+1,0,MIN($E$3,ROW()-4),1)))) | G24: =IF(20<$G$3,"",IF(824=0,"",IF(824<MAX(5,ROUND($G$3*0.8,0)),"样本不足",CORREL(OFFSET('04 变换后数据'!$D$5:$D$160,ROW()-5-$G$3+1,0,$G$3,1),OFFSET('04 变换后数据'!$H$5:$H$160,ROW()-5-$G$3+1,0,$G$3,1)))) | H24: =IF(20<$G$3,0,SUMPRODUCT(--(ROW('04 变换后数据'!$D$5:$D$160)<=ROW()),--ISNUMBER(OFFSET('04 变换后数据'!$D$5:$D$160,ROW()-5-$G$3+1,0,MIN($G$3,ROW()-4),1)),--ISNUMBER(OFFSET('04 变换后数据'!$H$5:$H$160,ROW()-5-$G$3+1,0,MIN($G$3,ROW()-4),1)))) | I24: =IF(ISNUMBER(E24),IF(ABS(E24)>=0.7,"强",IF(ABS(E24)>=0.4,"中","弱")),"-")
A25: 21 | B25: ='04 变换后数据'!B25 | C25: =IF(21<$C$3,"",IF(425=0,"",IF(425<MAX(5,ROUND($C$3*0.8,0)),"样本不足",CORREL(OFFSET('04 变换后数据'!$D$5:$D$160,ROW()-5-$C$3+1,0,$C$3,1),OFFSET('04 变换后数据'!$H$5:$H$160,ROW()-5-$C$3+1,0,$C$3,1)))) | D25: =IF(21<$C$3,0,SUMPRODUCT(--(ROW('04 变换后数据'!$D$5:$D$160)<=ROW()),--ISNUMBER(OFFSET('04 变换后数据'!$D$5:$D$160,ROW()-5-$C$3+1,0,MIN($C$3,ROW()-4),1)),--ISNUMBER(OFFSET('04 变换后数据'!$H$5:$H$160,ROW()-5-$C$3+1,0,MIN($C$3,ROW()-4),1)))) | E25: =IF(21<$E$3,"",IF(625=0,"",IF(625<MAX(5,ROUND($E$3*0.8,0)),"样本不足",CORREL(OFFSET('04 变换后数据'!$D$5:$D$160,ROW()-5-$E$3+1,0,$E$3,1),OFFSET('04 变换后数据'!$H$5:$H$160,ROW()-5-$E$3+1,0,$E$3,1)))) | F25: =IF(21<$E$3,0,SUMPRODUCT(--(ROW('04 变换后数据'!$D$5:$D$160)<=ROW()),--ISNUMBER(OFFSET('04 变换后数据'!$D$5:$D$160,ROW()-5-$E$3+1,0,MIN($E$3,ROW()-4),1)),--ISNUMBER(OFFSET('04 变换后数据'!$H$5:$H$160,ROW()-5-$E$3+1,0,MIN($E$3,ROW()-4),1)))) | G25: =IF(21<$G$3,"",IF(825=0,"",IF(825<MAX(5,ROUND($G$3*0.8,0)),"样本不足",CORREL(OFFSET('04 变换后数据'!$D$5:$D$160,ROW()-5-$G$3+1,0,$G$3,1),OFFSET('04 变换后数据'!$H$5:$H$160,ROW()-5-$G$3+1,0,$G$3,1)))) | H25: =IF(21<$G$3,0,SUMPRODUCT(--(ROW('04 变换后数据'!$D$5:$D$160)<=ROW()),--ISNUMBER(OFFSET('04 变换后数据'!$D$5:$D$160,ROW()-5-$G$3+1,0,MIN($G$3,ROW()-4),1)),--ISNUMBER(OFFSET('04 变换后数据'!$H$5:$H$160,ROW()-5-$G$3+1,0,MIN($G$3,ROW()-4),1)))) | I25: =IF(ISNUMBER(E25),IF(ABS(E25)>=0.7,"强",IF(ABS(E25)>=0.4,"中","弱")),"-")
A26: 22 | B26: ='04 变换后数据'!B26 | C26: =IF(22<$C$3,"",IF(426=0,"",IF(426<MAX(5,ROUND($C$3*0.8,0)),"样本不足",CORREL(OFFSET('04 变换后数据'!$D$5:$D$160,ROW()-5-$C$3+1,0,$C$3,1),OFFSET('04 变换后数据'!$H$5:$H$160,ROW()-5-$C$3+1,0,$C$3,1)))) | D26: =IF(22<$C$3,0,SUMPRODUCT(--(ROW('04 变换后数据'!$D$5:$D$160)<=ROW()),--ISNUMBER(OFFSET('04 变换后数据'!$D$5:$D$160,ROW()-5-$C$3+1,0,MIN($C$3,ROW()-4),1)),--ISNUMBER(OFFSET('04 变换后数据'!$H$5:$H$160,ROW()-5-$C$3+1,0,MIN($C$3,ROW()-4),1)))) | E26: =IF(22<$E$3,"",IF(626=0,"",IF(626<MAX(5,ROUND($E$3*0.8,0)),"样本不足",CORREL(OFFSET('04 变换后数据'!$D$5:$D$160,ROW()-5-$E$3+1,0,$E$3,1),OFFSET('04 变换后数据'!$H$5:$H$160,ROW()-5-$E$3+1,0,$E$3,1)))) | F26: =IF(22<$E$3,0,SUMPRODUCT(--(ROW('04 变换后数据'!$D$5:$D$160)<=ROW()),--ISNUMBER(OFFSET('04 变换后数据'!$D$5:$D$160,ROW()-5-$E$3+1,0,MIN($E$3,ROW()-4),1)),--ISNUMBER(OFFSET('04 变换后数据'!$H$5:$H$160,ROW()-5-$E$3+1,0,MIN($E$3,ROW()-4),1)))) | G26: =IF(22<$G$3,"",IF(826=0,"",IF(826<MAX(5,ROUND($G$3*0.8,0)),"样本不足",CORREL(OFFSET('04 变换后数据'!$D$5:$D$160,ROW()-5-$G$3+1,0,$G$3,1),OFFSET('04 变换后数据'!$H$5:$H$160,ROW()-5-$G$3+1,0,$G$3,1)))) | H26: =IF(22<$G$3,0,SUMPRODUCT(--(ROW('04 变换后数据'!$D$5:$D$160)<=ROW()),--ISNUMBER(OFFSET('04 变换后数据'!$D$5:$D$160,ROW()-5-$G$3+1,0,MIN($G$3,ROW()-4),1)),--ISNUMBER(OFFSET('04 变换后数据'!$H$5:$H$160,ROW()-5-$G$3+1,0,MIN($G$3,ROW()-4),1)))) | I26: =IF(ISNUMBER(E26),IF(ABS(E26)>=0.7,"强",IF(ABS(E26)>=0.4,"中","弱")),"-")
A27: 23 | B27: ='04 变换后数据'!B27 | C27: =IF(23<$C$3,"",IF(427=0,"",IF(427<MAX(5,ROUND($C$3*0.8,0)),"样本不足",CORREL(OFFSET('04 变换后数据'!$D$5:$D$160,ROW()-5-$C$3+1,0,$C$3,1),OFFSET('04 变换后数据'!$H$5:$H$160,ROW()-5-$C$3+1,0,$C$3,1)))) | D27: =IF(23<$C$3,0,SUMPRODUCT(--(ROW('04 变换后数据'!$D$5:$D$160)<=ROW()),--ISNUMBER(OFFSET('04 变换后数据'!$D$5:$D$160,ROW()-5-$C$3+1,0,MIN($C$3,ROW()-4),1)),--ISNUMBER(OFFSET('04 变换后数据'!$H$5:$H$160,ROW()-5-$C$3+1,0,MIN($C$3,ROW()-4),1)))) | E27: =IF(23<$E$3,"",IF(627=0,"",IF(627<MAX(5,ROUND($E$3*0.8,0)),"样本不足",CORREL(OFFSET('04 变换后数据'!$D$5:$D$160,ROW()-5-$E$3+1,0,$E$3,1),OFFSET('04 变换后数据'!$H$5:$H$160,ROW()-5-$E$3+1,0,$E$3,1)))) | F27: =IF(23<$E$3,0,SUMPRODUCT(--(ROW('04 变换后数据'!$D$5:$D$160)<=ROW()),--ISNUMBER(OFFSET('04 变换后数据'!$D$5:$D$160,ROW()-5-$E$3+1,0,MIN($E$3,ROW()-4),1)),--ISNUMBER(OFFSET('04 变换后数据'!$H$5:$H$160,ROW()-5-$E$3+1,0,MIN($E$3,ROW()-4),1)))) | G27: =IF(23<$G$3,"",IF(827=0,"",IF(827<MAX(5,ROUND($G$3*0.8,0)),"样本不足",CORREL(OFFSET('04 变换后数据'!$D$5:$D$160,ROW()-5-$G$3+1,0,$G$3,1),OFFSET('04 变换后数据'!$H$5:$H$160,ROW()-5-$G$3+1,0,$G$3,1)))) | H27: =IF(23<$G$3,0,SUMPRODUCT(--(ROW('04 变换后数据'!$D$5:$D$160)<=ROW()),--ISNUMBER(OFFSET('04 变换后数据'!$D$5:$D$160,ROW()-5-$G$3+1,0,MIN($G$3,ROW()-4),1)),--ISNUMBER(OFFSET('04 变换后数据'!$H$5:$H$160,ROW()-5-$G$3+1,0,MIN($G$3,ROW()-4),1)))) | I27: =IF(ISNUMBER(E27),IF(ABS(E27)>=0.7,"强",IF(ABS(E27)>=0.4,"中","弱")),"-")
A28: 24 | B28: ='04 变换后数据'!B28 | C28: =IF(24<$C$3,"",IF(428=0,"",IF(428<MAX(5,ROUND($C$3*0.8,0)),"样本不足",CORREL(OFFSET('04 变换后数据'!$D$5:$D$160,ROW()-5-$C$3+1,0,$C$3,1),OFFSET('04 变换后数据'!$H$5:$H$160,ROW()-5-$C$3+1,0,$C$3,1)))) | D28: =IF(24<$C$3,0,SUMPRODUCT(--(ROW('04 变换后数据'!$D$5:$D$160)<=ROW()),--ISNUMBER(OFFSET('04 变换后数据'!$D$5:$D$160,ROW()-5-$C$3+1,0,MIN($C$3,ROW()-4),1)),--ISNUMBER(OFFSET('04 变换后数据'!$H$5:$H$160,ROW()-5-$C$3+1,0,MIN($C$3,ROW()-4),1)))) | E28: =IF(24<$E$3,"",IF(628=0,"",IF(628<MAX(5,ROUND($E$3*0.8,0)),"样本不足",CORREL(OFFSET('04 变换后数据'!$D$5:$D$160,ROW()-5-$E$3+1,0,$E$3,1),OFFSET('04 变换后数据'!$H$5:$H$160,ROW()-5-$E$3+1,0,$E$3,1)))) | F28: =IF(24<$E$3,0,SUMPRODUCT(--(ROW('04 变换后数据'!$D$5:$D$160)<=ROW()),--ISNUMBER(OFFSET('04 变换后数据'!$D$5:$D$160,ROW()-5-$E$3+1,0,MIN($E$3,ROW()-4),1)),--ISNUMBER(OFFSET('04 变换后数据'!$H$5:$H$160,ROW()-5-$E$3+1,0,MIN($E$3,ROW()-4),1)))) | G28: =IF(24<$G$3,"",IF(828=0,"",IF(828<MAX(5,ROUND($G$3*0.8,0)),"样本不足",CORREL(OFFSET('04 变换后数据'!$D$5:$D$160,ROW()-5-$G$3+1,0,$G$3,1),OFFSET('04 变换后数据'!$H$5:$H$160,ROW()-5-$G$3+1,0,$G$3,1)))) | H28: =IF(24<$G$3,0,SUMPRODUCT(--(ROW('04 变换后数据'!$D$5:$D$160)<=ROW()),--ISNUMBER(OFFSET('04 变换后数据'!$D$5:$D$160,ROW()-5-$G$3+1,0,MIN($G$3,ROW()-4),1)),--ISNUMBER(OFFSET('04 变换后数据'!$H$5:$H$160,ROW()-5-$G$3+1,0,MIN($G$3,ROW()-4),1)))) | I28: =IF(ISNUMBER(E28),IF(ABS(E28)>=0.7,"强",IF(ABS(E28)>=0.4,"中","弱")),"-")
A29: 25 | B29: ='04 变换后数据'!B29 | C29: =IF(25<$C$3,"",IF(429=0,"",IF(429<MAX(5,ROUND($C$3*0.8,0)),"样本不足",CORREL(OFFSET('04 变换后数据'!$D$5:$D$160,ROW()-5-$C$3+1,0,$C$3,1),OFFSET('04 变换后数据'!$H$5:$H$160,ROW()-5-$C$3+1,0,$C$3,1)))) | D29: =IF(25<$C$3,0,SUMPRODUCT(--(ROW('04 变换后数据'!$D$5:$D$160)<=ROW()),--ISNUMBER(OFFSET('04 变换后数据'!$D$5:$D$160,ROW()-5-$C$3+1,0,MIN($C$3,ROW()-4),1)),--ISNUMBER(OFFSET('04 变换后数据'!$H$5:$H$160,ROW()-5-$C$3+1,0,MIN($C$3,ROW()-4),1)))) | E29: =IF(25<$E$3,"",IF(629=0,"",IF(629<MAX(5,ROUND($E$3*0.8,0)),"样本不足",CORREL(OFFSET('04 变换后数据'!$D$5:$D$160,ROW()-5-$E$3+1,0,$E$3,1),OFFSET('04 变换后数据'!$H$5:$H$160,ROW()-5-$E$3+1,0,$E$3,1)))) | F29: =IF(25<$E$3,0,SUMPRODUCT(--(ROW('04 变换后数据'!$D$5:$D$160)<=ROW()),--ISNUMBER(OFFSET('04 变换后数据'!$D$5:$D$160,ROW()-5-$E$3+1,0,MIN($E$3,ROW()-4),1)),--ISNUMBER(OFFSET('04 变换后数据'!$H$5:$H$160,ROW()-5-$E$3+1,0,MIN($E$3,ROW()-4),1)))) | G29: =IF(25<$G$3,"",IF(829=0,"",IF(829<MAX(5,ROUND($G$3*0.8,0)),"样本不足",CORREL(OFFSET('04 变换后数据'!$D$5:$D$160,ROW()-5-$G$3+1,0,$G$3,1),OFFSET('04 变换后数据'!$H$5:$H$160,ROW()-5-$G$3+1,0,$G$3,1)))) | H29: =IF(25<$G$3,0,SUMPRODUCT(--(ROW('04 变换后数据'!$D$5:$D$160)<=ROW()),--ISNUMBER(OFFSET('04 变换后数据'!$D$5:$D$160,ROW()-5-$G$3+1,0,MIN($G$3,ROW()-4),1)),--ISNUMBER(OFFSET('04 变换后数据'!$H$5:$H$160,ROW()-5-$G$3+1,0,MIN($G$3,ROW()-4),1)))) | I29: =IF(ISNUMBER(E29),IF(ABS(E29)>=0.7,"强",IF(ABS(E29)>=0.4,"中","弱")),"-")
A30: 26 | B30: ='04 变换后数据'!B30 | C30: =IF(26<$C$3,"",IF(430=0,"",IF(430<MAX(5,ROUND($C$3*0.8,0)),"样本不足",CORREL(OFFSET('04 变换后数据'!$D$5:$D$160,ROW()-5-$C$3+1,0,$C$3,1),OFFSET('04 变换后数据'!$H$5:$H$160,ROW()-5-$C$3+1,0,$C$3,1)))) | D30: =IF(26<$C$3,0,SUMPRODUCT(--(ROW('04 变换后数据'!$D$5:$D$160)<=ROW()),--ISNUMBER(OFFSET('04 变换后数据'!$D$5:$D$160,ROW()-5-$C$3+1,0,MIN($C$3,ROW()-4),1)),--ISNUMBER(OFFSET('04 变换后数据'!$H$5:$H$160,ROW()-5-$C$3+1,0,MIN($C$3,ROW()-4),1)))) | E30: =IF(26<$E$3,"",IF(630=0,"",IF(630<MAX(5,ROUND($E$3*0.8,0)),"样本不足",CORREL(OFFSET('04 变换后数据'!$D$5:$D$160,ROW()-5-$E$3+1,0,$E$3,1),OFFSET('04 变换后数据'!$H$5:$H$160,ROW()-5-$E$3+1,0,$E$3,1)))) | F30: =IF(26<$E$3,0,SUMPRODUCT(--(ROW('04 变换后数据'!$D$5:$D$160)<=ROW()),--ISNUMBER(OFFSET('04 变换后数据'!$D$5:$D$160,ROW()-5-$E$3+1,0,MIN($E$3,ROW()-4),1)),--ISNUMBER(OFFSET('04 变换后数据'!$H$5:$H$160,ROW()-5-$E$3+1,0,MIN($E$3,ROW()-4),1)))) | G30: =IF(26<$G$3,"",IF(830=0,"",IF(830<MAX(5,ROUND($G$3*0.8,0)),"样本不足",CORREL(OFFSET('04 变换后数据'!$D$5:$D$160,ROW()-5-$G$3+1,0,$G$3,1),OFFSET('04 变换后数据'!$H$5:$H$160,ROW()-5-$G$3+1,0,$G$3,1)))) | H30: =IF(26<$G$3,0,SUMPRODUCT(--(ROW('04 变换后数据'!$D$5:$D$160)<=ROW()),--ISNUMBER(OFFSET('04 变换后数据'!$D$5:$D$160,ROW()-5-$G$3+1,0,MIN($G$3,ROW()-4),1)),--ISNUMBER(OFFSET('04 变换后数据'!$H$5:$H$160,ROW()-5-$G$3+1,0,MIN($G$3,ROW()-4),1)))) | I30: =IF(ISNUMBER(E30),IF(ABS(E30)>=0.7,"强",IF(ABS(E30)>=0.4,"中","弱")),"-")
A31: 27 | B31: ='04 变换后数据'!B31 | C31: =IF(27<$C$3,"",IF(431=0,"",IF(431<MAX(5,ROUND($C$3*0.8,0)),"样本不足",CORREL(OFFSET('04 变换后数据'!$D$5:$D$160,ROW()-5-$C$3+1,0,$C$3,1),OFFSET('04 变换后数据'!$H$5:$H$160,ROW()-5-$C$3+1,0,$C$3,1)))) | D31: =IF(27<$C$3,0,SUMPRODUCT(--(ROW('04 变换后数据'!$D$5:$D$160)<=ROW()),--ISNUMBER(OFFSET('04 变换后数据'!$D$5:$D$160,ROW()-5-$C$3+1,0,MIN($C$3,ROW()-4),1)),--ISNUMBER(OFFSET('04 变换后数据'!$H$5:$H$160,ROW()-5-$C$3+1,0,MIN($C$3,ROW()-4),1)))) | E31: =IF(27<$E$3,"",IF(631=0,"",IF(631<MAX(5,ROUND($E$3*0.8,0)),"样本不足",CORREL(OFFSET('04 变换后数据'!$D$5:$D$160,ROW()-5-$E$3+1,0,$E$3,1),OFFSET('04 变换后数据'!$H$5:$H$160,ROW()-5-$E$3+1,0,$E$3,1)))) | F31: =IF(27<$E$3,0,SUMPRODUCT(--(ROW('04 变换后数据'!$D$5:$D$160)<=ROW()),--ISNUMBER(OFFSET('04 变换后数据'!$D$5:$D$160,ROW()-5-$E$3+1,0,MIN($E$3,ROW()-4),1)),--ISNUMBER(OFFSET('04 变换后数据'!$H$5:$H$160,ROW()-5-$E$3+1,0,MIN($E$3,ROW()-4),1)))) | G31: =IF(27<$G$3,"",IF(831=0,"",IF(831<MAX(5,ROUND($G$3*0.8,0)),"样本不足",CORREL(OFFSET('04 变换后数据'!$D$5:$D$160,ROW()-5-$G$3+1,0,$G$3,1),OFFSET('04 变换后数据'!$H$5:$H$160,ROW()-5-$G$3+1,0,$G$3,1)))) | H31: =IF(27<$G$3,0,SUMPRODUCT(--(ROW('04 变换后数据'!$D$5:$D$160)<=ROW()),--ISNUMBER(OFFSET('04 变换后数据'!$D$5:$D$160,ROW()-5-$G$3+1,0,MIN($G$3,ROW()-4),1)),--ISNUMBER(OFFSET('04 变换后数据'!$H$5:$H$160,ROW()-5-$G$3+1,0,MIN($G$3,ROW()-4),1)))) | I31: =IF(ISNUMBER(E31),IF(ABS(E31)>=0.7,"强",IF(ABS(E31)>=0.4,"中","弱")),"-")
A32: 28 | B32: ='04 变换后数据'!B32 | C32: =IF(28<$C$3,"",IF(432=0,"",IF(432<MAX(5,ROUND($C$3*0.8,0)),"样本不足",CORREL(OFFSET('04 变换后数据'!$D$5:$D$160,ROW()-5-$C$3+1,0,$C$3,1),OFFSET('04 变换后数据'!$H$5:$H$160,ROW()-5-$C$3+1,0,$C$3,1)))) | D32: =IF(28<$C$3,0,SUMPRODUCT(--(ROW('04 变换后数据'!$D$5:$D$160)<=ROW()),--ISNUMBER(OFFSET('04 变换后数据'!$D$5:$D$160,ROW()-5-$C$3+1,0,MIN($C$3,ROW()-4),1)),--ISNUMBER(OFFSET('04 变换后数据'!$H$5:$H$160,ROW()-5-$C$3+1,0,MIN($C$3,ROW()-4),1)))) | E32: =IF(28<$E$3,"",IF(632=0,"",IF(632<MAX(5,ROUND($E$3*0.8,0)),"样本不足",CORREL(OFFSET('04 变换后数据'!$D$5:$D$160,ROW()-5-$E$3+1,0,$E$3,1),OFFSET('04 变换后数据'!$H$5:$H$160,ROW()-5-$E$3+1,0,$E$3,1)))) | F32: =IF(28<$E$3,0,SUMPRODUCT(--(ROW('04 变换后数据'!$D$5:$D$160)<=ROW()),--ISNUMBER(OFFSET('04 变换后数据'!$D$5:$D$160,ROW()-5-$E$3+1,0,MIN($E$3,ROW()-4),1)),--ISNUMBER(OFFSET('04 变换后数据'!$H$5:$H$160,ROW()-5-$E$3+1,0,MIN($E$3,ROW()-4),1)))) | G32: =IF(28<$G$3,"",IF(832=0,"",IF(832<MAX(5,ROUND($G$3*0.8,0)),"样本不足",CORREL(OFFSET('04 变换后数据'!$D$5:$D$160,ROW()-5-$G$3+1,0,$G$3,1),OFFSET('04 变换后数据'!$H$5:$H$160,ROW()-5-$G$3+1,0,$G$3,1)))) | H32: =IF(28<$G$3,0,SUMPRODUCT(--(ROW('04 变换后数据'!$D$5:$D$160)<=ROW()),--ISNUMBER(OFFSET('04 变换后数据'!$D$5:$D$160,ROW()-5-$G$3+1,0,MIN($G$3,ROW()-4),1)),--ISNUMBER(OFFSET('04 变换后数据'!$H$5:$H$160,ROW()-5-$G$3+1,0,MIN($G$3,ROW()-4),1)))) | I32: =IF(ISNUMBER(E32),IF(ABS(E32)>=0.7,"强",IF(ABS(E32)>=0.4,"中","弱")),"-")
A33: 29 | B33: ='04 变换后数据'!B33 | C33: =IF(29<$C$3,"",IF(433=0,"",IF(433<MAX(5,ROUND($C$3*0.8,0)),"样本不足",CORREL(OFFSET('04 变换后数据'!$D$5:$D$160,ROW()-5-$C$3+1,0,$C$3,1),OFFSET('04 变换后数据'!$H$5:$H$160,ROW()-5-$C$3+1,0,$C$3,1)))) | D33: =IF(29<$C$3,0,SUMPRODUCT(--(ROW('04 变换后数据'!$D$5:$D$160)<=ROW()),--ISNUMBER(OFFSET('04 变换后数据'!$D$5:$D$160,ROW()-5-$C$3+1,0,MIN($C$3,ROW()-4),1)),--ISNUMBER(OFFSET('04 变换后数据'!$H$5:$H$160,ROW()-5-$C$3+1,0,MIN($C$3,ROW()-4),1)))) | E33: =IF(29<$E$3,"",IF(633=0,"",IF(633<MAX(5,ROUND($E$3*0.8,0)),"样本不足",CORREL(OFFSET('04 变换后数据'!$D$5:$D$160,ROW()-5-$E$3+1,0,$E$3,1),OFFSET('04 变换后数据'!$H$5:$H$160,ROW()-5-$E$3+1,0,$E$3,1)))) | F33: =IF(29<$E$3,0,SUMPRODUCT(--(ROW('04 变换后数据'!$D$5:$D$160)<=ROW()),--ISNUMBER(OFFSET('04 变换后数据'!$D$5:$D$160,ROW()-5-$E$3+1,0,MIN($E$3,ROW()-4),1)),--ISNUMBER(OFFSET('04 变换后数据'!$H$5:$H$160,ROW()-5-$E$3+1,0,MIN($E$3,ROW()-4),1)))) | G33: =IF(29<$G$3,"",IF(833=0,"",IF(833<MAX(5,ROUND($G$3*0.8,0)),"样本不足",CORREL(OFFSET('04 变换后数据'!$D$5:$D$160,ROW()-5-$G$3+1,0,$G$3,1),OFFSET('04 变换后数据'!$H$5:$H$160,ROW()-5-$G$3+1,0,$G$3,1)))) | H33: =IF(29<$G$3,0,SUMPRODUCT(--(ROW('04 变换后数据'!$D$5:$D$160)<=ROW()),--ISNUMBER(OFFSET('04 变换后数据'!$D$5:$D$160,ROW()-5-$G$3+1,0,MIN($G$3,ROW()-4),1)),--ISNUMBER(OFFSET('04 变换后数据'!$H$5:$H$160,ROW()-5-$G$3+1,0,MIN($G$3,ROW()-4),1)))) | I33: =IF(ISNUMBER(E33),IF(ABS(E33)>=0.7,"强",IF(ABS(E33)>=0.4,"中","弱")),"-")
A34: 30 | B34: ='04 变换后数据'!B34 | C34: =IF(30<$C$3,"",IF(434=0,"",IF(434<MAX(5,ROUND($C$3*0.8,0)),"样本不足",CORREL(OFFSET('04 变换后数据'!$D$5:$D$160,ROW()-5-$C$3+1,0,$C$3,1),OFFSET('04 变换后数据'!$H$5:$H$160,ROW()-5-$C$3+1,0,$C$3,1)))) | D34: =IF(30<$C$3,0,SUMPRODUCT(--(ROW('04 变换后数据'!$D$5:$D$160)<=ROW()),--ISNUMBER(OFFSET('04 变换后数据'!$D$5:$D$160,ROW()-5-$C$3+1,0,MIN($C$3,ROW()-4),1)),--ISNUMBER(OFFSET('04 变换后数据'!$H$5:$H$160,ROW()-5-$C$3+1,0,MIN($C$3,ROW()-4),1)))) | E34: =IF(30<$E$3,"",IF(634=0,"",IF(634<MAX(5,ROUND($E$3*0.8,0)),"样本不足",CORREL(OFFSET('04 变换后数据'!$D$5:$D$160,ROW()-5-$E$3+1,0,$E$3,1),OFFSET('04 变换后数据'!$H$5:$H$160,ROW()-5-$E$3+1,0,$E$3,1)))) | F34: =IF(30<$E$3,0,SUMPRODUCT(--(ROW('04 变换后数据'!$D$5:$D$160)<=ROW()),--ISNUMBER(OFFSET('04 变换后数据'!$D$5:$D$160,ROW()-5-$E$3+1,0,MIN($E$3,ROW()-4),1)),--ISNUMBER(OFFSET('04 变换后数据'!$H$5:$H$160,ROW()-5-$E$3+1,0,MIN($E$3,ROW()-4),1)))) | G34: =IF(30<$G$3,"",IF(834=0,"",IF(834<MAX(5,ROUND($G$3*0.8,0)),"样本不足",CORREL(OFFSET('04 变换后数据'!$D$5:$D$160,ROW()-5-$G$3+1,0,$G$3,1),OFFSET('04 变换后数据'!$H$5:$H$160,ROW()-5-$G$3+1,0,$G$3,1)))) | H34: =IF(30<$G$3,0,SUMPRODUCT(--(ROW('04 变换后数据'!$D$5:$D$160)<=ROW()),--ISNUMBER(OFFSET('04 变换后数据'!$D$5:$D$160,ROW()-5-$G$3+1,0,MIN($G$3,ROW()-4),1)),--ISNUMBER(OFFSET('04 变换后数据'!$H$5:$H$160,ROW()-5-$G$3+1,0,MIN($G$3,ROW()-4),1)))) | I34: =IF(ISNUMBER(E34),IF(ABS(E34)>=0.7,"强",IF(ABS(E34)>=0.4,"中","弱")),"-")
A35: 31 | B35: ='04 变换后数据'!B35 | C35: =IF(31<$C$3,"",IF(435=0,"",IF(435<MAX(5,ROUND($C$3*0.8,0)),"样本不足",CORREL(OFFSET('04 变换后数据'!$D$5:$D$160,ROW()-5-$C$3+1,0,$C$3,1),OFFSET('04 变换后数据'!$H$5:$H$160,ROW()-5-$C$3+1,0,$C$3,1)))) | D35: =IF(31<$C$3,0,SUMPRODUCT(--(ROW('04 变换后数据'!$D$5:$D$160)<=ROW()),--ISNUMBER(OFFSET('04 变换后数据'!$D$5:$D$160,ROW()-5-$C$3+1,0,MIN($C$3,ROW()-4),1)),--ISNUMBER(OFFSET('04 变换后数据'!$H$5:$H$160,ROW()-5-$C$3+1,0,MIN($C$3,ROW()-4),1)))) | E35: =IF(31<$E$3,"",IF(635=0,"",IF(635<MAX(5,ROUND($E$3*0.8,0)),"样本不足",CORREL(OFFSET('04 变换后数据'!$D$5:$D$160,ROW()-5-$E$3+1,0,$E$3,1),OFFSET('04 变换后数据'!$H$5:$H$160,ROW()-5-$E$3+1,0,$E$3,1)))) | F35: =IF(31<$E$3,0,SUMPRODUCT(--(ROW('04 变换后数据'!$D$5:$D$160)<=ROW()),--ISNUMBER(OFFSET('04 变换后数据'!$D$5:$D$160,ROW()-5-$E$3+1,0,MIN($E$3,ROW()-4),1)),--ISNUMBER(OFFSET('04 变换后数据'!$H$5:$H$160,ROW()-5-$E$3+1,0,MIN($E$3,ROW()-4),1)))) | G35: =IF(31<$G$3,"",IF(835=0,"",IF(835<MAX(5,ROUND($G$3*0.8,0)),"样本不足",CORREL(OFFSET('04 变换后数据'!$D$5:$D$160,ROW()-5-$G$3+1,0,$G$3,1),OFFSET('04 变换后数据'!$H$5:$H$160,ROW()-5-$G$3+1,0,$G$3,1)))) | H35: =IF(31<$G$3,0,SUMPRODUCT(--(ROW('04 变换后数据'!$D$5:$D$160)<=ROW()),--ISNUMBER(OFFSET('04 变换后数据'!$D$5:$D$160,ROW()-5-$G$3+1,0,MIN($G$3,ROW()-4),1)),--ISNUMBER(OFFSET('04 变换后数据'!$H$5:$H$160,ROW()-5-$G$3+1,0,MIN($G$3,ROW()-4),1)))) | I35: =IF(ISNUMBER(E35),IF(ABS(E35)>=0.7,"强",IF(ABS(E35)>=0.4,"中","弱")),"-")
A36: 32 | B36: ='04 变换后数据'!B36 | C36: =IF(32<$C$3,"",IF(436=0,"",IF(436<MAX(5,ROUND($C$3*0.8,0)),"样本不足",CORREL(OFFSET('04 变换后数据'!$D$5:$D$160,ROW()-5-$C$3+1,0,$C$3,1),OFFSET('04 变换后数据'!$H$5:$H$160,ROW()-5-$C$3+1,0,$C$3,1)))) | D36: =IF(32<$C$3,0,SUMPRODUCT(--(ROW('04 变换后数据'!$D$5:$D$160)<=ROW()),--ISNUMBER(OFFSET('04 变换后数据'!$D$5:$D$160,ROW()-5-$C$3+1,0,MIN($C$3,ROW()-4),1)),--ISNUMBER(OFFSET('04 变换后数据'!$H$5:$H$160,ROW()-5-$C$3+1,0,MIN($C$3,ROW()-4),1)))) | E36: =IF(32<$E$3,"",IF(636=0,"",IF(636<MAX(5,ROUND($E$3*0.8,0)),"样本不足",CORREL(OFFSET('04 变换后数据'!$D$5:$D$160,ROW()-5-$E$3+1,0,$E$3,1),OFFSET('04 变换后数据'!$H$5:$H$160,ROW()-5-$E$3+1,0,$E$3,1)))) | F36: =IF(32<$E$3,0,SUMPRODUCT(--(ROW('04 变换后数据'!$D$5:$D$160)<=ROW()),--ISNUMBER(OFFSET('04 变换后数据'!$D$5:$D$160,ROW()-5-$E$3+1,0,MIN($E$3,ROW()-4),1)),--ISNUMBER(OFFSET('04 变换后数据'!$H$5:$H$160,ROW()-5-$E$3+1,0,MIN($E$3,ROW()-4),1)))) | G36: =IF(32<$G$3,"",IF(836=0,"",IF(836<MAX(5,ROUND($G$3*0.8,0)),"样本不足",CORREL(OFFSET('04 变换后数据'!$D$5:$D$160,ROW()-5-$G$3+1,0,$G$3,1),OFFSET('04 变换后数据'!$H$5:$H$160,ROW()-5-$G$3+1,0,$G$3,1)))) | H36: =IF(32<$G$3,0,SUMPRODUCT(--(ROW('04 变换后数据'!$D$5:$D$160)<=ROW()),--ISNUMBER(OFFSET('04 变换后数据'!$D$5:$D$160,ROW()-5-$G$3+1,0,MIN($G$3,ROW()-4),1)),--ISNUMBER(OFFSET('04 变换后数据'!$H$5:$H$160,ROW()-5-$G$3+1,0,MIN($G$3,ROW()-4),1)))) | I36: =IF(ISNUMBER(E36),IF(ABS(E36)>=0.7,"强",IF(ABS(E36)>=0.4,"中","弱")),"-")
A37: 33 | B37: ='04 变换后数据'!B37 | C37: =IF(33<$C$3,"",IF(437=0,"",IF(437<MAX(5,ROUND($C$3*0.8,0)),"样本不足",CORREL(OFFSET('04 变换后数据'!$D$5:$D$160,ROW()-5-$C$3+1,0,$C$3,1),OFFSET('04 变换后数据'!$H$5:$H$160,ROW()-5-$C$3+1,0,$C$3,1)))) | D37: =IF(33<$C$3,0,SUMPRODUCT(--(ROW('04 变换后数据'!$D$5:$D$160)<=ROW()),--ISNUMBER(OFFSET('04 变换后数据'!$D$5:$D$160,ROW()-5-$C$3+1,0,MIN($C$3,ROW()-4),1)),--ISNUMBER(OFFSET('04 变换后数据'!$H$5:$H$160,ROW()-5-$C$3+1,0,MIN($C$3,ROW()-4),1)))) | E37: =IF(33<$E$3,"",IF(637=0,"",IF(637<MAX(5,ROUND($E$3*0.8,0)),"样本不足",CORREL(OFFSET('04 变换后数据'!$D$5:$D$160,ROW()-5-$E$3+1,0,$E$3,1),OFFSET('04 变换后数据'!$H$5:$H$160,ROW()-5-$E$3+1,0,$E$3,1)))) | F37: =IF(33<$E$3,0,SUMPRODUCT(--(ROW('04 变换后数据'!$D$5:$D$160)<=ROW()),--ISNUMBER(OFFSET('04 变换后数据'!$D$5:$D$160,ROW()-5-$E$3+1,0,MIN($E$3,ROW()-4),1)),--ISNUMBER(OFFSET('04 变换后数据'!$H$5:$H$160,ROW()-5-$E$3+1,0,MIN($E$3,ROW()-4),1)))) | G37: =IF(33<$G$3,"",IF(837=0,"",IF(837<MAX(5,ROUND($G$3*0.8,0)),"样本不足",CORREL(OFFSET('04 变换后数据'!$D$5:$D$160,ROW()-5-$G$3+1,0,$G$3,1),OFFSET('04 变换后数据'!$H$5:$H$160,ROW()-5-$G$3+1,0,$G$3,1)))) | H37: =IF(33<$G$3,0,SUMPRODUCT(--(ROW('04 变换后数据'!$D$5:$D$160)<=ROW()),--ISNUMBER(OFFSET('04 变换后数据'!$D$5:$D$160,ROW()-5-$G$3+1,0,MIN($G$3,ROW()-4),1)),--ISNUMBER(OFFSET('04 变换后数据'!$H$5:$H$160,ROW()-5-$G$3+1,0,MIN($G$3,ROW()-4),1)))) | I37: =IF(ISNUMBER(E37),IF(ABS(E37)>=0.7,"强",IF(ABS(E37)>=0.4,"中","弱")),"-")
A38: 34 | B38: ='04 变换后数据'!B38 | C38: =IF(34<$C$3,"",IF(438=0,"",IF(438<MAX(5,ROUND($C$3*0.8,0)),"样本不足",CORREL(OFFSET('04 变换后数据'!$D$5:$D$160,ROW()-5-$C$3+1,0,$C$3,1),OFFSET('04 变换后数据'!$H$5:$H$160,ROW()-5-$C$3+1,0,$C$3,1)))) | D38: =IF(34<$C$3,0,SUMPRODUCT(--(ROW('04 变换后数据'!$D$5:$D$160)<=ROW()),--ISNUMBER(OFFSET('04 变换后数据'!$D$5:$D$160,ROW()-5-$C$3+1,0,MIN($C$3,ROW()-4),1)),--ISNUMBER(OFFSET('04 变换后数据'!$H$5:$H$160,ROW()-5-$C$3+1,0,MIN($C$3,ROW()-4),1)))) | E38: =IF(34<$E$3,"",IF(638=0,"",IF(638<MAX(5,ROUND($E$3*0.8,0)),"样本不足",CORREL(OFFSET('04 变换后数据'!$D$5:$D$160,ROW()-5-$E$3+1,0,$E$3,1),OFFSET('04 变换后数据'!$H$5:$H$160,ROW()-5-$E$3+1,0,$E$3,1)))) | F38: =IF(34<$E$3,0,SUMPRODUCT(--(ROW('04 变换后数据'!$D$5:$D$160)<=ROW()),--ISNUMBER(OFFSET('04 变换后数据'!$D$5:$D$160,ROW()-5-$E$3+1,0,MIN($E$3,ROW()-4),1)),--ISNUMBER(OFFSET('04 变换后数据'!$H$5:$H$160,ROW()-5-$E$3+1,0,MIN($E$3,ROW()-4),1)))) | G38: =IF(34<$G$3,"",IF(838=0,"",IF(838<MAX(5,ROUND($G$3*0.8,0)),"样本不足",CORREL(OFFSET('04 变换后数据'!$D$5:$D$160,ROW()-5-$G$3+1,0,$G$3,1),OFFSET('04 变换后数据'!$H$5:$H$160,ROW()-5-$G$3+1,0,$G$3,1)))) | H38: =IF(34<$G$3,0,SUMPRODUCT(--(ROW('04 变换后数据'!$D$5:$D$160)<=ROW()),--ISNUMBER(OFFSET('04 变换后数据'!$D$5:$D$160,ROW()-5-$G$3+1,0,MIN($G$3,ROW()-4),1)),--ISNUMBER(OFFSET('04 变换后数据'!$H$5:$H$160,ROW()-5-$G$3+1,0,MIN($G$3,ROW()-4),1)))) | I38: =IF(ISNUMBER(E38),IF(ABS(E38)>=0.7,"强",IF(ABS(E38)>=0.4,"中","弱")),"-")
A39: 35 | B39: ='04 变换后数据'!B39 | C39: =IF(35<$C$3,"",IF(439=0,"",IF(439<MAX(5,ROUND($C$3*0.8,0)),"样本不足",CORREL(OFFSET('04 变换后数据'!$D$5:$D$160,ROW()-5-$C$3+1,0,$C$3,1),OFFSET('04 变换后数据'!$H$5:$H$160,ROW()-5-$C$3+1,0,$C$3,1)))) | D39: =IF(35<$C$3,0,SUMPRODUCT(--(ROW('04 变换后数据'!$D$5:$D$160)<=ROW()),--ISNUMBER(OFFSET('04 变换后数据'!$D$5:$D$160,ROW()-5-$C$3+1,0,MIN($C$3,ROW()-4),1)),--ISNUMBER(OFFSET('04 变换后数据'!$H$5:$H$160,ROW()-5-$C$3+1,0,MIN($C$3,ROW()-4),1)))) | E39: =IF(35<$E$3,"",IF(639=0,"",IF(639<MAX(5,ROUND($E$3*0.8,0)),"样本不足",CORREL(OFFSET('04 变换后数据'!$D$5:$D$160,ROW()-5-$E$3+1,0,$E$3,1),OFFSET('04 变换后数据'!$H$5:$H$160,ROW()-5-$E$3+1,0,$E$3,1)))) | F39: =IF(35<$E$3,0,SUMPRODUCT(--(ROW('04 变换后数据'!$D$5:$D$160)<=ROW()),--ISNUMBER(OFFSET('04 变换后数据'!$D$5:$D$160,ROW()-5-$E$3+1,0,MIN($E$3,ROW()-4),1)),--ISNUMBER(OFFSET('04 变换后数据'!$H$5:$H$160,ROW()-5-$E$3+1,0,MIN($E$3,ROW()-4),1)))) | G39: =IF(35<$G$3,"",IF(839=0,"",IF(839<MAX(5,ROUND($G$3*0.8,0)),"样本不足",CORREL(OFFSET('04 变换后数据'!$D$5:$D$160,ROW()-5-$G$3+1,0,$G$3,1),OFFSET('04 变换后数据'!$H$5:$H$160,ROW()-5-$G$3+1,0,$G$3,1)))) | H39: =IF(35<$G$3,0,SUMPRODUCT(--(ROW('04 变换后数据'!$D$5:$D$160)<=ROW()),--ISNUMBER(OFFSET('04 变换后数据'!$D$5:$D$160,ROW()-5-$G$3+1,0,MIN($G$3,ROW()-4),1)),--ISNUMBER(OFFSET('04 变换后数据'!$H$5:$H$160,ROW()-5-$G$3+1,0,MIN($G$3,ROW()-4),1)))) | I39: =IF(ISNUMBER(E39),IF(ABS(E39)>=0.7,"强",IF(ABS(E39)>=0.4,"中","弱")),"-")
A40: 36 | B40: ='04 变换后数据'!B40 | C40: =IF(36<$C$3,"",IF(440=0,"",IF(440<MAX(5,ROUND($C$3*0.8,0)),"样本不足",CORREL(OFFSET('04 变换后数据'!$D$5:$D$160,ROW()-5-$C$3+1,0,$C$3,1),OFFSET('04 变换后数据'!$H$5:$H$160,ROW()-5-$C$3+1,0,$C$3,1)))) | D40: =IF(36<$C$3,0,SUMPRODUCT(--(ROW('04 变换后数据'!$D$5:$D$160)<=ROW()),--ISNUMBER(OFFSET('04 变换后数据'!$D$5:$D$160,ROW()-5-$C$3+1,0,MIN($C$3,ROW()-4),1)),--ISNUMBER(OFFSET('04 变换后数据'!$H$5:$H$160,ROW()-5-$C$3+1,0,MIN($C$3,ROW()-4),1)))) | E40: =IF(36<$E$3,"",IF(640=0,"",IF(640<MAX(5,ROUND($E$3*0.8,0)),"样本不足",CORREL(OFFSET('04 变换后数据'!$D$5:$D$160,ROW()-5-$E$3+1,0,$E$3,1),OFFSET('04 变换后数据'!$H$5:$H$160,ROW()-5-$E$3+1,0,$E$3,1)))) | F40: =IF(36<$E$3,0,SUMPRODUCT(--(ROW('04 变换后数据'!$D$5:$D$160)<=ROW()),--ISNUMBER(OFFSET('04 变换后数据'!$D$5:$D$160,ROW()-5-$E$3+1,0,MIN($E$3,ROW()-4),1)),--ISNUMBER(OFFSET('04 变换后数据'!$H$5:$H$160,ROW()-5-$E$3+1,0,MIN($E$3,ROW()-4),1)))) | G40: =IF(36<$G$3,"",IF(840=0,"",IF(840<MAX(5,ROUND($G$3*0.8,0)),"样本不足",CORREL(OFFSET('04 变换后数据'!$D$5:$D$160,ROW()-5-$G$3+1,0,$G$3,1),OFFSET('04 变换后数据'!$H$5:$H$160,ROW()-5-$G$3+1,0,$G$3,1)))) | H40: =IF(36<$G$3,0,SUMPRODUCT(--(ROW('04 变换后数据'!$D$5:$D$160)<=ROW()),--ISNUMBER(OFFSET('04 变换后数据'!$D$5:$D$160,ROW()-5-$G$3+1,0,MIN($G$3,ROW()-4),1)),--ISNUMBER(OFFSET('04 变换后数据'!$H$5:$H$160,ROW()-5-$G$3+1,0,MIN($G$3,ROW()-4),1)))) | I40: =IF(ISNUMBER(E40),IF(ABS(E40)>=0.7,"强",IF(ABS(E40)>=0.4,"中","弱")),"-")
A41: 37 | B41: ='04 变换后数据'!B41 | C41: =IF(37<$C$3,"",IF(441=0,"",IF(441<MAX(5,ROUND($C$3*0.8,0)),"样本不足",CORREL(OFFSET('04 变换后数据'!$D$5:$D$160,ROW()-5-$C$3+1,0,$C$3,1),OFFSET('04 变换后数据'!$H$5:$H$160,ROW()-5-$C$3+1,0,$C$3,1)))) | D41: =IF(37<$C$3,0,SUMPRODUCT(--(ROW('04 变换后数据'!$D$5:$D$160)<=ROW()),--ISNUMBER(OFFSET('04 变换后数据'!$D$5:$D$160,ROW()-5-$C$3+1,0,MIN($C$3,ROW()-4),1)),--ISNUMBER(OFFSET('04 变换后数据'!$H$5:$H$160,ROW()-5-$C$3+1,0,MIN($C$3,ROW()-4),1)))) | E41: =IF(37<$E$3,"",IF(641=0,"",IF(641<MAX(5,ROUND($E$3*0.8,0)),"样本不足",CORREL(OFFSET('04 变换后数据'!$D$5:$D$160,ROW()-5-$E$3+1,0,$E$3,1),OFFSET('04 变换后数据'!$H$5:$H$160,ROW()-5-$E$3+1,0,$E$3,1)))) | F41: =IF(37<$E$3,0,SUMPRODUCT(--(ROW('04 变换后数据'!$D$5:$D$160)<=ROW()),--ISNUMBER(OFFSET('04 变换后数据'!$D$5:$D$160,ROW()-5-$E$3+1,0,MIN($E$3,ROW()-4),1)),--ISNUMBER(OFFSET('04 变换后数据'!$H$5:$H$160,ROW()-5-$E$3+1,0,MIN($E$3,ROW()-4),1)))) | G41: =IF(37<$G$3,"",IF(841=0,"",IF(841<MAX(5,ROUND($G$3*0.8,0)),"样本不足",CORREL(OFFSET('04 变换后数据'!$D$5:$D$160,ROW()-5-$G$3+1,0,$G$3,1),OFFSET('04 变换后数据'!$H$5:$H$160,ROW()-5-$G$3+1,0,$G$3,1)))) | H41: =IF(37<$G$3,0,SUMPRODUCT(--(ROW('04 变换后数据'!$D$5:$D$160)<=ROW()),--ISNUMBER(OFFSET('04 变换后数据'!$D$5:$D$160,ROW()-5-$G$3+1,0,MIN($G$3,ROW()-4),1)),--ISNUMBER(OFFSET('04 变换后数据'!$H$5:$H$160,ROW()-5-$G$3+1,0,MIN($G$3,ROW()-4),1)))) | I41: =IF(ISNUMBER(E41),IF(ABS(E41)>=0.7,"强",IF(ABS(E41)>=0.4,"中","弱")),"-")
A42: 38 | B42: ='04 变换后数据'!B42 | C42: =IF(38<$C$3,"",IF(442=0,"",IF(442<MAX(5,ROUND($C$3*0.8,0)),"样本不足",CORREL(OFFSET('04 变换后数据'!$D$5:$D$160,ROW()-5-$C$3+1,0,$C$3,1),OFFSET('04 变换后数据'!$H$5:$H$160,ROW()-5-$C$3+1,0,$C$3,1)))) | D42: =IF(38<$C$3,0,SUMPRODUCT(--(ROW('04 变换后数据'!$D$5:$D$160)<=ROW()),--ISNUMBER(OFFSET('04 变换后数据'!$D$5:$D$160,ROW()-5-$C$3+1,0,MIN($C$3,ROW()-4),1)),--ISNUMBER(OFFSET('04 变换后数据'!$H$5:$H$160,ROW()-5-$C$3+1,0,MIN($C$3,ROW()-4),1)))) | E42: =IF(38<$E$3,"",IF(642=0,"",IF(642<MAX(5,ROUND($E$3*0.8,0)),"样本不足",CORREL(OFFSET('04 变换后数据'!$D$5:$D$160,ROW()-5-$E$3+1,0,$E$3,1),OFFSET('04 变换后数据'!$H$5:$H$160,ROW()-5-$E$3+1,0,$E$3,1)))) | F42: =IF(38<$E$3,0,SUMPRODUCT(--(ROW('04 变换后数据'!$D$5:$D$160)<=ROW()),--ISNUMBER(OFFSET('04 变换后数据'!$D$5:$D$160,ROW()-5-$E$3+1,0,MIN($E$3,ROW()-4),1)),--ISNUMBER(OFFSET('04 变换后数据'!$H$5:$H$160,ROW()-5-$E$3+1,0,MIN($E$3,ROW()-4),1)))) | G42: =IF(38<$G$3,"",IF(842=0,"",IF(842<MAX(5,ROUND($G$3*0.8,0)),"样本不足",CORREL(OFFSET('04 变换后数据'!$D$5:$D$160,ROW()-5-$G$3+1,0,$G$3,1),OFFSET('04 变换后数据'!$H$5:$H$160,ROW()-5-$G$3+1,0,$G$3,1)))) | H42: =IF(38<$G$3,0,SUMPRODUCT(--(ROW('04 变换后数据'!$D$5:$D$160)<=ROW()),--ISNUMBER(OFFSET('04 变换后数据'!$D$5:$D$160,ROW()-5-$G$3+1,0,MIN($G$3,ROW()-4),1)),--ISNUMBER(OFFSET('04 变换后数据'!$H$5:$H$160,ROW()-5-$G$3+1,0,MIN($G$3,ROW()-4),1)))) | I42: =IF(ISNUMBER(E42),IF(ABS(E42)>=0.7,"强",IF(ABS(E42)>=0.4,"中","弱")),"-")
A43: 39 | B43: ='04 变换后数据'!B43 | C43: =IF(39<$C$3,"",IF(443=0,"",IF(443<MAX(5,ROUND($C$3*0.8,0)),"样本不足",CORREL(OFFSET('04 变换后数据'!$D$5:$D$160,ROW()-5-$C$3+1,0,$C$3,1),OFFSET('04 变换后数据'!$H$5:$H$160,ROW()-5-$C$3+1,0,$C$3,1)))) | D43: =IF(39<$C$3,0,SUMPRODUCT(--(ROW('04 变换后数据'!$D$5:$D$160)<=ROW()),--ISNUMBER(OFFSET('04 变换后数据'!$D$5:$D$160,ROW()-5-$C$3+1,0,MIN($C$3,ROW()-4),1)),--ISNUMBER(OFFSET('04 变换后数据'!$H$5:$H$160,ROW()-5-$C$3+1,0,MIN($C$3,ROW()-4),1)))) | E43: =IF(39<$E$3,"",IF(643=0,"",IF(643<MAX(5,ROUND($E$3*0.8,0)),"样本不足",CORREL(OFFSET('04 变换后数据'!$D$5:$D$160,ROW()-5-$E$3+1,0,$E$3,1),OFFSET('04 变换后数据'!$H$5:$H$160,ROW()-5-$E$3+1,0,$E$3,1)))) | F43: =IF(39<$E$3,0,SUMPRODUCT(--(ROW('04 变换后数据'!$D$5:$D$160)<=ROW()),--ISNUMBER(OFFSET('04 变换后数据'!$D$5:$D$160,ROW()-5-$E$3+1,0,MIN($E$3,ROW()-4),1)),--ISNUMBER(OFFSET('04 变换后数据'!$H$5:$H$160,ROW()-5-$E$3+1,0,MIN($E$3,ROW()-4),1)))) | G43: =IF(39<$G$3,"",IF(843=0,"",IF(843<MAX(5,ROUND($G$3*0.8,0)),"样本不足",CORREL(OFFSET('04 变换后数据'!$D$5:$D$160,ROW()-5-$G$3+1,0,$G$3,1),OFFSET('04 变换后数据'!$H$5:$H$160,ROW()-5-$G$3+1,0,$G$3,1)))) | H43: =IF(39<$G$3,0,SUMPRODUCT(--(ROW('04 变换后数据'!$D$5:$D$160)<=ROW()),--ISNUMBER(OFFSET('04 变换后数据'!$D$5:$D$160,ROW()-5-$G$3+1,0,MIN($G$3,ROW()-4),1)),--ISNUMBER(OFFSET('04 变换后数据'!$H$5:$H$160,ROW()-5-$G$3+1,0,MIN($G$3,ROW()-4),1)))) | I43: =IF(ISNUMBER(E43),IF(ABS(E43)>=0.7,"强",IF(ABS(E43)>=0.4,"中","弱")),"-")
A44: 40 | B44: ='04 变换后数据'!B44 | C44: =IF(40<$C$3,"",IF(444=0,"",IF(444<MAX(5,ROUND($C$3*0.8,0)),"样本不足",CORREL(OFFSET('04 变换后数据'!$D$5:$D$160,ROW()-5-$C$3+1,0,$C$3,1),OFFSET('04 变换后数据'!$H$5:$H$160,ROW()-5-$C$3+1,0,$C$3,1)))) | D44: =IF(40<$C$3,0,SUMPRODUCT(--(ROW('04 变换后数据'!$D$5:$D$160)<=ROW()),--ISNUMBER(OFFSET('04 变换后数据'!$D$5:$D$160,ROW()-5-$C$3+1,0,MIN($C$3,ROW()-4),1)),--ISNUMBER(OFFSET('04 变换后数据'!$H$5:$H$160,ROW()-5-$C$3+1,0,MIN($C$3,ROW()-4),1)))) | E44: =IF(40<$E$3,"",IF(644=0,"",IF(644<MAX(5,ROUND($E$3*0.8,0)),"样本不足",CORREL(OFFSET('04 变换后数据'!$D$5:$D$160,ROW()-5-$E$3+1,0,$E$3,1),OFFSET('04 变换后数据'!$H$5:$H$160,ROW()-5-$E$3+1,0,$E$3,1)))) | F44: =IF(40<$E$3,0,SUMPRODUCT(--(ROW('04 变换后数据'!$D$5:$D$160)<=ROW()),--ISNUMBER(OFFSET('04 变换后数据'!$D$5:$D$160,ROW()-5-$E$3+1,0,MIN($E$3,ROW()-4),1)),--ISNUMBER(OFFSET('04 变换后数据'!$H$5:$H$160,ROW()-5-$E$3+1,0,MIN($E$3,ROW()-4),1)))) | G44: =IF(40<$G$3,"",IF(844=0,"",IF(844<MAX(5,ROUND($G$3*0.8,0)),"样本不足",CORREL(OFFSET('04 变换后数据'!$D$5:$D$160,ROW()-5-$G$3+1,0,$G$3,1),OFFSET('04 变换后数据'!$H$5:$H$160,ROW()-5-$G$3+1,0,$G$3,1)))) | H44: =IF(40<$G$3,0,SUMPRODUCT(--(ROW('04 变换后数据'!$D$5:$D$160)<=ROW()),--ISNUMBER(OFFSET('04 变换后数据'!$D$5:$D$160,ROW()-5-$G$3+1,0,MIN($G$3,ROW()-4),1)),--ISNUMBER(OFFSET('04 变换后数据'!$H$5:$H$160,ROW()-5-$G$3+1,0,MIN($G$3,ROW()-4),1)))) | I44: =IF(ISNUMBER(E44),IF(ABS(E44)>=0.7,"强",IF(ABS(E44)>=0.4,"中","弱")),"-")
A45: 41 | B45: ='04 变换后数据'!B45 | C45: =IF(41<$C$3,"",IF(445=0,"",IF(445<MAX(5,ROUND($C$3*0.8,0)),"样本不足",CORREL(OFFSET('04 变换后数据'!$D$5:$D$160,ROW()-5-$C$3+1,0,$C$3,1),OFFSET('04 变换后数据'!$H$5:$H$160,ROW()-5-$C$3+1,0,$C$3,1)))) | D45: =IF(41<$C$3,0,SUMPRODUCT(--(ROW('04 变换后数据'!$D$5:$D$160)<=ROW()),--ISNUMBER(OFFSET('04 变换后数据'!$D$5:$D$160,ROW()-5-$C$3+1,0,MIN($C$3,ROW()-4),1)),--ISNUMBER(OFFSET('04 变换后数据'!$H$5:$H$160,ROW()-5-$C$3+1,0,MIN($C$3,ROW()-4),1)))) | E45: =IF(41<$E$3,"",IF(645=0,"",IF(645<MAX(5,ROUND($E$3*0.8,0)),"样本不足",CORREL(OFFSET('04 变换后数据'!$D$5:$D$160,ROW()-5-$E$3+1,0,$E$3,1),OFFSET('04 变换后数据'!$H$5:$H$160,ROW()-5-$E$3+1,0,$E$3,1)))) | F45: =IF(41<$E$3,0,SUMPRODUCT(--(ROW('04 变换后数据'!$D$5:$D$160)<=ROW()),--ISNUMBER(OFFSET('04 变换后数据'!$D$5:$D$160,ROW()-5-$E$3+1,0,MIN($E$3,ROW()-4),1)),--ISNUMBER(OFFSET('04 变换后数据'!$H$5:$H$160,ROW()-5-$E$3+1,0,MIN($E$3,ROW()-4),1)))) | G45: =IF(41<$G$3,"",IF(845=0,"",IF(845<MAX(5,ROUND($G$3*0.8,0)),"样本不足",CORREL(OFFSET('04 变换后数据'!$D$5:$D$160,ROW()-5-$G$3+1,0,$G$3,1),OFFSET('04 变换后数据'!$H$5:$H$160,ROW()-5-$G$3+1,0,$G$3,1)))) | H45: =IF(41<$G$3,0,SUMPRODUCT(--(ROW('04 变换后数据'!$D$5:$D$160)<=ROW()),--ISNUMBER(OFFSET('04 变换后数据'!$D$5:$D$160,ROW()-5-$G$3+1,0,MIN($G$3,ROW()-4),1)),--ISNUMBER(OFFSET('04 变换后数据'!$H$5:$H$160,ROW()-5-$G$3+1,0,MIN($G$3,ROW()-4),1)))) | I45: =IF(ISNUMBER(E45),IF(ABS(E45)>=0.7,"强",IF(ABS(E45)>=0.4,"中","弱")),"-")
A46: 42 | B46: ='04 变换后数据'!B46 | C46: =IF(42<$C$3,"",IF(446=0,"",IF(446<MAX(5,ROUND($C$3*0.8,0)),"样本不足",CORREL(OFFSET('04 变换后数据'!$D$5:$D$160,ROW()-5-$C$3+1,0,$C$3,1),OFFSET('04 变换后数据'!$H$5:$H$160,ROW()-5-$C$3+1,0,$C$3,1)))) | D46: =IF(42<$C$3,0,SUMPRODUCT(--(ROW('04 变换后数据'!$D$5:$D$160)<=ROW()),--ISNUMBER(OFFSET('04 变换后数据'!$D$5:$D$160,ROW()-5-$C$3+1,0,MIN($C$3,ROW()-4),1)),--ISNUMBER(OFFSET('04 变换后数据'!$H$5:$H$160,ROW()-5-$C$3+1,0,MIN($C$3,ROW()-4),1)))) | E46: =IF(42<$E$3,"",IF(646=0,"",IF(646<MAX(5,ROUND($E$3*0.8,0)),"样本不足",CORREL(OFFSET('04 变换后数据'!$D$5:$D$160,ROW()-5-$E$3+1,0,$E$3,1),OFFSET('04 变换后数据'!$H$5:$H$160,ROW()-5-$E$3+1,0,$E$3,1)))) | F46: =IF(42<$E$3,0,SUMPRODUCT(--(ROW('04 变换后数据'!$D$5:$D$160)<=ROW()),--ISNUMBER(OFFSET('04 变换后数据'!$D$5:$D$160,ROW()-5-$E$3+1,0,MIN($E$3,ROW()-4),1)),--ISNUMBER(OFFSET('04 变换后数据'!$H$5:$H$160,ROW()-5-$E$3+1,0,MIN($E$3,ROW()-4),1)))) | G46: =IF(42<$G$3,"",IF(846=0,"",IF(846<MAX(5,ROUND($G$3*0.8,0)),"样本不足",CORREL(OFFSET('04 变换后数据'!$D$5:$D$160,ROW()-5-$G$3+1,0,$G$3,1),OFFSET('04 变换后数据'!$H$5:$H$160,ROW()-5-$G$3+1,0,$G$3,1)))) | H46: =IF(42<$G$3,0,SUMPRODUCT(--(ROW('04 变换后数据'!$D$5:$D$160)<=ROW()),--ISNUMBER(OFFSET('04 变换后数据'!$D$5:$D$160,ROW()-5-$G$3+1,0,MIN($G$3,ROW()-4),1)),--ISNUMBER(OFFSET('04 变换后数据'!$H$5:$H$160,ROW()-5-$G$3+1,0,MIN($G$3,ROW()-4),1)))) | I46: =IF(ISNUMBER(E46),IF(ABS(E46)>=0.7,"强",IF(ABS(E46)>=0.4,"中","弱")),"-")
A47: 43 | B47: ='04 变换后数据'!B47 | C47: =IF(43<$C$3,"",IF(447=0,"",IF(447<MAX(5,ROUND($C$3*0.8,0)),"样本不足",CORREL(OFFSET('04 变换后数据'!$D$5:$D$160,ROW()-5-$C$3+1,0,$C$3,1),OFFSET('04 变换后数据'!$H$5:$H$160,ROW()-5-$C$3+1,0,$C$3,1)))) | D47: =IF(43<$C$3,0,SUMPRODUCT(--(ROW('04 变换后数据'!$D$5:$D$160)<=ROW()),--ISNUMBER(OFFSET('04 变换后数据'!$D$5:$D$160,ROW()-5-$C$3+1,0,MIN($C$3,ROW()-4),1)),--ISNUMBER(OFFSET('04 变换后数据'!$H$5:$H$160,ROW()-5-$C$3+1,0,MIN($C$3,ROW()-4),1)))) | E47: =IF(43<$E$3,"",IF(647=0,"",IF(647<MAX(5,ROUND($E$3*0.8,0)),"样本不足",CORREL(OFFSET('04 变换后数据'!$D$5:$D$160,ROW()-5-$E$3+1,0,$E$3,1),OFFSET('04 变换后数据'!$H$5:$H$160,ROW()-5-$E$3+1,0,$E$3,1)))) | F47: =IF(43<$E$3,0,SUMPRODUCT(--(ROW('04 变换后数据'!$D$5:$D$160)<=ROW()),--ISNUMBER(OFFSET('04 变换后数据'!$D$5:$D$160,ROW()-5-$E$3+1,0,MIN($E$3,ROW()-4),1)),--ISNUMBER(OFFSET('04 变换后数据'!$H$5:$H$160,ROW()-5-$E$3+1,0,MIN($E$3,ROW()-4),1)))) | G47: =IF(43<$G$3,"",IF(847=0,"",IF(847<MAX(5,ROUND($G$3*0.8,0)),"样本不足",CORREL(OFFSET('04 变换后数据'!$D$5:$D$160,ROW()-5-$G$3+1,0,$G$3,1),OFFSET('04 变换后数据'!$H$5:$H$160,ROW()-5-$G$3+1,0,$G$3,1)))) | H47: =IF(43<$G$3,0,SUMPRODUCT(--(ROW('04 变换后数据'!$D$5:$D$160)<=ROW()),--ISNUMBER(OFFSET('04 变换后数据'!$D$5:$D$160,ROW()-5-$G$3+1,0,MIN($G$3,ROW()-4),1)),--ISNUMBER(OFFSET('04 变换后数据'!$H$5:$H$160,ROW()-5-$G$3+1,0,MIN($G$3,ROW()-4),1)))) | I47: =IF(ISNUMBER(E47),IF(ABS(E47)>=0.7,"强",IF(ABS(E47)>=0.4,"中","弱")),"-")
A48: 44 | B48: ='04 变换后数据'!B48 | C48: =IF(44<$C$3,"",IF(448=0,"",IF(448<MAX(5,ROUND($C$3*0.8,0)),"样本不足",CORREL(OFFSET('04 变换后数据'!$D$5:$D$160,ROW()-5-$C$3+1,0,$C$3,1),OFFSET('04 变换后数据'!$H$5:$H$160,ROW()-5-$C$3+1,0,$C$3,1)))) | D48: =IF(44<$C$3,0,SUMPRODUCT(--(ROW('04 变换后数据'!$D$5:$D$160)<=ROW()),--ISNUMBER(OFFSET('04 变换后数据'!$D$5:$D$160,ROW()-5-$C$3+1,0,MIN($C$3,ROW()-4),1)),--ISNUMBER(OFFSET('04 变换后数据'!$H$5:$H$160,ROW()-5-$C$3+1,0,MIN($C$3,ROW()-4),1)))) | E48: =IF(44<$E$3,"",IF(648=0,"",IF(648<MAX(5,ROUND($E$3*0.8,0)),"样本不足",CORREL(OFFSET('04 变换后数据'!$D$5:$D$160,ROW()-5-$E$3+1,0,$E$3,1),OFFSET('04 变换后数据'!$H$5:$H$160,ROW()-5-$E$3+1,0,$E$3,1)))) | F48: =IF(44<$E$3,0,SUMPRODUCT(--(ROW('04 变换后数据'!$D$5:$D$160)<=ROW()),--ISNUMBER(OFFSET('04 变换后数据'!$D$5:$D$160,ROW()-5-$E$3+1,0,MIN($E$3,ROW()-4),1)),--ISNUMBER(OFFSET('04 变换后数据'!$H$5:$H$160,ROW()-5-$E$3+1,0,MIN($E$3,ROW()-4),1)))) | G48: =IF(44<$G$3,"",IF(848=0,"",IF(848<MAX(5,ROUND($G$3*0.8,0)),"样本不足",CORREL(OFFSET('04 变换后数据'!$D$5:$D$160,ROW()-5-$G$3+1,0,$G$3,1),OFFSET('04 变换后数据'!$H$5:$H$160,ROW()-5-$G$3+1,0,$G$3,1)))) | H48: =IF(44<$G$3,0,SUMPRODUCT(--(ROW('04 变换后数据'!$D$5:$D$160)<=ROW()),--ISNUMBER(OFFSET('04 变换后数据'!$D$5:$D$160,ROW()-5-$G$3+1,0,MIN($G$3,ROW()-4),1)),--ISNUMBER(OFFSET('04 变换后数据'!$H$5:$H$160,ROW()-5-$G$3+1,0,MIN($G$3,ROW()-4),1)))) | I48: =IF(ISNUMBER(E48),IF(ABS(E48)>=0.7,"强",IF(ABS(E48)>=0.4,"中","弱")),"-")
A49: 45 | B49: ='04 变换后数据'!B49 | C49: =IF(45<$C$3,"",IF(449=0,"",IF(449<MAX(5,ROUND($C$3*0.8,0)),"样本不足",CORREL(OFFSET('04 变换后数据'!$D$5:$D$160,ROW()-5-$C$3+1,0,$C$3,1),OFFSET('04 变换后数据'!$H$5:$H$160,ROW()-5-$C$3+1,0,$C$3,1)))) | D49: =IF(45<$C$3,0,SUMPRODUCT(--(ROW('04 变换后数据'!$D$5:$D$160)<=ROW()),--ISNUMBER(OFFSET('04 变换后数据'!$D$5:$D$160,ROW()-5-$C$3+1,0,MIN($C$3,ROW()-4),1)),--ISNUMBER(OFFSET('04 变换后数据'!$H$5:$H$160,ROW()-5-$C$3+1,0,MIN($C$3,ROW()-4),1)))) | E49: =IF(45<$E$3,"",IF(649=0,"",IF(649<MAX(5,ROUND($E$3*0.8,0)),"样本不足",CORREL(OFFSET('04 变换后数据'!$D$5:$D$160,ROW()-5-$E$3+1,0,$E$3,1),OFFSET('04 变换后数据'!$H$5:$H$160,ROW()-5-$E$3+1,0,$E$3,1)))) | F49: =IF(45<$E$3,0,SUMPRODUCT(--(ROW('04 变换后数据'!$D$5:$D$160)<=ROW()),--ISNUMBER(OFFSET('04 变换后数据'!$D$5:$D$160,ROW()-5-$E$3+1,0,MIN($E$3,ROW()-4),1)),--ISNUMBER(OFFSET('04 变换后数据'!$H$5:$H$160,ROW()-5-$E$3+1,0,MIN($E$3,ROW()-4),1)))) | G49: =IF(45<$G$3,"",IF(849=0,"",IF(849<MAX(5,ROUND($G$3*0.8,0)),"样本不足",CORREL(OFFSET('04 变换后数据'!$D$5:$D$160,ROW()-5-$G$3+1,0,$G$3,1),OFFSET('04 变换后数据'!$H$5:$H$160,ROW()-5-$G$3+1,0,$G$3,1)))) | H49: =IF(45<$G$3,0,SUMPRODUCT(--(ROW('04 变换后数据'!$D$5:$D$160)<=ROW()),--ISNUMBER(OFFSET('04 变换后数据'!$D$5:$D$160,ROW()-5-$G$3+1,0,MIN($G$3,ROW()-4),1)),--ISNUMBER(OFFSET('04 变换后数据'!$H$5:$H$160,ROW()-5-$G$3+1,0,MIN($G$3,ROW()-4),1)))) | I49: =IF(ISNUMBER(E49),IF(ABS(E49)>=0.7,"强",IF(ABS(E49)>=0.4,"中","弱")),"-")
A50: 46 | B50: ='04 变换后数据'!B50 | C50: =IF(46<$C$3,"",IF(450=0,"",IF(450<MAX(5,ROUND($C$3*0.8,0)),"样本不足",CORREL(OFFSET('04 变换后数据'!$D$5:$D$160,ROW()-5-$C$3+1,0,$C$3,1),OFFSET('04 变换后数据'!$H$5:$H$160,ROW()-5-$C$3+1,0,$C$3,1)))) | D50: =IF(46<$C$3,0,SUMPRODUCT(--(ROW('04 变换后数据'!$D$5:$D$160)<=ROW()),--ISNUMBER(OFFSET('04 变换后数据'!$D$5:$D$160,ROW()-5-$C$3+1,0,MIN($C$3,ROW()-4),1)),--ISNUMBER(OFFSET('04 变换后数据'!$H$5:$H$160,ROW()-5-$C$3+1,0,MIN($C$3,ROW()-4),1)))) | E50: =IF(46<$E$3,"",IF(650=0,"",IF(650<MAX(5,ROUND($E$3*0.8,0)),"样本不足",CORREL(OFFSET('04 变换后数据'!$D$5:$D$160,ROW()-5-$E$3+1,0,$E$3,1),OFFSET('04 变换后数据'!$H$5:$H$160,ROW()-5-$E$3+1,0,$E$3,1)))) | F50: =IF(46<$E$3,0,SUMPRODUCT(--(ROW('04 变换后数据'!$D$5:$D$160)<=ROW()),--ISNUMBER(OFFSET('04 变换后数据'!$D$5:$D$160,ROW()-5-$E$3+1,0,MIN($E$3,ROW()-4),1)),--ISNUMBER(OFFSET('04 变换后数据'!$H$5:$H$160,ROW()-5-$E$3+1,0,MIN($E$3,ROW()-4),1)))) | G50: =IF(46<$G$3,"",IF(850=0,"",IF(850<MAX(5,ROUND($G$3*0.8,0)),"样本不足",CORREL(OFFSET('04 变换后数据'!$D$5:$D$160,ROW()-5-$G$3+1,0,$G$3,1),OFFSET('04 变换后数据'!$H$5:$H$160,ROW()-5-$G$3+1,0,$G$3,1)))) | H50: =IF(46<$G$3,0,SUMPRODUCT(--(ROW('04 变换后数据'!$D$5:$D$160)<=ROW()),--ISNUMBER(OFFSET('04 变换后数据'!$D$5:$D$160,ROW()-5-$G$3+1,0,MIN($G$3,ROW()-4),1)),--ISNUMBER(OFFSET('04 变换后数据'!$H$5:$H$160,ROW()-5-$G$3+1,0,MIN($G$3,ROW()-4),1)))) | I50: =IF(ISNUMBER(E50),IF(ABS(E50)>=0.7,"强",IF(ABS(E50)>=0.4,"中","弱")),"-")
A51: 47 | B51: ='04 变换后数据'!B51 | C51: =IF(47<$C$3,"",IF(451=0,"",IF(451<MAX(5,ROUND($C$3*0.8,0)),"样本不足",CORREL(OFFSET('04 变换后数据'!$D$5:$D$160,ROW()-5-$C$3+1,0,$C$3,1),OFFSET('04 变换后数据'!$H$5:$H$160,ROW()-5-$C$3+1,0,$C$3,1)))) | D51: =IF(47<$C$3,0,SUMPRODUCT(--(ROW('04 变换后数据'!$D$5:$D$160)<=ROW()),--ISNUMBER(OFFSET('04 变换后数据'!$D$5:$D$160,ROW()-5-$C$3+1,0,MIN($C$3,ROW()-4),1)),--ISNUMBER(OFFSET('04 变换后数据'!$H$5:$H$160,ROW()-5-$C$3+1,0,MIN($C$3,ROW()-4),1)))) | E51: =IF(47<$E$3,"",IF(651=0,"",IF(651<MAX(5,ROUND($E$3*0.8,0)),"样本不足",CORREL(OFFSET('04 变换后数据'!$D$5:$D$160,ROW()-5-$E$3+1,0,$E$3,1),OFFSET('04 变换后数据'!$H$5:$H$160,ROW()-5-$E$3+1,0,$E$3,1)))) | F51: =IF(47<$E$3,0,SUMPRODUCT(--(ROW('04 变换后数据'!$D$5:$D$160)<=ROW()),--ISNUMBER(OFFSET('04 变换后数据'!$D$5:$D$160,ROW()-5-$E$3+1,0,MIN($E$3,ROW()-4),1)),--ISNUMBER(OFFSET('04 变换后数据'!$H$5:$H$160,ROW()-5-$E$3+1,0,MIN($E$3,ROW()-4),1)))) | G51: =IF(47<$G$3,"",IF(851=0,"",IF(851<MAX(5,ROUND($G$3*0.8,0)),"样本不足",CORREL(OFFSET('04 变换后数据'!$D$5:$D$160,ROW()-5-$G$3+1,0,$G$3,1),OFFSET('04 变换后数据'!$H$5:$H$160,ROW()-5-$G$3+1,0,$G$3,1)))) | H51: =IF(47<$G$3,0,SUMPRODUCT(--(ROW('04 变换后数据'!$D$5:$D$160)<=ROW()),--ISNUMBER(OFFSET('04 变换后数据'!$D$5:$D$160,ROW()-5-$G$3+1,0,MIN($G$3,ROW()-4),1)),--ISNUMBER(OFFSET('04 变换后数据'!$H$5:$H$160,ROW()-5-$G$3+1,0,MIN($G$3,ROW()-4),1)))) | I51: =IF(ISNUMBER(E51),IF(ABS(E51)>=0.7,"强",IF(ABS(E51)>=0.4,"中","弱")),"-")
A52: 48 | B52: ='04 变换后数据'!B52 | C52: =IF(48<$C$3,"",IF(452=0,"",IF(452<MAX(5,ROUND($C$3*0.8,0)),"样本不足",CORREL(OFFSET('04 变换后数据'!$D$5:$D$160,ROW()-5-$C$3+1,0,$C$3,1),OFFSET('04 变换后数据'!$H$5:$H$160,ROW()-5-$C$3+1,0,$C$3,1)))) | D52: =IF(48<$C$3,0,SUMPRODUCT(--(ROW('04 变换后数据'!$D$5:$D$160)<=ROW()),--ISNUMBER(OFFSET('04 变换后数据'!$D$5:$D$160,ROW()-5-$C$3+1,0,MIN($C$3,ROW()-4),1)),--ISNUMBER(OFFSET('04 变换后数据'!$H$5:$H$160,ROW()-5-$C$3+1,0,MIN($C$3,ROW()-4),1)))) | E52: =IF(48<$E$3,"",IF(652=0,"",IF(652<MAX(5,ROUND($E$3*0.8,0)),"样本不足",CORREL(OFFSET('04 变换后数据'!$D$5:$D$160,ROW()-5-$E$3+1,0,$E$3,1),OFFSET('04 变换后数据'!$H$5:$H$160,ROW()-5-$E$3+1,0,$E$3,1)))) | F52: =IF(48<$E$3,0,SUMPRODUCT(--(ROW('04 变换后数据'!$D$5:$D$160)<=ROW()),--ISNUMBER(OFFSET('04 变换后数据'!$D$5:$D$160,ROW()-5-$E$3+1,0,MIN($E$3,ROW()-4),1)),--ISNUMBER(OFFSET('04 变换后数据'!$H$5:$H$160,ROW()-5-$E$3+1,0,MIN($E$3,ROW()-4),1)))) | G52: =IF(48<$G$3,"",IF(852=0,"",IF(852<MAX(5,ROUND($G$3*0.8,0)),"样本不足",CORREL(OFFSET('04 变换后数据'!$D$5:$D$160,ROW()-5-$G$3+1,0,$G$3,1),OFFSET('04 变换后数据'!$H$5:$H$160,ROW()-5-$G$3+1,0,$G$3,1)))) | H52: =IF(48<$G$3,0,SUMPRODUCT(--(ROW('04 变换后数据'!$D$5:$D$160)<=ROW()),--ISNUMBER(OFFSET('04 变换后数据'!$D$5:$D$160,ROW()-5-$G$3+1,0,MIN($G$3,ROW()-4),1)),--ISNUMBER(OFFSET('04 变换后数据'!$H$5:$H$160,ROW()-5-$G$3+1,0,MIN($G$3,ROW()-4),1)))) | I52: =IF(ISNUMBER(E52),IF(ABS(E52)>=0.7,"强",IF(ABS(E52)>=0.4,"中","弱")),"-")
A53: 49 | B53: ='04 变换后数据'!B53 | C53: =IF(49<$C$3,"",IF(453=0,"",IF(453<MAX(5,ROUND($C$3*0.8,0)),"样本不足",CORREL(OFFSET('04 变换后数据'!$D$5:$D$160,ROW()-5-$C$3+1,0,$C$3,1),OFFSET('04 变换后数据'!$H$5:$H$160,ROW()-5-$C$3+1,0,$C$3,1)))) | D53: =IF(49<$C$3,0,SUMPRODUCT(--(ROW('04 变换后数据'!$D$5:$D$160)<=ROW()),--ISNUMBER(OFFSET('04 变换后数据'!$D$5:$D$160,ROW()-5-$C$3+1,0,MIN($C$3,ROW()-4),1)),--ISNUMBER(OFFSET('04 变换后数据'!$H$5:$H$160,ROW()-5-$C$3+1,0,MIN($C$3,ROW()-4),1)))) | E53: =IF(49<$E$3,"",IF(653=0,"",IF(653<MAX(5,ROUND($E$3*0.8,0)),"样本不足",CORREL(OFFSET('04 变换后数据'!$D$5:$D$160,ROW()-5-$E$3+1,0,$E$3,1),OFFSET('04 变换后数据'!$H$5:$H$160,ROW()-5-$E$3+1,0,$E$3,1)))) | F53: =IF(49<$E$3,0,SUMPRODUCT(--(ROW('04 变换后数据'!$D$5:$D$160)<=ROW()),--ISNUMBER(OFFSET('04 变换后数据'!$D$5:$D$160,ROW()-5-$E$3+1,0,MIN($E$3,ROW()-4),1)),--ISNUMBER(OFFSET('04 变换后数据'!$H$5:$H$160,ROW()-5-$E$3+1,0,MIN($E$3,ROW()-4),1)))) | G53: =IF(49<$G$3,"",IF(853=0,"",IF(853<MAX(5,ROUND($G$3*0.8,0)),"样本不足",CORREL(OFFSET('04 变换后数据'!$D$5:$D$160,ROW()-5-$G$3+1,0,$G$3,1),OFFSET('04 变换后数据'!$H$5:$H$160,ROW()-5-$G$3+1,0,$G$3,1)))) | H53: =IF(49<$G$3,0,SUMPRODUCT(--(ROW('04 变换后数据'!$D$5:$D$160)<=ROW()),--ISNUMBER(OFFSET('04 变换后数据'!$D$5:$D$160,ROW()-5-$G$3+1,0,MIN($G$3,ROW()-4),1)),--ISNUMBER(OFFSET('04 变换后数据'!$H$5:$H$160,ROW()-5-$G$3+1,0,MIN($G$3,ROW()-4),1)))) | I53: =IF(ISNUMBER(E53),IF(ABS(E53)>=0.7,"强",IF(ABS(E53)>=0.4,"中","弱")),"-")
A54: 50 | B54: ='04 变换后数据'!B54 | C54: =IF(50<$C$3,"",IF(454=0,"",IF(454<MAX(5,ROUND($C$3*0.8,0)),"样本不足",CORREL(OFFSET('04 变换后数据'!$D$5:$D$160,ROW()-5-$C$3+1,0,$C$3,1),OFFSET('04 变换后数据'!$H$5:$H$160,ROW()-5-$C$3+1,0,$C$3,1)))) | D54: =IF(50<$C$3,0,SUMPRODUCT(--(ROW('04 变换后数据'!$D$5:$D$160)<=ROW()),--ISNUMBER(OFFSET('04 变换后数据'!$D$5:$D$160,ROW()-5-$C$3+1,0,MIN($C$3,ROW()-4),1)),--ISNUMBER(OFFSET('04 变换后数据'!$H$5:$H$160,ROW()-5-$C$3+1,0,MIN($C$3,ROW()-4),1)))) | E54: =IF(50<$E$3,"",IF(654=0,"",IF(654<MAX(5,ROUND($E$3*0.8,0)),"样本不足",CORREL(OFFSET('04 变换后数据'!$D$5:$D$160,ROW()-5-$E$3+1,0,$E$3,1),OFFSET('04 变换后数据'!$H$5:$H$160,ROW()-5-$E$3+1,0,$E$3,1)))) | F54: =IF(50<$E$3,0,SUMPRODUCT(--(ROW('04 变换后数据'!$D$5:$D$160)<=ROW()),--ISNUMBER(OFFSET('04 变换后数据'!$D$5:$D$160,ROW()-5-$E$3+1,0,MIN($E$3,ROW()-4),1)),--ISNUMBER(OFFSET('04 变换后数据'!$H$5:$H$160,ROW()-5-$E$3+1,0,MIN($E$3,ROW()-4),1)))) | G54: =IF(50<$G$3,"",IF(854=0,"",IF(854<MAX(5,ROUND($G$3*0.8,0)),"样本不足",CORREL(OFFSET('04 变换后数据'!$D$5:$D$160,ROW()-5-$G$3+1,0,$G$3,1),OFFSET('04 变换后数据'!$H$5:$H$160,ROW()-5-$G$3+1,0,$G$3,1)))) | H54: =IF(50<$G$3,0,SUMPRODUCT(--(ROW('04 变换后数据'!$D$5:$D$160)<=ROW()),--ISNUMBER(OFFSET('04 变换后数据'!$D$5:$D$160,ROW()-5-$G$3+1,0,MIN($G$3,ROW()-4),1)),--ISNUMBER(OFFSET('04 变换后数据'!$H$5:$H$160,ROW()-5-$G$3+1,0,MIN($G$3,ROW()-4),1)))) | I54: =IF(ISNUMBER(E54),IF(ABS(E54)>=0.7,"强",IF(ABS(E54)>=0.4,"中","弱")),"-")
A55: 51 | B55: ='04 变换后数据'!B55 | C55: =IF(51<$C$3,"",IF(455=0,"",IF(455<MAX(5,ROUND($C$3*0.8,0)),"样本不足",CORREL(OFFSET('04 变换后数据'!$D$5:$D$160,ROW()-5-$C$3+1,0,$C$3,1),OFFSET('04 变换后数据'!$H$5:$H$160,ROW()-5-$C$3+1,0,$C$3,1)))) | D55: =IF(51<$C$3,0,SUMPRODUCT(--(ROW('04 变换后数据'!$D$5:$D$160)<=ROW()),--ISNUMBER(OFFSET('04 变换后数据'!$D$5:$D$160,ROW()-5-$C$3+1,0,MIN($C$3,ROW()-4),1)),--ISNUMBER(OFFSET('04 变换后数据'!$H$5:$H$160,ROW()-5-$C$3+1,0,MIN($C$3,ROW()-4),1)))) | E55: =IF(51<$E$3,"",IF(655=0,"",IF(655<MAX(5,ROUND($E$3*0.8,0)),"样本不足",CORREL(OFFSET('04 变换后数据'!$D$5:$D$160,ROW()-5-$E$3+1,0,$E$3,1),OFFSET('04 变换后数据'!$H$5:$H$160,ROW()-5-$E$3+1,0,$E$3,1)))) | F55: =IF(51<$E$3,0,SUMPRODUCT(--(ROW('04 变换后数据'!$D$5:$D$160)<=ROW()),--ISNUMBER(OFFSET('04 变换后数据'!$D$5:$D$160,ROW()-5-$E$3+1,0,MIN($E$3,ROW()-4),1)),--ISNUMBER(OFFSET('04 变换后数据'!$H$5:$H$160,ROW()-5-$E$3+1,0,MIN($E$3,ROW()-4),1)))) | G55: =IF(51<$G$3,"",IF(855=0,"",IF(855<MAX(5,ROUND($G$3*0.8,0)),"样本不足",CORREL(OFFSET('04 变换后数据'!$D$5:$D$160,ROW()-5-$G$3+1,0,$G$3,1),OFFSET('04 变换后数据'!$H$5:$H$160,ROW()-5-$G$3+1,0,$G$3,1)))) | H55: =IF(51<$G$3,0,SUMPRODUCT(--(ROW('04 变换后数据'!$D$5:$D$160)<=ROW()),--ISNUMBER(OFFSET('04 变换后数据'!$D$5:$D$160,ROW()-5-$G$3+1,0,MIN($G$3,ROW()-4),1)),--ISNUMBER(OFFSET('04 变换后数据'!$H$5:$H$160,ROW()-5-$G$3+1,0,MIN($G$3,ROW()-4),1)))) | I55: =IF(ISNUMBER(E55),IF(ABS(E55)>=0.7,"强",IF(ABS(E55)>=0.4,"中","弱")),"-")
A56: 52 | B56: ='04 变换后数据'!B56 | C56: =IF(52<$C$3,"",IF(456=0,"",IF(456<MAX(5,ROUND($C$3*0.8,0)),"样本不足",CORREL(OFFSET('04 变换后数据'!$D$5:$D$160,ROW()-5-$C$3+1,0,$C$3,1),OFFSET('04 变换后数据'!$H$5:$H$160,ROW()-5-$C$3+1,0,$C$3,1)))) | D56: =IF(52<$C$3,0,SUMPRODUCT(--(ROW('04 变换后数据'!$D$5:$D$160)<=ROW()),--ISNUMBER(OFFSET('04 变换后数据'!$D$5:$D$160,ROW()-5-$C$3+1,0,MIN($C$3,ROW()-4),1)),--ISNUMBER(OFFSET('04 变换后数据'!$H$5:$H$160,ROW()-5-$C$3+1,0,MIN($C$3,ROW()-4),1)))) | E56: =IF(52<$E$3,"",IF(656=0,"",IF(656<MAX(5,ROUND($E$3*0.8,0)),"样本不足",CORREL(OFFSET('04 变换后数据'!$D$5:$D$160,ROW()-5-$E$3+1,0,$E$3,1),OFFSET('04 变换后数据'!$H$5:$H$160,ROW()-5-$E$3+1,0,$E$3,1)))) | F56: =IF(52<$E$3,0,SUMPRODUCT(--(ROW('04 变换后数据'!$D$5:$D$160)<=ROW()),--ISNUMBER(OFFSET('04 变换后数据'!$D$5:$D$160,ROW()-5-$E$3+1,0,MIN($E$3,ROW()-4),1)),--ISNUMBER(OFFSET('04 变换后数据'!$H$5:$H$160,ROW()-5-$E$3+1,0,MIN($E$3,ROW()-4),1)))) | G56: =IF(52<$G$3,"",IF(856=0,"",IF(856<MAX(5,ROUND($G$3*0.8,0)),"样本不足",CORREL(OFFSET('04 变换后数据'!$D$5:$D$160,ROW()-5-$G$3+1,0,$G$3,1),OFFSET('04 变换后数据'!$H$5:$H$160,ROW()-5-$G$3+1,0,$G$3,1)))) | H56: =IF(52<$G$3,0,SUMPRODUCT(--(ROW('04 变换后数据'!$D$5:$D$160)<=ROW()),--ISNUMBER(OFFSET('04 变换后数据'!$D$5:$D$160,ROW()-5-$G$3+1,0,MIN($G$3,ROW()-4),1)),--ISNUMBER(OFFSET('04 变换后数据'!$H$5:$H$160,ROW()-5-$G$3+1,0,MIN($G$3,ROW()-4),1)))) | I56: =IF(ISNUMBER(E56),IF(ABS(E56)>=0.7,"强",IF(ABS(E56)>=0.4,"中","弱")),"-")
A57: 53 | B57: ='04 变换后数据'!B57 | C57: =IF(53<$C$3,"",IF(457=0,"",IF(457<MAX(5,ROUND($C$3*0.8,0)),"样本不足",CORREL(OFFSET('04 变换后数据'!$D$5:$D$160,ROW()-5-$C$3+1,0,$C$3,1),OFFSET('04 变换后数据'!$H$5:$H$160,ROW()-5-$C$3+1,0,$C$3,1)))) | D57: =IF(53<$C$3,0,SUMPRODUCT(--(ROW('04 变换后数据'!$D$5:$D$160)<=ROW()),--ISNUMBER(OFFSET('04 变换后数据'!$D$5:$D$160,ROW()-5-$C$3+1,0,MIN($C$3,ROW()-4),1)),--ISNUMBER(OFFSET('04 变换后数据'!$H$5:$H$160,ROW()-5-$C$3+1,0,MIN($C$3,ROW()-4),1)))) | E57: =IF(53<$E$3,"",IF(657=0,"",IF(657<MAX(5,ROUND($E$3*0.8,0)),"样本不足",CORREL(OFFSET('04 变换后数据'!$D$5:$D$160,ROW()-5-$E$3+1,0,$E$3,1),OFFSET('04 变换后数据'!$H$5:$H$160,ROW()-5-$E$3+1,0,$E$3,1)))) | F57: =IF(53<$E$3,0,SUMPRODUCT(--(ROW('04 变换后数据'!$D$5:$D$160)<=ROW()),--ISNUMBER(OFFSET('04 变换后数据'!$D$5:$D$160,ROW()-5-$E$3+1,0,MIN($E$3,ROW()-4),1)),--ISNUMBER(OFFSET('04 变换后数据'!$H$5:$H$160,ROW()-5-$E$3+1,0,MIN($E$3,ROW()-4),1)))) | G57: =IF(53<$G$3,"",IF(857=0,"",IF(857<MAX(5,ROUND($G$3*0.8,0)),"样本不足",CORREL(OFFSET('04 变换后数据'!$D$5:$D$160,ROW()-5-$G$3+1,0,$G$3,1),OFFSET('04 变换后数据'!$H$5:$H$160,ROW()-5-$G$3+1,0,$G$3,1)))) | H57: =IF(53<$G$3,0,SUMPRODUCT(--(ROW('04 变换后数据'!$D$5:$D$160)<=ROW()),--ISNUMBER(OFFSET('04 变换后数据'!$D$5:$D$160,ROW()-5-$G$3+1,0,MIN($G$3,ROW()-4),1)),--ISNUMBER(OFFSET('04 变换后数据'!$H$5:$H$160,ROW()-5-$G$3+1,0,MIN($G$3,ROW()-4),1)))) | I57: =IF(ISNUMBER(E57),IF(ABS(E57)>=0.7,"强",IF(ABS(E57)>=0.4,"中","弱")),"-")
A58: 54 | B58: ='04 变换后数据'!B58 | C58: =IF(54<$C$3,"",IF(458=0,"",IF(458<MAX(5,ROUND($C$3*0.8,0)),"样本不足",CORREL(OFFSET('04 变换后数据'!$D$5:$D$160,ROW()-5-$C$3+1,0,$C$3,1),OFFSET('04 变换后数据'!$H$5:$H$160,ROW()-5-$C$3+1,0,$C$3,1)))) | D58: =IF(54<$C$3,0,SUMPRODUCT(--(ROW('04 变换后数据'!$D$5:$D$160)<=ROW()),--ISNUMBER(OFFSET('04 变换后数据'!$D$5:$D$160,ROW()-5-$C$3+1,0,MIN($C$3,ROW()-4),1)),--ISNUMBER(OFFSET('04 变换后数据'!$H$5:$H$160,ROW()-5-$C$3+1,0,MIN($C$3,ROW()-4),1)))) | E58: =IF(54<$E$3,"",IF(658=0,"",IF(658<MAX(5,ROUND($E$3*0.8,0)),"样本不足",CORREL(OFFSET('04 变换后数据'!$D$5:$D$160,ROW()-5-$E$3+1,0,$E$3,1),OFFSET('04 变换后数据'!$H$5:$H$160,ROW()-5-$E$3+1,0,$E$3,1)))) | F58: =IF(54<$E$3,0,SUMPRODUCT(--(ROW('04 变换后数据'!$D$5:$D$160)<=ROW()),--ISNUMBER(OFFSET('04 变换后数据'!$D$5:$D$160,ROW()-5-$E$3+1,0,MIN($E$3,ROW()-4),1)),--ISNUMBER(OFFSET('04 变换后数据'!$H$5:$H$160,ROW()-5-$E$3+1,0,MIN($E$3,ROW()-4),1)))) | G58: =IF(54<$G$3,"",IF(858=0,"",IF(858<MAX(5,ROUND($G$3*0.8,0)),"样本不足",CORREL(OFFSET('04 变换后数据'!$D$5:$D$160,ROW()-5-$G$3+1,0,$G$3,1),OFFSET('04 变换后数据'!$H$5:$H$160,ROW()-5-$G$3+1,0,$G$3,1)))) | H58: =IF(54<$G$3,0,SUMPRODUCT(--(ROW('04 变换后数据'!$D$5:$D$160)<=ROW()),--ISNUMBER(OFFSET('04 变换后数据'!$D$5:$D$160,ROW()-5-$G$3+1,0,MIN($G$3,ROW()-4),1)),--ISNUMBER(OFFSET('04 变换后数据'!$H$5:$H$160,ROW()-5-$G$3+1,0,MIN($G$3,ROW()-4),1)))) | I58: =IF(ISNUMBER(E58),IF(ABS(E58)>=0.7,"强",IF(ABS(E58)>=0.4,"中","弱")),"-")
A59: 55 | B59: ='04 变换后数据'!B59 | C59: =IF(55<$C$3,"",IF(459=0,"",IF(459<MAX(5,ROUND($C$3*0.8,0)),"样本不足",CORREL(OFFSET('04 变换后数据'!$D$5:$D$160,ROW()-5-$C$3+1,0,$C$3,1),OFFSET('04 变换后数据'!$H$5:$H$160,ROW()-5-$C$3+1,0,$C$3,1)))) | D59: =IF(55<$C$3,0,SUMPRODUCT(--(ROW('04 变换后数据'!$D$5:$D$160)<=ROW()),--ISNUMBER(OFFSET('04 变换后数据'!$D$5:$D$160,ROW()-5-$C$3+1,0,MIN($C$3,ROW()-4),1)),--ISNUMBER(OFFSET('04 变换后数据'!$H$5:$H$160,ROW()-5-$C$3+1,0,MIN($C$3,ROW()-4),1)))) | E59: =IF(55<$E$3,"",IF(659=0,"",IF(659<MAX(5,ROUND($E$3*0.8,0)),"样本不足",CORREL(OFFSET('04 变换后数据'!$D$5:$D$160,ROW()-5-$E$3+1,0,$E$3,1),OFFSET('04 变换后数据'!$H$5:$H$160,ROW()-5-$E$3+1,0,$E$3,1)))) | F59: =IF(55<$E$3,0,SUMPRODUCT(--(ROW('04 变换后数据'!$D$5:$D$160)<=ROW()),--ISNUMBER(OFFSET('04 变换后数据'!$D$5:$D$160,ROW()-5-$E$3+1,0,MIN($E$3,ROW()-4),1)),--ISNUMBER(OFFSET('04 变换后数据'!$H$5:$H$160,ROW()-5-$E$3+1,0,MIN($E$3,ROW()-4),1)))) | G59: =IF(55<$G$3,"",IF(859=0,"",IF(859<MAX(5,ROUND($G$3*0.8,0)),"样本不足",CORREL(OFFSET('04 变换后数据'!$D$5:$D$160,ROW()-5-$G$3+1,0,$G$3,1),OFFSET('04 变换后数据'!$H$5:$H$160,ROW()-5-$G$3+1,0,$G$3,1)))) | H59: =IF(55<$G$3,0,SUMPRODUCT(--(ROW('04 变换后数据'!$D$5:$D$160)<=ROW()),--ISNUMBER(OFFSET('04 变换后数据'!$D$5:$D$160,ROW()-5-$G$3+1,0,MIN($G$3,ROW()-4),1)),--ISNUMBER(OFFSET('04 变换后数据'!$H$5:$H$160,ROW()-5-$G$3+1,0,MIN($G$3,ROW()-4),1)))) | I59: =IF(ISNUMBER(E59),IF(ABS(E59)>=0.7,"强",IF(ABS(E59)>=0.4,"中","弱")),"-")
A60: 56 | B60: ='04 变换后数据'!B60 | C60: =IF(56<$C$3,"",IF(460=0,"",IF(460<MAX(5,ROUND($C$3*0.8,0)),"样本不足",CORREL(OFFSET('04 变换后数据'!$D$5:$D$160,ROW()-5-$C$3+1,0,$C$3,1),OFFSET('04 变换后数据'!$H$5:$H$160,ROW()-5-$C$3+1,0,$C$3,1)))) | D60: =IF(56<$C$3,0,SUMPRODUCT(--(ROW('04 变换后数据'!$D$5:$D$160)<=ROW()),--ISNUMBER(OFFSET('04 变换后数据'!$D$5:$D$160,ROW()-5-$C$3+1,0,MIN($C$3,ROW()-4),1)),--ISNUMBER(OFFSET('04 变换后数据'!$H$5:$H$160,ROW()-5-$C$3+1,0,MIN($C$3,ROW()-4),1)))) | E60: =IF(56<$E$3,"",IF(660=0,"",IF(660<MAX(5,ROUND($E$3*0.8,0)),"样本不足",CORREL(OFFSET('04 变换后数据'!$D$5:$D$160,ROW()-5-$E$3+1,0,$E$3,1),OFFSET('04 变换后数据'!$H$5:$H$160,ROW()-5-$E$3+1,0,$E$3,1)))) | F60: =IF(56<$E$3,0,SUMPRODUCT(--(ROW('04 变换后数据'!$D$5:$D$160)<=ROW()),--ISNUMBER(OFFSET('04 变换后数据'!$D$5:$D$160,ROW()-5-$E$3+1,0,MIN($E$3,ROW()-4),1)),--ISNUMBER(OFFSET('04 变换后数据'!$H$5:$H$160,ROW()-5-$E$3+1,0,MIN($E$3,ROW()-4),1)))) | G60: =IF(56<$G$3,"",IF(860=0,"",IF(860<MAX(5,ROUND($G$3*0.8,0)),"样本不足",CORREL(OFFSET('04 变换后数据'!$D$5:$D$160,ROW()-5-$G$3+1,0,$G$3,1),OFFSET('04 变换后数据'!$H$5:$H$160,ROW()-5-$G$3+1,0,$G$3,1)))) | H60: =IF(56<$G$3,0,SUMPRODUCT(--(ROW('04 变换后数据'!$D$5:$D$160)<=ROW()),--ISNUMBER(OFFSET('04 变换后数据'!$D$5:$D$160,ROW()-5-$G$3+1,0,MIN($G$3,ROW()-4),1)),--ISNUMBER(OFFSET('04 变换后数据'!$H$5:$H$160,ROW()-5-$G$3+1,0,MIN($G$3,ROW()-4),1)))) | I60: =IF(ISNUMBER(E60),IF(ABS(E60)>=0.7,"强",IF(ABS(E60)>=0.4,"中","弱")),"-")
A61: 57 | B61: ='04 变换后数据'!B61 | C61: =IF(57<$C$3,"",IF(461=0,"",IF(461<MAX(5,ROUND($C$3*0.8,0)),"样本不足",CORREL(OFFSET('04 变换后数据'!$D$5:$D$160,ROW()-5-$C$3+1,0,$C$3,1),OFFSET('04 变换后数据'!$H$5:$H$160,ROW()-5-$C$3+1,0,$C$3,1)))) | D61: =IF(57<$C$3,0,SUMPRODUCT(--(ROW('04 变换后数据'!$D$5:$D$160)<=ROW()),--ISNUMBER(OFFSET('04 变换后数据'!$D$5:$D$160,ROW()-5-$C$3+1,0,MIN($C$3,ROW()-4),1)),--ISNUMBER(OFFSET('04 变换后数据'!$H$5:$H$160,ROW()-5-$C$3+1,0,MIN($C$3,ROW()-4),1)))) | E61: =IF(57<$E$3,"",IF(661=0,"",IF(661<MAX(5,ROUND($E$3*0.8,0)),"样本不足",CORREL(OFFSET('04 变换后数据'!$D$5:$D$160,ROW()-5-$E$3+1,0,$E$3,1),OFFSET('04 变换后数据'!$H$5:$H$160,ROW()-5-$E$3+1,0,$E$3,1)))) | F61: =IF(57<$E$3,0,SUMPRODUCT(--(ROW('04 变换后数据'!$D$5:$D$160)<=ROW()),--ISNUMBER(OFFSET('04 变换后数据'!$D$5:$D$160,ROW()-5-$E$3+1,0,MIN($E$3,ROW()-4),1)),--ISNUMBER(OFFSET('04 变换后数据'!$H$5:$H$160,ROW()-5-$E$3+1,0,MIN($E$3,ROW()-4),1)))) | G61: =IF(57<$G$3,"",IF(861=0,"",IF(861<MAX(5,ROUND($G$3*0.8,0)),"样本不足",CORREL(OFFSET('04 变换后数据'!$D$5:$D$160,ROW()-5-$G$3+1,0,$G$3,1),OFFSET('04 变换后数据'!$H$5:$H$160,ROW()-5-$G$3+1,0,$G$3,1)))) | H61: =IF(57<$G$3,0,SUMPRODUCT(--(ROW('04 变换后数据'!$D$5:$D$160)<=ROW()),--ISNUMBER(OFFSET('04 变换后数据'!$D$5:$D$160,ROW()-5-$G$3+1,0,MIN($G$3,ROW()-4),1)),--ISNUMBER(OFFSET('04 变换后数据'!$H$5:$H$160,ROW()-5-$G$3+1,0,MIN($G$3,ROW()-4),1)))) | I61: =IF(ISNUMBER(E61),IF(ABS(E61)>=0.7,"强",IF(ABS(E61)>=0.4,"中","弱")),"-")
A62: 58 | B62: ='04 变换后数据'!B62 | C62: =IF(58<$C$3,"",IF(462=0,"",IF(462<MAX(5,ROUND($C$3*0.8,0)),"样本不足",CORREL(OFFSET('04 变换后数据'!$D$5:$D$160,ROW()-5-$C$3+1,0,$C$3,1),OFFSET('04 变换后数据'!$H$5:$H$160,ROW()-5-$C$3+1,0,$C$3,1)))) | D62: =IF(58<$C$3,0,SUMPRODUCT(--(ROW('04 变换后数据'!$D$5:$D$160)<=ROW()),--ISNUMBER(OFFSET('04 变换后数据'!$D$5:$D$160,ROW()-5-$C$3+1,0,MIN($C$3,ROW()-4),1)),--ISNUMBER(OFFSET('04 变换后数据'!$H$5:$H$160,ROW()-5-$C$3+1,0,MIN($C$3,ROW()-4),1)))) | E62: =IF(58<$E$3,"",IF(662=0,"",IF(662<MAX(5,ROUND($E$3*0.8,0)),"样本不足",CORREL(OFFSET('04 变换后数据'!$D$5:$D$160,ROW()-5-$E$3+1,0,$E$3,1),OFFSET('04 变换后数据'!$H$5:$H$160,ROW()-5-$E$3+1,0,$E$3,1)))) | F62: =IF(58<$E$3,0,SUMPRODUCT(--(ROW('04 变换后数据'!$D$5:$D$160)<=ROW()),--ISNUMBER(OFFSET('04 变换后数据'!$D$5:$D$160,ROW()-5-$E$3+1,0,MIN($E$3,ROW()-4),1)),--ISNUMBER(OFFSET('04 变换后数据'!$H$5:$H$160,ROW()-5-$E$3+1,0,MIN($E$3,ROW()-4),1)))) | G62: =IF(58<$G$3,"",IF(862=0,"",IF(862<MAX(5,ROUND($G$3*0.8,0)),"样本不足",CORREL(OFFSET('04 变换后数据'!$D$5:$D$160,ROW()-5-$G$3+1,0,$G$3,1),OFFSET('04 变换后数据'!$H$5:$H$160,ROW()-5-$G$3+1,0,$G$3,1)))) | H62: =IF(58<$G$3,0,SUMPRODUCT(--(ROW('04 变换后数据'!$D$5:$D$160)<=ROW()),--ISNUMBER(OFFSET('04 变换后数据'!$D$5:$D$160,ROW()-5-$G$3+1,0,MIN($G$3,ROW()-4),1)),--ISNUMBER(OFFSET('04 变换后数据'!$H$5:$H$160,ROW()-5-$G$3+1,0,MIN($G$3,ROW()-4),1)))) | I62: =IF(ISNUMBER(E62),IF(ABS(E62)>=0.7,"强",IF(ABS(E62)>=0.4,"中","弱")),"-")
A63: 59 | B63: ='04 变换后数据'!B63 | C63: =IF(59<$C$3,"",IF(463=0,"",IF(463<MAX(5,ROUND($C$3*0.8,0)),"样本不足",CORREL(OFFSET('04 变换后数据'!$D$5:$D$160,ROW()-5-$C$3+1,0,$C$3,1),OFFSET('04 变换后数据'!$H$5:$H$160,ROW()-5-$C$3+1,0,$C$3,1)))) | D63: =IF(59<$C$3,0,SUMPRODUCT(--(ROW('04 变换后数据'!$D$5:$D$160)<=ROW()),--ISNUMBER(OFFSET('04 变换后数据'!$D$5:$D$160,ROW()-5-$C$3+1,0,MIN($C$3,ROW()-4),1)),--ISNUMBER(OFFSET('04 变换后数据'!$H$5:$H$160,ROW()-5-$C$3+1,0,MIN($C$3,ROW()-4),1)))) | E63: =IF(59<$E$3,"",IF(663=0,"",IF(663<MAX(5,ROUND($E$3*0.8,0)),"样本不足",CORREL(OFFSET('04 变换后数据'!$D$5:$D$160,ROW()-5-$E$3+1,0,$E$3,1),OFFSET('04 变换后数据'!$H$5:$H$160,ROW()-5-$E$3+1,0,$E$3,1)))) | F63: =IF(59<$E$3,0,SUMPRODUCT(--(ROW('04 变换后数据'!$D$5:$D$160)<=ROW()),--ISNUMBER(OFFSET('04 变换后数据'!$D$5:$D$160,ROW()-5-$E$3+1,0,MIN($E$3,ROW()-4),1)),--ISNUMBER(OFFSET('04 变换后数据'!$H$5:$H$160,ROW()-5-$E$3+1,0,MIN($E$3,ROW()-4),1)))) | G63: =IF(59<$G$3,"",IF(863=0,"",IF(863<MAX(5,ROUND($G$3*0.8,0)),"样本不足",CORREL(OFFSET('04 变换后数据'!$D$5:$D$160,ROW()-5-$G$3+1,0,$G$3,1),OFFSET('04 变换后数据'!$H$5:$H$160,ROW()-5-$G$3+1,0,$G$3,1)))) | H63: =IF(59<$G$3,0,SUMPRODUCT(--(ROW('04 变换后数据'!$D$5:$D$160)<=ROW()),--ISNUMBER(OFFSET('04 变换后数据'!$D$5:$D$160,ROW()-5-$G$3+1,0,MIN($G$3,ROW()-4),1)),--ISNUMBER(OFFSET('04 变换后数据'!$H$5:$H$160,ROW()-5-$G$3+1,0,MIN($G$3,ROW()-4),1)))) | I63: =IF(ISNUMBER(E63),IF(ABS(E63)>=0.7,"强",IF(ABS(E63)>=0.4,"中","弱")),"-")
A64: 60 | B64: ='04 变换后数据'!B64 | C64: =IF(60<$C$3,"",IF(464=0,"",IF(464<MAX(5,ROUND($C$3*0.8,0)),"样本不足",CORREL(OFFSET('04 变换后数据'!$D$5:$D$160,ROW()-5-$C$3+1,0,$C$3,1),OFFSET('04 变换后数据'!$H$5:$H$160,ROW()-5-$C$3+1,0,$C$3,1)))) | D64: =IF(60<$C$3,0,SUMPRODUCT(--(ROW('04 变换后数据'!$D$5:$D$160)<=ROW()),--ISNUMBER(OFFSET('04 变换后数据'!$D$5:$D$160,ROW()-5-$C$3+1,0,MIN($C$3,ROW()-4),1)),--ISNUMBER(OFFSET('04 变换后数据'!$H$5:$H$160,ROW()-5-$C$3+1,0,MIN($C$3,ROW()-4),1)))) | E64: =IF(60<$E$3,"",IF(664=0,"",IF(664<MAX(5,ROUND($E$3*0.8,0)),"样本不足",CORREL(OFFSET('04 变换后数据'!$D$5:$D$160,ROW()-5-$E$3+1,0,$E$3,1),OFFSET('04 变换后数据'!$H$5:$H$160,ROW()-5-$E$3+1,0,$E$3,1)))) | F64: =IF(60<$E$3,0,SUMPRODUCT(--(ROW('04 变换后数据'!$D$5:$D$160)<=ROW()),--ISNUMBER(OFFSET('04 变换后数据'!$D$5:$D$160,ROW()-5-$E$3+1,0,MIN($E$3,ROW()-4),1)),--ISNUMBER(OFFSET('04 变换后数据'!$H$5:$H$160,ROW()-5-$E$3+1,0,MIN($E$3,ROW()-4),1)))) | G64: =IF(60<$G$3,"",IF(864=0,"",IF(864<MAX(5,ROUND($G$3*0.8,0)),"样本不足",CORREL(OFFSET('04 变换后数据'!$D$5:$D$160,ROW()-5-$G$3+1,0,$G$3,1),OFFSET('04 变换后数据'!$H$5:$H$160,ROW()-5-$G$3+1,0,$G$3,1)))) | H64: =IF(60<$G$3,0,SUMPRODUCT(--(ROW('04 变换后数据'!$D$5:$D$160)<=ROW()),--ISNUMBER(OFFSET('04 变换后数据'!$D$5:$D$160,ROW()-5-$G$3+1,0,MIN($G$3,ROW()-4),1)),--ISNUMBER(OFFSET('04 变换后数据'!$H$5:$H$160,ROW()-5-$G$3+1,0,MIN($G$3,ROW()-4),1)))) | I64: =IF(ISNUMBER(E64),IF(ABS(E64)>=0.7,"强",IF(ABS(E64)>=0.4,"中","弱")),"-")
A65: 61 | B65: ='04 变换后数据'!B65 | C65: =IF(61<$C$3,"",IF(465=0,"",IF(465<MAX(5,ROUND($C$3*0.8,0)),"样本不足",CORREL(OFFSET('04 变换后数据'!$D$5:$D$160,ROW()-5-$C$3+1,0,$C$3,1),OFFSET('04 变换后数据'!$H$5:$H$160,ROW()-5-$C$3+1,0,$C$3,1)))) | D65: =IF(61<$C$3,0,SUMPRODUCT(--(ROW('04 变换后数据'!$D$5:$D$160)<=ROW()),--ISNUMBER(OFFSET('04 变换后数据'!$D$5:$D$160,ROW()-5-$C$3+1,0,MIN($C$3,ROW()-4),1)),--ISNUMBER(OFFSET('04 变换后数据'!$H$5:$H$160,ROW()-5-$C$3+1,0,MIN($C$3,ROW()-4),1)))) | E65: =IF(61<$E$3,"",IF(665=0,"",IF(665<MAX(5,ROUND($E$3*0.8,0)),"样本不足",CORREL(OFFSET('04 变换后数据'!$D$5:$D$160,ROW()-5-$E$3+1,0,$E$3,1),OFFSET('04 变换后数据'!$H$5:$H$160,ROW()-5-$E$3+1,0,$E$3,1)))) | F65: =IF(61<$E$3,0,SUMPRODUCT(--(ROW('04 变换后数据'!$D$5:$D$160)<=ROW()),--ISNUMBER(OFFSET('04 变换后数据'!$D$5:$D$160,ROW()-5-$E$3+1,0,MIN($E$3,ROW()-4),1)),--ISNUMBER(OFFSET('04 变换后数据'!$H$5:$H$160,ROW()-5-$E$3+1,0,MIN($E$3,ROW()-4),1)))) | G65: =IF(61<$G$3,"",IF(865=0,"",IF(865<MAX(5,ROUND($G$3*0.8,0)),"样本不足",CORREL(OFFSET('04 变换后数据'!$D$5:$D$160,ROW()-5-$G$3+1,0,$G$3,1),OFFSET('04 变换后数据'!$H$5:$H$160,ROW()-5-$G$3+1,0,$G$3,1)))) | H65: =IF(61<$G$3,0,SUMPRODUCT(--(ROW('04 变换后数据'!$D$5:$D$160)<=ROW()),--ISNUMBER(OFFSET('04 变换后数据'!$D$5:$D$160,ROW()-5-$G$3+1,0,MIN($G$3,ROW()-4),1)),--ISNUMBER(OFFSET('04 变换后数据'!$H$5:$H$160,ROW()-5-$G$3+1,0,MIN($G$3,ROW()-4),1)))) | I65: =IF(ISNUMBER(E65),IF(ABS(E65)>=0.7,"强",IF(ABS(E65)>=0.4,"中","弱")),"-")
A66: 62 | B66: ='04 变换后数据'!B66 | C66: =IF(62<$C$3,"",IF(466=0,"",IF(466<MAX(5,ROUND($C$3*0.8,0)),"样本不足",CORREL(OFFSET('04 变换后数据'!$D$5:$D$160,ROW()-5-$C$3+1,0,$C$3,1),OFFSET('04 变换后数据'!$H$5:$H$160,ROW()-5-$C$3+1,0,$C$3,1)))) | D66: =IF(62<$C$3,0,SUMPRODUCT(--(ROW('04 变换后数据'!$D$5:$D$160)<=ROW()),--ISNUMBER(OFFSET('04 变换后数据'!$D$5:$D$160,ROW()-5-$C$3+1,0,MIN($C$3,ROW()-4),1)),--ISNUMBER(OFFSET('04 变换后数据'!$H$5:$H$160,ROW()-5-$C$3+1,0,MIN($C$3,ROW()-4),1)))) | E66: =IF(62<$E$3,"",IF(666=0,"",IF(666<MAX(5,ROUND($E$3*0.8,0)),"样本不足",CORREL(OFFSET('04 变换后数据'!$D$5:$D$160,ROW()-5-$E$3+1,0,$E$3,1),OFFSET('04 变换后数据'!$H$5:$H$160,ROW()-5-$E$3+1,0,$E$3,1)))) | F66: =IF(62<$E$3,0,SUMPRODUCT(--(ROW('04 变换后数据'!$D$5:$D$160)<=ROW()),--ISNUMBER(OFFSET('04 变换后数据'!$D$5:$D$160,ROW()-5-$E$3+1,0,MIN($E$3,ROW()-4),1)),--ISNUMBER(OFFSET('04 变换后数据'!$H$5:$H$160,ROW()-5-$E$3+1,0,MIN($E$3,ROW()-4),1)))) | G66: =IF(62<$G$3,"",IF(866=0,"",IF(866<MAX(5,ROUND($G$3*0.8,0)),"样本不足",CORREL(OFFSET('04 变换后数据'!$D$5:$D$160,ROW()-5-$G$3+1,0,$G$3,1),OFFSET('04 变换后数据'!$H$5:$H$160,ROW()-5-$G$3+1,0,$G$3,1)))) | H66: =IF(62<$G$3,0,SUMPRODUCT(--(ROW('04 变换后数据'!$D$5:$D$160)<=ROW()),--ISNUMBER(OFFSET('04 变换后数据'!$D$5:$D$160,ROW()-5-$G$3+1,0,MIN($G$3,ROW()-4),1)),--ISNUMBER(OFFSET('04 变换后数据'!$H$5:$H$160,ROW()-5-$G$3+1,0,MIN($G$3,ROW()-4),1)))) | I66: =IF(ISNUMBER(E66),IF(ABS(E66)>=0.7,"强",IF(ABS(E66)>=0.4,"中","弱")),"-")
A67: 63 | B67: ='04 变换后数据'!B67 | C67: =IF(63<$C$3,"",IF(467=0,"",IF(467<MAX(5,ROUND($C$3*0.8,0)),"样本不足",CORREL(OFFSET('04 变换后数据'!$D$5:$D$160,ROW()-5-$C$3+1,0,$C$3,1),OFFSET('04 变换后数据'!$H$5:$H$160,ROW()-5-$C$3+1,0,$C$3,1)))) | D67: =IF(63<$C$3,0,SUMPRODUCT(--(ROW('04 变换后数据'!$D$5:$D$160)<=ROW()),--ISNUMBER(OFFSET('04 变换后数据'!$D$5:$D$160,ROW()-5-$C$3+1,0,MIN($C$3,ROW()-4),1)),--ISNUMBER(OFFSET('04 变换后数据'!$H$5:$H$160,ROW()-5-$C$3+1,0,MIN($C$3,ROW()-4),1)))) | E67: =IF(63<$E$3,"",IF(667=0,"",IF(667<MAX(5,ROUND($E$3*0.8,0)),"样本不足",CORREL(OFFSET('04 变换后数据'!$D$5:$D$160,ROW()-5-$E$3+1,0,$E$3,1),OFFSET('04 变换后数据'!$H$5:$H$160,ROW()-5-$E$3+1,0,$E$3,1)))) | F67: =IF(63<$E$3,0,SUMPRODUCT(--(ROW('04 变换后数据'!$D$5:$D$160)<=ROW()),--ISNUMBER(OFFSET('04 变换后数据'!$D$5:$D$160,ROW()-5-$E$3+1,0,MIN($E$3,ROW()-4),1)),--ISNUMBER(OFFSET('04 变换后数据'!$H$5:$H$160,ROW()-5-$E$3+1,0,MIN($E$3,ROW()-4),1)))) | G67: =IF(63<$G$3,"",IF(867=0,"",IF(867<MAX(5,ROUND($G$3*0.8,0)),"样本不足",CORREL(OFFSET('04 变换后数据'!$D$5:$D$160,ROW()-5-$G$3+1,0,$G$3,1),OFFSET('04 变换后数据'!$H$5:$H$160,ROW()-5-$G$3+1,0,$G$3,1)))) | H67: =IF(63<$G$3,0,SUMPRODUCT(--(ROW('04 变换后数据'!$D$5:$D$160)<=ROW()),--ISNUMBER(OFFSET('04 变换后数据'!$D$5:$D$160,ROW()-5-$G$3+1,0,MIN($G$3,ROW()-4),1)),--ISNUMBER(OFFSET('04 变换后数据'!$H$5:$H$160,ROW()-5-$G$3+1,0,MIN($G$3,ROW()-4),1)))) | I67: =IF(ISNUMBER(E67),IF(ABS(E67)>=0.7,"强",IF(ABS(E67)>=0.4,"中","弱")),"-")
A68: 64 | B68: ='04 变换后数据'!B68 | C68: =IF(64<$C$3,"",IF(468=0,"",IF(468<MAX(5,ROUND($C$3*0.8,0)),"样本不足",CORREL(OFFSET('04 变换后数据'!$D$5:$D$160,ROW()-5-$C$3+1,0,$C$3,1),OFFSET('04 变换后数据'!$H$5:$H$160,ROW()-5-$C$3+1,0,$C$3,1)))) | D68: =IF(64<$C$3,0,SUMPRODUCT(--(ROW('04 变换后数据'!$D$5:$D$160)<=ROW()),--ISNUMBER(OFFSET('04 变换后数据'!$D$5:$D$160,ROW()-5-$C$3+1,0,MIN($C$3,ROW()-4),1)),--ISNUMBER(OFFSET('04 变换后数据'!$H$5:$H$160,ROW()-5-$C$3+1,0,MIN($C$3,ROW()-4),1)))) | E68: =IF(64<$E$3,"",IF(668=0,"",IF(668<MAX(5,ROUND($E$3*0.8,0)),"样本不足",CORREL(OFFSET('04 变换后数据'!$D$5:$D$160,ROW()-5-$E$3+1,0,$E$3,1),OFFSET('04 变换后数据'!$H$5:$H$160,ROW()-5-$E$3+1,0,$E$3,1)))) | F68: =IF(64<$E$3,0,SUMPRODUCT(--(ROW('04 变换后数据'!$D$5:$D$160)<=ROW()),--ISNUMBER(OFFSET('04 变换后数据'!$D$5:$D$160,ROW()-5-$E$3+1,0,MIN($E$3,ROW()-4),1)),--ISNUMBER(OFFSET('04 变换后数据'!$H$5:$H$160,ROW()-5-$E$3+1,0,MIN($E$3,ROW()-4),1)))) | G68: =IF(64<$G$3,"",IF(868=0,"",IF(868<MAX(5,ROUND($G$3*0.8,0)),"样本不足",CORREL(OFFSET('04 变换后数据'!$D$5:$D$160,ROW()-5-$G$3+1,0,$G$3,1),OFFSET('04 变换后数据'!$H$5:$H$160,ROW()-5-$G$3+1,0,$G$3,1)))) | H68: =IF(64<$G$3,0,SUMPRODUCT(--(ROW('04 变换后数据'!$D$5:$D$160)<=ROW()),--ISNUMBER(OFFSET('04 变换后数据'!$D$5:$D$160,ROW()-5-$G$3+1,0,MIN($G$3,ROW()-4),1)),--ISNUMBER(OFFSET('04 变换后数据'!$H$5:$H$160,ROW()-5-$G$3+1,0,MIN($G$3,ROW()-4),1)))) | I68: =IF(ISNUMBER(E68),IF(ABS(E68)>=0.7,"强",IF(ABS(E68)>=0.4,"中","弱")),"-")
A69: 65 | B69: ='04 变换后数据'!B69 | C69: =IF(65<$C$3,"",IF(469=0,"",IF(469<MAX(5,ROUND($C$3*0.8,0)),"样本不足",CORREL(OFFSET('04 变换后数据'!$D$5:$D$160,ROW()-5-$C$3+1,0,$C$3,1),OFFSET('04 变换后数据'!$H$5:$H$160,ROW()-5-$C$3+1,0,$C$3,1)))) | D69: =IF(65<$C$3,0,SUMPRODUCT(--(ROW('04 变换后数据'!$D$5:$D$160)<=ROW()),--ISNUMBER(OFFSET('04 变换后数据'!$D$5:$D$160,ROW()-5-$C$3+1,0,MIN($C$3,ROW()-4),1)),--ISNUMBER(OFFSET('04 变换后数据'!$H$5:$H$160,ROW()-5-$C$3+1,0,MIN($C$3,ROW()-4),1)))) | E69: =IF(65<$E$3,"",IF(669=0,"",IF(669<MAX(5,ROUND($E$3*0.8,0)),"样本不足",CORREL(OFFSET('04 变换后数据'!$D$5:$D$160,ROW()-5-$E$3+1,0,$E$3,1),OFFSET('04 变换后数据'!$H$5:$H$160,ROW()-5-$E$3+1,0,$E$3,1)))) | F69: =IF(65<$E$3,0,SUMPRODUCT(--(ROW('04 变换后数据'!$D$5:$D$160)<=ROW()),--ISNUMBER(OFFSET('04 变换后数据'!$D$5:$D$160,ROW()-5-$E$3+1,0,MIN($E$3,ROW()-4),1)),--ISNUMBER(OFFSET('04 变换后数据'!$H$5:$H$160,ROW()-5-$E$3+1,0,MIN($E$3,ROW()-4),1)))) | G69: =IF(65<$G$3,"",IF(869=0,"",IF(869<MAX(5,ROUND($G$3*0.8,0)),"样本不足",CORREL(OFFSET('04 变换后数据'!$D$5:$D$160,ROW()-5-$G$3+1,0,$G$3,1),OFFSET('04 变换后数据'!$H$5:$H$160,ROW()-5-$G$3+1,0,$G$3,1)))) | H69: =IF(65<$G$3,0,SUMPRODUCT(--(ROW('04 变换后数据'!$D$5:$D$160)<=ROW()),--ISNUMBER(OFFSET('04 变换后数据'!$D$5:$D$160,ROW()-5-$G$3+1,0,MIN($G$3,ROW()-4),1)),--ISNUMBER(OFFSET('04 变换后数据'!$H$5:$H$160,ROW()-5-$G$3+1,0,MIN($G$3,ROW()-4),1)))) | I69: =IF(ISNUMBER(E69),IF(ABS(E69)>=0.7,"强",IF(ABS(E69)>=0.4,"中","弱")),"-")
A70: 66 | B70: ='04 变换后数据'!B70 | C70: =IF(66<$C$3,"",IF(470=0,"",IF(470<MAX(5,ROUND($C$3*0.8,0)),"样本不足",CORREL(OFFSET('04 变换后数据'!$D$5:$D$160,ROW()-5-$C$3+1,0,$C$3,1),OFFSET('04 变换后数据'!$H$5:$H$160,ROW()-5-$C$3+1,0,$C$3,1)))) | D70: =IF(66<$C$3,0,SUMPRODUCT(--(ROW('04 变换后数据'!$D$5:$D$160)<=ROW()),--ISNUMBER(OFFSET('04 变换后数据'!$D$5:$D$160,ROW()-5-$C$3+1,0,MIN($C$3,ROW()-4),1)),--ISNUMBER(OFFSET('04 变换后数据'!$H$5:$H$160,ROW()-5-$C$3+1,0,MIN($C$3,ROW()-4),1)))) | E70: =IF(66<$E$3,"",IF(670=0,"",IF(670<MAX(5,ROUND($E$3*0.8,0)),"样本不足",CORREL(OFFSET('04 变换后数据'!$D$5:$D$160,ROW()-5-$E$3+1,0,$E$3,1),OFFSET('04 变换后数据'!$H$5:$H$160,ROW()-5-$E$3+1,0,$E$3,1)))) | F70: =IF(66<$E$3,0,SUMPRODUCT(--(ROW('04 变换后数据'!$D$5:$D$160)<=ROW()),--ISNUMBER(OFFSET('04 变换后数据'!$D$5:$D$160,ROW()-5-$E$3+1,0,MIN($E$3,ROW()-4),1)),--ISNUMBER(OFFSET('04 变换后数据'!$H$5:$H$160,ROW()-5-$E$3+1,0,MIN($E$3,ROW()-4),1)))) | G70: =IF(66<$G$3,"",IF(870=0,"",IF(870<MAX(5,ROUND($G$3*0.8,0)),"样本不足",CORREL(OFFSET('04 变换后数据'!$D$5:$D$160,ROW()-5-$G$3+1,0,$G$3,1),OFFSET('04 变换后数据'!$H$5:$H$160,ROW()-5-$G$3+1,0,$G$3,1)))) | H70: =IF(66<$G$3,0,SUMPRODUCT(--(ROW('04 变换后数据'!$D$5:$D$160)<=ROW()),--ISNUMBER(OFFSET('04 变换后数据'!$D$5:$D$160,ROW()-5-$G$3+1,0,MIN($G$3,ROW()-4),1)),--ISNUMBER(OFFSET('04 变换后数据'!$H$5:$H$160,ROW()-5-$G$3+1,0,MIN($G$3,ROW()-4),1)))) | I70: =IF(ISNUMBER(E70),IF(ABS(E70)>=0.7,"强",IF(ABS(E70)>=0.4,"中","弱")),"-")
A71: 67 | B71: ='04 变换后数据'!B71 | C71: =IF(67<$C$3,"",IF(471=0,"",IF(471<MAX(5,ROUND($C$3*0.8,0)),"样本不足",CORREL(OFFSET('04 变换后数据'!$D$5:$D$160,ROW()-5-$C$3+1,0,$C$3,1),OFFSET('04 变换后数据'!$H$5:$H$160,ROW()-5-$C$3+1,0,$C$3,1)))) | D71: =IF(67<$C$3,0,SUMPRODUCT(--(ROW('04 变换后数据'!$D$5:$D$160)<=ROW()),--ISNUMBER(OFFSET('04 变换后数据'!$D$5:$D$160,ROW()-5-$C$3+1,0,MIN($C$3,ROW()-4),1)),--ISNUMBER(OFFSET('04 变换后数据'!$H$5:$H$160,ROW()-5-$C$3+1,0,MIN($C$3,ROW()-4),1)))) | E71: =IF(67<$E$3,"",IF(671=0,"",IF(671<MAX(5,ROUND($E$3*0.8,0)),"样本不足",CORREL(OFFSET('04 变换后数据'!$D$5:$D$160,ROW()-5-$E$3+1,0,$E$3,1),OFFSET('04 变换后数据'!$H$5:$H$160,ROW()-5-$E$3+1,0,$E$3,1)))) | F71: =IF(67<$E$3,0,SUMPRODUCT(--(ROW('04 变换后数据'!$D$5:$D$160)<=ROW()),--ISNUMBER(OFFSET('04 变换后数据'!$D$5:$D$160,ROW()-5-$E$3+1,0,MIN($E$3,ROW()-4),1)),--ISNUMBER(OFFSET('04 变换后数据'!$H$5:$H$160,ROW()-5-$E$3+1,0,MIN($E$3,ROW()-4),1)))) | G71: =IF(67<$G$3,"",IF(871=0,"",IF(871<MAX(5,ROUND($G$3*0.8,0)),"样本不足",CORREL(OFFSET('04 变换后数据'!$D$5:$D$160,ROW()-5-$G$3+1,0,$G$3,1),OFFSET('04 变换后数据'!$H$5:$H$160,ROW()-5-$G$3+1,0,$G$3,1)))) | H71: =IF(67<$G$3,0,SUMPRODUCT(--(ROW('04 变换后数据'!$D$5:$D$160)<=ROW()),--ISNUMBER(OFFSET('04 变换后数据'!$D$5:$D$160,ROW()-5-$G$3+1,0,MIN($G$3,ROW()-4),1)),--ISNUMBER(OFFSET('04 变换后数据'!$H$5:$H$160,ROW()-5-$G$3+1,0,MIN($G$3,ROW()-4),1)))) | I71: =IF(ISNUMBER(E71),IF(ABS(E71)>=0.7,"强",IF(ABS(E71)>=0.4,"中","弱")),"-")
A72: 68 | B72: ='04 变换后数据'!B72 | C72: =IF(68<$C$3,"",IF(472=0,"",IF(472<MAX(5,ROUND($C$3*0.8,0)),"样本不足",CORREL(OFFSET('04 变换后数据'!$D$5:$D$160,ROW()-5-$C$3+1,0,$C$3,1),OFFSET('04 变换后数据'!$H$5:$H$160,ROW()-5-$C$3+1,0,$C$3,1)))) | D72: =IF(68<$C$3,0,SUMPRODUCT(--(ROW('04 变换后数据'!$D$5:$D$160)<=ROW()),--ISNUMBER(OFFSET('04 变换后数据'!$D$5:$D$160,ROW()-5-$C$3+1,0,MIN($C$3,ROW()-4),1)),--ISNUMBER(OFFSET('04 变换后数据'!$H$5:$H$160,ROW()-5-$C$3+1,0,MIN($C$3,ROW()-4),1)))) | E72: =IF(68<$E$3,"",IF(672=0,"",IF(672<MAX(5,ROUND($E$3*0.8,0)),"样本不足",CORREL(OFFSET('04 变换后数据'!$D$5:$D$160,ROW()-5-$E$3+1,0,$E$3,1),OFFSET('04 变换后数据'!$H$5:$H$160,ROW()-5-$E$3+1,0,$E$3,1)))) | F72: =IF(68<$E$3,0,SUMPRODUCT(--(ROW('04 变换后数据'!$D$5:$D$160)<=ROW()),--ISNUMBER(OFFSET('04 变换后数据'!$D$5:$D$160,ROW()-5-$E$3+1,0,MIN($E$3,ROW()-4),1)),--ISNUMBER(OFFSET('04 变换后数据'!$H$5:$H$160,ROW()-5-$E$3+1,0,MIN($E$3,ROW()-4),1)))) | G72: =IF(68<$G$3,"",IF(872=0,"",IF(872<MAX(5,ROUND($G$3*0.8,0)),"样本不足",CORREL(OFFSET('04 变换后数据'!$D$5:$D$160,ROW()-5-$G$3+1,0,$G$3,1),OFFSET('04 变换后数据'!$H$5:$H$160,ROW()-5-$G$3+1,0,$G$3,1)))) | H72: =IF(68<$G$3,0,SUMPRODUCT(--(ROW('04 变换后数据'!$D$5:$D$160)<=ROW()),--ISNUMBER(OFFSET('04 变换后数据'!$D$5:$D$160,ROW()-5-$G$3+1,0,MIN($G$3,ROW()-4),1)),--ISNUMBER(OFFSET('04 变换后数据'!$H$5:$H$160,ROW()-5-$G$3+1,0,MIN($G$3,ROW()-4),1)))) | I72: =IF(ISNUMBER(E72),IF(ABS(E72)>=0.7,"强",IF(ABS(E72)>=0.4,"中","弱")),"-")
A73: 69 | B73: ='04 变换后数据'!B73 | C73: =IF(69<$C$3,"",IF(473=0,"",IF(473<MAX(5,ROUND($C$3*0.8,0)),"样本不足",CORREL(OFFSET('04 变换后数据'!$D$5:$D$160,ROW()-5-$C$3+1,0,$C$3,1),OFFSET('04 变换后数据'!$H$5:$H$160,ROW()-5-$C$3+1,0,$C$3,1)))) | D73: =IF(69<$C$3,0,SUMPRODUCT(--(ROW('04 变换后数据'!$D$5:$D$160)<=ROW()),--ISNUMBER(OFFSET('04 变换后数据'!$D$5:$D$160,ROW()-5-$C$3+1,0,MIN($C$3,ROW()-4),1)),--ISNUMBER(OFFSET('04 变换后数据'!$H$5:$H$160,ROW()-5-$C$3+1,0,MIN($C$3,ROW()-4),1)))) | E73: =IF(69<$E$3,"",IF(673=0,"",IF(673<MAX(5,ROUND($E$3*0.8,0)),"样本不足",CORREL(OFFSET('04 变换后数据'!$D$5:$D$160,ROW()-5-$E$3+1,0,$E$3,1),OFFSET('04 变换后数据'!$H$5:$H$160,ROW()-5-$E$3+1,0,$E$3,1)))) | F73: =IF(69<$E$3,0,SUMPRODUCT(--(ROW('04 变换后数据'!$D$5:$D$160)<=ROW()),--ISNUMBER(OFFSET('04 变换后数据'!$D$5:$D$160,ROW()-5-$E$3+1,0,MIN($E$3,ROW()-4),1)),--ISNUMBER(OFFSET('04 变换后数据'!$H$5:$H$160,ROW()-5-$E$3+1,0,MIN($E$3,ROW()-4),1)))) | G73: =IF(69<$G$3,"",IF(873=0,"",IF(873<MAX(5,ROUND($G$3*0.8,0)),"样本不足",CORREL(OFFSET('04 变换后数据'!$D$5:$D$160,ROW()-5-$G$3+1,0,$G$3,1),OFFSET('04 变换后数据'!$H$5:$H$160,ROW()-5-$G$3+1,0,$G$3,1)))) | H73: =IF(69<$G$3,0,SUMPRODUCT(--(ROW('04 变换后数据'!$D$5:$D$160)<=ROW()),--ISNUMBER(OFFSET('04 变换后数据'!$D$5:$D$160,ROW()-5-$G$3+1,0,MIN($G$3,ROW()-4),1)),--ISNUMBER(OFFSET('04 变换后数据'!$H$5:$H$160,ROW()-5-$G$3+1,0,MIN($G$3,ROW()-4),1)))) | I73: =IF(ISNUMBER(E73),IF(ABS(E73)>=0.7,"强",IF(ABS(E73)>=0.4,"中","弱")),"-")
A74: 70 | B74: ='04 变换后数据'!B74 | C74: =IF(70<$C$3,"",IF(474=0,"",IF(474<MAX(5,ROUND($C$3*0.8,0)),"样本不足",CORREL(OFFSET('04 变换后数据'!$D$5:$D$160,ROW()-5-$C$3+1,0,$C$3,1),OFFSET('04 变换后数据'!$H$5:$H$160,ROW()-5-$C$3+1,0,$C$3,1)))) | D74: =IF(70<$C$3,0,SUMPRODUCT(--(ROW('04 变换后数据'!$D$5:$D$160)<=ROW()),--ISNUMBER(OFFSET('04 变换后数据'!$D$5:$D$160,ROW()-5-$C$3+1,0,MIN($C$3,ROW()-4),1)),--ISNUMBER(OFFSET('04 变换后数据'!$H$5:$H$160,ROW()-5-$C$3+1,0,MIN($C$3,ROW()-4),1)))) | E74: =IF(70<$E$3,"",IF(674=0,"",IF(674<MAX(5,ROUND($E$3*0.8,0)),"样本不足",CORREL(OFFSET('04 变换后数据'!$D$5:$D$160,ROW()-5-$E$3+1,0,$E$3,1),OFFSET('04 变换后数据'!$H$5:$H$160,ROW()-5-$E$3+1,0,$E$3,1)))) | F74: =IF(70<$E$3,0,SUMPRODUCT(--(ROW('04 变换后数据'!$D$5:$D$160)<=ROW()),--ISNUMBER(OFFSET('04 变换后数据'!$D$5:$D$160,ROW()-5-$E$3+1,0,MIN($E$3,ROW()-4),1)),--ISNUMBER(OFFSET('04 变换后数据'!$H$5:$H$160,ROW()-5-$E$3+1,0,MIN($E$3,ROW()-4),1)))) | G74: =IF(70<$G$3,"",IF(874=0,"",IF(874<MAX(5,ROUND($G$3*0.8,0)),"样本不足",CORREL(OFFSET('04 变换后数据'!$D$5:$D$160,ROW()-5-$G$3+1,0,$G$3,1),OFFSET('04 变换后数据'!$H$5:$H$160,ROW()-5-$G$3+1,0,$G$3,1)))) | H74: =IF(70<$G$3,0,SUMPRODUCT(--(ROW('04 变换后数据'!$D$5:$D$160)<=ROW()),--ISNUMBER(OFFSET('04 变换后数据'!$D$5:$D$160,ROW()-5-$G$3+1,0,MIN($G$3,ROW()-4),1)),--ISNUMBER(OFFSET('04 变换后数据'!$H$5:$H$160,ROW()-5-$G$3+1,0,MIN($G$3,ROW()-4),1)))) | I74: =IF(ISNUMBER(E74),IF(ABS(E74)>=0.7,"强",IF(ABS(E74)>=0.4,"中","弱")),"-")
A75: 71 | B75: ='04 变换后数据'!B75 | C75: =IF(71<$C$3,"",IF(475=0,"",IF(475<MAX(5,ROUND($C$3*0.8,0)),"样本不足",CORREL(OFFSET('04 变换后数据'!$D$5:$D$160,ROW()-5-$C$3+1,0,$C$3,1),OFFSET('04 变换后数据'!$H$5:$H$160,ROW()-5-$C$3+1,0,$C$3,1)))) | D75: =IF(71<$C$3,0,SUMPRODUCT(--(ROW('04 变换后数据'!$D$5:$D$160)<=ROW()),--ISNUMBER(OFFSET('04 变换后数据'!$D$5:$D$160,ROW()-5-$C$3+1,0,MIN($C$3,ROW()-4),1)),--ISNUMBER(OFFSET('04 变换后数据'!$H$5:$H$160,ROW()-5-$C$3+1,0,MIN($C$3,ROW()-4),1)))) | E75: =IF(71<$E$3,"",IF(675=0,"",IF(675<MAX(5,ROUND($E$3*0.8,0)),"样本不足",CORREL(OFFSET('04 变换后数据'!$D$5:$D$160,ROW()-5-$E$3+1,0,$E$3,1),OFFSET('04 变换后数据'!$H$5:$H$160,ROW()-5-$E$3+1,0,$E$3,1)))) | F75: =IF(71<$E$3,0,SUMPRODUCT(--(ROW('04 变换后数据'!$D$5:$D$160)<=ROW()),--ISNUMBER(OFFSET('04 变换后数据'!$D$5:$D$160,ROW()-5-$E$3+1,0,MIN($E$3,ROW()-4),1)),--ISNUMBER(OFFSET('04 变换后数据'!$H$5:$H$160,ROW()-5-$E$3+1,0,MIN($E$3,ROW()-4),1)))) | G75: =IF(71<$G$3,"",IF(875=0,"",IF(875<MAX(5,ROUND($G$3*0.8,0)),"样本不足",CORREL(OFFSET('04 变换后数据'!$D$5:$D$160,ROW()-5-$G$3+1,0,$G$3,1),OFFSET('04 变换后数据'!$H$5:$H$160,ROW()-5-$G$3+1,0,$G$3,1)))) | H75: =IF(71<$G$3,0,SUMPRODUCT(--(ROW('04 变换后数据'!$D$5:$D$160)<=ROW()),--ISNUMBER(OFFSET('04 变换后数据'!$D$5:$D$160,ROW()-5-$G$3+1,0,MIN($G$3,ROW()-4),1)),--ISNUMBER(OFFSET('04 变换后数据'!$H$5:$H$160,ROW()-5-$G$3+1,0,MIN($G$3,ROW()-4),1)))) | I75: =IF(ISNUMBER(E75),IF(ABS(E75)>=0.7,"强",IF(ABS(E75)>=0.4,"中","弱")),"-")
A76: 72 | B76: ='04 变换后数据'!B76 | C76: =IF(72<$C$3,"",IF(476=0,"",IF(476<MAX(5,ROUND($C$3*0.8,0)),"样本不足",CORREL(OFFSET('04 变换后数据'!$D$5:$D$160,ROW()-5-$C$3+1,0,$C$3,1),OFFSET('04 变换后数据'!$H$5:$H$160,ROW()-5-$C$3+1,0,$C$3,1)))) | D76: =IF(72<$C$3,0,SUMPRODUCT(--(ROW('04 变换后数据'!$D$5:$D$160)<=ROW()),--ISNUMBER(OFFSET('04 变换后数据'!$D$5:$D$160,ROW()-5-$C$3+1,0,MIN($C$3,ROW()-4),1)),--ISNUMBER(OFFSET('04 变换后数据'!$H$5:$H$160,ROW()-5-$C$3+1,0,MIN($C$3,ROW()-4),1)))) | E76: =IF(72<$E$3,"",IF(676=0,"",IF(676<MAX(5,ROUND($E$3*0.8,0)),"样本不足",CORREL(OFFSET('04 变换后数据'!$D$5:$D$160,ROW()-5-$E$3+1,0,$E$3,1),OFFSET('04 变换后数据'!$H$5:$H$160,ROW()-5-$E$3+1,0,$E$3,1)))) | F76: =IF(72<$E$3,0,SUMPRODUCT(--(ROW('04 变换后数据'!$D$5:$D$160)<=ROW()),--ISNUMBER(OFFSET('04 变换后数据'!$D$5:$D$160,ROW()-5-$E$3+1,0,MIN($E$3,ROW()-4),1)),--ISNUMBER(OFFSET('04 变换后数据'!$H$5:$H$160,ROW()-5-$E$3+1,0,MIN($E$3,ROW()-4),1)))) | G76: =IF(72<$G$3,"",IF(876=0,"",IF(876<MAX(5,ROUND($G$3*0.8,0)),"样本不足",CORREL(OFFSET('04 变换后数据'!$D$5:$D$160,ROW()-5-$G$3+1,0,$G$3,1),OFFSET('04 变换后数据'!$H$5:$H$160,ROW()-5-$G$3+1,0,$G$3,1)))) | H76: =IF(72<$G$3,0,SUMPRODUCT(--(ROW('04 变换后数据'!$D$5:$D$160)<=ROW()),--ISNUMBER(OFFSET('04 变换后数据'!$D$5:$D$160,ROW()-5-$G$3+1,0,MIN($G$3,ROW()-4),1)),--ISNUMBER(OFFSET('04 变换后数据'!$H$5:$H$160,ROW()-5-$G$3+1,0,MIN($G$3,ROW()-4),1)))) | I76: =IF(ISNUMBER(E76),IF(ABS(E76)>=0.7,"强",IF(ABS(E76)>=0.4,"中","弱")),"-")
A77: 73 | B77: ='04 变换后数据'!B77 | C77: =IF(73<$C$3,"",IF(477=0,"",IF(477<MAX(5,ROUND($C$3*0.8,0)),"样本不足",CORREL(OFFSET('04 变换后数据'!$D$5:$D$160,ROW()-5-$C$3+1,0,$C$3,1),OFFSET('04 变换后数据'!$H$5:$H$160,ROW()-5-$C$3+1,0,$C$3,1)))) | D77: =IF(73<$C$3,0,SUMPRODUCT(--(ROW('04 变换后数据'!$D$5:$D$160)<=ROW()),--ISNUMBER(OFFSET('04 变换后数据'!$D$5:$D$160,ROW()-5-$C$3+1,0,MIN($C$3,ROW()-4),1)),--ISNUMBER(OFFSET('04 变换后数据'!$H$5:$H$160,ROW()-5-$C$3+1,0,MIN($C$3,ROW()-4),1)))) | E77: =IF(73<$E$3,"",IF(677=0,"",IF(677<MAX(5,ROUND($E$3*0.8,0)),"样本不足",CORREL(OFFSET('04 变换后数据'!$D$5:$D$160,ROW()-5-$E$3+1,0,$E$3,1),OFFSET('04 变换后数据'!$H$5:$H$160,ROW()-5-$E$3+1,0,$E$3,1)))) | F77: =IF(73<$E$3,0,SUMPRODUCT(--(ROW('04 变换后数据'!$D$5:$D$160)<=ROW()),--ISNUMBER(OFFSET('04 变换后数据'!$D$5:$D$160,ROW()-5-$E$3+1,0,MIN($E$3,ROW()-4),1)),--ISNUMBER(OFFSET('04 变换后数据'!$H$5:$H$160,ROW()-5-$E$3+1,0,MIN($E$3,ROW()-4),1)))) | G77: =IF(73<$G$3,"",IF(877=0,"",IF(877<MAX(5,ROUND($G$3*0.8,0)),"样本不足",CORREL(OFFSET('04 变换后数据'!$D$5:$D$160,ROW()-5-$G$3+1,0,$G$3,1),OFFSET('04 变换后数据'!$H$5:$H$160,ROW()-5-$G$3+1,0,$G$3,1)))) | H77: =IF(73<$G$3,0,SUMPRODUCT(--(ROW('04 变换后数据'!$D$5:$D$160)<=ROW()),--ISNUMBER(OFFSET('04 变换后数据'!$D$5:$D$160,ROW()-5-$G$3+1,0,MIN($G$3,ROW()-4),1)),--ISNUMBER(OFFSET('04 变换后数据'!$H$5:$H$160,ROW()-5-$G$3+1,0,MIN($G$3,ROW()-4),1)))) | I77: =IF(ISNUMBER(E77),IF(ABS(E77)>=0.7,"强",IF(ABS(E77)>=0.4,"中","弱")),"-")
A78: 74 | B78: ='04 变换后数据'!B78 | C78: =IF(74<$C$3,"",IF(478=0,"",IF(478<MAX(5,ROUND($C$3*0.8,0)),"样本不足",CORREL(OFFSET('04 变换后数据'!$D$5:$D$160,ROW()-5-$C$3+1,0,$C$3,1),OFFSET('04 变换后数据'!$H$5:$H$160,ROW()-5-$C$3+1,0,$C$3,1)))) | D78: =IF(74<$C$3,0,SUMPRODUCT(--(ROW('04 变换后数据'!$D$5:$D$160)<=ROW()),--ISNUMBER(OFFSET('04 变换后数据'!$D$5:$D$160,ROW()-5-$C$3+1,0,MIN($C$3,ROW()-4),1)),--ISNUMBER(OFFSET('04 变换后数据'!$H$5:$H$160,ROW()-5-$C$3+1,0,MIN($C$3,ROW()-4),1)))) | E78: =IF(74<$E$3,"",IF(678=0,"",IF(678<MAX(5,ROUND($E$3*0.8,0)),"样本不足",CORREL(OFFSET('04 变换后数据'!$D$5:$D$160,ROW()-5-$E$3+1,0,$E$3,1),OFFSET('04 变换后数据'!$H$5:$H$160,ROW()-5-$E$3+1,0,$E$3,1)))) | F78: =IF(74<$E$3,0,SUMPRODUCT(--(ROW('04 变换后数据'!$D$5:$D$160)<=ROW()),--ISNUMBER(OFFSET('04 变换后数据'!$D$5:$D$160,ROW()-5-$E$3+1,0,MIN($E$3,ROW()-4),1)),--ISNUMBER(OFFSET('04 变换后数据'!$H$5:$H$160,ROW()-5-$E$3+1,0,MIN($E$3,ROW()-4),1)))) | G78: =IF(74<$G$3,"",IF(878=0,"",IF(878<MAX(5,ROUND($G$3*0.8,0)),"样本不足",CORREL(OFFSET('04 变换后数据'!$D$5:$D$160,ROW()-5-$G$3+1,0,$G$3,1),OFFSET('04 变换后数据'!$H$5:$H$160,ROW()-5-$G$3+1,0,$G$3,1)))) | H78: =IF(74<$G$3,0,SUMPRODUCT(--(ROW('04 变换后数据'!$D$5:$D$160)<=ROW()),--ISNUMBER(OFFSET('04 变换后数据'!$D$5:$D$160,ROW()-5-$G$3+1,0,MIN($G$3,ROW()-4),1)),--ISNUMBER(OFFSET('04 变换后数据'!$H$5:$H$160,ROW()-5-$G$3+1,0,MIN($G$3,ROW()-4),1)))) | I78: =IF(ISNUMBER(E78),IF(ABS(E78)>=0.7,"强",IF(ABS(E78)>=0.4,"中","弱")),"-")
A79: 75 | B79: ='04 变换后数据'!B79 | C79: =IF(75<$C$3,"",IF(479=0,"",IF(479<MAX(5,ROUND($C$3*0.8,0)),"样本不足",CORREL(OFFSET('04 变换后数据'!$D$5:$D$160,ROW()-5-$C$3+1,0,$C$3,1),OFFSET('04 变换后数据'!$H$5:$H$160,ROW()-5-$C$3+1,0,$C$3,1)))) | D79: =IF(75<$C$3,0,SUMPRODUCT(--(ROW('04 变换后数据'!$D$5:$D$160)<=ROW()),--ISNUMBER(OFFSET('04 变换后数据'!$D$5:$D$160,ROW()-5-$C$3+1,0,MIN($C$3,ROW()-4),1)),--ISNUMBER(OFFSET('04 变换后数据'!$H$5:$H$160,ROW()-5-$C$3+1,0,MIN($C$3,ROW()-4),1)))) | E79: =IF(75<$E$3,"",IF(679=0,"",IF(679<MAX(5,ROUND($E$3*0.8,0)),"样本不足",CORREL(OFFSET('04 变换后数据'!$D$5:$D$160,ROW()-5-$E$3+1,0,$E$3,1),OFFSET('04 变换后数据'!$H$5:$H$160,ROW()-5-$E$3+1,0,$E$3,1)))) | F79: =IF(75<$E$3,0,SUMPRODUCT(--(ROW('04 变换后数据'!$D$5:$D$160)<=ROW()),--ISNUMBER(OFFSET('04 变换后数据'!$D$5:$D$160,ROW()-5-$E$3+1,0,MIN($E$3,ROW()-4),1)),--ISNUMBER(OFFSET('04 变换后数据'!$H$5:$H$160,ROW()-5-$E$3+1,0,MIN($E$3,ROW()-4),1)))) | G79: =IF(75<$G$3,"",IF(879=0,"",IF(879<MAX(5,ROUND($G$3*0.8,0)),"样本不足",CORREL(OFFSET('04 变换后数据'!$D$5:$D$160,ROW()-5-$G$3+1,0,$G$3,1),OFFSET('04 变换后数据'!$H$5:$H$160,ROW()-5-$G$3+1,0,$G$3,1)))) | H79: =IF(75<$G$3,0,SUMPRODUCT(--(ROW('04 变换后数据'!$D$5:$D$160)<=ROW()),--ISNUMBER(OFFSET('04 变换后数据'!$D$5:$D$160,ROW()-5-$G$3+1,0,MIN($G$3,ROW()-4),1)),--ISNUMBER(OFFSET('04 变换后数据'!$H$5:$H$160,ROW()-5-$G$3+1,0,MIN($G$3,ROW()-4),1)))) | I79: =IF(ISNUMBER(E79),IF(ABS(E79)>=0.7,"强",IF(ABS(E79)>=0.4,"中","弱")),"-")
A80: 76 | B80: ='04 变换后数据'!B80 | C80: =IF(76<$C$3,"",IF(480=0,"",IF(480<MAX(5,ROUND($C$3*0.8,0)),"样本不足",CORREL(OFFSET('04 变换后数据'!$D$5:$D$160,ROW()-5-$C$3+1,0,$C$3,1),OFFSET('04 变换后数据'!$H$5:$H$160,ROW()-5-$C$3+1,0,$C$3,1)))) | D80: =IF(76<$C$3,0,SUMPRODUCT(--(ROW('04 变换后数据'!$D$5:$D$160)<=ROW()),--ISNUMBER(OFFSET('04 变换后数据'!$D$5:$D$160,ROW()-5-$C$3+1,0,MIN($C$3,ROW()-4),1)),--ISNUMBER(OFFSET('04 变换后数据'!$H$5:$H$160,ROW()-5-$C$3+1,0,MIN($C$3,ROW()-4),1)))) | E80: =IF(76<$E$3,"",IF(680=0,"",IF(680<MAX(5,ROUND($E$3*0.8,0)),"样本不足",CORREL(OFFSET('04 变换后数据'!$D$5:$D$160,ROW()-5-$E$3+1,0,$E$3,1),OFFSET('04 变换后数据'!$H$5:$H$160,ROW()-5-$E$3+1,0,$E$3,1)))) | F80: =IF(76<$E$3,0,SUMPRODUCT(--(ROW('04 变换后数据'!$D$5:$D$160)<=ROW()),--ISNUMBER(OFFSET('04 变换后数据'!$D$5:$D$160,ROW()-5-$E$3+1,0,MIN($E$3,ROW()-4),1)),--ISNUMBER(OFFSET('04 变换后数据'!$H$5:$H$160,ROW()-5-$E$3+1,0,MIN($E$3,ROW()-4),1)))) | G80: =IF(76<$G$3,"",IF(880=0,"",IF(880<MAX(5,ROUND($G$3*0.8,0)),"样本不足",CORREL(OFFSET('04 变换后数据'!$D$5:$D$160,ROW()-5-$G$3+1,0,$G$3,1),OFFSET('04 变换后数据'!$H$5:$H$160,ROW()-5-$G$3+1,0,$G$3,1)))) | H80: =IF(76<$G$3,0,SUMPRODUCT(--(ROW('04 变换后数据'!$D$5:$D$160)<=ROW()),--ISNUMBER(OFFSET('04 变换后数据'!$D$5:$D$160,ROW()-5-$G$3+1,0,MIN($G$3,ROW()-4),1)),--ISNUMBER(OFFSET('04 变换后数据'!$H$5:$H$160,ROW()-5-$G$3+1,0,MIN($G$3,ROW()-4),1)))) | I80: =IF(ISNUMBER(E80),IF(ABS(E80)>=0.7,"强",IF(ABS(E80)>=0.4,"中","弱")),"-")
A81: 77 | B81: ='04 变换后数据'!B81 | C81: =IF(77<$C$3,"",IF(481=0,"",IF(481<MAX(5,ROUND($C$3*0.8,0)),"样本不足",CORREL(OFFSET('04 变换后数据'!$D$5:$D$160,ROW()-5-$C$3+1,0,$C$3,1),OFFSET('04 变换后数据'!$H$5:$H$160,ROW()-5-$C$3+1,0,$C$3,1)))) | D81: =IF(77<$C$3,0,SUMPRODUCT(--(ROW('04 变换后数据'!$D$5:$D$160)<=ROW()),--ISNUMBER(OFFSET('04 变换后数据'!$D$5:$D$160,ROW()-5-$C$3+1,0,MIN($C$3,ROW()-4),1)),--ISNUMBER(OFFSET('04 变换后数据'!$H$5:$H$160,ROW()-5-$C$3+1,0,MIN($C$3,ROW()-4),1)))) | E81: =IF(77<$E$3,"",IF(681=0,"",IF(681<MAX(5,ROUND($E$3*0.8,0)),"样本不足",CORREL(OFFSET('04 变换后数据'!$D$5:$D$160,ROW()-5-$E$3+1,0,$E$3,1),OFFSET('04 变换后数据'!$H$5:$H$160,ROW()-5-$E$3+1,0,$E$3,1)))) | F81: =IF(77<$E$3,0,SUMPRODUCT(--(ROW('04 变换后数据'!$D$5:$D$160)<=ROW()),--ISNUMBER(OFFSET('04 变换后数据'!$D$5:$D$160,ROW()-5-$E$3+1,0,MIN($E$3,ROW()-4),1)),--ISNUMBER(OFFSET('04 变换后数据'!$H$5:$H$160,ROW()-5-$E$3+1,0,MIN($E$3,ROW()-4),1)))) | G81: =IF(77<$G$3,"",IF(881=0,"",IF(881<MAX(5,ROUND($G$3*0.8,0)),"样本不足",CORREL(OFFSET('04 变换后数据'!$D$5:$D$160,ROW()-5-$G$3+1,0,$G$3,1),OFFSET('04 变换后数据'!$H$5:$H$160,ROW()-5-$G$3+1,0,$G$3,1)))) | H81: =IF(77<$G$3,0,SUMPRODUCT(--(ROW('04 变换后数据'!$D$5:$D$160)<=ROW()),--ISNUMBER(OFFSET('04 变换后数据'!$D$5:$D$160,ROW()-5-$G$3+1,0,MIN($G$3,ROW()-4),1)),--ISNUMBER(OFFSET('04 变换后数据'!$H$5:$H$160,ROW()-5-$G$3+1,0,MIN($G$3,ROW()-4),1)))) | I81: =IF(ISNUMBER(E81),IF(ABS(E81)>=0.7,"强",IF(ABS(E81)>=0.4,"中","弱")),"-")
A82: 78 | B82: ='04 变换后数据'!B82 | C82: =IF(78<$C$3,"",IF(482=0,"",IF(482<MAX(5,ROUND($C$3*0.8,0)),"样本不足",CORREL(OFFSET('04 变换后数据'!$D$5:$D$160,ROW()-5-$C$3+1,0,$C$3,1),OFFSET('04 变换后数据'!$H$5:$H$160,ROW()-5-$C$3+1,0,$C$3,1)))) | D82: =IF(78<$C$3,0,SUMPRODUCT(--(ROW('04 变换后数据'!$D$5:$D$160)<=ROW()),--ISNUMBER(OFFSET('04 变换后数据'!$D$5:$D$160,ROW()-5-$C$3+1,0,MIN($C$3,ROW()-4),1)),--ISNUMBER(OFFSET('04 变换后数据'!$H$5:$H$160,ROW()-5-$C$3+1,0,MIN($C$3,ROW()-4),1)))) | E82: =IF(78<$E$3,"",IF(682=0,"",IF(682<MAX(5,ROUND($E$3*0.8,0)),"样本不足",CORREL(OFFSET('04 变换后数据'!$D$5:$D$160,ROW()-5-$E$3+1,0,$E$3,1),OFFSET('04 变换后数据'!$H$5:$H$160,ROW()-5-$E$3+1,0,$E$3,1)))) | F82: =IF(78<$E$3,0,SUMPRODUCT(--(ROW('04 变换后数据'!$D$5:$D$160)<=ROW()),--ISNUMBER(OFFSET('04 变换后数据'!$D$5:$D$160,ROW()-5-$E$3+1,0,MIN($E$3,ROW()-4),1)),--ISNUMBER(OFFSET('04 变换后数据'!$H$5:$H$160,ROW()-5-$E$3+1,0,MIN($E$3,ROW()-4),1)))) | G82: =IF(78<$G$3,"",IF(882=0,"",IF(882<MAX(5,ROUND($G$3*0.8,0)),"样本不足",CORREL(OFFSET('04 变换后数据'!$D$5:$D$160,ROW()-5-$G$3+1,0,$G$3,1),OFFSET('04 变换后数据'!$H$5:$H$160,ROW()-5-$G$3+1,0,$G$3,1)))) | H82: =IF(78<$G$3,0,SUMPRODUCT(--(ROW('04 变换后数据'!$D$5:$D$160)<=ROW()),--ISNUMBER(OFFSET('04 变换后数据'!$D$5:$D$160,ROW()-5-$G$3+1,0,MIN($G$3,ROW()-4),1)),--ISNUMBER(OFFSET('04 变换后数据'!$H$5:$H$160,ROW()-5-$G$3+1,0,MIN($G$3,ROW()-4),1)))) | I82: =IF(ISNUMBER(E82),IF(ABS(E82)>=0.7,"强",IF(ABS(E82)>=0.4,"中","弱")),"-")
A83: 79 | B83: ='04 变换后数据'!B83 | C83: =IF(79<$C$3,"",IF(483=0,"",IF(483<MAX(5,ROUND($C$3*0.8,0)),"样本不足",CORREL(OFFSET('04 变换后数据'!$D$5:$D$160,ROW()-5-$C$3+1,0,$C$3,1),OFFSET('04 变换后数据'!$H$5:$H$160,ROW()-5-$C$3+1,0,$C$3,1)))) | D83: =IF(79<$C$3,0,SUMPRODUCT(--(ROW('04 变换后数据'!$D$5:$D$160)<=ROW()),--ISNUMBER(OFFSET('04 变换后数据'!$D$5:$D$160,ROW()-5-$C$3+1,0,MIN($C$3,ROW()-4),1)),--ISNUMBER(OFFSET('04 变换后数据'!$H$5:$H$160,ROW()-5-$C$3+1,0,MIN($C$3,ROW()-4),1)))) | E83: =IF(79<$E$3,"",IF(683=0,"",IF(683<MAX(5,ROUND($E$3*0.8,0)),"样本不足",CORREL(OFFSET('04 变换后数据'!$D$5:$D$160,ROW()-5-$E$3+1,0,$E$3,1),OFFSET('04 变换后数据'!$H$5:$H$160,ROW()-5-$E$3+1,0,$E$3,1)))) | F83: =IF(79<$E$3,0,SUMPRODUCT(--(ROW('04 变换后数据'!$D$5:$D$160)<=ROW()),--ISNUMBER(OFFSET('04 变换后数据'!$D$5:$D$160,ROW()-5-$E$3+1,0,MIN($E$3,ROW()-4),1)),--ISNUMBER(OFFSET('04 变换后数据'!$H$5:$H$160,ROW()-5-$E$3+1,0,MIN($E$3,ROW()-4),1)))) | G83: =IF(79<$G$3,"",IF(883=0,"",IF(883<MAX(5,ROUND($G$3*0.8,0)),"样本不足",CORREL(OFFSET('04 变换后数据'!$D$5:$D$160,ROW()-5-$G$3+1,0,$G$3,1),OFFSET('04 变换后数据'!$H$5:$H$160,ROW()-5-$G$3+1,0,$G$3,1)))) | H83: =IF(79<$G$3,0,SUMPRODUCT(--(ROW('04 变换后数据'!$D$5:$D$160)<=ROW()),--ISNUMBER(OFFSET('04 变换后数据'!$D$5:$D$160,ROW()-5-$G$3+1,0,MIN($G$3,ROW()-4),1)),--ISNUMBER(OFFSET('04 变换后数据'!$H$5:$H$160,ROW()-5-$G$3+1,0,MIN($G$3,ROW()-4),1)))) | I83: =IF(ISNUMBER(E83),IF(ABS(E83)>=0.7,"强",IF(ABS(E83)>=0.4,"中","弱")),"-")
A84: 80 | B84: ='04 变换后数据'!B84 | C84: =IF(80<$C$3,"",IF(484=0,"",IF(484<MAX(5,ROUND($C$3*0.8,0)),"样本不足",CORREL(OFFSET('04 变换后数据'!$D$5:$D$160,ROW()-5-$C$3+1,0,$C$3,1),OFFSET('04 变换后数据'!$H$5:$H$160,ROW()-5-$C$3+1,0,$C$3,1)))) | D84: =IF(80<$C$3,0,SUMPRODUCT(--(ROW('04 变换后数据'!$D$5:$D$160)<=ROW()),--ISNUMBER(OFFSET('04 变换后数据'!$D$5:$D$160,ROW()-5-$C$3+1,0,MIN($C$3,ROW()-4),1)),--ISNUMBER(OFFSET('04 变换后数据'!$H$5:$H$160,ROW()-5-$C$3+1,0,MIN($C$3,ROW()-4),1)))) | E84: =IF(80<$E$3,"",IF(684=0,"",IF(684<MAX(5,ROUND($E$3*0.8,0)),"样本不足",CORREL(OFFSET('04 变换后数据'!$D$5:$D$160,ROW()-5-$E$3+1,0,$E$3,1),OFFSET('04 变换后数据'!$H$5:$H$160,ROW()-5-$E$3+1,0,$E$3,1)))) | F84: =IF(80<$E$3,0,SUMPRODUCT(--(ROW('04 变换后数据'!$D$5:$D$160)<=ROW()),--ISNUMBER(OFFSET('04 变换后数据'!$D$5:$D$160,ROW()-5-$E$3+1,0,MIN($E$3,ROW()-4),1)),--ISNUMBER(OFFSET('04 变换后数据'!$H$5:$H$160,ROW()-5-$E$3+1,0,MIN($E$3,ROW()-4),1)))) | G84: =IF(80<$G$3,"",IF(884=0,"",IF(884<MAX(5,ROUND($G$3*0.8,0)),"样本不足",CORREL(OFFSET('04 变换后数据'!$D$5:$D$160,ROW()-5-$G$3+1,0,$G$3,1),OFFSET('04 变换后数据'!$H$5:$H$160,ROW()-5-$G$3+1,0,$G$3,1)))) | H84: =IF(80<$G$3,0,SUMPRODUCT(--(ROW('04 变换后数据'!$D$5:$D$160)<=ROW()),--ISNUMBER(OFFSET('04 变换后数据'!$D$5:$D$160,ROW()-5-$G$3+1,0,MIN($G$3,ROW()-4),1)),--ISNUMBER(OFFSET('04 变换后数据'!$H$5:$H$160,ROW()-5-$G$3+1,0,MIN($G$3,ROW()-4),1)))) | I84: =IF(ISNUMBER(E84),IF(ABS(E84)>=0.7,"强",IF(ABS(E84)>=0.4,"中","弱")),"-")
A85: 81 | B85: ='04 变换后数据'!B85 | C85: =IF(81<$C$3,"",IF(485=0,"",IF(485<MAX(5,ROUND($C$3*0.8,0)),"样本不足",CORREL(OFFSET('04 变换后数据'!$D$5:$D$160,ROW()-5-$C$3+1,0,$C$3,1),OFFSET('04 变换后数据'!$H$5:$H$160,ROW()-5-$C$3+1,0,$C$3,1)))) | D85: =IF(81<$C$3,0,SUMPRODUCT(--(ROW('04 变换后数据'!$D$5:$D$160)<=ROW()),--ISNUMBER(OFFSET('04 变换后数据'!$D$5:$D$160,ROW()-5-$C$3+1,0,MIN($C$3,ROW()-4),1)),--ISNUMBER(OFFSET('04 变换后数据'!$H$5:$H$160,ROW()-5-$C$3+1,0,MIN($C$3,ROW()-4),1)))) | E85: =IF(81<$E$3,"",IF(685=0,"",IF(685<MAX(5,ROUND($E$3*0.8,0)),"样本不足",CORREL(OFFSET('04 变换后数据'!$D$5:$D$160,ROW()-5-$E$3+1,0,$E$3,1),OFFSET('04 变换后数据'!$H$5:$H$160,ROW()-5-$E$3+1,0,$E$3,1)))) | F85: =IF(81<$E$3,0,SUMPRODUCT(--(ROW('04 变换后数据'!$D$5:$D$160)<=ROW()),--ISNUMBER(OFFSET('04 变换后数据'!$D$5:$D$160,ROW()-5-$E$3+1,0,MIN($E$3,ROW()-4),1)),--ISNUMBER(OFFSET('04 变换后数据'!$H$5:$H$160,ROW()-5-$E$3+1,0,MIN($E$3,ROW()-4),1)))) | G85: =IF(81<$G$3,"",IF(885=0,"",IF(885<MAX(5,ROUND($G$3*0.8,0)),"样本不足",CORREL(OFFSET('04 变换后数据'!$D$5:$D$160,ROW()-5-$G$3+1,0,$G$3,1),OFFSET('04 变换后数据'!$H$5:$H$160,ROW()-5-$G$3+1,0,$G$3,1)))) | H85: =IF(81<$G$3,0,SUMPRODUCT(--(ROW('04 变换后数据'!$D$5:$D$160)<=ROW()),--ISNUMBER(OFFSET('04 变换后数据'!$D$5:$D$160,ROW()-5-$G$3+1,0,MIN($G$3,ROW()-4),1)),--ISNUMBER(OFFSET('04 变换后数据'!$H$5:$H$160,ROW()-5-$G$3+1,0,MIN($G$3,ROW()-4),1)))) | I85: =IF(ISNUMBER(E85),IF(ABS(E85)>=0.7,"强",IF(ABS(E85)>=0.4,"中","弱")),"-")
A86: 82 | B86: ='04 变换后数据'!B86 | C86: =IF(82<$C$3,"",IF(486=0,"",IF(486<MAX(5,ROUND($C$3*0.8,0)),"样本不足",CORREL(OFFSET('04 变换后数据'!$D$5:$D$160,ROW()-5-$C$3+1,0,$C$3,1),OFFSET('04 变换后数据'!$H$5:$H$160,ROW()-5-$C$3+1,0,$C$3,1)))) | D86: =IF(82<$C$3,0,SUMPRODUCT(--(ROW('04 变换后数据'!$D$5:$D$160)<=ROW()),--ISNUMBER(OFFSET('04 变换后数据'!$D$5:$D$160,ROW()-5-$C$3+1,0,MIN($C$3,ROW()-4),1)),--ISNUMBER(OFFSET('04 变换后数据'!$H$5:$H$160,ROW()-5-$C$3+1,0,MIN($C$3,ROW()-4),1)))) | E86: =IF(82<$E$3,"",IF(686=0,"",IF(686<MAX(5,ROUND($E$3*0.8,0)),"样本不足",CORREL(OFFSET('04 变换后数据'!$D$5:$D$160,ROW()-5-$E$3+1,0,$E$3,1),OFFSET('04 变换后数据'!$H$5:$H$160,ROW()-5-$E$3+1,0,$E$3,1)))) | F86: =IF(82<$E$3,0,SUMPRODUCT(--(ROW('04 变换后数据'!$D$5:$D$160)<=ROW()),--ISNUMBER(OFFSET('04 变换后数据'!$D$5:$D$160,ROW()-5-$E$3+1,0,MIN($E$3,ROW()-4),1)),--ISNUMBER(OFFSET('04 变换后数据'!$H$5:$H$160,ROW()-5-$E$3+1,0,MIN($E$3,ROW()-4),1)))) | G86: =IF(82<$G$3,"",IF(886=0,"",IF(886<MAX(5,ROUND($G$3*0.8,0)),"样本不足",CORREL(OFFSET('04 变换后数据'!$D$5:$D$160,ROW()-5-$G$3+1,0,$G$3,1),OFFSET('04 变换后数据'!$H$5:$H$160,ROW()-5-$G$3+1,0,$G$3,1)))) | H86: =IF(82<$G$3,0,SUMPRODUCT(--(ROW('04 变换后数据'!$D$5:$D$160)<=ROW()),--ISNUMBER(OFFSET('04 变换后数据'!$D$5:$D$160,ROW()-5-$G$3+1,0,MIN($G$3,ROW()-4),1)),--ISNUMBER(OFFSET('04 变换后数据'!$H$5:$H$160,ROW()-5-$G$3+1,0,MIN($G$3,ROW()-4),1)))) | I86: =IF(ISNUMBER(E86),IF(ABS(E86)>=0.7,"强",IF(ABS(E86)>=0.4,"中","弱")),"-")
A87: 83 | B87: ='04 变换后数据'!B87 | C87: =IF(83<$C$3,"",IF(487=0,"",IF(487<MAX(5,ROUND($C$3*0.8,0)),"样本不足",CORREL(OFFSET('04 变换后数据'!$D$5:$D$160,ROW()-5-$C$3+1,0,$C$3,1),OFFSET('04 变换后数据'!$H$5:$H$160,ROW()-5-$C$3+1,0,$C$3,1)))) | D87: =IF(83<$C$3,0,SUMPRODUCT(--(ROW('04 变换后数据'!$D$5:$D$160)<=ROW()),--ISNUMBER(OFFSET('04 变换后数据'!$D$5:$D$160,ROW()-5-$C$3+1,0,MIN($C$3,ROW()-4),1)),--ISNUMBER(OFFSET('04 变换后数据'!$H$5:$H$160,ROW()-5-$C$3+1,0,MIN($C$3,ROW()-4),1)))) | E87: =IF(83<$E$3,"",IF(687=0,"",IF(687<MAX(5,ROUND($E$3*0.8,0)),"样本不足",CORREL(OFFSET('04 变换后数据'!$D$5:$D$160,ROW()-5-$E$3+1,0,$E$3,1),OFFSET('04 变换后数据'!$H$5:$H$160,ROW()-5-$E$3+1,0,$E$3,1)))) | F87: =IF(83<$E$3,0,SUMPRODUCT(--(ROW('04 变换后数据'!$D$5:$D$160)<=ROW()),--ISNUMBER(OFFSET('04 变换后数据'!$D$5:$D$160,ROW()-5-$E$3+1,0,MIN($E$3,ROW()-4),1)),--ISNUMBER(OFFSET('04 变换后数据'!$H$5:$H$160,ROW()-5-$E$3+1,0,MIN($E$3,ROW()-4),1)))) | G87: =IF(83<$G$3,"",IF(887=0,"",IF(887<MAX(5,ROUND($G$3*0.8,0)),"样本不足",CORREL(OFFSET('04 变换后数据'!$D$5:$D$160,ROW()-5-$G$3+1,0,$G$3,1),OFFSET('04 变换后数据'!$H$5:$H$160,ROW()-5-$G$3+1,0,$G$3,1)))) | H87: =IF(83<$G$3,0,SUMPRODUCT(--(ROW('04 变换后数据'!$D$5:$D$160)<=ROW()),--ISNUMBER(OFFSET('04 变换后数据'!$D$5:$D$160,ROW()-5-$G$3+1,0,MIN($G$3,ROW()-4),1)),--ISNUMBER(OFFSET('04 变换后数据'!$H$5:$H$160,ROW()-5-$G$3+1,0,MIN($G$3,ROW()-4),1)))) | I87: =IF(ISNUMBER(E87),IF(ABS(E87)>=0.7,"强",IF(ABS(E87)>=0.4,"中","弱")),"-")
A88: 84 | B88: ='04 变换后数据'!B88 | C88: =IF(84<$C$3,"",IF(488=0,"",IF(488<MAX(5,ROUND($C$3*0.8,0)),"样本不足",CORREL(OFFSET('04 变换后数据'!$D$5:$D$160,ROW()-5-$C$3+1,0,$C$3,1),OFFSET('04 变换后数据'!$H$5:$H$160,ROW()-5-$C$3+1,0,$C$3,1)))) | D88: =IF(84<$C$3,0,SUMPRODUCT(--(ROW('04 变换后数据'!$D$5:$D$160)<=ROW()),--ISNUMBER(OFFSET('04 变换后数据'!$D$5:$D$160,ROW()-5-$C$3+1,0,MIN($C$3,ROW()-4),1)),--ISNUMBER(OFFSET('04 变换后数据'!$H$5:$H$160,ROW()-5-$C$3+1,0,MIN($C$3,ROW()-4),1)))) | E88: =IF(84<$E$3,"",IF(688=0,"",IF(688<MAX(5,ROUND($E$3*0.8,0)),"样本不足",CORREL(OFFSET('04 变换后数据'!$D$5:$D$160,ROW()-5-$E$3+1,0,$E$3,1),OFFSET('04 变换后数据'!$H$5:$H$160,ROW()-5-$E$3+1,0,$E$3,1)))) | F88: =IF(84<$E$3,0,SUMPRODUCT(--(ROW('04 变换后数据'!$D$5:$D$160)<=ROW()),--ISNUMBER(OFFSET('04 变换后数据'!$D$5:$D$160,ROW()-5-$E$3+1,0,MIN($E$3,ROW()-4),1)),--ISNUMBER(OFFSET('04 变换后数据'!$H$5:$H$160,ROW()-5-$E$3+1,0,MIN($E$3,ROW()-4),1)))) | G88: =IF(84<$G$3,"",IF(888=0,"",IF(888<MAX(5,ROUND($G$3*0.8,0)),"样本不足",CORREL(OFFSET('04 变换后数据'!$D$5:$D$160,ROW()-5-$G$3+1,0,$G$3,1),OFFSET('04 变换后数据'!$H$5:$H$160,ROW()-5-$G$3+1,0,$G$3,1)))) | H88: =IF(84<$G$3,0,SUMPRODUCT(--(ROW('04 变换后数据'!$D$5:$D$160)<=ROW()),--ISNUMBER(OFFSET('04 变换后数据'!$D$5:$D$160,ROW()-5-$G$3+1,0,MIN($G$3,ROW()-4),1)),--ISNUMBER(OFFSET('04 变换后数据'!$H$5:$H$160,ROW()-5-$G$3+1,0,MIN($G$3,ROW()-4),1)))) | I88: =IF(ISNUMBER(E88),IF(ABS(E88)>=0.7,"强",IF(ABS(E88)>=0.4,"中","弱")),"-")
A89: 85 | B89: ='04 变换后数据'!B89 | C89: =IF(85<$C$3,"",IF(489=0,"",IF(489<MAX(5,ROUND($C$3*0.8,0)),"样本不足",CORREL(OFFSET('04 变换后数据'!$D$5:$D$160,ROW()-5-$C$3+1,0,$C$3,1),OFFSET('04 变换后数据'!$H$5:$H$160,ROW()-5-$C$3+1,0,$C$3,1)))) | D89: =IF(85<$C$3,0,SUMPRODUCT(--(ROW('04 变换后数据'!$D$5:$D$160)<=ROW()),--ISNUMBER(OFFSET('04 变换后数据'!$D$5:$D$160,ROW()-5-$C$3+1,0,MIN($C$3,ROW()-4),1)),--ISNUMBER(OFFSET('04 变换后数据'!$H$5:$H$160,ROW()-5-$C$3+1,0,MIN($C$3,ROW()-4),1)))) | E89: =IF(85<$E$3,"",IF(689=0,"",IF(689<MAX(5,ROUND($E$3*0.8,0)),"样本不足",CORREL(OFFSET('04 变换后数据'!$D$5:$D$160,ROW()-5-$E$3+1,0,$E$3,1),OFFSET('04 变换后数据'!$H$5:$H$160,ROW()-5-$E$3+1,0,$E$3,1)))) | F89: =IF(85<$E$3,0,SUMPRODUCT(--(ROW('04 变换后数据'!$D$5:$D$160)<=ROW()),--ISNUMBER(OFFSET('04 变换后数据'!$D$5:$D$160,ROW()-5-$E$3+1,0,MIN($E$3,ROW()-4),1)),--ISNUMBER(OFFSET('04 变换后数据'!$H$5:$H$160,ROW()-5-$E$3+1,0,MIN($E$3,ROW()-4),1)))) | G89: =IF(85<$G$3,"",IF(889=0,"",IF(889<MAX(5,ROUND($G$3*0.8,0)),"样本不足",CORREL(OFFSET('04 变换后数据'!$D$5:$D$160,ROW()-5-$G$3+1,0,$G$3,1),OFFSET('04 变换后数据'!$H$5:$H$160,ROW()-5-$G$3+1,0,$G$3,1)))) | H89: =IF(85<$G$3,0,SUMPRODUCT(--(ROW('04 变换后数据'!$D$5:$D$160)<=ROW()),--ISNUMBER(OFFSET('04 变换后数据'!$D$5:$D$160,ROW()-5-$G$3+1,0,MIN($G$3,ROW()-4),1)),--ISNUMBER(OFFSET('04 变换后数据'!$H$5:$H$160,ROW()-5-$G$3+1,0,MIN($G$3,ROW()-4),1)))) | I89: =IF(ISNUMBER(E89),IF(ABS(E89)>=0.7,"强",IF(ABS(E89)>=0.4,"中","弱")),"-")
A90: 86 | B90: ='04 变换后数据'!B90 | C90: =IF(86<$C$3,"",IF(490=0,"",IF(490<MAX(5,ROUND($C$3*0.8,0)),"样本不足",CORREL(OFFSET('04 变换后数据'!$D$5:$D$160,ROW()-5-$C$3+1,0,$C$3,1),OFFSET('04 变换后数据'!$H$5:$H$160,ROW()-5-$C$3+1,0,$C$3,1)))) | D90: =IF(86<$C$3,0,SUMPRODUCT(--(ROW('04 变换后数据'!$D$5:$D$160)<=ROW()),--ISNUMBER(OFFSET('04 变换后数据'!$D$5:$D$160,ROW()-5-$C$3+1,0,MIN($C$3,ROW()-4),1)),--ISNUMBER(OFFSET('04 变换后数据'!$H$5:$H$160,ROW()-5-$C$3+1,0,MIN($C$3,ROW()-4),1)))) | E90: =IF(86<$E$3,"",IF(690=0,"",IF(690<MAX(5,ROUND($E$3*0.8,0)),"样本不足",CORREL(OFFSET('04 变换后数据'!$D$5:$D$160,ROW()-5-$E$3+1,0,$E$3,1),OFFSET('04 变换后数据'!$H$5:$H$160,ROW()-5-$E$3+1,0,$E$3,1)))) | F90: =IF(86<$E$3,0,SUMPRODUCT(--(ROW('04 变换后数据'!$D$5:$D$160)<=ROW()),--ISNUMBER(OFFSET('04 变换后数据'!$D$5:$D$160,ROW()-5-$E$3+1,0,MIN($E$3,ROW()-4),1)),--ISNUMBER(OFFSET('04 变换后数据'!$H$5:$H$160,ROW()-5-$E$3+1,0,MIN($E$3,ROW()-4),1)))) | G90: =IF(86<$G$3,"",IF(890=0,"",IF(890<MAX(5,ROUND($G$3*0.8,0)),"样本不足",CORREL(OFFSET('04 变换后数据'!$D$5:$D$160,ROW()-5-$G$3+1,0,$G$3,1),OFFSET('04 变换后数据'!$H$5:$H$160,ROW()-5-$G$3+1,0,$G$3,1)))) | H90: =IF(86<$G$3,0,SUMPRODUCT(--(ROW('04 变换后数据'!$D$5:$D$160)<=ROW()),--ISNUMBER(OFFSET('04 变换后数据'!$D$5:$D$160,ROW()-5-$G$3+1,0,MIN($G$3,ROW()-4),1)),--ISNUMBER(OFFSET('04 变换后数据'!$H$5:$H$160,ROW()-5-$G$3+1,0,MIN($G$3,ROW()-4),1)))) | I90: =IF(ISNUMBER(E90),IF(ABS(E90)>=0.7,"强",IF(ABS(E90)>=0.4,"中","弱")),"-")
A91: 87 | B91: ='04 变换后数据'!B91 | C91: =IF(87<$C$3,"",IF(491=0,"",IF(491<MAX(5,ROUND($C$3*0.8,0)),"样本不足",CORREL(OFFSET('04 变换后数据'!$D$5:$D$160,ROW()-5-$C$3+1,0,$C$3,1),OFFSET('04 变换后数据'!$H$5:$H$160,ROW()-5-$C$3+1,0,$C$3,1)))) | D91: =IF(87<$C$3,0,SUMPRODUCT(--(ROW('04 变换后数据'!$D$5:$D$160)<=ROW()),--ISNUMBER(OFFSET('04 变换后数据'!$D$5:$D$160,ROW()-5-$C$3+1,0,MIN($C$3,ROW()-4),1)),--ISNUMBER(OFFSET('04 变换后数据'!$H$5:$H$160,ROW()-5-$C$3+1,0,MIN($C$3,ROW()-4),1)))) | E91: =IF(87<$E$3,"",IF(691=0,"",IF(691<MAX(5,ROUND($E$3*0.8,0)),"样本不足",CORREL(OFFSET('04 变换后数据'!$D$5:$D$160,ROW()-5-$E$3+1,0,$E$3,1),OFFSET('04 变换后数据'!$H$5:$H$160,ROW()-5-$E$3+1,0,$E$3,1)))) | F91: =IF(87<$E$3,0,SUMPRODUCT(--(ROW('04 变换后数据'!$D$5:$D$160)<=ROW()),--ISNUMBER(OFFSET('04 变换后数据'!$D$5:$D$160,ROW()-5-$E$3+1,0,MIN($E$3,ROW()-4),1)),--ISNUMBER(OFFSET('04 变换后数据'!$H$5:$H$160,ROW()-5-$E$3+1,0,MIN($E$3,ROW()-4),1)))) | G91: =IF(87<$G$3,"",IF(891=0,"",IF(891<MAX(5,ROUND($G$3*0.8,0)),"样本不足",CORREL(OFFSET('04 变换后数据'!$D$5:$D$160,ROW()-5-$G$3+1,0,$G$3,1),OFFSET('04 变换后数据'!$H$5:$H$160,ROW()-5-$G$3+1,0,$G$3,1)))) | H91: =IF(87<$G$3,0,SUMPRODUCT(--(ROW('04 变换后数据'!$D$5:$D$160)<=ROW()),--ISNUMBER(OFFSET('04 变换后数据'!$D$5:$D$160,ROW()-5-$G$3+1,0,MIN($G$3,ROW()-4),1)),--ISNUMBER(OFFSET('04 变换后数据'!$H$5:$H$160,ROW()-5-$G$3+1,0,MIN($G$3,ROW()-4),1)))) | I91: =IF(ISNUMBER(E91),IF(ABS(E91)>=0.7,"强",IF(ABS(E91)>=0.4,"中","弱")),"-")
A92: 88 | B92: ='04 变换后数据'!B92 | C92: =IF(88<$C$3,"",IF(492=0,"",IF(492<MAX(5,ROUND($C$3*0.8,0)),"样本不足",CORREL(OFFSET('04 变换后数据'!$D$5:$D$160,ROW()-5-$C$3+1,0,$C$3,1),OFFSET('04 变换后数据'!$H$5:$H$160,ROW()-5-$C$3+1,0,$C$3,1)))) | D92: =IF(88<$C$3,0,SUMPRODUCT(--(ROW('04 变换后数据'!$D$5:$D$160)<=ROW()),--ISNUMBER(OFFSET('04 变换后数据'!$D$5:$D$160,ROW()-5-$C$3+1,0,MIN($C$3,ROW()-4),1)),--ISNUMBER(OFFSET('04 变换后数据'!$H$5:$H$160,ROW()-5-$C$3+1,0,MIN($C$3,ROW()-4),1)))) | E92: =IF(88<$E$3,"",IF(692=0,"",IF(692<MAX(5,ROUND($E$3*0.8,0)),"样本不足",CORREL(OFFSET('04 变换后数据'!$D$5:$D$160,ROW()-5-$E$3+1,0,$E$3,1),OFFSET('04 变换后数据'!$H$5:$H$160,ROW()-5-$E$3+1,0,$E$3,1)))) | F92: =IF(88<$E$3,0,SUMPRODUCT(--(ROW('04 变换后数据'!$D$5:$D$160)<=ROW()),--ISNUMBER(OFFSET('04 变换后数据'!$D$5:$D$160,ROW()-5-$E$3+1,0,MIN($E$3,ROW()-4),1)),--ISNUMBER(OFFSET('04 变换后数据'!$H$5:$H$160,ROW()-5-$E$3+1,0,MIN($E$3,ROW()-4),1)))) | G92: =IF(88<$G$3,"",IF(892=0,"",IF(892<MAX(5,ROUND($G$3*0.8,0)),"样本不足",CORREL(OFFSET('04 变换后数据'!$D$5:$D$160,ROW()-5-$G$3+1,0,$G$3,1),OFFSET('04 变换后数据'!$H$5:$H$160,ROW()-5-$G$3+1,0,$G$3,1)))) | H92: =IF(88<$G$3,0,SUMPRODUCT(--(ROW('04 变换后数据'!$D$5:$D$160)<=ROW()),--ISNUMBER(OFFSET('04 变换后数据'!$D$5:$D$160,ROW()-5-$G$3+1,0,MIN($G$3,ROW()-4),1)),--ISNUMBER(OFFSET('04 变换后数据'!$H$5:$H$160,ROW()-5-$G$3+1,0,MIN($G$3,ROW()-4),1)))) | I92: =IF(ISNUMBER(E92),IF(ABS(E92)>=0.7,"强",IF(ABS(E92)>=0.4,"中","弱")),"-")
A93: 89 | B93: ='04 变换后数据'!B93 | C93: =IF(89<$C$3,"",IF(493=0,"",IF(493<MAX(5,ROUND($C$3*0.8,0)),"样本不足",CORREL(OFFSET('04 变换后数据'!$D$5:$D$160,ROW()-5-$C$3+1,0,$C$3,1),OFFSET('04 变换后数据'!$H$5:$H$160,ROW()-5-$C$3+1,0,$C$3,1)))) | D93: =IF(89<$C$3,0,SUMPRODUCT(--(ROW('04 变换后数据'!$D$5:$D$160)<=ROW()),--ISNUMBER(OFFSET('04 变换后数据'!$D$5:$D$160,ROW()-5-$C$3+1,0,MIN($C$3,ROW()-4),1)),--ISNUMBER(OFFSET('04 变换后数据'!$H$5:$H$160,ROW()-5-$C$3+1,0,MIN($C$3,ROW()-4),1)))) | E93: =IF(89<$E$3,"",IF(693=0,"",IF(693<MAX(5,ROUND($E$3*0.8,0)),"样本不足",CORREL(OFFSET('04 变换后数据'!$D$5:$D$160,ROW()-5-$E$3+1,0,$E$3,1),OFFSET('04 变换后数据'!$H$5:$H$160,ROW()-5-$E$3+1,0,$E$3,1)))) | F93: =IF(89<$E$3,0,SUMPRODUCT(--(ROW('04 变换后数据'!$D$5:$D$160)<=ROW()),--ISNUMBER(OFFSET('04 变换后数据'!$D$5:$D$160,ROW()-5-$E$3+1,0,MIN($E$3,ROW()-4),1)),--ISNUMBER(OFFSET('04 变换后数据'!$H$5:$H$160,ROW()-5-$E$3+1,0,MIN($E$3,ROW()-4),1)))) | G93: =IF(89<$G$3,"",IF(893=0,"",IF(893<MAX(5,ROUND($G$3*0.8,0)),"样本不足",CORREL(OFFSET('04 变换后数据'!$D$5:$D$160,ROW()-5-$G$3+1,0,$G$3,1),OFFSET('04 变换后数据'!$H$5:$H$160,ROW()-5-$G$3+1,0,$G$3,1)))) | H93: =IF(89<$G$3,0,SUMPRODUCT(--(ROW('04 变换后数据'!$D$5:$D$160)<=ROW()),--ISNUMBER(OFFSET('04 变换后数据'!$D$5:$D$160,ROW()-5-$G$3+1,0,MIN($G$3,ROW()-4),1)),--ISNUMBER(OFFSET('04 变换后数据'!$H$5:$H$160,ROW()-5-$G$3+1,0,MIN($G$3,ROW()-4),1)))) | I93: =IF(ISNUMBER(E93),IF(ABS(E93)>=0.7,"强",IF(ABS(E93)>=0.4,"中","弱")),"-")
A94: 90 | B94: ='04 变换后数据'!B94 | C94: =IF(90<$C$3,"",IF(494=0,"",IF(494<MAX(5,ROUND($C$3*0.8,0)),"样本不足",CORREL(OFFSET('04 变换后数据'!$D$5:$D$160,ROW()-5-$C$3+1,0,$C$3,1),OFFSET('04 变换后数据'!$H$5:$H$160,ROW()-5-$C$3+1,0,$C$3,1)))) | D94: =IF(90<$C$3,0,SUMPRODUCT(--(ROW('04 变换后数据'!$D$5:$D$160)<=ROW()),--ISNUMBER(OFFSET('04 变换后数据'!$D$5:$D$160,ROW()-5-$C$3+1,0,MIN($C$3,ROW()-4),1)),--ISNUMBER(OFFSET('04 变换后数据'!$H$5:$H$160,ROW()-5-$C$3+1,0,MIN($C$3,ROW()-4),1)))) | E94: =IF(90<$E$3,"",IF(694=0,"",IF(694<MAX(5,ROUND($E$3*0.8,0)),"样本不足",CORREL(OFFSET('04 变换后数据'!$D$5:$D$160,ROW()-5-$E$3+1,0,$E$3,1),OFFSET('04 变换后数据'!$H$5:$H$160,ROW()-5-$E$3+1,0,$E$3,1)))) | F94: =IF(90<$E$3,0,SUMPRODUCT(--(ROW('04 变换后数据'!$D$5:$D$160)<=ROW()),--ISNUMBER(OFFSET('04 变换后数据'!$D$5:$D$160,ROW()-5-$E$3+1,0,MIN($E$3,ROW()-4),1)),--ISNUMBER(OFFSET('04 变换后数据'!$H$5:$H$160,ROW()-5-$E$3+1,0,MIN($E$3,ROW()-4),1)))) | G94: =IF(90<$G$3,"",IF(894=0,"",IF(894<MAX(5,ROUND($G$3*0.8,0)),"样本不足",CORREL(OFFSET('04 变换后数据'!$D$5:$D$160,ROW()-5-$G$3+1,0,$G$3,1),OFFSET('04 变换后数据'!$H$5:$H$160,ROW()-5-$G$3+1,0,$G$3,1)))) | H94: =IF(90<$G$3,0,SUMPRODUCT(--(ROW('04 变换后数据'!$D$5:$D$160)<=ROW()),--ISNUMBER(OFFSET('04 变换后数据'!$D$5:$D$160,ROW()-5-$G$3+1,0,MIN($G$3,ROW()-4),1)),--ISNUMBER(OFFSET('04 变换后数据'!$H$5:$H$160,ROW()-5-$G$3+1,0,MIN($G$3,ROW()-4),1)))) | I94: =IF(ISNUMBER(E94),IF(ABS(E94)>=0.7,"强",IF(ABS(E94)>=0.4,"中","弱")),"-")
A95: 91 | B95: ='04 变换后数据'!B95 | C95: =IF(91<$C$3,"",IF(495=0,"",IF(495<MAX(5,ROUND($C$3*0.8,0)),"样本不足",CORREL(OFFSET('04 变换后数据'!$D$5:$D$160,ROW()-5-$C$3+1,0,$C$3,1),OFFSET('04 变换后数据'!$H$5:$H$160,ROW()-5-$C$3+1,0,$C$3,1)))) | D95: =IF(91<$C$3,0,SUMPRODUCT(--(ROW('04 变换后数据'!$D$5:$D$160)<=ROW()),--ISNUMBER(OFFSET('04 变换后数据'!$D$5:$D$160,ROW()-5-$C$3+1,0,MIN($C$3,ROW()-4),1)),--ISNUMBER(OFFSET('04 变换后数据'!$H$5:$H$160,ROW()-5-$C$3+1,0,MIN($C$3,ROW()-4),1)))) | E95: =IF(91<$E$3,"",IF(695=0,"",IF(695<MAX(5,ROUND($E$3*0.8,0)),"样本不足",CORREL(OFFSET('04 变换后数据'!$D$5:$D$160,ROW()-5-$E$3+1,0,$E$3,1),OFFSET('04 变换后数据'!$H$5:$H$160,ROW()-5-$E$3+1,0,$E$3,1)))) | F95: =IF(91<$E$3,0,SUMPRODUCT(--(ROW('04 变换后数据'!$D$5:$D$160)<=ROW()),--ISNUMBER(OFFSET('04 变换后数据'!$D$5:$D$160,ROW()-5-$E$3+1,0,MIN($E$3,ROW()-4),1)),--ISNUMBER(OFFSET('04 变换后数据'!$H$5:$H$160,ROW()-5-$E$3+1,0,MIN($E$3,ROW()-4),1)))) | G95: =IF(91<$G$3,"",IF(895=0,"",IF(895<MAX(5,ROUND($G$3*0.8,0)),"样本不足",CORREL(OFFSET('04 变换后数据'!$D$5:$D$160,ROW()-5-$G$3+1,0,$G$3,1),OFFSET('04 变换后数据'!$H$5:$H$160,ROW()-5-$G$3+1,0,$G$3,1)))) | H95: =IF(91<$G$3,0,SUMPRODUCT(--(ROW('04 变换后数据'!$D$5:$D$160)<=ROW()),--ISNUMBER(OFFSET('04 变换后数据'!$D$5:$D$160,ROW()-5-$G$3+1,0,MIN($G$3,ROW()-4),1)),--ISNUMBER(OFFSET('04 变换后数据'!$H$5:$H$160,ROW()-5-$G$3+1,0,MIN($G$3,ROW()-4),1)))) | I95: =IF(ISNUMBER(E95),IF(ABS(E95)>=0.7,"强",IF(ABS(E95)>=0.4,"中","弱")),"-")
A96: 92 | B96: ='04 变换后数据'!B96 | C96: =IF(92<$C$3,"",IF(496=0,"",IF(496<MAX(5,ROUND($C$3*0.8,0)),"样本不足",CORREL(OFFSET('04 变换后数据'!$D$5:$D$160,ROW()-5-$C$3+1,0,$C$3,1),OFFSET('04 变换后数据'!$H$5:$H$160,ROW()-5-$C$3+1,0,$C$3,1)))) | D96: =IF(92<$C$3,0,SUMPRODUCT(--(ROW('04 变换后数据'!$D$5:$D$160)<=ROW()),--ISNUMBER(OFFSET('04 变换后数据'!$D$5:$D$160,ROW()-5-$C$3+1,0,MIN($C$3,ROW()-4),1)),--ISNUMBER(OFFSET('04 变换后数据'!$H$5:$H$160,ROW()-5-$C$3+1,0,MIN($C$3,ROW()-4),1)))) | E96: =IF(92<$E$3,"",IF(696=0,"",IF(696<MAX(5,ROUND($E$3*0.8,0)),"样本不足",CORREL(OFFSET('04 变换后数据'!$D$5:$D$160,ROW()-5-$E$3+1,0,$E$3,1),OFFSET('04 变换后数据'!$H$5:$H$160,ROW()-5-$E$3+1,0,$E$3,1)))) | F96: =IF(92<$E$3,0,SUMPRODUCT(--(ROW('04 变换后数据'!$D$5:$D$160)<=ROW()),--ISNUMBER(OFFSET('04 变换后数据'!$D$5:$D$160,ROW()-5-$E$3+1,0,MIN($E$3,ROW()-4),1)),--ISNUMBER(OFFSET('04 变换后数据'!$H$5:$H$160,ROW()-5-$E$3+1,0,MIN($E$3,ROW()-4),1)))) | G96: =IF(92<$G$3,"",IF(896=0,"",IF(896<MAX(5,ROUND($G$3*0.8,0)),"样本不足",CORREL(OFFSET('04 变换后数据'!$D$5:$D$160,ROW()-5-$G$3+1,0,$G$3,1),OFFSET('04 变换后数据'!$H$5:$H$160,ROW()-5-$G$3+1,0,$G$3,1)))) | H96: =IF(92<$G$3,0,SUMPRODUCT(--(ROW('04 变换后数据'!$D$5:$D$160)<=ROW()),--ISNUMBER(OFFSET('04 变换后数据'!$D$5:$D$160,ROW()-5-$G$3+1,0,MIN($G$3,ROW()-4),1)),--ISNUMBER(OFFSET('04 变换后数据'!$H$5:$H$160,ROW()-5-$G$3+1,0,MIN($G$3,ROW()-4),1)))) | I96: =IF(ISNUMBER(E96),IF(ABS(E96)>=0.7,"强",IF(ABS(E96)>=0.4,"中","弱")),"-")
A97: 93 | B97: ='04 变换后数据'!B97 | C97: =IF(93<$C$3,"",IF(497=0,"",IF(497<MAX(5,ROUND($C$3*0.8,0)),"样本不足",CORREL(OFFSET('04 变换后数据'!$D$5:$D$160,ROW()-5-$C$3+1,0,$C$3,1),OFFSET('04 变换后数据'!$H$5:$H$160,ROW()-5-$C$3+1,0,$C$3,1)))) | D97: =IF(93<$C$3,0,SUMPRODUCT(--(ROW('04 变换后数据'!$D$5:$D$160)<=ROW()),--ISNUMBER(OFFSET('04 变换后数据'!$D$5:$D$160,ROW()-5-$C$3+1,0,MIN($C$3,ROW()-4),1)),--ISNUMBER(OFFSET('04 变换后数据'!$H$5:$H$160,ROW()-5-$C$3+1,0,MIN($C$3,ROW()-4),1)))) | E97: =IF(93<$E$3,"",IF(697=0,"",IF(697<MAX(5,ROUND($E$3*0.8,0)),"样本不足",CORREL(OFFSET('04 变换后数据'!$D$5:$D$160,ROW()-5-$E$3+1,0,$E$3,1),OFFSET('04 变换后数据'!$H$5:$H$160,ROW()-5-$E$3+1,0,$E$3,1)))) | F97: =IF(93<$E$3,0,SUMPRODUCT(--(ROW('04 变换后数据'!$D$5:$D$160)<=ROW()),--ISNUMBER(OFFSET('04 变换后数据'!$D$5:$D$160,ROW()-5-$E$3+1,0,MIN($E$3,ROW()-4),1)),--ISNUMBER(OFFSET('04 变换后数据'!$H$5:$H$160,ROW()-5-$E$3+1,0,MIN($E$3,ROW()-4),1)))) | G97: =IF(93<$G$3,"",IF(897=0,"",IF(897<MAX(5,ROUND($G$3*0.8,0)),"样本不足",CORREL(OFFSET('04 变换后数据'!$D$5:$D$160,ROW()-5-$G$3+1,0,$G$3,1),OFFSET('04 变换后数据'!$H$5:$H$160,ROW()-5-$G$3+1,0,$G$3,1)))) | H97: =IF(93<$G$3,0,SUMPRODUCT(--(ROW('04 变换后数据'!$D$5:$D$160)<=ROW()),--ISNUMBER(OFFSET('04 变换后数据'!$D$5:$D$160,ROW()-5-$G$3+1,0,MIN($G$3,ROW()-4),1)),--ISNUMBER(OFFSET('04 变换后数据'!$H$5:$H$160,ROW()-5-$G$3+1,0,MIN($G$3,ROW()-4),1)))) | I97: =IF(ISNUMBER(E97),IF(ABS(E97)>=0.7,"强",IF(ABS(E97)>=0.4,"中","弱")),"-")
A98: 94 | B98: ='04 变换后数据'!B98 | C98: =IF(94<$C$3,"",IF(498=0,"",IF(498<MAX(5,ROUND($C$3*0.8,0)),"样本不足",CORREL(OFFSET('04 变换后数据'!$D$5:$D$160,ROW()-5-$C$3+1,0,$C$3,1),OFFSET('04 变换后数据'!$H$5:$H$160,ROW()-5-$C$3+1,0,$C$3,1)))) | D98: =IF(94<$C$3,0,SUMPRODUCT(--(ROW('04 变换后数据'!$D$5:$D$160)<=ROW()),--ISNUMBER(OFFSET('04 变换后数据'!$D$5:$D$160,ROW()-5-$C$3+1,0,MIN($C$3,ROW()-4),1)),--ISNUMBER(OFFSET('04 变换后数据'!$H$5:$H$160,ROW()-5-$C$3+1,0,MIN($C$3,ROW()-4),1)))) | E98: =IF(94<$E$3,"",IF(698=0,"",IF(698<MAX(5,ROUND($E$3*0.8,0)),"样本不足",CORREL(OFFSET('04 变换后数据'!$D$5:$D$160,ROW()-5-$E$3+1,0,$E$3,1),OFFSET('04 变换后数据'!$H$5:$H$160,ROW()-5-$E$3+1,0,$E$3,1)))) | F98: =IF(94<$E$3,0,SUMPRODUCT(--(ROW('04 变换后数据'!$D$5:$D$160)<=ROW()),--ISNUMBER(OFFSET('04 变换后数据'!$D$5:$D$160,ROW()-5-$E$3+1,0,MIN($E$3,ROW()-4),1)),--ISNUMBER(OFFSET('04 变换后数据'!$H$5:$H$160,ROW()-5-$E$3+1,0,MIN($E$3,ROW()-4),1)))) | G98: =IF(94<$G$3,"",IF(898=0,"",IF(898<MAX(5,ROUND($G$3*0.8,0)),"样本不足",CORREL(OFFSET('04 变换后数据'!$D$5:$D$160,ROW()-5-$G$3+1,0,$G$3,1),OFFSET('04 变换后数据'!$H$5:$H$160,ROW()-5-$G$3+1,0,$G$3,1)))) | H98: =IF(94<$G$3,0,SUMPRODUCT(--(ROW('04 变换后数据'!$D$5:$D$160)<=ROW()),--ISNUMBER(OFFSET('04 变换后数据'!$D$5:$D$160,ROW()-5-$G$3+1,0,MIN($G$3,ROW()-4),1)),--ISNUMBER(OFFSET('04 变换后数据'!$H$5:$H$160,ROW()-5-$G$3+1,0,MIN($G$3,ROW()-4),1)))) | I98: =IF(ISNUMBER(E98),IF(ABS(E98)>=0.7,"强",IF(ABS(E98)>=0.4,"中","弱")),"-")
A99: 95 | B99: ='04 变换后数据'!B99 | C99: =IF(95<$C$3,"",IF(499=0,"",IF(499<MAX(5,ROUND($C$3*0.8,0)),"样本不足",CORREL(OFFSET('04 变换后数据'!$D$5:$D$160,ROW()-5-$C$3+1,0,$C$3,1),OFFSET('04 变换后数据'!$H$5:$H$160,ROW()-5-$C$3+1,0,$C$3,1)))) | D99: =IF(95<$C$3,0,SUMPRODUCT(--(ROW('04 变换后数据'!$D$5:$D$160)<=ROW()),--ISNUMBER(OFFSET('04 变换后数据'!$D$5:$D$160,ROW()-5-$C$3+1,0,MIN($C$3,ROW()-4),1)),--ISNUMBER(OFFSET('04 变换后数据'!$H$5:$H$160,ROW()-5-$C$3+1,0,MIN($C$3,ROW()-4),1)))) | E99: =IF(95<$E$3,"",IF(699=0,"",IF(699<MAX(5,ROUND($E$3*0.8,0)),"样本不足",CORREL(OFFSET('04 变换后数据'!$D$5:$D$160,ROW()-5-$E$3+1,0,$E$3,1),OFFSET('04 变换后数据'!$H$5:$H$160,ROW()-5-$E$3+1,0,$E$3,1)))) | F99: =IF(95<$E$3,0,SUMPRODUCT(--(ROW('04 变换后数据'!$D$5:$D$160)<=ROW()),--ISNUMBER(OFFSET('04 变换后数据'!$D$5:$D$160,ROW()-5-$E$3+1,0,MIN($E$3,ROW()-4),1)),--ISNUMBER(OFFSET('04 变换后数据'!$H$5:$H$160,ROW()-5-$E$3+1,0,MIN($E$3,ROW()-4),1)))) | G99: =IF(95<$G$3,"",IF(899=0,"",IF(899<MAX(5,ROUND($G$3*0.8,0)),"样本不足",CORREL(OFFSET('04 变换后数据'!$D$5:$D$160,ROW()-5-$G$3+1,0,$G$3,1),OFFSET('04 变换后数据'!$H$5:$H$160,ROW()-5-$G$3+1,0,$G$3,1)))) | H99: =IF(95<$G$3,0,SUMPRODUCT(--(ROW('04 变换后数据'!$D$5:$D$160)<=ROW()),--ISNUMBER(OFFSET('04 变换后数据'!$D$5:$D$160,ROW()-5-$G$3+1,0,MIN($G$3,ROW()-4),1)),--ISNUMBER(OFFSET('04 变换后数据'!$H$5:$H$160,ROW()-5-$G$3+1,0,MIN($G$3,ROW()-4),1)))) | I99: =IF(ISNUMBER(E99),IF(ABS(E99)>=0.7,"强",IF(ABS(E99)>=0.4,"中","弱")),"-")
A100: 96 | B100: ='04 变换后数据'!B100 | C100: =IF(96<$C$3,"",IF(4100=0,"",IF(4100<MAX(5,ROUND($C$3*0.8,0)),"样本不足",CORREL(OFFSET('04 变换后数据'!$D$5:$D$160,ROW()-5-$C$3+1,0,$C$3,1),OFFSET('04 变换后数据'!$H$5:$H$160,ROW()-5-$C$3+1,0,$C$3,1)))) | D100: =IF(96<$C$3,0,SUMPRODUCT(--(ROW('04 变换后数据'!$D$5:$D$160)<=ROW()),--ISNUMBER(OFFSET('04 变换后数据'!$D$5:$D$160,ROW()-5-$C$3+1,0,MIN($C$3,ROW()-4),1)),--ISNUMBER(OFFSET('04 变换后数据'!$H$5:$H$160,ROW()-5-$C$3+1,0,MIN($C$3,ROW()-4),1)))) | E100: =IF(96<$E$3,"",IF(6100=0,"",IF(6100<MAX(5,ROUND($E$3*0.8,0)),"样本不足",CORREL(OFFSET('04 变换后数据'!$D$5:$D$160,ROW()-5-$E$3+1,0,$E$3,1),OFFSET('04 变换后数据'!$H$5:$H$160,ROW()-5-$E$3+1,0,$E$3,1)))) | F100: =IF(96<$E$3,0,SUMPRODUCT(--(ROW('04 变换后数据'!$D$5:$D$160)<=ROW()),--ISNUMBER(OFFSET('04 变换后数据'!$D$5:$D$160,ROW()-5-$E$3+1,0,MIN($E$3,ROW()-4),1)),--ISNUMBER(OFFSET('04 变换后数据'!$H$5:$H$160,ROW()-5-$E$3+1,0,MIN($E$3,ROW()-4),1)))) | G100: =IF(96<$G$3,"",IF(8100=0,"",IF(8100<MAX(5,ROUND($G$3*0.8,0)),"样本不足",CORREL(OFFSET('04 变换后数据'!$D$5:$D$160,ROW()-5-$G$3+1,0,$G$3,1),OFFSET('04 变换后数据'!$H$5:$H$160,ROW()-5-$G$3+1,0,$G$3,1)))) | H100: =IF(96<$G$3,0,SUMPRODUCT(--(ROW('04 变换后数据'!$D$5:$D$160)<=ROW()),--ISNUMBER(OFFSET('04 变换后数据'!$D$5:$D$160,ROW()-5-$G$3+1,0,MIN($G$3,ROW()-4),1)),--ISNUMBER(OFFSET('04 变换后数据'!$H$5:$H$160,ROW()-5-$G$3+1,0,MIN($G$3,ROW()-4),1)))) | I100: =IF(ISNUMBER(E100),IF(ABS(E100)>=0.7,"强",IF(ABS(E100)>=0.4,"中","弱")),"-")
...

Sheet 07 分阶段结果
A1: 分阶段结果（相关强度会随市场阶段变化）
A2: 断点写在第 4 行，改日期后公式自动重算。断点应按行业逻辑设定（检修季、需求淡季、产能投放、政策窗口），不要为凑结果反复切分。
B4: 2023-10-11 | C4: 2024-09-01 | D4: 2025-09-01 | E4: 2026-09-30
B5: 阶段1断点 → | C5: 阶段2断点 → | D5: 阶段3断点 →
A7: 阶段 | B7: 起始 | C7: 结束 | D7: N | E7: Pearson r | F7: Spearman ρ | G7: p 值 | H7: 强度 | I7: 显著性
A8: 阶段1 | B8: =TEXT(B4,"yyyy-mm-dd") | C8: =TEXT(C4,"yyyy-mm-dd") | D8: =SUMPRODUCT(('04 变换后数据'!$B$5:$B$160>=$B8)*('04 变换后数据'!$B$5:$B$160<=$C8)*ISNUMBER('04 变换后数据'!$D$5:$D$160)*ISNUMBER('04 变换后数据'!$H$5:$H$160)) | E8: =IFERROR(CORREL(IF(('04 变换后数据'!$B$5:$B$160>=$B8)*('04 变换后数据'!$B$5:$B$160<=$C8),'04 变换后数据'!$D$5:$D$160),IF(('04 变换后数据'!$B$5:$B$160>=$B8)*('04 变换后数据'!$B$5:$B$160<=$C8),'04 变换后数据'!$H$5:$H$160)),"") | F8: =IFERROR(CORREL(IF(('04 变换后数据'!$B$5:$B$160>=$B8)*('04 变换后数据'!$B$5:$B$160<=$C8),'04 变换后数据'!$D$5:$D$160),IF(('04 变换后数据'!$B$5:$B$160>=$B8)*('04 变换后数据'!$B$5:$B$160<=$C8),'04 变换后数据'!$H$5:$H$160)),"") | G8: =IFERROR(_XLFN.T.DIST.2T(ABS(E8*SQRT((D8-2)/(1-E8^2))),D8-2),"") | H8: =IF(E8="","-",IF(ABS(E8)>=0.7,"强",IF(ABS(E8)>=0.4,"中","弱"))) | I8: =IF(G8="","",IF(G8<0.05,"显著","不显著"))
A9: 阶段2 | B9: =TEXT(C4,"yyyy-mm-dd") | C9: =TEXT(D4,"yyyy-mm-dd") | D9: =SUMPRODUCT(('04 变换后数据'!$B$5:$B$160>=$B9)*('04 变换后数据'!$B$5:$B$160<=$C9)*ISNUMBER('04 变换后数据'!$D$5:$D$160)*ISNUMBER('04 变换后数据'!$H$5:$H$160)) | E9: =IFERROR(CORREL(IF(('04 变换后数据'!$B$5:$B$160>=$B9)*('04 变换后数据'!$B$5:$B$160<=$C9),'04 变换后数据'!$D$5:$D$160),IF(('04 变换后数据'!$B$5:$B$160>=$B9)*('04 变换后数据'!$B$5:$B$160<=$C9),'04 变换后数据'!$H$5:$H$160)),"") | F9: =IFERROR(CORREL(IF(('04 变换后数据'!$B$5:$B$160>=$B9)*('04 变换后数据'!$B$5:$B$160<=$C9),'04 变换后数据'!$D$5:$D$160),IF(('04 变换后数据'!$B$5:$B$160>=$B9)*('04 变换后数据'!$B$5:$B$160<=$C9),'04 变换后数据'!$H$5:$H$160)),"") | G9: =IFERROR(_XLFN.T.DIST.2T(ABS(E9*SQRT((D9-2)/(1-E9^2))),D9-2),"") | H9: =IF(E9="","-",IF(ABS(E9)>=0.7,"强",IF(ABS(E9)>=0.4,"中","弱"))) | I9: =IF(G9="","",IF(G9<0.05,"显著","不显著"))
A10: 阶段3 | B10: =TEXT(D4,"yyyy-mm-dd") | C10: =TEXT(E4,"yyyy-mm-dd") | D10: =SUMPRODUCT(('04 变换后数据'!$B$5:$B$160>=$B10)*('04 变换后数据'!$B$5:$B$160<=$C10)*ISNUMBER('04 变换后数据'!$D$5:$D$160)*ISNUMBER('04 变换后数据'!$H$5:$H$160)) | E10: =IFERROR(CORREL(IF(('04 变换后数据'!$B$5:$B$160>=$B10)*('04 变换后数据'!$B$5:$B$160<=$C10),'04 变换后数据'!$D$5:$D$160),IF(('04 变换后数据'!$B$5:$B$160>=$B10)*('04 变换后数据'!$B$5:$B$160<=$C10),'04 变换后数据'!$H$5:$H$160)),"") | F10: =IFERROR(CORREL(IF(('04 变换后数据'!$B$5:$B$160>=$B10)*('04 变换后数据'!$B$5:$B$160<=$C10),'04 变换后数据'!$D$5:$D$160),IF(('04 变换后数据'!$B$5:$B$160>=$B10)*('04 变换后数据'!$B$5:$B$160<=$C10),'04 变换后数据'!$H$5:$H$160)),"") | G10: =IFERROR(_XLFN.T.DIST.2T(ABS(E10*SQRT((D10-2)/(1-E10^2))),D10-2),"") | H10: =IF(E10="","-",IF(ABS(E10)>=0.7,"强",IF(ABS(E10)>=0.4,"中","弱"))) | I10: =IF(G10="","",IF(G10<0.05,"显著","不显著"))
B12: E/F 列为 IF 掩码数组公式：Excel 365 / WPS 直接回车即可；旧版 Excel 需 Ctrl+Shift+Enter。Spearman ρ 在此按 Pearson 掩码近似占位，精确秩相关由 scripts/analyze.py 输出（见 10 滞后相关旁的脚本结果）。

Sheet 08 形态组合矩阵
A1: 形态组合矩阵（3×3）
A2: 同一对指标换形态后 r 可以差很多。写结论必须写明“哪种形态对哪种形态”，否则无法复核。
B4: 库存 ＼ 价格 | C4: 价格-水平 | D4: 价格-差分 | E4: 价格-环比%
B5: 库存-水平 | C5: =IFERROR(CORREL('04 变换后数据'!$C$5:$C$160,'04 变换后数据'!$F$5:$F$160),"") | D5: =IFERROR(CORREL('04 变换后数据'!$C$5:$C$160,'04 变换后数据'!$G$5:$G$160),"") | E5: =IFERROR(CORREL('04 变换后数据'!$C$5:$C$160,'04 变换后数据'!$H$5:$H$160),"")
B6: 库存-差分 | C6: =IFERROR(CORREL('04 变换后数据'!$D$5:$D$160,'04 变换后数据'!$F$5:$F$160),"") | D6: =IFERROR(CORREL('04 变换后数据'!$D$5:$D$160,'04 变换后数据'!$G$5:$G$160),"") | E6: =IFERROR(CORREL('04 变换后数据'!$D$5:$D$160,'04 变换后数据'!$H$5:$H$160),"")
B7: 库存-环比% | C7: =IFERROR(CORREL('04 变换后数据'!$E$5:$E$160,'04 变换后数据'!$F$5:$F$160),"") | D7: =IFERROR(CORREL('04 变换后数据'!$E$5:$E$160,'04 变换后数据'!$G$5:$G$160),"") | E7: =IFERROR(CORREL('04 变换后数据'!$E$5:$E$160,'04 变换后数据'!$H$5:$H$160),"")
B9: 解读 | C9: 主口径建议“库存差分 × 价格环比%”（第 3 行第 3 列）：两端都是变化量、各自用合适单位，且不会因共同趋势虚高。“水平 × 水平”只能作背景描述，必须同时给出差分口径并说明差异。

Sheet 09 稳健性与伪相关诊断
A1: 稳健性与伪相关诊断
A2: 逐项检验“这个相关是不是只来自趋势 / 自相关 / 共同外部因素”。任何一项让 r 大幅衰减，都要在结论里如实写出来。
A4: 诊断项 | B4: 数值 | C4: 计算口径 | D4: 判读标准 | E4: 结论与处理
A5: 基准：库存差分 × 价格环比% | B5: ='05 总体相关'!C7 | C5: CORREL(库存差分, 价格环比%) | D5: 其余诊断的参照基准 | E5: 所有稳健性结论相对此项比较
A6: 去趋势后 r | B6: ='09b 辅助计算(残差)'!$D$162 | C6: 对时间回归取残差后的 CORREL | D6: 显著低于基准 → 有共同趋势成分 | E6: 结论以变化口径为准
A7: 水平 × 水平（对照） | B7: ='05 总体相关'!C5 | C7: CORREL(库存水平, 价格水平) | D7: 通常明显高于差分口径 | E7: 只作背景，不作结论依据
A8: 库存一阶自相关 ρ₁ | B8: ='04 变换后数据'!C6 | C8: CORREL(水平_t, 水平_t-1) | D8: >0.7 表示强记忆性 | E8: 用有效样本量修正 p
A9: 价格一阶自相关 ρ₁ | B9: ='04 变换后数据'!F6 | C9: 同上 | D9: 同上 | E9: 同上
A10: 剔极值后 r | B10: 见 analyze.py 输出 | C10: 剔除上下 5% 后重算 | D10: 与基准接近 → 结论不由极值撑起 | E10: 如变化大，需点名极值日期
A11: 分段一致性 | B11: 见 analyze.py 输出 | C11: 前 1/3 与后 1/3 分别计算 | D11: 方向一致才谈“稳定” | E11: 方向相反必须写“阶段性失效”
A12: 控制煤价后的偏相关 | B12: 见 analyze.py 输出 | C12: 对煤价回归取残差再相关 | D12: 明显低于基准 → 成本解释一部分 | E12: 写明“控制成本后仍剩多少”
A13: 有效样本量 N_eff | B13: 见 analyze.py 输出 | C13: n(1-ρxρy)/(1+ρxρy) | D13: 比名义 N 小很多时，名义 p 过于乐观 | E13: 报告修正 p（见 analyze.py）

Sheet 09b 辅助计算(残差)
A1: 辅助计算：回归残差（去趋势）
A2: 用 SLOPE/INTERCEPT 逐行算预测值与残差；残差之间的相关即“去趋势后相关”。改数据后自动重算。
A4: 序号 | B4: 日期 | C4: t | D4: 库存-水平 | E4: 价格-水平 | F4: 库存趋势拟合 | G4: 库存残差 | H4: 价格趋势拟合 | I4: 价格残差
A5: 1 | B5: ='04 变换后数据'!B5 | C5: 1 | D5: ='04 变换后数据'!C5 | E5: ='04 变换后数据'!F5 | F5: =IF(ISNUMBER(D5),SLOPE('04 变换后数据'!$C$5:$C$160,'09b 辅助计算(残差)'!$C$5:$C$160)*C5+INTERCEPT('04 变换后数据'!$C$5:$C$160,'09b 辅助计算(残差)'!$C$5:$C$160),"") | G5: =IF(ISNUMBER(D5),D5-F5,"") | H5: =IF(ISNUMBER(E5),SLOPE('04 变换后数据'!$F$5:$F$160,'09b 辅助计算(残差)'!$C$5:$C$160)*C5+INTERCEPT('04 变换后数据'!$F$5:$F$160,'09b 辅助计算(残差)'!$C$5:$C$160),"") | I5: =IF(ISNUMBER(E5),E5-H5,"")
A6: 2 | B6: ='04 变换后数据'!B6 | C6: 2 | D6: ='04 变换后数据'!C6 | E6: ='04 变换后数据'!F6 | F6: =IF(ISNUMBER(D6),SLOPE('04 变换后数据'!$C$5:$C$160,'09b 辅助计算(残差)'!$C$5:$C$160)*C6+INTERCEPT('04 变换后数据'!$C$5:$C$160,'09b 辅助计算(残差)'!$C$5:$C$160),"") | G6: =IF(ISNUMBER(D6),D6-F6,"") | H6: =IF(ISNUMBER(E6),SLOPE('04 变换后数据'!$F$5:$F$160,'09b 辅助计算(残差)'!$C$5:$C$160)*C6+INTERCEPT('04 变换后数据'!$F$5:$F$160,'09b 辅助计算(残差)'!$C$5:$C$160),"") | I6: =IF(ISNUMBER(E6),E6-H6,"")
A7: 3 | B7: ='04 变换后数据'!B7 | C7: 3 | D7: ='04 变换后数据'!C7 | E7: ='04 变换后数据'!F7 | F7: =IF(ISNUMBER(D7),SLOPE('04 变换后数据'!$C$5:$C$160,'09b 辅助计算(残差)'!$C$5:$C$160)*C7+INTERCEPT('04 变换后数据'!$C$5:$C$160,'09b 辅助计算(残差)'!$C$5:$C$160),"") | G7: =IF(ISNUMBER(D7),D7-F7,"") | H7: =IF(ISNUMBER(E7),SLOPE('04 变换后数据'!$F$5:$F$160,'09b 辅助计算(残差)'!$C$5:$C$160)*C7+INTERCEPT('04 变换后数据'!$F$5:$F$160,'09b 辅助计算(残差)'!$C$5:$C$160),"") | I7: =IF(ISNUMBER(E7),E7-H7,"")
A8: 4 | B8: ='04 变换后数据'!B8 | C8: 4 | D8: ='04 变换后数据'!C8 | E8: ='04 变换后数据'!F8 | F8: =IF(ISNUMBER(D8),SLOPE('04 变换后数据'!$C$5:$C$160,'09b 辅助计算(残差)'!$C$5:$C$160)*C8+INTERCEPT('04 变换后数据'!$C$5:$C$160,'09b 辅助计算(残差)'!$C$5:$C$160),"") | G8: =IF(ISNUMBER(D8),D8-F8,"") | H8: =IF(ISNUMBER(E8),SLOPE('04 变换后数据'!$F$5:$F$160,'09b 辅助计算(残差)'!$C$5:$C$160)*C8+INTERCEPT('04 变换后数据'!$F$5:$F$160,'09b 辅助计算(残差)'!$C$5:$C$160),"") | I8: =IF(ISNUMBER(E8),E8-H8,"")
A9: 5 | B9: ='04 变换后数据'!B9 | C9: 5 | D9: ='04 变换后数据'!C9 | E9: ='04 变换后数据'!F9 | F9: =IF(ISNUMBER(D9),SLOPE('04 变换后数据'!$C$5:$C$160,'09b 辅助计算(残差)'!$C$5:$C$160)*C9+INTERCEPT('04 变换后数据'!$C$5:$C$160,'09b 辅助计算(残差)'!$C$5:$C$160),"") | G9: =IF(ISNUMBER(D9),D9-F9,"") | H9: =IF(ISNUMBER(E9),SLOPE('04 变换后数据'!$F$5:$F$160,'09b 辅助计算(残差)'!$C$5:$C$160)*C9+INTERCEPT('04 变换后数据'!$F$5:$F$160,'09b 辅助计算(残差)'!$C$5:$C$160),"") | I9: =IF(ISNUMBER(E9),E9-H9,"")
A10: 6 | B10: ='04 变换后数据'!B10 | C10: 6 | D10: ='04 变换后数据'!C10 | E10: ='04 变换后数据'!F10 | F10: =IF(ISNUMBER(D10),SLOPE('04 变换后数据'!$C$5:$C$160,'09b 辅助计算(残差)'!$C$5:$C$160)*C10+INTERCEPT('04 变换后数据'!$C$5:$C$160,'09b 辅助计算(残差)'!$C$5:$C$160),"") | G10: =IF(ISNUMBER(D10),D10-F10,"") | H10: =IF(ISNUMBER(E10),SLOPE('04 变换后数据'!$F$5:$F$160,'09b 辅助计算(残差)'!$C$5:$C$160)*C10+INTERCEPT('04 变换后数据'!$F$5:$F$160,'09b 辅助计算(残差)'!$C$5:$C$160),"") | I10: =IF(ISNUMBER(E10),E10-H10,"")
A11: 7 | B11: ='04 变换后数据'!B11 | C11: 7 | D11: ='04 变换后数据'!C11 | E11: ='04 变换后数据'!F11 | F11: =IF(ISNUMBER(D11),SLOPE('04 变换后数据'!$C$5:$C$160,'09b 辅助计算(残差)'!$C$5:$C$160)*C11+INTERCEPT('04 变换后数据'!$C$5:$C$160,'09b 辅助计算(残差)'!$C$5:$C$160),"") | G11: =IF(ISNUMBER(D11),D11-F11,"") | H11: =IF(ISNUMBER(E11),SLOPE('04 变换后数据'!$F$5:$F$160,'09b 辅助计算(残差)'!$C$5:$C$160)*C11+INTERCEPT('04 变换后数据'!$F$5:$F$160,'09b 辅助计算(残差)'!$C$5:$C$160),"") | I11: =IF(ISNUMBER(E11),E11-H11,"")
A12: 8 | B12: ='04 变换后数据'!B12 | C12: 8 | D12: ='04 变换后数据'!C12 | E12: ='04 变换后数据'!F12 | F12: =IF(ISNUMBER(D12),SLOPE('04 变换后数据'!$C$5:$C$160,'09b 辅助计算(残差)'!$C$5:$C$160)*C12+INTERCEPT('04 变换后数据'!$C$5:$C$160,'09b 辅助计算(残差)'!$C$5:$C$160),"") | G12: =IF(ISNUMBER(D12),D12-F12,"") | H12: =IF(ISNUMBER(E12),SLOPE('04 变换后数据'!$F$5:$F$160,'09b 辅助计算(残差)'!$C$5:$C$160)*C12+INTERCEPT('04 变换后数据'!$F$5:$F$160,'09b 辅助计算(残差)'!$C$5:$C$160),"") | I12: =IF(ISNUMBER(E12),E12-H12,"")
A13: 9 | B13: ='04 变换后数据'!B13 | C13: 9 | D13: ='04 变换后数据'!C13 | E13: ='04 变换后数据'!F13 | F13: =IF(ISNUMBER(D13),SLOPE('04 变换后数据'!$C$5:$C$160,'09b 辅助计算(残差)'!$C$5:$C$160)*C13+INTERCEPT('04 变换后数据'!$C$5:$C$160,'09b 辅助计算(残差)'!$C$5:$C$160),"") | G13: =IF(ISNUMBER(D13),D13-F13,"") | H13: =IF(ISNUMBER(E13),SLOPE('04 变换后数据'!$F$5:$F$160,'09b 辅助计算(残差)'!$C$5:$C$160)*C13+INTERCEPT('04 变换后数据'!$F$5:$F$160,'09b 辅助计算(残差)'!$C$5:$C$160),"") | I13: =IF(ISNUMBER(E13),E13-H13,"")
A14: 10 | B14: ='04 变换后数据'!B14 | C14: 10 | D14: ='04 变换后数据'!C14 | E14: ='04 变换后数据'!F14 | F14: =IF(ISNUMBER(D14),SLOPE('04 变换后数据'!$C$5:$C$160,'09b 辅助计算(残差)'!$C$5:$C$160)*C14+INTERCEPT('04 变换后数据'!$C$5:$C$160,'09b 辅助计算(残差)'!$C$5:$C$160),"") | G14: =IF(ISNUMBER(D14),D14-F14,"") | H14: =IF(ISNUMBER(E14),SLOPE('04 变换后数据'!$F$5:$F$160,'09b 辅助计算(残差)'!$C$5:$C$160)*C14+INTERCEPT('04 变换后数据'!$F$5:$F$160,'09b 辅助计算(残差)'!$C$5:$C$160),"") | I14: =IF(ISNUMBER(E14),E14-H14,"")
A15: 11 | B15: ='04 变换后数据'!B15 | C15: 11 | D15: ='04 变换后数据'!C15 | E15: ='04 变换后数据'!F15 | F15: =IF(ISNUMBER(D15),SLOPE('04 变换后数据'!$C$5:$C$160,'09b 辅助计算(残差)'!$C$5:$C$160)*C15+INTERCEPT('04 变换后数据'!$C$5:$C$160,'09b 辅助计算(残差)'!$C$5:$C$160),"") | G15: =IF(ISNUMBER(D15),D15-F15,"") | H15: =IF(ISNUMBER(E15),SLOPE('04 变换后数据'!$F$5:$F$160,'09b 辅助计算(残差)'!$C$5:$C$160)*C15+INTERCEPT('04 变换后数据'!$F$5:$F$160,'09b 辅助计算(残差)'!$C$5:$C$160),"") | I15: =IF(ISNUMBER(E15),E15-H15,"")
A16: 12 | B16: ='04 变换后数据'!B16 | C16: 12 | D16: ='04 变换后数据'!C16 | E16: ='04 变换后数据'!F16 | F16: =IF(ISNUMBER(D16),SLOPE('04 变换后数据'!$C$5:$C$160,'09b 辅助计算(残差)'!$C$5:$C$160)*C16+INTERCEPT('04 变换后数据'!$C$5:$C$160,'09b 辅助计算(残差)'!$C$5:$C$160),"") | G16: =IF(ISNUMBER(D16),D16-F16,"") | H16: =IF(ISNUMBER(E16),SLOPE('04 变换后数据'!$F$5:$F$160,'09b 辅助计算(残差)'!$C$5:$C$160)*C16+INTERCEPT('04 变换后数据'!$F$5:$F$160,'09b 辅助计算(残差)'!$C$5:$C$160),"") | I16: =IF(ISNUMBER(E16),E16-H16,"")
... A160: 156 | B160: ='04 变换后数据'!B160 | C160: 156 | D160: ='04 变换后数据'!C160 | E160: ='04 变换后数据'!F160 | F160: =IF(ISNUMBER(D160),SLOPE('04 变换后数据'!$C$5:$C$160,'09b 辅助计算(残差)'!$C$5:$C$160)*C160+INTERCEPT('04 变换后数据'!$C$5:$C$160,'09b 辅助计算(残差)'!$C$5:$C$160),"") | G160: =IF(ISNUMBER(D160),D160-F160,"") | H160: =IF(ISNUMBER(E160),SLOPE('04 变换后数据'!$F$5:$F$160,'09b 辅助计算(残差)'!$C$5:$C$160)*C160+INTERCEPT('04 变换后数据'!$F$5:$F$160,'09b 辅助计算(残差)'!$C$5:$C$160),"") | I160: =IF(ISNUMBER(E160),E160-H160,"")
B162: 去趋势后相关 r = | D162: =IFERROR(CORREL(G5:G160,I5:I160),"")
B163: R²（库存 vs 时间）= | D163: =IFERROR(RSQ('04 变换后数据'!$C$5:$C$160,'09b 辅助计算(残差)'!$C$5:$C$160),"")
B164: R²（价格 vs 时间）= | D164: =IFERROR(RSQ('04 变换后数据'!$F$5:$F$160,'09b 辅助计算(残差)'!$C$5:$C$160),"")
B165: 库存时间趋势斜率 = | D165: =IFERROR(SLOPE('04 变换后数据'!$C$5:$C$160,'09b 辅助计算(残差)'!$C$5:$C$160),"")
B166: 价格时间趋势斜率 = | D166: =IFERROR(SLOPE('04 变换后数据'!$F$5:$F$160,'09b 辅助计算(残差)'!$C$5:$C$160),"")

Sheet 10 滞后相关
A1: 滞后相关（lag = -4 ~ +4 期，主口径）
A2: lag>0：库存领先价格（库存[t] 对 价格[t+lag]）。峰值在 lag>0 只能说明先后顺序与数据吻合，不能证明因果。数值由 analyze.py 预计算写入。
A4: lag（期） | B4: 含义 | C4: Pearson r | D4: N
A5: -4 | B5: 价格领先库存 | C5: 0.1253 | D5: 151
A6: -3 | B6: 价格领先库存 | C6: -0.019 | D6: 152
A7: -2 | B7: 价格领先库存 | C7: -0.0538 | D7: 153
A8: -1 | B8: 价格领先库存 | C8: -0.2545 | D8: 154
A9: 0 | B9: 同期 | C9: -0.6011 | D9: 155
A10: 1 | B10: 库存领先价格 | C10: -0.1918 | D10: 154
A11: 2 | B11: 库存领先价格 | C11: 0.0095 | D11: 153
A12: 3 | B12: 库存领先价格 | C12: 0.008 | D12: 152
A13: 4 | B13: 库存领先价格 | C13: 0.0262 | D13: 151
B15: 替换数据后请重跑：python scripts/analyze.py ... 以更新本表。

Sheet 11 事件与口径提示
A1: 行业事件与口径提示（用于解释“相关性为何变化”）
A2: 只记录可公开核对的事件与口径风险；不写因果断言、不写交易建议。事件与价格/库存的关系需单独验证。
A4: 起始 | B4: 结束 | C4: 类型 | D4: 事件 | E4: 说明
A5: 2024-01-01 | B5: 2024-02-29 | C5: 季节性 | D5: 春节前后累库窗口 | E5: 国产与进口到港集中在节前，下游停工，港口库存通常季节性抬升；此阶段库存与价格的相关性往往被季节性主导。
A6: 2024-03-15 | B6: 2024-05-31 | C6: 供给 | D6: 春季装置检修与进口到港节奏 | E6: 内地装置春季检修、进口船期后移，港口去库与到港断档并存，价格对库存的敏感度上升。
A7: 2024-06-01 | B7: 2024-08-31 | C7: 需求 | D7: 传统需求淡季（甲醛/板材、MTO 利润承压） | E7: 淡季下游提货走弱，库存变动更多由到港驱动而非需求驱动，需分开看“到港冲击”和“需求变化”。
A8: 2024-09-01 | B8: 2024-10-31 | C8: 成本 | D8: 冬季前能源成本与运费抬升预期 | E8: 煤价/运费预期上行时，成本项对价格的解释力上升，会稀释库存与现货价的相关强度。
A9: 2024-11-01 | B9: 2025-03-31 | C9: 季节性 | D9: 冬季天然气限气与进口节奏切换 | E9: 气头装置降负荷、进口长约执行节奏变化，库存与价格的关系容易出现阶段性失效。
A10: 2025-04-01 | B10: 2025-08-31 | C10: 供给 | D10: 新增产能投放与进口到港回升 | E10: 供给端增量使库存中枢抬升，价格对库存水平的弹性可能改变，需要按阶段重算相关系数。
A11: 2025-09-01 | B11: 2026-01-31 | C11: 需求 | D11: 下游利润压缩、需求转弱阶段 | E11: 需求走弱时，价格由“成本+预期”主导的成分上升，库存与价格的相关性常出现弱化/脱钩。
A12: 2026-02-01 | B12: 2026-03-31 | C12: 季节性 | D12: 春节后复工节奏与船期错配 | E12: 复工慢于往年时，库存堆积但价格不跌，二者短期脱钩。
A13: 2026-04-01 | B13: 2026-09-30 | C13: 统计口径 | D13: 港口样本口径与统计周期提示 | E13: 港口样本库存为企业/第三方机构抽样口径，调查日、发布时点（通常周三下午）与价格报价时点（当日午评）不一致时，需按同一时点对齐。

Sheet 12 公式说明
A1: 公式说明（统计口径与 Excel 实现）
A2: 每条都能在工作簿内找到对应单元格复核；Excel 无法原生实现的量注明由哪个脚本输出。
A4: 统计量 | B4: 定义/公式 | C4: Excel 写法 | D4: 注意事项
A5: Pearson r | B5: r = Σ(x-x̄)(y-ȳ) / √(Σ(x-x̄)²·Σ(y-ȳ)²) | C5: CORREL(区域X, 区域Y) | D5: 只度量线性关系；对离群点敏感
A6: Spearman ρ | B6: 两列取平均秩后求 Pearson | C6: CORREL(RANK.AVG 秩列) 或 matrix 脚本输出 | D6: 抗离群，可捕捉单调非线性
A7: R² | B7: r²，解释的方差比例 | C7: RSQ(y, x) 或 r² | D7: 不是因果强度
A8: t 统计量 | B8: t = r·√((N-2)/(1-r²)) | C8: r*SQRT((N-2)/(1-r^2)) | D8: N 必须是有效配对数
A9: p 值 | B9: 双侧，自由度 N-2 | C9: T.DIST.2T(ABS(t), N-2) | D9: p 小 ≠ 相关强
A10: 95% 置信区间 | B10: Fisher-z：z=atanh(r)，SE=1/√(N-3)，tanh 回推 | C10: TANH(ATANH(r)±1.96/SQRT(N-3)) | D10: N 小时区间会极宽
A11: HAC 标准误 | B11: Newey-West 长期方差 | C11: scripts/analyze.py 输出 | D11: Excel 无原生实现
A12: 有效样本量 N_eff | B12: n(1-ρxρy)/(1+ρxρy) | C12: scripts/analyze.py 输出 | D12: 修正自相关造成的显著性夸大
A13: 去趋势相关 | B13: 对时间回归取残差后求 r | C13: '09b 辅助计算(残差)'!D$行号 | D13: 检验共同趋势造成的伪相关
A14: 偏相关 | B14: 对控制变量回归取残差后求 r | C14: CORREL(残差X, 残差Y) | D14: 控制变量需与两者都相关才有意义
A15: 滚动相关 | B15: 窗口内 CORREL，末端对齐日期 | C15: CORREL(OFFSET(...)) | D15: 有效配对不足时留空
A16: 一阶差分/环比 | B16: Δx = x_t − x_{t−1}；(x_t−x_{t−1})/|x_{t−1}| | C16: '04 变换后数据' | D16: 首期必为空
