Workbook

Sheet 01 基础参数
A1: 出口报价工作簿 · 01 基础参数
A2: 引擎 v1.0.0 · 生成于 2026-10-19 · 本表是唯一录入区之一（与 03 表同源录入）
A4: A. 贸易主体与货物
A5: 参数 | B5: 值 | C5: 单位 | D5: 说明
A6: 产品（中文） | B6: 重质纯碱（碳酸钠） | D6: 出口品名，与报关单/装箱单一致
A7: 产品（英文） | B7: Sodium Carbonate Heavy Ash (Soda Ash Dense) | D7: 报价单与提单英文品名
A8: 规格 | B8: Na2CO3 ≥ 99.2%，堆积密度 ~1.0 g/cm³，工业级，25kg 覆膜编织袋 | D8: 客户验收指标原话；不自行换算
A9: HS 编码 | B9: 2836200000 | D9: 中国海关商品编码；决定退税率与监管条件
A10: 工厂所在地 | B10: 山东·青岛周边工厂 | D10: 内陆段起点
A11: 起运港 | B11: 青岛港 Qingdao (CNQDG) | D11: FOB 交货点 / CFR·CIF 装运港
A12: 目的港 | B12: 雅加达港 Jakarta (IDJKT) | D12: CFR·CIF 运费计至该港
A14: B. 数量与计量单位
A15: 出口数量 | B15: 500 | C15: 吨 (MT) | D15: 报价与成本的统一计价单位；如合同按吨/袋/托盘，请先折算成吨
A16: 进口国品名/编码（可选） | D16: 目的国 HS 可能不同（前 6 位衔接）；DDP 时用于查进口税率
A18: C. 汇率（由用户提供，系统不取实时牌价）
A19: 币种 | B19: 汇率 CNY/1外币 | C19: 用途
A20: USD | B20: 7.1 | C20: 海运费计价 / 报价展示币种
A21: EUR | B21: 7.72 | C21: 备用
A22: IDR | B22: 0.000437 | C22: 备用
A23: CNY | B23: 1 | C23: 基准币种（人民币）
A24: 报价币种 | B24: USD | C24: USD / EUR / IDR / CNY
A25: 报价汇率 | B25: =IFERROR(VLOOKUP('01 基础参数'!$B$24,'01 基础参数'!$A$20:$B$23,2,FALSE),"") | C25: '= 按报价币种自动取上述汇率
A27: D. 毛利口径（毛利率与成本加成率必须区分）
A28: 毛利口径 | B28: 毛利率（按售价） | C28: 毛利率 = 毛利÷售价；成本加成率 = 毛利÷成本。8% 毛利率 ≈ 8.70% 加成率，不可混用。
A29: 毛利数值 | B29: 0.08 | C29: 毛利率/加成率填百分比；「直接定价」时本格忽略
A30: 直接定价（¥/吨） | C30: 仅当口径=「直接定价」时生效
A31: 毛利基准术语 | B31: FOB | C31: 「目标毛利」是针对哪一个术语的价格而言——不写清，FOB 与 CIF 的毛利会被混算
A33: E. 出口退税（单列，默认不抵减报价成本）
A34: 退税率 | B34: 13 | C34: 须按商品代码核对退税率文库；系统不默认 13%
A35: 增值税率 | B35: 0.13 | C35: 出口货物适用税率（一般 13%）
A36: 出厂成本是否含税 | B36: 否 | C36: 影响退税计税依据：含税价需先除 (1+税率) 还原
A38: ⚠ 使用约定 1) 本工作簿不提供市场价、参考运价、建议毛利或税费默认值；所有费率须由用户或货代/保险公司提供。 2) 黄色单元格 = 待填写；紫色 = 模拟演示值（SIMULATED，非实时运价）；浅蓝 = 公式自动计算，请勿手改。 3) 缺失项留空即可，公式会显示「待查询」，不会显示 0 或 #VALUE!。

Sheet 02 术语与口径
A1: Incoterms® 2020 · 费用与风险对照
A2: 依据 ICC IncoTerms® 2020；分段口径与 03/05 表完全对应，避免重复计费
A4: 术语 | B4: 名称 | C4: 卖方承担成本段 | D4: 风险转移点 | E4: 适用运输方式 | F4: 出口清关 | G4: 海运费 | H4: 保险费
A5: EXW | B5: 工厂交货 | C5: 无（仅 S1 出厂价） | D5: 货物在卖方场所备妥时 | E5: 任何 | F5: 买方 | G5: 买方 | H5: 买方
A6: FCA | B6: 货交承运人 | C6: S1 S2 S3 | D6: 货交买方指定承运人时 | E6: 任何 | F6: 卖方 | G6: 买方 | H6: 买方
A7: FAS | B7: 船边交货 | C7: S1 S2 S3 | D7: 货物置于船边时 | E7: 海运/内河 | F7: 卖方 | G7: 买方 | H7: 买方
A8: FOB | B8: 装运港船上交货 | C8: S1 S2 S3 S4 | D8: 装运港装上船时 | E8: 海运/内河 | F8: 卖方 | G8: 买方 | H8: 买方
A9: CFR | B9: 成本加运费 | C9: S1 S2 S3 S4 S5 | D9: 装运港装上船时（≠目的地） | E9: 海运/内河 | F9: 卖方 | G9: 卖方 | H9: 买方
A10: CIF | B10: 成本保险加运费 | C10: S1 S2 S3 S4 S5 S6 | D10: 装运港装上船时（≠目的地） | E10: 海运/内河 | F10: 卖方 | G10: 卖方 | H10: 卖方(≥110%, ICC C)
A11: CPT | B11: 运费付至 | C11: S1 S2 S3 S4 S5 | D11: 货交第一承运人时 | E11: 任何 | F11: 卖方 | G11: 卖方 | H11: 买方
A12: CIP | B12: 运费保险付至 | C12: S1 S2 S3 S4 S5 S6 | D12: 货交第一承运人时 | E12: 任何 | F12: 卖方 | G12: 卖方 | H12: 卖方(≥110%, ICC A)
A13: DAP | B13: 目的地交货 | C13: …+S9 目的港费用 | D13: 目的地运输工具上待卸时 | E13: 任何 | F13: 卖方 | G13: 卖方 | H13: 卖方
A14: DPU | B14: 目的地卸货后交货 | C14: …+S9（含卸货） | D14: 目的地卸货完成后 | E14: 任何 | F14: 卖方 | G14: 卖方 | H14: 卖方
A15: DDP | B15: 完税后交货 | C15: …+S9+进口关税 | D15: 目的地已清关、待卸时 | E15: 任何 | F15: 卖方 | G15: 卖方 | H15: 卖方
A17: 三条最常被搞错的规则 ① CIF/CFR 的风险转移 = 装运港货物装上船，不是到达目的港；运费/保险是「费用」，不是「风险」。 ② CIF 保险费按 CIF 价 × 110% 计，默认 ICC(C)；若客户要求 ICC(A) 或更高保额，需另算保费并改条款。 ③ FOB/CIF/CFR 只能用于海运或内河运输；集装箱出口到内陆点应改用 FCA/CPT/CIP/DAP。

Sheet 03 费用明细
A1: 03 费用明细（唯一录入区）
A2: 每条费用行只归入一个成本段 → 术语价 = 对应段之和，杜绝重复计费
A4: 成本段 | B4: 代码 | C4: 成本项 | D4: 录入口径 | E4: 数值 | F4: 单位 | G4: 状态 | H4: 依据/来源 | I4: 承担方
A5: S1 | B5: EXW | C5: 出厂价（不含包装） | D5: ¥/吨 | E5: 1450 | F5: ¥/t | G5: =IF(E5="","待查询",IF(E5=0,"0","已填")) | H5: 不含包装与出口环节费用 | I5: 卖方
A6: S2 | B6: PKG | C6: 包装成本 | D6: ¥/吨 | E6: 60 | F6: ¥/t | G6: =IF(E6="","待查询",IF(E6=0,"0","已填")) | H6: 袋装/吨袋/托盘折吨价 | I6: 卖方
A7: S3 | B7: INLAND | C7: 内陆运输（工厂→起运港） | D7: ¥/吨 | E7: 110 | F7: ¥/t | G7: =IF(E7="","待查询",IF(E7=0,"0","已填")) | H7: 货代报价 | I7: 卖方
A8: S4 | B8: PORT | C8: 港口及报关费用 | D8: ¥/吨 | E8: 95 | F8: ¥/t | G8: =IF(E8="","待查询",IF(E8=0,"0","已填")) | H8: THC/报关/单证/码头作业 | I8: 卖方
A9: S5 | B9: FRT-USD | C9: 海运费（柜价） | D9: USD/柜 | E9: 1250 | F9: USD/柜 | G9: =IF(E9="","待查询","已填") | H9: 货代报价（若按吨报价，直接填下一行） | I9: 卖方
A10: S5 | B10: LOAD | C10: 装柜吨数 | D10: 吨/柜 | E10: 25 | F10: t/柜 | G10: =IF(E10="","待查询","已填") | H10: 必须来自实际装箱方案（含 VGM 上限），不按理论满载假设 | I10: 计算依据
A11: S5 | B11: FREIGHT | C11: 海运费（折算 ¥/吨） | D11: 公式：柜价×汇率÷吨数 | E11: =IF(OR('03 费用明细'!$E$9="",'03 费用明细'!$E$10=""),"",'03 费用明细'!$E$9*'01 基础参数'!$B$25/'03 费用明细'!$E$10) | F11: ¥/t | G11: =IF(ISNUMBER(E11),"已算","待查询") | H11: '='03 费用明细'!$E$9 × 报价汇率 ÷ '03 费用明细'!$E$10 | I11: 卖方
A12: S6 | B12: INS-RATE | C12: 保险费率（占 CIF） | D12: 百分数（如 0.3 表示 0.3%） | E12: 0.3 | F12: % | G12: =IF(E12="","待查询","已填") | H12: 保险公司报价；CIF 投保金额 = CIF × 110% | I12: 卖方(CIF)
A13: S6 | B13: INS-FLOOR | C13: 保单最低保费（整票） | D13: ¥/票 | E13: 300 | F13: ¥ | G13: =IF(E13="","待查询","已填") | H13: 可选：按费率算出的保费低于最低保费时，按最低保费分摊 | I13: 卖方(CIF)
A14: S7 | B14: EXPORT_TAX | C14: 出口关税及其他出口税费 | D14: ¥/吨 | E14: 0 | F14: ¥/t | G14: =IF(E14="","待查询",IF(E14=0,"0","已填")) | H14: HS 2836200000 出口关税 0%（海关公示）；其他出口税费另计 | I14: 卖方
A15: S8 | B15: OTHER | C15: 其他出口费用 | D15: ¥/吨 | E15: 25 | F15: ¥/t | G15: =IF(E15="","待查询",IF(E15=0,"0","已填")) | H15: 结汇/银行费、检验、认证、配额等 | I15: 卖方
A16: S9 | B16: DEST_PORT | C16: 目的港费用 / 目的地交货费用 | D16: ¥/吨 | F16: ¥/t | G16: =IF(E16="","待查询",IF(E16=0,"0","已填")) | H16: 仅 DAP/DPU/DDP 由卖方承担，F/C 组不计入 | I16: 卖方(D组)/买方(F/C组)
A18: 说明 | B18: • 黄色=待填，紫色=SIMULATED 模拟值，浅蓝=公式。空单元格在后续表中显示「待查询」。 • 海运费两种录入口径：柜价（USD/柜）+ 装柜吨数 → 自动折 ¥/t；或直接把 ¥/t 填到 FREIGHT 行（覆盖公式）。 • 保险费在 04 表按 CIF 自洽式求解，原因见 04 表脚注：用 CFR×费率会系统性低估保费。

Sheet 04 术语成本
A1: 04 术语成本推导（公式驱动）
A2: 从费用链逐层累加：FOB → CFR → CIF；保险费按 CIF×110% 自洽求解
A4: 项目 | B4: 符号 | C4: 公式 / 说明 | D4: 金额（¥/吨） | E4: 校验
A5: 一、成本段合计
A6: 出厂价 | B6: S1 | C6: 03 费用明细 · EXW | D6: ='03 费用明细'!$E$5
A7: 包装 | B7: S2 | C7: 03 费用明细 · PKG | D7: ='03 费用明细'!$E$6
A8: 内陆运输 | B8: S3 | C8: 03 费用明细 · INLAND | D8: ='03 费用明细'!$E$7
A9: 港口及报关 | B9: S4 | C9: 03 费用明细 · PORT | D9: ='03 费用明细'!$E$8
A10: 海运费 | B10: S5 | C10: '=USD/柜 × 汇率 ÷ 装柜吨数 | D10: ='03 费用明细'!$E$11
A11: 出口税费 | B11: S7 | C11: 03 费用明细 · EXPORT_TAX | D11: ='03 费用明细'!$E$14
A12: 其他出口费用 | B12: S8 | C12: 03 费用明细 · OTHER | D12: ='03 费用明细'!$E$15
A13: 保险费 | B13: S6 | C13: '= CFR × 1.10r /(1 − 1.10r)，r=保险费率（自洽解） | D13: =IF(OR('03 费用明细'!$E$12="",NOT(ISNUMBER('04 术语成本'!$D$10))),"",IFERROR(MAX(('04 术语成本'!$D$10+'04 术语成本'!$D$6+'04 术语成本'!$D$7+'04 术语成本'!$D$8+'04 术语成本'!$D$9+'04 术语成本'!$D$11+'04 术语成本'!$D$12)*(1.1*('03 费用明细'!$E$12/100))/(1-1.1*('03 费用明细'!$E$12/100)),IFERROR('03 费用明细'!$E$13/'01 基础参数'!$B$15,0)),""))
A14: 目的地及进口环节 | B14: S9 | C14: 03 费用明细 · DEST_PORT（仅 D 组） | D14: ='03 费用明细'!$E$16
A16: 二、术语成本（费用不重复）
A17: FOB 成本 | B17: CFOB | C17: S1+S2+S3+S4+S7+S8 | D17: =IFERROR('04 术语成本'!$D$6+'04 术语成本'!$D$7+'04 术语成本'!$D$8+'04 术语成本'!$D$9+'04 术语成本'!$D$11+'04 术语成本'!$D$12,"")
A18: CFR 成本 | B18: CCFR | C18: CFOB + S5 | D18: =IFERROR('04 术语成本'!$D$17+'04 术语成本'!$D$10,"")
A19: CIF 成本 | B19: CCIF | C19: CCFR + S6 | D19: =IFERROR('04 术语成本'!$D$18+'04 术语成本'!$D$13,"")
A20: FCA 成本（卖方场所） | B20: CFCA | C20: S1+S2（出口清关费另计） | D20: =IFERROR('04 术语成本'!$D$6+'04 术语成本'!$D$7,"")
A22: 恒等式校验 | B22: =IF(AND(ISNUMBER('04 术语成本'!$D$18),ISNUMBER('04 术语成本'!$D$17),ISNUMBER('04 术语成本'!$D$10)),IF(ABS('04 术语成本'!$D$18-('04 术语成本'!$D$17+'04 术语成本'!$D$10))<0.000001,"✓ CFR = FOB + 运费","✗ CFR 校验失败"),"— 待补数据")
A23: 恒等式校验 | B23: =IF(AND(ISNUMBER('04 术语成本'!$D$19),ISNUMBER('04 术语成本'!$D$18),ISNUMBER('04 术语成本'!$D$13)),IF(ABS('04 术语成本'!$D$19-('04 术语成本'!$D$18+'04 术语成本'!$D$13))<0.000001,"✓ CIF = CFR + 保险费","✗ CIF 校验失败"),"— 待补数据")
A24: 恒等式校验 | B24: =IF(AND(ISNUMBER('04 术语成本'!$D$13),ISNUMBER('03 费用明细'!$E$12)),IF(ABS('04 术语成本'!$D$13-IFERROR('04 术语成本'!$D$19*1.1*'03 费用明细'!$E$12,0))<0.0001,"✓ 保险费 = CIF × 110% × 费率","✗ 保险费校验失败"),"— 待补数据")
A26: 为什么保险费不能用 CFR × 费率？ CIF 条款下投保金额 = 合同价值（即 CIF 价）× 110%，而 CIF 价本身含保险费——这是一个方程而非一次乘法： CCIF = CCFR + 1.10 × r × CCIF ⇒ CCIF = CCFR / (1 − 1.10r) 保险费 = 1.10 r × CCIF 若按 CFR × 费率，会系统性低估。r=0.3% 时，低估幅度约 0.33%；r 越高差距越大。 注：本式假设保费基于整票 CIF 金额；若保单设有最低保费，则按 最低保费 ÷ 数量 分摊（MAX 已内置）。

Sheet 05 FOB-CFR-CIF报价
A1: 05 三术语报价（人民币 + 外币）
A2: 改 01/03 任一参数，本表自动重算；毛利口径与基准术语取自 01 表
A4: 术语 | B4: 成本 ¥/t | C4: 毛利口径 | D4: 毛利率 | E4: 加成率 | F4: 单价 ¥/t | G4: 单价外币/t | H4: 总报价外币 | I4: 毛利总额 ¥
A5: FCA | B5: =IFERROR('04 术语成本'!$D$20,"") | C5: =IF('01 基础参数'!$B$31=A5,'01 基础参数'!$B$28,"同口径派生") | D5: =IF(OR(NOT(ISNUMBER(F5)),F5=0),"",IF(NOT(ISNUMBER(B5)),"",(F5-B5)/F5)) | E5: =IF(OR(NOT(ISNUMBER(F5)),NOT(ISNUMBER(B5)),B5=0),"",(F5-B5)/B5) | F5: =IF(NOT(ISNUMBER(B5)),"",IF('01 基础参数'!$B$28="直接定价",IF(ISNUMBER('01 基础参数'!$B$30),'01 基础参数'!$B$30,""),IF('01 基础参数'!$B$29="","",IF('01 基础参数'!$B$28="毛利率（按售价）",IFERROR(B5/(1-'01 基础参数'!$B$29),""),IFERROR(B5*(1+'01 基础参数'!$B$29),""))))) | G5: =IF(OR(NOT(ISNUMBER(F5)),NOT(ISNUMBER('01 基础参数'!$B$25))),"",F5/'01 基础参数'!$B$25) | H5: =IF(OR(G5="",NOT(ISNUMBER('01 基础参数'!$B$15))),"",G5*'01 基础参数'!$B$15) | I5: =IF(OR(NOT(ISNUMBER(F5)),NOT(ISNUMBER(B5)),NOT(ISNUMBER('01 基础参数'!$B$15))),"",(F5-B5)*'01 基础参数'!$B$15)
A6: FOB | B6: =IFERROR('04 术语成本'!$D$17,"") | C6: =IF('01 基础参数'!$B$31=A6,'01 基础参数'!$B$28,"同口径派生") | D6: =IF(OR(NOT(ISNUMBER(F6)),F6=0),"",IF(NOT(ISNUMBER(B6)),"",(F6-B6)/F6)) | E6: =IF(OR(NOT(ISNUMBER(F6)),NOT(ISNUMBER(B6)),B6=0),"",(F6-B6)/B6) | F6: =IF(NOT(ISNUMBER(B6)),"",IF('01 基础参数'!$B$28="直接定价",IF(ISNUMBER('01 基础参数'!$B$30),'01 基础参数'!$B$30,""),IF('01 基础参数'!$B$29="","",IF('01 基础参数'!$B$28="毛利率（按售价）",IFERROR(B6/(1-'01 基础参数'!$B$29),""),IFERROR(B6*(1+'01 基础参数'!$B$29),""))))) | G6: =IF(OR(NOT(ISNUMBER(F6)),NOT(ISNUMBER('01 基础参数'!$B$25))),"",F6/'01 基础参数'!$B$25) | H6: =IF(OR(G6="",NOT(ISNUMBER('01 基础参数'!$B$15))),"",G6*'01 基础参数'!$B$15) | I6: =IF(OR(NOT(ISNUMBER(F6)),NOT(ISNUMBER(B6)),NOT(ISNUMBER('01 基础参数'!$B$15))),"",(F6-B6)*'01 基础参数'!$B$15)
A7: CFR | B7: =IFERROR('04 术语成本'!$D$18,"") | C7: =IF('01 基础参数'!$B$31=A7,'01 基础参数'!$B$28,"同口径派生") | D7: =IF(OR(NOT(ISNUMBER(F7)),F7=0),"",IF(NOT(ISNUMBER(B7)),"",(F7-B7)/F7)) | E7: =IF(OR(NOT(ISNUMBER(F7)),NOT(ISNUMBER(B7)),B7=0),"",(F7-B7)/B7) | F7: =IF(NOT(ISNUMBER(B7)),"",IF('01 基础参数'!$B$28="直接定价",IF(ISNUMBER('01 基础参数'!$B$30),'01 基础参数'!$B$30,""),IF('01 基础参数'!$B$29="","",IF('01 基础参数'!$B$28="毛利率（按售价）",IFERROR(B7/(1-'01 基础参数'!$B$29),""),IFERROR(B7*(1+'01 基础参数'!$B$29),""))))) | G7: =IF(OR(NOT(ISNUMBER(F7)),NOT(ISNUMBER('01 基础参数'!$B$25))),"",F7/'01 基础参数'!$B$25) | H7: =IF(OR(G7="",NOT(ISNUMBER('01 基础参数'!$B$15))),"",G7*'01 基础参数'!$B$15) | I7: =IF(OR(NOT(ISNUMBER(F7)),NOT(ISNUMBER(B7)),NOT(ISNUMBER('01 基础参数'!$B$15))),"",(F7-B7)*'01 基础参数'!$B$15)
A8: CIF | B8: =IFERROR('04 术语成本'!$D$19,"") | C8: =IF('01 基础参数'!$B$31=A8,'01 基础参数'!$B$28,"同口径派生") | D8: =IF(OR(NOT(ISNUMBER(F8)),F8=0),"",IF(NOT(ISNUMBER(B8)),"",(F8-B8)/F8)) | E8: =IF(OR(NOT(ISNUMBER(F8)),NOT(ISNUMBER(B8)),B8=0),"",(F8-B8)/B8) | F8: =IF(NOT(ISNUMBER(B8)),"",IF('01 基础参数'!$B$28="直接定价",IF(ISNUMBER('01 基础参数'!$B$30),'01 基础参数'!$B$30,""),IF('01 基础参数'!$B$29="","",IF('01 基础参数'!$B$28="毛利率（按售价）",IFERROR(B8/(1-'01 基础参数'!$B$29),""),IFERROR(B8*(1+'01 基础参数'!$B$29),""))))) | G8: =IF(OR(NOT(ISNUMBER(F8)),NOT(ISNUMBER('01 基础参数'!$B$25))),"",F8/'01 基础参数'!$B$25) | H8: =IF(OR(G8="",NOT(ISNUMBER('01 基础参数'!$B$15))),"",G8*'01 基础参数'!$B$15) | I8: =IF(OR(NOT(ISNUMBER(F8)),NOT(ISNUMBER(B8)),NOT(ISNUMBER('01 基础参数'!$B$15))),"",(F8-B8)*'01 基础参数'!$B$15)
A10: 数量与汇率（引用 01 表）
A11: 数量(吨) | B11: ='01 基础参数'!$B$15
A12: 报价币种 | B12: ='01 基础参数'!$B$24
A13: 汇率 | B13: ='01 基础参数'!$B$25
A14: 毛利基准术语 | B14: ='01 基础参数'!$B$31
A16: 读法：① 成本列来自 04 表；② 毛利只对「基准术语」那一行生效（01 表设定），其余术语按同一成本链派生； ③ 若某术语成本为「待查询」（海运费/保险费缺失），该行单价与外币价都会留空——系统不会用 0 或估算值顶替。 ④ 「直接定价」模式下，四行都用同一个手工单价（你输入的价格，系统不评判高低）。

Sheet 06 汇率换算
A1: 06 汇率换算与外币报价
A2: 由 01 表汇率驱动；可在此做多币种对照（汇率仍由你录入）
A4: 币种 | B4: 汇率 CNY/1 | C4: FOB 外币/t | D4: CFR 外币/t | E4: CIF 外币/t | F4: CIF 总额（外币） | G4: 备注
A5: USD | B5: ='01 基础参数'!$B$20 | C5: =IF(OR(NOT(ISNUMBER(B5)),NOT(ISNUMBER('05 FOB-CFR-CIF报价'!$F$6))),"",'05 FOB-CFR-CIF报价'!$F$6/B5) | D5: =IF(OR(NOT(ISNUMBER(B5)),NOT(ISNUMBER('05 FOB-CFR-CIF报价'!$F$7))),"",'05 FOB-CFR-CIF报价'!$F$7/B5) | E5: =IF(OR(NOT(ISNUMBER(B5)),NOT(ISNUMBER('05 FOB-CFR-CIF报价'!$F$8))),"",'05 FOB-CFR-CIF报价'!$F$8/B5) | F5: =IF(OR(E5="",NOT(ISNUMBER('01 基础参数'!$B$15))),"",E5*'01 基础参数'!$B$15) | G5: 外币单价 = 人民币单价 ÷ 汇率
A6: EUR | B6: ='01 基础参数'!$B$21 | C6: =IF(OR(NOT(ISNUMBER(B6)),NOT(ISNUMBER('05 FOB-CFR-CIF报价'!$F$6))),"",'05 FOB-CFR-CIF报价'!$F$6/B6) | D6: =IF(OR(NOT(ISNUMBER(B6)),NOT(ISNUMBER('05 FOB-CFR-CIF报价'!$F$7))),"",'05 FOB-CFR-CIF报价'!$F$7/B6) | E6: =IF(OR(NOT(ISNUMBER(B6)),NOT(ISNUMBER('05 FOB-CFR-CIF报价'!$F$8))),"",'05 FOB-CFR-CIF报价'!$F$8/B6) | F6: =IF(OR(E6="",NOT(ISNUMBER('01 基础参数'!$B$15))),"",E6*'01 基础参数'!$B$15)
A7: IDR | B7: ='01 基础参数'!$B$22 | C7: =IF(OR(NOT(ISNUMBER(B7)),NOT(ISNUMBER('05 FOB-CFR-CIF报价'!$F$6))),"",'05 FOB-CFR-CIF报价'!$F$6/B7) | D7: =IF(OR(NOT(ISNUMBER(B7)),NOT(ISNUMBER('05 FOB-CFR-CIF报价'!$F$7))),"",'05 FOB-CFR-CIF报价'!$F$7/B7) | E7: =IF(OR(NOT(ISNUMBER(B7)),NOT(ISNUMBER('05 FOB-CFR-CIF报价'!$F$8))),"",'05 FOB-CFR-CIF报价'!$F$8/B7) | F7: =IF(OR(E7="",NOT(ISNUMBER('01 基础参数'!$B$15))),"",E7*'01 基础参数'!$B$15)
A9: 换算口径：外币单价 = 人民币单价 ÷（CNY/1 外币）。汇率由 01 表提供，系统不取中间价或实时牌价。 若实际结汇采用不同汇率（如远期锁汇价、银行买入价），请把该汇率填进 01 表，而不是事后手工改外币单价。 IDR 小数位较多，建议同时保留人民币价与美元价，避免印尼盾报价尾差。

Sheet 07 毛利测算
A1: 07 毛利与加价测算
A2: 毛利率 vs 成本加成率：两种口径的换算与陷阱
A4: 项目 | B4: 公式 | C4: 数值 | D4: 说明
A5: 基准术语 | B5: '=01!毛利基准术语 | C5: ='01 基础参数'!$B$31
A6: 基准术语成本 | B6: '=IF(基准=FOB, FOB成本, IF(基准=CFR, CFR成本, CIF成本)) | C6: =IFERROR(CHOOSE(MATCH($C$5,{"FCA","FOB","CFR","CIF"},0),'04 术语成本'!$D$20,'04 术语成本'!$D$17,'04 术语成本'!$D$18,'04 术语成本'!$D$19),"")
A7: 设定毛利（口径值） | B7: '=01!毛利数值 | C7: ='01 基础参数'!$B$29
A8: 若为毛利率 → 售价 | B8: P = C / (1 − m) | C8: =IF(NOT(ISNUMBER(C6)),"",IFERROR(C6/(1-C7),""))
A9: 若为加成率 → 售价 | B9: P = C × (1 + k) | C9: =IF(NOT(ISNUMBER(C6)),"",C6*(1+C7))
A10: 当前口径下的售价 | B10: '=05 表对应术语单价 | C10: =IFERROR(IF($C$5="CIF",'05 FOB-CFR-CIF报价'!$F$8,IF($C$5="CFR",'05 FOB-CFR-CIF报价'!$F$7,IF($C$5="FOB",'05 FOB-CFR-CIF报价'!$F$6,'05 FOB-CFR-CIF报价'!$F$5))),"")
A12: 口径换算（同一个价格，两种表述）
A13: 毛利率 m | B13: 对应加成率 k = m/(1−m) | C13: 加成率 k | D13: 对应毛利率 m = k/(1+k)
A14: 0.03 | B14: =IF(OR(A14="",A14>=1),"",A14/(1-A14)) | C14: 0.03 | D14: =IF(OR(C14="",C14<=-1),"",C14/(1+C14))
A15: 0.05 | B15: =IF(OR(A15="",A15>=1),"",A15/(1-A15)) | C15: 0.05 | D15: =IF(OR(C15="",C15<=-1),"",C15/(1+C15))
A16: 0.08 | B16: =IF(OR(A16="",A16>=1),"",A16/(1-A16)) | C16: 0.08 | D16: =IF(OR(C16="",C16<=-1),"",C16/(1+C16))
A17: 0.1 | B17: =IF(OR(A17="",A17>=1),"",A17/(1-A17)) | C17: 0.1 | D17: =IF(OR(C17="",C17<=-1),"",C17/(1+C17))
A18: 0.15 | B18: =IF(OR(A18="",A18>=1),"",A18/(1-A18)) | C18: 0.15 | D18: =IF(OR(C18="",C18<=-1),"",C18/(1+C18))
A19: 0.2 | B19: =IF(OR(A19="",A19>=1),"",A19/(1-A19)) | C19: 0.2 | D19: =IF(OR(C19="",C19<=-1),"",C19/(1+C19))
A20: 0.3 | B20: =IF(OR(A20="",A20>=1),"",A20/(1-A20)) | C20: 0.3 | D20: =IF(OR(C20="",C20<=-1),"",C20/(1+C20))
A22: 校验 | B22: (1+加成率)(1−毛利率) 应 = 1 | C22: =IF(NOT(ISNUMBER(C10)),"",IFERROR((1+((C10-C6)/C6))*(1-((C10-C6)/C10)),""))
A24: 最常见的自伤：把「成本加成 8%」写成「毛利 8%」。C=100 时，加成 8% 售价 108，毛利率只有 7.41%； 反过来，要拿到 8% 毛利率，售价必须是 100/(1−8%) = 108.70（加成 8.70%）。按加成 8% 报价，每吨少赚 0.70。 谈「毛利几个点」时必须同时说清：① 哪种口径 ② 针对哪个术语（FOB 还是 CIF）③ 是否含退税。

Sheet 08 敏感性分析
A1: 08 敏感性分析（运费 / 汇率 / 毛利）
A2: 一维情景：其余参数不变。表格全为公式，改 03 表任意项后自动重算
A4: A. 海运费变动 → 三术语成本与报价（其余不变）
A5: 运费变动 | B5: 运费 ¥/t | C5: FOB 成本 | D5: CFR 成本 | E5: CIF 成本 | F5: CIF 单价 ¥/t | G5: CIF 外币/t | H5: 毛利率
A6: -0.2 | B6: =IF(NOT(ISNUMBER('04 术语成本'!$D$10)),"",'04 术语成本'!$D$10*(1+A6)) | C6: =IF(NOT(ISNUMBER('04 术语成本'!$D$17)),"",'04 术语成本'!$D$17) | D6: =IF(NOT(ISNUMBER('04 术语成本'!$D$17)),"",'04 术语成本'!$D$17+'04 术语成本'!$D$10*(1+A6)) | E6: =IF(OR(NOT(ISNUMBER(D6)),NOT(ISNUMBER('03 费用明细'!$E$12))),"",IFERROR(D6/(1-1.1*('03 费用明细'!$E$12/100)),"")) | F6: =IF(NOT(ISNUMBER(E6)),"",IF('01 基础参数'!$B$28="直接定价",IF(ISNUMBER('01 基础参数'!$B$30),'01 基础参数'!$B$30,""),IF('01 基础参数'!$B$29="","",IF('01 基础参数'!$B$28="毛利率（按售价）",IFERROR(E6/(1-'01 基础参数'!$B$29),""),E6*(1+'01 基础参数'!$B$29))))) | G6: =IF(OR(NOT(ISNUMBER(F6)),NOT(ISNUMBER('01 基础参数'!$B$25))),"",F6/'01 基础参数'!$B$25) | H6: =IF(OR(NOT(ISNUMBER(F6)),NOT(ISNUMBER(E6)),F6=0),"",(F6-E6)/F6)
A7: -0.1 | B7: =IF(NOT(ISNUMBER('04 术语成本'!$D$10)),"",'04 术语成本'!$D$10*(1+A7)) | C7: =IF(NOT(ISNUMBER('04 术语成本'!$D$17)),"",'04 术语成本'!$D$17) | D7: =IF(NOT(ISNUMBER('04 术语成本'!$D$17)),"",'04 术语成本'!$D$17+'04 术语成本'!$D$10*(1+A7)) | E7: =IF(OR(NOT(ISNUMBER(D7)),NOT(ISNUMBER('03 费用明细'!$E$12))),"",IFERROR(D7/(1-1.1*('03 费用明细'!$E$12/100)),"")) | F7: =IF(NOT(ISNUMBER(E7)),"",IF('01 基础参数'!$B$28="直接定价",IF(ISNUMBER('01 基础参数'!$B$30),'01 基础参数'!$B$30,""),IF('01 基础参数'!$B$29="","",IF('01 基础参数'!$B$28="毛利率（按售价）",IFERROR(E7/(1-'01 基础参数'!$B$29),""),E7*(1+'01 基础参数'!$B$29))))) | G7: =IF(OR(NOT(ISNUMBER(F7)),NOT(ISNUMBER('01 基础参数'!$B$25))),"",F7/'01 基础参数'!$B$25) | H7: =IF(OR(NOT(ISNUMBER(F7)),NOT(ISNUMBER(E7)),F7=0),"",(F7-E7)/F7)
A8: 0 | B8: =IF(NOT(ISNUMBER('04 术语成本'!$D$10)),"",'04 术语成本'!$D$10*(1+A8)) | C8: =IF(NOT(ISNUMBER('04 术语成本'!$D$17)),"",'04 术语成本'!$D$17) | D8: =IF(NOT(ISNUMBER('04 术语成本'!$D$17)),"",'04 术语成本'!$D$17+'04 术语成本'!$D$10*(1+A8)) | E8: =IF(OR(NOT(ISNUMBER(D8)),NOT(ISNUMBER('03 费用明细'!$E$12))),"",IFERROR(D8/(1-1.1*('03 费用明细'!$E$12/100)),"")) | F8: =IF(NOT(ISNUMBER(E8)),"",IF('01 基础参数'!$B$28="直接定价",IF(ISNUMBER('01 基础参数'!$B$30),'01 基础参数'!$B$30,""),IF('01 基础参数'!$B$29="","",IF('01 基础参数'!$B$28="毛利率（按售价）",IFERROR(E8/(1-'01 基础参数'!$B$29),""),E8*(1+'01 基础参数'!$B$29))))) | G8: =IF(OR(NOT(ISNUMBER(F8)),NOT(ISNUMBER('01 基础参数'!$B$25))),"",F8/'01 基础参数'!$B$25) | H8: =IF(OR(NOT(ISNUMBER(F8)),NOT(ISNUMBER(E8)),F8=0),"",(F8-E8)/F8)
A9: 0.1 | B9: =IF(NOT(ISNUMBER('04 术语成本'!$D$10)),"",'04 术语成本'!$D$10*(1+A9)) | C9: =IF(NOT(ISNUMBER('04 术语成本'!$D$17)),"",'04 术语成本'!$D$17) | D9: =IF(NOT(ISNUMBER('04 术语成本'!$D$17)),"",'04 术语成本'!$D$17+'04 术语成本'!$D$10*(1+A9)) | E9: =IF(OR(NOT(ISNUMBER(D9)),NOT(ISNUMBER('03 费用明细'!$E$12))),"",IFERROR(D9/(1-1.1*('03 费用明细'!$E$12/100)),"")) | F9: =IF(NOT(ISNUMBER(E9)),"",IF('01 基础参数'!$B$28="直接定价",IF(ISNUMBER('01 基础参数'!$B$30),'01 基础参数'!$B$30,""),IF('01 基础参数'!$B$29="","",IF('01 基础参数'!$B$28="毛利率（按售价）",IFERROR(E9/(1-'01 基础参数'!$B$29),""),E9*(1+'01 基础参数'!$B$29))))) | G9: =IF(OR(NOT(ISNUMBER(F9)),NOT(ISNUMBER('01 基础参数'!$B$25))),"",F9/'01 基础参数'!$B$25) | H9: =IF(OR(NOT(ISNUMBER(F9)),NOT(ISNUMBER(E9)),F9=0),"",(F9-E9)/F9)
A10: 0.2 | B10: =IF(NOT(ISNUMBER('04 术语成本'!$D$10)),"",'04 术语成本'!$D$10*(1+A10)) | C10: =IF(NOT(ISNUMBER('04 术语成本'!$D$17)),"",'04 术语成本'!$D$17) | D10: =IF(NOT(ISNUMBER('04 术语成本'!$D$17)),"",'04 术语成本'!$D$17+'04 术语成本'!$D$10*(1+A10)) | E10: =IF(OR(NOT(ISNUMBER(D10)),NOT(ISNUMBER('03 费用明细'!$E$12))),"",IFERROR(D10/(1-1.1*('03 费用明细'!$E$12/100)),"")) | F10: =IF(NOT(ISNUMBER(E10)),"",IF('01 基础参数'!$B$28="直接定价",IF(ISNUMBER('01 基础参数'!$B$30),'01 基础参数'!$B$30,""),IF('01 基础参数'!$B$29="","",IF('01 基础参数'!$B$28="毛利率（按售价）",IFERROR(E10/(1-'01 基础参数'!$B$29),""),E10*(1+'01 基础参数'!$B$29))))) | G10: =IF(OR(NOT(ISNUMBER(F10)),NOT(ISNUMBER('01 基础参数'!$B$25))),"",F10/'01 基础参数'!$B$25) | H10: =IF(OR(NOT(ISNUMBER(F10)),NOT(ISNUMBER(E10)),F10=0),"",(F10-E10)/F10)
A13: B. 汇率变动 → 外币单价（人民币成本不变，但外币计价运费/保费折人民币会变）
A14: 汇率变动 | B14: 汇率 CNY | C14: CIF 成本 ¥/t | D14: CIF 单价 ¥/t | E14: CIF 外币/t | F14: 外币总额
A15: -0.1 | B15: =IF(NOT(ISNUMBER('01 基础参数'!$B$25)),"",'01 基础参数'!$B$25*(1+A15)) | C15: =IF(OR(NOT(ISNUMBER(B15)),NOT(ISNUMBER('04 术语成本'!$D$17))),"",IFERROR(('04 术语成本'!$D$17+IFERROR('03 费用明细'!$E$9*B15/'03 费用明细'!$E$10,0))/(1-IFERROR(1.1*('03 费用明细'!$E$12/100),0)),"")) | D15: =IF(NOT(ISNUMBER(C15)),"",IF('01 基础参数'!$B$28="直接定价",IF(ISNUMBER('01 基础参数'!$B$30),'01 基础参数'!$B$30,""),IF('01 基础参数'!$B$29="","",IF('01 基础参数'!$B$28="毛利率（按售价）",IFERROR(C15/(1-'01 基础参数'!$B$29),""),C15*(1+'01 基础参数'!$B$29))))) | E15: =IF(OR(NOT(ISNUMBER(D15)),NOT(ISNUMBER(B15))),"",D15/B15) | F15: =IF(OR(E15="",NOT(ISNUMBER('01 基础参数'!$B$15))),"",E15*'01 基础参数'!$B$15)
A16: -0.05 | B16: =IF(NOT(ISNUMBER('01 基础参数'!$B$25)),"",'01 基础参数'!$B$25*(1+A16)) | C16: =IF(OR(NOT(ISNUMBER(B16)),NOT(ISNUMBER('04 术语成本'!$D$17))),"",IFERROR(('04 术语成本'!$D$17+IFERROR('03 费用明细'!$E$9*B16/'03 费用明细'!$E$10,0))/(1-IFERROR(1.1*('03 费用明细'!$E$12/100),0)),"")) | D16: =IF(NOT(ISNUMBER(C16)),"",IF('01 基础参数'!$B$28="直接定价",IF(ISNUMBER('01 基础参数'!$B$30),'01 基础参数'!$B$30,""),IF('01 基础参数'!$B$29="","",IF('01 基础参数'!$B$28="毛利率（按售价）",IFERROR(C16/(1-'01 基础参数'!$B$29),""),C16*(1+'01 基础参数'!$B$29))))) | E16: =IF(OR(NOT(ISNUMBER(D16)),NOT(ISNUMBER(B16))),"",D16/B16) | F16: =IF(OR(E16="",NOT(ISNUMBER('01 基础参数'!$B$15))),"",E16*'01 基础参数'!$B$15)
A17: 0 | B17: =IF(NOT(ISNUMBER('01 基础参数'!$B$25)),"",'01 基础参数'!$B$25*(1+A17)) | C17: =IF(OR(NOT(ISNUMBER(B17)),NOT(ISNUMBER('04 术语成本'!$D$17))),"",IFERROR(('04 术语成本'!$D$17+IFERROR('03 费用明细'!$E$9*B17/'03 费用明细'!$E$10,0))/(1-IFERROR(1.1*('03 费用明细'!$E$12/100),0)),"")) | D17: =IF(NOT(ISNUMBER(C17)),"",IF('01 基础参数'!$B$28="直接定价",IF(ISNUMBER('01 基础参数'!$B$30),'01 基础参数'!$B$30,""),IF('01 基础参数'!$B$29="","",IF('01 基础参数'!$B$28="毛利率（按售价）",IFERROR(C17/(1-'01 基础参数'!$B$29),""),C17*(1+'01 基础参数'!$B$29))))) | E17: =IF(OR(NOT(ISNUMBER(D17)),NOT(ISNUMBER(B17))),"",D17/B17) | F17: =IF(OR(E17="",NOT(ISNUMBER('01 基础参数'!$B$15))),"",E17*'01 基础参数'!$B$15)
A18: 0.05 | B18: =IF(NOT(ISNUMBER('01 基础参数'!$B$25)),"",'01 基础参数'!$B$25*(1+A18)) | C18: =IF(OR(NOT(ISNUMBER(B18)),NOT(ISNUMBER('04 术语成本'!$D$17))),"",IFERROR(('04 术语成本'!$D$17+IFERROR('03 费用明细'!$E$9*B18/'03 费用明细'!$E$10,0))/(1-IFERROR(1.1*('03 费用明细'!$E$12/100),0)),"")) | D18: =IF(NOT(ISNUMBER(C18)),"",IF('01 基础参数'!$B$28="直接定价",IF(ISNUMBER('01 基础参数'!$B$30),'01 基础参数'!$B$30,""),IF('01 基础参数'!$B$29="","",IF('01 基础参数'!$B$28="毛利率（按售价）",IFERROR(C18/(1-'01 基础参数'!$B$29),""),C18*(1+'01 基础参数'!$B$29))))) | E18: =IF(OR(NOT(ISNUMBER(D18)),NOT(ISNUMBER(B18))),"",D18/B18) | F18: =IF(OR(E18="",NOT(ISNUMBER('01 基础参数'!$B$15))),"",E18*'01 基础参数'!$B$15)
A19: 0.1 | B19: =IF(NOT(ISNUMBER('01 基础参数'!$B$25)),"",'01 基础参数'!$B$25*(1+A19)) | C19: =IF(OR(NOT(ISNUMBER(B19)),NOT(ISNUMBER('04 术语成本'!$D$17))),"",IFERROR(('04 术语成本'!$D$17+IFERROR('03 费用明细'!$E$9*B19/'03 费用明细'!$E$10,0))/(1-IFERROR(1.1*('03 费用明细'!$E$12/100),0)),"")) | D19: =IF(NOT(ISNUMBER(C19)),"",IF('01 基础参数'!$B$28="直接定价",IF(ISNUMBER('01 基础参数'!$B$30),'01 基础参数'!$B$30,""),IF('01 基础参数'!$B$29="","",IF('01 基础参数'!$B$28="毛利率（按售价）",IFERROR(C19/(1-'01 基础参数'!$B$29),""),C19*(1+'01 基础参数'!$B$29))))) | E19: =IF(OR(NOT(ISNUMBER(D19)),NOT(ISNUMBER(B19))),"",D19/B19) | F19: =IF(OR(E19="",NOT(ISNUMBER('01 基础参数'!$B$15))),"",E19*'01 基础参数'!$B$15)
A22: C. 目标毛利变动 → 报价（按当前口径）
A23: 增长率 | B23: 毛利口径值 | C23: FOB 单价 | D23: CFR 单价 | E23: CIF 单价 | F23: CIF 外币/t | G23: 毛利/吨
A24: -0.03 | B24: =IF('01 基础参数'!$B$29="","",'01 基础参数'!$B$29+A24) | C24: =IF(OR(B24="",NOT(ISNUMBER('04 术语成本'!$D$17))),"",IF('01 基础参数'!$B$28="直接定价",IF(ISNUMBER('01 基础参数'!$B$30),'01 基础参数'!$B$30,""),IF('01 基础参数'!$B$28="毛利率（按售价）",IFERROR('04 术语成本'!$D$17/(1-B24),""),'04 术语成本'!$D$17*(1+B24)))) | D24: =IF(OR(B24="",NOT(ISNUMBER('04 术语成本'!$D$18))),"",IF('01 基础参数'!$B$28="直接定价",IF(ISNUMBER('01 基础参数'!$B$30),'01 基础参数'!$B$30,""),IF('01 基础参数'!$B$28="毛利率（按售价）",IFERROR('04 术语成本'!$D$18/(1-B24),""),'04 术语成本'!$D$18*(1+B24)))) | E24: =IF(OR(B24="",NOT(ISNUMBER('04 术语成本'!$D$19))),"",IF('01 基础参数'!$B$28="直接定价",IF(ISNUMBER('01 基础参数'!$B$30),'01 基础参数'!$B$30,""),IF('01 基础参数'!$B$28="毛利率（按售价）",IFERROR('04 术语成本'!$D$19/(1-B24),""),'04 术语成本'!$D$19*(1+B24)))) | F24: =IF(OR(E24="",NOT(ISNUMBER('01 基础参数'!$B$25))),"",E24/'01 基础参数'!$B$25) | G24: =IF(OR(E24="",NOT(ISNUMBER('04 术语成本'!$D$19))),"",E24-'04 术语成本'!$D$19)
A25: -0.01 | B25: =IF('01 基础参数'!$B$29="","",'01 基础参数'!$B$29+A25) | C25: =IF(OR(B25="",NOT(ISNUMBER('04 术语成本'!$D$17))),"",IF('01 基础参数'!$B$28="直接定价",IF(ISNUMBER('01 基础参数'!$B$30),'01 基础参数'!$B$30,""),IF('01 基础参数'!$B$28="毛利率（按售价）",IFERROR('04 术语成本'!$D$17/(1-B25),""),'04 术语成本'!$D$17*(1+B25)))) | D25: =IF(OR(B25="",NOT(ISNUMBER('04 术语成本'!$D$18))),"",IF('01 基础参数'!$B$28="直接定价",IF(ISNUMBER('01 基础参数'!$B$30),'01 基础参数'!$B$30,""),IF('01 基础参数'!$B$28="毛利率（按售价）",IFERROR('04 术语成本'!$D$18/(1-B25),""),'04 术语成本'!$D$18*(1+B25)))) | E25: =IF(OR(B25="",NOT(ISNUMBER('04 术语成本'!$D$19))),"",IF('01 基础参数'!$B$28="直接定价",IF(ISNUMBER('01 基础参数'!$B$30),'01 基础参数'!$B$30,""),IF('01 基础参数'!$B$28="毛利率（按售价）",IFERROR('04 术语成本'!$D$19/(1-B25),""),'04 术语成本'!$D$19*(1+B25)))) | F25: =IF(OR(E25="",NOT(ISNUMBER('01 基础参数'!$B$25))),"",E25/'01 基础参数'!$B$25) | G25: =IF(OR(E25="",NOT(ISNUMBER('04 术语成本'!$D$19))),"",E25-'04 术语成本'!$D$19)
A26: 0 | B26: =IF('01 基础参数'!$B$29="","",'01 基础参数'!$B$29+A26) | C26: =IF(OR(B26="",NOT(ISNUMBER('04 术语成本'!$D$17))),"",IF('01 基础参数'!$B$28="直接定价",IF(ISNUMBER('01 基础参数'!$B$30),'01 基础参数'!$B$30,""),IF('01 基础参数'!$B$28="毛利率（按售价）",IFERROR('04 术语成本'!$D$17/(1-B26),""),'04 术语成本'!$D$17*(1+B26)))) | D26: =IF(OR(B26="",NOT(ISNUMBER('04 术语成本'!$D$18))),"",IF('01 基础参数'!$B$28="直接定价",IF(ISNUMBER('01 基础参数'!$B$30),'01 基础参数'!$B$30,""),IF('01 基础参数'!$B$28="毛利率（按售价）",IFERROR('04 术语成本'!$D$18/(1-B26),""),'04 术语成本'!$D$18*(1+B26)))) | E26: =IF(OR(B26="",NOT(ISNUMBER('04 术语成本'!$D$19))),"",IF('01 基础参数'!$B$28="直接定价",IF(ISNUMBER('01 基础参数'!$B$30),'01 基础参数'!$B$30,""),IF('01 基础参数'!$B$28="毛利率（按售价）",IFERROR('04 术语成本'!$D$19/(1-B26),""),'04 术语成本'!$D$19*(1+B26)))) | F26: =IF(OR(E26="",NOT(ISNUMBER('01 基础参数'!$B$25))),"",E26/'01 基础参数'!$B$25) | G26: =IF(OR(E26="",NOT(ISNUMBER('04 术语成本'!$D$19))),"",E26-'04 术语成本'!$D$19)
A27: 0.01 | B27: =IF('01 基础参数'!$B$29="","",'01 基础参数'!$B$29+A27) | C27: =IF(OR(B27="",NOT(ISNUMBER('04 术语成本'!$D$17))),"",IF('01 基础参数'!$B$28="直接定价",IF(ISNUMBER('01 基础参数'!$B$30),'01 基础参数'!$B$30,""),IF('01 基础参数'!$B$28="毛利率（按售价）",IFERROR('04 术语成本'!$D$17/(1-B27),""),'04 术语成本'!$D$17*(1+B27)))) | D27: =IF(OR(B27="",NOT(ISNUMBER('04 术语成本'!$D$18))),"",IF('01 基础参数'!$B$28="直接定价",IF(ISNUMBER('01 基础参数'!$B$30),'01 基础参数'!$B$30,""),IF('01 基础参数'!$B$28="毛利率（按售价）",IFERROR('04 术语成本'!$D$18/(1-B27),""),'04 术语成本'!$D$18*(1+B27)))) | E27: =IF(OR(B27="",NOT(ISNUMBER('04 术语成本'!$D$19))),"",IF('01 基础参数'!$B$28="直接定价",IF(ISNUMBER('01 基础参数'!$B$30),'01 基础参数'!$B$30,""),IF('01 基础参数'!$B$28="毛利率（按售价）",IFERROR('04 术语成本'!$D$19/(1-B27),""),'04 术语成本'!$D$19*(1+B27)))) | F27: =IF(OR(E27="",NOT(ISNUMBER('01 基础参数'!$B$25))),"",E27/'01 基础参数'!$B$25) | G27: =IF(OR(E27="",NOT(ISNUMBER('04 术语成本'!$D$19))),"",E27-'04 术语成本'!$D$19)
A28: 0.03 | B28: =IF('01 基础参数'!$B$29="","",'01 基础参数'!$B$29+A28) | C28: =IF(OR(B28="",NOT(ISNUMBER('04 术语成本'!$D$17))),"",IF('01 基础参数'!$B$28="直接定价",IF(ISNUMBER('01 基础参数'!$B$30),'01 基础参数'!$B$30,""),IF('01 基础参数'!$B$28="毛利率（按售价）",IFERROR('04 术语成本'!$D$17/(1-B28),""),'04 术语成本'!$D$17*(1+B28)))) | D28: =IF(OR(B28="",NOT(ISNUMBER('04 术语成本'!$D$18))),"",IF('01 基础参数'!$B$28="直接定价",IF(ISNUMBER('01 基础参数'!$B$30),'01 基础参数'!$B$30,""),IF('01 基础参数'!$B$28="毛利率（按售价）",IFERROR('04 术语成本'!$D$18/(1-B28),""),'04 术语成本'!$D$18*(1+B28)))) | E28: =IF(OR(B28="",NOT(ISNUMBER('04 术语成本'!$D$19))),"",IF('01 基础参数'!$B$28="直接定价",IF(ISNUMBER('01 基础参数'!$B$30),'01 基础参数'!$B$30,""),IF('01 基础参数'!$B$28="毛利率（按售价）",IFERROR('04 术语成本'!$D$19/(1-B28),""),'04 术语成本'!$D$19*(1+B28)))) | F28: =IF(OR(E28="",NOT(ISNUMBER('01 基础参数'!$B$25))),"",E28/'01 基础参数'!$B$25) | G28: =IF(OR(E28="",NOT(ISNUMBER('04 术语成本'!$D$19))),"",E28-'04 术语成本'!$D$19)
A31: 读法：A 表告诉你「运费涨 10%，CIF 单价要涨多少」（它还带动保险费同向变动，所以略高于 10%×运费占比）； B 表告诉你「人民币升值 5%，外币报价要降多少」——注意外币计价的运费折人民币成本也同步下降； C 表告诉你「毛利每加 1 个百分点，价格跳多少」——越接近 100% 毛利率，曲线越陡（1/(1−m) 放大）。

Sheet 09 多方案比较
A1: 09 多方案比较
A2: 方案 = 一组假设（运费/汇率/毛利口径）；灰底为录入，其余为公式派生
A4: 方案 | B4: 说明 | C4: 运费系数 | D4: 汇率 CNY | E4: 毛利口径 | F4: 毛利值 | G4: FOB ¥/t | H4: CFR ¥/t | I4: CIF ¥/t | J4: CIF 外币/t
A5: A | B5: 基准：按 01/03 表当前值 | C5: 1 | D5: ='01 基础参数'!$B$25 | E5: 毛利率（按售价） | F5: 0.08 | G5: =IF(NOT(ISNUMBER('04 术语成本'!$D$17)),"",'04 术语成本'!$D$17) | H5: =IF(NOT(ISNUMBER('04 术语成本'!$D$17)),"",'04 术语成本'!$D$17+IFERROR('04 术语成本'!$D$10,0)*C5) | I5: =IF(OR(NOT(ISNUMBER(H5)),NOT(ISNUMBER('03 费用明细'!$E$12))),"",IFERROR(H5/(1-1.1*('03 费用明细'!$E$12/100)),"")) | J5: =IF(OR(NOT(ISNUMBER(I5)),NOT(ISNUMBER(D5))),"",IF(E5="毛利率（按售价）",IFERROR(I5/(1-F5)/D5,""),I5*(1+F5)/D5))
A6: B | B6: 运费上浮 30% | C6: 1.3 | D6: ='01 基础参数'!$B$25 | E6: 毛利率（按售价） | F6: 0.08 | G6: =IF(NOT(ISNUMBER('04 术语成本'!$D$17)),"",'04 术语成本'!$D$17) | H6: =IF(NOT(ISNUMBER('04 术语成本'!$D$17)),"",'04 术语成本'!$D$17+IFERROR('04 术语成本'!$D$10,0)*C6) | I6: =IF(OR(NOT(ISNUMBER(H6)),NOT(ISNUMBER('03 费用明细'!$E$12))),"",IFERROR(H6/(1-1.1*('03 费用明细'!$E$12/100)),"")) | J6: =IF(OR(NOT(ISNUMBER(I6)),NOT(ISNUMBER(D6))),"",IF(E6="毛利率（按售价）",IFERROR(I6/(1-F6)/D6,""),I6*(1+F6)/D6))
A7: C | B7: 人民币升值（汇率 −5%） | C7: 1 | D7: =IFERROR('01 基础参数'!$B$25*0.95,'01 基础参数'!$B$25) | E7: 毛利率（按售价） | F7: 0.08 | G7: =IF(NOT(ISNUMBER('04 术语成本'!$D$17)),"",'04 术语成本'!$D$17) | H7: =IF(NOT(ISNUMBER('04 术语成本'!$D$17)),"",'04 术语成本'!$D$17+IFERROR('04 术语成本'!$D$10,0)*C7) | I7: =IF(OR(NOT(ISNUMBER(H7)),NOT(ISNUMBER('03 费用明细'!$E$12))),"",IFERROR(H7/(1-1.1*('03 费用明细'!$E$12/100)),"")) | J7: =IF(OR(NOT(ISNUMBER(I7)),NOT(ISNUMBER(D7))),"",IF(E7="毛利率（按售价）",IFERROR(I7/(1-F7)/D7,""),I7*(1+F7)/D7))
A8: D | B8: 成本加成率口径（对照） | C8: 1 | D8: ='01 基础参数'!$B$25 | E8: 成本加成率（按成本） | F8: 0.08 | G8: =IF(NOT(ISNUMBER('04 术语成本'!$D$17)),"",'04 术语成本'!$D$17) | H8: =IF(NOT(ISNUMBER('04 术语成本'!$D$17)),"",'04 术语成本'!$D$17+IFERROR('04 术语成本'!$D$10,0)*C8) | I8: =IF(OR(NOT(ISNUMBER(H8)),NOT(ISNUMBER('03 费用明细'!$E$12))),"",IFERROR(H8/(1-1.1*('03 费用明细'!$E$12/100)),"")) | J8: =IF(OR(NOT(ISNUMBER(I8)),NOT(ISNUMBER(D8))),"",IF(E8="毛利率（按售价）",IFERROR(I8/(1-F8)/D8,""),I8*(1+F8)/D8))
A9: E | B9: 自定义 | C9: 1 | D9: ='01 基础参数'!$B$25 | E9: 毛利率（按售价） | F9: 0.08 | G9: =IF(NOT(ISNUMBER('04 术语成本'!$D$17)),"",'04 术语成本'!$D$17) | H9: =IF(NOT(ISNUMBER('04 术语成本'!$D$17)),"",'04 术语成本'!$D$17+IFERROR('04 术语成本'!$D$10,0)*C9) | I9: =IF(OR(NOT(ISNUMBER(H9)),NOT(ISNUMBER('03 费用明细'!$E$12))),"",IFERROR(H9/(1-1.1*('03 费用明细'!$E$12/100)),"")) | J9: =IF(OR(NOT(ISNUMBER(I9)),NOT(ISNUMBER(D9))),"",IF(E9="毛利率（按售价）",IFERROR(I9/(1-F9)/D9,""),I9*(1+F9)/D9))
A11: 这些方案是「同一套成本链、不同假设」的算术对照，不是系统推荐方案。 真实报价还需要你决定：是否锁汇、运费是否含滞期、是否需要报价有效期条款、客户要求 ICC(A) 时的额外保费。

Sheet 10 缺失与假设
A1: 10 缺失费用与假设清单
A2: 这里列的每一项，都是「没有可靠依据、系统拒绝代填」的项目
A4: 代码 | B4: 缺失项 | C4: 成本段 | D4: 为什么不能自动填 | E4: 补数来源 | F4: 状态
A5: FREIGHT | B5: 海运费 | C5: S5 | D5: 运价随船期/箱型/货量波动，且是货代报价资产，不能跨航线外推 | E5: 货代书面报价（注明有效期） | F5: =IF('03 费用明细'!$E$9="","待补","已提供")
A6: INSURANCE | B6: 保险费率 | C6: S6 | D6: 费率取决于航线、险别（ICC A/B/C）、免赔额与承运人，不同保司差异大 | E6: 保险公司/货代保险部报价 | F6: =IF('03 费用明细'!$E$12="","待补","已提供")
A7: INLAND | B7: 内陆运输 | C7: S3 | D7: 取决于起运地、车型、装载方式与是否含装车费 | E7: 承运人报价 | F7: =IF('03 费用明细'!$E$7="","待补","已提供")
A8: PORT | B8: 港口及报关 | C8: S4 | D8: 取决于港口/码头、THC、单证与报关代理费 | E8: 货代一票全含报价 | F8: =IF('03 费用明细'!$E$8="","待补","已提供")
A9: EXPORT_TAX | B9: 出口税费 | C9: S7 | D9: 关税/出口环节税费以税则与申报要素为准 | E9: 海关税则、报关行确认 | F9: =IF('03 费用明细'!$E$14="","待补","已提供")
A10: OTHER | B10: 其他出口费用 | C10: S8 | D10: 检验/认证/结汇费按实际发生计 | E10: 银行、检验机构、认证机构 | F10: =IF('03 费用明细'!$E$15="","待补","已提供")
A12: 模拟值标注（SIMULATED · 非实时运价）
A13: 字段 | B13: 模拟值 | C13: 用途 | D13: 必须在发给客户前替换为
A14: 内陆运输 | B14: 110 | C14: 演示内陆段 | D14: 承运人报价
A15: 港口及报关费 | B15: 95 | C15: 演示港口段 | D15: 货代报价
A16: 海运费 USD/柜 | B16: 1250 | C16: 演示完整计算流程 | D16: 货代书面报价
A17: 装柜吨数 | B17: 25 | C17: 把柜价折成吨价 | D17: 实际装箱方案
A18: 保险费率 | B18: 0.3 | C18: 演示 CIF 保险自洽求解 | D18: 保险公司费率

Sheet 11 公式与校验
A1: 11 全部计算公式与校验结果
A2: 与 HTML 计算器、Python 引擎 calc_engine.py 同一套公式
A4: 编号 | B4: 项目 | C4: 公式（Excel 等价写法） | D4: 当前结果 | E4: 说明
A5: F01 | B5: 海运费折吨价 | C5: P_freight = USD/柜 × 汇率 ÷ 装柜吨数 | D5: ='04 术语成本'!$D$10 | E5: 外币计价段必须先折人民币
A6: F02 | B6: 保险费（CIF 自洽） | C6: P_ins = 1.10r × C_CIF = C_CFR × 1.10r /(1 − 1.10r) | D6: ='04 术语成本'!$D$13 | E6: r = 保险费率；默认 ICC(C)
A7: F03 | B7: FOB 成本 | C7: C_FOB = EXW + PKG + INLAND + PORT + TAX + OTHER | D7: ='04 术语成本'!$D$17 | E7: 到装运港上船为止
A8: F04 | B8: CFR 成本 | C8: C_CFR = C_FOB + P_freight | D8: ='04 术语成本'!$D$18 | E8: 卖方付运费，风险仍在装运港转移
A9: F05 | B9: CIF 成本 | C9: C_CIF = C_CFR + P_ins | D9: ='04 术语成本'!$D$19 | E9: 卖方投保
A10: F06 | B10: 毛利润 | C10: GP = P − C | D10: =IF(NOT(ISNUMBER(10)),"",10-6) | E10: 毛利永远按售价口径计算
A11: F07 | B11: 毛利率 | C11: m = GP / P | D11: =IF(NOT(ISNUMBER(10)),"",(10-6)/10) | E11: 按售价；P = C /(1−m)
A12: F08 | B12: 成本加成率 | C12: k = GP / C | D12: =IF(NOT(ISNUMBER(6)),"",(10-6)/6) | E12: 按成本；P = C ×(1+k)
A13: F09 | B13: 两口径关系 | C13: (1+k)(1−m) = 1 | D13: =IF(NOT(ISNUMBER(10)),"",(1+(10-6)/6)*(1-(10-6)/10)) | E13: k = m/(1−m)；m = k/(1+k)
A14: F10 | B14: 外币单价 | C14: P_fx = P ÷ (CNY/1 外币) | D14: =IFERROR('05 FOB-CFR-CIF报价'!$G$8,"") | E14: 汇率由用户提供
A15: F11 | B15: 外币总额 | C15: Total_fx = P_fx × 数量 | D15: =IFERROR('05 FOB-CFR-CIF报价'!$H$8,"")
A16: F12 | B16: 出口退税（参考） | C16: 生产企业：离岸价 × 汇率 × 退税率；外贸企业：购进金额 × 退税率 | D16: =IF(OR('01 基础参数'!$B$34="",NOT(ISNUMBER('04 术语成本'!$D$17)),NOT(ISNUMBER('01 基础参数'!$B$15))),"",IF('01 基础参数'!$B$36="是",'04 术语成本'!$D$17/(1+'01 基础参数'!$B$35)*'01 基础参数'!$B$34*'01 基础参数'!$B$15,'04 术语成本'!$D$17*'01 基础参数'!$B$34*'01 基础参数'!$B$15)) | E16: 单列，不自动抵减成本
A18: 校验面板
A19: 编号 | B19: 校验项 | C19: 断言 | D19: 结果 | E19: 不通过怎么办
A20: C1 | B20: CFR = FOB + 运费 | C20: IF(ABS('04 术语成本'!$D$18-('04 术语成本'!$D$17+'04 术语成本'!$D$10))<0.000001,"PASS","FAIL") | D20: =IF(ABS('04 术语成本'!$D$18-('04 术语成本'!$D$17+'04 术语成本'!$D$10))<0.000001,"PASS","FAIL") | E20: 检查 03 表海运费是否被重复计入
A21: C2 | B21: CIF = CFR + 保险费 | C21: IF(ABS('04 术语成本'!$D$19-('04 术语成本'!$D$18+'04 术语成本'!$D$13))<0.000001,"PASS","FAIL") | D21: =IF(ABS('04 术语成本'!$D$19-('04 术语成本'!$D$18+'04 术语成本'!$D$13))<0.000001,"PASS","FAIL") | E21: 检查保险费是否被重复或漏计
A22: C3 | B22: 保险费 = CIF×110%×费率 | C22: IF(ABS('04 术语成本'!$D$13-'04 术语成本'!$D$19*1.1*('03 费用明细'!$E$12/100))<0.0001,"PASS","FAIL") | D22: =IF(ABS('04 术语成本'!$D$13-'04 术语成本'!$D$19*1.1*('03 费用明细'!$E$12/100))<0.0001,"PASS","FAIL") | E22: 检查保险费公式是否仍为自洽解
A23: C4 | B23: (1+k)(1−m) = 1 | C23: IF(ABS((1+(10-6)/6)*(1-(10-6)/10)-1)<0.000001,"PASS","FAIL") | D23: =IF(ABS((1+(10-6)/6)*(1-(10-6)/10)-1)<0.000001,"PASS","FAIL") | E23: 检查毛利率与加成率口径是否混用
A24: C5 | B24: 数量已填 | C24: IF(ISNUMBER('01 基础参数'!$B$15),"PASS","FAIL") | D24: =IF(ISNUMBER('01 基础参数'!$B$15),"PASS","FAIL") | E24: 在 01 表填出口数量
A25: C6 | B25: 汇率已填 | C25: IF(AND(ISNUMBER('01 基础参数'!$B$25),'01 基础参数'!$B$25>0),"PASS","FAIL") | D25: =IF(AND(ISNUMBER('01 基础参数'!$B$25),'01 基础参数'!$B$25>0),"PASS","FAIL") | E25: 在 01 表填报价币种汇率
A26: C7 | B26: 成本项完整（无待查询） | C26: COUNTBLANK(03 表 E 列关键行) = 0 | D26: =IF(COUNTBLANK('03 费用明细'!$E$9)+COUNTBLANK('03 费用明细'!$E$12)+COUNTBLANK('03 费用明细'!$E$10)=0,"PASS","FAIL") | E26: 在 03 表补齐 10 表所列项目
A28: 本表公式与 HTML 计算器、scripts/calc_engine.py 完全同源；三处任何一处结果不一致，说明有人手改了中间值。 Excel 重算方式：改 01 表汇率/毛利或 03 表任一费用 → 全表联动（含 05、06、08、09、11）。 若某单元格显示「— 待补数据」或空白，请先看 10 表缺什么，不要用 0 顶替。

Sheet 12 报价草稿
A1: 12 英文报价草稿（需人工确认后发送）
A2: 数字全部引用 05 表；灰底 CANNOT-SEND 区块必须删除或替换后才能外发
A4: Ref. | B4: =CONCATENATE("Q-",TEXT(TODAY(),"YYYYMMDD"))
A5: Commodity | B5: Sodium Carbonate Heavy Ash (Soda Ash Dense)
A6: HS Code | B6: 2836200000
A7: Specification | B7: Na2CO3 ≥ 99.2%，堆积密度 ~1.0 g/cm³，工业级，25kg 覆膜编织袋
A8: Quantity | B8: ='01 基础参数'!$B$15 | C8: MT
A9: Loading port | B9: 青岛港 Qingdao (CNQDG)
A10: Destination | B10: 雅加达港 Jakarta (IDJKT)
A12: Incoterms® 2020 | B12: Unit price | C12: Currency | D12: Amount
A13: FOB | B13: ='05 FOB-CFR-CIF报价'!$G$6 | C13: ='01 基础参数'!$B$24 | D13: ='05 FOB-CFR-CIF报价'!$H$6
A14: CFR | B14: ='05 FOB-CFR-CIF报价'!$G$7 | C14: ='01 基础参数'!$B$24 | D14: ='05 FOB-CFR-CIF报价'!$H$7
A15: CIF | B15: ='05 FOB-CFR-CIF报价'!$G$8 | C15: ='01 基础参数'!$B$24 | D15: ='05 FOB-CFR-CIF报价'!$H$8
A17: 1. Price basis: Incoterms® 2020 as stated above.
A18: 2. Risk transfer (FOB/CFR/CIF): when the goods are placed on board the vessel at the port of shipment.
A19: 3. Insurance (CIF only): shall cover 110% of the invoice value, Institute Cargo Clauses (C) unless otherwise agreed. [CONFIRM required clauses with buyer]
A20: 4. Payment: [TO BE CONFIRMED].
A21: 5. Packing: [TO BE CONFIRMED].
A22: 6. Shipment: [TO BE CONFIRMED].
A23: 7. Validity: [TO BE CONFIRMED] — freight and exchange rate are the main moving parts.
A24: 8. Origin: China. [Confirm whether a Certificate of Origin / preferential origin document is applicable]
A25: INTERNAL NOTE — REMOVE BEFORE SENDING • 本报价由销售设定的成本、汇率、毛利口径计算，非系统推荐价。 • 任何标记 SIMULATED 的运杂费/保险费必须替换为真实报价后重算（见 10 表）。 • 出口关税、目的国进口关税与原产地优惠须单独核实，本表不自动假定为 0。
