Workbook
Name Lambda: '02_参数'!$C$5
Name LambdaLo: '02_参数'!$C$6
Name LambdaHi: '02_参数'!$C$7
Name OtherCost: '02_参数'!$C$8
Name AceticCoef: '02_参数'!$C$9
Name WinA: '02_参数'!$C$10
Name WinB: '02_参数'!$C$11
Name WinC: '02_参数'!$C$12
Name MinObs: '02_参数'!$C$13
Name Alpha: '02_参数'!$C$14

Sheet 00_说明
A1: PX × PTA 上下游价格联动研究 · 数据与计算工作簿
A2: 所有结果均为活公式；改动「02_参数」的 λ 或「03_原始数据」的价格，其余各表自动重算。
B4: 研究问题 | C4: PX（上游）与 PTA（下游）之间价格传导是否明显？哪些阶段出现背离？理论加工价差处于历史什么位置？是否存在可识别的领先/滞后？
B5: 产业关系 | C5: PTA 由 PX 液相空气氧化制得（醋酸为溶剂、Co-Mn-Br 催化），PX 是唯一主要原料，不存在第二条主要原料路线 → 允许做单耗折算加工价差。
B6: 数据源 | C6: 100ppi 生意社 PX/PTA 基准价（中文，2025-05-22 起）；SunSirs 日度现货价（英文站，可回溯 2023-01）。两源在重叠期逐日一致（差异 0 元/吨）。
B7: 价格口径 | C7: 元/吨，含增值税，华东现货基准价；同一机构同一口径，避免跨源拼接。
B8: 频率与样本 | C8: 日频；成对有效样本 N=869；区间 2023-10-08 ~ 2026-10-20。缺失日不插值，统计一律用成对有效样本。
B9: 发布时点 | C9: 生意社基准价于当日 08:30 发布，反映当日市场水平（发布滞后 0 天）；SunSirs 英文站页面日期为报道日，价格对应链接日期（滞后 1 天），已校正。
B10: 单耗来源 | C10: 0.655 t PX/t PTA：长江期货 2023-12-18；0.653：SCI99 2026-08-20；0.647~0.657：天风证券 2019-12-14 表 4 逐套装置。见「04_单耗台账」。
B11: 加工价差定义 | C11: Δ = PTA − λ×PX − 其他成本。λ 默认 0.655；「其他成本」= 醋酸贡献(≈0.032 t/t×醋酸价) + 动力 + 折旧的简化项，默认为 0，含义为「不含折旧与能源的收入型加工费」。
B12: 禁止事项 | C12: ① 不得把相关性表述为成本传导的因果证据；② 加工价差不等同企业利润；③ 不得给出交易建议/目标价；④ 单耗无出处时不得自造系数；⑤ 缺失不插值。
B13: 待补缺口 | C13: 醋酸价格序列未纳入（未取得可靠日频公开序列），故「其他成本」以参数形式暴露，默认 0 并在敏感性中说明；一体化装置的内部结算价与物流成本未剔除。

Sheet 01_口径与来源
A1: 口径与来源台账
A2: 每一条价格数据都必须能回答：什么品种/规格、哪个地区、含不含税、哪天发布、来自哪里。
A4: 序号 | B4: 口径项 | C4: 上游 PX | D4: 下游 PTA | E4: 是否一致 | F4: 处理方式 | G4: 数据来源 | H4: 发布时点 | I4: 备注
A5: 1 | B5: 品种/规格 | C5: 对二甲苯 PX，优等品 | D5: 精对苯二甲酸 PTA，优等品 | E5: 是 | F5: 按品种标准品取值 | G5: 生意社/ SunSirs | H5: 每日
A6: 2 | B6: 地区 | C6: 华东综合现货 | D6: 华东现货 | E6: 近似一致 | F6: 统一用华东口径，不做跨区拼价 | G6: 生意社/ SunSirs | H6: 每日 | I6: 跨区升贴水未剔除
A7: 3 | B7: 计量单位 | C7: 元/吨 | D7: 元/吨 | E7: 是 | F7: 无需换算 | G7: — | H7: —
A8: 4 | B8: 税费 | C8: 含增值税 | D8: 含增值税 | E8: 是 | F8: 税基相同，无需价税分离 | G8: — | H8: — | I8: 若一含税一不含税须先×1.13/1.09
A9: 5 | B9: 价格性质 | C9: 现货基准价 | D9: 现货基准价 | E9: 是 | F9: 不使用期货价格，避免基差混入 | G9: 生意社/ SunSirs | H9: 每日 08:30 | I9: 期货仅用于交叉验证
A10: 6 | B10: 频率 | C10: 日度 | D10: 日度 | E10: 是 | F10: 成对有效样本 | G10: — | H10: — | I10: 缺失不插值
A11: 7 | B11: 日期对齐 | C11: 价格口径日 | D11: 价格口径日 | E11: 是 | F11: 英文站滞后一天已校正 | G11: — | H11: — | I11: 错位会导致价差约 80 元/吨的系统偏差
A12: 8 | B12: 交叉校验 | C12: 两源重叠期逐日一致 | D12: 两源重叠期逐日一致 | E12: 是 | F12: 差异 0 元/吨，误差 0.00% | G12: 100ppi vs SunSirs | H12: — | I12: 见 12_公式说明 的校验方法

Sheet 02_参数
A1: 参数与命名区域
A2: 改这里，全表重算。λ 只有一个出处，禁止在各表重复写死。
A4: 参数 | B4: 名称 | C4: 取值 | D4: 单位 | E4: 来源/说明
A5: 单耗系数 λ | B5: Lambda | C5: 0.655 | D5: t PX/t PTA | E5: 长江期货 2023-12-18（行业通用 0.655）
A6: 单耗下限 | B6: LambdaLo | C6: 0.647 | D6: t PX/t PTA | E6: 天风证券 2019-12-14 表4：新凤鸣独山
A7: 单耗上限 | B7: LambdaHi | C7: 0.657 | D7: t PX/t PTA | E7: 天风证券 2019-12-14 表4：汉邦一期/桐昆嘉兴一期
A8: 其他成本 | B8: OtherCost | C8: 0 | D8: 元/吨 | E8: 醋酸+动力+折旧简化项；默认 0 = 仅收入型加工费
A9: 醋酸单耗 | B9: AceticCoef | C9: 0.032 | D9: t/t | E9: 天风证券表4（0.029~0.040）；SCI99 0.030~0.039
A10: 滚动窗口A | B10: WinA | C10: 20 | D10: 观测 | E10: 短期
A11: 滚动窗口B | B11: WinB | C11: 60 | D11: 观测 | E11: 主口径（报告 §5 默认）
A12: 滚动窗口C | B12: WinC | C12: 120 | D12: 观测 | E12: 中期
A13: 最小有效样本比 | B13: MinObs | C13: 0.8 | D13: 比例 | E13: 窗口内有效样本 < 80% 时不出数
A14: 显著水平 | B14: Alpha | C14: 0.05 | D14: — | E14: 双尾
A17: 阶段定义
A18: 阶段 | B18: 起始日 | C18: 结束日 | D18: 名称
A19: S1 | B19: 2023-10-07 | C19: 2024-12-31 | D19: PX扩能兑现+PTA过剩，加工费中枢下移
A20: S2 | B20: 2025-01-01 | C20: 2025-12-31 | D20: PX供给趋紧、PTA加工费走阔
A21: S3 | B21: 2026-01-01 | C21: 2026-10-20 | D21: PTA集中检修+地缘油价扰动

Sheet 03_原始数据
A1: 原始价格数据与派生列
A2: E/F/G/H 列为公式，改 PX/PTA 两列即全表联动。
N3: 阶段起点行 | O3: 阶段终点行
A4: 日期 | B4: PX 元/吨 | C4: PTA 元/吨 | D4: 区间涨跌 PX% | E4: 理论价差 | F4: PTA/PX | G4: PX 日收益 | H4: PTA 日收益
A5: 2023-10-08 | B5: 9500 | C5: 6013.64 | E5: =C5-Lambda*B5-OtherCost | F5: =C5/B5 | N5: 5 | O5: 328
A6: 2023-10-09 | B6: 9500 | C6: 5962.73 | E6: =C6-Lambda*B6-OtherCost | F6: =C6/B6 | G6: =B6/B5-1 | H6: =C6/C5-1 | N6: 329 | O6: 622
A7: 2023-10-10 | B7: 9100 | C7: 5961.82 | E7: =C7-Lambda*B7-OtherCost | F7: =C7/B7 | G7: =B7/B6-1 | H7: =C7/C6-1 | N7: 623 | O7: 873
A8: 2023-10-11 | B8: 9100 | C8: 5898 | E8: =C8-Lambda*B8-OtherCost | F8: =C8/B8 | G8: =B8/B7-1 | H8: =C8/C7-1
A9: 2023-10-12 | B9: 9100 | C9: 5854.5 | E9: =C9-Lambda*B9-OtherCost | F9: =C9/B9 | G9: =B9/B8-1 | H9: =C9/C8-1
A10: 2023-10-15 | B10: 9100 | C10: 5871 | E10: =C10-Lambda*B10-OtherCost | F10: =C10/B10 | G10: =B10/B9-1 | H10: =C10/C9-1
A11: 2023-10-16 | B11: 9100 | C11: 5870 | E11: =C11-Lambda*B11-OtherCost | F11: =C11/B11 | G11: =B11/B10-1 | H11: =C11/C10-1
A12: 2023-10-17 | B12: 9100 | C12: 5867.5 | E12: =C12-Lambda*B12-OtherCost | F12: =C12/B12 | G12: =B12/B11-1 | H12: =C12/C11-1
A13: 2023-10-18 | B13: 9100 | C13: 5856 | E13: =C13-Lambda*B13-OtherCost | F13: =C13/B13 | G13: =B13/B12-1 | H13: =C13/C12-1
A14: 2023-10-19 | B14: 9100 | C14: 5851 | E14: =C14-Lambda*B14-OtherCost | F14: =C14/B14 | G14: =B14/B13-1 | H14: =C14/C13-1
A15: 2023-10-22 | B15: 9100 | C15: 5851 | E15: =C15-Lambda*B15-OtherCost | F15: =C15/B15 | G15: =B15/B14-1 | H15: =C15/C14-1
A16: 2023-10-23 | B16: 9100 | C16: 5851 | E16: =C16-Lambda*B16-OtherCost | F16: =C16/B16 | G16: =B16/B15-1 | H16: =C16/C15-1
A17: 2023-10-24 | B17: 9100 | C17: 5851.5 | E17: =C17-Lambda*B17-OtherCost | F17: =C17/B17 | G17: =B17/B16-1 | H17: =C17/C16-1
A18: 2023-10-25 | B18: 9100 | C18: 5873 | E18: =C18-Lambda*B18-OtherCost | F18: =C18/B18 | G18: =B18/B17-1 | H18: =C18/C17-1
A19: 2023-10-26 | B19: 9100 | C19: 5875.5 | E19: =C19-Lambda*B19-OtherCost | F19: =C19/B19 | G19: =B19/B18-1 | H19: =C19/C18-1
... A873: 2026-10-20 | B873: 10500 | C873: 7054.5 | E873: =C873-Lambda*B873-OtherCost | F873: =C873/B873 | G873: =B873/B872-1 | H873: =C873/C872-1

Sheet 04_单耗台账
A1: 单耗台账：0.647~0.657 的出处
A2: 单耗是加工价差的唯一乘数，必须逐条可追溯；无出处不得使用。
A4: 序号 | B4: 装置/口径 | C4: PX 单耗 t/t | D4: 醋酸 t/t | E4: 高压蒸汽 t/t | F4: 电力 kWh/t | G4: 来源
A5: 1 | B5: 汉邦石化一期 | C5: 0.657 | D5: 0.036 | E5: 1.15 | F5: 26.4 | G5: 天风证券 2019-12-14 表4
A6: 2 | B6: 华彬石化 | C6: 0.654 | D6: 0.04 | E6: 1.04 | F6: 68.6 | G6: 同上
A7: 3 | B7: 恒力石化 1-3# | C7: 0.655 | D7: 0.036 | E7: 0.67 | F7: -17.8 | G7: 同上（电力为负＝副产外送）
A8: 4 | B8: 桐昆嘉兴一期 | C8: 0.657 | D8: 0.038 | E8: 0.76 | F8: 0 | G8: 同上
A9: 5 | B9: 汉邦石化二期 | C9: 0.654 | D9: 0.035 | E9: 0.6 | F9: 92.4 | G9: 同上
A10: 6 | B10: 桐昆嘉兴二期 | C10: 0.651 | D10: 0.033 | E10: 0.52 | F10: 0 | G10: 同上
A11: 7 | B11: 新凤鸣独山 | C11: 0.647 | D11: 0.032 | E11: 0.65 | F11: -25.1 | G11: 同上
A12: 8 | B12: 恒力石化 4-5#（P8+） | C12: 0.649 | D12: 0.029 | E12: 0.48 | F12: -100 | G12: 同上
A13: 9 | B13: 行业通用（估值口径） | C13: 0.655 | D13: 0.032 | G13: 长江期货 2023-12-18
A14: 10 | B14: SCI99 调研口径 | C14: 0.653 | D14: 0.035 | G14: SCI99 2026-08-20（醋酸 0.030~0.039）
A15: 11 | B15: 均值（1-8 行） | C15: =AVERAGE(C5:C12) | D15: =AVERAGE(D5:D12) | E15: =AVERAGE(E5:E12) | F15: =AVERAGE(F5:F12) | G15: 逐套装置算术平均
A16: 12 | B16: 极差（1-8 行） | C16: =MAX(C5:C12)-MIN(C5:C12) | D16: =MAX(D5:D12)-MIN(D5:D12) | E16: =MAX(E5:E12)-MIN(E5:E12) | G16: 单耗离散度：PX 仅 ±0.8%，说明单耗稳定

Sheet 05_单耗敏感性
A1: 单耗敏感性
A2: λ 每变动 0.001 t/t，价差水平整体平移约 PX 价格×0.001（元/吨）。
M3: 辅助：各 λ 下的价差序列（列＝λ，行＝日期观测）
A4: λ | B4: 价差均值 | C4: 价差中位 | D4: P10 | E4: P50 | F4: P90 | G4: 价差标准差 | H4: 与 λ=0.655 之差 | M4: 0.6 | N4: 0.605 | O4: 0.61 | P4: 0.615 | Q4: 0.62 | R4: 0.625 | S4: 0.63 | T4: 0.635 | U4: 0.64 | V4: 0.645 | W4: 0.65 | X4: 0.655 | Y4: 0.66 | Z4: 0.665 | AA4: 0.67 | AB4: 0.675 | AC4: 0.68 | AD4: 0.685 | AE4: 0.69 | AF4: 0.695 | AG4: 0.7
A5: 0.6 | B5: =AVERAGE($M$5:$M$873) | C5: =MEDIAN($M$5:$M$873) | D5: =_xlfn.PERCENTILE.INC($M$5:$M$873,0.1) | E5: =_xlfn.PERCENTILE.INC($M$5:$M$873,0.5) | F5: =_xlfn.PERCENTILE.INC($M$5:$M$873,0.9) | G5: =STDEV($M$5:$M$873) | H5: =B5-$B$16 | M5: ='03_原始数据'!C5-0.6*'03_原始数据'!B5-OtherCost | N5: ='03_原始数据'!C5-0.605*'03_原始数据'!B5-OtherCost | O5: ='03_原始数据'!C5-0.61*'03_原始数据'!B5-OtherCost | P5: ='03_原始数据'!C5-0.615*'03_原始数据'!B5-OtherCost | Q5: ='03_原始数据'!C5-0.62*'03_原始数据'!B5-OtherCost | R5: ='03_原始数据'!C5-0.625*'03_原始数据'!B5-OtherCost | S5: ='03_原始数据'!C5-0.63*'03_原始数据'!B5-OtherCost | T5: ='03_原始数据'!C5-0.635*'03_原始数据'!B5-OtherCost | U5: ='03_原始数据'!C5-0.64*'03_原始数据'!B5-OtherCost | V5: ='03_原始数据'!C5-0.645*'03_原始数据'!B5-OtherCost | W5: ='03_原始数据'!C5-0.65*'03_原始数据'!B5-OtherCost | X5: ='03_原始数据'!C5-0.655*'03_原始数据'!B5-OtherCost | Y5: ='03_原始数据'!C5-0.66*'03_原始数据'!B5-OtherCost | Z5: ='03_原始数据'!C5-0.665*'03_原始数据'!B5-OtherCost | AA5: ='03_原始数据'!C5-0.67*'03_原始数据'!B5-OtherCost | AB5: ='03_原始数据'!C5-0.675*'03_原始数据'!B5-OtherCost | AC5: ='03_原始数据'!C5-0.68*'03_原始数据'!B5-OtherCost | AD5: ='03_原始数据'!C5-0.685*'03_原始数据'!B5-OtherCost | AE5: ='03_原始数据'!C5-0.69*'03_原始数据'!B5-OtherCost | AF5: ='03_原始数据'!C5-0.695*'03_原始数据'!B5-OtherCost | AG5: ='03_原始数据'!C5-0.7*'03_原始数据'!B5-OtherCost
A6: 0.605 | B6: =AVERAGE($N$5:$N$873) | C6: =MEDIAN($N$5:$N$873) | D6: =_xlfn.PERCENTILE.INC($N$5:$N$873,0.1) | E6: =_xlfn.PERCENTILE.INC($N$5:$N$873,0.5) | F6: =_xlfn.PERCENTILE.INC($N$5:$N$873,0.9) | G6: =STDEV($N$5:$N$873) | H6: =B6-$B$16 | M6: ='03_原始数据'!C6-0.6*'03_原始数据'!B6-OtherCost | N6: ='03_原始数据'!C6-0.605*'03_原始数据'!B6-OtherCost | O6: ='03_原始数据'!C6-0.61*'03_原始数据'!B6-OtherCost | P6: ='03_原始数据'!C6-0.615*'03_原始数据'!B6-OtherCost | Q6: ='03_原始数据'!C6-0.62*'03_原始数据'!B6-OtherCost | R6: ='03_原始数据'!C6-0.625*'03_原始数据'!B6-OtherCost | S6: ='03_原始数据'!C6-0.63*'03_原始数据'!B6-OtherCost | T6: ='03_原始数据'!C6-0.635*'03_原始数据'!B6-OtherCost | U6: ='03_原始数据'!C6-0.64*'03_原始数据'!B6-OtherCost | V6: ='03_原始数据'!C6-0.645*'03_原始数据'!B6-OtherCost | W6: ='03_原始数据'!C6-0.65*'03_原始数据'!B6-OtherCost | X6: ='03_原始数据'!C6-0.655*'03_原始数据'!B6-OtherCost | Y6: ='03_原始数据'!C6-0.66*'03_原始数据'!B6-OtherCost | Z6: ='03_原始数据'!C6-0.665*'03_原始数据'!B6-OtherCost | AA6: ='03_原始数据'!C6-0.67*'03_原始数据'!B6-OtherCost | AB6: ='03_原始数据'!C6-0.675*'03_原始数据'!B6-OtherCost | AC6: ='03_原始数据'!C6-0.68*'03_原始数据'!B6-OtherCost | AD6: ='03_原始数据'!C6-0.685*'03_原始数据'!B6-OtherCost | AE6: ='03_原始数据'!C6-0.69*'03_原始数据'!B6-OtherCost | AF6: ='03_原始数据'!C6-0.695*'03_原始数据'!B6-OtherCost | AG6: ='03_原始数据'!C6-0.7*'03_原始数据'!B6-OtherCost
A7: 0.61 | B7: =AVERAGE($O$5:$O$873) | C7: =MEDIAN($O$5:$O$873) | D7: =_xlfn.PERCENTILE.INC($O$5:$O$873,0.1) | E7: =_xlfn.PERCENTILE.INC($O$5:$O$873,0.5) | F7: =_xlfn.PERCENTILE.INC($O$5:$O$873,0.9) | G7: =STDEV($O$5:$O$873) | H7: =B7-$B$16 | M7: ='03_原始数据'!C7-0.6*'03_原始数据'!B7-OtherCost | N7: ='03_原始数据'!C7-0.605*'03_原始数据'!B7-OtherCost | O7: ='03_原始数据'!C7-0.61*'03_原始数据'!B7-OtherCost | P7: ='03_原始数据'!C7-0.615*'03_原始数据'!B7-OtherCost | Q7: ='03_原始数据'!C7-0.62*'03_原始数据'!B7-OtherCost | R7: ='03_原始数据'!C7-0.625*'03_原始数据'!B7-OtherCost | S7: ='03_原始数据'!C7-0.63*'03_原始数据'!B7-OtherCost | T7: ='03_原始数据'!C7-0.635*'03_原始数据'!B7-OtherCost | U7: ='03_原始数据'!C7-0.64*'03_原始数据'!B7-OtherCost | V7: ='03_原始数据'!C7-0.645*'03_原始数据'!B7-OtherCost | W7: ='03_原始数据'!C7-0.65*'03_原始数据'!B7-OtherCost | X7: ='03_原始数据'!C7-0.655*'03_原始数据'!B7-OtherCost | Y7: ='03_原始数据'!C7-0.66*'03_原始数据'!B7-OtherCost | Z7: ='03_原始数据'!C7-0.665*'03_原始数据'!B7-OtherCost | AA7: ='03_原始数据'!C7-0.67*'03_原始数据'!B7-OtherCost | AB7: ='03_原始数据'!C7-0.675*'03_原始数据'!B7-OtherCost | AC7: ='03_原始数据'!C7-0.68*'03_原始数据'!B7-OtherCost | AD7: ='03_原始数据'!C7-0.685*'03_原始数据'!B7-OtherCost | AE7: ='03_原始数据'!C7-0.69*'03_原始数据'!B7-OtherCost | AF7: ='03_原始数据'!C7-0.695*'03_原始数据'!B7-OtherCost | AG7: ='03_原始数据'!C7-0.7*'03_原始数据'!B7-OtherCost
A8: 0.615 | B8: =AVERAGE($P$5:$P$873) | C8: =MEDIAN($P$5:$P$873) | D8: =_xlfn.PERCENTILE.INC($P$5:$P$873,0.1) | E8: =_xlfn.PERCENTILE.INC($P$5:$P$873,0.5) | F8: =_xlfn.PERCENTILE.INC($P$5:$P$873,0.9) | G8: =STDEV($P$5:$P$873) | H8: =B8-$B$16 | J8: 注：PERCENTILE.INC 与报告和 Python 的线性插值分位一致；PERCENTILE.EXC 会给出不同结果，勿混用。 | M8: ='03_原始数据'!C8-0.6*'03_原始数据'!B8-OtherCost | N8: ='03_原始数据'!C8-0.605*'03_原始数据'!B8-OtherCost | O8: ='03_原始数据'!C8-0.61*'03_原始数据'!B8-OtherCost | P8: ='03_原始数据'!C8-0.615*'03_原始数据'!B8-OtherCost | Q8: ='03_原始数据'!C8-0.62*'03_原始数据'!B8-OtherCost | R8: ='03_原始数据'!C8-0.625*'03_原始数据'!B8-OtherCost | S8: ='03_原始数据'!C8-0.63*'03_原始数据'!B8-OtherCost | T8: ='03_原始数据'!C8-0.635*'03_原始数据'!B8-OtherCost | U8: ='03_原始数据'!C8-0.64*'03_原始数据'!B8-OtherCost | V8: ='03_原始数据'!C8-0.645*'03_原始数据'!B8-OtherCost | W8: ='03_原始数据'!C8-0.65*'03_原始数据'!B8-OtherCost | X8: ='03_原始数据'!C8-0.655*'03_原始数据'!B8-OtherCost | Y8: ='03_原始数据'!C8-0.66*'03_原始数据'!B8-OtherCost | Z8: ='03_原始数据'!C8-0.665*'03_原始数据'!B8-OtherCost | AA8: ='03_原始数据'!C8-0.67*'03_原始数据'!B8-OtherCost | AB8: ='03_原始数据'!C8-0.675*'03_原始数据'!B8-OtherCost | AC8: ='03_原始数据'!C8-0.68*'03_原始数据'!B8-OtherCost | AD8: ='03_原始数据'!C8-0.685*'03_原始数据'!B8-OtherCost | AE8: ='03_原始数据'!C8-0.69*'03_原始数据'!B8-OtherCost | AF8: ='03_原始数据'!C8-0.695*'03_原始数据'!B8-OtherCost | AG8: ='03_原始数据'!C8-0.7*'03_原始数据'!B8-OtherCost
A9: 0.62 | B9: =AVERAGE($Q$5:$Q$873) | C9: =MEDIAN($Q$5:$Q$873) | D9: =_xlfn.PERCENTILE.INC($Q$5:$Q$873,0.1) | E9: =_xlfn.PERCENTILE.INC($Q$5:$Q$873,0.5) | F9: =_xlfn.PERCENTILE.INC($Q$5:$Q$873,0.9) | G9: =STDEV($Q$5:$Q$873) | H9: =B9-$B$16 | M9: ='03_原始数据'!C9-0.6*'03_原始数据'!B9-OtherCost | N9: ='03_原始数据'!C9-0.605*'03_原始数据'!B9-OtherCost | O9: ='03_原始数据'!C9-0.61*'03_原始数据'!B9-OtherCost | P9: ='03_原始数据'!C9-0.615*'03_原始数据'!B9-OtherCost | Q9: ='03_原始数据'!C9-0.62*'03_原始数据'!B9-OtherCost | R9: ='03_原始数据'!C9-0.625*'03_原始数据'!B9-OtherCost | S9: ='03_原始数据'!C9-0.63*'03_原始数据'!B9-OtherCost | T9: ='03_原始数据'!C9-0.635*'03_原始数据'!B9-OtherCost | U9: ='03_原始数据'!C9-0.64*'03_原始数据'!B9-OtherCost | V9: ='03_原始数据'!C9-0.645*'03_原始数据'!B9-OtherCost | W9: ='03_原始数据'!C9-0.65*'03_原始数据'!B9-OtherCost | X9: ='03_原始数据'!C9-0.655*'03_原始数据'!B9-OtherCost | Y9: ='03_原始数据'!C9-0.66*'03_原始数据'!B9-OtherCost | Z9: ='03_原始数据'!C9-0.665*'03_原始数据'!B9-OtherCost | AA9: ='03_原始数据'!C9-0.67*'03_原始数据'!B9-OtherCost | AB9: ='03_原始数据'!C9-0.675*'03_原始数据'!B9-OtherCost | AC9: ='03_原始数据'!C9-0.68*'03_原始数据'!B9-OtherCost | AD9: ='03_原始数据'!C9-0.685*'03_原始数据'!B9-OtherCost | AE9: ='03_原始数据'!C9-0.69*'03_原始数据'!B9-OtherCost | AF9: ='03_原始数据'!C9-0.695*'03_原始数据'!B9-OtherCost | AG9: ='03_原始数据'!C9-0.7*'03_原始数据'!B9-OtherCost
A10: 0.625 | B10: =AVERAGE($R$5:$R$873) | C10: =MEDIAN($R$5:$R$873) | D10: =_xlfn.PERCENTILE.INC($R$5:$R$873,0.1) | E10: =_xlfn.PERCENTILE.INC($R$5:$R$873,0.5) | F10: =_xlfn.PERCENTILE.INC($R$5:$R$873,0.9) | G10: =STDEV($R$5:$R$873) | H10: =B10-$B$16 | M10: ='03_原始数据'!C10-0.6*'03_原始数据'!B10-OtherCost | N10: ='03_原始数据'!C10-0.605*'03_原始数据'!B10-OtherCost | O10: ='03_原始数据'!C10-0.61*'03_原始数据'!B10-OtherCost | P10: ='03_原始数据'!C10-0.615*'03_原始数据'!B10-OtherCost | Q10: ='03_原始数据'!C10-0.62*'03_原始数据'!B10-OtherCost | R10: ='03_原始数据'!C10-0.625*'03_原始数据'!B10-OtherCost | S10: ='03_原始数据'!C10-0.63*'03_原始数据'!B10-OtherCost | T10: ='03_原始数据'!C10-0.635*'03_原始数据'!B10-OtherCost | U10: ='03_原始数据'!C10-0.64*'03_原始数据'!B10-OtherCost | V10: ='03_原始数据'!C10-0.645*'03_原始数据'!B10-OtherCost | W10: ='03_原始数据'!C10-0.65*'03_原始数据'!B10-OtherCost | X10: ='03_原始数据'!C10-0.655*'03_原始数据'!B10-OtherCost | Y10: ='03_原始数据'!C10-0.66*'03_原始数据'!B10-OtherCost | Z10: ='03_原始数据'!C10-0.665*'03_原始数据'!B10-OtherCost | AA10: ='03_原始数据'!C10-0.67*'03_原始数据'!B10-OtherCost | AB10: ='03_原始数据'!C10-0.675*'03_原始数据'!B10-OtherCost | AC10: ='03_原始数据'!C10-0.68*'03_原始数据'!B10-OtherCost | AD10: ='03_原始数据'!C10-0.685*'03_原始数据'!B10-OtherCost | AE10: ='03_原始数据'!C10-0.69*'03_原始数据'!B10-OtherCost | AF10: ='03_原始数据'!C10-0.695*'03_原始数据'!B10-OtherCost | AG10: ='03_原始数据'!C10-0.7*'03_原始数据'!B10-OtherCost
A11: 0.63 | B11: =AVERAGE($S$5:$S$873) | C11: =MEDIAN($S$5:$S$873) | D11: =_xlfn.PERCENTILE.INC($S$5:$S$873,0.1) | E11: =_xlfn.PERCENTILE.INC($S$5:$S$873,0.5) | F11: =_xlfn.PERCENTILE.INC($S$5:$S$873,0.9) | G11: =STDEV($S$5:$S$873) | H11: =B11-$B$16 | M11: ='03_原始数据'!C11-0.6*'03_原始数据'!B11-OtherCost | N11: ='03_原始数据'!C11-0.605*'03_原始数据'!B11-OtherCost | O11: ='03_原始数据'!C11-0.61*'03_原始数据'!B11-OtherCost | P11: ='03_原始数据'!C11-0.615*'03_原始数据'!B11-OtherCost | Q11: ='03_原始数据'!C11-0.62*'03_原始数据'!B11-OtherCost | R11: ='03_原始数据'!C11-0.625*'03_原始数据'!B11-OtherCost | S11: ='03_原始数据'!C11-0.63*'03_原始数据'!B11-OtherCost | T11: ='03_原始数据'!C11-0.635*'03_原始数据'!B11-OtherCost | U11: ='03_原始数据'!C11-0.64*'03_原始数据'!B11-OtherCost | V11: ='03_原始数据'!C11-0.645*'03_原始数据'!B11-OtherCost | W11: ='03_原始数据'!C11-0.65*'03_原始数据'!B11-OtherCost | X11: ='03_原始数据'!C11-0.655*'03_原始数据'!B11-OtherCost | Y11: ='03_原始数据'!C11-0.66*'03_原始数据'!B11-OtherCost | Z11: ='03_原始数据'!C11-0.665*'03_原始数据'!B11-OtherCost | AA11: ='03_原始数据'!C11-0.67*'03_原始数据'!B11-OtherCost | AB11: ='03_原始数据'!C11-0.675*'03_原始数据'!B11-OtherCost | AC11: ='03_原始数据'!C11-0.68*'03_原始数据'!B11-OtherCost | AD11: ='03_原始数据'!C11-0.685*'03_原始数据'!B11-OtherCost | AE11: ='03_原始数据'!C11-0.69*'03_原始数据'!B11-OtherCost | AF11: ='03_原始数据'!C11-0.695*'03_原始数据'!B11-OtherCost | AG11: ='03_原始数据'!C11-0.7*'03_原始数据'!B11-OtherCost
A12: 0.635 | B12: =AVERAGE($T$5:$T$873) | C12: =MEDIAN($T$5:$T$873) | D12: =_xlfn.PERCENTILE.INC($T$5:$T$873,0.1) | E12: =_xlfn.PERCENTILE.INC($T$5:$T$873,0.5) | F12: =_xlfn.PERCENTILE.INC($T$5:$T$873,0.9) | G12: =STDEV($T$5:$T$873) | H12: =B12-$B$16 | M12: ='03_原始数据'!C12-0.6*'03_原始数据'!B12-OtherCost | N12: ='03_原始数据'!C12-0.605*'03_原始数据'!B12-OtherCost | O12: ='03_原始数据'!C12-0.61*'03_原始数据'!B12-OtherCost | P12: ='03_原始数据'!C12-0.615*'03_原始数据'!B12-OtherCost | Q12: ='03_原始数据'!C12-0.62*'03_原始数据'!B12-OtherCost | R12: ='03_原始数据'!C12-0.625*'03_原始数据'!B12-OtherCost | S12: ='03_原始数据'!C12-0.63*'03_原始数据'!B12-OtherCost | T12: ='03_原始数据'!C12-0.635*'03_原始数据'!B12-OtherCost | U12: ='03_原始数据'!C12-0.64*'03_原始数据'!B12-OtherCost | V12: ='03_原始数据'!C12-0.645*'03_原始数据'!B12-OtherCost | W12: ='03_原始数据'!C12-0.65*'03_原始数据'!B12-OtherCost | X12: ='03_原始数据'!C12-0.655*'03_原始数据'!B12-OtherCost | Y12: ='03_原始数据'!C12-0.66*'03_原始数据'!B12-OtherCost | Z12: ='03_原始数据'!C12-0.665*'03_原始数据'!B12-OtherCost | AA12: ='03_原始数据'!C12-0.67*'03_原始数据'!B12-OtherCost | AB12: ='03_原始数据'!C12-0.675*'03_原始数据'!B12-OtherCost | AC12: ='03_原始数据'!C12-0.68*'03_原始数据'!B12-OtherCost | AD12: ='03_原始数据'!C12-0.685*'03_原始数据'!B12-OtherCost | AE12: ='03_原始数据'!C12-0.69*'03_原始数据'!B12-OtherCost | AF12: ='03_原始数据'!C12-0.695*'03_原始数据'!B12-OtherCost | AG12: ='03_原始数据'!C12-0.7*'03_原始数据'!B12-OtherCost
A13: 0.64 | B13: =AVERAGE($U$5:$U$873) | C13: =MEDIAN($U$5:$U$873) | D13: =_xlfn.PERCENTILE.INC($U$5:$U$873,0.1) | E13: =_xlfn.PERCENTILE.INC($U$5:$U$873,0.5) | F13: =_xlfn.PERCENTILE.INC($U$5:$U$873,0.9) | G13: =STDEV($U$5:$U$873) | H13: =B13-$B$16 | M13: ='03_原始数据'!C13-0.6*'03_原始数据'!B13-OtherCost | N13: ='03_原始数据'!C13-0.605*'03_原始数据'!B13-OtherCost | O13: ='03_原始数据'!C13-0.61*'03_原始数据'!B13-OtherCost | P13: ='03_原始数据'!C13-0.615*'03_原始数据'!B13-OtherCost | Q13: ='03_原始数据'!C13-0.62*'03_原始数据'!B13-OtherCost | R13: ='03_原始数据'!C13-0.625*'03_原始数据'!B13-OtherCost | S13: ='03_原始数据'!C13-0.63*'03_原始数据'!B13-OtherCost | T13: ='03_原始数据'!C13-0.635*'03_原始数据'!B13-OtherCost | U13: ='03_原始数据'!C13-0.64*'03_原始数据'!B13-OtherCost | V13: ='03_原始数据'!C13-0.645*'03_原始数据'!B13-OtherCost | W13: ='03_原始数据'!C13-0.65*'03_原始数据'!B13-OtherCost | X13: ='03_原始数据'!C13-0.655*'03_原始数据'!B13-OtherCost | Y13: ='03_原始数据'!C13-0.66*'03_原始数据'!B13-OtherCost | Z13: ='03_原始数据'!C13-0.665*'03_原始数据'!B13-OtherCost | AA13: ='03_原始数据'!C13-0.67*'03_原始数据'!B13-OtherCost | AB13: ='03_原始数据'!C13-0.675*'03_原始数据'!B13-OtherCost | AC13: ='03_原始数据'!C13-0.68*'03_原始数据'!B13-OtherCost | AD13: ='03_原始数据'!C13-0.685*'03_原始数据'!B13-OtherCost | AE13: ='03_原始数据'!C13-0.69*'03_原始数据'!B13-OtherCost | AF13: ='03_原始数据'!C13-0.695*'03_原始数据'!B13-OtherCost | AG13: ='03_原始数据'!C13-0.7*'03_原始数据'!B13-OtherCost
A14: 0.645 | B14: =AVERAGE($V$5:$V$873) | C14: =MEDIAN($V$5:$V$873) | D14: =_xlfn.PERCENTILE.INC($V$5:$V$873,0.1) | E14: =_xlfn.PERCENTILE.INC($V$5:$V$873,0.5) | F14: =_xlfn.PERCENTILE.INC($V$5:$V$873,0.9) | G14: =STDEV($V$5:$V$873) | H14: =B14-$B$16 | M14: ='03_原始数据'!C14-0.6*'03_原始数据'!B14-OtherCost | N14: ='03_原始数据'!C14-0.605*'03_原始数据'!B14-OtherCost | O14: ='03_原始数据'!C14-0.61*'03_原始数据'!B14-OtherCost | P14: ='03_原始数据'!C14-0.615*'03_原始数据'!B14-OtherCost | Q14: ='03_原始数据'!C14-0.62*'03_原始数据'!B14-OtherCost | R14: ='03_原始数据'!C14-0.625*'03_原始数据'!B14-OtherCost | S14: ='03_原始数据'!C14-0.63*'03_原始数据'!B14-OtherCost | T14: ='03_原始数据'!C14-0.635*'03_原始数据'!B14-OtherCost | U14: ='03_原始数据'!C14-0.64*'03_原始数据'!B14-OtherCost | V14: ='03_原始数据'!C14-0.645*'03_原始数据'!B14-OtherCost | W14: ='03_原始数据'!C14-0.65*'03_原始数据'!B14-OtherCost | X14: ='03_原始数据'!C14-0.655*'03_原始数据'!B14-OtherCost | Y14: ='03_原始数据'!C14-0.66*'03_原始数据'!B14-OtherCost | Z14: ='03_原始数据'!C14-0.665*'03_原始数据'!B14-OtherCost | AA14: ='03_原始数据'!C14-0.67*'03_原始数据'!B14-OtherCost | AB14: ='03_原始数据'!C14-0.675*'03_原始数据'!B14-OtherCost | AC14: ='03_原始数据'!C14-0.68*'03_原始数据'!B14-OtherCost | AD14: ='03_原始数据'!C14-0.685*'03_原始数据'!B14-OtherCost | AE14: ='03_原始数据'!C14-0.69*'03_原始数据'!B14-OtherCost | AF14: ='03_原始数据'!C14-0.695*'03_原始数据'!B14-OtherCost | AG14: ='03_原始数据'!C14-0.7*'03_原始数据'!B14-OtherCost
A15: 0.65 | B15: =AVERAGE($W$5:$W$873) | C15: =MEDIAN($W$5:$W$873) | D15: =_xlfn.PERCENTILE.INC($W$5:$W$873,0.1) | E15: =_xlfn.PERCENTILE.INC($W$5:$W$873,0.5) | F15: =_xlfn.PERCENTILE.INC($W$5:$W$873,0.9) | G15: =STDEV($W$5:$W$873) | H15: =B15-$B$16 | M15: ='03_原始数据'!C15-0.6*'03_原始数据'!B15-OtherCost | N15: ='03_原始数据'!C15-0.605*'03_原始数据'!B15-OtherCost | O15: ='03_原始数据'!C15-0.61*'03_原始数据'!B15-OtherCost | P15: ='03_原始数据'!C15-0.615*'03_原始数据'!B15-OtherCost | Q15: ='03_原始数据'!C15-0.62*'03_原始数据'!B15-OtherCost | R15: ='03_原始数据'!C15-0.625*'03_原始数据'!B15-OtherCost | S15: ='03_原始数据'!C15-0.63*'03_原始数据'!B15-OtherCost | T15: ='03_原始数据'!C15-0.635*'03_原始数据'!B15-OtherCost | U15: ='03_原始数据'!C15-0.64*'03_原始数据'!B15-OtherCost | V15: ='03_原始数据'!C15-0.645*'03_原始数据'!B15-OtherCost | W15: ='03_原始数据'!C15-0.65*'03_原始数据'!B15-OtherCost | X15: ='03_原始数据'!C15-0.655*'03_原始数据'!B15-OtherCost | Y15: ='03_原始数据'!C15-0.66*'03_原始数据'!B15-OtherCost | Z15: ='03_原始数据'!C15-0.665*'03_原始数据'!B15-OtherCost | AA15: ='03_原始数据'!C15-0.67*'03_原始数据'!B15-OtherCost | AB15: ='03_原始数据'!C15-0.675*'03_原始数据'!B15-OtherCost | AC15: ='03_原始数据'!C15-0.68*'03_原始数据'!B15-OtherCost | AD15: ='03_原始数据'!C15-0.685*'03_原始数据'!B15-OtherCost | AE15: ='03_原始数据'!C15-0.69*'03_原始数据'!B15-OtherCost | AF15: ='03_原始数据'!C15-0.695*'03_原始数据'!B15-OtherCost | AG15: ='03_原始数据'!C15-0.7*'03_原始数据'!B15-OtherCost
A16: 0.655 | B16: =AVERAGE($X$5:$X$873) | C16: =MEDIAN($X$5:$X$873) | D16: =_xlfn.PERCENTILE.INC($X$5:$X$873,0.1) | E16: =_xlfn.PERCENTILE.INC($X$5:$X$873,0.5) | F16: =_xlfn.PERCENTILE.INC($X$5:$X$873,0.9) | G16: =STDEV($X$5:$X$873) | H16: =B16-$B$16 | M16: ='03_原始数据'!C16-0.6*'03_原始数据'!B16-OtherCost | N16: ='03_原始数据'!C16-0.605*'03_原始数据'!B16-OtherCost | O16: ='03_原始数据'!C16-0.61*'03_原始数据'!B16-OtherCost | P16: ='03_原始数据'!C16-0.615*'03_原始数据'!B16-OtherCost | Q16: ='03_原始数据'!C16-0.62*'03_原始数据'!B16-OtherCost | R16: ='03_原始数据'!C16-0.625*'03_原始数据'!B16-OtherCost | S16: ='03_原始数据'!C16-0.63*'03_原始数据'!B16-OtherCost | T16: ='03_原始数据'!C16-0.635*'03_原始数据'!B16-OtherCost | U16: ='03_原始数据'!C16-0.64*'03_原始数据'!B16-OtherCost | V16: ='03_原始数据'!C16-0.645*'03_原始数据'!B16-OtherCost | W16: ='03_原始数据'!C16-0.65*'03_原始数据'!B16-OtherCost | X16: ='03_原始数据'!C16-0.655*'03_原始数据'!B16-OtherCost | Y16: ='03_原始数据'!C16-0.66*'03_原始数据'!B16-OtherCost | Z16: ='03_原始数据'!C16-0.665*'03_原始数据'!B16-OtherCost | AA16: ='03_原始数据'!C16-0.67*'03_原始数据'!B16-OtherCost | AB16: ='03_原始数据'!C16-0.675*'03_原始数据'!B16-OtherCost | AC16: ='03_原始数据'!C16-0.68*'03_原始数据'!B16-OtherCost | AD16: ='03_原始数据'!C16-0.685*'03_原始数据'!B16-OtherCost | AE16: ='03_原始数据'!C16-0.69*'03_原始数据'!B16-OtherCost | AF16: ='03_原始数据'!C16-0.695*'03_原始数据'!B16-OtherCost | AG16: ='03_原始数据'!C16-0.7*'03_原始数据'!B16-OtherCost
A17: 0.66 | B17: =AVERAGE($Y$5:$Y$873) | C17: =MEDIAN($Y$5:$Y$873) | D17: =_xlfn.PERCENTILE.INC($Y$5:$Y$873,0.1) | E17: =_xlfn.PERCENTILE.INC($Y$5:$Y$873,0.5) | F17: =_xlfn.PERCENTILE.INC($Y$5:$Y$873,0.9) | G17: =STDEV($Y$5:$Y$873) | H17: =B17-$B$16 | M17: ='03_原始数据'!C17-0.6*'03_原始数据'!B17-OtherCost | N17: ='03_原始数据'!C17-0.605*'03_原始数据'!B17-OtherCost | O17: ='03_原始数据'!C17-0.61*'03_原始数据'!B17-OtherCost | P17: ='03_原始数据'!C17-0.615*'03_原始数据'!B17-OtherCost | Q17: ='03_原始数据'!C17-0.62*'03_原始数据'!B17-OtherCost | R17: ='03_原始数据'!C17-0.625*'03_原始数据'!B17-OtherCost | S17: ='03_原始数据'!C17-0.63*'03_原始数据'!B17-OtherCost | T17: ='03_原始数据'!C17-0.635*'03_原始数据'!B17-OtherCost | U17: ='03_原始数据'!C17-0.64*'03_原始数据'!B17-OtherCost | V17: ='03_原始数据'!C17-0.645*'03_原始数据'!B17-OtherCost | W17: ='03_原始数据'!C17-0.65*'03_原始数据'!B17-OtherCost | X17: ='03_原始数据'!C17-0.655*'03_原始数据'!B17-OtherCost | Y17: ='03_原始数据'!C17-0.66*'03_原始数据'!B17-OtherCost | Z17: ='03_原始数据'!C17-0.665*'03_原始数据'!B17-OtherCost | AA17: ='03_原始数据'!C17-0.67*'03_原始数据'!B17-OtherCost | AB17: ='03_原始数据'!C17-0.675*'03_原始数据'!B17-OtherCost | AC17: ='03_原始数据'!C17-0.68*'03_原始数据'!B17-OtherCost | AD17: ='03_原始数据'!C17-0.685*'03_原始数据'!B17-OtherCost | AE17: ='03_原始数据'!C17-0.69*'03_原始数据'!B17-OtherCost | AF17: ='03_原始数据'!C17-0.695*'03_原始数据'!B17-OtherCost | AG17: ='03_原始数据'!C17-0.7*'03_原始数据'!B17-OtherCost
A18: 0.665 | B18: =AVERAGE($Z$5:$Z$873) | C18: =MEDIAN($Z$5:$Z$873) | D18: =_xlfn.PERCENTILE.INC($Z$5:$Z$873,0.1) | E18: =_xlfn.PERCENTILE.INC($Z$5:$Z$873,0.5) | F18: =_xlfn.PERCENTILE.INC($Z$5:$Z$873,0.9) | G18: =STDEV($Z$5:$Z$873) | H18: =B18-$B$16 | M18: ='03_原始数据'!C18-0.6*'03_原始数据'!B18-OtherCost | N18: ='03_原始数据'!C18-0.605*'03_原始数据'!B18-OtherCost | O18: ='03_原始数据'!C18-0.61*'03_原始数据'!B18-OtherCost | P18: ='03_原始数据'!C18-0.615*'03_原始数据'!B18-OtherCost | Q18: ='03_原始数据'!C18-0.62*'03_原始数据'!B18-OtherCost | R18: ='03_原始数据'!C18-0.625*'03_原始数据'!B18-OtherCost | S18: ='03_原始数据'!C18-0.63*'03_原始数据'!B18-OtherCost | T18: ='03_原始数据'!C18-0.635*'03_原始数据'!B18-OtherCost | U18: ='03_原始数据'!C18-0.64*'03_原始数据'!B18-OtherCost | V18: ='03_原始数据'!C18-0.645*'03_原始数据'!B18-OtherCost | W18: ='03_原始数据'!C18-0.65*'03_原始数据'!B18-OtherCost | X18: ='03_原始数据'!C18-0.655*'03_原始数据'!B18-OtherCost | Y18: ='03_原始数据'!C18-0.66*'03_原始数据'!B18-OtherCost | Z18: ='03_原始数据'!C18-0.665*'03_原始数据'!B18-OtherCost | AA18: ='03_原始数据'!C18-0.67*'03_原始数据'!B18-OtherCost | AB18: ='03_原始数据'!C18-0.675*'03_原始数据'!B18-OtherCost | AC18: ='03_原始数据'!C18-0.68*'03_原始数据'!B18-OtherCost | AD18: ='03_原始数据'!C18-0.685*'03_原始数据'!B18-OtherCost | AE18: ='03_原始数据'!C18-0.69*'03_原始数据'!B18-OtherCost | AF18: ='03_原始数据'!C18-0.695*'03_原始数据'!B18-OtherCost | AG18: ='03_原始数据'!C18-0.7*'03_原始数据'!B18-OtherCost
A19: 0.67 | B19: =AVERAGE($AA$5:$AA$873) | C19: =MEDIAN($AA$5:$AA$873) | D19: =_xlfn.PERCENTILE.INC($AA$5:$AA$873,0.1) | E19: =_xlfn.PERCENTILE.INC($AA$5:$AA$873,0.5) | F19: =_xlfn.PERCENTILE.INC($AA$5:$AA$873,0.9) | G19: =STDEV($AA$5:$AA$873) | H19: =B19-$B$16 | M19: ='03_原始数据'!C19-0.6*'03_原始数据'!B19-OtherCost | N19: ='03_原始数据'!C19-0.605*'03_原始数据'!B19-OtherCost | O19: ='03_原始数据'!C19-0.61*'03_原始数据'!B19-OtherCost | P19: ='03_原始数据'!C19-0.615*'03_原始数据'!B19-OtherCost | Q19: ='03_原始数据'!C19-0.62*'03_原始数据'!B19-OtherCost | R19: ='03_原始数据'!C19-0.625*'03_原始数据'!B19-OtherCost | S19: ='03_原始数据'!C19-0.63*'03_原始数据'!B19-OtherCost | T19: ='03_原始数据'!C19-0.635*'03_原始数据'!B19-OtherCost | U19: ='03_原始数据'!C19-0.64*'03_原始数据'!B19-OtherCost | V19: ='03_原始数据'!C19-0.645*'03_原始数据'!B19-OtherCost | W19: ='03_原始数据'!C19-0.65*'03_原始数据'!B19-OtherCost | X19: ='03_原始数据'!C19-0.655*'03_原始数据'!B19-OtherCost | Y19: ='03_原始数据'!C19-0.66*'03_原始数据'!B19-OtherCost | Z19: ='03_原始数据'!C19-0.665*'03_原始数据'!B19-OtherCost | AA19: ='03_原始数据'!C19-0.67*'03_原始数据'!B19-OtherCost | AB19: ='03_原始数据'!C19-0.675*'03_原始数据'!B19-OtherCost | AC19: ='03_原始数据'!C19-0.68*'03_原始数据'!B19-OtherCost | AD19: ='03_原始数据'!C19-0.685*'03_原始数据'!B19-OtherCost | AE19: ='03_原始数据'!C19-0.69*'03_原始数据'!B19-OtherCost | AF19: ='03_原始数据'!C19-0.695*'03_原始数据'!B19-OtherCost | AG19: ='03_原始数据'!C19-0.7*'03_原始数据'!B19-OtherCost
A20: 0.675 | B20: =AVERAGE($AB$5:$AB$873) | C20: =MEDIAN($AB$5:$AB$873) | D20: =_xlfn.PERCENTILE.INC($AB$5:$AB$873,0.1) | E20: =_xlfn.PERCENTILE.INC($AB$5:$AB$873,0.5) | F20: =_xlfn.PERCENTILE.INC($AB$5:$AB$873,0.9) | G20: =STDEV($AB$5:$AB$873) | H20: =B20-$B$16 | M20: ='03_原始数据'!C20-0.6*'03_原始数据'!B20-OtherCost | N20: ='03_原始数据'!C20-0.605*'03_原始数据'!B20-OtherCost | O20: ='03_原始数据'!C20-0.61*'03_原始数据'!B20-OtherCost | P20: ='03_原始数据'!C20-0.615*'03_原始数据'!B20-OtherCost | Q20: ='03_原始数据'!C20-0.62*'03_原始数据'!B20-OtherCost | R20: ='03_原始数据'!C20-0.625*'03_原始数据'!B20-OtherCost | S20: ='03_原始数据'!C20-0.63*'03_原始数据'!B20-OtherCost | T20: ='03_原始数据'!C20-0.635*'03_原始数据'!B20-OtherCost | U20: ='03_原始数据'!C20-0.64*'03_原始数据'!B20-OtherCost | V20: ='03_原始数据'!C20-0.645*'03_原始数据'!B20-OtherCost | W20: ='03_原始数据'!C20-0.65*'03_原始数据'!B20-OtherCost | X20: ='03_原始数据'!C20-0.655*'03_原始数据'!B20-OtherCost | Y20: ='03_原始数据'!C20-0.66*'03_原始数据'!B20-OtherCost | Z20: ='03_原始数据'!C20-0.665*'03_原始数据'!B20-OtherCost | AA20: ='03_原始数据'!C20-0.67*'03_原始数据'!B20-OtherCost | AB20: ='03_原始数据'!C20-0.675*'03_原始数据'!B20-OtherCost | AC20: ='03_原始数据'!C20-0.68*'03_原始数据'!B20-OtherCost | AD20: ='03_原始数据'!C20-0.685*'03_原始数据'!B20-OtherCost | AE20: ='03_原始数据'!C20-0.69*'03_原始数据'!B20-OtherCost | AF20: ='03_原始数据'!C20-0.695*'03_原始数据'!B20-OtherCost | AG20: ='03_原始数据'!C20-0.7*'03_原始数据'!B20-OtherCost
A21: 0.68 | B21: =AVERAGE($AC$5:$AC$873) | C21: =MEDIAN($AC$5:$AC$873) | D21: =_xlfn.PERCENTILE.INC($AC$5:$AC$873,0.1) | E21: =_xlfn.PERCENTILE.INC($AC$5:$AC$873,0.5) | F21: =_xlfn.PERCENTILE.INC($AC$5:$AC$873,0.9) | G21: =STDEV($AC$5:$AC$873) | H21: =B21-$B$16 | M21: ='03_原始数据'!C21-0.6*'03_原始数据'!B21-OtherCost | N21: ='03_原始数据'!C21-0.605*'03_原始数据'!B21-OtherCost | O21: ='03_原始数据'!C21-0.61*'03_原始数据'!B21-OtherCost | P21: ='03_原始数据'!C21-0.615*'03_原始数据'!B21-OtherCost | Q21: ='03_原始数据'!C21-0.62*'03_原始数据'!B21-OtherCost | R21: ='03_原始数据'!C21-0.625*'03_原始数据'!B21-OtherCost | S21: ='03_原始数据'!C21-0.63*'03_原始数据'!B21-OtherCost | T21: ='03_原始数据'!C21-0.635*'03_原始数据'!B21-OtherCost | U21: ='03_原始数据'!C21-0.64*'03_原始数据'!B21-OtherCost | V21: ='03_原始数据'!C21-0.645*'03_原始数据'!B21-OtherCost | W21: ='03_原始数据'!C21-0.65*'03_原始数据'!B21-OtherCost | X21: ='03_原始数据'!C21-0.655*'03_原始数据'!B21-OtherCost | Y21: ='03_原始数据'!C21-0.66*'03_原始数据'!B21-OtherCost | Z21: ='03_原始数据'!C21-0.665*'03_原始数据'!B21-OtherCost | AA21: ='03_原始数据'!C21-0.67*'03_原始数据'!B21-OtherCost | AB21: ='03_原始数据'!C21-0.675*'03_原始数据'!B21-OtherCost | AC21: ='03_原始数据'!C21-0.68*'03_原始数据'!B21-OtherCost | AD21: ='03_原始数据'!C21-0.685*'03_原始数据'!B21-OtherCost | AE21: ='03_原始数据'!C21-0.69*'03_原始数据'!B21-OtherCost | AF21: ='03_原始数据'!C21-0.695*'03_原始数据'!B21-OtherCost | AG21: ='03_原始数据'!C21-0.7*'03_原始数据'!B21-OtherCost
A22: 0.685 | B22: =AVERAGE($AD$5:$AD$873) | C22: =MEDIAN($AD$5:$AD$873) | D22: =_xlfn.PERCENTILE.INC($AD$5:$AD$873,0.1) | E22: =_xlfn.PERCENTILE.INC($AD$5:$AD$873,0.5) | F22: =_xlfn.PERCENTILE.INC($AD$5:$AD$873,0.9) | G22: =STDEV($AD$5:$AD$873) | H22: =B22-$B$16 | M22: ='03_原始数据'!C22-0.6*'03_原始数据'!B22-OtherCost | N22: ='03_原始数据'!C22-0.605*'03_原始数据'!B22-OtherCost | O22: ='03_原始数据'!C22-0.61*'03_原始数据'!B22-OtherCost | P22: ='03_原始数据'!C22-0.615*'03_原始数据'!B22-OtherCost | Q22: ='03_原始数据'!C22-0.62*'03_原始数据'!B22-OtherCost | R22: ='03_原始数据'!C22-0.625*'03_原始数据'!B22-OtherCost | S22: ='03_原始数据'!C22-0.63*'03_原始数据'!B22-OtherCost | T22: ='03_原始数据'!C22-0.635*'03_原始数据'!B22-OtherCost | U22: ='03_原始数据'!C22-0.64*'03_原始数据'!B22-OtherCost | V22: ='03_原始数据'!C22-0.645*'03_原始数据'!B22-OtherCost | W22: ='03_原始数据'!C22-0.65*'03_原始数据'!B22-OtherCost | X22: ='03_原始数据'!C22-0.655*'03_原始数据'!B22-OtherCost | Y22: ='03_原始数据'!C22-0.66*'03_原始数据'!B22-OtherCost | Z22: ='03_原始数据'!C22-0.665*'03_原始数据'!B22-OtherCost | AA22: ='03_原始数据'!C22-0.67*'03_原始数据'!B22-OtherCost | AB22: ='03_原始数据'!C22-0.675*'03_原始数据'!B22-OtherCost | AC22: ='03_原始数据'!C22-0.68*'03_原始数据'!B22-OtherCost | AD22: ='03_原始数据'!C22-0.685*'03_原始数据'!B22-OtherCost | AE22: ='03_原始数据'!C22-0.69*'03_原始数据'!B22-OtherCost | AF22: ='03_原始数据'!C22-0.695*'03_原始数据'!B22-OtherCost | AG22: ='03_原始数据'!C22-0.7*'03_原始数据'!B22-OtherCost
A23: 0.69 | B23: =AVERAGE($AE$5:$AE$873) | C23: =MEDIAN($AE$5:$AE$873) | D23: =_xlfn.PERCENTILE.INC($AE$5:$AE$873,0.1) | E23: =_xlfn.PERCENTILE.INC($AE$5:$AE$873,0.5) | F23: =_xlfn.PERCENTILE.INC($AE$5:$AE$873,0.9) | G23: =STDEV($AE$5:$AE$873) | H23: =B23-$B$16 | M23: ='03_原始数据'!C23-0.6*'03_原始数据'!B23-OtherCost | N23: ='03_原始数据'!C23-0.605*'03_原始数据'!B23-OtherCost | O23: ='03_原始数据'!C23-0.61*'03_原始数据'!B23-OtherCost | P23: ='03_原始数据'!C23-0.615*'03_原始数据'!B23-OtherCost | Q23: ='03_原始数据'!C23-0.62*'03_原始数据'!B23-OtherCost | R23: ='03_原始数据'!C23-0.625*'03_原始数据'!B23-OtherCost | S23: ='03_原始数据'!C23-0.63*'03_原始数据'!B23-OtherCost | T23: ='03_原始数据'!C23-0.635*'03_原始数据'!B23-OtherCost | U23: ='03_原始数据'!C23-0.64*'03_原始数据'!B23-OtherCost | V23: ='03_原始数据'!C23-0.645*'03_原始数据'!B23-OtherCost | W23: ='03_原始数据'!C23-0.65*'03_原始数据'!B23-OtherCost | X23: ='03_原始数据'!C23-0.655*'03_原始数据'!B23-OtherCost | Y23: ='03_原始数据'!C23-0.66*'03_原始数据'!B23-OtherCost | Z23: ='03_原始数据'!C23-0.665*'03_原始数据'!B23-OtherCost | AA23: ='03_原始数据'!C23-0.67*'03_原始数据'!B23-OtherCost | AB23: ='03_原始数据'!C23-0.675*'03_原始数据'!B23-OtherCost | AC23: ='03_原始数据'!C23-0.68*'03_原始数据'!B23-OtherCost | AD23: ='03_原始数据'!C23-0.685*'03_原始数据'!B23-OtherCost | AE23: ='03_原始数据'!C23-0.69*'03_原始数据'!B23-OtherCost | AF23: ='03_原始数据'!C23-0.695*'03_原始数据'!B23-OtherCost | AG23: ='03_原始数据'!C23-0.7*'03_原始数据'!B23-OtherCost
A24: 0.695 | B24: =AVERAGE($AF$5:$AF$873) | C24: =MEDIAN($AF$5:$AF$873) | D24: =_xlfn.PERCENTILE.INC($AF$5:$AF$873,0.1) | E24: =_xlfn.PERCENTILE.INC($AF$5:$AF$873,0.5) | F24: =_xlfn.PERCENTILE.INC($AF$5:$AF$873,0.9) | G24: =STDEV($AF$5:$AF$873) | H24: =B24-$B$16 | M24: ='03_原始数据'!C24-0.6*'03_原始数据'!B24-OtherCost | N24: ='03_原始数据'!C24-0.605*'03_原始数据'!B24-OtherCost | O24: ='03_原始数据'!C24-0.61*'03_原始数据'!B24-OtherCost | P24: ='03_原始数据'!C24-0.615*'03_原始数据'!B24-OtherCost | Q24: ='03_原始数据'!C24-0.62*'03_原始数据'!B24-OtherCost | R24: ='03_原始数据'!C24-0.625*'03_原始数据'!B24-OtherCost | S24: ='03_原始数据'!C24-0.63*'03_原始数据'!B24-OtherCost | T24: ='03_原始数据'!C24-0.635*'03_原始数据'!B24-OtherCost | U24: ='03_原始数据'!C24-0.64*'03_原始数据'!B24-OtherCost | V24: ='03_原始数据'!C24-0.645*'03_原始数据'!B24-OtherCost | W24: ='03_原始数据'!C24-0.65*'03_原始数据'!B24-OtherCost | X24: ='03_原始数据'!C24-0.655*'03_原始数据'!B24-OtherCost | Y24: ='03_原始数据'!C24-0.66*'03_原始数据'!B24-OtherCost | Z24: ='03_原始数据'!C24-0.665*'03_原始数据'!B24-OtherCost | AA24: ='03_原始数据'!C24-0.67*'03_原始数据'!B24-OtherCost | AB24: ='03_原始数据'!C24-0.675*'03_原始数据'!B24-OtherCost | AC24: ='03_原始数据'!C24-0.68*'03_原始数据'!B24-OtherCost | AD24: ='03_原始数据'!C24-0.685*'03_原始数据'!B24-OtherCost | AE24: ='03_原始数据'!C24-0.69*'03_原始数据'!B24-OtherCost | AF24: ='03_原始数据'!C24-0.695*'03_原始数据'!B24-OtherCost | AG24: ='03_原始数据'!C24-0.7*'03_原始数据'!B24-OtherCost
A25: 0.7 | B25: =AVERAGE($AG$5:$AG$873) | C25: =MEDIAN($AG$5:$AG$873) | D25: =_xlfn.PERCENTILE.INC($AG$5:$AG$873,0.1) | E25: =_xlfn.PERCENTILE.INC($AG$5:$AG$873,0.5) | F25: =_xlfn.PERCENTILE.INC($AG$5:$AG$873,0.9) | G25: =STDEV($AG$5:$AG$873) | H25: =B25-$B$16 | M25: ='03_原始数据'!C25-0.6*'03_原始数据'!B25-OtherCost | N25: ='03_原始数据'!C25-0.605*'03_原始数据'!B25-OtherCost | O25: ='03_原始数据'!C25-0.61*'03_原始数据'!B25-OtherCost | P25: ='03_原始数据'!C25-0.615*'03_原始数据'!B25-OtherCost | Q25: ='03_原始数据'!C25-0.62*'03_原始数据'!B25-OtherCost | R25: ='03_原始数据'!C25-0.625*'03_原始数据'!B25-OtherCost | S25: ='03_原始数据'!C25-0.63*'03_原始数据'!B25-OtherCost | T25: ='03_原始数据'!C25-0.635*'03_原始数据'!B25-OtherCost | U25: ='03_原始数据'!C25-0.64*'03_原始数据'!B25-OtherCost | V25: ='03_原始数据'!C25-0.645*'03_原始数据'!B25-OtherCost | W25: ='03_原始数据'!C25-0.65*'03_原始数据'!B25-OtherCost | X25: ='03_原始数据'!C25-0.655*'03_原始数据'!B25-OtherCost | Y25: ='03_原始数据'!C25-0.66*'03_原始数据'!B25-OtherCost | Z25: ='03_原始数据'!C25-0.665*'03_原始数据'!B25-OtherCost | AA25: ='03_原始数据'!C25-0.67*'03_原始数据'!B25-OtherCost | AB25: ='03_原始数据'!C25-0.675*'03_原始数据'!B25-OtherCost | AC25: ='03_原始数据'!C25-0.68*'03_原始数据'!B25-OtherCost | AD25: ='03_原始数据'!C25-0.685*'03_原始数据'!B25-OtherCost | AE25: ='03_原始数据'!C25-0.69*'03_原始数据'!B25-OtherCost | AF25: ='03_原始数据'!C25-0.695*'03_原始数据'!B25-OtherCost | AG25: ='03_原始数据'!C25-0.7*'03_原始数据'!B25-OtherCost
M26: ='03_原始数据'!C26-0.6*'03_原始数据'!B26-OtherCost | N26: ='03_原始数据'!C26-0.605*'03_原始数据'!B26-OtherCost | O26: ='03_原始数据'!C26-0.61*'03_原始数据'!B26-OtherCost | P26: ='03_原始数据'!C26-0.615*'03_原始数据'!B26-OtherCost | Q26: ='03_原始数据'!C26-0.62*'03_原始数据'!B26-OtherCost | R26: ='03_原始数据'!C26-0.625*'03_原始数据'!B26-OtherCost | S26: ='03_原始数据'!C26-0.63*'03_原始数据'!B26-OtherCost | T26: ='03_原始数据'!C26-0.635*'03_原始数据'!B26-OtherCost | U26: ='03_原始数据'!C26-0.64*'03_原始数据'!B26-OtherCost | V26: ='03_原始数据'!C26-0.645*'03_原始数据'!B26-OtherCost | W26: ='03_原始数据'!C26-0.65*'03_原始数据'!B26-OtherCost | X26: ='03_原始数据'!C26-0.655*'03_原始数据'!B26-OtherCost | Y26: ='03_原始数据'!C26-0.66*'03_原始数据'!B26-OtherCost | Z26: ='03_原始数据'!C26-0.665*'03_原始数据'!B26-OtherCost | AA26: ='03_原始数据'!C26-0.67*'03_原始数据'!B26-OtherCost | AB26: ='03_原始数据'!C26-0.675*'03_原始数据'!B26-OtherCost | AC26: ='03_原始数据'!C26-0.68*'03_原始数据'!B26-OtherCost | AD26: ='03_原始数据'!C26-0.685*'03_原始数据'!B26-OtherCost | AE26: ='03_原始数据'!C26-0.69*'03_原始数据'!B26-OtherCost | AF26: ='03_原始数据'!C26-0.695*'03_原始数据'!B26-OtherCost | AG26: ='03_原始数据'!C26-0.7*'03_原始数据'!B26-OtherCost
M27: ='03_原始数据'!C27-0.6*'03_原始数据'!B27-OtherCost | N27: ='03_原始数据'!C27-0.605*'03_原始数据'!B27-OtherCost | O27: ='03_原始数据'!C27-0.61*'03_原始数据'!B27-OtherCost | P27: ='03_原始数据'!C27-0.615*'03_原始数据'!B27-OtherCost | Q27: ='03_原始数据'!C27-0.62*'03_原始数据'!B27-OtherCost | R27: ='03_原始数据'!C27-0.625*'03_原始数据'!B27-OtherCost | S27: ='03_原始数据'!C27-0.63*'03_原始数据'!B27-OtherCost | T27: ='03_原始数据'!C27-0.635*'03_原始数据'!B27-OtherCost | U27: ='03_原始数据'!C27-0.64*'03_原始数据'!B27-OtherCost | V27: ='03_原始数据'!C27-0.645*'03_原始数据'!B27-OtherCost | W27: ='03_原始数据'!C27-0.65*'03_原始数据'!B27-OtherCost | X27: ='03_原始数据'!C27-0.655*'03_原始数据'!B27-OtherCost | Y27: ='03_原始数据'!C27-0.66*'03_原始数据'!B27-OtherCost | Z27: ='03_原始数据'!C27-0.665*'03_原始数据'!B27-OtherCost | AA27: ='03_原始数据'!C27-0.67*'03_原始数据'!B27-OtherCost | AB27: ='03_原始数据'!C27-0.675*'03_原始数据'!B27-OtherCost | AC27: ='03_原始数据'!C27-0.68*'03_原始数据'!B27-OtherCost | AD27: ='03_原始数据'!C27-0.685*'03_原始数据'!B27-OtherCost | AE27: ='03_原始数据'!C27-0.69*'03_原始数据'!B27-OtherCost | AF27: ='03_原始数据'!C27-0.695*'03_原始数据'!B27-OtherCost | AG27: ='03_原始数据'!C27-0.7*'03_原始数据'!B27-OtherCost
M28: ='03_原始数据'!C28-0.6*'03_原始数据'!B28-OtherCost | N28: ='03_原始数据'!C28-0.605*'03_原始数据'!B28-OtherCost | O28: ='03_原始数据'!C28-0.61*'03_原始数据'!B28-OtherCost | P28: ='03_原始数据'!C28-0.615*'03_原始数据'!B28-OtherCost | Q28: ='03_原始数据'!C28-0.62*'03_原始数据'!B28-OtherCost | R28: ='03_原始数据'!C28-0.625*'03_原始数据'!B28-OtherCost | S28: ='03_原始数据'!C28-0.63*'03_原始数据'!B28-OtherCost | T28: ='03_原始数据'!C28-0.635*'03_原始数据'!B28-OtherCost | U28: ='03_原始数据'!C28-0.64*'03_原始数据'!B28-OtherCost | V28: ='03_原始数据'!C28-0.645*'03_原始数据'!B28-OtherCost | W28: ='03_原始数据'!C28-0.65*'03_原始数据'!B28-OtherCost | X28: ='03_原始数据'!C28-0.655*'03_原始数据'!B28-OtherCost | Y28: ='03_原始数据'!C28-0.66*'03_原始数据'!B28-OtherCost | Z28: ='03_原始数据'!C28-0.665*'03_原始数据'!B28-OtherCost | AA28: ='03_原始数据'!C28-0.67*'03_原始数据'!B28-OtherCost | AB28: ='03_原始数据'!C28-0.675*'03_原始数据'!B28-OtherCost | AC28: ='03_原始数据'!C28-0.68*'03_原始数据'!B28-OtherCost | AD28: ='03_原始数据'!C28-0.685*'03_原始数据'!B28-OtherCost | AE28: ='03_原始数据'!C28-0.69*'03_原始数据'!B28-OtherCost | AF28: ='03_原始数据'!C28-0.695*'03_原始数据'!B28-OtherCost | AG28: ='03_原始数据'!C28-0.7*'03_原始数据'!B28-OtherCost
M29: ='03_原始数据'!C29-0.6*'03_原始数据'!B29-OtherCost | N29: ='03_原始数据'!C29-0.605*'03_原始数据'!B29-OtherCost | O29: ='03_原始数据'!C29-0.61*'03_原始数据'!B29-OtherCost | P29: ='03_原始数据'!C29-0.615*'03_原始数据'!B29-OtherCost | Q29: ='03_原始数据'!C29-0.62*'03_原始数据'!B29-OtherCost | R29: ='03_原始数据'!C29-0.625*'03_原始数据'!B29-OtherCost | S29: ='03_原始数据'!C29-0.63*'03_原始数据'!B29-OtherCost | T29: ='03_原始数据'!C29-0.635*'03_原始数据'!B29-OtherCost | U29: ='03_原始数据'!C29-0.64*'03_原始数据'!B29-OtherCost | V29: ='03_原始数据'!C29-0.645*'03_原始数据'!B29-OtherCost | W29: ='03_原始数据'!C29-0.65*'03_原始数据'!B29-OtherCost | X29: ='03_原始数据'!C29-0.655*'03_原始数据'!B29-OtherCost | Y29: ='03_原始数据'!C29-0.66*'03_原始数据'!B29-OtherCost | Z29: ='03_原始数据'!C29-0.665*'03_原始数据'!B29-OtherCost | AA29: ='03_原始数据'!C29-0.67*'03_原始数据'!B29-OtherCost | AB29: ='03_原始数据'!C29-0.675*'03_原始数据'!B29-OtherCost | AC29: ='03_原始数据'!C29-0.68*'03_原始数据'!B29-OtherCost | AD29: ='03_原始数据'!C29-0.685*'03_原始数据'!B29-OtherCost | AE29: ='03_原始数据'!C29-0.69*'03_原始数据'!B29-OtherCost | AF29: ='03_原始数据'!C29-0.695*'03_原始数据'!B29-OtherCost | AG29: ='03_原始数据'!C29-0.7*'03_原始数据'!B29-OtherCost
M30: ='03_原始数据'!C30-0.6*'03_原始数据'!B30-OtherCost | N30: ='03_原始数据'!C30-0.605*'03_原始数据'!B30-OtherCost | O30: ='03_原始数据'!C30-0.61*'03_原始数据'!B30-OtherCost | P30: ='03_原始数据'!C30-0.615*'03_原始数据'!B30-OtherCost | Q30: ='03_原始数据'!C30-0.62*'03_原始数据'!B30-OtherCost | R30: ='03_原始数据'!C30-0.625*'03_原始数据'!B30-OtherCost | S30: ='03_原始数据'!C30-0.63*'03_原始数据'!B30-OtherCost | T30: ='03_原始数据'!C30-0.635*'03_原始数据'!B30-OtherCost | U30: ='03_原始数据'!C30-0.64*'03_原始数据'!B30-OtherCost | V30: ='03_原始数据'!C30-0.645*'03_原始数据'!B30-OtherCost | W30: ='03_原始数据'!C30-0.65*'03_原始数据'!B30-OtherCost | X30: ='03_原始数据'!C30-0.655*'03_原始数据'!B30-OtherCost | Y30: ='03_原始数据'!C30-0.66*'03_原始数据'!B30-OtherCost | Z30: ='03_原始数据'!C30-0.665*'03_原始数据'!B30-OtherCost | AA30: ='03_原始数据'!C30-0.67*'03_原始数据'!B30-OtherCost | AB30: ='03_原始数据'!C30-0.675*'03_原始数据'!B30-OtherCost | AC30: ='03_原始数据'!C30-0.68*'03_原始数据'!B30-OtherCost | AD30: ='03_原始数据'!C30-0.685*'03_原始数据'!B30-OtherCost | AE30: ='03_原始数据'!C30-0.69*'03_原始数据'!B30-OtherCost | AF30: ='03_原始数据'!C30-0.695*'03_原始数据'!B30-OtherCost | AG30: ='03_原始数据'!C30-0.7*'03_原始数据'!B30-OtherCost
M31: ='03_原始数据'!C31-0.6*'03_原始数据'!B31-OtherCost | N31: ='03_原始数据'!C31-0.605*'03_原始数据'!B31-OtherCost | O31: ='03_原始数据'!C31-0.61*'03_原始数据'!B31-OtherCost | P31: ='03_原始数据'!C31-0.615*'03_原始数据'!B31-OtherCost | Q31: ='03_原始数据'!C31-0.62*'03_原始数据'!B31-OtherCost | R31: ='03_原始数据'!C31-0.625*'03_原始数据'!B31-OtherCost | S31: ='03_原始数据'!C31-0.63*'03_原始数据'!B31-OtherCost | T31: ='03_原始数据'!C31-0.635*'03_原始数据'!B31-OtherCost | U31: ='03_原始数据'!C31-0.64*'03_原始数据'!B31-OtherCost | V31: ='03_原始数据'!C31-0.645*'03_原始数据'!B31-OtherCost | W31: ='03_原始数据'!C31-0.65*'03_原始数据'!B31-OtherCost | X31: ='03_原始数据'!C31-0.655*'03_原始数据'!B31-OtherCost | Y31: ='03_原始数据'!C31-0.66*'03_原始数据'!B31-OtherCost | Z31: ='03_原始数据'!C31-0.665*'03_原始数据'!B31-OtherCost | AA31: ='03_原始数据'!C31-0.67*'03_原始数据'!B31-OtherCost | AB31: ='03_原始数据'!C31-0.675*'03_原始数据'!B31-OtherCost | AC31: ='03_原始数据'!C31-0.68*'03_原始数据'!B31-OtherCost | AD31: ='03_原始数据'!C31-0.685*'03_原始数据'!B31-OtherCost | AE31: ='03_原始数据'!C31-0.69*'03_原始数据'!B31-OtherCost | AF31: ='03_原始数据'!C31-0.695*'03_原始数据'!B31-OtherCost | AG31: ='03_原始数据'!C31-0.7*'03_原始数据'!B31-OtherCost
M32: ='03_原始数据'!C32-0.6*'03_原始数据'!B32-OtherCost | N32: ='03_原始数据'!C32-0.605*'03_原始数据'!B32-OtherCost | O32: ='03_原始数据'!C32-0.61*'03_原始数据'!B32-OtherCost | P32: ='03_原始数据'!C32-0.615*'03_原始数据'!B32-OtherCost | Q32: ='03_原始数据'!C32-0.62*'03_原始数据'!B32-OtherCost | R32: ='03_原始数据'!C32-0.625*'03_原始数据'!B32-OtherCost | S32: ='03_原始数据'!C32-0.63*'03_原始数据'!B32-OtherCost | T32: ='03_原始数据'!C32-0.635*'03_原始数据'!B32-OtherCost | U32: ='03_原始数据'!C32-0.64*'03_原始数据'!B32-OtherCost | V32: ='03_原始数据'!C32-0.645*'03_原始数据'!B32-OtherCost | W32: ='03_原始数据'!C32-0.65*'03_原始数据'!B32-OtherCost | X32: ='03_原始数据'!C32-0.655*'03_原始数据'!B32-OtherCost | Y32: ='03_原始数据'!C32-0.66*'03_原始数据'!B32-OtherCost | Z32: ='03_原始数据'!C32-0.665*'03_原始数据'!B32-OtherCost | AA32: ='03_原始数据'!C32-0.67*'03_原始数据'!B32-OtherCost | AB32: ='03_原始数据'!C32-0.675*'03_原始数据'!B32-OtherCost | AC32: ='03_原始数据'!C32-0.68*'03_原始数据'!B32-OtherCost | AD32: ='03_原始数据'!C32-0.685*'03_原始数据'!B32-OtherCost | AE32: ='03_原始数据'!C32-0.69*'03_原始数据'!B32-OtherCost | AF32: ='03_原始数据'!C32-0.695*'03_原始数据'!B32-OtherCost | AG32: ='03_原始数据'!C32-0.7*'03_原始数据'!B32-OtherCost
M33: ='03_原始数据'!C33-0.6*'03_原始数据'!B33-OtherCost | N33: ='03_原始数据'!C33-0.605*'03_原始数据'!B33-OtherCost | O33: ='03_原始数据'!C33-0.61*'03_原始数据'!B33-OtherCost | P33: ='03_原始数据'!C33-0.615*'03_原始数据'!B33-OtherCost | Q33: ='03_原始数据'!C33-0.62*'03_原始数据'!B33-OtherCost | R33: ='03_原始数据'!C33-0.625*'03_原始数据'!B33-OtherCost | S33: ='03_原始数据'!C33-0.63*'03_原始数据'!B33-OtherCost | T33: ='03_原始数据'!C33-0.635*'03_原始数据'!B33-OtherCost | U33: ='03_原始数据'!C33-0.64*'03_原始数据'!B33-OtherCost | V33: ='03_原始数据'!C33-0.645*'03_原始数据'!B33-OtherCost | W33: ='03_原始数据'!C33-0.65*'03_原始数据'!B33-OtherCost | X33: ='03_原始数据'!C33-0.655*'03_原始数据'!B33-OtherCost | Y33: ='03_原始数据'!C33-0.66*'03_原始数据'!B33-OtherCost | Z33: ='03_原始数据'!C33-0.665*'03_原始数据'!B33-OtherCost | AA33: ='03_原始数据'!C33-0.67*'03_原始数据'!B33-OtherCost | AB33: ='03_原始数据'!C33-0.675*'03_原始数据'!B33-OtherCost | AC33: ='03_原始数据'!C33-0.68*'03_原始数据'!B33-OtherCost | AD33: ='03_原始数据'!C33-0.685*'03_原始数据'!B33-OtherCost | AE33: ='03_原始数据'!C33-0.69*'03_原始数据'!B33-OtherCost | AF33: ='03_原始数据'!C33-0.695*'03_原始数据'!B33-OtherCost | AG33: ='03_原始数据'!C33-0.7*'03_原始数据'!B33-OtherCost
M34: ='03_原始数据'!C34-0.6*'03_原始数据'!B34-OtherCost | N34: ='03_原始数据'!C34-0.605*'03_原始数据'!B34-OtherCost | O34: ='03_原始数据'!C34-0.61*'03_原始数据'!B34-OtherCost | P34: ='03_原始数据'!C34-0.615*'03_原始数据'!B34-OtherCost | Q34: ='03_原始数据'!C34-0.62*'03_原始数据'!B34-OtherCost | R34: ='03_原始数据'!C34-0.625*'03_原始数据'!B34-OtherCost | S34: ='03_原始数据'!C34-0.63*'03_原始数据'!B34-OtherCost | T34: ='03_原始数据'!C34-0.635*'03_原始数据'!B34-OtherCost | U34: ='03_原始数据'!C34-0.64*'03_原始数据'!B34-OtherCost | V34: ='03_原始数据'!C34-0.645*'03_原始数据'!B34-OtherCost | W34: ='03_原始数据'!C34-0.65*'03_原始数据'!B34-OtherCost | X34: ='03_原始数据'!C34-0.655*'03_原始数据'!B34-OtherCost | Y34: ='03_原始数据'!C34-0.66*'03_原始数据'!B34-OtherCost | Z34: ='03_原始数据'!C34-0.665*'03_原始数据'!B34-OtherCost | AA34: ='03_原始数据'!C34-0.67*'03_原始数据'!B34-OtherCost | AB34: ='03_原始数据'!C34-0.675*'03_原始数据'!B34-OtherCost | AC34: ='03_原始数据'!C34-0.68*'03_原始数据'!B34-OtherCost | AD34: ='03_原始数据'!C34-0.685*'03_原始数据'!B34-OtherCost | AE34: ='03_原始数据'!C34-0.69*'03_原始数据'!B34-OtherCost | AF34: ='03_原始数据'!C34-0.695*'03_原始数据'!B34-OtherCost | AG34: ='03_原始数据'!C34-0.7*'03_原始数据'!B34-OtherCost
M35: ='03_原始数据'!C35-0.6*'03_原始数据'!B35-OtherCost | N35: ='03_原始数据'!C35-0.605*'03_原始数据'!B35-OtherCost | O35: ='03_原始数据'!C35-0.61*'03_原始数据'!B35-OtherCost | P35: ='03_原始数据'!C35-0.615*'03_原始数据'!B35-OtherCost | Q35: ='03_原始数据'!C35-0.62*'03_原始数据'!B35-OtherCost | R35: ='03_原始数据'!C35-0.625*'03_原始数据'!B35-OtherCost | S35: ='03_原始数据'!C35-0.63*'03_原始数据'!B35-OtherCost | T35: ='03_原始数据'!C35-0.635*'03_原始数据'!B35-OtherCost | U35: ='03_原始数据'!C35-0.64*'03_原始数据'!B35-OtherCost | V35: ='03_原始数据'!C35-0.645*'03_原始数据'!B35-OtherCost | W35: ='03_原始数据'!C35-0.65*'03_原始数据'!B35-OtherCost | X35: ='03_原始数据'!C35-0.655*'03_原始数据'!B35-OtherCost | Y35: ='03_原始数据'!C35-0.66*'03_原始数据'!B35-OtherCost | Z35: ='03_原始数据'!C35-0.665*'03_原始数据'!B35-OtherCost | AA35: ='03_原始数据'!C35-0.67*'03_原始数据'!B35-OtherCost | AB35: ='03_原始数据'!C35-0.675*'03_原始数据'!B35-OtherCost | AC35: ='03_原始数据'!C35-0.68*'03_原始数据'!B35-OtherCost | AD35: ='03_原始数据'!C35-0.685*'03_原始数据'!B35-OtherCost | AE35: ='03_原始数据'!C35-0.69*'03_原始数据'!B35-OtherCost | AF35: ='03_原始数据'!C35-0.695*'03_原始数据'!B35-OtherCost | AG35: ='03_原始数据'!C35-0.7*'03_原始数据'!B35-OtherCost
M36: ='03_原始数据'!C36-0.6*'03_原始数据'!B36-OtherCost | N36: ='03_原始数据'!C36-0.605*'03_原始数据'!B36-OtherCost | O36: ='03_原始数据'!C36-0.61*'03_原始数据'!B36-OtherCost | P36: ='03_原始数据'!C36-0.615*'03_原始数据'!B36-OtherCost | Q36: ='03_原始数据'!C36-0.62*'03_原始数据'!B36-OtherCost | R36: ='03_原始数据'!C36-0.625*'03_原始数据'!B36-OtherCost | S36: ='03_原始数据'!C36-0.63*'03_原始数据'!B36-OtherCost | T36: ='03_原始数据'!C36-0.635*'03_原始数据'!B36-OtherCost | U36: ='03_原始数据'!C36-0.64*'03_原始数据'!B36-OtherCost | V36: ='03_原始数据'!C36-0.645*'03_原始数据'!B36-OtherCost | W36: ='03_原始数据'!C36-0.65*'03_原始数据'!B36-OtherCost | X36: ='03_原始数据'!C36-0.655*'03_原始数据'!B36-OtherCost | Y36: ='03_原始数据'!C36-0.66*'03_原始数据'!B36-OtherCost | Z36: ='03_原始数据'!C36-0.665*'03_原始数据'!B36-OtherCost | AA36: ='03_原始数据'!C36-0.67*'03_原始数据'!B36-OtherCost | AB36: ='03_原始数据'!C36-0.675*'03_原始数据'!B36-OtherCost | AC36: ='03_原始数据'!C36-0.68*'03_原始数据'!B36-OtherCost | AD36: ='03_原始数据'!C36-0.685*'03_原始数据'!B36-OtherCost | AE36: ='03_原始数据'!C36-0.69*'03_原始数据'!B36-OtherCost | AF36: ='03_原始数据'!C36-0.695*'03_原始数据'!B36-OtherCost | AG36: ='03_原始数据'!C36-0.7*'03_原始数据'!B36-OtherCost
M37: ='03_原始数据'!C37-0.6*'03_原始数据'!B37-OtherCost | N37: ='03_原始数据'!C37-0.605*'03_原始数据'!B37-OtherCost | O37: ='03_原始数据'!C37-0.61*'03_原始数据'!B37-OtherCost | P37: ='03_原始数据'!C37-0.615*'03_原始数据'!B37-OtherCost | Q37: ='03_原始数据'!C37-0.62*'03_原始数据'!B37-OtherCost | R37: ='03_原始数据'!C37-0.625*'03_原始数据'!B37-OtherCost | S37: ='03_原始数据'!C37-0.63*'03_原始数据'!B37-OtherCost | T37: ='03_原始数据'!C37-0.635*'03_原始数据'!B37-OtherCost | U37: ='03_原始数据'!C37-0.64*'03_原始数据'!B37-OtherCost | V37: ='03_原始数据'!C37-0.645*'03_原始数据'!B37-OtherCost | W37: ='03_原始数据'!C37-0.65*'03_原始数据'!B37-OtherCost | X37: ='03_原始数据'!C37-0.655*'03_原始数据'!B37-OtherCost | Y37: ='03_原始数据'!C37-0.66*'03_原始数据'!B37-OtherCost | Z37: ='03_原始数据'!C37-0.665*'03_原始数据'!B37-OtherCost | AA37: ='03_原始数据'!C37-0.67*'03_原始数据'!B37-OtherCost | AB37: ='03_原始数据'!C37-0.675*'03_原始数据'!B37-OtherCost | AC37: ='03_原始数据'!C37-0.68*'03_原始数据'!B37-OtherCost | AD37: ='03_原始数据'!C37-0.685*'03_原始数据'!B37-OtherCost | AE37: ='03_原始数据'!C37-0.69*'03_原始数据'!B37-OtherCost | AF37: ='03_原始数据'!C37-0.695*'03_原始数据'!B37-OtherCost | AG37: ='03_原始数据'!C37-0.7*'03_原始数据'!B37-OtherCost
... M873: ='03_原始数据'!C873-0.6*'03_原始数据'!B873-OtherCost | N873: ='03_原始数据'!C873-0.605*'03_原始数据'!B873-OtherCost | O873: ='03_原始数据'!C873-0.61*'03_原始数据'!B873-OtherCost | P873: ='03_原始数据'!C873-0.615*'03_原始数据'!B873-OtherCost | Q873: ='03_原始数据'!C873-0.62*'03_原始数据'!B873-OtherCost | R873: ='03_原始数据'!C873-0.625*'03_原始数据'!B873-OtherCost | S873: ='03_原始数据'!C873-0.63*'03_原始数据'!B873-OtherCost | T873: ='03_原始数据'!C873-0.635*'03_原始数据'!B873-OtherCost | U873: ='03_原始数据'!C873-0.64*'03_原始数据'!B873-OtherCost | V873: ='03_原始数据'!C873-0.645*'03_原始数据'!B873-OtherCost | W873: ='03_原始数据'!C873-0.65*'03_原始数据'!B873-OtherCost | X873: ='03_原始数据'!C873-0.655*'03_原始数据'!B873-OtherCost | Y873: ='03_原始数据'!C873-0.66*'03_原始数据'!B873-OtherCost | Z873: ='03_原始数据'!C873-0.665*'03_原始数据'!B873-OtherCost | AA873: ='03_原始数据'!C873-0.67*'03_原始数据'!B873-OtherCost | AB873: ='03_原始数据'!C873-0.675*'03_原始数据'!B873-OtherCost | AC873: ='03_原始数据'!C873-0.68*'03_原始数据'!B873-OtherCost | AD873: ='03_原始数据'!C873-0.685*'03_原始数据'!B873-OtherCost | AE873: ='03_原始数据'!C873-0.69*'03_原始数据'!B873-OtherCost | AF873: ='03_原始数据'!C873-0.695*'03_原始数据'!B873-OtherCost | AG873: ='03_原始数据'!C873-0.7*'03_原始数据'!B873-OtherCost

Sheet 06_加工价差
A1: 理论加工价差与分位
A2: 价差 = PTA − λ×PX − 其他成本。分位用 PERCENTRANK.INC（与报告一致）。
A4: 日期 | B4: PX | C4: PTA | D4: 加工价差 | E4: 历史分位（全样本） | F4: 滚动60日均值 | G4: 滚动60日标准差
A5: ='03_原始数据'!A5 | B5: ='03_原始数据'!B5 | C5: ='03_原始数据'!C5 | D5: ='03_原始数据'!E5 | E5: =_xlfn.PERCENTRANK.INC('03_原始数据'!$E$5:$E$873,'03_原始数据'!E5) | F5: =IF(False,AVERAGE('03_原始数据'!$E$5:$E$5),"") | G5: =IF(False,STDEV('03_原始数据'!$E$5:$E$5),"")
A6: ='03_原始数据'!A6 | B6: ='03_原始数据'!B6 | C6: ='03_原始数据'!C6 | D6: ='03_原始数据'!E6 | E6: =_xlfn.PERCENTRANK.INC('03_原始数据'!$E$5:$E$873,'03_原始数据'!E6) | F6: =IF(False,AVERAGE('03_原始数据'!$E$5:$E$6),"") | G6: =IF(False,STDEV('03_原始数据'!$E$5:$E$6),"")
A7: ='03_原始数据'!A7 | B7: ='03_原始数据'!B7 | C7: ='03_原始数据'!C7 | D7: ='03_原始数据'!E7 | E7: =_xlfn.PERCENTRANK.INC('03_原始数据'!$E$5:$E$873,'03_原始数据'!E7) | F7: =IF(False,AVERAGE('03_原始数据'!$E$5:$E$7),"") | G7: =IF(False,STDEV('03_原始数据'!$E$5:$E$7),"")
A8: ='03_原始数据'!A8 | B8: ='03_原始数据'!B8 | C8: ='03_原始数据'!C8 | D8: ='03_原始数据'!E8 | E8: =_xlfn.PERCENTRANK.INC('03_原始数据'!$E$5:$E$873,'03_原始数据'!E8) | F8: =IF(False,AVERAGE('03_原始数据'!$E$5:$E$8),"") | G8: =IF(False,STDEV('03_原始数据'!$E$5:$E$8),"")
A9: ='03_原始数据'!A9 | B9: ='03_原始数据'!B9 | C9: ='03_原始数据'!C9 | D9: ='03_原始数据'!E9 | E9: =_xlfn.PERCENTRANK.INC('03_原始数据'!$E$5:$E$873,'03_原始数据'!E9) | F9: =IF(False,AVERAGE('03_原始数据'!$E$5:$E$9),"") | G9: =IF(False,STDEV('03_原始数据'!$E$5:$E$9),"")
A10: ='03_原始数据'!A10 | B10: ='03_原始数据'!B10 | C10: ='03_原始数据'!C10 | D10: ='03_原始数据'!E10 | E10: =_xlfn.PERCENTRANK.INC('03_原始数据'!$E$5:$E$873,'03_原始数据'!E10) | F10: =IF(False,AVERAGE('03_原始数据'!$E$5:$E$10),"") | G10: =IF(False,STDEV('03_原始数据'!$E$5:$E$10),"")
A11: ='03_原始数据'!A11 | B11: ='03_原始数据'!B11 | C11: ='03_原始数据'!C11 | D11: ='03_原始数据'!E11 | E11: =_xlfn.PERCENTRANK.INC('03_原始数据'!$E$5:$E$873,'03_原始数据'!E11) | F11: =IF(False,AVERAGE('03_原始数据'!$E$5:$E$11),"") | G11: =IF(False,STDEV('03_原始数据'!$E$5:$E$11),"")
A12: ='03_原始数据'!A12 | B12: ='03_原始数据'!B12 | C12: ='03_原始数据'!C12 | D12: ='03_原始数据'!E12 | E12: =_xlfn.PERCENTRANK.INC('03_原始数据'!$E$5:$E$873,'03_原始数据'!E12) | F12: =IF(False,AVERAGE('03_原始数据'!$E$5:$E$12),"") | G12: =IF(False,STDEV('03_原始数据'!$E$5:$E$12),"")
A13: ='03_原始数据'!A13 | B13: ='03_原始数据'!B13 | C13: ='03_原始数据'!C13 | D13: ='03_原始数据'!E13 | E13: =_xlfn.PERCENTRANK.INC('03_原始数据'!$E$5:$E$873,'03_原始数据'!E13) | F13: =IF(False,AVERAGE('03_原始数据'!$E$5:$E$13),"") | G13: =IF(False,STDEV('03_原始数据'!$E$5:$E$13),"")
A14: ='03_原始数据'!A14 | B14: ='03_原始数据'!B14 | C14: ='03_原始数据'!C14 | D14: ='03_原始数据'!E14 | E14: =_xlfn.PERCENTRANK.INC('03_原始数据'!$E$5:$E$873,'03_原始数据'!E14) | F14: =IF(False,AVERAGE('03_原始数据'!$E$5:$E$14),"") | G14: =IF(False,STDEV('03_原始数据'!$E$5:$E$14),"")
A15: ='03_原始数据'!A15 | B15: ='03_原始数据'!B15 | C15: ='03_原始数据'!C15 | D15: ='03_原始数据'!E15 | E15: =_xlfn.PERCENTRANK.INC('03_原始数据'!$E$5:$E$873,'03_原始数据'!E15) | F15: =IF(False,AVERAGE('03_原始数据'!$E$5:$E$15),"") | G15: =IF(False,STDEV('03_原始数据'!$E$5:$E$15),"")
A16: ='03_原始数据'!A16 | B16: ='03_原始数据'!B16 | C16: ='03_原始数据'!C16 | D16: ='03_原始数据'!E16 | E16: =_xlfn.PERCENTRANK.INC('03_原始数据'!$E$5:$E$873,'03_原始数据'!E16) | F16: =IF(False,AVERAGE('03_原始数据'!$E$5:$E$16),"") | G16: =IF(False,STDEV('03_原始数据'!$E$5:$E$16),"")
A17: ='03_原始数据'!A17 | B17: ='03_原始数据'!B17 | C17: ='03_原始数据'!C17 | D17: ='03_原始数据'!E17 | E17: =_xlfn.PERCENTRANK.INC('03_原始数据'!$E$5:$E$873,'03_原始数据'!E17) | F17: =IF(False,AVERAGE('03_原始数据'!$E$5:$E$17),"") | G17: =IF(False,STDEV('03_原始数据'!$E$5:$E$17),"")
A18: ='03_原始数据'!A18 | B18: ='03_原始数据'!B18 | C18: ='03_原始数据'!C18 | D18: ='03_原始数据'!E18 | E18: =_xlfn.PERCENTRANK.INC('03_原始数据'!$E$5:$E$873,'03_原始数据'!E18) | F18: =IF(False,AVERAGE('03_原始数据'!$E$5:$E$18),"") | G18: =IF(False,STDEV('03_原始数据'!$E$5:$E$18),"")
A19: ='03_原始数据'!A19 | B19: ='03_原始数据'!B19 | C19: ='03_原始数据'!C19 | D19: ='03_原始数据'!E19 | E19: =_xlfn.PERCENTRANK.INC('03_原始数据'!$E$5:$E$873,'03_原始数据'!E19) | F19: =IF(False,AVERAGE('03_原始数据'!$E$5:$E$19),"") | G19: =IF(False,STDEV('03_原始数据'!$E$5:$E$19),"")
A20: ='03_原始数据'!A20 | B20: ='03_原始数据'!B20 | C20: ='03_原始数据'!C20 | D20: ='03_原始数据'!E20 | E20: =_xlfn.PERCENTRANK.INC('03_原始数据'!$E$5:$E$873,'03_原始数据'!E20) | F20: =IF(False,AVERAGE('03_原始数据'!$E$5:$E$20),"") | G20: =IF(False,STDEV('03_原始数据'!$E$5:$E$20),"")
A21: ='03_原始数据'!A21 | B21: ='03_原始数据'!B21 | C21: ='03_原始数据'!C21 | D21: ='03_原始数据'!E21 | E21: =_xlfn.PERCENTRANK.INC('03_原始数据'!$E$5:$E$873,'03_原始数据'!E21) | F21: =IF(False,AVERAGE('03_原始数据'!$E$5:$E$21),"") | G21: =IF(False,STDEV('03_原始数据'!$E$5:$E$21),"")
A22: ='03_原始数据'!A22 | B22: ='03_原始数据'!B22 | C22: ='03_原始数据'!C22 | D22: ='03_原始数据'!E22 | E22: =_xlfn.PERCENTRANK.INC('03_原始数据'!$E$5:$E$873,'03_原始数据'!E22) | F22: =IF(False,AVERAGE('03_原始数据'!$E$5:$E$22),"") | G22: =IF(False,STDEV('03_原始数据'!$E$5:$E$22),"")
A23: ='03_原始数据'!A23 | B23: ='03_原始数据'!B23 | C23: ='03_原始数据'!C23 | D23: ='03_原始数据'!E23 | E23: =_xlfn.PERCENTRANK.INC('03_原始数据'!$E$5:$E$873,'03_原始数据'!E23) | F23: =IF(False,AVERAGE('03_原始数据'!$E$5:$E$23),"") | G23: =IF(False,STDEV('03_原始数据'!$E$5:$E$23),"")
A24: ='03_原始数据'!A24 | B24: ='03_原始数据'!B24 | C24: ='03_原始数据'!C24 | D24: ='03_原始数据'!E24 | E24: =_xlfn.PERCENTRANK.INC('03_原始数据'!$E$5:$E$873,'03_原始数据'!E24) | F24: =IF(False,AVERAGE('03_原始数据'!$E$5:$E$24),"") | G24: =IF(False,STDEV('03_原始数据'!$E$5:$E$24),"")
A25: ='03_原始数据'!A25 | B25: ='03_原始数据'!B25 | C25: ='03_原始数据'!C25 | D25: ='03_原始数据'!E25 | E25: =_xlfn.PERCENTRANK.INC('03_原始数据'!$E$5:$E$873,'03_原始数据'!E25) | F25: =IF(False,AVERAGE('03_原始数据'!$E$5:$E$25),"") | G25: =IF(False,STDEV('03_原始数据'!$E$5:$E$25),"")
A26: ='03_原始数据'!A26 | B26: ='03_原始数据'!B26 | C26: ='03_原始数据'!C26 | D26: ='03_原始数据'!E26 | E26: =_xlfn.PERCENTRANK.INC('03_原始数据'!$E$5:$E$873,'03_原始数据'!E26) | F26: =IF(False,AVERAGE('03_原始数据'!$E$5:$E$26),"") | G26: =IF(False,STDEV('03_原始数据'!$E$5:$E$26),"")
A27: ='03_原始数据'!A27 | B27: ='03_原始数据'!B27 | C27: ='03_原始数据'!C27 | D27: ='03_原始数据'!E27 | E27: =_xlfn.PERCENTRANK.INC('03_原始数据'!$E$5:$E$873,'03_原始数据'!E27) | F27: =IF(False,AVERAGE('03_原始数据'!$E$5:$E$27),"") | G27: =IF(False,STDEV('03_原始数据'!$E$5:$E$27),"")
A28: ='03_原始数据'!A28 | B28: ='03_原始数据'!B28 | C28: ='03_原始数据'!C28 | D28: ='03_原始数据'!E28 | E28: =_xlfn.PERCENTRANK.INC('03_原始数据'!$E$5:$E$873,'03_原始数据'!E28) | F28: =IF(False,AVERAGE('03_原始数据'!$E$5:$E$28),"") | G28: =IF(False,STDEV('03_原始数据'!$E$5:$E$28),"")
A29: ='03_原始数据'!A29 | B29: ='03_原始数据'!B29 | C29: ='03_原始数据'!C29 | D29: ='03_原始数据'!E29 | E29: =_xlfn.PERCENTRANK.INC('03_原始数据'!$E$5:$E$873,'03_原始数据'!E29) | F29: =IF(False,AVERAGE('03_原始数据'!$E$5:$E$29),"") | G29: =IF(False,STDEV('03_原始数据'!$E$5:$E$29),"")
A30: ='03_原始数据'!A30 | B30: ='03_原始数据'!B30 | C30: ='03_原始数据'!C30 | D30: ='03_原始数据'!E30 | E30: =_xlfn.PERCENTRANK.INC('03_原始数据'!$E$5:$E$873,'03_原始数据'!E30) | F30: =IF(False,AVERAGE('03_原始数据'!$E$5:$E$30),"") | G30: =IF(False,STDEV('03_原始数据'!$E$5:$E$30),"")
A31: ='03_原始数据'!A31 | B31: ='03_原始数据'!B31 | C31: ='03_原始数据'!C31 | D31: ='03_原始数据'!E31 | E31: =_xlfn.PERCENTRANK.INC('03_原始数据'!$E$5:$E$873,'03_原始数据'!E31) | F31: =IF(False,AVERAGE('03_原始数据'!$E$5:$E$31),"") | G31: =IF(False,STDEV('03_原始数据'!$E$5:$E$31),"")
A32: ='03_原始数据'!A32 | B32: ='03_原始数据'!B32 | C32: ='03_原始数据'!C32 | D32: ='03_原始数据'!E32 | E32: =_xlfn.PERCENTRANK.INC('03_原始数据'!$E$5:$E$873,'03_原始数据'!E32) | F32: =IF(False,AVERAGE('03_原始数据'!$E$5:$E$32),"") | G32: =IF(False,STDEV('03_原始数据'!$E$5:$E$32),"")
A33: ='03_原始数据'!A33 | B33: ='03_原始数据'!B33 | C33: ='03_原始数据'!C33 | D33: ='03_原始数据'!E33 | E33: =_xlfn.PERCENTRANK.INC('03_原始数据'!$E$5:$E$873,'03_原始数据'!E33) | F33: =IF(False,AVERAGE('03_原始数据'!$E$5:$E$33),"") | G33: =IF(False,STDEV('03_原始数据'!$E$5:$E$33),"")
A34: ='03_原始数据'!A34 | B34: ='03_原始数据'!B34 | C34: ='03_原始数据'!C34 | D34: ='03_原始数据'!E34 | E34: =_xlfn.PERCENTRANK.INC('03_原始数据'!$E$5:$E$873,'03_原始数据'!E34) | F34: =IF(False,AVERAGE('03_原始数据'!$E$5:$E$34),"") | G34: =IF(False,STDEV('03_原始数据'!$E$5:$E$34),"")
A35: ='03_原始数据'!A35 | B35: ='03_原始数据'!B35 | C35: ='03_原始数据'!C35 | D35: ='03_原始数据'!E35 | E35: =_xlfn.PERCENTRANK.INC('03_原始数据'!$E$5:$E$873,'03_原始数据'!E35) | F35: =IF(False,AVERAGE('03_原始数据'!$E$5:$E$35),"") | G35: =IF(False,STDEV('03_原始数据'!$E$5:$E$35),"")
A36: ='03_原始数据'!A36 | B36: ='03_原始数据'!B36 | C36: ='03_原始数据'!C36 | D36: ='03_原始数据'!E36 | E36: =_xlfn.PERCENTRANK.INC('03_原始数据'!$E$5:$E$873,'03_原始数据'!E36) | F36: =IF(False,AVERAGE('03_原始数据'!$E$5:$E$36),"") | G36: =IF(False,STDEV('03_原始数据'!$E$5:$E$36),"")
A37: ='03_原始数据'!A37 | B37: ='03_原始数据'!B37 | C37: ='03_原始数据'!C37 | D37: ='03_原始数据'!E37 | E37: =_xlfn.PERCENTRANK.INC('03_原始数据'!$E$5:$E$873,'03_原始数据'!E37) | F37: =IF(False,AVERAGE('03_原始数据'!$E$5:$E$37),"") | G37: =IF(False,STDEV('03_原始数据'!$E$5:$E$37),"")
A38: ='03_原始数据'!A38 | B38: ='03_原始数据'!B38 | C38: ='03_原始数据'!C38 | D38: ='03_原始数据'!E38 | E38: =_xlfn.PERCENTRANK.INC('03_原始数据'!$E$5:$E$873,'03_原始数据'!E38) | F38: =IF(False,AVERAGE('03_原始数据'!$E$5:$E$38),"") | G38: =IF(False,STDEV('03_原始数据'!$E$5:$E$38),"")
A39: ='03_原始数据'!A39 | B39: ='03_原始数据'!B39 | C39: ='03_原始数据'!C39 | D39: ='03_原始数据'!E39 | E39: =_xlfn.PERCENTRANK.INC('03_原始数据'!$E$5:$E$873,'03_原始数据'!E39) | F39: =IF(False,AVERAGE('03_原始数据'!$E$5:$E$39),"") | G39: =IF(False,STDEV('03_原始数据'!$E$5:$E$39),"")
A40: ='03_原始数据'!A40 | B40: ='03_原始数据'!B40 | C40: ='03_原始数据'!C40 | D40: ='03_原始数据'!E40 | E40: =_xlfn.PERCENTRANK.INC('03_原始数据'!$E$5:$E$873,'03_原始数据'!E40) | F40: =IF(False,AVERAGE('03_原始数据'!$E$5:$E$40),"") | G40: =IF(False,STDEV('03_原始数据'!$E$5:$E$40),"")
A41: ='03_原始数据'!A41 | B41: ='03_原始数据'!B41 | C41: ='03_原始数据'!C41 | D41: ='03_原始数据'!E41 | E41: =_xlfn.PERCENTRANK.INC('03_原始数据'!$E$5:$E$873,'03_原始数据'!E41) | F41: =IF(False,AVERAGE('03_原始数据'!$E$5:$E$41),"") | G41: =IF(False,STDEV('03_原始数据'!$E$5:$E$41),"")
A42: ='03_原始数据'!A42 | B42: ='03_原始数据'!B42 | C42: ='03_原始数据'!C42 | D42: ='03_原始数据'!E42 | E42: =_xlfn.PERCENTRANK.INC('03_原始数据'!$E$5:$E$873,'03_原始数据'!E42) | F42: =IF(False,AVERAGE('03_原始数据'!$E$5:$E$42),"") | G42: =IF(False,STDEV('03_原始数据'!$E$5:$E$42),"")
A43: ='03_原始数据'!A43 | B43: ='03_原始数据'!B43 | C43: ='03_原始数据'!C43 | D43: ='03_原始数据'!E43 | E43: =_xlfn.PERCENTRANK.INC('03_原始数据'!$E$5:$E$873,'03_原始数据'!E43) | F43: =IF(False,AVERAGE('03_原始数据'!$E$5:$E$43),"") | G43: =IF(False,STDEV('03_原始数据'!$E$5:$E$43),"")
A44: ='03_原始数据'!A44 | B44: ='03_原始数据'!B44 | C44: ='03_原始数据'!C44 | D44: ='03_原始数据'!E44 | E44: =_xlfn.PERCENTRANK.INC('03_原始数据'!$E$5:$E$873,'03_原始数据'!E44) | F44: =IF(False,AVERAGE('03_原始数据'!$E$5:$E$44),"") | G44: =IF(False,STDEV('03_原始数据'!$E$5:$E$44),"")
A45: ='03_原始数据'!A45 | B45: ='03_原始数据'!B45 | C45: ='03_原始数据'!C45 | D45: ='03_原始数据'!E45 | E45: =_xlfn.PERCENTRANK.INC('03_原始数据'!$E$5:$E$873,'03_原始数据'!E45) | F45: =IF(False,AVERAGE('03_原始数据'!$E$5:$E$45),"") | G45: =IF(False,STDEV('03_原始数据'!$E$5:$E$45),"")
A46: ='03_原始数据'!A46 | B46: ='03_原始数据'!B46 | C46: ='03_原始数据'!C46 | D46: ='03_原始数据'!E46 | E46: =_xlfn.PERCENTRANK.INC('03_原始数据'!$E$5:$E$873,'03_原始数据'!E46) | F46: =IF(False,AVERAGE('03_原始数据'!$E$5:$E$46),"") | G46: =IF(False,STDEV('03_原始数据'!$E$5:$E$46),"")
A47: ='03_原始数据'!A47 | B47: ='03_原始数据'!B47 | C47: ='03_原始数据'!C47 | D47: ='03_原始数据'!E47 | E47: =_xlfn.PERCENTRANK.INC('03_原始数据'!$E$5:$E$873,'03_原始数据'!E47) | F47: =IF(False,AVERAGE('03_原始数据'!$E$5:$E$47),"") | G47: =IF(False,STDEV('03_原始数据'!$E$5:$E$47),"")
A48: ='03_原始数据'!A48 | B48: ='03_原始数据'!B48 | C48: ='03_原始数据'!C48 | D48: ='03_原始数据'!E48 | E48: =_xlfn.PERCENTRANK.INC('03_原始数据'!$E$5:$E$873,'03_原始数据'!E48) | F48: =IF(False,AVERAGE('03_原始数据'!$E$5:$E$48),"") | G48: =IF(False,STDEV('03_原始数据'!$E$5:$E$48),"")
A49: ='03_原始数据'!A49 | B49: ='03_原始数据'!B49 | C49: ='03_原始数据'!C49 | D49: ='03_原始数据'!E49 | E49: =_xlfn.PERCENTRANK.INC('03_原始数据'!$E$5:$E$873,'03_原始数据'!E49) | F49: =IF(False,AVERAGE('03_原始数据'!$E$5:$E$49),"") | G49: =IF(False,STDEV('03_原始数据'!$E$5:$E$49),"")
A50: ='03_原始数据'!A50 | B50: ='03_原始数据'!B50 | C50: ='03_原始数据'!C50 | D50: ='03_原始数据'!E50 | E50: =_xlfn.PERCENTRANK.INC('03_原始数据'!$E$5:$E$873,'03_原始数据'!E50) | F50: =IF(False,AVERAGE('03_原始数据'!$E$5:$E$50),"") | G50: =IF(False,STDEV('03_原始数据'!$E$5:$E$50),"")
A51: ='03_原始数据'!A51 | B51: ='03_原始数据'!B51 | C51: ='03_原始数据'!C51 | D51: ='03_原始数据'!E51 | E51: =_xlfn.PERCENTRANK.INC('03_原始数据'!$E$5:$E$873,'03_原始数据'!E51) | F51: =IF(False,AVERAGE('03_原始数据'!$E$5:$E$51),"") | G51: =IF(False,STDEV('03_原始数据'!$E$5:$E$51),"")
A52: ='03_原始数据'!A52 | B52: ='03_原始数据'!B52 | C52: ='03_原始数据'!C52 | D52: ='03_原始数据'!E52 | E52: =_xlfn.PERCENTRANK.INC('03_原始数据'!$E$5:$E$873,'03_原始数据'!E52) | F52: =IF(False,AVERAGE('03_原始数据'!$E$5:$E$52),"") | G52: =IF(False,STDEV('03_原始数据'!$E$5:$E$52),"")
A53: ='03_原始数据'!A53 | B53: ='03_原始数据'!B53 | C53: ='03_原始数据'!C53 | D53: ='03_原始数据'!E53 | E53: =_xlfn.PERCENTRANK.INC('03_原始数据'!$E$5:$E$873,'03_原始数据'!E53) | F53: =IF(False,AVERAGE('03_原始数据'!$E$5:$E$53),"") | G53: =IF(False,STDEV('03_原始数据'!$E$5:$E$53),"")
A54: ='03_原始数据'!A54 | B54: ='03_原始数据'!B54 | C54: ='03_原始数据'!C54 | D54: ='03_原始数据'!E54 | E54: =_xlfn.PERCENTRANK.INC('03_原始数据'!$E$5:$E$873,'03_原始数据'!E54) | F54: =IF(False,AVERAGE('03_原始数据'!$E$5:$E$54),"") | G54: =IF(False,STDEV('03_原始数据'!$E$5:$E$54),"")
A55: ='03_原始数据'!A55 | B55: ='03_原始数据'!B55 | C55: ='03_原始数据'!C55 | D55: ='03_原始数据'!E55 | E55: =_xlfn.PERCENTRANK.INC('03_原始数据'!$E$5:$E$873,'03_原始数据'!E55) | F55: =IF(False,AVERAGE('03_原始数据'!$E$5:$E$55),"") | G55: =IF(False,STDEV('03_原始数据'!$E$5:$E$55),"")
A56: ='03_原始数据'!A56 | B56: ='03_原始数据'!B56 | C56: ='03_原始数据'!C56 | D56: ='03_原始数据'!E56 | E56: =_xlfn.PERCENTRANK.INC('03_原始数据'!$E$5:$E$873,'03_原始数据'!E56) | F56: =IF(False,AVERAGE('03_原始数据'!$E$5:$E$56),"") | G56: =IF(False,STDEV('03_原始数据'!$E$5:$E$56),"")
A57: ='03_原始数据'!A57 | B57: ='03_原始数据'!B57 | C57: ='03_原始数据'!C57 | D57: ='03_原始数据'!E57 | E57: =_xlfn.PERCENTRANK.INC('03_原始数据'!$E$5:$E$873,'03_原始数据'!E57) | F57: =IF(False,AVERAGE('03_原始数据'!$E$5:$E$57),"") | G57: =IF(False,STDEV('03_原始数据'!$E$5:$E$57),"")
A58: ='03_原始数据'!A58 | B58: ='03_原始数据'!B58 | C58: ='03_原始数据'!C58 | D58: ='03_原始数据'!E58 | E58: =_xlfn.PERCENTRANK.INC('03_原始数据'!$E$5:$E$873,'03_原始数据'!E58) | F58: =IF(False,AVERAGE('03_原始数据'!$E$5:$E$58),"") | G58: =IF(False,STDEV('03_原始数据'!$E$5:$E$58),"")
A59: ='03_原始数据'!A59 | B59: ='03_原始数据'!B59 | C59: ='03_原始数据'!C59 | D59: ='03_原始数据'!E59 | E59: =_xlfn.PERCENTRANK.INC('03_原始数据'!$E$5:$E$873,'03_原始数据'!E59) | F59: =IF(False,AVERAGE('03_原始数据'!$E$5:$E$59),"") | G59: =IF(False,STDEV('03_原始数据'!$E$5:$E$59),"")
A60: ='03_原始数据'!A60 | B60: ='03_原始数据'!B60 | C60: ='03_原始数据'!C60 | D60: ='03_原始数据'!E60 | E60: =_xlfn.PERCENTRANK.INC('03_原始数据'!$E$5:$E$873,'03_原始数据'!E60) | F60: =IF(False,AVERAGE('03_原始数据'!$E$5:$E$60),"") | G60: =IF(False,STDEV('03_原始数据'!$E$5:$E$60),"")
A61: ='03_原始数据'!A61 | B61: ='03_原始数据'!B61 | C61: ='03_原始数据'!C61 | D61: ='03_原始数据'!E61 | E61: =_xlfn.PERCENTRANK.INC('03_原始数据'!$E$5:$E$873,'03_原始数据'!E61) | F61: =IF(False,AVERAGE('03_原始数据'!$E$5:$E$61),"") | G61: =IF(False,STDEV('03_原始数据'!$E$5:$E$61),"")
A62: ='03_原始数据'!A62 | B62: ='03_原始数据'!B62 | C62: ='03_原始数据'!C62 | D62: ='03_原始数据'!E62 | E62: =_xlfn.PERCENTRANK.INC('03_原始数据'!$E$5:$E$873,'03_原始数据'!E62) | F62: =IF(False,AVERAGE('03_原始数据'!$E$5:$E$62),"") | G62: =IF(False,STDEV('03_原始数据'!$E$5:$E$62),"")
A63: ='03_原始数据'!A63 | B63: ='03_原始数据'!B63 | C63: ='03_原始数据'!C63 | D63: ='03_原始数据'!E63 | E63: =_xlfn.PERCENTRANK.INC('03_原始数据'!$E$5:$E$873,'03_原始数据'!E63) | F63: =IF(False,AVERAGE('03_原始数据'!$E$5:$E$63),"") | G63: =IF(False,STDEV('03_原始数据'!$E$5:$E$63),"")
A64: ='03_原始数据'!A64 | B64: ='03_原始数据'!B64 | C64: ='03_原始数据'!C64 | D64: ='03_原始数据'!E64 | E64: =_xlfn.PERCENTRANK.INC('03_原始数据'!$E$5:$E$873,'03_原始数据'!E64) | F64: =IF(True,AVERAGE('03_原始数据'!$E$5:$E$64),"") | G64: =IF(True,STDEV('03_原始数据'!$E$5:$E$64),"")
A65: ='03_原始数据'!A65 | B65: ='03_原始数据'!B65 | C65: ='03_原始数据'!C65 | D65: ='03_原始数据'!E65 | E65: =_xlfn.PERCENTRANK.INC('03_原始数据'!$E$5:$E$873,'03_原始数据'!E65) | F65: =IF(True,AVERAGE('03_原始数据'!$E$6:$E$65),"") | G65: =IF(True,STDEV('03_原始数据'!$E$6:$E$65),"")
A66: ='03_原始数据'!A66 | B66: ='03_原始数据'!B66 | C66: ='03_原始数据'!C66 | D66: ='03_原始数据'!E66 | E66: =_xlfn.PERCENTRANK.INC('03_原始数据'!$E$5:$E$873,'03_原始数据'!E66) | F66: =IF(True,AVERAGE('03_原始数据'!$E$7:$E$66),"") | G66: =IF(True,STDEV('03_原始数据'!$E$7:$E$66),"")
A67: ='03_原始数据'!A67 | B67: ='03_原始数据'!B67 | C67: ='03_原始数据'!C67 | D67: ='03_原始数据'!E67 | E67: =_xlfn.PERCENTRANK.INC('03_原始数据'!$E$5:$E$873,'03_原始数据'!E67) | F67: =IF(True,AVERAGE('03_原始数据'!$E$8:$E$67),"") | G67: =IF(True,STDEV('03_原始数据'!$E$8:$E$67),"")
A68: ='03_原始数据'!A68 | B68: ='03_原始数据'!B68 | C68: ='03_原始数据'!C68 | D68: ='03_原始数据'!E68 | E68: =_xlfn.PERCENTRANK.INC('03_原始数据'!$E$5:$E$873,'03_原始数据'!E68) | F68: =IF(True,AVERAGE('03_原始数据'!$E$9:$E$68),"") | G68: =IF(True,STDEV('03_原始数据'!$E$9:$E$68),"")
A69: ='03_原始数据'!A69 | B69: ='03_原始数据'!B69 | C69: ='03_原始数据'!C69 | D69: ='03_原始数据'!E69 | E69: =_xlfn.PERCENTRANK.INC('03_原始数据'!$E$5:$E$873,'03_原始数据'!E69) | F69: =IF(True,AVERAGE('03_原始数据'!$E$10:$E$69),"") | G69: =IF(True,STDEV('03_原始数据'!$E$10:$E$69),"")
A70: ='03_原始数据'!A70 | B70: ='03_原始数据'!B70 | C70: ='03_原始数据'!C70 | D70: ='03_原始数据'!E70 | E70: =_xlfn.PERCENTRANK.INC('03_原始数据'!$E$5:$E$873,'03_原始数据'!E70) | F70: =IF(True,AVERAGE('03_原始数据'!$E$11:$E$70),"") | G70: =IF(True,STDEV('03_原始数据'!$E$11:$E$70),"")
A71: ='03_原始数据'!A71 | B71: ='03_原始数据'!B71 | C71: ='03_原始数据'!C71 | D71: ='03_原始数据'!E71 | E71: =_xlfn.PERCENTRANK.INC('03_原始数据'!$E$5:$E$873,'03_原始数据'!E71) | F71: =IF(True,AVERAGE('03_原始数据'!$E$12:$E$71),"") | G71: =IF(True,STDEV('03_原始数据'!$E$12:$E$71),"")
A72: ='03_原始数据'!A72 | B72: ='03_原始数据'!B72 | C72: ='03_原始数据'!C72 | D72: ='03_原始数据'!E72 | E72: =_xlfn.PERCENTRANK.INC('03_原始数据'!$E$5:$E$873,'03_原始数据'!E72) | F72: =IF(True,AVERAGE('03_原始数据'!$E$13:$E$72),"") | G72: =IF(True,STDEV('03_原始数据'!$E$13:$E$72),"")
A73: ='03_原始数据'!A73 | B73: ='03_原始数据'!B73 | C73: ='03_原始数据'!C73 | D73: ='03_原始数据'!E73 | E73: =_xlfn.PERCENTRANK.INC('03_原始数据'!$E$5:$E$873,'03_原始数据'!E73) | F73: =IF(True,AVERAGE('03_原始数据'!$E$14:$E$73),"") | G73: =IF(True,STDEV('03_原始数据'!$E$14:$E$73),"")
A74: ='03_原始数据'!A74 | B74: ='03_原始数据'!B74 | C74: ='03_原始数据'!C74 | D74: ='03_原始数据'!E74 | E74: =_xlfn.PERCENTRANK.INC('03_原始数据'!$E$5:$E$873,'03_原始数据'!E74) | F74: =IF(True,AVERAGE('03_原始数据'!$E$15:$E$74),"") | G74: =IF(True,STDEV('03_原始数据'!$E$15:$E$74),"")
A75: ='03_原始数据'!A75 | B75: ='03_原始数据'!B75 | C75: ='03_原始数据'!C75 | D75: ='03_原始数据'!E75 | E75: =_xlfn.PERCENTRANK.INC('03_原始数据'!$E$5:$E$873,'03_原始数据'!E75) | F75: =IF(True,AVERAGE('03_原始数据'!$E$16:$E$75),"") | G75: =IF(True,STDEV('03_原始数据'!$E$16:$E$75),"")
A76: ='03_原始数据'!A76 | B76: ='03_原始数据'!B76 | C76: ='03_原始数据'!C76 | D76: ='03_原始数据'!E76 | E76: =_xlfn.PERCENTRANK.INC('03_原始数据'!$E$5:$E$873,'03_原始数据'!E76) | F76: =IF(True,AVERAGE('03_原始数据'!$E$17:$E$76),"") | G76: =IF(True,STDEV('03_原始数据'!$E$17:$E$76),"")
A77: ='03_原始数据'!A77 | B77: ='03_原始数据'!B77 | C77: ='03_原始数据'!C77 | D77: ='03_原始数据'!E77 | E77: =_xlfn.PERCENTRANK.INC('03_原始数据'!$E$5:$E$873,'03_原始数据'!E77) | F77: =IF(True,AVERAGE('03_原始数据'!$E$18:$E$77),"") | G77: =IF(True,STDEV('03_原始数据'!$E$18:$E$77),"")
A78: ='03_原始数据'!A78 | B78: ='03_原始数据'!B78 | C78: ='03_原始数据'!C78 | D78: ='03_原始数据'!E78 | E78: =_xlfn.PERCENTRANK.INC('03_原始数据'!$E$5:$E$873,'03_原始数据'!E78) | F78: =IF(True,AVERAGE('03_原始数据'!$E$19:$E$78),"") | G78: =IF(True,STDEV('03_原始数据'!$E$19:$E$78),"")
A79: ='03_原始数据'!A79 | B79: ='03_原始数据'!B79 | C79: ='03_原始数据'!C79 | D79: ='03_原始数据'!E79 | E79: =_xlfn.PERCENTRANK.INC('03_原始数据'!$E$5:$E$873,'03_原始数据'!E79) | F79: =IF(True,AVERAGE('03_原始数据'!$E$20:$E$79),"") | G79: =IF(True,STDEV('03_原始数据'!$E$20:$E$79),"")
A80: ='03_原始数据'!A80 | B80: ='03_原始数据'!B80 | C80: ='03_原始数据'!C80 | D80: ='03_原始数据'!E80 | E80: =_xlfn.PERCENTRANK.INC('03_原始数据'!$E$5:$E$873,'03_原始数据'!E80) | F80: =IF(True,AVERAGE('03_原始数据'!$E$21:$E$80),"") | G80: =IF(True,STDEV('03_原始数据'!$E$21:$E$80),"")
A81: ='03_原始数据'!A81 | B81: ='03_原始数据'!B81 | C81: ='03_原始数据'!C81 | D81: ='03_原始数据'!E81 | E81: =_xlfn.PERCENTRANK.INC('03_原始数据'!$E$5:$E$873,'03_原始数据'!E81) | F81: =IF(True,AVERAGE('03_原始数据'!$E$22:$E$81),"") | G81: =IF(True,STDEV('03_原始数据'!$E$22:$E$81),"")
A82: ='03_原始数据'!A82 | B82: ='03_原始数据'!B82 | C82: ='03_原始数据'!C82 | D82: ='03_原始数据'!E82 | E82: =_xlfn.PERCENTRANK.INC('03_原始数据'!$E$5:$E$873,'03_原始数据'!E82) | F82: =IF(True,AVERAGE('03_原始数据'!$E$23:$E$82),"") | G82: =IF(True,STDEV('03_原始数据'!$E$23:$E$82),"")
A83: ='03_原始数据'!A83 | B83: ='03_原始数据'!B83 | C83: ='03_原始数据'!C83 | D83: ='03_原始数据'!E83 | E83: =_xlfn.PERCENTRANK.INC('03_原始数据'!$E$5:$E$873,'03_原始数据'!E83) | F83: =IF(True,AVERAGE('03_原始数据'!$E$24:$E$83),"") | G83: =IF(True,STDEV('03_原始数据'!$E$24:$E$83),"")
A84: ='03_原始数据'!A84 | B84: ='03_原始数据'!B84 | C84: ='03_原始数据'!C84 | D84: ='03_原始数据'!E84 | E84: =_xlfn.PERCENTRANK.INC('03_原始数据'!$E$5:$E$873,'03_原始数据'!E84) | F84: =IF(True,AVERAGE('03_原始数据'!$E$25:$E$84),"") | G84: =IF(True,STDEV('03_原始数据'!$E$25:$E$84),"")
A85: ='03_原始数据'!A85 | B85: ='03_原始数据'!B85 | C85: ='03_原始数据'!C85 | D85: ='03_原始数据'!E85 | E85: =_xlfn.PERCENTRANK.INC('03_原始数据'!$E$5:$E$873,'03_原始数据'!E85) | F85: =IF(True,AVERAGE('03_原始数据'!$E$26:$E$85),"") | G85: =IF(True,STDEV('03_原始数据'!$E$26:$E$85),"")
A86: ='03_原始数据'!A86 | B86: ='03_原始数据'!B86 | C86: ='03_原始数据'!C86 | D86: ='03_原始数据'!E86 | E86: =_xlfn.PERCENTRANK.INC('03_原始数据'!$E$5:$E$873,'03_原始数据'!E86) | F86: =IF(True,AVERAGE('03_原始数据'!$E$27:$E$86),"") | G86: =IF(True,STDEV('03_原始数据'!$E$27:$E$86),"")
A87: ='03_原始数据'!A87 | B87: ='03_原始数据'!B87 | C87: ='03_原始数据'!C87 | D87: ='03_原始数据'!E87 | E87: =_xlfn.PERCENTRANK.INC('03_原始数据'!$E$5:$E$873,'03_原始数据'!E87) | F87: =IF(True,AVERAGE('03_原始数据'!$E$28:$E$87),"") | G87: =IF(True,STDEV('03_原始数据'!$E$28:$E$87),"")
A88: ='03_原始数据'!A88 | B88: ='03_原始数据'!B88 | C88: ='03_原始数据'!C88 | D88: ='03_原始数据'!E88 | E88: =_xlfn.PERCENTRANK.INC('03_原始数据'!$E$5:$E$873,'03_原始数据'!E88) | F88: =IF(True,AVERAGE('03_原始数据'!$E$29:$E$88),"") | G88: =IF(True,STDEV('03_原始数据'!$E$29:$E$88),"")
A89: ='03_原始数据'!A89 | B89: ='03_原始数据'!B89 | C89: ='03_原始数据'!C89 | D89: ='03_原始数据'!E89 | E89: =_xlfn.PERCENTRANK.INC('03_原始数据'!$E$5:$E$873,'03_原始数据'!E89) | F89: =IF(True,AVERAGE('03_原始数据'!$E$30:$E$89),"") | G89: =IF(True,STDEV('03_原始数据'!$E$30:$E$89),"")
A90: ='03_原始数据'!A90 | B90: ='03_原始数据'!B90 | C90: ='03_原始数据'!C90 | D90: ='03_原始数据'!E90 | E90: =_xlfn.PERCENTRANK.INC('03_原始数据'!$E$5:$E$873,'03_原始数据'!E90) | F90: =IF(True,AVERAGE('03_原始数据'!$E$31:$E$90),"") | G90: =IF(True,STDEV('03_原始数据'!$E$31:$E$90),"")
A91: ='03_原始数据'!A91 | B91: ='03_原始数据'!B91 | C91: ='03_原始数据'!C91 | D91: ='03_原始数据'!E91 | E91: =_xlfn.PERCENTRANK.INC('03_原始数据'!$E$5:$E$873,'03_原始数据'!E91) | F91: =IF(True,AVERAGE('03_原始数据'!$E$32:$E$91),"") | G91: =IF(True,STDEV('03_原始数据'!$E$32:$E$91),"")
A92: ='03_原始数据'!A92 | B92: ='03_原始数据'!B92 | C92: ='03_原始数据'!C92 | D92: ='03_原始数据'!E92 | E92: =_xlfn.PERCENTRANK.INC('03_原始数据'!$E$5:$E$873,'03_原始数据'!E92) | F92: =IF(True,AVERAGE('03_原始数据'!$E$33:$E$92),"") | G92: =IF(True,STDEV('03_原始数据'!$E$33:$E$92),"")
A93: ='03_原始数据'!A93 | B93: ='03_原始数据'!B93 | C93: ='03_原始数据'!C93 | D93: ='03_原始数据'!E93 | E93: =_xlfn.PERCENTRANK.INC('03_原始数据'!$E$5:$E$873,'03_原始数据'!E93) | F93: =IF(True,AVERAGE('03_原始数据'!$E$34:$E$93),"") | G93: =IF(True,STDEV('03_原始数据'!$E$34:$E$93),"")
A94: ='03_原始数据'!A94 | B94: ='03_原始数据'!B94 | C94: ='03_原始数据'!C94 | D94: ='03_原始数据'!E94 | E94: =_xlfn.PERCENTRANK.INC('03_原始数据'!$E$5:$E$873,'03_原始数据'!E94) | F94: =IF(True,AVERAGE('03_原始数据'!$E$35:$E$94),"") | G94: =IF(True,STDEV('03_原始数据'!$E$35:$E$94),"")
A95: ='03_原始数据'!A95 | B95: ='03_原始数据'!B95 | C95: ='03_原始数据'!C95 | D95: ='03_原始数据'!E95 | E95: =_xlfn.PERCENTRANK.INC('03_原始数据'!$E$5:$E$873,'03_原始数据'!E95) | F95: =IF(True,AVERAGE('03_原始数据'!$E$36:$E$95),"") | G95: =IF(True,STDEV('03_原始数据'!$E$36:$E$95),"")
A96: ='03_原始数据'!A96 | B96: ='03_原始数据'!B96 | C96: ='03_原始数据'!C96 | D96: ='03_原始数据'!E96 | E96: =_xlfn.PERCENTRANK.INC('03_原始数据'!$E$5:$E$873,'03_原始数据'!E96) | F96: =IF(True,AVERAGE('03_原始数据'!$E$37:$E$96),"") | G96: =IF(True,STDEV('03_原始数据'!$E$37:$E$96),"")
A97: ='03_原始数据'!A97 | B97: ='03_原始数据'!B97 | C97: ='03_原始数据'!C97 | D97: ='03_原始数据'!E97 | E97: =_xlfn.PERCENTRANK.INC('03_原始数据'!$E$5:$E$873,'03_原始数据'!E97) | F97: =IF(True,AVERAGE('03_原始数据'!$E$38:$E$97),"") | G97: =IF(True,STDEV('03_原始数据'!$E$38:$E$97),"")
A98: ='03_原始数据'!A98 | B98: ='03_原始数据'!B98 | C98: ='03_原始数据'!C98 | D98: ='03_原始数据'!E98 | E98: =_xlfn.PERCENTRANK.INC('03_原始数据'!$E$5:$E$873,'03_原始数据'!E98) | F98: =IF(True,AVERAGE('03_原始数据'!$E$39:$E$98),"") | G98: =IF(True,STDEV('03_原始数据'!$E$39:$E$98),"")
A99: ='03_原始数据'!A99 | B99: ='03_原始数据'!B99 | C99: ='03_原始数据'!C99 | D99: ='03_原始数据'!E99 | E99: =_xlfn.PERCENTRANK.INC('03_原始数据'!$E$5:$E$873,'03_原始数据'!E99) | F99: =IF(True,AVERAGE('03_原始数据'!$E$40:$E$99),"") | G99: =IF(True,STDEV('03_原始数据'!$E$40:$E$99),"")
A100: ='03_原始数据'!A100 | B100: ='03_原始数据'!B100 | C100: ='03_原始数据'!C100 | D100: ='03_原始数据'!E100 | E100: =_xlfn.PERCENTRANK.INC('03_原始数据'!$E$5:$E$873,'03_原始数据'!E100) | F100: =IF(True,AVERAGE('03_原始数据'!$E$41:$E$100),"") | G100: =IF(True,STDEV('03_原始数据'!$E$41:$E$100),"")
A101: ='03_原始数据'!A101 | B101: ='03_原始数据'!B101 | C101: ='03_原始数据'!C101 | D101: ='03_原始数据'!E101 | E101: =_xlfn.PERCENTRANK.INC('03_原始数据'!$E$5:$E$873,'03_原始数据'!E101) | F101: =IF(True,AVERAGE('03_原始数据'!$E$42:$E$101),"") | G101: =IF(True,STDEV('03_原始数据'!$E$42:$E$101),"")
...

Sheet 07_历史分位
A1: 历史分位表
A2: 同一张表同时给出「价差处于什么位置」和「对应多少钱」，便于业务直接引用。
A4: 分位 | B4: 加工价差 元/吨 | C4: 含义 | D4: 分位 | E4: 加工价差 元/吨 | F4: 含义
A5: 0% | B5: =_xlfn.PERCENTILE.INC('03_原始数据'!$E$5:$E$873,0) | C5: 历史最低 | D5: 50% | E5: =_xlfn.PERCENTILE.INC('03_原始数据'!$E$5:$E$873,0.5) | F5: 中位
A6: 1% | B6: =_xlfn.PERCENTILE.INC('03_原始数据'!$E$5:$E$873,0.01) | C6: 极低 | D6: 75% | E6: =_xlfn.PERCENTILE.INC('03_原始数据'!$E$5:$E$873,0.75) | F6: 上四分位
A7: 5% | B7: =_xlfn.PERCENTILE.INC('03_原始数据'!$E$5:$E$873,0.05) | C7: 极低（历史 5% 以下） | D7: 90% | E7: =_xlfn.PERCENTILE.INC('03_原始数据'!$E$5:$E$873,0.9) | F7: 偏高
A8: 10% | B8: =_xlfn.PERCENTILE.INC('03_原始数据'!$E$5:$E$873,0.1) | C8: 偏低 | D8: 95% | E8: =_xlfn.PERCENTILE.INC('03_原始数据'!$E$5:$E$873,0.95) | F8: 极高
A9: 25% | B9: =_xlfn.PERCENTILE.INC('03_原始数据'!$E$5:$E$873,0.25) | C9: 下四分位 | D9: 100% | E9: =_xlfn.PERCENTILE.INC('03_原始数据'!$E$5:$E$873,1) | F9: 历史最高
A11: 定位
A12: 指标 | B12: 数值 | C12: 公式说明
A13: 最新价差 | B13: ='03_原始数据'!E873 | C13: 直接引用最后一行
A14: 最新分位 | B14: =_xlfn.PERCENTRANK.INC('03_原始数据'!$E$5:$E$873,'03_原始数据'!E873) | C14: PERCENTRANK.INC：与 Python 的 pct_rank 定义一致
A15: 均值 | B15: =AVERAGE('03_原始数据'!E5:E873) | C15: 全样本算术均值
A16: 标准差(样本) | B16: =STDEV('03_原始数据'!E5:E873) | C16: STDEV = 样本标准差；STDEV.P 为总体
A17: 偏度 | B17: =SKEW('03_原始数据'!E5:E873) | C17: >0 右偏，说明高位出现过极端值
A18: 峰度 | B18: =KURT('03_原始数据'!E5:E873) | C18: 超额峰度，>0 厚尾
A19: 样本数 N | B19: =COUNT('03_原始数据'!E5:E873) | C19: 成对有效价格数
A20: IQR | B20: =_xlfn.PERCENTILE.INC('03_原始数据'!E5:E873,0.75)-_xlfn.PERCENTILE.INC('03_原始数据'!E5:E873,0.25) | C20: 四分位距，抗极端值
A21: 当前价差／P50 比值 | B21: ='03_原始数据'!E873/_xlfn.PERCENTILE.INC('03_原始数据'!E$5:E$873,0.5) | C21: 相对中位水平的位置

Sheet 08_相关性
A1: 水平相关 vs 收益率相关
A2: 这两个数字不可互相替代：水平高相关多半来自共同趋势，收益率才反映逐期传导。
N3: 辅助：PX 秩 | O3: 辅助：PTA 秩 | P3: 辅助：Δ%PX 秩 | Q3: 辅助：Δ%PTA 秩
A4: 口径 | B4: Pearson r | C4: R² | D4: N | E4: t 统计量 | F4: p 值（双尾） | G4: 95%CI 下限 | H4: 95%CI 上限
A5: 价格水平（PX vs PTA） | B5: =CORREL('03_原始数据'!$B$5:$B$873,'03_原始数据'!$C$5:$C$873) | C5: =RSQ('03_原始数据'!$C$5:$C$873,'03_原始数据'!$B$5:$B$873) | D5: =COUNT('03_原始数据'!$B$5:$B$873) | E5: =B5*SQRT((D5-2)/(1-B5^2)) | F5: =IF(D5>2,_xlfn.T.DIST.2T(ABS(E5),D5-2),"NA") | G5: =TANH(ATANH(B5)-_xlfn.NORM.S.INV(1-Alpha/2)/SQRT(D5-3)) | H5: =TANH(ATANH(B5)+_xlfn.NORM.S.INV(1-Alpha/2)/SQRT(D5-3)) | N5: 767.5 | O5: 690
A6: 日收益率（Δ%PX vs Δ%PTA） | B6: =CORREL('03_原始数据'!$G$6:$G$873,'03_原始数据'!$H$6:$H$873) | C6: =RSQ('03_原始数据'!$H$6:$H$873,'03_原始数据'!$G$6:$G$873) | D6: =COUNT('03_原始数据'!$G$6:$G$873) | E6: =B6*SQRT((D6-2)/(1-B6^2)) | F6: =IF(D6>2,_xlfn.T.DIST.2T(ABS(E6),D6-2),"NA") | G6: =TANH(ATANH(B6)-_xlfn.NORM.S.INV(1-Alpha/2)/SQRT(D6-3)) | H6: =TANH(ATANH(B6)+_xlfn.NORM.S.INV(1-Alpha/2)/SQRT(D6-3)) | N6: 767.5 | O6: 643 | P6: 767 | Q6: 643
A7: 价差 vs PX 水平 | B7: =CORREL('03_原始数据'!$B$5:$B$873,'03_原始数据'!$E$5:$E$873) | C7: =RSQ('03_原始数据'!$E$5:$E$873,'03_原始数据'!$B$5:$B$873) | D7: =COUNT('03_原始数据'!$B$5:$B$873) | E7: =B7*SQRT((D7-2)/(1-B7^2)) | F7: =IF(D7>2,_xlfn.T.DIST.2T(ABS(E7),D7-2),"NA") | G7: =TANH(ATANH(B7)-_xlfn.NORM.S.INV(1-Alpha/2)/SQRT(D7-3)) | H7: =TANH(ATANH(B7)+_xlfn.NORM.S.INV(1-Alpha/2)/SQRT(D7-3)) | N7: 760 | O7: 642 | P7: 760 | Q7: 642
A8: Spearman 秩相关（抗异常值） | N8: 760 | O8: 564 | P8: 760 | Q8: 564
A9: 口径 | B9: Spearman ρ | C9: N | D9: 说明 | N9: 760 | O9: 530 | P9: 760 | Q9: 530
A10: 价格水平 | B10: =CORREL($N$5:$N$873,$O$5:$O$873) | C10: =COUNT('03_原始数据'!$B$5:$B$873) | D10: 秩为数据属性（并列取平均秩），放在灰字辅助列 N/O；本格仍为活公式 | N10: 760 | O10: 539 | P10: 760 | Q10: 539
A11: 日收益率 | B11: =CORREL($P$6:$P$873,$Q$6:$Q$873) | C11: =COUNT('03_原始数据'!$G$6:$G$873) | D11: 同上；收益率的辅助秩在 P/Q。替换数据后请同步重算辅助秩 | N11: 760 | O11: 538 | P11: 760 | Q11: 538
N12: 760 | O12: 536 | P12: 760 | Q12: 536
N13: 760 | O13: 531 | P13: 760 | Q13: 531
A14: 有效样本量校正（Pyper & Peterman） | N14: 760 | O14: 525 | P14: 760 | Q14: 525
A15: 口径 | B15: 原始 N | C15: ρ(PX) | D15: ρ(PTA) | E15: 有效 N | F15: 说明 | N15: 760 | O15: 525 | P15: 760 | Q15: 525
A16: 价格水平 | B16: =COUNT('03_原始数据'!$B$5:$B$873) | C16: =CORREL('03_原始数据'!$B$5:$B$873,ROW('03_原始数据'!$B$5:$B$873)) | D16: =CORREL('03_原始数据'!$C$5:$C$873,ROW('03_原始数据'!$C$5:$C$873)) | E16: =B16*(1-C16*D16)/(1+C16*D16) | F16: 自相关越高，有效样本越少，显著性容易被高估 | N16: 760 | O16: 525 | P16: 760 | Q16: 525
A17: 日收益率 | B17: =COUNT('03_原始数据'!$G$6:$G$873) | C17: =CORREL('03_原始数据'!$G$6:$G$873,ROW('03_原始数据'!$G$6:$G$873)) | D17: =CORREL('03_原始数据'!$H$6:$H$873,ROW('03_原始数据'!$H$6:$H$873)) | E17: =B17*(1-C17*D17)/(1+C17*D17) | F17: 自相关越高，有效样本越少，显著性容易被高估 | N17: 760 | O17: 527 | P17: 760 | Q17: 527
N18: 760 | O18: 540 | P18: 760 | Q18: 540
N19: 760 | O19: 545 | P19: 760 | Q19: 545
N20: 647 | O20: 578 | P20: 647 | Q20: 578
N21: 647 | O21: 578 | P21: 647 | Q21: 578
N22: 647 | O22: 597.5 | P22: 647 | Q22: 597.5
N23: 647 | O23: 597.5 | P23: 647 | Q23: 597.5
N24: 647 | O24: 600 | P24: 647 | Q24: 600
N25: 647 | O25: 580 | P25: 647 | Q25: 580
N26: 647 | O26: 568 | P26: 647 | Q26: 568
N27: 647 | O27: 557.5 | P27: 647 | Q27: 557.5
N28: 647 | O28: 557.5 | P28: 647 | Q28: 557.5
N29: 647 | O29: 560 | P29: 647 | Q29: 560
... N873: 864 | O873: 841.5 | P873: 863 | Q873: 840.5

Sheet 09_滚动相关
A1: 滚动相关系数（活公式）
A2: 窗口内有效样本不足 80% 时返回空，避免小样本噪声；数据源用绝对引用，整块可安全拖动。
A4: 日期 | B4: 滚动20 水平 | C4: 滚动60 水平 | D4: 滚动120 水平 | E4: 滚动60 收益率 | F4: 有效窗口?
A5: ='03_原始数据'!A5 | B5: =IF(0=1,IFERROR(CORREL('03_原始数据'!$B$5:$B$5,'03_原始数据'!$C$5:$C$5),""),"") | C5: =IF(0=1,IFERROR(CORREL('03_原始数据'!$B$5:$B$5,'03_原始数据'!$C$5:$C$5),""),"") | D5: =IF(0=1,IFERROR(CORREL('03_原始数据'!$B$5:$B$5,'03_原始数据'!$C$5:$C$5),""),"") | E5: =IF(0=1,IFERROR(CORREL('03_原始数据'!$G$6:$G$5,'03_原始数据'!$H$6:$H$5),""),"") | F5: =IF(N(B5)=0,"不足","有效")
A6: ='03_原始数据'!A6 | B6: =IF(0=1,IFERROR(CORREL('03_原始数据'!$B$5:$B$6,'03_原始数据'!$C$5:$C$6),""),"") | C6: =IF(0=1,IFERROR(CORREL('03_原始数据'!$B$5:$B$6,'03_原始数据'!$C$5:$C$6),""),"") | D6: =IF(0=1,IFERROR(CORREL('03_原始数据'!$B$5:$B$6,'03_原始数据'!$C$5:$C$6),""),"") | E6: =IF(0=1,IFERROR(CORREL('03_原始数据'!$G$6:$G$6,'03_原始数据'!$H$6:$H$6),""),"") | F6: =IF(N(B6)=0,"不足","有效")
A7: ='03_原始数据'!A7 | B7: =IF(0=1,IFERROR(CORREL('03_原始数据'!$B$5:$B$7,'03_原始数据'!$C$5:$C$7),""),"") | C7: =IF(0=1,IFERROR(CORREL('03_原始数据'!$B$5:$B$7,'03_原始数据'!$C$5:$C$7),""),"") | D7: =IF(0=1,IFERROR(CORREL('03_原始数据'!$B$5:$B$7,'03_原始数据'!$C$5:$C$7),""),"") | E7: =IF(0=1,IFERROR(CORREL('03_原始数据'!$G$6:$G$7,'03_原始数据'!$H$6:$H$7),""),"") | F7: =IF(N(B7)=0,"不足","有效")
A8: ='03_原始数据'!A8 | B8: =IF(0=1,IFERROR(CORREL('03_原始数据'!$B$5:$B$8,'03_原始数据'!$C$5:$C$8),""),"") | C8: =IF(0=1,IFERROR(CORREL('03_原始数据'!$B$5:$B$8,'03_原始数据'!$C$5:$C$8),""),"") | D8: =IF(0=1,IFERROR(CORREL('03_原始数据'!$B$5:$B$8,'03_原始数据'!$C$5:$C$8),""),"") | E8: =IF(0=1,IFERROR(CORREL('03_原始数据'!$G$6:$G$8,'03_原始数据'!$H$6:$H$8),""),"") | F8: =IF(N(B8)=0,"不足","有效")
A9: ='03_原始数据'!A9 | B9: =IF(0=1,IFERROR(CORREL('03_原始数据'!$B$5:$B$9,'03_原始数据'!$C$5:$C$9),""),"") | C9: =IF(0=1,IFERROR(CORREL('03_原始数据'!$B$5:$B$9,'03_原始数据'!$C$5:$C$9),""),"") | D9: =IF(0=1,IFERROR(CORREL('03_原始数据'!$B$5:$B$9,'03_原始数据'!$C$5:$C$9),""),"") | E9: =IF(0=1,IFERROR(CORREL('03_原始数据'!$G$6:$G$9,'03_原始数据'!$H$6:$H$9),""),"") | F9: =IF(N(B9)=0,"不足","有效")
A10: ='03_原始数据'!A10 | B10: =IF(0=1,IFERROR(CORREL('03_原始数据'!$B$5:$B$10,'03_原始数据'!$C$5:$C$10),""),"") | C10: =IF(0=1,IFERROR(CORREL('03_原始数据'!$B$5:$B$10,'03_原始数据'!$C$5:$C$10),""),"") | D10: =IF(0=1,IFERROR(CORREL('03_原始数据'!$B$5:$B$10,'03_原始数据'!$C$5:$C$10),""),"") | E10: =IF(0=1,IFERROR(CORREL('03_原始数据'!$G$6:$G$10,'03_原始数据'!$H$6:$H$10),""),"") | F10: =IF(N(B10)=0,"不足","有效")
A11: ='03_原始数据'!A11 | B11: =IF(0=1,IFERROR(CORREL('03_原始数据'!$B$5:$B$11,'03_原始数据'!$C$5:$C$11),""),"") | C11: =IF(0=1,IFERROR(CORREL('03_原始数据'!$B$5:$B$11,'03_原始数据'!$C$5:$C$11),""),"") | D11: =IF(0=1,IFERROR(CORREL('03_原始数据'!$B$5:$B$11,'03_原始数据'!$C$5:$C$11),""),"") | E11: =IF(0=1,IFERROR(CORREL('03_原始数据'!$G$6:$G$11,'03_原始数据'!$H$6:$H$11),""),"") | F11: =IF(N(B11)=0,"不足","有效")
A12: ='03_原始数据'!A12 | B12: =IF(0=1,IFERROR(CORREL('03_原始数据'!$B$5:$B$12,'03_原始数据'!$C$5:$C$12),""),"") | C12: =IF(0=1,IFERROR(CORREL('03_原始数据'!$B$5:$B$12,'03_原始数据'!$C$5:$C$12),""),"") | D12: =IF(0=1,IFERROR(CORREL('03_原始数据'!$B$5:$B$12,'03_原始数据'!$C$5:$C$12),""),"") | E12: =IF(0=1,IFERROR(CORREL('03_原始数据'!$G$6:$G$12,'03_原始数据'!$H$6:$H$12),""),"") | F12: =IF(N(B12)=0,"不足","有效")
A13: ='03_原始数据'!A13 | B13: =IF(0=1,IFERROR(CORREL('03_原始数据'!$B$5:$B$13,'03_原始数据'!$C$5:$C$13),""),"") | C13: =IF(0=1,IFERROR(CORREL('03_原始数据'!$B$5:$B$13,'03_原始数据'!$C$5:$C$13),""),"") | D13: =IF(0=1,IFERROR(CORREL('03_原始数据'!$B$5:$B$13,'03_原始数据'!$C$5:$C$13),""),"") | E13: =IF(0=1,IFERROR(CORREL('03_原始数据'!$G$6:$G$13,'03_原始数据'!$H$6:$H$13),""),"") | F13: =IF(N(B13)=0,"不足","有效")
A14: ='03_原始数据'!A14 | B14: =IF(0=1,IFERROR(CORREL('03_原始数据'!$B$5:$B$14,'03_原始数据'!$C$5:$C$14),""),"") | C14: =IF(0=1,IFERROR(CORREL('03_原始数据'!$B$5:$B$14,'03_原始数据'!$C$5:$C$14),""),"") | D14: =IF(0=1,IFERROR(CORREL('03_原始数据'!$B$5:$B$14,'03_原始数据'!$C$5:$C$14),""),"") | E14: =IF(0=1,IFERROR(CORREL('03_原始数据'!$G$6:$G$14,'03_原始数据'!$H$6:$H$14),""),"") | F14: =IF(N(B14)=0,"不足","有效")
A15: ='03_原始数据'!A15 | B15: =IF(0=1,IFERROR(CORREL('03_原始数据'!$B$5:$B$15,'03_原始数据'!$C$5:$C$15),""),"") | C15: =IF(0=1,IFERROR(CORREL('03_原始数据'!$B$5:$B$15,'03_原始数据'!$C$5:$C$15),""),"") | D15: =IF(0=1,IFERROR(CORREL('03_原始数据'!$B$5:$B$15,'03_原始数据'!$C$5:$C$15),""),"") | E15: =IF(0=1,IFERROR(CORREL('03_原始数据'!$G$6:$G$15,'03_原始数据'!$H$6:$H$15),""),"") | F15: =IF(N(B15)=0,"不足","有效")
A16: ='03_原始数据'!A16 | B16: =IF(0=1,IFERROR(CORREL('03_原始数据'!$B$5:$B$16,'03_原始数据'!$C$5:$C$16),""),"") | C16: =IF(0=1,IFERROR(CORREL('03_原始数据'!$B$5:$B$16,'03_原始数据'!$C$5:$C$16),""),"") | D16: =IF(0=1,IFERROR(CORREL('03_原始数据'!$B$5:$B$16,'03_原始数据'!$C$5:$C$16),""),"") | E16: =IF(0=1,IFERROR(CORREL('03_原始数据'!$G$6:$G$16,'03_原始数据'!$H$6:$H$16),""),"") | F16: =IF(N(B16)=0,"不足","有效")
A17: ='03_原始数据'!A17 | B17: =IF(0=1,IFERROR(CORREL('03_原始数据'!$B$5:$B$17,'03_原始数据'!$C$5:$C$17),""),"") | C17: =IF(0=1,IFERROR(CORREL('03_原始数据'!$B$5:$B$17,'03_原始数据'!$C$5:$C$17),""),"") | D17: =IF(0=1,IFERROR(CORREL('03_原始数据'!$B$5:$B$17,'03_原始数据'!$C$5:$C$17),""),"") | E17: =IF(0=1,IFERROR(CORREL('03_原始数据'!$G$6:$G$17,'03_原始数据'!$H$6:$H$17),""),"") | F17: =IF(N(B17)=0,"不足","有效")
A18: ='03_原始数据'!A18 | B18: =IF(0=1,IFERROR(CORREL('03_原始数据'!$B$5:$B$18,'03_原始数据'!$C$5:$C$18),""),"") | C18: =IF(0=1,IFERROR(CORREL('03_原始数据'!$B$5:$B$18,'03_原始数据'!$C$5:$C$18),""),"") | D18: =IF(0=1,IFERROR(CORREL('03_原始数据'!$B$5:$B$18,'03_原始数据'!$C$5:$C$18),""),"") | E18: =IF(0=1,IFERROR(CORREL('03_原始数据'!$G$6:$G$18,'03_原始数据'!$H$6:$H$18),""),"") | F18: =IF(N(B18)=0,"不足","有效")
A19: ='03_原始数据'!A19 | B19: =IF(0=1,IFERROR(CORREL('03_原始数据'!$B$5:$B$19,'03_原始数据'!$C$5:$C$19),""),"") | C19: =IF(0=1,IFERROR(CORREL('03_原始数据'!$B$5:$B$19,'03_原始数据'!$C$5:$C$19),""),"") | D19: =IF(0=1,IFERROR(CORREL('03_原始数据'!$B$5:$B$19,'03_原始数据'!$C$5:$C$19),""),"") | E19: =IF(0=1,IFERROR(CORREL('03_原始数据'!$G$6:$G$19,'03_原始数据'!$H$6:$H$19),""),"") | F19: =IF(N(B19)=0,"不足","有效")
A20: ='03_原始数据'!A20 | B20: =IF(1=1,IFERROR(CORREL('03_原始数据'!$B$5:$B$20,'03_原始数据'!$C$5:$C$20),""),"") | C20: =IF(0=1,IFERROR(CORREL('03_原始数据'!$B$5:$B$20,'03_原始数据'!$C$5:$C$20),""),"") | D20: =IF(0=1,IFERROR(CORREL('03_原始数据'!$B$5:$B$20,'03_原始数据'!$C$5:$C$20),""),"") | E20: =IF(0=1,IFERROR(CORREL('03_原始数据'!$G$6:$G$20,'03_原始数据'!$H$6:$H$20),""),"") | F20: =IF(N(B20)=0,"不足","有效")
A21: ='03_原始数据'!A21 | B21: =IF(1=1,IFERROR(CORREL('03_原始数据'!$B$5:$B$21,'03_原始数据'!$C$5:$C$21),""),"") | C21: =IF(0=1,IFERROR(CORREL('03_原始数据'!$B$5:$B$21,'03_原始数据'!$C$5:$C$21),""),"") | D21: =IF(0=1,IFERROR(CORREL('03_原始数据'!$B$5:$B$21,'03_原始数据'!$C$5:$C$21),""),"") | E21: =IF(0=1,IFERROR(CORREL('03_原始数据'!$G$6:$G$21,'03_原始数据'!$H$6:$H$21),""),"") | F21: =IF(N(B21)=0,"不足","有效")
A22: ='03_原始数据'!A22 | B22: =IF(1=1,IFERROR(CORREL('03_原始数据'!$B$5:$B$22,'03_原始数据'!$C$5:$C$22),""),"") | C22: =IF(0=1,IFERROR(CORREL('03_原始数据'!$B$5:$B$22,'03_原始数据'!$C$5:$C$22),""),"") | D22: =IF(0=1,IFERROR(CORREL('03_原始数据'!$B$5:$B$22,'03_原始数据'!$C$5:$C$22),""),"") | E22: =IF(0=1,IFERROR(CORREL('03_原始数据'!$G$6:$G$22,'03_原始数据'!$H$6:$H$22),""),"") | F22: =IF(N(B22)=0,"不足","有效")
A23: ='03_原始数据'!A23 | B23: =IF(1=1,IFERROR(CORREL('03_原始数据'!$B$5:$B$23,'03_原始数据'!$C$5:$C$23),""),"") | C23: =IF(0=1,IFERROR(CORREL('03_原始数据'!$B$5:$B$23,'03_原始数据'!$C$5:$C$23),""),"") | D23: =IF(0=1,IFERROR(CORREL('03_原始数据'!$B$5:$B$23,'03_原始数据'!$C$5:$C$23),""),"") | E23: =IF(0=1,IFERROR(CORREL('03_原始数据'!$G$6:$G$23,'03_原始数据'!$H$6:$H$23),""),"") | F23: =IF(N(B23)=0,"不足","有效")
A24: ='03_原始数据'!A24 | B24: =IF(1=1,IFERROR(CORREL('03_原始数据'!$B$5:$B$24,'03_原始数据'!$C$5:$C$24),""),"") | C24: =IF(0=1,IFERROR(CORREL('03_原始数据'!$B$5:$B$24,'03_原始数据'!$C$5:$C$24),""),"") | D24: =IF(0=1,IFERROR(CORREL('03_原始数据'!$B$5:$B$24,'03_原始数据'!$C$5:$C$24),""),"") | E24: =IF(0=1,IFERROR(CORREL('03_原始数据'!$G$6:$G$24,'03_原始数据'!$H$6:$H$24),""),"") | F24: =IF(N(B24)=0,"不足","有效")
A25: ='03_原始数据'!A25 | B25: =IF(1=1,IFERROR(CORREL('03_原始数据'!$B$6:$B$25,'03_原始数据'!$C$6:$C$25),""),"") | C25: =IF(0=1,IFERROR(CORREL('03_原始数据'!$B$5:$B$25,'03_原始数据'!$C$5:$C$25),""),"") | D25: =IF(0=1,IFERROR(CORREL('03_原始数据'!$B$5:$B$25,'03_原始数据'!$C$5:$C$25),""),"") | E25: =IF(0=1,IFERROR(CORREL('03_原始数据'!$G$6:$G$25,'03_原始数据'!$H$6:$H$25),""),"") | F25: =IF(N(B25)=0,"不足","有效")
A26: ='03_原始数据'!A26 | B26: =IF(1=1,IFERROR(CORREL('03_原始数据'!$B$7:$B$26,'03_原始数据'!$C$7:$C$26),""),"") | C26: =IF(0=1,IFERROR(CORREL('03_原始数据'!$B$5:$B$26,'03_原始数据'!$C$5:$C$26),""),"") | D26: =IF(0=1,IFERROR(CORREL('03_原始数据'!$B$5:$B$26,'03_原始数据'!$C$5:$C$26),""),"") | E26: =IF(0=1,IFERROR(CORREL('03_原始数据'!$G$6:$G$26,'03_原始数据'!$H$6:$H$26),""),"") | F26: =IF(N(B26)=0,"不足","有效")
A27: ='03_原始数据'!A27 | B27: =IF(1=1,IFERROR(CORREL('03_原始数据'!$B$8:$B$27,'03_原始数据'!$C$8:$C$27),""),"") | C27: =IF(0=1,IFERROR(CORREL('03_原始数据'!$B$5:$B$27,'03_原始数据'!$C$5:$C$27),""),"") | D27: =IF(0=1,IFERROR(CORREL('03_原始数据'!$B$5:$B$27,'03_原始数据'!$C$5:$C$27),""),"") | E27: =IF(0=1,IFERROR(CORREL('03_原始数据'!$G$6:$G$27,'03_原始数据'!$H$6:$H$27),""),"") | F27: =IF(N(B27)=0,"不足","有效")
A28: ='03_原始数据'!A28 | B28: =IF(1=1,IFERROR(CORREL('03_原始数据'!$B$9:$B$28,'03_原始数据'!$C$9:$C$28),""),"") | C28: =IF(0=1,IFERROR(CORREL('03_原始数据'!$B$5:$B$28,'03_原始数据'!$C$5:$C$28),""),"") | D28: =IF(0=1,IFERROR(CORREL('03_原始数据'!$B$5:$B$28,'03_原始数据'!$C$5:$C$28),""),"") | E28: =IF(0=1,IFERROR(CORREL('03_原始数据'!$G$6:$G$28,'03_原始数据'!$H$6:$H$28),""),"") | F28: =IF(N(B28)=0,"不足","有效")
A29: ='03_原始数据'!A29 | B29: =IF(1=1,IFERROR(CORREL('03_原始数据'!$B$10:$B$29,'03_原始数据'!$C$10:$C$29),""),"") | C29: =IF(0=1,IFERROR(CORREL('03_原始数据'!$B$5:$B$29,'03_原始数据'!$C$5:$C$29),""),"") | D29: =IF(0=1,IFERROR(CORREL('03_原始数据'!$B$5:$B$29,'03_原始数据'!$C$5:$C$29),""),"") | E29: =IF(0=1,IFERROR(CORREL('03_原始数据'!$G$6:$G$29,'03_原始数据'!$H$6:$H$29),""),"") | F29: =IF(N(B29)=0,"不足","有效")
A30: ='03_原始数据'!A30 | B30: =IF(1=1,IFERROR(CORREL('03_原始数据'!$B$11:$B$30,'03_原始数据'!$C$11:$C$30),""),"") | C30: =IF(0=1,IFERROR(CORREL('03_原始数据'!$B$5:$B$30,'03_原始数据'!$C$5:$C$30),""),"") | D30: =IF(0=1,IFERROR(CORREL('03_原始数据'!$B$5:$B$30,'03_原始数据'!$C$5:$C$30),""),"") | E30: =IF(0=1,IFERROR(CORREL('03_原始数据'!$G$6:$G$30,'03_原始数据'!$H$6:$H$30),""),"") | F30: =IF(N(B30)=0,"不足","有效")
A31: ='03_原始数据'!A31 | B31: =IF(1=1,IFERROR(CORREL('03_原始数据'!$B$12:$B$31,'03_原始数据'!$C$12:$C$31),""),"") | C31: =IF(0=1,IFERROR(CORREL('03_原始数据'!$B$5:$B$31,'03_原始数据'!$C$5:$C$31),""),"") | D31: =IF(0=1,IFERROR(CORREL('03_原始数据'!$B$5:$B$31,'03_原始数据'!$C$5:$C$31),""),"") | E31: =IF(0=1,IFERROR(CORREL('03_原始数据'!$G$6:$G$31,'03_原始数据'!$H$6:$H$31),""),"") | F31: =IF(N(B31)=0,"不足","有效")
A32: ='03_原始数据'!A32 | B32: =IF(1=1,IFERROR(CORREL('03_原始数据'!$B$13:$B$32,'03_原始数据'!$C$13:$C$32),""),"") | C32: =IF(0=1,IFERROR(CORREL('03_原始数据'!$B$5:$B$32,'03_原始数据'!$C$5:$C$32),""),"") | D32: =IF(0=1,IFERROR(CORREL('03_原始数据'!$B$5:$B$32,'03_原始数据'!$C$5:$C$32),""),"") | E32: =IF(0=1,IFERROR(CORREL('03_原始数据'!$G$6:$G$32,'03_原始数据'!$H$6:$H$32),""),"") | F32: =IF(N(B32)=0,"不足","有效")
A33: ='03_原始数据'!A33 | B33: =IF(1=1,IFERROR(CORREL('03_原始数据'!$B$14:$B$33,'03_原始数据'!$C$14:$C$33),""),"") | C33: =IF(0=1,IFERROR(CORREL('03_原始数据'!$B$5:$B$33,'03_原始数据'!$C$5:$C$33),""),"") | D33: =IF(0=1,IFERROR(CORREL('03_原始数据'!$B$5:$B$33,'03_原始数据'!$C$5:$C$33),""),"") | E33: =IF(0=1,IFERROR(CORREL('03_原始数据'!$G$6:$G$33,'03_原始数据'!$H$6:$H$33),""),"") | F33: =IF(N(B33)=0,"不足","有效")
A34: ='03_原始数据'!A34 | B34: =IF(1=1,IFERROR(CORREL('03_原始数据'!$B$15:$B$34,'03_原始数据'!$C$15:$C$34),""),"") | C34: =IF(0=1,IFERROR(CORREL('03_原始数据'!$B$5:$B$34,'03_原始数据'!$C$5:$C$34),""),"") | D34: =IF(0=1,IFERROR(CORREL('03_原始数据'!$B$5:$B$34,'03_原始数据'!$C$5:$C$34),""),"") | E34: =IF(0=1,IFERROR(CORREL('03_原始数据'!$G$6:$G$34,'03_原始数据'!$H$6:$H$34),""),"") | F34: =IF(N(B34)=0,"不足","有效")
A35: ='03_原始数据'!A35 | B35: =IF(1=1,IFERROR(CORREL('03_原始数据'!$B$16:$B$35,'03_原始数据'!$C$16:$C$35),""),"") | C35: =IF(0=1,IFERROR(CORREL('03_原始数据'!$B$5:$B$35,'03_原始数据'!$C$5:$C$35),""),"") | D35: =IF(0=1,IFERROR(CORREL('03_原始数据'!$B$5:$B$35,'03_原始数据'!$C$5:$C$35),""),"") | E35: =IF(0=1,IFERROR(CORREL('03_原始数据'!$G$6:$G$35,'03_原始数据'!$H$6:$H$35),""),"") | F35: =IF(N(B35)=0,"不足","有效")
A36: ='03_原始数据'!A36 | B36: =IF(1=1,IFERROR(CORREL('03_原始数据'!$B$17:$B$36,'03_原始数据'!$C$17:$C$36),""),"") | C36: =IF(0=1,IFERROR(CORREL('03_原始数据'!$B$5:$B$36,'03_原始数据'!$C$5:$C$36),""),"") | D36: =IF(0=1,IFERROR(CORREL('03_原始数据'!$B$5:$B$36,'03_原始数据'!$C$5:$C$36),""),"") | E36: =IF(0=1,IFERROR(CORREL('03_原始数据'!$G$6:$G$36,'03_原始数据'!$H$6:$H$36),""),"") | F36: =IF(N(B36)=0,"不足","有效")
A37: ='03_原始数据'!A37 | B37: =IF(1=1,IFERROR(CORREL('03_原始数据'!$B$18:$B$37,'03_原始数据'!$C$18:$C$37),""),"") | C37: =IF(0=1,IFERROR(CORREL('03_原始数据'!$B$5:$B$37,'03_原始数据'!$C$5:$C$37),""),"") | D37: =IF(0=1,IFERROR(CORREL('03_原始数据'!$B$5:$B$37,'03_原始数据'!$C$5:$C$37),""),"") | E37: =IF(0=1,IFERROR(CORREL('03_原始数据'!$G$6:$G$37,'03_原始数据'!$H$6:$H$37),""),"") | F37: =IF(N(B37)=0,"不足","有效")
A38: ='03_原始数据'!A38 | B38: =IF(1=1,IFERROR(CORREL('03_原始数据'!$B$19:$B$38,'03_原始数据'!$C$19:$C$38),""),"") | C38: =IF(0=1,IFERROR(CORREL('03_原始数据'!$B$5:$B$38,'03_原始数据'!$C$5:$C$38),""),"") | D38: =IF(0=1,IFERROR(CORREL('03_原始数据'!$B$5:$B$38,'03_原始数据'!$C$5:$C$38),""),"") | E38: =IF(0=1,IFERROR(CORREL('03_原始数据'!$G$6:$G$38,'03_原始数据'!$H$6:$H$38),""),"") | F38: =IF(N(B38)=0,"不足","有效")
A39: ='03_原始数据'!A39 | B39: =IF(1=1,IFERROR(CORREL('03_原始数据'!$B$20:$B$39,'03_原始数据'!$C$20:$C$39),""),"") | C39: =IF(0=1,IFERROR(CORREL('03_原始数据'!$B$5:$B$39,'03_原始数据'!$C$5:$C$39),""),"") | D39: =IF(0=1,IFERROR(CORREL('03_原始数据'!$B$5:$B$39,'03_原始数据'!$C$5:$C$39),""),"") | E39: =IF(0=1,IFERROR(CORREL('03_原始数据'!$G$6:$G$39,'03_原始数据'!$H$6:$H$39),""),"") | F39: =IF(N(B39)=0,"不足","有效")
A40: ='03_原始数据'!A40 | B40: =IF(1=1,IFERROR(CORREL('03_原始数据'!$B$21:$B$40,'03_原始数据'!$C$21:$C$40),""),"") | C40: =IF(0=1,IFERROR(CORREL('03_原始数据'!$B$5:$B$40,'03_原始数据'!$C$5:$C$40),""),"") | D40: =IF(0=1,IFERROR(CORREL('03_原始数据'!$B$5:$B$40,'03_原始数据'!$C$5:$C$40),""),"") | E40: =IF(0=1,IFERROR(CORREL('03_原始数据'!$G$6:$G$40,'03_原始数据'!$H$6:$H$40),""),"") | F40: =IF(N(B40)=0,"不足","有效")
A41: ='03_原始数据'!A41 | B41: =IF(1=1,IFERROR(CORREL('03_原始数据'!$B$22:$B$41,'03_原始数据'!$C$22:$C$41),""),"") | C41: =IF(0=1,IFERROR(CORREL('03_原始数据'!$B$5:$B$41,'03_原始数据'!$C$5:$C$41),""),"") | D41: =IF(0=1,IFERROR(CORREL('03_原始数据'!$B$5:$B$41,'03_原始数据'!$C$5:$C$41),""),"") | E41: =IF(0=1,IFERROR(CORREL('03_原始数据'!$G$6:$G$41,'03_原始数据'!$H$6:$H$41),""),"") | F41: =IF(N(B41)=0,"不足","有效")
A42: ='03_原始数据'!A42 | B42: =IF(1=1,IFERROR(CORREL('03_原始数据'!$B$23:$B$42,'03_原始数据'!$C$23:$C$42),""),"") | C42: =IF(0=1,IFERROR(CORREL('03_原始数据'!$B$5:$B$42,'03_原始数据'!$C$5:$C$42),""),"") | D42: =IF(0=1,IFERROR(CORREL('03_原始数据'!$B$5:$B$42,'03_原始数据'!$C$5:$C$42),""),"") | E42: =IF(0=1,IFERROR(CORREL('03_原始数据'!$G$6:$G$42,'03_原始数据'!$H$6:$H$42),""),"") | F42: =IF(N(B42)=0,"不足","有效")
A43: ='03_原始数据'!A43 | B43: =IF(1=1,IFERROR(CORREL('03_原始数据'!$B$24:$B$43,'03_原始数据'!$C$24:$C$43),""),"") | C43: =IF(0=1,IFERROR(CORREL('03_原始数据'!$B$5:$B$43,'03_原始数据'!$C$5:$C$43),""),"") | D43: =IF(0=1,IFERROR(CORREL('03_原始数据'!$B$5:$B$43,'03_原始数据'!$C$5:$C$43),""),"") | E43: =IF(0=1,IFERROR(CORREL('03_原始数据'!$G$6:$G$43,'03_原始数据'!$H$6:$H$43),""),"") | F43: =IF(N(B43)=0,"不足","有效")
A44: ='03_原始数据'!A44 | B44: =IF(1=1,IFERROR(CORREL('03_原始数据'!$B$25:$B$44,'03_原始数据'!$C$25:$C$44),""),"") | C44: =IF(0=1,IFERROR(CORREL('03_原始数据'!$B$5:$B$44,'03_原始数据'!$C$5:$C$44),""),"") | D44: =IF(0=1,IFERROR(CORREL('03_原始数据'!$B$5:$B$44,'03_原始数据'!$C$5:$C$44),""),"") | E44: =IF(0=1,IFERROR(CORREL('03_原始数据'!$G$6:$G$44,'03_原始数据'!$H$6:$H$44),""),"") | F44: =IF(N(B44)=0,"不足","有效")
A45: ='03_原始数据'!A45 | B45: =IF(1=1,IFERROR(CORREL('03_原始数据'!$B$26:$B$45,'03_原始数据'!$C$26:$C$45),""),"") | C45: =IF(0=1,IFERROR(CORREL('03_原始数据'!$B$5:$B$45,'03_原始数据'!$C$5:$C$45),""),"") | D45: =IF(0=1,IFERROR(CORREL('03_原始数据'!$B$5:$B$45,'03_原始数据'!$C$5:$C$45),""),"") | E45: =IF(0=1,IFERROR(CORREL('03_原始数据'!$G$6:$G$45,'03_原始数据'!$H$6:$H$45),""),"") | F45: =IF(N(B45)=0,"不足","有效")
A46: ='03_原始数据'!A46 | B46: =IF(1=1,IFERROR(CORREL('03_原始数据'!$B$27:$B$46,'03_原始数据'!$C$27:$C$46),""),"") | C46: =IF(0=1,IFERROR(CORREL('03_原始数据'!$B$5:$B$46,'03_原始数据'!$C$5:$C$46),""),"") | D46: =IF(0=1,IFERROR(CORREL('03_原始数据'!$B$5:$B$46,'03_原始数据'!$C$5:$C$46),""),"") | E46: =IF(0=1,IFERROR(CORREL('03_原始数据'!$G$6:$G$46,'03_原始数据'!$H$6:$H$46),""),"") | F46: =IF(N(B46)=0,"不足","有效")
A47: ='03_原始数据'!A47 | B47: =IF(1=1,IFERROR(CORREL('03_原始数据'!$B$28:$B$47,'03_原始数据'!$C$28:$C$47),""),"") | C47: =IF(0=1,IFERROR(CORREL('03_原始数据'!$B$5:$B$47,'03_原始数据'!$C$5:$C$47),""),"") | D47: =IF(0=1,IFERROR(CORREL('03_原始数据'!$B$5:$B$47,'03_原始数据'!$C$5:$C$47),""),"") | E47: =IF(0=1,IFERROR(CORREL('03_原始数据'!$G$6:$G$47,'03_原始数据'!$H$6:$H$47),""),"") | F47: =IF(N(B47)=0,"不足","有效")
A48: ='03_原始数据'!A48 | B48: =IF(1=1,IFERROR(CORREL('03_原始数据'!$B$29:$B$48,'03_原始数据'!$C$29:$C$48),""),"") | C48: =IF(0=1,IFERROR(CORREL('03_原始数据'!$B$5:$B$48,'03_原始数据'!$C$5:$C$48),""),"") | D48: =IF(0=1,IFERROR(CORREL('03_原始数据'!$B$5:$B$48,'03_原始数据'!$C$5:$C$48),""),"") | E48: =IF(0=1,IFERROR(CORREL('03_原始数据'!$G$6:$G$48,'03_原始数据'!$H$6:$H$48),""),"") | F48: =IF(N(B48)=0,"不足","有效")
A49: ='03_原始数据'!A49 | B49: =IF(1=1,IFERROR(CORREL('03_原始数据'!$B$30:$B$49,'03_原始数据'!$C$30:$C$49),""),"") | C49: =IF(0=1,IFERROR(CORREL('03_原始数据'!$B$5:$B$49,'03_原始数据'!$C$5:$C$49),""),"") | D49: =IF(0=1,IFERROR(CORREL('03_原始数据'!$B$5:$B$49,'03_原始数据'!$C$5:$C$49),""),"") | E49: =IF(0=1,IFERROR(CORREL('03_原始数据'!$G$6:$G$49,'03_原始数据'!$H$6:$H$49),""),"") | F49: =IF(N(B49)=0,"不足","有效")
A50: ='03_原始数据'!A50 | B50: =IF(1=1,IFERROR(CORREL('03_原始数据'!$B$31:$B$50,'03_原始数据'!$C$31:$C$50),""),"") | C50: =IF(0=1,IFERROR(CORREL('03_原始数据'!$B$5:$B$50,'03_原始数据'!$C$5:$C$50),""),"") | D50: =IF(0=1,IFERROR(CORREL('03_原始数据'!$B$5:$B$50,'03_原始数据'!$C$5:$C$50),""),"") | E50: =IF(0=1,IFERROR(CORREL('03_原始数据'!$G$6:$G$50,'03_原始数据'!$H$6:$H$50),""),"") | F50: =IF(N(B50)=0,"不足","有效")
A51: ='03_原始数据'!A51 | B51: =IF(1=1,IFERROR(CORREL('03_原始数据'!$B$32:$B$51,'03_原始数据'!$C$32:$C$51),""),"") | C51: =IF(0=1,IFERROR(CORREL('03_原始数据'!$B$5:$B$51,'03_原始数据'!$C$5:$C$51),""),"") | D51: =IF(0=1,IFERROR(CORREL('03_原始数据'!$B$5:$B$51,'03_原始数据'!$C$5:$C$51),""),"") | E51: =IF(0=1,IFERROR(CORREL('03_原始数据'!$G$6:$G$51,'03_原始数据'!$H$6:$H$51),""),"") | F51: =IF(N(B51)=0,"不足","有效")
A52: ='03_原始数据'!A52 | B52: =IF(1=1,IFERROR(CORREL('03_原始数据'!$B$33:$B$52,'03_原始数据'!$C$33:$C$52),""),"") | C52: =IF(1=1,IFERROR(CORREL('03_原始数据'!$B$5:$B$52,'03_原始数据'!$C$5:$C$52),""),"") | D52: =IF(0=1,IFERROR(CORREL('03_原始数据'!$B$5:$B$52,'03_原始数据'!$C$5:$C$52),""),"") | E52: =IF(0=1,IFERROR(CORREL('03_原始数据'!$G$6:$G$52,'03_原始数据'!$H$6:$H$52),""),"") | F52: =IF(N(B52)=0,"不足","有效")
A53: ='03_原始数据'!A53 | B53: =IF(1=1,IFERROR(CORREL('03_原始数据'!$B$34:$B$53,'03_原始数据'!$C$34:$C$53),""),"") | C53: =IF(1=1,IFERROR(CORREL('03_原始数据'!$B$5:$B$53,'03_原始数据'!$C$5:$C$53),""),"") | D53: =IF(0=1,IFERROR(CORREL('03_原始数据'!$B$5:$B$53,'03_原始数据'!$C$5:$C$53),""),"") | E53: =IF(1=1,IFERROR(CORREL('03_原始数据'!$G$6:$G$53,'03_原始数据'!$H$6:$H$53),""),"") | F53: =IF(N(B53)=0,"不足","有效")
A54: ='03_原始数据'!A54 | B54: =IF(1=1,IFERROR(CORREL('03_原始数据'!$B$35:$B$54,'03_原始数据'!$C$35:$C$54),""),"") | C54: =IF(1=1,IFERROR(CORREL('03_原始数据'!$B$5:$B$54,'03_原始数据'!$C$5:$C$54),""),"") | D54: =IF(0=1,IFERROR(CORREL('03_原始数据'!$B$5:$B$54,'03_原始数据'!$C$5:$C$54),""),"") | E54: =IF(1=1,IFERROR(CORREL('03_原始数据'!$G$6:$G$54,'03_原始数据'!$H$6:$H$54),""),"") | F54: =IF(N(B54)=0,"不足","有效")
A55: ='03_原始数据'!A55 | B55: =IF(1=1,IFERROR(CORREL('03_原始数据'!$B$36:$B$55,'03_原始数据'!$C$36:$C$55),""),"") | C55: =IF(1=1,IFERROR(CORREL('03_原始数据'!$B$5:$B$55,'03_原始数据'!$C$5:$C$55),""),"") | D55: =IF(0=1,IFERROR(CORREL('03_原始数据'!$B$5:$B$55,'03_原始数据'!$C$5:$C$55),""),"") | E55: =IF(1=1,IFERROR(CORREL('03_原始数据'!$G$6:$G$55,'03_原始数据'!$H$6:$H$55),""),"") | F55: =IF(N(B55)=0,"不足","有效")
A56: ='03_原始数据'!A56 | B56: =IF(1=1,IFERROR(CORREL('03_原始数据'!$B$37:$B$56,'03_原始数据'!$C$37:$C$56),""),"") | C56: =IF(1=1,IFERROR(CORREL('03_原始数据'!$B$5:$B$56,'03_原始数据'!$C$5:$C$56),""),"") | D56: =IF(0=1,IFERROR(CORREL('03_原始数据'!$B$5:$B$56,'03_原始数据'!$C$5:$C$56),""),"") | E56: =IF(1=1,IFERROR(CORREL('03_原始数据'!$G$6:$G$56,'03_原始数据'!$H$6:$H$56),""),"") | F56: =IF(N(B56)=0,"不足","有效")
A57: ='03_原始数据'!A57 | B57: =IF(1=1,IFERROR(CORREL('03_原始数据'!$B$38:$B$57,'03_原始数据'!$C$38:$C$57),""),"") | C57: =IF(1=1,IFERROR(CORREL('03_原始数据'!$B$5:$B$57,'03_原始数据'!$C$5:$C$57),""),"") | D57: =IF(0=1,IFERROR(CORREL('03_原始数据'!$B$5:$B$57,'03_原始数据'!$C$5:$C$57),""),"") | E57: =IF(1=1,IFERROR(CORREL('03_原始数据'!$G$6:$G$57,'03_原始数据'!$H$6:$H$57),""),"") | F57: =IF(N(B57)=0,"不足","有效")
A58: ='03_原始数据'!A58 | B58: =IF(1=1,IFERROR(CORREL('03_原始数据'!$B$39:$B$58,'03_原始数据'!$C$39:$C$58),""),"") | C58: =IF(1=1,IFERROR(CORREL('03_原始数据'!$B$5:$B$58,'03_原始数据'!$C$5:$C$58),""),"") | D58: =IF(0=1,IFERROR(CORREL('03_原始数据'!$B$5:$B$58,'03_原始数据'!$C$5:$C$58),""),"") | E58: =IF(1=1,IFERROR(CORREL('03_原始数据'!$G$6:$G$58,'03_原始数据'!$H$6:$H$58),""),"") | F58: =IF(N(B58)=0,"不足","有效")
A59: ='03_原始数据'!A59 | B59: =IF(1=1,IFERROR(CORREL('03_原始数据'!$B$40:$B$59,'03_原始数据'!$C$40:$C$59),""),"") | C59: =IF(1=1,IFERROR(CORREL('03_原始数据'!$B$5:$B$59,'03_原始数据'!$C$5:$C$59),""),"") | D59: =IF(0=1,IFERROR(CORREL('03_原始数据'!$B$5:$B$59,'03_原始数据'!$C$5:$C$59),""),"") | E59: =IF(1=1,IFERROR(CORREL('03_原始数据'!$G$6:$G$59,'03_原始数据'!$H$6:$H$59),""),"") | F59: =IF(N(B59)=0,"不足","有效")
A60: ='03_原始数据'!A60 | B60: =IF(1=1,IFERROR(CORREL('03_原始数据'!$B$41:$B$60,'03_原始数据'!$C$41:$C$60),""),"") | C60: =IF(1=1,IFERROR(CORREL('03_原始数据'!$B$5:$B$60,'03_原始数据'!$C$5:$C$60),""),"") | D60: =IF(0=1,IFERROR(CORREL('03_原始数据'!$B$5:$B$60,'03_原始数据'!$C$5:$C$60),""),"") | E60: =IF(1=1,IFERROR(CORREL('03_原始数据'!$G$6:$G$60,'03_原始数据'!$H$6:$H$60),""),"") | F60: =IF(N(B60)=0,"不足","有效")
A61: ='03_原始数据'!A61 | B61: =IF(1=1,IFERROR(CORREL('03_原始数据'!$B$42:$B$61,'03_原始数据'!$C$42:$C$61),""),"") | C61: =IF(1=1,IFERROR(CORREL('03_原始数据'!$B$5:$B$61,'03_原始数据'!$C$5:$C$61),""),"") | D61: =IF(0=1,IFERROR(CORREL('03_原始数据'!$B$5:$B$61,'03_原始数据'!$C$5:$C$61),""),"") | E61: =IF(1=1,IFERROR(CORREL('03_原始数据'!$G$6:$G$61,'03_原始数据'!$H$6:$H$61),""),"") | F61: =IF(N(B61)=0,"不足","有效")
A62: ='03_原始数据'!A62 | B62: =IF(1=1,IFERROR(CORREL('03_原始数据'!$B$43:$B$62,'03_原始数据'!$C$43:$C$62),""),"") | C62: =IF(1=1,IFERROR(CORREL('03_原始数据'!$B$5:$B$62,'03_原始数据'!$C$5:$C$62),""),"") | D62: =IF(0=1,IFERROR(CORREL('03_原始数据'!$B$5:$B$62,'03_原始数据'!$C$5:$C$62),""),"") | E62: =IF(1=1,IFERROR(CORREL('03_原始数据'!$G$6:$G$62,'03_原始数据'!$H$6:$H$62),""),"") | F62: =IF(N(B62)=0,"不足","有效")
A63: ='03_原始数据'!A63 | B63: =IF(1=1,IFERROR(CORREL('03_原始数据'!$B$44:$B$63,'03_原始数据'!$C$44:$C$63),""),"") | C63: =IF(1=1,IFERROR(CORREL('03_原始数据'!$B$5:$B$63,'03_原始数据'!$C$5:$C$63),""),"") | D63: =IF(0=1,IFERROR(CORREL('03_原始数据'!$B$5:$B$63,'03_原始数据'!$C$5:$C$63),""),"") | E63: =IF(1=1,IFERROR(CORREL('03_原始数据'!$G$6:$G$63,'03_原始数据'!$H$6:$H$63),""),"") | F63: =IF(N(B63)=0,"不足","有效")
A64: ='03_原始数据'!A64 | B64: =IF(1=1,IFERROR(CORREL('03_原始数据'!$B$45:$B$64,'03_原始数据'!$C$45:$C$64),""),"") | C64: =IF(1=1,IFERROR(CORREL('03_原始数据'!$B$5:$B$64,'03_原始数据'!$C$5:$C$64),""),"") | D64: =IF(0=1,IFERROR(CORREL('03_原始数据'!$B$5:$B$64,'03_原始数据'!$C$5:$C$64),""),"") | E64: =IF(1=1,IFERROR(CORREL('03_原始数据'!$G$6:$G$64,'03_原始数据'!$H$6:$H$64),""),"") | F64: =IF(N(B64)=0,"不足","有效")
A65: ='03_原始数据'!A65 | B65: =IF(1=1,IFERROR(CORREL('03_原始数据'!$B$46:$B$65,'03_原始数据'!$C$46:$C$65),""),"") | C65: =IF(1=1,IFERROR(CORREL('03_原始数据'!$B$6:$B$65,'03_原始数据'!$C$6:$C$65),""),"") | D65: =IF(0=1,IFERROR(CORREL('03_原始数据'!$B$5:$B$65,'03_原始数据'!$C$5:$C$65),""),"") | E65: =IF(1=1,IFERROR(CORREL('03_原始数据'!$G$6:$G$65,'03_原始数据'!$H$6:$H$65),""),"") | F65: =IF(N(B65)=0,"不足","有效")
A66: ='03_原始数据'!A66 | B66: =IF(1=1,IFERROR(CORREL('03_原始数据'!$B$47:$B$66,'03_原始数据'!$C$47:$C$66),""),"") | C66: =IF(1=1,IFERROR(CORREL('03_原始数据'!$B$7:$B$66,'03_原始数据'!$C$7:$C$66),""),"") | D66: =IF(0=1,IFERROR(CORREL('03_原始数据'!$B$5:$B$66,'03_原始数据'!$C$5:$C$66),""),"") | E66: =IF(1=1,IFERROR(CORREL('03_原始数据'!$G$7:$G$66,'03_原始数据'!$H$7:$H$66),""),"") | F66: =IF(N(B66)=0,"不足","有效")
A67: ='03_原始数据'!A67 | B67: =IF(1=1,IFERROR(CORREL('03_原始数据'!$B$48:$B$67,'03_原始数据'!$C$48:$C$67),""),"") | C67: =IF(1=1,IFERROR(CORREL('03_原始数据'!$B$8:$B$67,'03_原始数据'!$C$8:$C$67),""),"") | D67: =IF(0=1,IFERROR(CORREL('03_原始数据'!$B$5:$B$67,'03_原始数据'!$C$5:$C$67),""),"") | E67: =IF(1=1,IFERROR(CORREL('03_原始数据'!$G$8:$G$67,'03_原始数据'!$H$8:$H$67),""),"") | F67: =IF(N(B67)=0,"不足","有效")
A68: ='03_原始数据'!A68 | B68: =IF(1=1,IFERROR(CORREL('03_原始数据'!$B$49:$B$68,'03_原始数据'!$C$49:$C$68),""),"") | C68: =IF(1=1,IFERROR(CORREL('03_原始数据'!$B$9:$B$68,'03_原始数据'!$C$9:$C$68),""),"") | D68: =IF(0=1,IFERROR(CORREL('03_原始数据'!$B$5:$B$68,'03_原始数据'!$C$5:$C$68),""),"") | E68: =IF(1=1,IFERROR(CORREL('03_原始数据'!$G$9:$G$68,'03_原始数据'!$H$9:$H$68),""),"") | F68: =IF(N(B68)=0,"不足","有效")
A69: ='03_原始数据'!A69 | B69: =IF(1=1,IFERROR(CORREL('03_原始数据'!$B$50:$B$69,'03_原始数据'!$C$50:$C$69),""),"") | C69: =IF(1=1,IFERROR(CORREL('03_原始数据'!$B$10:$B$69,'03_原始数据'!$C$10:$C$69),""),"") | D69: =IF(0=1,IFERROR(CORREL('03_原始数据'!$B$5:$B$69,'03_原始数据'!$C$5:$C$69),""),"") | E69: =IF(1=1,IFERROR(CORREL('03_原始数据'!$G$10:$G$69,'03_原始数据'!$H$10:$H$69),""),"") | F69: =IF(N(B69)=0,"不足","有效")
A70: ='03_原始数据'!A70 | B70: =IF(1=1,IFERROR(CORREL('03_原始数据'!$B$51:$B$70,'03_原始数据'!$C$51:$C$70),""),"") | C70: =IF(1=1,IFERROR(CORREL('03_原始数据'!$B$11:$B$70,'03_原始数据'!$C$11:$C$70),""),"") | D70: =IF(0=1,IFERROR(CORREL('03_原始数据'!$B$5:$B$70,'03_原始数据'!$C$5:$C$70),""),"") | E70: =IF(1=1,IFERROR(CORREL('03_原始数据'!$G$11:$G$70,'03_原始数据'!$H$11:$H$70),""),"") | F70: =IF(N(B70)=0,"不足","有效")
A71: ='03_原始数据'!A71 | B71: =IF(1=1,IFERROR(CORREL('03_原始数据'!$B$52:$B$71,'03_原始数据'!$C$52:$C$71),""),"") | C71: =IF(1=1,IFERROR(CORREL('03_原始数据'!$B$12:$B$71,'03_原始数据'!$C$12:$C$71),""),"") | D71: =IF(0=1,IFERROR(CORREL('03_原始数据'!$B$5:$B$71,'03_原始数据'!$C$5:$C$71),""),"") | E71: =IF(1=1,IFERROR(CORREL('03_原始数据'!$G$12:$G$71,'03_原始数据'!$H$12:$H$71),""),"") | F71: =IF(N(B71)=0,"不足","有效")
A72: ='03_原始数据'!A72 | B72: =IF(1=1,IFERROR(CORREL('03_原始数据'!$B$53:$B$72,'03_原始数据'!$C$53:$C$72),""),"") | C72: =IF(1=1,IFERROR(CORREL('03_原始数据'!$B$13:$B$72,'03_原始数据'!$C$13:$C$72),""),"") | D72: =IF(0=1,IFERROR(CORREL('03_原始数据'!$B$5:$B$72,'03_原始数据'!$C$5:$C$72),""),"") | E72: =IF(1=1,IFERROR(CORREL('03_原始数据'!$G$13:$G$72,'03_原始数据'!$H$13:$H$72),""),"") | F72: =IF(N(B72)=0,"不足","有效")
A73: ='03_原始数据'!A73 | B73: =IF(1=1,IFERROR(CORREL('03_原始数据'!$B$54:$B$73,'03_原始数据'!$C$54:$C$73),""),"") | C73: =IF(1=1,IFERROR(CORREL('03_原始数据'!$B$14:$B$73,'03_原始数据'!$C$14:$C$73),""),"") | D73: =IF(0=1,IFERROR(CORREL('03_原始数据'!$B$5:$B$73,'03_原始数据'!$C$5:$C$73),""),"") | E73: =IF(1=1,IFERROR(CORREL('03_原始数据'!$G$14:$G$73,'03_原始数据'!$H$14:$H$73),""),"") | F73: =IF(N(B73)=0,"不足","有效")
A74: ='03_原始数据'!A74 | B74: =IF(1=1,IFERROR(CORREL('03_原始数据'!$B$55:$B$74,'03_原始数据'!$C$55:$C$74),""),"") | C74: =IF(1=1,IFERROR(CORREL('03_原始数据'!$B$15:$B$74,'03_原始数据'!$C$15:$C$74),""),"") | D74: =IF(0=1,IFERROR(CORREL('03_原始数据'!$B$5:$B$74,'03_原始数据'!$C$5:$C$74),""),"") | E74: =IF(1=1,IFERROR(CORREL('03_原始数据'!$G$15:$G$74,'03_原始数据'!$H$15:$H$74),""),"") | F74: =IF(N(B74)=0,"不足","有效")
A75: ='03_原始数据'!A75 | B75: =IF(1=1,IFERROR(CORREL('03_原始数据'!$B$56:$B$75,'03_原始数据'!$C$56:$C$75),""),"") | C75: =IF(1=1,IFERROR(CORREL('03_原始数据'!$B$16:$B$75,'03_原始数据'!$C$16:$C$75),""),"") | D75: =IF(0=1,IFERROR(CORREL('03_原始数据'!$B$5:$B$75,'03_原始数据'!$C$5:$C$75),""),"") | E75: =IF(1=1,IFERROR(CORREL('03_原始数据'!$G$16:$G$75,'03_原始数据'!$H$16:$H$75),""),"") | F75: =IF(N(B75)=0,"不足","有效")
A76: ='03_原始数据'!A76 | B76: =IF(1=1,IFERROR(CORREL('03_原始数据'!$B$57:$B$76,'03_原始数据'!$C$57:$C$76),""),"") | C76: =IF(1=1,IFERROR(CORREL('03_原始数据'!$B$17:$B$76,'03_原始数据'!$C$17:$C$76),""),"") | D76: =IF(0=1,IFERROR(CORREL('03_原始数据'!$B$5:$B$76,'03_原始数据'!$C$5:$C$76),""),"") | E76: =IF(1=1,IFERROR(CORREL('03_原始数据'!$G$17:$G$76,'03_原始数据'!$H$17:$H$76),""),"") | F76: =IF(N(B76)=0,"不足","有效")
A77: ='03_原始数据'!A77 | B77: =IF(1=1,IFERROR(CORREL('03_原始数据'!$B$58:$B$77,'03_原始数据'!$C$58:$C$77),""),"") | C77: =IF(1=1,IFERROR(CORREL('03_原始数据'!$B$18:$B$77,'03_原始数据'!$C$18:$C$77),""),"") | D77: =IF(0=1,IFERROR(CORREL('03_原始数据'!$B$5:$B$77,'03_原始数据'!$C$5:$C$77),""),"") | E77: =IF(1=1,IFERROR(CORREL('03_原始数据'!$G$18:$G$77,'03_原始数据'!$H$18:$H$77),""),"") | F77: =IF(N(B77)=0,"不足","有效")
A78: ='03_原始数据'!A78 | B78: =IF(1=1,IFERROR(CORREL('03_原始数据'!$B$59:$B$78,'03_原始数据'!$C$59:$C$78),""),"") | C78: =IF(1=1,IFERROR(CORREL('03_原始数据'!$B$19:$B$78,'03_原始数据'!$C$19:$C$78),""),"") | D78: =IF(0=1,IFERROR(CORREL('03_原始数据'!$B$5:$B$78,'03_原始数据'!$C$5:$C$78),""),"") | E78: =IF(1=1,IFERROR(CORREL('03_原始数据'!$G$19:$G$78,'03_原始数据'!$H$19:$H$78),""),"") | F78: =IF(N(B78)=0,"不足","有效")
A79: ='03_原始数据'!A79 | B79: =IF(1=1,IFERROR(CORREL('03_原始数据'!$B$60:$B$79,'03_原始数据'!$C$60:$C$79),""),"") | C79: =IF(1=1,IFERROR(CORREL('03_原始数据'!$B$20:$B$79,'03_原始数据'!$C$20:$C$79),""),"") | D79: =IF(0=1,IFERROR(CORREL('03_原始数据'!$B$5:$B$79,'03_原始数据'!$C$5:$C$79),""),"") | E79: =IF(1=1,IFERROR(CORREL('03_原始数据'!$G$20:$G$79,'03_原始数据'!$H$20:$H$79),""),"") | F79: =IF(N(B79)=0,"不足","有效")
A80: ='03_原始数据'!A80 | B80: =IF(1=1,IFERROR(CORREL('03_原始数据'!$B$61:$B$80,'03_原始数据'!$C$61:$C$80),""),"") | C80: =IF(1=1,IFERROR(CORREL('03_原始数据'!$B$21:$B$80,'03_原始数据'!$C$21:$C$80),""),"") | D80: =IF(0=1,IFERROR(CORREL('03_原始数据'!$B$5:$B$80,'03_原始数据'!$C$5:$C$80),""),"") | E80: =IF(1=1,IFERROR(CORREL('03_原始数据'!$G$21:$G$80,'03_原始数据'!$H$21:$H$80),""),"") | F80: =IF(N(B80)=0,"不足","有效")
A81: ='03_原始数据'!A81 | B81: =IF(1=1,IFERROR(CORREL('03_原始数据'!$B$62:$B$81,'03_原始数据'!$C$62:$C$81),""),"") | C81: =IF(1=1,IFERROR(CORREL('03_原始数据'!$B$22:$B$81,'03_原始数据'!$C$22:$C$81),""),"") | D81: =IF(0=1,IFERROR(CORREL('03_原始数据'!$B$5:$B$81,'03_原始数据'!$C$5:$C$81),""),"") | E81: =IF(1=1,IFERROR(CORREL('03_原始数据'!$G$22:$G$81,'03_原始数据'!$H$22:$H$81),""),"") | F81: =IF(N(B81)=0,"不足","有效")
A82: ='03_原始数据'!A82 | B82: =IF(1=1,IFERROR(CORREL('03_原始数据'!$B$63:$B$82,'03_原始数据'!$C$63:$C$82),""),"") | C82: =IF(1=1,IFERROR(CORREL('03_原始数据'!$B$23:$B$82,'03_原始数据'!$C$23:$C$82),""),"") | D82: =IF(0=1,IFERROR(CORREL('03_原始数据'!$B$5:$B$82,'03_原始数据'!$C$5:$C$82),""),"") | E82: =IF(1=1,IFERROR(CORREL('03_原始数据'!$G$23:$G$82,'03_原始数据'!$H$23:$H$82),""),"") | F82: =IF(N(B82)=0,"不足","有效")
A83: ='03_原始数据'!A83 | B83: =IF(1=1,IFERROR(CORREL('03_原始数据'!$B$64:$B$83,'03_原始数据'!$C$64:$C$83),""),"") | C83: =IF(1=1,IFERROR(CORREL('03_原始数据'!$B$24:$B$83,'03_原始数据'!$C$24:$C$83),""),"") | D83: =IF(0=1,IFERROR(CORREL('03_原始数据'!$B$5:$B$83,'03_原始数据'!$C$5:$C$83),""),"") | E83: =IF(1=1,IFERROR(CORREL('03_原始数据'!$G$24:$G$83,'03_原始数据'!$H$24:$H$83),""),"") | F83: =IF(N(B83)=0,"不足","有效")
A84: ='03_原始数据'!A84 | B84: =IF(1=1,IFERROR(CORREL('03_原始数据'!$B$65:$B$84,'03_原始数据'!$C$65:$C$84),""),"") | C84: =IF(1=1,IFERROR(CORREL('03_原始数据'!$B$25:$B$84,'03_原始数据'!$C$25:$C$84),""),"") | D84: =IF(0=1,IFERROR(CORREL('03_原始数据'!$B$5:$B$84,'03_原始数据'!$C$5:$C$84),""),"") | E84: =IF(1=1,IFERROR(CORREL('03_原始数据'!$G$25:$G$84,'03_原始数据'!$H$25:$H$84),""),"") | F84: =IF(N(B84)=0,"不足","有效")
A85: ='03_原始数据'!A85 | B85: =IF(1=1,IFERROR(CORREL('03_原始数据'!$B$66:$B$85,'03_原始数据'!$C$66:$C$85),""),"") | C85: =IF(1=1,IFERROR(CORREL('03_原始数据'!$B$26:$B$85,'03_原始数据'!$C$26:$C$85),""),"") | D85: =IF(0=1,IFERROR(CORREL('03_原始数据'!$B$5:$B$85,'03_原始数据'!$C$5:$C$85),""),"") | E85: =IF(1=1,IFERROR(CORREL('03_原始数据'!$G$26:$G$85,'03_原始数据'!$H$26:$H$85),""),"") | F85: =IF(N(B85)=0,"不足","有效")
A86: ='03_原始数据'!A86 | B86: =IF(1=1,IFERROR(CORREL('03_原始数据'!$B$67:$B$86,'03_原始数据'!$C$67:$C$86),""),"") | C86: =IF(1=1,IFERROR(CORREL('03_原始数据'!$B$27:$B$86,'03_原始数据'!$C$27:$C$86),""),"") | D86: =IF(0=1,IFERROR(CORREL('03_原始数据'!$B$5:$B$86,'03_原始数据'!$C$5:$C$86),""),"") | E86: =IF(1=1,IFERROR(CORREL('03_原始数据'!$G$27:$G$86,'03_原始数据'!$H$27:$H$86),""),"") | F86: =IF(N(B86)=0,"不足","有效")
A87: ='03_原始数据'!A87 | B87: =IF(1=1,IFERROR(CORREL('03_原始数据'!$B$68:$B$87,'03_原始数据'!$C$68:$C$87),""),"") | C87: =IF(1=1,IFERROR(CORREL('03_原始数据'!$B$28:$B$87,'03_原始数据'!$C$28:$C$87),""),"") | D87: =IF(0=1,IFERROR(CORREL('03_原始数据'!$B$5:$B$87,'03_原始数据'!$C$5:$C$87),""),"") | E87: =IF(1=1,IFERROR(CORREL('03_原始数据'!$G$28:$G$87,'03_原始数据'!$H$28:$H$87),""),"") | F87: =IF(N(B87)=0,"不足","有效")
A88: ='03_原始数据'!A88 | B88: =IF(1=1,IFERROR(CORREL('03_原始数据'!$B$69:$B$88,'03_原始数据'!$C$69:$C$88),""),"") | C88: =IF(1=1,IFERROR(CORREL('03_原始数据'!$B$29:$B$88,'03_原始数据'!$C$29:$C$88),""),"") | D88: =IF(0=1,IFERROR(CORREL('03_原始数据'!$B$5:$B$88,'03_原始数据'!$C$5:$C$88),""),"") | E88: =IF(1=1,IFERROR(CORREL('03_原始数据'!$G$29:$G$88,'03_原始数据'!$H$29:$H$88),""),"") | F88: =IF(N(B88)=0,"不足","有效")
A89: ='03_原始数据'!A89 | B89: =IF(1=1,IFERROR(CORREL('03_原始数据'!$B$70:$B$89,'03_原始数据'!$C$70:$C$89),""),"") | C89: =IF(1=1,IFERROR(CORREL('03_原始数据'!$B$30:$B$89,'03_原始数据'!$C$30:$C$89),""),"") | D89: =IF(0=1,IFERROR(CORREL('03_原始数据'!$B$5:$B$89,'03_原始数据'!$C$5:$C$89),""),"") | E89: =IF(1=1,IFERROR(CORREL('03_原始数据'!$G$30:$G$89,'03_原始数据'!$H$30:$H$89),""),"") | F89: =IF(N(B89)=0,"不足","有效")
A90: ='03_原始数据'!A90 | B90: =IF(1=1,IFERROR(CORREL('03_原始数据'!$B$71:$B$90,'03_原始数据'!$C$71:$C$90),""),"") | C90: =IF(1=1,IFERROR(CORREL('03_原始数据'!$B$31:$B$90,'03_原始数据'!$C$31:$C$90),""),"") | D90: =IF(0=1,IFERROR(CORREL('03_原始数据'!$B$5:$B$90,'03_原始数据'!$C$5:$C$90),""),"") | E90: =IF(1=1,IFERROR(CORREL('03_原始数据'!$G$31:$G$90,'03_原始数据'!$H$31:$H$90),""),"") | F90: =IF(N(B90)=0,"不足","有效")
A91: ='03_原始数据'!A91 | B91: =IF(1=1,IFERROR(CORREL('03_原始数据'!$B$72:$B$91,'03_原始数据'!$C$72:$C$91),""),"") | C91: =IF(1=1,IFERROR(CORREL('03_原始数据'!$B$32:$B$91,'03_原始数据'!$C$32:$C$91),""),"") | D91: =IF(0=1,IFERROR(CORREL('03_原始数据'!$B$5:$B$91,'03_原始数据'!$C$5:$C$91),""),"") | E91: =IF(1=1,IFERROR(CORREL('03_原始数据'!$G$32:$G$91,'03_原始数据'!$H$32:$H$91),""),"") | F91: =IF(N(B91)=0,"不足","有效")
A92: ='03_原始数据'!A92 | B92: =IF(1=1,IFERROR(CORREL('03_原始数据'!$B$73:$B$92,'03_原始数据'!$C$73:$C$92),""),"") | C92: =IF(1=1,IFERROR(CORREL('03_原始数据'!$B$33:$B$92,'03_原始数据'!$C$33:$C$92),""),"") | D92: =IF(0=1,IFERROR(CORREL('03_原始数据'!$B$5:$B$92,'03_原始数据'!$C$5:$C$92),""),"") | E92: =IF(1=1,IFERROR(CORREL('03_原始数据'!$G$33:$G$92,'03_原始数据'!$H$33:$H$92),""),"") | F92: =IF(N(B92)=0,"不足","有效")
A93: ='03_原始数据'!A93 | B93: =IF(1=1,IFERROR(CORREL('03_原始数据'!$B$74:$B$93,'03_原始数据'!$C$74:$C$93),""),"") | C93: =IF(1=1,IFERROR(CORREL('03_原始数据'!$B$34:$B$93,'03_原始数据'!$C$34:$C$93),""),"") | D93: =IF(0=1,IFERROR(CORREL('03_原始数据'!$B$5:$B$93,'03_原始数据'!$C$5:$C$93),""),"") | E93: =IF(1=1,IFERROR(CORREL('03_原始数据'!$G$34:$G$93,'03_原始数据'!$H$34:$H$93),""),"") | F93: =IF(N(B93)=0,"不足","有效")
A94: ='03_原始数据'!A94 | B94: =IF(1=1,IFERROR(CORREL('03_原始数据'!$B$75:$B$94,'03_原始数据'!$C$75:$C$94),""),"") | C94: =IF(1=1,IFERROR(CORREL('03_原始数据'!$B$35:$B$94,'03_原始数据'!$C$35:$C$94),""),"") | D94: =IF(0=1,IFERROR(CORREL('03_原始数据'!$B$5:$B$94,'03_原始数据'!$C$5:$C$94),""),"") | E94: =IF(1=1,IFERROR(CORREL('03_原始数据'!$G$35:$G$94,'03_原始数据'!$H$35:$H$94),""),"") | F94: =IF(N(B94)=0,"不足","有效")
A95: ='03_原始数据'!A95 | B95: =IF(1=1,IFERROR(CORREL('03_原始数据'!$B$76:$B$95,'03_原始数据'!$C$76:$C$95),""),"") | C95: =IF(1=1,IFERROR(CORREL('03_原始数据'!$B$36:$B$95,'03_原始数据'!$C$36:$C$95),""),"") | D95: =IF(0=1,IFERROR(CORREL('03_原始数据'!$B$5:$B$95,'03_原始数据'!$C$5:$C$95),""),"") | E95: =IF(1=1,IFERROR(CORREL('03_原始数据'!$G$36:$G$95,'03_原始数据'!$H$36:$H$95),""),"") | F95: =IF(N(B95)=0,"不足","有效")
A96: ='03_原始数据'!A96 | B96: =IF(1=1,IFERROR(CORREL('03_原始数据'!$B$77:$B$96,'03_原始数据'!$C$77:$C$96),""),"") | C96: =IF(1=1,IFERROR(CORREL('03_原始数据'!$B$37:$B$96,'03_原始数据'!$C$37:$C$96),""),"") | D96: =IF(0=1,IFERROR(CORREL('03_原始数据'!$B$5:$B$96,'03_原始数据'!$C$5:$C$96),""),"") | E96: =IF(1=1,IFERROR(CORREL('03_原始数据'!$G$37:$G$96,'03_原始数据'!$H$37:$H$96),""),"") | F96: =IF(N(B96)=0,"不足","有效")
A97: ='03_原始数据'!A97 | B97: =IF(1=1,IFERROR(CORREL('03_原始数据'!$B$78:$B$97,'03_原始数据'!$C$78:$C$97),""),"") | C97: =IF(1=1,IFERROR(CORREL('03_原始数据'!$B$38:$B$97,'03_原始数据'!$C$38:$C$97),""),"") | D97: =IF(0=1,IFERROR(CORREL('03_原始数据'!$B$5:$B$97,'03_原始数据'!$C$5:$C$97),""),"") | E97: =IF(1=1,IFERROR(CORREL('03_原始数据'!$G$38:$G$97,'03_原始数据'!$H$38:$H$97),""),"") | F97: =IF(N(B97)=0,"不足","有效")
A98: ='03_原始数据'!A98 | B98: =IF(1=1,IFERROR(CORREL('03_原始数据'!$B$79:$B$98,'03_原始数据'!$C$79:$C$98),""),"") | C98: =IF(1=1,IFERROR(CORREL('03_原始数据'!$B$39:$B$98,'03_原始数据'!$C$39:$C$98),""),"") | D98: =IF(0=1,IFERROR(CORREL('03_原始数据'!$B$5:$B$98,'03_原始数据'!$C$5:$C$98),""),"") | E98: =IF(1=1,IFERROR(CORREL('03_原始数据'!$G$39:$G$98,'03_原始数据'!$H$39:$H$98),""),"") | F98: =IF(N(B98)=0,"不足","有效")
A99: ='03_原始数据'!A99 | B99: =IF(1=1,IFERROR(CORREL('03_原始数据'!$B$80:$B$99,'03_原始数据'!$C$80:$C$99),""),"") | C99: =IF(1=1,IFERROR(CORREL('03_原始数据'!$B$40:$B$99,'03_原始数据'!$C$40:$C$99),""),"") | D99: =IF(0=1,IFERROR(CORREL('03_原始数据'!$B$5:$B$99,'03_原始数据'!$C$5:$C$99),""),"") | E99: =IF(1=1,IFERROR(CORREL('03_原始数据'!$G$40:$G$99,'03_原始数据'!$H$40:$H$99),""),"") | F99: =IF(N(B99)=0,"不足","有效")
A100: ='03_原始数据'!A100 | B100: =IF(1=1,IFERROR(CORREL('03_原始数据'!$B$81:$B$100,'03_原始数据'!$C$81:$C$100),""),"") | C100: =IF(1=1,IFERROR(CORREL('03_原始数据'!$B$41:$B$100,'03_原始数据'!$C$41:$C$100),""),"") | D100: =IF(1=1,IFERROR(CORREL('03_原始数据'!$B$5:$B$100,'03_原始数据'!$C$5:$C$100),""),"") | E100: =IF(1=1,IFERROR(CORREL('03_原始数据'!$G$41:$G$100,'03_原始数据'!$H$41:$H$100),""),"") | F100: =IF(N(B100)=0,"不足","有效")
A101: ='03_原始数据'!A101 | B101: =IF(1=1,IFERROR(CORREL('03_原始数据'!$B$82:$B$101,'03_原始数据'!$C$82:$C$101),""),"") | C101: =IF(1=1,IFERROR(CORREL('03_原始数据'!$B$42:$B$101,'03_原始数据'!$C$42:$C$101),""),"") | D101: =IF(1=1,IFERROR(CORREL('03_原始数据'!$B$5:$B$101,'03_原始数据'!$C$5:$C$101),""),"") | E101: =IF(1=1,IFERROR(CORREL('03_原始数据'!$G$42:$G$101,'03_原始数据'!$H$42:$H$101),""),"") | F101: =IF(N(B101)=0,"不足","有效")
...

Sheet 10_领先滞后
A1: 交叉相关（领先/滞后）
A2: 正 lag = PX 领先 PTA；水平与收益率两套口径分别看，结论以后者为准。
A4: lag | B4: 水平 r | C4: 水平 N | D4: 收益率 r | E4: 收益率 N | F4: 方向
A5: -10 | B5: =CORREL('03_原始数据'!$B$15:$B$873,'03_原始数据'!$C$5:$C$863) | C5: =COUNT('03_原始数据'!$B$15:$B$873) | D5: =CORREL('03_原始数据'!$G$16:$G$873,'03_原始数据'!$H$6:$H$863) | E5: =COUNT('03_原始数据'!$G$16:$G$873) | F5: PTA 领先
A6: -9 | B6: =CORREL('03_原始数据'!$B$14:$B$873,'03_原始数据'!$C$5:$C$864) | C6: =COUNT('03_原始数据'!$B$14:$B$873) | D6: =CORREL('03_原始数据'!$G$15:$G$873,'03_原始数据'!$H$6:$H$864) | E6: =COUNT('03_原始数据'!$G$15:$G$873) | F6: PTA 领先
A7: -8 | B7: =CORREL('03_原始数据'!$B$13:$B$873,'03_原始数据'!$C$5:$C$865) | C7: =COUNT('03_原始数据'!$B$13:$B$873) | D7: =CORREL('03_原始数据'!$G$14:$G$873,'03_原始数据'!$H$6:$H$865) | E7: =COUNT('03_原始数据'!$G$14:$G$873) | F7: PTA 领先
A8: -7 | B8: =CORREL('03_原始数据'!$B$12:$B$873,'03_原始数据'!$C$5:$C$866) | C8: =COUNT('03_原始数据'!$B$12:$B$873) | D8: =CORREL('03_原始数据'!$G$13:$G$873,'03_原始数据'!$H$6:$H$866) | E8: =COUNT('03_原始数据'!$G$13:$G$873) | F8: PTA 领先
A9: -6 | B9: =CORREL('03_原始数据'!$B$11:$B$873,'03_原始数据'!$C$5:$C$867) | C9: =COUNT('03_原始数据'!$B$11:$B$873) | D9: =CORREL('03_原始数据'!$G$12:$G$873,'03_原始数据'!$H$6:$H$867) | E9: =COUNT('03_原始数据'!$G$12:$G$873) | F9: PTA 领先
A10: -5 | B10: =CORREL('03_原始数据'!$B$10:$B$873,'03_原始数据'!$C$5:$C$868) | C10: =COUNT('03_原始数据'!$B$10:$B$873) | D10: =CORREL('03_原始数据'!$G$11:$G$873,'03_原始数据'!$H$6:$H$868) | E10: =COUNT('03_原始数据'!$G$11:$G$873) | F10: PTA 领先
A11: -4 | B11: =CORREL('03_原始数据'!$B$9:$B$873,'03_原始数据'!$C$5:$C$869) | C11: =COUNT('03_原始数据'!$B$9:$B$873) | D11: =CORREL('03_原始数据'!$G$10:$G$873,'03_原始数据'!$H$6:$H$869) | E11: =COUNT('03_原始数据'!$G$10:$G$873) | F11: PTA 领先
A12: -3 | B12: =CORREL('03_原始数据'!$B$8:$B$873,'03_原始数据'!$C$5:$C$870) | C12: =COUNT('03_原始数据'!$B$8:$B$873) | D12: =CORREL('03_原始数据'!$G$9:$G$873,'03_原始数据'!$H$6:$H$870) | E12: =COUNT('03_原始数据'!$G$9:$G$873) | F12: PTA 领先
A13: -2 | B13: =CORREL('03_原始数据'!$B$7:$B$873,'03_原始数据'!$C$5:$C$871) | C13: =COUNT('03_原始数据'!$B$7:$B$873) | D13: =CORREL('03_原始数据'!$G$8:$G$873,'03_原始数据'!$H$6:$H$871) | E13: =COUNT('03_原始数据'!$G$8:$G$873) | F13: PTA 领先
A14: -1 | B14: =CORREL('03_原始数据'!$B$6:$B$873,'03_原始数据'!$C$5:$C$872) | C14: =COUNT('03_原始数据'!$B$6:$B$873) | D14: =CORREL('03_原始数据'!$G$7:$G$873,'03_原始数据'!$H$6:$H$872) | E14: =COUNT('03_原始数据'!$G$7:$G$873) | F14: PTA 领先
A15: 0 | B15: =CORREL('03_原始数据'!$B$5:$B$873,'03_原始数据'!$C$5:$C$873) | C15: =COUNT('03_原始数据'!$B$5:$B$873) | D15: =CORREL('03_原始数据'!$G$6:$G$873,'03_原始数据'!$H$6:$H$873) | E15: =COUNT('03_原始数据'!$G$6:$G$873) | F15: 同步
A16: 1 | B16: =CORREL('03_原始数据'!$B$5:$B$872,'03_原始数据'!$C$6:$C$873) | C16: =COUNT('03_原始数据'!$B$5:$B$872) | D16: =CORREL('03_原始数据'!$G$6:$G$872,'03_原始数据'!$H$7:$H$873) | E16: =COUNT('03_原始数据'!$G$6:$G$872) | F16: PX 领先
A17: 2 | B17: =CORREL('03_原始数据'!$B$5:$B$871,'03_原始数据'!$C$7:$C$873) | C17: =COUNT('03_原始数据'!$B$5:$B$871) | D17: =CORREL('03_原始数据'!$G$6:$G$871,'03_原始数据'!$H$8:$H$873) | E17: =COUNT('03_原始数据'!$G$6:$G$871) | F17: PX 领先
A18: 3 | B18: =CORREL('03_原始数据'!$B$5:$B$870,'03_原始数据'!$C$8:$C$873) | C18: =COUNT('03_原始数据'!$B$5:$B$870) | D18: =CORREL('03_原始数据'!$G$6:$G$870,'03_原始数据'!$H$9:$H$873) | E18: =COUNT('03_原始数据'!$G$6:$G$870) | F18: PX 领先
A19: 4 | B19: =CORREL('03_原始数据'!$B$5:$B$869,'03_原始数据'!$C$9:$C$873) | C19: =COUNT('03_原始数据'!$B$5:$B$869) | D19: =CORREL('03_原始数据'!$G$6:$G$869,'03_原始数据'!$H$10:$H$873) | E19: =COUNT('03_原始数据'!$G$6:$G$869) | F19: PX 领先
A20: 5 | B20: =CORREL('03_原始数据'!$B$5:$B$868,'03_原始数据'!$C$10:$C$873) | C20: =COUNT('03_原始数据'!$B$5:$B$868) | D20: =CORREL('03_原始数据'!$G$6:$G$868,'03_原始数据'!$H$11:$H$873) | E20: =COUNT('03_原始数据'!$G$6:$G$868) | F20: PX 领先
A21: 6 | B21: =CORREL('03_原始数据'!$B$5:$B$867,'03_原始数据'!$C$11:$C$873) | C21: =COUNT('03_原始数据'!$B$5:$B$867) | D21: =CORREL('03_原始数据'!$G$6:$G$867,'03_原始数据'!$H$12:$H$873) | E21: =COUNT('03_原始数据'!$G$6:$G$867) | F21: PX 领先
A22: 7 | B22: =CORREL('03_原始数据'!$B$5:$B$866,'03_原始数据'!$C$12:$C$873) | C22: =COUNT('03_原始数据'!$B$5:$B$866) | D22: =CORREL('03_原始数据'!$G$6:$G$866,'03_原始数据'!$H$13:$H$873) | E22: =COUNT('03_原始数据'!$G$6:$G$866) | F22: PX 领先
A23: 8 | B23: =CORREL('03_原始数据'!$B$5:$B$865,'03_原始数据'!$C$13:$C$873) | C23: =COUNT('03_原始数据'!$B$5:$B$865) | D23: =CORREL('03_原始数据'!$G$6:$G$865,'03_原始数据'!$H$14:$H$873) | E23: =COUNT('03_原始数据'!$G$6:$G$865) | F23: PX 领先
A24: 9 | B24: =CORREL('03_原始数据'!$B$5:$B$864,'03_原始数据'!$C$14:$C$873) | C24: =COUNT('03_原始数据'!$B$5:$B$864) | D24: =CORREL('03_原始数据'!$G$6:$G$864,'03_原始数据'!$H$15:$H$873) | E24: =COUNT('03_原始数据'!$G$6:$G$864) | F24: PX 领先
A25: 10 | B25: =CORREL('03_原始数据'!$B$5:$B$863,'03_原始数据'!$C$15:$C$873) | C25: =COUNT('03_原始数据'!$B$5:$B$863) | D25: =CORREL('03_原始数据'!$G$6:$G$863,'03_原始数据'!$H$16:$H$873) | E25: =COUNT('03_原始数据'!$G$6:$G$863) | F25: PX 领先
A27: 峰值（最大正相关所在 lag）
A28: 口径 | B28: 峰值 lag | C28: 峰值 r | D28: 说明
A29: 价格水平 | B29: =INDEX($A$5:$A$25,MATCH(MAX($B$5:$B$25),$B$5:$B$25,0)) | C29: =MAX($B$5:$B$25) | D29: MAX 找最大正相关所在 lag；若要看反向领先需另看 MIN
A30: 日收益率 | B30: =INDEX($A$5:$A$25,MATCH(MAX($D$5:$D$25),$D$5:$D$25,0)) | C30: =MAX($D$5:$D$25) | D30: 收益率口径噪声更大，峰值也更不稳定

Sheet 11_阶段与背离
A1: 分阶段统计与背离区间
A2: 阶段按产业逻辑预定义（不按结果反复切）；背离区间由方向冲突规则识别。
A4: 阶段 | B4: 名称 | C4: 起 | D4: 止 | E4: N | F4: PX 涨跌 | G4: PTA 涨跌 | H4: 价差均值 | I4: 区段水平相关 r
A5: S1 | B5: PX扩能兑现+PTA过剩，加工费中枢下移 | C5: 2023-10-07 | D5: 2024-12-31 | E5: ='03_原始数据'!$O$5-'03_原始数据'!$N$5+1 | F5: =INDEX('03_原始数据'!$B$5:$B$873,324)/INDEX('03_原始数据'!$B$5:$B$873,1)-1 | G5: =INDEX('03_原始数据'!$C$5:$C$873,324)/INDEX('03_原始数据'!$C$5:$C$873,1)-1 | H5: =AVERAGE(OFFSET('03_原始数据'!$E$5,'03_原始数据'!$N$5-5,0,'03_原始数据'!$O$5-'03_原始数据'!$N$5+1,1)) | I5: =CORREL(OFFSET('03_原始数据'!$B$5,'03_原始数据'!$N$5-5,0,'03_原始数据'!$O$5-'03_原始数据'!$N$5+1,1),OFFSET('03_原始数据'!$C$5,'03_原始数据'!$N$5-5,0,'03_原始数据'!$O$5-'03_原始数据'!$N$5+1,1))
A6: S2 | B6: PX供给趋紧、PTA加工费走阔 | C6: 2025-01-01 | D6: 2025-12-31 | E6: ='03_原始数据'!$O$6-'03_原始数据'!$N$6+1 | F6: =INDEX('03_原始数据'!$B$5:$B$873,618)/INDEX('03_原始数据'!$B$5:$B$873,325)-1 | G6: =INDEX('03_原始数据'!$C$5:$C$873,618)/INDEX('03_原始数据'!$C$5:$C$873,325)-1 | H6: =AVERAGE(OFFSET('03_原始数据'!$E$5,'03_原始数据'!$N$6-5,0,'03_原始数据'!$O$6-'03_原始数据'!$N$6+1,1)) | I6: =CORREL(OFFSET('03_原始数据'!$B$5,'03_原始数据'!$N$6-5,0,'03_原始数据'!$O$6-'03_原始数据'!$N$6+1,1),OFFSET('03_原始数据'!$C$5,'03_原始数据'!$N$6-5,0,'03_原始数据'!$O$6-'03_原始数据'!$N$6+1,1))
A7: S3 | B7: PTA集中检修+地缘油价扰动 | C7: 2026-01-01 | D7: 2026-10-20 | E7: ='03_原始数据'!$O$7-'03_原始数据'!$N$7+1 | F7: =INDEX('03_原始数据'!$B$5:$B$873,869)/INDEX('03_原始数据'!$B$5:$B$873,619)-1 | G7: =INDEX('03_原始数据'!$C$5:$C$873,869)/INDEX('03_原始数据'!$C$5:$C$873,619)-1 | H7: =AVERAGE(OFFSET('03_原始数据'!$E$5,'03_原始数据'!$N$7-5,0,'03_原始数据'!$O$7-'03_原始数据'!$N$7+1,1)) | I7: =CORREL(OFFSET('03_原始数据'!$B$5,'03_原始数据'!$N$7-5,0,'03_原始数据'!$O$7-'03_原始数据'!$N$7+1,1),OFFSET('03_原始数据'!$C$5,'03_原始数据'!$N$7-5,0,'03_原始数据'!$O$7-'03_原始数据'!$N$7+1,1))
A10: 背离区间（|20 观测 ΔPX| ≥ 3% 且 PTA 方向相反）
A11: 起点 | B11: 终点 | C11: 天数 | D11: PX 涨跌 | E11: PTA 涨跌 | F11: 价差变化
A12: 2023-11-09 | B12: 2023-11-21 | C12: 9 | D12: 0 | E12: -0.0023 | F12: -13.8
A13: 2024-10-06 | B13: 2024-10-16 | C13: 9 | D13: -0.0204 | E13: -0.0083 | F13: 57.2
A14: 注：区段相关用 INDEX 取区间（而非 AVERAGEIFS 比较日期文本），起止日期改到区间外时会自动跟随；若某阶段边界在数据中不存在，该行会被跳过。
A15: 2026-02-17 | B15: 2026-02-22 | C15: 5 | D15: 0 | E15: 0.0025 | F15: 13
A16: 2026-05-15 | B16: 2026-05-20 | C16: 5 | D16: 0 | E16: 0.0106 | F16: 69
A17: 2026-06-07 | B17: 2026-06-14 | C17: 7 | D17: 0 | E17: -0.0193 | F17: -127.7
A18: 2026-07-14 | B18: 2026-07-20 | C18: 6 | D18: 0.0633 | E18: -0.001 | F18: -333.7

Sheet 12_公式说明
A1: 公式说明与使用陷阱
A2: 照抄公式前先看这一页：每个函数的口径差异都会改变结论。
A4: 用途 | B4: 公式 | C4: 口径说明 | D4: 陷阱
A5: 加工价差 | B5: =PTA − Lambda*PX − OtherCost | C5: 收入型加工费，不含折旧、能源、物流 | D5: λ 必须来自台账；不同代际 0.647~0.657，差 0.008 ≈ 价差平移 60~80 元/吨
A6: Pearson r | B6: =CORREL(x,y) | C6: 线性相关，对异常值敏感 | D6: 水平序列都有趋势 → r 虚高；必须同时报收益率口径
A7: 决定系数 | B7: =RSQ(y,x) | C7: r 的平方，解释方差比例 | D7: 不能解释为「因果解释力」
A8: t 统计量 | B8: =r*SQRT((n-2)/(1-r^2)) | C8: H0: ρ=0 | D8: n 是有效样本，不是自然日数
A9: p 值 | B9: =_xlfn.T.DIST.2T(ABS(t),df) | C9: 双尾 | D9: 自相关序列需用 Newey-West 或有效样本量校正
A10: Fisher 置信区间 | B10: =TANH(ATANH(r)±NORMSINV(1-α/2)/SQRT(n-3)) | C10: Fisher z 变换 | D10: n<10 时不可靠
A11: 有效样本量 | B11: =n(1-ρxρy)/(1+ρxρy) | C11: Pyper & Peterman 校正 | D11: 水平序列有效 N 常只有原始 N 的 10~30%
A12: 分位 | B12: =_xlfn.PERCENTILE.INC(range,p) | C12: 线性插值（含端点） | D12: PERCENTILE.EXC 差距可达数十元/吨，两者不可混用；报告统一用 INC
A13: 分位rank | B13: =_xlfn.PERCENTRANK.INC(range,x) | C13: 当前值在历史中的位置 | D13: 与 PERCENTILE.INC 配对；结并列时取平均位置
A14: 滚动相关 | B14: =CORREL(offset range) | C14: 窗口不足 80% 不出数 | D14: 窗口越长越平滑，会掩盖拐点
A15: 交叉相关 | B15: =CORREL(x[0:n-lag], y[lag:n]) | C15: 正 lag = x 领先 y | D15: 只看 Pearson，无法排除共同趋势
A16: Granger F | B16: 受限/非受限 RSS 比较 | C16: 检验是否含增量预测信息 | D16: Granger 不是因果，只说明时序上「先动」有价值
A17: 中位数 | B17: =MEDIAN(range) | C17: 抗异常值 | D17: 与均值差距大说明分布偏斜，报告须同时给
A18: 条件均值 | B18: =AVERAGEIFS(val,date,">="&a,date,"<="&b) | C18: 分阶段统计 | D18: 日期必须是文本可比格式或真日期
