Workbook

Sheet 客户判断总览
A1: 纯碱客户多维判断卡 · 客户准入总览
A2: 销售产品：重质纯碱 99%（散装罐车/吨袋） | 卖家：山东潍坊 · 碱厂/一级贸易商 · 月可供 5,000 吨 | 判断时点：2026-10 | 排序参考分仅用于决定跟进顺序，不是评级、不代表成交概率。
A4: 排名 | B4: 客户名称 | C4: 证券代码 | D4: 所在地/基地 | E4: 距发货地 | F4: 年需求估算 | G4: 年采购额估算 | H4: 建议动作 | I4: 产品匹配 | J4: 需求规模 | K4: 真实产能 | L4: 企业规模 | M4: 距离/区域 | N4: 近期机会 | O4: 不确定性 | P4: 产品匹配分 | Q4: 需求规模分 | R4: 真实产能分 | S4: 企业规模分 | T4: 距离/区域分 | U4: 近期机会分 | V4: 不确定性分 | W4: 排序参考分 | X4: 最强积极信号
A5: =RANK(W5,$W$5:$W$8) -> 3 | B5: 河南安彩高科 | C5: 600207.SH | D5: 河南安阳（光伏新材料、光热基地在龙安区） | E5: 潍坊→安阳 ≈480 km（公路，估） | F5: ≈10±3 万吨/年（估） | G5: ≈1.0 亿元/年 | H5: 先投标入围，卡 900t/d 改造投产节点；报价锚定河南天然碱到厂价，账期争取「现汇+部分承兑」、锁量不锁价。 | I5: 高 | J5: 中高 | K5: 中 | L5: 中 | M5: 高 | N5: 中高 | O5: 高 | P5: 90 | Q5: 75 | R5: 60 | S5: 60 | T5: 80 | U5: 75 | V5: 40 | W5: =SUMPRODUCT(P5:V5,'权重与排序'!$B$5:$H$5)/SUM('权重与排序'!$B$5:$H$5) -> 68.571429 | X5: 900t/d 光伏线 4.98 亿元升级改造带来的「投产换供应商」窗口，叠加公开招标/询比的合规进入通道——不靠关系也能投进去。
A6: =RANK(W6,$W$5:$W$8) -> 2 | B6: 株洲旗滨集团 | C6: 601636.SH | D6: 总部湖南株洲；产线在醴陵/河源/漳州/昭通/马来西亚沙巴 | E6: 距潍坊 1,300–2,200 km（不经济） | F6: ≈80–110 万吨/年（产能口径，估） | G6: ≈8–11 亿元/年 | H6: 不作当前主攻；作为行业价格标杆收集情报，若你厂有华中/华南仓或水运能力再启动接触。 | I6: 高 | J6: 高 | K6: 高 | L6: 高 | M6: 低 | N6: 中 | O6: 中低 | P6: 90 | Q6: 95 | R6: 85 | S6: 95 | T6: 35 | U6: 50 | V6: 65 | W6: =SUMPRODUCT(P6:V6,'权重与排序'!$B$5:$H$5)/SUM('权重与排序'!$B$5:$H$5) -> 73.571429 | X6: 规模最大的潜在客户：若进其总部集采长协名单，一张合同顶几十家小厂。
A7: =RANK(W7,$W$5:$W$8) -> 1 | B7: 信义玻璃 | C7: 00868.HK | D7: 主要营业地安徽芜湖；另有东莞/江门/北海/马来西亚基地 | E7: 潍坊→芜湖 ≈700 km（主基地更远） | F7: ≈40–100 万吨/年（浮法口径，估） | G7: ≈5–9 亿元/年 | H7: 以「旺季保供/区域副供」切入，不打价格战，重点展示稳定性与交付能力。 | I7: 高 | J7: 高 | K7: 高 | L7: 高 | M7: 低 | N7: 低 | O7: 中低 | P7: 90 | Q7: 98 | R7: 85 | S7: 100 | T7: 45 | U7: 45 | V7: 65 | W7: =SUMPRODUCT(P7:V7,'权重与排序'!$B$5:$H$5)/SUM('权重与排序'!$B$5:$H$5) -> 75.428571 | X7: 现金牛客户：量与付款都稳定，一旦进长协就是多年饭票。
A8: =RANK(W8,$W$5:$W$8) -> 4 | B8: 山西利虎玻璃集团 | C8: 非上市 · 吕梁交城 | D8: 山西吕梁交城县经济开发区（+青耀等子公司） | E8: 潍坊→交城 ≈620 km | F8: ≈8–12 万吨/年（口径较旧，待核） | G8: ≈0.8–1.2 亿元/年 | H8: 直连采购负责人，先带样品与小批量方案试单 1–2 车，同时谈死账期与付款习惯。 | I8: 高 | J8: 中 | K8: 中 | L8: 中低 | M8: 中 | N8: 中 | O8: 中 | P8: 85 | Q8: 65 | R8: 70 | S8: 55 | T8: 60 | U8: 65 | V8: 50 | W8: =SUMPRODUCT(P8:V8,'权重与排序'!$B$5:$H$5)/SUM('权重与排序'!$B$5:$H$5) -> 64.285714 | X8: 决策链短、没有公开招标的资格门槛——一通电话就能见到采购负责人，适合新销售建关系、练打法。
A10: 注：评级阈值 高≥75 / 中55–74 / 低<55；分数是事实→排序的映射，看到「低」时请优先读同行的「事实」列。需求/运费/距离为估算口径，成交前以客户确认数为准。

Sheet 七维判断明细
A1: 七维判断明细 · 一客户一维度一行，事实与证据可追溯
A2: 「口径」标注估算/核实；来源对应本工作簿「数据来源」表。评级只是锚点，请以事实为准。
A4: 客户 | B4: 维度 | C4: 评级 | D4: 分值 | E4: 事实与依据 | F4: 口径 | G4: 证据来源 | H4: 来源链接 | I4: 来源日期
A5: 河南安彩高科 | B5: 产品匹配 | C5: 高 | D5: 90 | E5: 玻璃熔窑是纯碱第一大下游，浮法/光伏玻璃以重质碱为主；公司确认纯碱采购采用「期现结合」控成本，原料有公开询比/招标记录，采购体系开放、可投标进入。 | F5: 核实 | G5: 每经：纯碱采购期现结合 | H5: 打开链接 | I5: 2023-02-20
A6: 河南安彩高科 | B6: 需求规模 | C6: 中高 | D6: 75 | E6: 可核熔量约1,500–1,800吨/日（900t/d光伏线+600t/d超白浮法线等），按单耗0.2、330天估算：年需求约10±3万吨、采购额约1亿元（1,000元/吨）。 | F6: 估算 | G6: 900t/d 产线改造公告 | H6: 打开链接 | I6: 2025-12-05
A7: 河南安彩高科 | B7: 真实产能 | C7: 中 | D7: 60 | E7: 2026H1营收10.77亿（-38.2%），光伏玻璃价历史低位、行业冷修压力大；900t/d线2025年12月公告投4.98亿元改造——改造期熔量有变数，投产后是提产窗口。 | F7: 核实+预估 | G7: 2026半年度业绩说明会 | H7: 打开链接 | I7: 2026-09-16
A8: 河南安彩高科 | B8: 企业规模 | C8: 中 | D8: 60 | E8: 2025年营收29.19亿（-32.7%）、归母净亏7.27亿；2024年营收43.39亿、亏3.54亿。A股上市、河南投资集团控股——中型平台但连亏削弱付款能力。 | F8: 核实 | G8: 2025年年度报告 | H8: 打开链接 | I8: 2026-04-18
A9: 河南安彩高科 | B9: 距离/区域 | C9: 高 | D9: 80 | E9: 安阳距潍坊≈480km，公路运费估170–240元/吨（约占碱价20%），在可竞争半径内；河南本地天然碱（桐柏）货源竞争需对标（待核实）。 | F9: 估算 | G9: 河南重质碱市场价1,050元/吨 | H9: 打开链接 | I9: 2026-10-15
A10: 河南安彩高科 | B10: 近期机会 | C10: 中高 | D10: 75 | E10: 三个切入点：①900t/d线改造投产前供应商重选；②公开招标/询比惯例（2021供应商准入、2023药玻原料）；③光热玻璃在手1,380MW、药玻项目多需求。 | F10: 核实 | G10: 900t/d 改造公告 | H10: 打开链接 | I10: 2025-12-05
A11: 河南安彩高科 | B11: 不确定性 | C11: 高 | D11: 40 | E11: 2023–2025连亏扩大（-0.19亿→-7.27亿），2026H1再亏3.28亿；2026年9月申请委托贷款、拟简易定增——资金偏紧，防极致压价与长账期。 | F11: 核实 | G11: 2026半年度业绩说明会 | H11: 打开链接 | I11: 2026-09-16
A12: 株洲旗滨集团 | B12: 产品匹配 | C12: 高 | D12: 90 | E12: 浮法+光伏玻璃集团，纯碱超级买家，规格以重质碱散装为主，与标准碱厂产品完全对口。 | F12: 核实 | G12: 2025年半年度报告 | H12: 打开链接 | I12: 2025-08-28
A13: 株洲旗滨集团 | B13: 需求规模 | C13: 高 | D13: 95 | E13: 2024年在产浮法产能约1.1亿重箱（≈550万吨/年玻璃口径），另有11条以上光伏玻璃线；按0.2单耗估算年需求约80–110万吨、采购额8–11亿元。 | F13: 估算 | G13: 研报：在产浮法1.1亿重箱 | H13: 打开链接 | I13: 2024-11-18
A14: 株洲旗滨集团 | B14: 真实产能 | C14: 高 | D14: 85 | E14: 2025年营收157.4亿（+0.6%）、利润总额6.2亿（+138%），行业磨底中率先修复、产线维持开工；昭通1,200t/d超白光伏线推进。 | F14: 核实 | G14: 2025年年度报告数据（新浪） | H14: 打开链接 | I14: 2026-04
A15: 株洲旗滨集团 | B15: 企业规模 | C15: 高 | D15: 95 | E15: 2025年营收157.37亿元、总市值约150亿元（2025-04）；浮法行业龙头，资产与现金流第一梯队。 | F15: 核实 | G15: 2025年年度报告数据 | H15: 打开链接 | I15: 2026-04
A16: 株洲旗滨集团 | B16: 距离/区域 | C16: 低 | D16: 35 | E16: 主力产线在湖南/广东/云南/马来西亚，距潍坊1,300km以上，公路运费>600元/吨，跨区配送不经济。 | F16: 估算 | G16: 2025年半年报（基地分布） | H16: 打开链接 | I16: 2025-08-28
... A32: 山西利虎玻璃集团 | B32: 不确定性 | C32: 中 | D32: 50 | E32: 信息不透明：产能利用率、账期、付款方式全靠尽调与同行口碑；民企账期风险需当面谈死。 | F32: 研判 | G32: 中国玻璃网公司页 | H32: 打开链接 | I32: 口径较旧

Sheet 权重与排序
A1: 权重与排序 · 改黄色权重格，全表联动重排
A2: 「当前权重」影响总览表与客户排名；「情景对比」仅演示不同权重下排序如何变化——事实不变，排序变。
A3: A. 当前权重（可修改，0–5）
A4: 权重项 | B4: 产品匹配 | C4: 需求规模 | D4: 真实产能 | E4: 企业规模 | F4: 距离/区域 | G4: 近期机会 | H4: 不确定性 | I4: 合计
A5: 权重（可调） | B5: 1 | C5: 1 | D5: 1 | E5: 1 | F5: 1 | G5: 1 | H5: 1 | I5: =SUM(B5:H5) -> 7
A7: B. 客户排序（当前权重）
A8: 客户 | B8: 加权排序分 | C8: 排名
A9: 河南安彩高科 | B9: =SUMPRODUCT('客户判断总览'!P5:V5,$B$5:$H$5)/SUM($B$5:$H$5) -> 68.571429 | C9: =RANK(B9,$B$9:$B$12) -> 3
A10: 株洲旗滨集团 | B10: =SUMPRODUCT('客户判断总览'!P6:V6,$B$5:$H$5)/SUM($B$5:$H$5) -> 73.571429 | C10: =RANK(B10,$B$9:$B$12) -> 2
A11: 信义玻璃 | B11: =SUMPRODUCT('客户判断总览'!P7:V7,$B$5:$H$5)/SUM($B$5:$H$5) -> 75.428571 | C11: =RANK(B11,$B$9:$B$12) -> 1
A12: 山西利虎玻璃集团 | B12: =SUMPRODUCT('客户判断总览'!P8:V8,$B$5:$H$5)/SUM($B$5:$H$5) -> 64.285714 | C12: =RANK(B12,$B$9:$B$12) -> 4
A15: C. 情景对比：不同权重下的排序（只演示，不改 A 区）
A16: 场景 | B16: 产品匹配 | C16: 需求规模 | D16: 真实产能 | E16: 企业规模 | F16: 距离/区域 | G16: 近期机会 | H16: 不确定性
A17: 均衡 | B17: 1 | C17: 1 | D17: 1 | E17: 1 | F17: 1 | G17: 1 | H17: 1
A18: 规模更重要 | B18: 0.5 | C18: 1 | D18: 0.5 | E18: 2.5 | F18: 0.5 | G18: 1 | H18: 0.5
A19: 近期机会更重要 | B19: 1 | C19: 1 | D19: 1 | E19: 0.5 | F19: 0.5 | G19: 2.5 | H19: 0.5
A20: 距离更重要 | B20: 0.5 | C20: 0.5 | D20: 0.5 | E20: 0.5 | F20: 2.5 | G20: 0.5 | H20: 0.5
A22: 客户 | B22: 均衡 | C22: 规模更重要 | D22: 近期机会更重要 | E22: 距离更重要
A23: 河南安彩高科 | B23: =SUMPRODUCT('客户判断总览'!P5:V5,$B$17:$H$17)/SUM($B$17:$H$17) -> 68.571429 | C23: =SUMPRODUCT('客户判断总览'!P5:V5,$B$18:$H$18)/SUM($B$18:$H$18) -> 66.923077 | D23: =SUMPRODUCT('客户判断总览'!P5:V5,$B$19:$H$19)/SUM($B$19:$H$19) -> 71.785714 | E23: =SUMPRODUCT('客户判断总览'!P5:V5,$B$20:$H$20)/SUM($B$20:$H$20) -> 72.727273
A24: 株洲旗滨集团 | B24: =SUMPRODUCT('客户判断总览'!P6:V6,$B$17:$H$17)/SUM($B$17:$H$17) -> 73.571429 | C24: =SUMPRODUCT('客户判断总览'!P6:V6,$B$18:$H$18)/SUM($B$18:$H$18) -> 80 | D24: =SUMPRODUCT('客户判断总览'!P6:V6,$B$19:$H$19)/SUM($B$19:$H$19) -> 70.357143 | E24: =SUMPRODUCT('客户判断总览'!P6:V6,$B$20:$H$20)/SUM($B$20:$H$20) -> 59.545455
A25: 信义玻璃 | B25: =SUMPRODUCT('客户判断总览'!P7:V7,$B$17:$H$17)/SUM($B$17:$H$17) -> 75.428571 | C25: =SUMPRODUCT('客户判断总览'!P7:V7,$B$18:$H$18)/SUM($B$18:$H$18) -> 82.384615 | D25: =SUMPRODUCT('客户判断总览'!P7:V7,$B$19:$H$19)/SUM($B$19:$H$19) -> 70.071429 | E25: =SUMPRODUCT('客户判断总览'!P7:V7,$B$20:$H$20)/SUM($B$20:$H$20) -> 64.363636
A26: 山西利虎玻璃集团 | B26: =SUMPRODUCT('客户判断总览'!P8:V8,$B$17:$H$17)/SUM($B$17:$H$17) -> 64.285714 | C26: =SUMPRODUCT('客户判断总览'!P8:V8,$B$18:$H$18)/SUM($B$18:$H$18) -> 61.538462 | D26: =SUMPRODUCT('客户判断总览'!P8:V8,$B$19:$H$19)/SUM($B$19:$H$19) -> 66.428571 | E26: =SUMPRODUCT('客户判断总览'!P8:V8,$B$20:$H$20)/SUM($B$20:$H$20) -> 62.727273

Sheet 待确认清单
A1: 待确认清单 · 问对了再投销售资源
A2: 每条问题都对应一个「影响哪个判断」：客户答不上来或含糊其辞，本身就是信号。
A4: 序号 | B4: 客户 | C4: 优先级 | D4: 待确认事项 | E4: 为什么重要（影响哪个判断） | F4: 建议对象/方式
A5: 1 | B5: 河南安彩高科 | C5: P1 | D5: 在产窑炉清单与日熔量？900t/d 改造线预计何时点火/达产？ | E5: 产品匹配/真实产能｜直接决定真实月采购量，避免把投产后的量当当下量 | F5: 采购部 + 生产计划
A6: 2 | B6: 河南安彩高科 | C6: P1 | D6: 纯碱月均采购量与现供结构（碱厂直销/贸易商占比）、到厂结算价？ | E6: 需求规模/产品匹配｜判断可拿到的量级与价差空间，对标天然碱 | F6: 采购部
A7: 3 | B7: 河南安彩高科 | C7: P1 | D7: 供应商准入走哪个平台？需要什么资质、业绩门槛和保证金？ | E7: 近期机会｜公开招标是唯一可控的进场通道，先确认流程再投入 | F7: 招标平台/采购部
A8: 4 | B8: 河南安彩高科 | C8: P1 | D8: 质量指标（松密度、NaCl、铁等）？散装罐车还是吨袋？厂内卸货条件？ | E8: 产品匹配｜浮法/光伏对碱品质敏感，卸货条件影响运费与损耗 | F8: 质检/采购
A9: 5 | B9: 河南安彩高科 | C9: P1 | D9: 结算方式与账期（现汇/承兑比例）？有无提前付款折扣？ | E9: 不确定性｜资金链紧张客户，账期为最大隐性成本 | F9: 财务/采购
A10: 6 | B10: 株洲旗滨集团 | C10: P4 | D10: 浮法/光伏板块纯碱是否总部集采？年度招标时间节点？ | E10: 近期机会｜确认是否存在公开可投标窗口 | F10: 集采中心
A11: 7 | B11: 株洲旗滨集团 | C11: P4 | D11: 新供应商准入条件（产能规模、运距、账期要求）？ | E11: 产品匹配/距离｜判断资质与供货半径是否够格 | F11: 集采中心
A12: 8 | B12: 信义玻璃 | C12: P3 | D12: 芜湖基地纯碱月采购量与主供结构？ | E12: 需求规模/产品匹配｜确认能否以副供身份切入 | F12: 供应链采购中心
A13: 9 | B13: 信义玻璃 | C13: P3 | D13: 是否接受区域副供/旺季补充供应商？ | E13: 近期机会｜找到非价格竞争的位置 | F13: 供应链采购中心
A14: 10 | B14: 山西利虎玻璃集团 | C14: P2 | D14: 现在几条线在产？日熔量多少？ | E14: 真实产能/需求规模｜摸清真实可用量，避免按旧产能估算 | F14: 采购部
A15: 11 | B15: 山西利虎玻璃集团 | C15: P2 | D15: 纯碱月采购量、谁在供、什么价、什么账期？ | E15: 需求规模/不确定性｜定价与账期是两个核心谈判点 | F15: 采购部/财务
A16: 12 | B16: 山西利虎玻璃集团 | C16: P2 | D16: 是否接受小批量试单（1–2 车）？ | E16: 近期机会｜低门槛切入、先建信任 | F16: 采购部

Sheet 数据来源
A1: 数据来源 · 每条事实可回溯到公开链接
A2: 来源类型：年报/半年报/公告/研报/政府函件/行业资讯/媒体/招标/报价。日期为发布日。
A4: 编号 | B4: 所属 | C4: 类型 | D4: 来源名称 | E4: 链接 | F4: 日期
A5: S01 | B5: 河南安彩高科 | C5: 年报 | D5: 2025 年年度报告（巨潮） | E5: 打开链接 | F5: 2026-04-18
A6: S02 | B6: 河南安彩高科 | C6: 年报 | D6: 2024 年年度报告摘要（新浪） | E6: 打开链接 | F6: 2025-03-29
A7: S03 | B7: 河南安彩高科 | C7: 公告 | D7: 生产线改造提升公告（900t/d 光伏线） | E7: 打开链接 | F7: 2025-12-05
A8: S04 | B8: 河南安彩高科 | C8: 行业资讯 | D8: 安彩光热 600t/d 超白浮法线（1,380MW 业绩） | E8: 打开链接 | F8: 2025-10-09
A9: S05 | B9: 河南安彩高科 | C9: 媒体 | D9: 2026 年半年度业绩说明会（大河财立方） | E9: 打开链接 | F9: 2026-09-16
A10: S06 | B10: 河南安彩高科 | C10: 互动问答 | D10: 投资者互动：纯碱采购采用期现结合 | E10: 打开链接 | F10: 2023-02-20
A11: S07 | B11: 河南安彩高科 | C11: 招标 | D11: 2021 年度原料供应商资格准入公开招标 | E11: 打开链接 | F11: 2021-03-05
A12: S08 | B12: 河南安彩高科 | C12: 报价 | D12: 河南重质纯碱市场价 1,050 元/吨 | E12: 打开链接 | F12: 2026-10-15
A13: S09 | B13: 河南安彩高科 | C13: 公告 | D13: 公司公告列表（委托贷款/简易定增） | E13: 打开链接 | F13: 2026-09-03
A14: S10 | B14: 株洲旗滨集团 | C14: 半年报 | D14: 2025 年半年度报告（巨潮） | E14: 打开链接 | F14: 2025-08-28
A15: S11 | B15: 株洲旗滨集团 | C15: 研报 | D15: 2024 年三季报点评：在产浮法 1.1 亿重箱 | E15: 打开链接 | F15: 2024-11-18
... A37: M33 | B37: 市场背景 | C37: 行情/报价 | D37: 浮法玻璃产量同比 | E37: 打开链接 | F37: 2026-10

Sheet 市场背景
A1: 市场背景 · 行情快照（2026-10）
A2: 先确定市场处于买方还是卖方市场：这决定客户压价意愿、开工率假设与你的报价空间。
A4: 指标 | B4: 数值 | C4: 时点 | D4: 来源 | E4: 链接
A5: 重质纯碱现货（河南市场价） | B5: ≈1,050 元/吨 | C5: 2026-10-15 | D5: 化工网 | E5: 打开链接
A6: 重质纯碱成交价区间 | B6: 970–1,050 元/吨 | C6: 2026-10 | D6: 生意社 | E6: 打开链接
A7: 纯碱厂家库存 | B7: ≈178 万吨 | C7: 2026-10-09 | D7: 新浪期货日评 | E7: 打开链接
A8: 纯碱装置开工率 | B8: ≈65% | C8: 2026-10 | D8: 新浪期货日评 | E8: 打开链接
A9: 浮法玻璃在产日熔量 | B9: 14.1–14.3 万吨/日 | C9: 2026-10 | D9: 钢联/紫金天风 | E9: 打开链接
A10: 光伏玻璃在产日熔量 | B10: 6.68 万吨/日 | C10: 2026-10 | D10: 钢联/紫金天风 | E10: 打开链接
A11: 浮法玻璃产能利用率 | B11: ≈71% | C11: 2026-10 | D11: 新浪期货日评 | E11: 打开链接
A12: 浮法玻璃现货均价 | B12: ≈1,075 元/吨 | C12: 2026-10 | D12: 隆众资讯 | E12: 打开链接
A13: 浮法玻璃产量同比 | B13: -11.53% | C13: 2026-10 | D13: 新浪期货日评 | E13: 打开链接

Sheet 阅读说明
A1: 阅读说明 · 方法与口径
A2: 这份工作簿回答一个问题：把有限的销售时间投给谁？它给出事实、评级与排序参考，最终判断权在你。
A4: 一、怎么用（3 步）
A5: ① 带入：把客户名称（或客户池）与销售产品填入——维度数据随之就位；
A6: ② 看事实：逐维读「七维判断明细」，每个维度都有依据、口径（估算/核实）与来源链接；
A7: ③ 定顺序：在「权重与排序」里调权重，用排序结果决定本周先打谁——但事实不因权重改变。
A9: 二、维度定义
A10: 维度 | B10: 看什么 | C10: 高 / 中 / 低锚点
A11: 产品匹配 | B11: 产品规格/用途是否对口、采购体系是否开放、能否投标进入 | C11: 高：窑炉/产线用户且采购公开；中：用途对口但准入门槛不明；低：规格不对口或仅用替代品
A12: 需求规模 | B12: 年采购量与采购额（按产能×单耗估算） | C12: 高：年需求≥20 万吨；中：5–20 万吨；低：<5 万吨
A13: 真实产能 | B13: 窑炉是否在产、开工率、改造/冷修影响 | C13: 高：产线满开且盈利；中：部分冷修/改造降量；低：大面积停产
A14: 企业规模 | B14: 营收/资产规模与信用 | C14: 高：龙头、盈利、评级好；中：中型上市但亏损；低：小微/信息不透明
A15: 距离/区域 | B15: 运距与运费占比、是否在竞争半径内 | C15: 高：≤600km 且运费<25%货值；中：600–1200km；低：>1200km 或海外
A16: 近期机会 | B16: 改造/点火/扩建/招标等时间窗口与需求增量 | C16: 高：6 个月内有投产或招标；中：12 个月内有；低：无明确节点
A17: 不确定性 | B17: 越低越好：资信、账期、锁价与需求波动风险 | C17: 高：连亏+长账期；中：信息不透明；低：盈利稳定+付款好（分数越低风险越大）
A19: 三、评分与阈值
A20: 维度分值 0–100 是「事实 → 排序」的映射：排序分 = Σ(维度分 × 权重) / Σ权重。
A21: 评级阈值：高 ≥75、中 55–74、低 <55。评级只是快速锚点，请始终以「事实」列为准。
A22: 「不确定性」维度分数越低=风险越大（与其他维度方向相反），总览中以红色提示。
A24: 四、估算口径（务必在成交前核实）
A25: 年纯碱需求 ≈ 日熔量 × 0.2 吨碱/吨玻璃 × 年运行 330 天（玻璃行业单耗 0.18–0.22 取中值）；
A26: 年采购额按 1,000 元/吨估算（2026-10 重碱现货 970–1,050 元/吨）；
A27: 公路运费按 0.35–0.5 元/吨·公里估算，距离取地图公路里程近似值；
A28: 客户产线/开工数据以最近一期年报、半年报及行业产线动态为准，改造/冷修期间的量需单独扣减。
A30: 五、局限与免责
A31: 本工作簿依据 2026-10 时点公开信息整理，实际采购量、价格与账期需向客户直接确认；
A32: 评分与排序是销售资源分配辅助工具，不构成投资、授信或采购建议；
A33: 事实更新后请同步更新「七维判断明细」与来源日期，历史判断不应被当成永久结论。
